{
"type": "FeatureCollection",
"crs": { "type": "name", "properties": { "name": "urn:ogc:def:crs:OGC:1.3:CRS84" } },
"features": [
{ "type": "Feature", "properties": { "point_type": "origin", "points_str": "45.442296, -122.699127" }, "geometry": { "type": "Point", "coordinates": [ -122.699127456748784, 45.442295988444606 ] } },
{ "type": "Feature", "properties": { "point_type": "destination", "points_str": "45.473896, -122.579874" }, "geometry": { "type": "Point", "coordinates": [ -122.579873692674212, 45.473895747518014 ] } }
]
}
