{
"type": "FeatureCollection",
"crs": { "type": "name", "properties": { "name": "urn:ogc:def:crs:OGC:1.3:CRS84" } },
"features": [
{ "type": "Feature", "properties": { "point_type": "origin", "points_str": "45.583568, -122.706159" }, "geometry": { "type": "Point", "coordinates": [ -122.706158704796493, 45.583567938137612 ] } },
{ "type": "Feature", "properties": { "point_type": "destination", "points_str": "45.560244, -122.724489" }, "geometry": { "type": "Point", "coordinates": [ -122.724488898666451, 45.560243862495078 ] } }
]
}
