{
"type": "FeatureCollection",
"name": "origin_destination_points",
"crs": { "type": "name", "properties": { "name": "urn:ogc:def:crs:OGC:1.3:CRS84" } },
"features": [
{ "type": "Feature", "properties": { "point_type": "origin", "points_str": "45.349718, -122.595241" }, "geometry": { "type": "Point", "coordinates": [ -122.595240543293869, 45.349717585123535 ] } },
{ "type": "Feature", "properties": { "point_type": "destination", "points_str": "45.442747, -122.586159" }, "geometry": { "type": "Point", "coordinates": [ -122.586159256465024, 45.442746637831114 ] } }
]
}
