{
"type": "FeatureCollection",
"name": "origin_destination_points",
"crs": { "type": "name", "properties": { "name": "urn:ogc:def:crs:OGC:1.3:CRS84" } },
"features": [
{ "type": "Feature", "properties": { "point_type": "origin", "points_str": "45.493833, -122.787657" }, "geometry": { "type": "Point", "coordinates": [ -122.787657327914971, 45.493833487545068 ] } },
{ "type": "Feature", "properties": { "point_type": "destination", "points_str": "45.501657, -122.755957" }, "geometry": { "type": "Point", "coordinates": [ -122.755956512773722, 45.501657448966114 ] } }
]
}
