{
"type": "FeatureCollection",
"crs": { "type": "name", "properties": { "name": "urn:ogc:def:crs:OGC:1.3:CRS84" } },
"features": [
{ "type": "Feature", "properties": { "point_type": "origin", "points_str": "45.483853, -122.636021" }, "geometry": { "type": "Point", "coordinates": [ -122.636021235868128, 45.483852943684525 ] } },
{ "type": "Feature", "properties": { "point_type": "destination", "points_str": "45.46185, -122.719762" }, "geometry": { "type": "Point", "coordinates": [ -122.719762094656005, 45.461850075199607 ] } }
]
}
