{
"type": "FeatureCollection",
"crs": { "type": "name", "properties": { "name": "urn:ogc:def:crs:OGC:1.3:CRS84" } },
"features": [
{ "type": "Feature", "properties": { "point_type": "origin", "points_str": "45.539842, -122.705037" }, "geometry": { "type": "Point", "coordinates": [ -122.705037343723831, 45.539841521635218 ] } },
{ "type": "Feature", "properties": { "point_type": "destination", "points_str": "45.535872, -122.553646" }, "geometry": { "type": "Point", "coordinates": [ -122.553646007734656, 45.535872223212657 ] } }
]
}
