{
"type": "FeatureCollection",
"name": "origin_destination_points",
"crs": { "type": "name", "properties": { "name": "urn:ogc:def:crs:OGC:1.3:CRS84" } },
"features": [
{ "type": "Feature", "properties": { "point_type": "origin", "points_str": "45.571743, -122.635204" }, "geometry": { "type": "Point", "coordinates": [ -122.635203570829177, 45.571743399593181 ] } },
{ "type": "Feature", "properties": { "point_type": "destination", "points_str": "45.595432, -122.744205" }, "geometry": { "type": "Point", "coordinates": [ -122.744204699334517, 45.595432481926501 ] } }
]
}
