{
"type": "FeatureCollection",
"name": "origin_destination_points",
"crs": { "type": "name", "properties": { "name": "urn:ogc:def:crs:OGC:1.3:CRS84" } },
"features": [
{ "type": "Feature", "properties": { "point_type": "origin", "points_str": "45.508912, -122.583162" }, "geometry": { "type": "Point", "coordinates": [ -122.58316235767721, 45.508911693928837 ] } },
{ "type": "Feature", "properties": { "point_type": "destination", "points_str": "45.504842, -122.639655" }, "geometry": { "type": "Point", "coordinates": [ -122.639654950520764, 45.504841695408182 ] } }
]
}
