{
"type": "FeatureCollection",
"name": "origin_destination_points",
"crs": { "type": "name", "properties": { "name": "urn:ogc:def:crs:OGC:1.3:CRS84" } },
"features": [
{ "type": "Feature", "properties": { "point_type": "origin", "points_str": "45.437139, -122.724092" }, "geometry": { "type": "Point", "coordinates": [ -122.72409244886542, 45.437138874140921 ] } },
{ "type": "Feature", "properties": { "point_type": "destination", "points_str": "45.458504, -122.708918" }, "geometry": { "type": "Point", "coordinates": [ -122.708918126764743, 45.458503769139085 ] } }
]
}
