{
"type": "FeatureCollection",
"name": "origin_destination_points",
"crs": { "type": "name", "properties": { "name": "urn:ogc:def:crs:OGC:1.3:CRS84" } },
"features": [
{ "type": "Feature", "properties": { "point_type": "origin", "points_str": "45.52113, -122.947391" }, "geometry": { "type": "Point", "coordinates": [ -122.947391374161086, 45.521129916315907 ] } },
{ "type": "Feature", "properties": { "point_type": "destination", "points_str": "45.526326, -122.86276" }, "geometry": { "type": "Point", "coordinates": [ -122.862759544416193, 45.526325910230945 ] } }
]
}
