{
"type": "FeatureCollection",
"crs": { "type": "name", "properties": { "name": "urn:ogc:def:crs:OGC:1.3:CRS84" } },
"features": [
{ "type": "Feature", "properties": { "point_type": "origin", "points_str": "45.32133, -122.57777" }, "geometry": { "type": "Point", "coordinates": [ -122.577770460317751, 45.321329930657846 ] } },
{ "type": "Feature", "properties": { "point_type": "destination", "points_str": "45.377214, -122.378276" }, "geometry": { "type": "Point", "coordinates": [ -122.378275808543407, 45.377213813728609 ] } }
]
}
