{
"type": "FeatureCollection",
"crs": { "type": "name", "properties": { "name": "urn:ogc:def:crs:OGC:1.3:CRS84" } },
"features": [
{ "type": "Feature", "properties": { "point_type": "origin", "points_str": "45.493086, -122.792225" }, "geometry": { "type": "Point", "coordinates": [ -122.792225179647517, 45.493085613005398 ] } },
{ "type": "Feature", "properties": { "point_type": "destination", "points_str": "45.508978, -122.693734" }, "geometry": { "type": "Point", "coordinates": [ -122.693733831237054, 45.508978134240145 ] } }
]
}
