{
"type": "FeatureCollection",
"crs": { "type": "name", "properties": { "name": "urn:ogc:def:crs:OGC:1.3:CRS84" } },
"features": [
{ "type": "Feature", "properties": { "point_type": "origin", "points_str": "45.495979, -122.763483" }, "geometry": { "type": "Point", "coordinates": [ -122.763482609456233, 45.495979156495274 ] } },
{ "type": "Feature", "properties": { "point_type": "destination", "points_str": "45.498763, -122.678495" }, "geometry": { "type": "Point", "coordinates": [ -122.678495430955621, 45.498763172041329 ] } }
]
}
