{
"type": "FeatureCollection",
"crs": { "type": "name", "properties": { "name": "urn:ogc:def:crs:OGC:1.3:CRS84" } },
"features": [
{ "type": "Feature", "properties": { "point_type": "origin", "points_str": "45.547892, -122.867603" }, "geometry": { "type": "Point", "coordinates": [ -122.867603353732136, 45.547892138145464 ] } },
{ "type": "Feature", "properties": { "point_type": "destination", "points_str": "45.439474, -122.822324" }, "geometry": { "type": "Point", "coordinates": [ -122.822324352552855, 45.439473744167366 ] } }
]
}
