{
"type": "FeatureCollection",
"crs": { "type": "name", "properties": { "name": "urn:ogc:def:crs:OGC:1.3:CRS84" } },
"features": [
{ "type": "Feature", "properties": { "point_type": "origin", "points_str": "45.502142, -122.8776" }, "geometry": { "type": "Point", "coordinates": [ -122.877600113643354, 45.502141855100774 ] } },
{ "type": "Feature", "properties": { "point_type": "destination", "points_str": "45.522468, -122.856198" }, "geometry": { "type": "Point", "coordinates": [ -122.856198122920972, 45.52246782143726 ] } }
]
}
