{
"type": "FeatureCollection",
"name": "origin_destination_points",
"crs": { "type": "name", "properties": { "name": "urn:ogc:def:crs:OGC:1.3:CRS84" } },
"features": [
{ "type": "Feature", "properties": { "point_type": "origin", "points_str": "45.485234, -122.538109" }, "geometry": { "type": "Point", "coordinates": [ -122.538109027366602, 45.485234163899747 ] } },
{ "type": "Feature", "properties": { "point_type": "destination", "points_str": "45.561947, -122.702755" }, "geometry": { "type": "Point", "coordinates": [ -122.70275470882396, 45.561946689720862 ] } }
]
}
