{
"type": "FeatureCollection",
"name": "origin_destination_points",
"crs": { "type": "name", "properties": { "name": "urn:ogc:def:crs:OGC:1.3:CRS84" } },
"features": [
{ "type": "Feature", "properties": { "point_type": "origin", "points_str": "45.510638, -122.761919" }, "geometry": { "type": "Point", "coordinates": [ -122.761919058497881, 45.510638315145904 ] } },
{ "type": "Feature", "properties": { "point_type": "destination", "points_str": "45.493265, -122.631182" }, "geometry": { "type": "Point", "coordinates": [ -122.631182276769252, 45.493264691669488 ] } }
]
}
