{
"type": "FeatureCollection",
"name": "origin_destination_points",
"crs": { "type": "name", "properties": { "name": "urn:ogc:def:crs:OGC:1.3:CRS84" } },
"features": [
{ "type": "Feature", "properties": { "point_type": "origin", "points_str": "45.429767, -122.638603" }, "geometry": { "type": "Point", "coordinates": [ -122.638602697907757, 45.429766560992498 ] } },
{ "type": "Feature", "properties": { "point_type": "destination", "points_str": "45.400909, -122.497641" }, "geometry": { "type": "Point", "coordinates": [ -122.497640986545917, 45.400909394142865 ] } }
]
}
