{
"type": "FeatureCollection",
"crs": { "type": "name", "properties": { "name": "urn:ogc:def:crs:OGC:1.3:CRS84" } },
"features": [
{ "type": "Feature", "properties": { "point_type": "origin", "points_str": "45.473824, -122.761905" }, "geometry": { "type": "Point", "coordinates": [ -122.761904766027172, 45.473824254379579 ] } },
{ "type": "Feature", "properties": { "point_type": "destination", "points_str": "45.520478, -122.926297" }, "geometry": { "type": "Point", "coordinates": [ -122.926296988882797, 45.520477733666674 ] } }
]
}
