{
"type": "FeatureCollection",
"crs": { "type": "name", "properties": { "name": "urn:ogc:def:crs:OGC:1.3:CRS84" } },
"features": [
{ "type": "Feature", "properties": { "point_type": "origin", "points_str": "45.489156, -122.755121" }, "geometry": { "type": "Point", "coordinates": [ -122.755120566354293, 45.489155991498627 ] } },
{ "type": "Feature", "properties": { "point_type": "destination", "points_str": "45.596336, -122.741023" }, "geometry": { "type": "Point", "coordinates": [ -122.741023215884468, 45.596336369443051 ] } }
]
}
