{
"type": "FeatureCollection",
"crs": { "type": "name", "properties": { "name": "urn:ogc:def:crs:OGC:1.3:CRS84" } },
"features": [
{ "type": "Feature", "properties": { "point_type": "origin", "points_str": "45.495754, -122.642092" }, "geometry": { "type": "Point", "coordinates": [ -122.642092277183693, 45.495753794548719 ] } },
{ "type": "Feature", "properties": { "point_type": "destination", "points_str": "45.325037, -122.562495" }, "geometry": { "type": "Point", "coordinates": [ -122.562495029676711, 45.325037243856272 ] } }
]
}
