{
"type": "FeatureCollection",
"name": "origin_destination_points",
"crs": { "type": "name", "properties": { "name": "urn:ogc:def:crs:OGC:1.3:CRS84" } },
"features": [
{ "type": "Feature", "properties": { "point_type": "origin", "points_str": "45.523611, -122.605357" }, "geometry": { "type": "Point", "coordinates": [ -122.605356522397642, 45.523611128722742 ] } },
{ "type": "Feature", "properties": { "point_type": "destination", "points_str": "45.427886, -122.538826" }, "geometry": { "type": "Point", "coordinates": [ -122.538825862764028, 45.42788585444746 ] } }
]
}
