{
"type": "FeatureCollection",
"name": "origin_destination_points",
"crs": { "type": "name", "properties": { "name": "urn:ogc:def:crs:OGC:1.3:CRS84" } },
"features": [
{ "type": "Feature", "properties": { "point_type": "origin", "points_str": "45.530472, -122.664999" }, "geometry": { "type": "Point", "coordinates": [ -122.664999456753577, 45.530472359078196 ] } },
{ "type": "Feature", "properties": { "point_type": "destination", "points_str": "45.553877, -122.578833" }, "geometry": { "type": "Point", "coordinates": [ -122.578833236519131, 45.553876740678163 ] } }
]
}
