{
"type": "FeatureCollection",
"name": "origin_destination_points",
"crs": { "type": "name", "properties": { "name": "urn:ogc:def:crs:OGC:1.3:CRS84" } },
"features": [
{ "type": "Feature", "properties": { "point_type": "origin", "points_str": "45.530874, -122.628068" }, "geometry": { "type": "Point", "coordinates": [ -122.628068414697026, 45.530874173207692 ] } },
{ "type": "Feature", "properties": { "point_type": "destination", "points_str": "45.450533, -122.761007" }, "geometry": { "type": "Point", "coordinates": [ -122.761007495053221, 45.450533109176142 ] } }
]
}
