{
"type": "FeatureCollection",
"name": "origin_destination_points",
"crs": { "type": "name", "properties": { "name": "urn:ogc:def:crs:OGC:1.3:CRS84" } },
"features": [
{ "type": "Feature", "properties": { "point_type": "origin", "points_str": "45.501564, -122.655322" }, "geometry": { "type": "Point", "coordinates": [ -122.655321546342279, 45.501564212660838 ] } },
{ "type": "Feature", "properties": { "point_type": "destination", "points_str": "45.484961, -122.449072" }, "geometry": { "type": "Point", "coordinates": [ -122.449072194820076, 45.4849610407109 ] } }
]
}
