{
"type": "FeatureCollection",
"crs": { "type": "name", "properties": { "name": "urn:ogc:def:crs:OGC:1.3:CRS84" } },
"features": [
{ "type": "Feature", "properties": { "point_type": "origin", "points_str": "45.548029, -122.718353" }, "geometry": { "type": "Point", "coordinates": [ -122.718353441539435, 45.548028817832019 ] } },
{ "type": "Feature", "properties": { "point_type": "destination", "points_str": "45.364982, -122.60116" }, "geometry": { "type": "Point", "coordinates": [ -122.601159612518813, 45.364982204252364 ] } }
]
}
