{
"type": "FeatureCollection",
"name": "origin_destination_points",
"crs": { "type": "name", "properties": { "name": "urn:ogc:def:crs:OGC:1.3:CRS84" } },
"features": [
{ "type": "Feature", "properties": { "point_type": "origin", "points_str": "45.550092, -122.593187" }, "geometry": { "type": "Point", "coordinates": [ -122.593186701621391, 45.550092200975399 ] } },
{ "type": "Feature", "properties": { "point_type": "destination", "points_str": "45.557588, -122.57404" }, "geometry": { "type": "Point", "coordinates": [ -122.574039698255746, 45.557588493499388 ] } }
]
}
