{
"type": "FeatureCollection",
"name": "origin_destination_points",
"crs": { "type": "name", "properties": { "name": "urn:ogc:def:crs:OGC:1.3:CRS84" } },
"features": [
{ "type": "Feature", "properties": { "point_type": "origin", "points_str": "45.508456, -122.759164" }, "geometry": { "type": "Point", "coordinates": [ -122.75916408409924, 45.50845636121884 ] } },
{ "type": "Feature", "properties": { "point_type": "destination", "points_str": "45.5341, -122.695526" }, "geometry": { "type": "Point", "coordinates": [ -122.695526480104476, 45.534099861642062 ] } }
]
}
