{
"type": "FeatureCollection",
"name": "origin_destination_points",
"crs": { "type": "name", "properties": { "name": "urn:ogc:def:crs:OGC:1.3:CRS84" } },
"features": [
{ "type": "Feature", "properties": { "point_type": "origin", "points_str": "45.545941, -122.60077" }, "geometry": { "type": "Point", "coordinates": [ -122.600770293367518, 45.545941313049063 ] } },
{ "type": "Feature", "properties": { "point_type": "destination", "points_str": "45.466132, -122.603967" }, "geometry": { "type": "Point", "coordinates": [ -122.60396707719859, 45.466132166992622 ] } }
]
}
