{
"type": "FeatureCollection",
"crs": { "type": "name", "properties": { "name": "urn:ogc:def:crs:OGC:1.3:CRS84" } },
"features": [
{ "type": "Feature", "properties": { "point_type": "origin", "points_str": "45.553242, -122.57254" }, "geometry": { "type": "Point", "coordinates": [ -122.572539665001514, 45.55324163315624 ] } },
{ "type": "Feature", "properties": { "point_type": "destination", "points_str": "45.55129, -122.537066" }, "geometry": { "type": "Point", "coordinates": [ -122.537066021013885, 45.551290471710615 ] } }
]
}
