{
"type": "FeatureCollection",
"name": "origin_destination_points",
"crs": { "type": "name", "properties": { "name": "urn:ogc:def:crs:OGC:1.3:CRS84" } },
"features": [
{ "type": "Feature", "properties": { "point_type": "origin", "points_str": "45.390959, -122.646936" }, "geometry": { "type": "Point", "coordinates": [ -122.646935690484099, 45.390958562708924 ] } },
{ "type": "Feature", "properties": { "point_type": "destination", "points_str": "45.326752, -122.579299" }, "geometry": { "type": "Point", "coordinates": [ -122.579299062086164, 45.326751752725464 ] } }
]
}
