{
"type": "FeatureCollection",
"name": "origin_destination_points",
"crs": { "type": "name", "properties": { "name": "urn:ogc:def:crs:OGC:1.3:CRS84" } },
"features": [
{ "type": "Feature", "properties": { "point_type": "origin", "points_str": "45.522732, -122.669402" }, "geometry": { "type": "Point", "coordinates": [ -122.669402300562496, 45.522732026062293 ] } },
{ "type": "Feature", "properties": { "point_type": "destination", "points_str": "45.472898, -122.612729" }, "geometry": { "type": "Point", "coordinates": [ -122.612729463693029, 45.472897652287195 ] } }
]
}
