{
"type": "FeatureCollection",
"name": "origin_destination_points",
"crs": { "type": "name", "properties": { "name": "urn:ogc:def:crs:OGC:1.3:CRS84" } },
"features": [
{ "type": "Feature", "properties": { "point_type": "origin", "points_str": "45.467568, -122.577928" }, "geometry": { "type": "Point", "coordinates": [ -122.577927548847924, 45.467567800232757 ] } },
{ "type": "Feature", "properties": { "point_type": "destination", "points_str": "45.405825, -122.50261" }, "geometry": { "type": "Point", "coordinates": [ -122.502610071716191, 45.405825348308412 ] } }
]
}
