{
"type": "FeatureCollection",
"name": "origin_destination_points",
"crs": { "type": "name", "properties": { "name": "urn:ogc:def:crs:OGC:1.3:CRS84" } },
"features": [
{ "type": "Feature", "properties": { "point_type": "origin", "points_str": "45.469144, -122.797958" }, "geometry": { "type": "Point", "coordinates": [ -122.797958327233033, 45.469143851833415 ] } },
{ "type": "Feature", "properties": { "point_type": "destination", "points_str": "45.48857, -122.875867" }, "geometry": { "type": "Point", "coordinates": [ -122.875867023073198, 45.488570496796022 ] } }
]
}
