{
"type": "FeatureCollection",
"name": "origin_destination_points",
"crs": { "type": "name", "properties": { "name": "urn:ogc:def:crs:OGC:1.3:CRS84" } },
"features": [
{ "type": "Feature", "properties": { "point_type": "origin", "points_str": "45.437792, -122.77851" }, "geometry": { "type": "Point", "coordinates": [ -122.778510160876863, 45.437791862010201 ] } },
{ "type": "Feature", "properties": { "point_type": "destination", "points_str": "45.432907, -122.720572" }, "geometry": { "type": "Point", "coordinates": [ -122.720572239204472, 45.43290749026476 ] } }
]
}
