{
"type": "FeatureCollection",
"name": "origin_destination_points",
"crs": { "type": "name", "properties": { "name": "urn:ogc:def:crs:OGC:1.3:CRS84" } },
"features": [
{ "type": "Feature", "properties": { "point_type": "origin", "points_str": "45.564447, -122.667655" }, "geometry": { "type": "Point", "coordinates": [ -122.667655388579831, 45.564447016919999 ] } },
{ "type": "Feature", "properties": { "point_type": "destination", "points_str": "45.523261, -122.67255" }, "geometry": { "type": "Point", "coordinates": [ -122.672549588360837, 45.523260589559641 ] } }
]
}
