{
"type": "FeatureCollection",
"name": "origin_destination_points",
"crs": { "type": "name", "properties": { "name": "urn:ogc:def:crs:OGC:1.3:CRS84" } },
"features": [
{ "type": "Feature", "properties": { "point_type": "origin", "points_str": "45.470825, -122.606708" }, "geometry": { "type": "Point", "coordinates": [ -122.60670799623098, 45.470825196553541 ] } },
{ "type": "Feature", "properties": { "point_type": "destination", "points_str": "45.53911, -122.700631" }, "geometry": { "type": "Point", "coordinates": [ -122.700630502973752, 45.539109546653897 ] } }
]
}
