{
"type": "FeatureCollection",
"crs": { "type": "name", "properties": { "name": "urn:ogc:def:crs:OGC:1.3:CRS84" } },
"features": [
{ "type": "Feature", "properties": { "point_type": "origin", "points_str": "45.519497, -122.477021" }, "geometry": { "type": "Point", "coordinates": [ -122.477020933256, 45.519497302075166 ] } },
{ "type": "Feature", "properties": { "point_type": "destination", "points_str": "45.555986, -122.500734" }, "geometry": { "type": "Point", "coordinates": [ -122.500733865162616, 45.555986157949796 ] } }
]
}
