{
"type": "FeatureCollection",
"name": "origin_destination_points",
"crs": { "type": "name", "properties": { "name": "urn:ogc:def:crs:OGC:1.3:CRS84" } },
"features": [
{ "type": "Feature", "properties": { "point_type": "origin", "points_str": "45.502542, -122.420241" }, "geometry": { "type": "Point", "coordinates": [ -122.420241483669173, 45.502542320582215 ] } },
{ "type": "Feature", "properties": { "point_type": "destination", "points_str": "45.502576, -122.870212" }, "geometry": { "type": "Point", "coordinates": [ -122.870212130603974, 45.502576478380909 ] } }
]
}
