{
"type": "FeatureCollection",
"name": "origin_destination_points",
"crs": { "type": "name", "properties": { "name": "urn:ogc:def:crs:OGC:1.3:CRS84" } },
"features": [
{ "type": "Feature", "properties": { "point_type": "origin", "points_str": "45.504026, -122.480094" }, "geometry": { "type": "Point", "coordinates": [ -122.480094201066578, 45.504026472288764 ] } },
{ "type": "Feature", "properties": { "point_type": "destination", "points_str": "45.506378, -122.512585" }, "geometry": { "type": "Point", "coordinates": [ -122.512585221589276, 45.506378145561406 ] } }
]
}
