{
"type": "FeatureCollection",
"crs": { "type": "name", "properties": { "name": "urn:ogc:def:crs:OGC:1.3:CRS84" } },
"features": [
{ "type": "Feature", "properties": { "point_type": "origin", "points_str": "45.527902, -122.664035" }, "geometry": { "type": "Point", "coordinates": [ -122.664035195918004, 45.527901676831746 ] } },
{ "type": "Feature", "properties": { "point_type": "destination", "points_str": "45.565363, -122.683145" }, "geometry": { "type": "Point", "coordinates": [ -122.683145103654226, 45.565363207772364 ] } }
]
}
