{
"type": "FeatureCollection",
"crs": { "type": "name", "properties": { "name": "urn:ogc:def:crs:OGC:1.3:CRS84" } },
"features": [
{ "type": "Feature", "properties": { "point_type": "origin", "points_str": "45.478705, -122.686729" }, "geometry": { "type": "Point", "coordinates": [ -122.686728794153623, 45.478705432479103 ] } },
{ "type": "Feature", "properties": { "point_type": "destination", "points_str": "45.492536, -122.847628" }, "geometry": { "type": "Point", "coordinates": [ -122.84762827425358, 45.492536275051862 ] } }
]
}
