{
"type": "FeatureCollection",
"name": "origin_destination_points",
"crs": { "type": "name", "properties": { "name": "urn:ogc:def:crs:OGC:1.3:CRS84" } },
"features": [
{ "type": "Feature", "properties": { "point_type": "origin", "points_str": "45.50189, -122.449722" }, "geometry": { "type": "Point", "coordinates": [ -122.449721979819472, 45.501890009087688 ] } },
{ "type": "Feature", "properties": { "point_type": "destination", "points_str": "45.364772, -122.615567" }, "geometry": { "type": "Point", "coordinates": [ -122.615567101770765, 45.364772022322896 ] } }
]
}
