{
"type": "FeatureCollection",
"crs": { "type": "name", "properties": { "name": "urn:ogc:def:crs:OGC:1.3:CRS84" } },
"features": [
{ "type": "Feature", "properties": { "point_type": "origin", "points_str": "45.329798, -122.593115" }, "geometry": { "type": "Point", "coordinates": [ -122.593114889730032, 45.329797528970161 ] } },
{ "type": "Feature", "properties": { "point_type": "destination", "points_str": "45.501524, -122.653439" }, "geometry": { "type": "Point", "coordinates": [ -122.653438870579549, 45.501524403150363 ] } }
]
}
