{
"type": "FeatureCollection",
"name": "origin_destination_points",
"crs": { "type": "name", "properties": { "name": "urn:ogc:def:crs:OGC:1.3:CRS84" } },
"features": [
{ "type": "Feature", "properties": { "point_type": "origin", "points_str": "45.553104, -122.679032" }, "geometry": { "type": "Point", "coordinates": [ -122.679031905393018, 45.553104284660911 ] } },
{ "type": "Feature", "properties": { "point_type": "destination", "points_str": "45.52257, -122.493824" }, "geometry": { "type": "Point", "coordinates": [ -122.493824280304395, 45.522570482158002 ] } }
]
}
