{
"type": "FeatureCollection",
"crs": { "type": "name", "properties": { "name": "urn:ogc:def:crs:OGC:1.3:CRS84" } },
"features": [
{ "type": "Feature", "properties": { "point_type": "origin", "points_str": "45.479561, -122.522229" }, "geometry": { "type": "Point", "coordinates": [ -122.522229120125346, 45.479561060363302 ] } },
{ "type": "Feature", "properties": { "point_type": "destination", "points_str": "45.482802, -122.58704" }, "geometry": { "type": "Point", "coordinates": [ -122.587039814699239, 45.48280164746226 ] } }
]
}
