{
"type": "FeatureCollection",
"name": "origin_destination_points",
"crs": { "type": "name", "properties": { "name": "urn:ogc:def:crs:OGC:1.3:CRS84" } },
"features": [
{ "type": "Feature", "properties": { "point_type": "origin", "points_str": "45.418704, -122.659902" }, "geometry": { "type": "Point", "coordinates": [ -122.65990206523287, 45.418704468943041 ] } },
{ "type": "Feature", "properties": { "point_type": "destination", "points_str": "45.497766, -122.533346" }, "geometry": { "type": "Point", "coordinates": [ -122.533345711900452, 45.497766109585363 ] } }
]
}
