{
"type": "FeatureCollection",
"name": "origin_destination_points",
"crs": { "type": "name", "properties": { "name": "urn:ogc:def:crs:OGC:1.3:CRS84" } },
"features": [
{ "type": "Feature", "properties": { "point_type": "origin", "points_str": "45.557375, -122.493923" }, "geometry": { "type": "Point", "coordinates": [ -122.493922714175667, 45.557375138561206 ] } },
{ "type": "Feature", "properties": { "point_type": "destination", "points_str": "45.533638, -122.623598" }, "geometry": { "type": "Point", "coordinates": [ -122.623598368662783, 45.533638046464091 ] } }
]
}
