{
"type": "FeatureCollection",
"name": "origin_destination_points",
"crs": { "type": "name", "properties": { "name": "urn:ogc:def:crs:OGC:1.3:CRS84" } },
"features": [
{ "type": "Feature", "properties": { "point_type": "origin", "points_str": "45.437531, -122.749909" }, "geometry": { "type": "Point", "coordinates": [ -122.749909388351909, 45.437531393152646 ] } },
{ "type": "Feature", "properties": { "point_type": "destination", "points_str": "45.467303, -122.681413" }, "geometry": { "type": "Point", "coordinates": [ -122.681413014569145, 45.467302882894479 ] } }
]
}
