{
"type": "FeatureCollection",
"name": "origin_destination_points",
"crs": { "type": "name", "properties": { "name": "urn:ogc:def:crs:OGC:1.3:CRS84" } },
"features": [
{ "type": "Feature", "properties": { "point_type": "origin", "points_str": "45.370793, -122.774407" }, "geometry": { "type": "Point", "coordinates": [ -122.774407112624246, 45.37079294039922 ] } },
{ "type": "Feature", "properties": { "point_type": "destination", "points_str": "45.41359, -122.745796" }, "geometry": { "type": "Point", "coordinates": [ -122.745795966373279, 45.413590316332154 ] } }
]
}
