{
"type": "FeatureCollection",
"name": "origin_destination_points",
"crs": { "type": "name", "properties": { "name": "urn:ogc:def:crs:OGC:1.3:CRS84" } },
"features": [
{ "type": "Feature", "properties": { "point_type": "origin", "points_str": "45.555865, -122.573308" }, "geometry": { "type": "Point", "coordinates": [ -122.573307797153618, 45.555864773004075 ] } },
{ "type": "Feature", "properties": { "point_type": "destination", "points_str": "45.468372, -122.684339" }, "geometry": { "type": "Point", "coordinates": [ -122.684338677307721, 45.468371631661427 ] } }
]
}
