{
"type": "FeatureCollection",
"name": "origin_destination_points",
"crs": { "type": "name", "properties": { "name": "urn:ogc:def:crs:OGC:1.3:CRS84" } },
"features": [
{ "type": "Feature", "properties": { "point_type": "origin", "points_str": "45.555601, -122.680885" }, "geometry": { "type": "Point", "coordinates": [ -122.680884937550687, 45.555600800704731 ] } },
{ "type": "Feature", "properties": { "point_type": "destination", "points_str": "45.562653, -122.580862" }, "geometry": { "type": "Point", "coordinates": [ -122.580861762241028, 45.562653223179169 ] } }
]
}
