{
"type": "FeatureCollection",
"name": "origin_destination_points",
"crs": { "type": "name", "properties": { "name": "urn:ogc:def:crs:OGC:1.3:CRS84" } },
"features": [
{ "type": "Feature", "properties": { "point_type": "origin", "points_str": "45.587293, -122.72002" }, "geometry": { "type": "Point", "coordinates": [ -122.720020052394091, 45.587293433860395 ] } },
{ "type": "Feature", "properties": { "point_type": "destination", "points_str": "45.451494, -122.67825" }, "geometry": { "type": "Point", "coordinates": [ -122.678250491487944, 45.45149419599197 ] } }
]
}
