{
"type": "FeatureCollection",
"name": "origin_destination_points",
"crs": { "type": "name", "properties": { "name": "urn:ogc:def:crs:OGC:1.3:CRS84" } },
"features": [
{ "type": "Feature", "properties": { "point_type": "origin", "points_str": "45.542651, -122.67524" }, "geometry": { "type": "Point", "coordinates": [ -122.675240013978595, 45.542650758398793 ] } },
{ "type": "Feature", "properties": { "point_type": "destination", "points_str": "45.559216, -122.682625" }, "geometry": { "type": "Point", "coordinates": [ -122.682625368665398, 45.5592155931663 ] } }
]
}
