{
"type": "FeatureCollection",
"crs": { "type": "name", "properties": { "name": "urn:ogc:def:crs:OGC:1.3:CRS84" } },
"features": [
{ "type": "Feature", "properties": { "point_type": "origin", "points_str": "45.501162, -122.799507" }, "geometry": { "type": "Point", "coordinates": [ -122.799507318229416, 45.501162369991803 ] } },
{ "type": "Feature", "properties": { "point_type": "destination", "points_str": "45.552498, -122.72456" }, "geometry": { "type": "Point", "coordinates": [ -122.724559571297348, 45.55249805024399 ] } }
]
}
