{
"type": "FeatureCollection",
"crs": { "type": "name", "properties": { "name": "urn:ogc:def:crs:OGC:1.3:CRS84" } },
"features": [
{ "type": "Feature", "properties": { "point_type": "origin", "points_str": "45.478605, -122.821265" }, "geometry": { "type": "Point", "coordinates": [ -122.8212652385469, 45.478604568754982 ] } },
{ "type": "Feature", "properties": { "point_type": "destination", "points_str": "45.457323, -122.821604" }, "geometry": { "type": "Point", "coordinates": [ -122.821603765870563, 45.457323314144787 ] } }
]
}
