{
"type": "FeatureCollection",
"name": "origin_destination_points",
"crs": { "type": "name", "properties": { "name": "urn:ogc:def:crs:OGC:1.3:CRS84" } },
"features": [
{ "type": "Feature", "properties": { "point_type": "origin", "points_str": "45.492685, -122.603369" }, "geometry": { "type": "Point", "coordinates": [ -122.603368524304557, 45.492685201026596 ] } },
{ "type": "Feature", "properties": { "point_type": "destination", "points_str": "45.479341, -122.595285" }, "geometry": { "type": "Point", "coordinates": [ -122.595285272521394, 45.479341099015855 ] } }
]
}
