{
"type": "FeatureCollection",
"name": "origin_destination_points",
"crs": { "type": "name", "properties": { "name": "urn:ogc:def:crs:OGC:1.3:CRS84" } },
"features": [
{ "type": "Feature", "properties": { "point_type": "origin", "points_str": "45.460526, -122.636186" }, "geometry": { "type": "Point", "coordinates": [ -122.636185911854483, 45.460525549857365 ] } },
{ "type": "Feature", "properties": { "point_type": "destination", "points_str": "45.447427, -122.62457" }, "geometry": { "type": "Point", "coordinates": [ -122.624570396461522, 45.447427269066388 ] } }
]
}
