{
"type": "FeatureCollection",
"name": "origin_destination_points",
"crs": { "type": "name", "properties": { "name": "urn:ogc:def:crs:OGC:1.3:CRS84" } },
"features": [
{ "type": "Feature", "properties": { "point_type": "origin", "points_str": "45.521177, -122.432876" }, "geometry": { "type": "Point", "coordinates": [ -122.432876428815177, 45.521176941703658 ] } },
{ "type": "Feature", "properties": { "point_type": "destination", "points_str": "45.545851, -122.434676" }, "geometry": { "type": "Point", "coordinates": [ -122.434675991627472, 45.545851112944788 ] } }
]
}
