{
"type": "FeatureCollection",
"name": "origin_destination_points",
"crs": { "type": "name", "properties": { "name": "urn:ogc:def:crs:OGC:1.3:CRS84" } },
"features": [
{ "type": "Feature", "properties": { "point_type": "origin", "points_str": "45.511363, -122.736513" }, "geometry": { "type": "Point", "coordinates": [ -122.736512552888669, 45.511362762952693 ] } },
{ "type": "Feature", "properties": { "point_type": "destination", "points_str": "45.515971, -123.017206" }, "geometry": { "type": "Point", "coordinates": [ -123.017206414080235, 45.515970734241122 ] } }
]
}
