{
"type": "FeatureCollection",
"crs": { "type": "name", "properties": { "name": "urn:ogc:def:crs:OGC:1.3:CRS84" } },
"features": [
{ "type": "Feature", "properties": { "point_type": "origin", "points_str": "45.517076, -122.839348" }, "geometry": { "type": "Point", "coordinates": [ -122.839347814427924, 45.517076363828778 ] } },
{ "type": "Feature", "properties": { "point_type": "destination", "points_str": "45.531785, -122.822115" }, "geometry": { "type": "Point", "coordinates": [ -122.822114641753927, 45.531785461625383 ] } }
]
}
