{
"type": "FeatureCollection",
"name": "origin_destination_points",
"crs": { "type": "name", "properties": { "name": "urn:ogc:def:crs:OGC:1.3:CRS84" } },
"features": [
{ "type": "Feature", "properties": { "point_type": "origin", "points_str": "45.580104, -122.693734" }, "geometry": { "type": "Point", "coordinates": [ -122.693733779542768, 45.580104104881237 ] } },
{ "type": "Feature", "properties": { "point_type": "destination", "points_str": "45.368363, -122.592087" }, "geometry": { "type": "Point", "coordinates": [ -122.592086694998002, 45.368362539057294 ] } }
]
}
