{
"type": "FeatureCollection",
"crs": { "type": "name", "properties": { "name": "urn:ogc:def:crs:OGC:1.3:CRS84" } },
"features": [
{ "type": "Feature", "properties": { "point_type": "origin", "points_str": "45.383505, -122.815954" }, "geometry": { "type": "Point", "coordinates": [ -122.815953823207238, 45.383505294672808 ] } },
{ "type": "Feature", "properties": { "point_type": "destination", "points_str": "45.458524, -122.758043" }, "geometry": { "type": "Point", "coordinates": [ -122.758043251823139, 45.45852384046551 ] } }
]
}
