{
"type": "FeatureCollection",
"name": "origin_destination_points",
"crs": { "type": "name", "properties": { "name": "urn:ogc:def:crs:OGC:1.3:CRS84" } },
"features": [
{ "type": "Feature", "properties": { "point_type": "origin", "points_str": "45.571197, -122.685351" }, "geometry": { "type": "Point", "coordinates": [ -122.685350855547767, 45.571196506998909 ] } },
{ "type": "Feature", "properties": { "point_type": "destination", "points_str": "45.58607, -122.597922" }, "geometry": { "type": "Point", "coordinates": [ -122.597922263397393, 45.58607009741776 ] } }
]
}
