{
"type": "FeatureCollection",
"name": "origin_destination_points",
"crs": { "type": "name", "properties": { "name": "urn:ogc:def:crs:OGC:1.3:CRS84" } },
"features": [
{ "type": "Feature", "properties": { "point_type": "origin", "points_str": "45.517944, -122.744479" }, "geometry": { "type": "Point", "coordinates": [ -122.744479178732803, 45.517943904718123 ] } },
{ "type": "Feature", "properties": { "point_type": "destination", "points_str": "45.521381, -122.452861" }, "geometry": { "type": "Point", "coordinates": [ -122.45286093278753, 45.521380603447462 ] } }
]
}
