{
"type": "FeatureCollection",
"name": "origin_destination_points",
"crs": { "type": "name", "properties": { "name": "urn:ogc:def:crs:OGC:1.3:CRS84" } },
"features": [
{ "type": "Feature", "properties": { "point_type": "origin", "points_str": "45.486482, -122.726071" }, "geometry": { "type": "Point", "coordinates": [ -122.72607116460982, 45.486482480132409 ] } },
{ "type": "Feature", "properties": { "point_type": "destination", "points_str": "45.515797, -122.483646" }, "geometry": { "type": "Point", "coordinates": [ -122.483645695679769, 45.51579730469183 ] } }
]
}
