{
"type": "FeatureCollection",
"name": "origin_destination_points",
"crs": { "type": "name", "properties": { "name": "urn:ogc:def:crs:OGC:1.3:CRS84" } },
"features": [
{ "type": "Feature", "properties": { "point_type": "origin", "points_str": "45.519728, -122.639087" }, "geometry": { "type": "Point", "coordinates": [ -122.639087441634274, 45.519727960039951 ] } },
{ "type": "Feature", "properties": { "point_type": "destination", "points_str": "45.525598, -122.48607" }, "geometry": { "type": "Point", "coordinates": [ -122.486070419319461, 45.525598279505694 ] } }
]
}
