{
"type": "FeatureCollection",
"name": "origin_destination_points",
"crs": { "type": "name", "properties": { "name": "urn:ogc:def:crs:OGC:1.3:CRS84" } },
"features": [
{ "type": "Feature", "properties": { "point_type": "origin", "points_str": "45.497495, -122.814344" }, "geometry": { "type": "Point", "coordinates": [ -122.814343552759382, 45.49749537643261 ] } },
{ "type": "Feature", "properties": { "point_type": "destination", "points_str": "45.52183, -122.401983" }, "geometry": { "type": "Point", "coordinates": [ -122.401982847393782, 45.521829513993652 ] } }
]
}
