{
"type": "FeatureCollection",
"name": "origin_destination_points",
"crs": { "type": "name", "properties": { "name": "urn:ogc:def:crs:OGC:1.3:CRS84" } },
"features": [
{ "type": "Feature", "properties": { "point_type": "origin", "points_str": "45.463908, -122.588271" }, "geometry": { "type": "Point", "coordinates": [ -122.588270967108045, 45.463907772170238 ] } },
{ "type": "Feature", "properties": { "point_type": "destination", "points_str": "45.431685, -122.540551" }, "geometry": { "type": "Point", "coordinates": [ -122.540550942825263, 45.431685102202017 ] } }
]
}
