{
"type": "FeatureCollection",
"crs": { "type": "name", "properties": { "name": "urn:ogc:def:crs:OGC:1.3:CRS84" } },
"features": [
{ "type": "Feature", "properties": { "point_type": "origin", "points_str": "45.492639, -122.702751" }, "geometry": { "type": "Point", "coordinates": [ -122.702750801195549, 45.492639496420587 ] } },
{ "type": "Feature", "properties": { "point_type": "destination", "points_str": "45.522065, -122.513618" }, "geometry": { "type": "Point", "coordinates": [ -122.513618229263358, 45.522064636856598 ] } }
]
}
