{
"type": "FeatureCollection",
"name": "origin_destination_points",
"crs": { "type": "name", "properties": { "name": "urn:ogc:def:crs:OGC:1.3:CRS84" } },
"features": [
{ "type": "Feature", "properties": { "point_type": "origin", "points_str": "45.558757, -122.582966" }, "geometry": { "type": "Point", "coordinates": [ -122.582965911018107, 45.55875730907276 ] } },
{ "type": "Feature", "properties": { "point_type": "destination", "points_str": "45.526774, -122.610884" }, "geometry": { "type": "Point", "coordinates": [ -122.610883706123303, 45.526774205669952 ] } }
]
}
