{
"type": "FeatureCollection",
"crs": { "type": "name", "properties": { "name": "urn:ogc:def:crs:OGC:1.3:CRS84" } },
"features": [
{ "type": "Feature", "properties": { "point_type": "origin", "points_str": "45.537812, -122.624797" }, "geometry": { "type": "Point", "coordinates": [ -122.624796936718525, 45.537812485174641 ] } },
{ "type": "Feature", "properties": { "point_type": "destination", "points_str": "45.444276, -122.759264" }, "geometry": { "type": "Point", "coordinates": [ -122.759264360457948, 45.444276297881309 ] } }
]
}
