{
"type": "FeatureCollection",
"name": "origin_destination_points",
"crs": { "type": "name", "properties": { "name": "urn:ogc:def:crs:OGC:1.3:CRS84" } },
"features": [
{ "type": "Feature", "properties": { "point_type": "origin", "points_str": "45.376631, -122.747559" }, "geometry": { "type": "Point", "coordinates": [ -122.747559210647751, 45.376631411168013 ] } },
{ "type": "Feature", "properties": { "point_type": "destination", "points_str": "45.497948, -122.86314" }, "geometry": { "type": "Point", "coordinates": [ -122.863139807326561, 45.497947938340239 ] } }
]
}
