{
"type": "FeatureCollection",
"name": "origin_destination_points",
"crs": { "type": "name", "properties": { "name": "urn:ogc:def:crs:OGC:1.3:CRS84" } },
"features": [
{ "type": "Feature", "properties": { "point_type": "origin", "points_str": "45.529609, -122.667859" }, "geometry": { "type": "Point", "coordinates": [ -122.667859423323137, 45.529609356625237 ] } },
{ "type": "Feature", "properties": { "point_type": "destination", "points_str": "45.538324, -122.89466" }, "geometry": { "type": "Point", "coordinates": [ -122.894659852820595, 45.538324277586334 ] } }
]
}
