{
"type": "FeatureCollection",
"crs": { "type": "name", "properties": { "name": "urn:ogc:def:crs:OGC:1.3:CRS84" } },
"features": [
{ "type": "Feature", "properties": { "point_type": "origin", "points_str": "45.465718, -122.792277" }, "geometry": { "type": "Point", "coordinates": [ -122.792277346451911, 45.465717656107728 ] } },
{ "type": "Feature", "properties": { "point_type": "destination", "points_str": "45.500501, -122.864169" }, "geometry": { "type": "Point", "coordinates": [ -122.864169485081959, 45.500501491700696 ] } }
]
}
