{
"type": "FeatureCollection",
"name": "origin_destination_points",
"crs": { "type": "name", "properties": { "name": "urn:ogc:def:crs:OGC:1.3:CRS84" } },
"features": [
{ "type": "Feature", "properties": { "point_type": "origin", "points_str": "45.468637, -122.794396" }, "geometry": { "type": "Point", "coordinates": [ -122.794395749950795, 45.468637102010049 ] } },
{ "type": "Feature", "properties": { "point_type": "destination", "points_str": "45.465044, -122.820986" }, "geometry": { "type": "Point", "coordinates": [ -122.820985648228941, 45.465044482262449 ] } }
]
}
