{
"type": "FeatureCollection",
"name": "origin_destination_points",
"crs": { "type": "name", "properties": { "name": "urn:ogc:def:crs:OGC:1.3:CRS84" } },
"features": [
{ "type": "Feature", "properties": { "point_type": "origin", "points_str": "45.496629, -122.60154" }, "geometry": { "type": "Point", "coordinates": [ -122.601539948374423, 45.496628547366655 ] } },
{ "type": "Feature", "properties": { "point_type": "destination", "points_str": "45.492515, -122.802896" }, "geometry": { "type": "Point", "coordinates": [ -122.802895705845856, 45.492514701163422 ] } }
]
}
