{
"type": "FeatureCollection",
"name": "origin_destination_points",
"crs": { "type": "name", "properties": { "name": "urn:ogc:def:crs:OGC:1.3:CRS84" } },
"features": [
{ "type": "Feature", "properties": { "point_type": "origin", "points_str": "45.499428, -122.528331" }, "geometry": { "type": "Point", "coordinates": [ -122.528331325102059, 45.499428336455608 ] } },
{ "type": "Feature", "properties": { "point_type": "destination", "points_str": "45.37829, -122.6336" }, "geometry": { "type": "Point", "coordinates": [ -122.633599718922468, 45.378290114238368 ] } }
]
}
