{
"type": "FeatureCollection",
"name": "origin_destination_points",
"crs": { "type": "name", "properties": { "name": "urn:ogc:def:crs:OGC:1.3:CRS84" } },
"features": [
{ "type": "Feature", "properties": { "point_type": "origin", "points_str": "45.49419, -122.769343" }, "geometry": { "type": "Point", "coordinates": [ -122.769342728674971, 45.494190381345 ] } },
{ "type": "Feature", "properties": { "point_type": "destination", "points_str": "45.465169, -122.803014" }, "geometry": { "type": "Point", "coordinates": [ -122.803013646234007, 45.465169281187286 ] } }
]
}
