{
"type": "FeatureCollection",
"name": "origin_destination_points",
"crs": { "type": "name", "properties": { "name": "urn:ogc:def:crs:OGC:1.3:CRS84" } },
"features": [
{ "type": "Feature", "properties": { "point_type": "origin", "points_str": "45.507742, -122.664515" }, "geometry": { "type": "Point", "coordinates": [ -122.66451535738463, 45.507741860262414 ] } },
{ "type": "Feature", "properties": { "point_type": "destination", "points_str": "45.521085, -122.533676" }, "geometry": { "type": "Point", "coordinates": [ -122.53367622207648, 45.521085196031983 ] } }
]
}
