{
"type": "FeatureCollection",
"crs": { "type": "name", "properties": { "name": "urn:ogc:def:crs:OGC:1.3:CRS84" } },
"features": [
{ "type": "Feature", "properties": { "point_type": "origin", "points_str": "45.5137, -122.877606" }, "geometry": { "type": "Point", "coordinates": [ -122.877606293267817, 45.513699525275833 ] } },
{ "type": "Feature", "properties": { "point_type": "destination", "points_str": "45.476181, -122.793944" }, "geometry": { "type": "Point", "coordinates": [ -122.793943672648808, 45.47618130155908 ] } }
]
}
