{
"type": "FeatureCollection",
"name": "origin_destination_points",
"crs": { "type": "name", "properties": { "name": "urn:ogc:def:crs:OGC:1.3:CRS84" } },
"features": [
{ "type": "Feature", "properties": { "point_type": "origin", "points_str": "45.508611, -122.853316" }, "geometry": { "type": "Point", "coordinates": [ -122.853315609622996, 45.508611252274264 ] } },
{ "type": "Feature", "properties": { "point_type": "destination", "points_str": "45.515936, -123.11368" }, "geometry": { "type": "Point", "coordinates": [ -123.113680091642621, 45.515936255915555 ] } }
]
}
