{
"type": "FeatureCollection",
"crs": { "type": "name", "properties": { "name": "urn:ogc:def:crs:OGC:1.3:CRS84" } },
"features": [
{ "type": "Feature", "properties": { "point_type": "origin", "points_str": "45.518928, -122.487091" }, "geometry": { "type": "Point", "coordinates": [ -122.487091412356861, 45.518927558557316 ] } },
{ "type": "Feature", "properties": { "point_type": "destination", "points_str": "45.538123, -122.618362" }, "geometry": { "type": "Point", "coordinates": [ -122.618361757245637, 45.538123271447738 ] } }
]
}
