{
"type": "FeatureCollection",
"name": "origin_destination_points",
"crs": { "type": "name", "properties": { "name": "urn:ogc:def:crs:OGC:1.3:CRS84" } },
"features": [
{ "type": "Feature", "properties": { "point_type": "origin", "points_str": "45.535105, -122.665817" }, "geometry": { "type": "Point", "coordinates": [ -122.665817447068264, 45.535104839305582 ] } },
{ "type": "Feature", "properties": { "point_type": "destination", "points_str": "45.600913, -122.783843" }, "geometry": { "type": "Point", "coordinates": [ -122.783842678691542, 45.600912760392525 ] } }
]
}
