{
"type": "FeatureCollection",
"name": "origin_destination_points",
"crs": { "type": "name", "properties": { "name": "urn:ogc:def:crs:OGC:1.3:CRS84" } },
"features": [
{ "type": "Feature", "properties": { "point_type": "origin", "points_str": "45.520853, -123.117471" }, "geometry": { "type": "Point", "coordinates": [ -123.117470576465635, 45.520853355944581 ] } },
{ "type": "Feature", "properties": { "point_type": "destination", "points_str": "45.534769, -122.936019" }, "geometry": { "type": "Point", "coordinates": [ -122.936018660913078, 45.534769155230549 ] } }
]
}
