{
"type": "FeatureCollection",
"name": "origin_destination_points",
"crs": { "type": "name", "properties": { "name": "urn:ogc:def:crs:OGC:1.3:CRS84" } },
"features": [
{ "type": "Feature", "properties": { "point_type": "origin", "points_str": "45.522702, -122.652276" }, "geometry": { "type": "Point", "coordinates": [ -122.652275743189847, 45.522702088045151 ] } },
{ "type": "Feature", "properties": { "point_type": "destination", "points_str": "45.520201, -122.544336" }, "geometry": { "type": "Point", "coordinates": [ -122.544335727372854, 45.520201161229942 ] } }
]
}
