{
"type": "FeatureCollection",
"name": "origin_destination_points",
"crs": { "type": "name", "properties": { "name": "urn:ogc:def:crs:OGC:1.3:CRS84" } },
"features": [
{ "type": "Feature", "properties": { "point_type": "origin", "points_str": "45.494732, -122.817613" }, "geometry": { "type": "Point", "coordinates": [ -122.817613397087868, 45.494732253499819 ] } },
{ "type": "Feature", "properties": { "point_type": "destination", "points_str": "45.505352, -122.750818" }, "geometry": { "type": "Point", "coordinates": [ -122.750818044100171, 45.505351982446925 ] } }
]
}
