{
"type": "FeatureCollection",
"name": "origin_destination_points",
"crs": { "type": "name", "properties": { "name": "urn:ogc:def:crs:OGC:1.3:CRS84" } },
"features": [
{ "type": "Feature", "properties": { "point_type": "origin", "points_str": "45.357423, -122.359045" }, "geometry": { "type": "Point", "coordinates": [ -122.359044529394325, 45.357422792602662 ] } },
{ "type": "Feature", "properties": { "point_type": "destination", "points_str": "45.358566, -122.599331" }, "geometry": { "type": "Point", "coordinates": [ -122.5993308996743, 45.358565715608954 ] } }
]
}
