{
"type": "FeatureCollection",
"name": "origin_destination_points",
"crs": { "type": "name", "properties": { "name": "urn:ogc:def:crs:OGC:1.3:CRS84" } },
"features": [
{ "type": "Feature", "properties": { "point_type": "origin", "points_str": "45.522197, -122.598356" }, "geometry": { "type": "Point", "coordinates": [ -122.598355514118595, 45.522197405853994 ] } },
{ "type": "Feature", "properties": { "point_type": "destination", "points_str": "45.519414, -122.622852" }, "geometry": { "type": "Point", "coordinates": [ -122.622851853631033, 45.519413707631124 ] } }
]
}
