{
"type": "FeatureCollection",
"name": "origin_destination_points",
"crs": { "type": "name", "properties": { "name": "urn:ogc:def:crs:OGC:1.3:CRS84" } },
"features": [
{ "type": "Feature", "properties": { "point_type": "origin", "points_str": "45.364406, -122.845356" }, "geometry": { "type": "Point", "coordinates": [ -122.845356203640478, 45.364406238631787 ] } },
{ "type": "Feature", "properties": { "point_type": "destination", "points_str": "45.539349, -122.61279" }, "geometry": { "type": "Point", "coordinates": [ -122.612790176546028, 45.539349306651779 ] } }
]
}
