{
"type": "FeatureCollection",
"crs": { "type": "name", "properties": { "name": "urn:ogc:def:crs:OGC:1.3:CRS84" } },
"features": [
{ "type": "Feature", "properties": { "point_type": "origin", "points_str": "45.49349, -122.583411" }, "geometry": { "type": "Point", "coordinates": [ -122.583411080714143, 45.493490054192741 ] } },
{ "type": "Feature", "properties": { "point_type": "destination", "points_str": "45.428131, -122.596053" }, "geometry": { "type": "Point", "coordinates": [ -122.596053326230503, 45.428130650444501 ] } }
]
}
