{
"type": "FeatureCollection",
"name": "origin_destination_points",
"crs": { "type": "name", "properties": { "name": "urn:ogc:def:crs:OGC:1.3:CRS84" } },
"features": [
{ "type": "Feature", "properties": { "point_type": "origin", "points_str": "45.534869, -122.525855" }, "geometry": { "type": "Point", "coordinates": [ -122.525854623057839, 45.534868531504088 ] } },
{ "type": "Feature", "properties": { "point_type": "destination", "points_str": "45.494003, -122.803885" }, "geometry": { "type": "Point", "coordinates": [ -122.803884858395051, 45.494002711542052 ] } }
]
}
