{
"type": "FeatureCollection",
"crs": { "type": "name", "properties": { "name": "urn:ogc:def:crs:OGC:1.3:CRS84" } },
"features": [
{ "type": "Feature", "properties": { "point_type": "origin", "points_str": "45.567824, -122.689191" }, "geometry": { "type": "Point", "coordinates": [ -122.689191253032249, 45.567823678371148 ] } },
{ "type": "Feature", "properties": { "point_type": "destination", "points_str": "45.505694, -122.490823" }, "geometry": { "type": "Point", "coordinates": [ -122.490822532813226, 45.505693822092418 ] } }
]
}
