{
"type": "FeatureCollection",
"name": "origin_destination_points",
"crs": { "type": "name", "properties": { "name": "urn:ogc:def:crs:OGC:1.3:CRS84" } },
"features": [
{ "type": "Feature", "properties": { "point_type": "origin", "points_str": "45.541823, -122.482646" }, "geometry": { "type": "Point", "coordinates": [ -122.482646279362129, 45.541823203243787 ] } },
{ "type": "Feature", "properties": { "point_type": "destination", "points_str": "45.529851, -122.402537" }, "geometry": { "type": "Point", "coordinates": [ -122.402536559900156, 45.529851188713465 ] } }
]
}
