{
"type": "FeatureCollection",
"name": "origin_destination_points",
"crs": { "type": "name", "properties": { "name": "urn:ogc:def:crs:OGC:1.3:CRS84" } },
"features": [
{ "type": "Feature", "properties": { "point_type": "origin", "points_str": "45.438686, -122.732101" }, "geometry": { "type": "Point", "coordinates": [ -122.732100519239395, 45.438686219381623 ] } },
{ "type": "Feature", "properties": { "point_type": "destination", "points_str": "45.487718, -122.818739" }, "geometry": { "type": "Point", "coordinates": [ -122.818738735476572, 45.487718251982379 ] } }
]
}
