{
"type": "FeatureCollection",
"name": "origin_destination_points",
"crs": { "type": "name", "properties": { "name": "urn:ogc:def:crs:OGC:1.3:CRS84" } },
"features": [
{ "type": "Feature", "properties": { "point_type": "origin", "points_str": "45.523459, -123.08695" }, "geometry": { "type": "Point", "coordinates": [ -123.086950469996751, 45.523458970856062 ] } },
{ "type": "Feature", "properties": { "point_type": "destination", "points_str": "45.486454, -122.869965" }, "geometry": { "type": "Point", "coordinates": [ -122.869964633744502, 45.486453960438681 ] } }
]
}
