{
"type": "FeatureCollection",
"name": "origin_destination_points",
"crs": { "type": "name", "properties": { "name": "urn:ogc:def:crs:OGC:1.3:CRS84" } },
"features": [
{ "type": "Feature", "properties": { "point_type": "origin", "points_str": "45.515943, -123.058863" }, "geometry": { "type": "Point", "coordinates": [ -123.058863216578402, 45.515943166573344 ] } },
{ "type": "Feature", "properties": { "point_type": "destination", "points_str": "45.500883, -122.832496" }, "geometry": { "type": "Point", "coordinates": [ -122.832495695843008, 45.500883496633776 ] } }
]
}
