{
"type": "FeatureCollection",
"crs": { "type": "name", "properties": { "name": "urn:ogc:def:crs:OGC:1.3:CRS84" } },
"features": [
{ "type": "Feature", "properties": { "point_type": "origin", "points_str": "45.39723, -122.605679" }, "geometry": { "type": "Point", "coordinates": [ -122.605679155004353, 45.397229992828777 ] } },
{ "type": "Feature", "properties": { "point_type": "destination", "points_str": "45.50819, -122.622376" }, "geometry": { "type": "Point", "coordinates": [ -122.622376376433849, 45.50818999872854 ] } }
]
}
