{
"type": "FeatureCollection",
"name": "origin_destination_points",
"crs": { "type": "name", "properties": { "name": "urn:ogc:def:crs:OGC:1.3:CRS84" } },
"features": [
{ "type": "Feature", "properties": { "point_type": "origin", "points_str": "45.597427, -122.742793" }, "geometry": { "type": "Point", "coordinates": [ -122.742792730921238, 45.597427160432545 ] } },
{ "type": "Feature", "properties": { "point_type": "destination", "points_str": "45.488714, -122.52274" }, "geometry": { "type": "Point", "coordinates": [ -122.522740088715324, 45.488714410197424 ] } }
]
}
