{
"type": "FeatureCollection",
"crs": { "type": "name", "properties": { "name": "urn:ogc:def:crs:OGC:1.3:CRS84" } },
"features": [
{ "type": "Feature", "properties": { "point_type": "origin", "points_str": "45.560041, -122.635776" }, "geometry": { "type": "Point", "coordinates": [ -122.63577604882164, 45.560041258406748 ] } },
{ "type": "Feature", "properties": { "point_type": "destination", "points_str": "45.434572, -122.581804" }, "geometry": { "type": "Point", "coordinates": [ -122.581804255620895, 45.434572031249658 ] } }
]
}
