{
"type": "FeatureCollection",
"crs": { "type": "name", "properties": { "name": "urn:ogc:def:crs:OGC:1.3:CRS84" } },
"features": [
{ "type": "Feature", "properties": { "point_type": "origin", "points_str": "45.515056, -122.49101" }, "geometry": { "type": "Point", "coordinates": [ -122.491010255706527, 45.515056028034962 ] } },
{ "type": "Feature", "properties": { "point_type": "destination", "points_str": "45.424633, -122.556881" }, "geometry": { "type": "Point", "coordinates": [ -122.556880936286504, 45.424632868482639 ] } }
]
}
