{
"type": "FeatureCollection",
"name": "origin_destination_points",
"crs": { "type": "name", "properties": { "name": "urn:ogc:def:crs:OGC:1.3:CRS84" } },
"features": [
{ "type": "Feature", "properties": { "point_type": "origin", "points_str": "45.518548, -122.448965" }, "geometry": { "type": "Point", "coordinates": [ -122.448964811351502, 45.518547514309617 ] } },
{ "type": "Feature", "properties": { "point_type": "destination", "points_str": "45.464859, -122.582768" }, "geometry": { "type": "Point", "coordinates": [ -122.582767649793595, 45.464859281690458 ] } }
]
}
