{
"type": "FeatureCollection",
"crs": { "type": "name", "properties": { "name": "urn:ogc:def:crs:OGC:1.3:CRS84" } },
"features": [
{ "type": "Feature", "properties": { "point_type": "origin", "points_str": "45.503947, -122.864307" }, "geometry": { "type": "Point", "coordinates": [ -122.864306581818482, 45.50394655948314 ] } },
{ "type": "Feature", "properties": { "point_type": "destination", "points_str": "45.543775, -122.865525" }, "geometry": { "type": "Point", "coordinates": [ -122.865524687425193, 45.54377464145562 ] } }
]
}
