{
"type": "FeatureCollection",
"name": "origin_destination_points",
"crs": { "type": "name", "properties": { "name": "urn:ogc:def:crs:OGC:1.3:CRS84" } },
"features": [
{ "type": "Feature", "properties": { "point_type": "origin", "points_str": "45.445674, -122.741955" }, "geometry": { "type": "Point", "coordinates": [ -122.741954751081266, 45.445674480330638 ] } },
{ "type": "Feature", "properties": { "point_type": "destination", "points_str": "45.579471, -122.756631" }, "geometry": { "type": "Point", "coordinates": [ -122.756631058464279, 45.579471188725748 ] } }
]
}
