{
"type": "FeatureCollection",
"crs": { "type": "name", "properties": { "name": "urn:ogc:def:crs:OGC:1.3:CRS84" } },
"features": [
{ "type": "Feature", "properties": { "point_type": "origin", "points_str": "45.367759, -122.775516" }, "geometry": { "type": "Point", "coordinates": [ -122.77551633249341, 45.367758719505055 ] } },
{ "type": "Feature", "properties": { "point_type": "destination", "points_str": "45.49919, -122.492903" }, "geometry": { "type": "Point", "coordinates": [ -122.492903281402334, 45.49918981594012 ] } }
]
}
