{
"type": "FeatureCollection",
"crs": { "type": "name", "properties": { "name": "urn:ogc:def:crs:OGC:1.3:CRS84" } },
"features": [
{ "type": "Feature", "properties": { "point_type": "origin", "points_str": "45.473318, -122.567556" }, "geometry": { "type": "Point", "coordinates": [ -122.567556055324445, 45.473317960826883 ] } },
{ "type": "Feature", "properties": { "point_type": "destination", "points_str": "45.508669, -122.471945" }, "geometry": { "type": "Point", "coordinates": [ -122.47194461176889, 45.50866902405955 ] } }
]
}
