{
"type": "FeatureCollection",
"crs": { "type": "name", "properties": { "name": "urn:ogc:def:crs:OGC:1.3:CRS84" } },
"features": [
{ "type": "Feature", "properties": { "point_type": "origin", "points_str": "45.406278, -122.587468" }, "geometry": { "type": "Point", "coordinates": [ -122.587467673594531, 45.406278293019092 ] } },
{ "type": "Feature", "properties": { "point_type": "destination", "points_str": "45.567163, -122.627489" }, "geometry": { "type": "Point", "coordinates": [ -122.627489020286035, 45.567162946784613 ] } }
]
}
