{
"type": "FeatureCollection",
"name": "origin_destination_points",
"crs": { "type": "name", "properties": { "name": "urn:ogc:def:crs:OGC:1.3:CRS84" } },
"features": [
{ "type": "Feature", "properties": { "point_type": "origin", "points_str": "45.466781, -122.852403" }, "geometry": { "type": "Point", "coordinates": [ -122.852402803724303, 45.466781130969061 ] } },
{ "type": "Feature", "properties": { "point_type": "destination", "points_str": "45.499478, -122.428917" }, "geometry": { "type": "Point", "coordinates": [ -122.428916775251807, 45.49947756675914 ] } }
]
}
