{
"type": "FeatureCollection",
"name": "origin_destination_points",
"crs": { "type": "name", "properties": { "name": "urn:ogc:def:crs:OGC:1.3:CRS84" } },
"features": [
{ "type": "Feature", "properties": { "point_type": "origin", "points_str": "45.532466, -122.619818" }, "geometry": { "type": "Point", "coordinates": [ -122.619818252214429, 45.532466019589954 ] } },
{ "type": "Feature", "properties": { "point_type": "destination", "points_str": "45.476248, -122.823036" }, "geometry": { "type": "Point", "coordinates": [ -122.823036008680717, 45.476247572522993 ] } }
]
}
