{
"type": "FeatureCollection",
"crs": { "type": "name", "properties": { "name": "urn:ogc:def:crs:OGC:1.3:CRS84" } },
"features": [
{ "type": "Feature", "properties": { "point_type": "origin", "points_str": "45.342696, -122.597072" }, "geometry": { "type": "Point", "coordinates": [ -122.597071722875526, 45.342696429663341 ] } },
{ "type": "Feature", "properties": { "point_type": "destination", "points_str": "45.585621, -122.731368" }, "geometry": { "type": "Point", "coordinates": [ -122.731368079552638, 45.585621133482064 ] } }
]
}
