{
"type": "FeatureCollection",
"crs": { "type": "name", "properties": { "name": "urn:ogc:def:crs:OGC:1.3:CRS84" } },
"features": [
{ "type": "Feature", "properties": { "point_type": "origin", "points_str": "45.500154, -122.404037" }, "geometry": { "type": "Point", "coordinates": [ -122.40403721759192, 45.500153967808245 ] } },
{ "type": "Feature", "properties": { "point_type": "destination", "points_str": "45.509873, -122.625477" }, "geometry": { "type": "Point", "coordinates": [ -122.625477429004576, 45.509873075625414 ] } }
]
}
