{
"type": "FeatureCollection",
"name": "origin_destination_points",
"crs": { "type": "name", "properties": { "name": "urn:ogc:def:crs:OGC:1.3:CRS84" } },
"features": [
{ "type": "Feature", "properties": { "point_type": "origin", "points_str": "45.441413, -122.741111" }, "geometry": { "type": "Point", "coordinates": [ -122.741110773846088, 45.44141282578952 ] } },
{ "type": "Feature", "properties": { "point_type": "destination", "points_str": "45.526321, -122.618355" }, "geometry": { "type": "Point", "coordinates": [ -122.618354693444772, 45.526321074895868 ] } }
]
}
