{
"type": "FeatureCollection",
"name": "origin_destination_points",
"crs": { "type": "name", "properties": { "name": "urn:ogc:def:crs:OGC:1.3:CRS84" } },
"features": [
{ "type": "Feature", "properties": { "point_type": "origin", "points_str": "45.499344, -122.423242" }, "geometry": { "type": "Point", "coordinates": [ -122.42324188013994, 45.499343813768768 ] } },
{ "type": "Feature", "properties": { "point_type": "destination", "points_str": "45.504553, -122.576657" }, "geometry": { "type": "Point", "coordinates": [ -122.576656845218636, 45.504553451253692 ] } }
]
}
