{
"type": "FeatureCollection",
"name": "origin_destination_points",
"crs": { "type": "name", "properties": { "name": "urn:ogc:def:crs:OGC:1.3:CRS84" } },
"features": [
{ "type": "Feature", "properties": { "point_type": "origin", "points_str": "45.523122, -122.710786" }, "geometry": { "type": "Point", "coordinates": [ -122.710785755007322, 45.523122092348117 ] } },
{ "type": "Feature", "properties": { "point_type": "destination", "points_str": "45.574688, -122.718979" }, "geometry": { "type": "Point", "coordinates": [ -122.718978956926449, 45.574688198829207 ] } }
]
}
