{
"type": "FeatureCollection",
"crs": { "type": "name", "properties": { "name": "urn:ogc:def:crs:OGC:1.3:CRS84" } },
"features": [
{ "type": "Feature", "properties": { "point_type": "origin", "points_str": "45.522235, -123.080938" }, "geometry": { "type": "Point", "coordinates": [ -123.080937941628804, 45.522235303188168 ] } },
{ "type": "Feature", "properties": { "point_type": "destination", "points_str": "45.498428, -122.818591" }, "geometry": { "type": "Point", "coordinates": [ -122.818591182195831, 45.498427524571902 ] } }
]
}
