{
"type": "FeatureCollection",
"name": "origin_destination_points",
"crs": { "type": "name", "properties": { "name": "urn:ogc:def:crs:OGC:1.3:CRS84" } },
"features": [
{ "type": "Feature", "properties": { "point_type": "origin", "points_str": "45.509326, -122.673892" }, "geometry": { "type": "Point", "coordinates": [ -122.673892404761375, 45.509326172332202 ] } },
{ "type": "Feature", "properties": { "point_type": "destination", "points_str": "45.488699, -122.80095" }, "geometry": { "type": "Point", "coordinates": [ -122.800949941132671, 45.488699032253649 ] } }
]
}
