{
"type": "FeatureCollection",
"crs": { "type": "name", "properties": { "name": "urn:ogc:def:crs:OGC:1.3:CRS84" } },
"features": [
{ "type": "Feature", "properties": { "point_type": "origin", "points_str": "45.487053, -122.793998" }, "geometry": { "type": "Point", "coordinates": [ -122.793997537195679, 45.487052876857135 ] } },
{ "type": "Feature", "properties": { "point_type": "destination", "points_str": "45.483874, -122.590811" }, "geometry": { "type": "Point", "coordinates": [ -122.590811062658659, 45.483873667908505 ] } }
]
}
