{
"type": "FeatureCollection",
"crs": { "type": "name", "properties": { "name": "urn:ogc:def:crs:OGC:1.3:CRS84" } },
"features": [
{ "type": "Feature", "properties": { "point_type": "origin", "points_str": "45.5199, -122.997857" }, "geometry": { "type": "Point", "coordinates": [ -122.997856951774423, 45.519899612199161 ] } },
{ "type": "Feature", "properties": { "point_type": "destination", "points_str": "45.533978, -122.578831" }, "geometry": { "type": "Point", "coordinates": [ -122.578830923231834, 45.533977579331747 ] } }
]
}
