{
"type": "FeatureCollection",
"name": "origin_destination_points",
"crs": { "type": "name", "properties": { "name": "urn:ogc:def:crs:OGC:1.3:CRS84" } },
"features": [
{ "type": "Feature", "properties": { "point_type": "origin", "points_str": "45.535553, -122.662564" }, "geometry": { "type": "Point", "coordinates": [ -122.662564003988308, 45.53555302875462 ] } },
{ "type": "Feature", "properties": { "point_type": "destination", "points_str": "45.463494, -122.664467" }, "geometry": { "type": "Point", "coordinates": [ -122.664467405968907, 45.463494029587096 ] } }
]
}
