{
"type": "FeatureCollection",
"name": "origin_destination_points",
"crs": { "type": "name", "properties": { "name": "urn:ogc:def:crs:OGC:1.3:CRS84" } },
"features": [
{ "type": "Feature", "properties": { "point_type": "origin", "points_str": "45.445082, -122.735717" }, "geometry": { "type": "Point", "coordinates": [ -122.73571736747509, 45.445081876847055 ] } },
{ "type": "Feature", "properties": { "point_type": "destination", "points_str": "45.531032, -122.680713" }, "geometry": { "type": "Point", "coordinates": [ -122.680713384433304, 45.531032356611369 ] } }
]
}
