{
"type": "FeatureCollection",
"crs": { "type": "name", "properties": { "name": "urn:ogc:def:crs:OGC:1.3:CRS84" } },
"features": [
{ "type": "Feature", "properties": { "point_type": "origin", "points_str": "45.501164, -122.804368" }, "geometry": { "type": "Point", "coordinates": [ -122.804367901907611, 45.501163725849246 ] } },
{ "type": "Feature", "properties": { "point_type": "destination", "points_str": "45.464609, -122.796241" }, "geometry": { "type": "Point", "coordinates": [ -122.796240726677169, 45.464608786923968 ] } }
]
}
