{
"type": "FeatureCollection",
"crs": { "type": "name", "properties": { "name": "urn:ogc:def:crs:OGC:1.3:CRS84" } },
"features": [
{ "type": "Feature", "properties": { "point_type": "origin", "points_str": "45.571976, -122.685019" }, "geometry": { "type": "Point", "coordinates": [ -122.685019429183598, 45.571976493745048 ] } },
{ "type": "Feature", "properties": { "point_type": "destination", "points_str": "45.525326, -122.511274" }, "geometry": { "type": "Point", "coordinates": [ -122.511274119398848, 45.525326452457548 ] } }
]
}
