{
"type": "FeatureCollection",
"crs": { "type": "name", "properties": { "name": "urn:ogc:def:crs:OGC:1.3:CRS84" } },
"features": [
{ "type": "Feature", "properties": { "point_type": "origin", "points_str": "45.539248, -122.404958" }, "geometry": { "type": "Point", "coordinates": [ -122.404958026746101, 45.539247918615317 ] } },
{ "type": "Feature", "properties": { "point_type": "destination", "points_str": "45.559621, -122.500386" }, "geometry": { "type": "Point", "coordinates": [ -122.500385563616305, 45.559620787350418 ] } }
]
}
