{
"type": "FeatureCollection",
"name": "origin_destination_points",
"crs": { "type": "name", "properties": { "name": "urn:ogc:def:crs:OGC:1.3:CRS84" } },
"features": [
{ "type": "Feature", "properties": { "point_type": "origin", "points_str": "45.510342, -122.440448" }, "geometry": { "type": "Point", "coordinates": [ -122.440448189003504, 45.510341586199125 ] } },
{ "type": "Feature", "properties": { "point_type": "destination", "points_str": "45.559849, -122.565147" }, "geometry": { "type": "Point", "coordinates": [ -122.565147102925891, 45.559848537555546 ] } }
]
}
