{
"type": "FeatureCollection",
"name": "origin_destination_points",
"crs": { "type": "name", "properties": { "name": "urn:ogc:def:crs:OGC:1.3:CRS84" } },
"features": [
{ "type": "Feature", "properties": { "point_type": "origin", "points_str": "45.53721, -122.394668" }, "geometry": { "type": "Point", "coordinates": [ -122.394667953710567, 45.537210423574869 ] } },
{ "type": "Feature", "properties": { "point_type": "destination", "points_str": "45.514849, -122.576072" }, "geometry": { "type": "Point", "coordinates": [ -122.576072390041702, 45.514848598950593 ] } }
]
}
