{
"type": "FeatureCollection",
"name": "origin_destination_points",
"crs": { "type": "name", "properties": { "name": "urn:ogc:def:crs:OGC:1.3:CRS84" } },
"features": [
{ "type": "Feature", "properties": { "point_type": "origin", "points_str": "45.441264, -122.81739" }, "geometry": { "type": "Point", "coordinates": [ -122.817389682520044, 45.441263640139574 ] } },
{ "type": "Feature", "properties": { "point_type": "destination", "points_str": "45.488484, -122.82026" }, "geometry": { "type": "Point", "coordinates": [ -122.820259502087978, 45.488484391057064 ] } }
]
}
