{
"type": "FeatureCollection",
"crs": { "type": "name", "properties": { "name": "urn:ogc:def:crs:OGC:1.3:CRS84" } },
"features": [
{ "type": "Feature", "properties": { "point_type": "origin", "points_str": "45.529718, -122.848795" }, "geometry": { "type": "Point", "coordinates": [ -122.848794892646907, 45.529718389154809 ] } },
{ "type": "Feature", "properties": { "point_type": "destination", "points_str": "45.511647, -122.836385" }, "geometry": { "type": "Point", "coordinates": [ -122.836385089264027, 45.511647268307655 ] } }
]
}
