{
"type": "FeatureCollection",
"name": "origin_destination_points",
"crs": { "type": "name", "properties": { "name": "urn:ogc:def:crs:OGC:1.3:CRS84" } },
"features": [
{ "type": "Feature", "properties": { "point_type": "origin", "points_str": "45.476131, -122.791794" }, "geometry": { "type": "Point", "coordinates": [ -122.791793744618928, 45.476131039631674 ] } },
{ "type": "Feature", "properties": { "point_type": "destination", "points_str": "45.500077, -122.931051" }, "geometry": { "type": "Point", "coordinates": [ -122.931050935177282, 45.500077020624509 ] } }
]
}
