{
"type": "FeatureCollection",
"name": "origin_destination_points",
"crs": { "type": "name", "properties": { "name": "urn:ogc:def:crs:OGC:1.3:CRS84" } },
"features": [
{ "type": "Feature", "properties": { "point_type": "origin", "points_str": "45.594489, -122.715512" }, "geometry": { "type": "Point", "coordinates": [ -122.71551242674667, 45.594489202319735 ] } },
{ "type": "Feature", "properties": { "point_type": "destination", "points_str": "45.577536, -122.714569" }, "geometry": { "type": "Point", "coordinates": [ -122.714568572981776, 45.577536020902954 ] } }
]
}
