{
"type": "FeatureCollection",
"crs": { "type": "name", "properties": { "name": "urn:ogc:def:crs:OGC:1.3:CRS84" } },
"features": [
{ "type": "Feature", "properties": { "point_type": "origin", "points_str": "45.495589, -122.536896" }, "geometry": { "type": "Point", "coordinates": [ -122.536895866316627, 45.495589123424573 ] } },
{ "type": "Feature", "properties": { "point_type": "destination", "points_str": "45.438645, -122.569767" }, "geometry": { "type": "Point", "coordinates": [ -122.569766619454441, 45.438644767666105 ] } }
]
}
