{
"type": "FeatureCollection",
"name": "origin_destination_points",
"crs": { "type": "name", "properties": { "name": "urn:ogc:def:crs:OGC:1.3:CRS84" } },
"features": [
{ "type": "Feature", "properties": { "point_type": "origin", "points_str": "45.502146, -122.550653" }, "geometry": { "type": "Point", "coordinates": [ -122.550653196949966, 45.502146139507033 ] } },
{ "type": "Feature", "properties": { "point_type": "destination", "points_str": "45.561725, -122.720317" }, "geometry": { "type": "Point", "coordinates": [ -122.720317368689834, 45.561724698185095 ] } }
]
}
