{
"type": "FeatureCollection",
"name": "origin_destination_points",
"crs": { "type": "name", "properties": { "name": "urn:ogc:def:crs:OGC:1.3:CRS84" } },
"features": [
{ "type": "Feature", "properties": { "point_type": "origin", "points_str": "45.526786, -122.61489" }, "geometry": { "type": "Point", "coordinates": [ -122.61488987765847, 45.526786264833348 ] } },
{ "type": "Feature", "properties": { "point_type": "destination", "points_str": "45.483998, -122.705862" }, "geometry": { "type": "Point", "coordinates": [ -122.705861925267797, 45.483998449406066 ] } }
]
}
