{
"type": "FeatureCollection",
"name": "origin_destination_points",
"crs": { "type": "name", "properties": { "name": "urn:ogc:def:crs:OGC:1.3:CRS84" } },
"features": [
{ "type": "Feature", "properties": { "point_type": "origin", "points_str": "45.442545, -122.752529" }, "geometry": { "type": "Point", "coordinates": [ -122.752528811524826, 45.442544511031095 ] } },
{ "type": "Feature", "properties": { "point_type": "destination", "points_str": "45.542385, -122.675201" }, "geometry": { "type": "Point", "coordinates": [ -122.675201146773375, 45.542385406605092 ] } }
]
}
