{
"type": "FeatureCollection",
"name": "origin_destination_points",
"crs": { "type": "name", "properties": { "name": "urn:ogc:def:crs:OGC:1.3:CRS84" } },
"features": [
{ "type": "Feature", "properties": { "point_type": "origin", "points_str": "45.396429, -122.501277" }, "geometry": { "type": "Point", "coordinates": [ -122.501277358065323, 45.396429022253187 ] } },
{ "type": "Feature", "properties": { "point_type": "destination", "points_str": "45.36032, -122.370488" }, "geometry": { "type": "Point", "coordinates": [ -122.370487785652443, 45.360319958228956 ] } }
]
}
