{
"type": "FeatureCollection",
"crs": { "type": "name", "properties": { "name": "urn:ogc:def:crs:OGC:1.3:CRS84" } },
"features": [
{ "type": "Feature", "properties": { "point_type": "origin", "points_str": "45.453526, -122.680009" }, "geometry": { "type": "Point", "coordinates": [ -122.680008834091083, 45.453525582527249 ] } },
{ "type": "Feature", "properties": { "point_type": "destination", "points_str": "45.556273, -122.652665" }, "geometry": { "type": "Point", "coordinates": [ -122.652665077405572, 45.556272587463589 ] } }
]
}
