{
"type": "FeatureCollection",
"name": "origin_destination_points",
"crs": { "type": "name", "properties": { "name": "urn:ogc:def:crs:OGC:1.3:CRS84" } },
"features": [
{ "type": "Feature", "properties": { "point_type": "origin", "points_str": "45.520365, -122.685802" }, "geometry": { "type": "Point", "coordinates": [ -122.685802059707228, 45.520365126257161 ] } },
{ "type": "Feature", "properties": { "point_type": "destination", "points_str": "45.534538, -122.679888" }, "geometry": { "type": "Point", "coordinates": [ -122.679887978780883, 45.534538135714854 ] } }
]
}
