{
"type": "FeatureCollection",
"name": "origin_destination_points",
"crs": { "type": "name", "properties": { "name": "urn:ogc:def:crs:OGC:1.3:CRS84" } },
"features": [
{ "type": "Feature", "properties": { "point_type": "origin", "points_str": "45.504281, -122.43481" }, "geometry": { "type": "Point", "coordinates": [ -122.434809866223375, 45.504280794122813 ] } },
{ "type": "Feature", "properties": { "point_type": "destination", "points_str": "45.519532, -122.611958" }, "geometry": { "type": "Point", "coordinates": [ -122.611957788494479, 45.519531668614214 ] } }
]
}
