{
"type": "FeatureCollection",
"crs": { "type": "name", "properties": { "name": "urn:ogc:def:crs:OGC:1.3:CRS84" } },
"features": [
{ "type": "Feature", "properties": { "point_type": "origin", "points_str": "45.531086, -122.667559" }, "geometry": { "type": "Point", "coordinates": [ -122.667558780214407, 45.531085842673825 ] } },
{ "type": "Feature", "properties": { "point_type": "destination", "points_str": "45.487589, -122.635817" }, "geometry": { "type": "Point", "coordinates": [ -122.635817391770189, 45.487589238291314 ] } }
]
}
