{
"type": "FeatureCollection",
"crs": { "type": "name", "properties": { "name": "urn:ogc:def:crs:OGC:1.3:CRS84" } },
"features": [
{ "type": "Feature", "properties": { "point_type": "origin", "points_str": "45.454366, -122.697616" }, "geometry": { "type": "Point", "coordinates": [ -122.697615691310105, 45.454365909048022 ] } },
{ "type": "Feature", "properties": { "point_type": "destination", "points_str": "45.526957, -122.790462" }, "geometry": { "type": "Point", "coordinates": [ -122.79046224246548, 45.526956922292783 ] } }
]
}
