{
"type": "FeatureCollection",
"name": "origin_destination_points",
"crs": { "type": "name", "properties": { "name": "urn:ogc:def:crs:OGC:1.3:CRS84" } },
"features": [
{ "type": "Feature", "properties": { "point_type": "origin", "points_str": "45.423756, -122.556762" }, "geometry": { "type": "Point", "coordinates": [ -122.556761685105172, 45.423755510068034 ] } },
{ "type": "Feature", "properties": { "point_type": "destination", "points_str": "45.373426, -122.601154" }, "geometry": { "type": "Point", "coordinates": [ -122.601153589654928, 45.373426034516292 ] } }
]
}
