{
"type": "FeatureCollection",
"name": "origin_destination_points",
"crs": { "type": "name", "properties": { "name": "urn:ogc:def:crs:OGC:1.3:CRS84" } },
"features": [
{ "type": "Feature", "properties": { "point_type": "origin", "points_str": "45.421845, -122.701355" }, "geometry": { "type": "Point", "coordinates": [ -122.701354956837264, 45.421845003036388 ] } },
{ "type": "Feature", "properties": { "point_type": "destination", "points_str": "45.420791, -122.78192" }, "geometry": { "type": "Point", "coordinates": [ -122.781920495802169, 45.420790749229745 ] } }
]
}
