{
"type": "FeatureCollection",
"crs": { "type": "name", "properties": { "name": "urn:ogc:def:crs:OGC:1.3:CRS84" } },
"features": [
{ "type": "Feature", "properties": { "point_type": "origin", "points_str": "45.48474, -122.836024" }, "geometry": { "type": "Point", "coordinates": [ -122.836024274631583, 45.484739586398291 ] } },
{ "type": "Feature", "properties": { "point_type": "destination", "points_str": "45.492583, -122.802679" }, "geometry": { "type": "Point", "coordinates": [ -122.80267850745544, 45.492583417862967 ] } }
]
}
