{
"type": "FeatureCollection",
"name": "origin_destination_points",
"crs": { "type": "name", "properties": { "name": "urn:ogc:def:crs:OGC:1.3:CRS84" } },
"features": [
{ "type": "Feature", "properties": { "point_type": "origin", "points_str": "45.560183, -122.576254" }, "geometry": { "type": "Point", "coordinates": [ -122.576254327468646, 45.56018315004922 ] } },
{ "type": "Feature", "properties": { "point_type": "destination", "points_str": "45.497465, -122.52175" }, "geometry": { "type": "Point", "coordinates": [ -122.521749577630715, 45.49746502854029 ] } }
]
}
