{
"type": "FeatureCollection",
"crs": { "type": "name", "properties": { "name": "urn:ogc:def:crs:OGC:1.3:CRS84" } },
"features": [
{ "type": "Feature", "properties": { "point_type": "origin", "points_str": "45.533314, -122.600072" }, "geometry": { "type": "Point", "coordinates": [ -122.600072150592311, 45.533314318869749 ] } },
{ "type": "Feature", "properties": { "point_type": "destination", "points_str": "45.488924, -122.630904" }, "geometry": { "type": "Point", "coordinates": [ -122.630903746529199, 45.488923800398169 ] } }
]
}
