{
"type": "FeatureCollection",
"name": "origin_destination_points",
"crs": { "type": "name", "properties": { "name": "urn:ogc:def:crs:OGC:1.3:CRS84" } },
"features": [
{ "type": "Feature", "properties": { "point_type": "origin", "points_str": "45.517736, -122.546327" }, "geometry": { "type": "Point", "coordinates": [ -122.546326994870114, 45.517735912333869 ] } },
{ "type": "Feature", "properties": { "point_type": "destination", "points_str": "45.555336, -122.561234" }, "geometry": { "type": "Point", "coordinates": [ -122.561234230631584, 45.555335526960533 ] } }
]
}
