{
"type": "FeatureCollection",
"crs": { "type": "name", "properties": { "name": "urn:ogc:def:crs:OGC:1.3:CRS84" } },
"features": [
{ "type": "Feature", "properties": { "point_type": "origin", "points_str": "45.449211, -122.62834" }, "geometry": { "type": "Point", "coordinates": [ -122.62834035729044, 45.449211161931693 ] } },
{ "type": "Feature", "properties": { "point_type": "destination", "points_str": "45.426304, -122.520233" }, "geometry": { "type": "Point", "coordinates": [ -122.52023314909691, 45.426303923371897 ] } }
]
}
