{
"type": "FeatureCollection",
"crs": { "type": "name", "properties": { "name": "urn:ogc:def:crs:OGC:1.3:CRS84" } },
"features": [
{ "type": "Feature", "properties": { "point_type": "origin", "points_str": "45.510381, -122.701071" }, "geometry": { "type": "Point", "coordinates": [ -122.701070658986737, 45.510381364941324 ] } },
{ "type": "Feature", "properties": { "point_type": "destination", "points_str": "45.489301, -122.710794" }, "geometry": { "type": "Point", "coordinates": [ -122.710793711068959, 45.489300699449707 ] } }
]
}
