{
"type": "FeatureCollection",
"name": "origin_destination_points",
"crs": { "type": "name", "properties": { "name": "urn:ogc:def:crs:OGC:1.3:CRS84" } },
"features": [
{ "type": "Feature", "properties": { "point_type": "origin", "points_str": "45.375619, -122.602416" }, "geometry": { "type": "Point", "coordinates": [ -122.602415725323354, 45.375619139627695 ] } },
{ "type": "Feature", "properties": { "point_type": "destination", "points_str": "45.349306, -122.638975" }, "geometry": { "type": "Point", "coordinates": [ -122.638974939490993, 45.34930592154042 ] } }
]
}
