{
"type": "FeatureCollection",
"name": "origin_destination_points",
"crs": { "type": "name", "properties": { "name": "urn:ogc:def:crs:OGC:1.3:CRS84" } },
"features": [
{ "type": "Feature", "properties": { "point_type": "origin", "points_str": "45.497317, -122.93073" }, "geometry": { "type": "Point", "coordinates": [ -122.930730281692902, 45.497317346442578 ] } },
{ "type": "Feature", "properties": { "point_type": "destination", "points_str": "45.524597, -123.068547" }, "geometry": { "type": "Point", "coordinates": [ -123.068546535942858, 45.524597214490235 ] } }
]
}
