{
"type": "FeatureCollection",
"name": "origin_destination_points",
"crs": { "type": "name", "properties": { "name": "urn:ogc:def:crs:OGC:1.3:CRS84" } },
"features": [
{ "type": "Feature", "properties": { "point_type": "origin", "points_str": "45.477216, -122.702633" }, "geometry": { "type": "Point", "coordinates": [ -122.702633166892923, 45.477216429114115 ] } },
{ "type": "Feature", "properties": { "point_type": "destination", "points_str": "45.493701, -122.788948" }, "geometry": { "type": "Point", "coordinates": [ -122.78894821807576, 45.493700682196973 ] } }
]
}
