{
"type": "FeatureCollection",
"crs": { "type": "name", "properties": { "name": "urn:ogc:def:crs:OGC:1.3:CRS84" } },
"features": [
{ "type": "Feature", "properties": { "point_type": "origin", "points_str": "45.485786, -122.840714" }, "geometry": { "type": "Point", "coordinates": [ -122.840714074901371, 45.485785783819317 ] } },
{ "type": "Feature", "properties": { "point_type": "destination", "points_str": "45.383871, -122.756793" }, "geometry": { "type": "Point", "coordinates": [ -122.756793304116414, 45.383871021852997 ] } }
]
}
