{
"type": "FeatureCollection",
"name": "origin_destination_points",
"crs": { "type": "name", "properties": { "name": "urn:ogc:def:crs:OGC:1.3:CRS84" } },
"features": [
{ "type": "Feature", "properties": { "point_type": "origin", "points_str": "45.461846, -122.556406" }, "geometry": { "type": "Point", "coordinates": [ -122.556406099795453, 45.461845794153611 ] } },
{ "type": "Feature", "properties": { "point_type": "destination", "points_str": "45.435262, -122.693971" }, "geometry": { "type": "Point", "coordinates": [ -122.693970610321287, 45.435261538326046 ] } }
]
}
