{
"type": "FeatureCollection",
"name": "origin_destination_points",
"crs": { "type": "name", "properties": { "name": "urn:ogc:def:crs:OGC:1.3:CRS84" } },
"features": [
{ "type": "Feature", "properties": { "point_type": "origin", "points_str": "45.508997, -122.716735" }, "geometry": { "type": "Point", "coordinates": [ -122.716734862354514, 45.508997086261516 ] } },
{ "type": "Feature", "properties": { "point_type": "destination", "points_str": "45.403856, -122.663652" }, "geometry": { "type": "Point", "coordinates": [ -122.663651571563875, 45.403856355334845 ] } }
]
}
