{
"type": "FeatureCollection",
"name": "origin_destination_points",
"crs": { "type": "name", "properties": { "name": "urn:ogc:def:crs:OGC:1.3:CRS84" } },
"features": [
{ "type": "Feature", "properties": { "point_type": "origin", "points_str": "45.594674, -122.7201" }, "geometry": { "type": "Point", "coordinates": [ -122.720099982803902, 45.594674036533199 ] } },
{ "type": "Feature", "properties": { "point_type": "destination", "points_str": "45.444647, -122.655501" }, "geometry": { "type": "Point", "coordinates": [ -122.655501493444717, 45.444646877230909 ] } }
]
}
