{
"type": "FeatureCollection",
"crs": { "type": "name", "properties": { "name": "urn:ogc:def:crs:OGC:1.3:CRS84" } },
"features": [
{ "type": "Feature", "properties": { "point_type": "origin", "points_str": "45.538013, -122.941293" }, "geometry": { "type": "Point", "coordinates": [ -122.941292740466295, 45.538013313148006 ] } },
{ "type": "Feature", "properties": { "point_type": "destination", "points_str": "45.544914, -122.880507" }, "geometry": { "type": "Point", "coordinates": [ -122.880507051581304, 45.544913866162432 ] } }
]
}
