{
"type": "FeatureCollection",
"name": "origin_destination_points",
"crs": { "type": "name", "properties": { "name": "urn:ogc:def:crs:OGC:1.3:CRS84" } },
"features": [
{ "type": "Feature", "properties": { "point_type": "origin", "points_str": "45.532539, -122.668474" }, "geometry": { "type": "Point", "coordinates": [ -122.668474020301375, 45.532539096094375 ] } },
{ "type": "Feature", "properties": { "point_type": "destination", "points_str": "45.428472, -122.576619" }, "geometry": { "type": "Point", "coordinates": [ -122.576619487158695, 45.428471890251473 ] } }
]
}
