{
"type": "FeatureCollection",
"crs": { "type": "name", "properties": { "name": "urn:ogc:def:crs:OGC:1.3:CRS84" } },
"features": [
{ "type": "Feature", "properties": { "point_type": "origin", "points_str": "45.584534, -122.732897" }, "geometry": { "type": "Point", "coordinates": [ -122.732897261350629, 45.58453359593544 ] } },
{ "type": "Feature", "properties": { "point_type": "destination", "points_str": "45.58004, -122.694432" }, "geometry": { "type": "Point", "coordinates": [ -122.694431598364915, 45.580039762367456 ] } }
]
}
