{
"type": "FeatureCollection",
"name": "origin_destination_points",
"crs": { "type": "name", "properties": { "name": "urn:ogc:def:crs:OGC:1.3:CRS84" } },
"features": [
{ "type": "Feature", "properties": { "point_type": "origin", "points_str": "45.52037, -123.010709" }, "geometry": { "type": "Point", "coordinates": [ -123.010708563221584, 45.520370044246334 ] } },
{ "type": "Feature", "properties": { "point_type": "destination", "points_str": "45.550426, -122.867391" }, "geometry": { "type": "Point", "coordinates": [ -122.867390554701657, 45.550425675093443 ] } }
]
}
