{
"type": "FeatureCollection",
"crs": { "type": "name", "properties": { "name": "urn:ogc:def:crs:OGC:1.3:CRS84" } },
"features": [
{ "type": "Feature", "properties": { "point_type": "origin", "points_str": "45.545787, -122.494714" }, "geometry": { "type": "Point", "coordinates": [ -122.494714364322363, 45.545787286655376 ] } },
{ "type": "Feature", "properties": { "point_type": "destination", "points_str": "45.543759, -122.473952" }, "geometry": { "type": "Point", "coordinates": [ -122.473952168532449, 45.543758771393364 ] } }
]
}
