{
"type": "FeatureCollection",
"name": "origin_destination_points",
"crs": { "type": "name", "properties": { "name": "urn:ogc:def:crs:OGC:1.3:CRS84" } },
"features": [
{ "type": "Feature", "properties": { "point_type": "origin", "points_str": "45.435913, -122.734398" }, "geometry": { "type": "Point", "coordinates": [ -122.734397904797106, 45.435912784346144 ] } },
{ "type": "Feature", "properties": { "point_type": "destination", "points_str": "45.37886, -122.835186" }, "geometry": { "type": "Point", "coordinates": [ -122.835186281393916, 45.378859557733044 ] } }
]
}
