{
"type": "FeatureCollection",
"name": "origin_destination_points",
"crs": { "type": "name", "properties": { "name": "urn:ogc:def:crs:OGC:1.3:CRS84" } },
"features": [
{ "type": "Feature", "properties": { "point_type": "origin", "points_str": "45.49658, -122.609395" }, "geometry": { "type": "Point", "coordinates": [ -122.609395125010693, 45.496579789432467 ] } },
{ "type": "Feature", "properties": { "point_type": "destination", "points_str": "45.402896, -122.495818" }, "geometry": { "type": "Point", "coordinates": [ -122.495818249281839, 45.40289616872105 ] } }
]
}
