{
"type": "FeatureCollection",
"name": "origin_destination_points",
"crs": { "type": "name", "properties": { "name": "urn:ogc:def:crs:OGC:1.3:CRS84" } },
"features": [
{ "type": "Feature", "properties": { "point_type": "origin", "points_str": "45.421615, -122.592997" }, "geometry": { "type": "Point", "coordinates": [ -122.592996536145236, 45.421615069740227 ] } },
{ "type": "Feature", "properties": { "point_type": "destination", "points_str": "45.424664, -122.490428" }, "geometry": { "type": "Point", "coordinates": [ -122.490427542012895, 45.424664376144833 ] } }
]
}
