{
"type": "FeatureCollection",
"name": "origin_destination_points",
"crs": { "type": "name", "properties": { "name": "urn:ogc:def:crs:OGC:1.3:CRS84" } },
"features": [
{ "type": "Feature", "properties": { "point_type": "origin", "points_str": "45.510431, -122.779361" }, "geometry": { "type": "Point", "coordinates": [ -122.77936090412301, 45.510431223392537 ] } },
{ "type": "Feature", "properties": { "point_type": "destination", "points_str": "45.549427, -122.539164" }, "geometry": { "type": "Point", "coordinates": [ -122.539163561752787, 45.54942679266145 ] } }
]
}
