{
"type": "FeatureCollection",
"name": "origin_destination_points",
"crs": { "type": "name", "properties": { "name": "urn:ogc:def:crs:OGC:1.3:CRS84" } },
"features": [
{ "type": "Feature", "properties": { "point_type": "origin", "points_str": "45.506673, -122.476899" }, "geometry": { "type": "Point", "coordinates": [ -122.476898641035802, 45.506673157569494 ] } },
{ "type": "Feature", "properties": { "point_type": "destination", "points_str": "45.507729, -122.765026" }, "geometry": { "type": "Point", "coordinates": [ -122.765025968605812, 45.507728534177254 ] } }
]
}
