{
"type": "FeatureCollection",
"name": "origin_destination_points",
"crs": { "type": "name", "properties": { "name": "urn:ogc:def:crs:OGC:1.3:CRS84" } },
"features": [
{ "type": "Feature", "properties": { "point_type": "origin", "points_str": "45.478478, -122.867493" }, "geometry": { "type": "Point", "coordinates": [ -122.867492540449618, 45.478477977873666 ] } },
{ "type": "Feature", "properties": { "point_type": "destination", "points_str": "45.522184, -122.856155" }, "geometry": { "type": "Point", "coordinates": [ -122.85615483321709, 45.522183888540006 ] } }
]
}
