{
"type": "FeatureCollection",
"name": "origin_destination_points",
"crs": { "type": "name", "properties": { "name": "urn:ogc:def:crs:OGC:1.3:CRS84" } },
"features": [
{ "type": "Feature", "properties": { "point_type": "origin", "points_str": "45.525406, -122.601598" }, "geometry": { "type": "Point", "coordinates": [ -122.601597558276822, 45.525406157330863 ] } },
{ "type": "Feature", "properties": { "point_type": "destination", "points_str": "45.529693, -122.626826" }, "geometry": { "type": "Point", "coordinates": [ -122.626825809132413, 45.529692950314683 ] } }
]
}
