{
"type": "FeatureCollection",
"crs": { "type": "name", "properties": { "name": "urn:ogc:def:crs:OGC:1.3:CRS84" } },
"features": [
{ "type": "Feature", "properties": { "point_type": "origin", "points_str": "45.499147, -122.54199" }, "geometry": { "type": "Point", "coordinates": [ -122.541989945222298, 45.499147187729378 ] } },
{ "type": "Feature", "properties": { "point_type": "destination", "points_str": "45.526184, -122.694062" }, "geometry": { "type": "Point", "coordinates": [ -122.69406193837122, 45.526183551457102 ] } }
]
}
