{
"type": "FeatureCollection",
"crs": { "type": "name", "properties": { "name": "urn:ogc:def:crs:OGC:1.3:CRS84" } },
"features": [
{ "type": "Feature", "properties": { "point_type": "origin", "points_str": "45.518026, -122.517589" }, "geometry": { "type": "Point", "coordinates": [ -122.517589372944428, 45.518026142112681 ] } },
{ "type": "Feature", "properties": { "point_type": "destination", "points_str": "45.568726, -122.704199" }, "geometry": { "type": "Point", "coordinates": [ -122.704198920704556, 45.568725728680306 ] } }
]
}
