{
"type": "FeatureCollection",
"crs": { "type": "name", "properties": { "name": "urn:ogc:def:crs:OGC:1.3:CRS84" } },
"features": [
{ "type": "Feature", "properties": { "point_type": "origin", "points_str": "45.468106, -122.673562" }, "geometry": { "type": "Point", "coordinates": [ -122.673561869072756, 45.468106005264744 ] } },
{ "type": "Feature", "properties": { "point_type": "destination", "points_str": "45.536642, -122.701177" }, "geometry": { "type": "Point", "coordinates": [ -122.701177417989896, 45.536641795625883 ] } }
]
}
