{
"type": "FeatureCollection",
"name": "origin_destination_points",
"crs": { "type": "name", "properties": { "name": "urn:ogc:def:crs:OGC:1.3:CRS84" } },
"features": [
{ "type": "Feature", "properties": { "point_type": "origin", "points_str": "45.550984, -122.600041" }, "geometry": { "type": "Point", "coordinates": [ -122.600041420853984, 45.550984123583355 ] } },
{ "type": "Feature", "properties": { "point_type": "destination", "points_str": "45.554095, -122.544417" }, "geometry": { "type": "Point", "coordinates": [ -122.544417259860651, 45.554094981835327 ] } }
]
}
