{
"type": "FeatureCollection",
"crs": { "type": "name", "properties": { "name": "urn:ogc:def:crs:OGC:1.3:CRS84" } },
"features": [
{ "type": "Feature", "properties": { "point_type": "origin", "points_str": "45.40486, -122.800506" }, "geometry": { "type": "Point", "coordinates": [ -122.800506170240624, 45.404860477808931 ] } },
{ "type": "Feature", "properties": { "point_type": "destination", "points_str": "45.447256, -122.77943" }, "geometry": { "type": "Point", "coordinates": [ -122.779429714080933, 45.447256301010718 ] } }
]
}
