{
"type": "FeatureCollection",
"name": "origin_destination_points",
"crs": { "type": "name", "properties": { "name": "urn:ogc:def:crs:OGC:1.3:CRS84" } },
"features": [
{ "type": "Feature", "properties": { "point_type": "origin", "points_str": "45.554964, -122.525457" }, "geometry": { "type": "Point", "coordinates": [ -122.525456878524636, 45.554963994913301 ] } },
{ "type": "Feature", "properties": { "point_type": "destination", "points_str": "45.544279, -122.44961" }, "geometry": { "type": "Point", "coordinates": [ -122.449609739082234, 45.544278754459285 ] } }
]
}
