{
"type": "FeatureCollection",
"name": "origin_destination_points",
"crs": { "type": "name", "properties": { "name": "urn:ogc:def:crs:OGC:1.3:CRS84" } },
"features": [
{ "type": "Feature", "properties": { "point_type": "origin", "points_str": "45.509025, -122.776905" }, "geometry": { "type": "Point", "coordinates": [ -122.776905172614278, 45.509025430212418 ] } },
{ "type": "Feature", "properties": { "point_type": "destination", "points_str": "45.609361, -122.674071" }, "geometry": { "type": "Point", "coordinates": [ -122.674070606180251, 45.609361256051926 ] } }
]
}
