{
"type": "FeatureCollection",
"name": "origin_destination_points",
"crs": { "type": "name", "properties": { "name": "urn:ogc:def:crs:OGC:1.3:CRS84" } },
"features": [
{ "type": "Feature", "properties": { "point_type": "origin", "points_str": "45.521959, -123.091565" }, "geometry": { "type": "Point", "coordinates": [ -123.091565047334981, 45.521959337084205 ] } },
{ "type": "Feature", "properties": { "point_type": "destination", "points_str": "45.481945, -122.824573" }, "geometry": { "type": "Point", "coordinates": [ -122.824573267170265, 45.481945184654855 ] } }
]
}
