{
"type": "FeatureCollection",
"name": "origin_destination_points",
"crs": { "type": "name", "properties": { "name": "urn:ogc:def:crs:OGC:1.3:CRS84" } },
"features": [
{ "type": "Feature", "properties": { "point_type": "origin", "points_str": "45.519507, -122.868431" }, "geometry": { "type": "Point", "coordinates": [ -122.868430837377375, 45.519507020045779 ] } },
{ "type": "Feature", "properties": { "point_type": "destination", "points_str": "45.612572, -122.686033" }, "geometry": { "type": "Point", "coordinates": [ -122.686033445828002, 45.612572341989534 ] } }
]
}
