{
"type": "FeatureCollection",
"name": "origin_destination_points",
"crs": { "type": "name", "properties": { "name": "urn:ogc:def:crs:OGC:1.3:CRS84" } },
"features": [
{ "type": "Feature", "properties": { "point_type": "origin", "points_str": "45.534411, -122.639653" }, "geometry": { "type": "Point", "coordinates": [ -122.639653317977789, 45.534411027722292 ] } },
{ "type": "Feature", "properties": { "point_type": "destination", "points_str": "45.495328, -122.568285" }, "geometry": { "type": "Point", "coordinates": [ -122.568284702128096, 45.495327836405686 ] } }
]
}
