{
"type": "FeatureCollection",
"crs": { "type": "name", "properties": { "name": "urn:ogc:def:crs:OGC:1.3:CRS84" } },
"features": [
{ "type": "Feature", "properties": { "point_type": "origin", "points_str": "45.452221, -122.764931" }, "geometry": { "type": "Point", "coordinates": [ -122.76493064626797, 45.452220983887386 ] } },
{ "type": "Feature", "properties": { "point_type": "destination", "points_str": "45.469073, -122.657308" }, "geometry": { "type": "Point", "coordinates": [ -122.657307758596204, 45.469073422615097 ] } }
]
}
