{
"type": "FeatureCollection",
"name": "origin_destination_points",
"crs": { "type": "name", "properties": { "name": "urn:ogc:def:crs:OGC:1.3:CRS84" } },
"features": [
{ "type": "Feature", "properties": { "point_type": "origin", "points_str": "45.523416, -122.968313" }, "geometry": { "type": "Point", "coordinates": [ -122.968312706443072, 45.523416305777253 ] } },
{ "type": "Feature", "properties": { "point_type": "destination", "points_str": "45.494911, -122.864716" }, "geometry": { "type": "Point", "coordinates": [ -122.864716161787811, 45.494911363722288 ] } }
]
}
