{
"type": "FeatureCollection",
"name": "origin_destination_points",
"crs": { "type": "name", "properties": { "name": "urn:ogc:def:crs:OGC:1.3:CRS84" } },
"features": [
{ "type": "Feature", "properties": { "point_type": "origin", "points_str": "45.358187, -122.846858" }, "geometry": { "type": "Point", "coordinates": [ -122.846858483901997, 45.358187031122391 ] } },
{ "type": "Feature", "properties": { "point_type": "destination", "points_str": "45.379308, -122.759929" }, "geometry": { "type": "Point", "coordinates": [ -122.759929158815723, 45.379308491147142 ] } }
]
}
