{
"type": "FeatureCollection",
"name": "origin_destination_points",
"crs": { "type": "name", "properties": { "name": "urn:ogc:def:crs:OGC:1.3:CRS84" } },
"features": [
{ "type": "Feature", "properties": { "point_type": "origin", "points_str": "45.493379, -122.530006" }, "geometry": { "type": "Point", "coordinates": [ -122.530005606701096, 45.493378922870946 ] } },
{ "type": "Feature", "properties": { "point_type": "destination", "points_str": "45.560897, -122.591247" }, "geometry": { "type": "Point", "coordinates": [ -122.591247458379357, 45.560897402253858 ] } }
]
}
