{
"type": "FeatureCollection",
"name": "origin_destination_points",
"crs": { "type": "name", "properties": { "name": "urn:ogc:def:crs:OGC:1.3:CRS84" } },
"features": [
{ "type": "Feature", "properties": { "point_type": "origin", "points_str": "45.456315, -122.627477" }, "geometry": { "type": "Point", "coordinates": [ -122.62747725650901, 45.456314776611343 ] } },
{ "type": "Feature", "properties": { "point_type": "destination", "points_str": "45.381098, -122.604509" }, "geometry": { "type": "Point", "coordinates": [ -122.604508521787338, 45.381097806263483 ] } }
]
}
