{
"type": "FeatureCollection",
"name": "origin_destination_points",
"crs": { "type": "name", "properties": { "name": "urn:ogc:def:crs:OGC:1.3:CRS84" } },
"features": [
{ "type": "Feature", "properties": { "point_type": "origin", "points_str": "45.451921, -122.672484" }, "geometry": { "type": "Point", "coordinates": [ -122.672483813770199, 45.451920905836168 ] } },
{ "type": "Feature", "properties": { "point_type": "destination", "points_str": "45.53241, -122.460414" }, "geometry": { "type": "Point", "coordinates": [ -122.46041417502785, 45.532409596492826 ] } }
]
}
