{
"type": "FeatureCollection",
"name": "origin_destination_points",
"crs": { "type": "name", "properties": { "name": "urn:ogc:def:crs:OGC:1.3:CRS84" } },
"features": [
{ "type": "Feature", "properties": { "point_type": "origin", "points_str": "45.476477, -122.614591" }, "geometry": { "type": "Point", "coordinates": [ -122.614591225767441, 45.476476921096868 ] } },
{ "type": "Feature", "properties": { "point_type": "destination", "points_str": "45.521177, -122.463707" }, "geometry": { "type": "Point", "coordinates": [ -122.463707413876236, 45.52117732447374 ] } }
]
}
