{
"type": "FeatureCollection",
"crs": { "type": "name", "properties": { "name": "urn:ogc:def:crs:OGC:1.3:CRS84" } },
"features": [
{ "type": "Feature", "properties": { "point_type": "origin", "points_str": "45.357276, -122.356352" }, "geometry": { "type": "Point", "coordinates": [ -122.356351958584725, 45.357275525959821 ] } },
{ "type": "Feature", "properties": { "point_type": "destination", "points_str": "45.467649, -122.576185" }, "geometry": { "type": "Point", "coordinates": [ -122.576185019358007, 45.467648615612298 ] } }
]
}
