{
"type": "FeatureCollection",
"name": "origin_destination_points",
"crs": { "type": "name", "properties": { "name": "urn:ogc:def:crs:OGC:1.3:CRS84" } },
"features": [
{ "type": "Feature", "properties": { "point_type": "origin", "points_str": "45.522045, -122.473736" }, "geometry": { "type": "Point", "coordinates": [ -122.473736151081923, 45.522044902165632 ] } },
{ "type": "Feature", "properties": { "point_type": "destination", "points_str": "45.477758, -122.371657" }, "geometry": { "type": "Point", "coordinates": [ -122.371656855857012, 45.477758264738455 ] } }
]
}
