{
"type": "FeatureCollection",
"crs": { "type": "name", "properties": { "name": "urn:ogc:def:crs:OGC:1.3:CRS84" } },
"features": [
{ "type": "Feature", "properties": { "point_type": "origin", "points_str": "45.497763, -122.551074" }, "geometry": { "type": "Point", "coordinates": [ -122.551074220166825, 45.497763227885706 ] } },
{ "type": "Feature", "properties": { "point_type": "destination", "points_str": "45.557409, -122.620701" }, "geometry": { "type": "Point", "coordinates": [ -122.620700666252233, 45.557409463011915 ] } }
]
}
