{
"type": "FeatureCollection",
"name": "origin_destination_points",
"crs": { "type": "name", "properties": { "name": "urn:ogc:def:crs:OGC:1.3:CRS84" } },
"features": [
{ "type": "Feature", "properties": { "point_type": "origin", "points_str": "45.514804, -122.672457" }, "geometry": { "type": "Point", "coordinates": [ -122.672457197156319, 45.514804182655332 ] } },
{ "type": "Feature", "properties": { "point_type": "destination", "points_str": "45.543225, -122.471244" }, "geometry": { "type": "Point", "coordinates": [ -122.471244165595166, 45.543225014374691 ] } }
]
}
