{
"type": "FeatureCollection",
"name": "origin_destination_points",
"crs": { "type": "name", "properties": { "name": "urn:ogc:def:crs:OGC:1.3:CRS84" } },
"features": [
{ "type": "Feature", "properties": { "point_type": "origin", "points_str": "45.370606, -122.627514" }, "geometry": { "type": "Point", "coordinates": [ -122.627513656341577, 45.370605664398482 ] } },
{ "type": "Feature", "properties": { "point_type": "destination", "points_str": "45.323507, -122.57082" }, "geometry": { "type": "Point", "coordinates": [ -122.570819762838497, 45.323507086634699 ] } }
]
}
