{
"type": "FeatureCollection",
"crs": { "type": "name", "properties": { "name": "urn:ogc:def:crs:OGC:1.3:CRS84" } },
"features": [
{ "type": "Feature", "properties": { "point_type": "origin", "points_str": "45.520671, -122.578657" }, "geometry": { "type": "Point", "coordinates": [ -122.578656681590317, 45.520670968290652 ] } },
{ "type": "Feature", "properties": { "point_type": "destination", "points_str": "45.350456, -122.621755" }, "geometry": { "type": "Point", "coordinates": [ -122.621755187652525, 45.350455970597402 ] } }
]
}
