{
"type": "FeatureCollection",
"name": "origin_destination_points",
"crs": { "type": "name", "properties": { "name": "urn:ogc:def:crs:OGC:1.3:CRS84" } },
"features": [
{ "type": "Feature", "properties": { "point_type": "origin", "points_str": "45.520256, -122.404344" }, "geometry": { "type": "Point", "coordinates": [ -122.404343745586885, 45.520256299162703 ] } },
{ "type": "Feature", "properties": { "point_type": "destination", "points_str": "45.528328, -122.434315" }, "geometry": { "type": "Point", "coordinates": [ -122.434314833156151, 45.528327726518768 ] } }
]
}
