{
"type": "FeatureCollection",
"name": "origin_destination_points",
"crs": { "type": "name", "properties": { "name": "urn:ogc:def:crs:OGC:1.3:CRS84" } },
"features": [
{ "type": "Feature", "properties": { "point_type": "origin", "points_str": "45.497594, -122.628866" }, "geometry": { "type": "Point", "coordinates": [ -122.628866021016421, 45.497593818892874 ] } },
{ "type": "Feature", "properties": { "point_type": "destination", "points_str": "45.550039, -122.727194" }, "geometry": { "type": "Point", "coordinates": [ -122.727194354858554, 45.550038541320035 ] } }
]
}
