{
"type": "FeatureCollection",
"crs": { "type": "name", "properties": { "name": "urn:ogc:def:crs:OGC:1.3:CRS84" } },
"features": [
{ "type": "Feature", "properties": { "point_type": "origin", "points_str": "45.516262, -122.69618" }, "geometry": { "type": "Point", "coordinates": [ -122.696179521119646, 45.516262412136427 ] } },
{ "type": "Feature", "properties": { "point_type": "destination", "points_str": "45.518406, -122.868103" }, "geometry": { "type": "Point", "coordinates": [ -122.868102794353831, 45.518406467482613 ] } }
]
}
