{
"type": "FeatureCollection",
"name": "origin_destination_points",
"crs": { "type": "name", "properties": { "name": "urn:ogc:def:crs:OGC:1.3:CRS84" } },
"features": [
{ "type": "Feature", "properties": { "point_type": "origin", "points_str": "45.523596, -122.533815" }, "geometry": { "type": "Point", "coordinates": [ -122.533814633960446, 45.523595940794387 ] } },
{ "type": "Feature", "properties": { "point_type": "destination", "points_str": "45.521646, -122.507071" }, "geometry": { "type": "Point", "coordinates": [ -122.507070687673178, 45.521645739999741 ] } }
]
}
