{
"type": "FeatureCollection",
"crs": { "type": "name", "properties": { "name": "urn:ogc:def:crs:OGC:1.3:CRS84" } },
"features": [
{ "type": "Feature", "properties": { "point_type": "origin", "points_str": "45.466474, -122.57855" }, "geometry": { "type": "Point", "coordinates": [ -122.578549834675144, 45.466474393531158 ] } },
{ "type": "Feature", "properties": { "point_type": "destination", "points_str": "45.540778, -122.709264" }, "geometry": { "type": "Point", "coordinates": [ -122.709264459408672, 45.54077763935927 ] } }
]
}
