{
"type": "FeatureCollection",
"name": "origin_destination_points",
"crs": { "type": "name", "properties": { "name": "urn:ogc:def:crs:OGC:1.3:CRS84" } },
"features": [
{ "type": "Feature", "properties": { "point_type": "origin", "points_str": "45.424856, -122.782685" }, "geometry": { "type": "Point", "coordinates": [ -122.782685297468859, 45.42485557041887 ] } },
{ "type": "Feature", "properties": { "point_type": "destination", "points_str": "45.369674, -122.844438" }, "geometry": { "type": "Point", "coordinates": [ -122.844438345654837, 45.369674001041979 ] } }
]
}
