{
"type": "FeatureCollection",
"crs": { "type": "name", "properties": { "name": "urn:ogc:def:crs:OGC:1.3:CRS84" } },
"features": [
{ "type": "Feature", "properties": { "point_type": "origin", "points_str": "45.477719, -122.721563" }, "geometry": { "type": "Point", "coordinates": [ -122.721563167161662, 45.477719445293992 ] } },
{ "type": "Feature", "properties": { "point_type": "destination", "points_str": "45.380899, -122.643675" }, "geometry": { "type": "Point", "coordinates": [ -122.643674529663599, 45.380899171628478 ] } }
]
}
