{
"type": "FeatureCollection",
"name": "origin_destination_points",
"crs": { "type": "name", "properties": { "name": "urn:ogc:def:crs:OGC:1.3:CRS84" } },
"features": [
{ "type": "Feature", "properties": { "point_type": "origin", "points_str": "45.585011, -122.750453" }, "geometry": { "type": "Point", "coordinates": [ -122.750452878863669, 45.585011362896182 ] } },
{ "type": "Feature", "properties": { "point_type": "destination", "points_str": "45.379034, -122.635027" }, "geometry": { "type": "Point", "coordinates": [ -122.635026579478392, 45.379034492091435 ] } }
]
}
