{
"type": "FeatureCollection",
"name": "origin_destination_points",
"crs": { "type": "name", "properties": { "name": "urn:ogc:def:crs:OGC:1.3:CRS84" } },
"features": [
{ "type": "Feature", "properties": { "point_type": "origin", "points_str": "45.533998, -122.59236" }, "geometry": { "type": "Point", "coordinates": [ -122.592360223373518, 45.533997836581491 ] } },
{ "type": "Feature", "properties": { "point_type": "destination", "points_str": "45.556657, -122.510093" }, "geometry": { "type": "Point", "coordinates": [ -122.510092626510087, 45.556656894269253 ] } }
]
}
