{
"type": "FeatureCollection",
"crs": { "type": "name", "properties": { "name": "urn:ogc:def:crs:OGC:1.3:CRS84" } },
"features": [
{ "type": "Feature", "properties": { "point_type": "origin", "points_str": "45.511457, -122.711423" }, "geometry": { "type": "Point", "coordinates": [ -122.711422558272133, 45.511456559561083 ] } },
{ "type": "Feature", "properties": { "point_type": "destination", "points_str": "45.47512, -122.368021" }, "geometry": { "type": "Point", "coordinates": [ -122.368020967916635, 45.475120440477646 ] } }
]
}
