{
"type": "FeatureCollection",
"name": "origin_destination_points",
"crs": { "type": "name", "properties": { "name": "urn:ogc:def:crs:OGC:1.3:CRS84" } },
"features": [
{ "type": "Feature", "properties": { "point_type": "origin", "points_str": "45.440172, -122.572888" }, "geometry": { "type": "Point", "coordinates": [ -122.5728875785246, 45.440172036536559 ] } },
{ "type": "Feature", "properties": { "point_type": "destination", "points_str": "45.505324, -122.602571" }, "geometry": { "type": "Point", "coordinates": [ -122.602570846503326, 45.505323910730127 ] } }
]
}
