{
"type": "FeatureCollection",
"name": "origin_destination_points",
"crs": { "type": "name", "properties": { "name": "urn:ogc:def:crs:OGC:1.3:CRS84" } },
"features": [
{ "type": "Feature", "properties": { "point_type": "origin", "points_str": "45.524194, -122.495991" }, "geometry": { "type": "Point", "coordinates": [ -122.495990987897983, 45.52419370803154 ] } },
{ "type": "Feature", "properties": { "point_type": "destination", "points_str": "45.527032, -122.517121" }, "geometry": { "type": "Point", "coordinates": [ -122.517121302119776, 45.527031940030049 ] } }
]
}
