{
"type": "FeatureCollection",
"crs": { "type": "name", "properties": { "name": "urn:ogc:def:crs:OGC:1.3:CRS84" } },
"features": [
{ "type": "Feature", "properties": { "point_type": "origin", "points_str": "45.467755, -122.600677" }, "geometry": { "type": "Point", "coordinates": [ -122.600677315390783, 45.467755486068974 ] } },
{ "type": "Feature", "properties": { "point_type": "destination", "points_str": "45.445528, -122.602557" }, "geometry": { "type": "Point", "coordinates": [ -122.602556754291143, 45.445528020610382 ] } }
]
}
