{
"type": "FeatureCollection",
"name": "origin_destination_points",
"crs": { "type": "name", "properties": { "name": "urn:ogc:def:crs:OGC:1.3:CRS84" } },
"features": [
{ "type": "Feature", "properties": { "point_type": "origin", "points_str": "45.524336, -122.805494" }, "geometry": { "type": "Point", "coordinates": [ -122.805493591968897, 45.524336310024246 ] } },
{ "type": "Feature", "properties": { "point_type": "destination", "points_str": "45.561434, -122.864902" }, "geometry": { "type": "Point", "coordinates": [ -122.864901650786095, 45.561433975979369 ] } }
]
}
