{
"type": "FeatureCollection",
"name": "origin_destination_points",
"crs": { "type": "name", "properties": { "name": "urn:ogc:def:crs:OGC:1.3:CRS84" } },
"features": [
{ "type": "Feature", "properties": { "point_type": "origin", "points_str": "45.474359, -122.86052" }, "geometry": { "type": "Point", "coordinates": [ -122.860519743167316, 45.474358724573776 ] } },
{ "type": "Feature", "properties": { "point_type": "destination", "points_str": "45.506389, -122.415444" }, "geometry": { "type": "Point", "coordinates": [ -122.415444460049471, 45.506389063661253 ] } }
]
}
