{
"type": "FeatureCollection",
"name": "origin_destination_points",
"crs": { "type": "name", "properties": { "name": "urn:ogc:def:crs:OGC:1.3:CRS84" } },
"features": [
{ "type": "Feature", "properties": { "point_type": "origin", "points_str": "45.506635, -122.627035" }, "geometry": { "type": "Point", "coordinates": [ -122.627034716744291, 45.506634711527411 ] } },
{ "type": "Feature", "properties": { "point_type": "destination", "points_str": "45.566986, -122.617796" }, "geometry": { "type": "Point", "coordinates": [ -122.617795940885415, 45.566986339968437 ] } }
]
}
