{
"type": "FeatureCollection",
"name": "origin_destination_points",
"crs": { "type": "name", "properties": { "name": "urn:ogc:def:crs:OGC:1.3:CRS84" } },
"features": [
{ "type": "Feature", "properties": { "point_type": "origin", "points_str": "45.5239, -122.641874" }, "geometry": { "type": "Point", "coordinates": [ -122.641874435119533, 45.523900236741007 ] } },
{ "type": "Feature", "properties": { "point_type": "destination", "points_str": "45.500053, -122.805843" }, "geometry": { "type": "Point", "coordinates": [ -122.805842529236813, 45.500052515129454 ] } }
]
}
