{
"type": "FeatureCollection",
"name": "origin_destination_points",
"crs": { "type": "name", "properties": { "name": "urn:ogc:def:crs:OGC:1.3:CRS84" } },
"features": [
{ "type": "Feature", "properties": { "point_type": "origin", "points_str": "45.507003, -122.489127" }, "geometry": { "type": "Point", "coordinates": [ -122.489126521132221, 45.507003494226808 ] } },
{ "type": "Feature", "properties": { "point_type": "destination", "points_str": "45.509292, -122.6508" }, "geometry": { "type": "Point", "coordinates": [ -122.650799810525186, 45.509291852511744 ] } }
]
}
