{
"type": "FeatureCollection",
"name": "origin_destination_points",
"crs": { "type": "name", "properties": { "name": "urn:ogc:def:crs:OGC:1.3:CRS84" } },
"features": [
{ "type": "Feature", "properties": { "point_type": "origin", "points_str": "45.515093, -122.872985" }, "geometry": { "type": "Point", "coordinates": [ -122.872984872288498, 45.515092892936465 ] } },
{ "type": "Feature", "properties": { "point_type": "destination", "points_str": "45.47651, -122.775977" }, "geometry": { "type": "Point", "coordinates": [ -122.775977401034908, 45.476510445194315 ] } }
]
}
