{
"type": "FeatureCollection",
"crs": { "type": "name", "properties": { "name": "urn:ogc:def:crs:OGC:1.3:CRS84" } },
"features": [
{ "type": "Feature", "properties": { "point_type": "origin", "points_str": "45.465419, -122.726206" }, "geometry": { "type": "Point", "coordinates": [ -122.726206169933988, 45.465419417783338 ] } },
{ "type": "Feature", "properties": { "point_type": "destination", "points_str": "45.446004, -122.809138" }, "geometry": { "type": "Point", "coordinates": [ -122.809137961158498, 45.446004389198194 ] } }
]
}
