{
"type": "FeatureCollection",
"name": "origin_destination_points",
"crs": { "type": "name", "properties": { "name": "urn:ogc:def:crs:OGC:1.3:CRS84" } },
"features": [
{ "type": "Feature", "properties": { "point_type": "origin", "points_str": "45.480052, -122.608954" }, "geometry": { "type": "Point", "coordinates": [ -122.608954006866867, 45.480051702691405 ] } },
{ "type": "Feature", "properties": { "point_type": "destination", "points_str": "45.51651, -122.581474" }, "geometry": { "type": "Point", "coordinates": [ -122.581474215779835, 45.516509553898217 ] } }
]
}
