{
"type": "FeatureCollection",
"name": "origin_destination_points",
"crs": { "type": "name", "properties": { "name": "urn:ogc:def:crs:OGC:1.3:CRS84" } },
"features": [
{ "type": "Feature", "properties": { "point_type": "origin", "points_str": "45.551445, -122.38965" }, "geometry": { "type": "Point", "coordinates": [ -122.389649509229812, 45.551444610558761 ] } },
{ "type": "Feature", "properties": { "point_type": "destination", "points_str": "45.515565, -122.388508" }, "geometry": { "type": "Point", "coordinates": [ -122.388507907570713, 45.515564726897637 ] } }
]
}
