{
"type": "FeatureCollection",
"name": "origin_destination_points",
"crs": { "type": "name", "properties": { "name": "urn:ogc:def:crs:OGC:1.3:CRS84" } },
"features": [
{ "type": "Feature", "properties": { "point_type": "origin", "points_str": "45.506396, -122.686517" }, "geometry": { "type": "Point", "coordinates": [ -122.686517316931941, 45.506396320974005 ] } },
{ "type": "Feature", "properties": { "point_type": "destination", "points_str": "45.496291, -122.668269" }, "geometry": { "type": "Point", "coordinates": [ -122.668268823294383, 45.496291379711145 ] } }
]
}
