{
"type": "FeatureCollection",
"name": "origin_destination_points",
"crs": { "type": "name", "properties": { "name": "urn:ogc:def:crs:OGC:1.3:CRS84" } },
"features": [
{ "type": "Feature", "properties": { "point_type": "origin", "points_str": "45.551942, -122.671608" }, "geometry": { "type": "Point", "coordinates": [ -122.671608214749725, 45.551941949712386 ] } },
{ "type": "Feature", "properties": { "point_type": "destination", "points_str": "45.575025, -122.756891" }, "geometry": { "type": "Point", "coordinates": [ -122.756890840239635, 45.575025172679617 ] } }
]
}
