{
"type": "FeatureCollection",
"name": "origin_destination_points",
"crs": { "type": "name", "properties": { "name": "urn:ogc:def:crs:OGC:1.3:CRS84" } },
"features": [
{ "type": "Feature", "properties": { "point_type": "origin", "points_str": "45.540977, -122.666254" }, "geometry": { "type": "Point", "coordinates": [ -122.66625385351648, 45.540976851668411 ] } },
{ "type": "Feature", "properties": { "point_type": "destination", "points_str": "45.555534, -122.638823" }, "geometry": { "type": "Point", "coordinates": [ -122.638822577592805, 45.555534067091052 ] } }
]
}
