{
"type": "FeatureCollection",
"name": "origin_destination_points",
"crs": { "type": "name", "properties": { "name": "urn:ogc:def:crs:OGC:1.3:CRS84" } },
"features": [
{ "type": "Feature", "properties": { "point_type": "origin", "points_str": "45.519785, -122.795009" }, "geometry": { "type": "Point", "coordinates": [ -122.795008831133131, 45.519785486936257 ] } },
{ "type": "Feature", "properties": { "point_type": "destination", "points_str": "45.502073, -122.958031" }, "geometry": { "type": "Point", "coordinates": [ -122.958031313521147, 45.502073208741457 ] } }
]
}
