{
"type": "FeatureCollection",
"name": "origin_destination_points",
"crs": { "type": "name", "properties": { "name": "urn:ogc:def:crs:OGC:1.3:CRS84" } },
"features": [
{ "type": "Feature", "properties": { "point_type": "origin", "points_str": "45.501231, -122.5972" }, "geometry": { "type": "Point", "coordinates": [ -122.597199531089657, 45.501231263983279 ] } },
{ "type": "Feature", "properties": { "point_type": "destination", "points_str": "45.557482, -122.573444" }, "geometry": { "type": "Point", "coordinates": [ -122.57344399517433, 45.557482209515243 ] } }
]
}
