{
"type": "FeatureCollection",
"name": "origin_destination_points",
"crs": { "type": "name", "properties": { "name": "urn:ogc:def:crs:OGC:1.3:CRS84" } },
"features": [
{ "type": "Feature", "properties": { "point_type": "origin", "points_str": "45.434883, -122.588786" }, "geometry": { "type": "Point", "coordinates": [ -122.588785721127792, 45.434882968737647 ] } },
{ "type": "Feature", "properties": { "point_type": "destination", "points_str": "45.424091, -122.517694" }, "geometry": { "type": "Point", "coordinates": [ -122.517693942338909, 45.424090628941983 ] } }
]
}
