{
"type": "FeatureCollection",
"name": "origin_destination_points",
"crs": { "type": "name", "properties": { "name": "urn:ogc:def:crs:OGC:1.3:CRS84" } },
"features": [
{ "type": "Feature", "properties": { "point_type": "origin", "points_str": "45.522802, -122.97786" }, "geometry": { "type": "Point", "coordinates": [ -122.977859945504065, 45.522801924300495 ] } },
{ "type": "Feature", "properties": { "point_type": "destination", "points_str": "45.544727, -122.964372" }, "geometry": { "type": "Point", "coordinates": [ -122.964371633646053, 45.544727387638723 ] } }
]
}
