{
"type": "FeatureCollection",
"crs": { "type": "name", "properties": { "name": "urn:ogc:def:crs:OGC:1.3:CRS84" } },
"features": [
{ "type": "Feature", "properties": { "point_type": "origin", "points_str": "45.429303, -122.799937" }, "geometry": { "type": "Point", "coordinates": [ -122.799937362948313, 45.429302576673408 ] } },
{ "type": "Feature", "properties": { "point_type": "destination", "points_str": "45.466206, -122.65558" }, "geometry": { "type": "Point", "coordinates": [ -122.655580056221837, 45.466205750832927 ] } }
]
}
