{
"type": "FeatureCollection",
"crs": { "type": "name", "properties": { "name": "urn:ogc:def:crs:OGC:1.3:CRS84" } },
"features": [
{ "type": "Feature", "properties": { "point_type": "origin", "points_str": "45.519467, -122.67798" }, "geometry": { "type": "Point", "coordinates": [ -122.677979644407372, 45.519466913617755 ] } },
{ "type": "Feature", "properties": { "point_type": "destination", "points_str": "45.53333, -122.498753" }, "geometry": { "type": "Point", "coordinates": [ -122.498753470339508, 45.53333036952526 ] } }
]
}
