{
"type": "FeatureCollection",
"name": "origin_destination_points",
"crs": { "type": "name", "properties": { "name": "urn:ogc:def:crs:OGC:1.3:CRS84" } },
"features": [
{ "type": "Feature", "properties": { "point_type": "origin", "points_str": "45.535354, -122.575858" }, "geometry": { "type": "Point", "coordinates": [ -122.575857938835611, 45.535353598533611 ] } },
{ "type": "Feature", "properties": { "point_type": "destination", "points_str": "45.52705, -122.639632" }, "geometry": { "type": "Point", "coordinates": [ -122.639631770171206, 45.527050377487704 ] } }
]
}
