{
"type": "FeatureCollection",
"crs": { "type": "name", "properties": { "name": "urn:ogc:def:crs:OGC:1.3:CRS84" } },
"features": [
{ "type": "Feature", "properties": { "point_type": "origin", "points_str": "45.53284, -122.495964" }, "geometry": { "type": "Point", "coordinates": [ -122.495963718331836, 45.532840022439764 ] } },
{ "type": "Feature", "properties": { "point_type": "destination", "points_str": "45.547953, -122.595252" }, "geometry": { "type": "Point", "coordinates": [ -122.59525160210697, 45.547953450918726 ] } }
]
}
