{
"type": "FeatureCollection",
"crs": { "type": "name", "properties": { "name": "urn:ogc:def:crs:OGC:1.3:CRS84" } },
"features": [
{ "type": "Feature", "properties": { "point_type": "origin", "points_str": "45.543008, -122.719734" }, "geometry": { "type": "Point", "coordinates": [ -122.719733896714715, 45.543008439642506 ] } },
{ "type": "Feature", "properties": { "point_type": "destination", "points_str": "45.572437, -122.677461" }, "geometry": { "type": "Point", "coordinates": [ -122.677460747973541, 45.572436559505242 ] } }
]
}
