{
"type": "FeatureCollection",
"name": "origin_destination_points",
"crs": { "type": "name", "properties": { "name": "urn:ogc:def:crs:OGC:1.3:CRS84" } },
"features": [
{ "type": "Feature", "properties": { "point_type": "origin", "points_str": "45.531828, -122.823824" }, "geometry": { "type": "Point", "coordinates": [ -122.823823873400087, 45.531828171083554 ] } },
{ "type": "Feature", "properties": { "point_type": "destination", "points_str": "45.51721, -122.532788" }, "geometry": { "type": "Point", "coordinates": [ -122.532788008583879, 45.517210185611084 ] } }
]
}
