{
"type": "FeatureCollection",
"crs": { "type": "name", "properties": { "name": "urn:ogc:def:crs:OGC:1.3:CRS84" } },
"features": [
{ "type": "Feature", "properties": { "point_type": "origin", "points_str": "45.495597, -122.40006" }, "geometry": { "type": "Point", "coordinates": [ -122.400060351499405, 45.495597234472811 ] } },
{ "type": "Feature", "properties": { "point_type": "destination", "points_str": "45.52112, -122.402473" }, "geometry": { "type": "Point", "coordinates": [ -122.402472565919325, 45.521120153627628 ] } }
]
}
