{
"type": "FeatureCollection",
"crs": { "type": "name", "properties": { "name": "urn:ogc:def:crs:OGC:1.3:CRS84" } },
"features": [
{ "type": "Feature", "properties": { "point_type": "origin", "points_str": "45.522141, -122.974498" }, "geometry": { "type": "Point", "coordinates": [ -122.974498040410026, 45.522140634983479 ] } },
{ "type": "Feature", "properties": { "point_type": "destination", "points_str": "45.536743, -122.934919" }, "geometry": { "type": "Point", "coordinates": [ -122.934918889928937, 45.536743308124052 ] } }
]
}
