{
"type": "FeatureCollection",
"name": "origin_destination_points",
"crs": { "type": "name", "properties": { "name": "urn:ogc:def:crs:OGC:1.3:CRS84" } },
"features": [
{ "type": "Feature", "properties": { "point_type": "origin", "points_str": "45.518886, -122.510488" }, "geometry": { "type": "Point", "coordinates": [ -122.510487773269304, 45.518885801703355 ] } },
{ "type": "Feature", "properties": { "point_type": "destination", "points_str": "45.547067, -122.709171" }, "geometry": { "type": "Point", "coordinates": [ -122.709171091363373, 45.547067244533878 ] } }
]
}
