{
"type": "FeatureCollection",
"crs": { "type": "name", "properties": { "name": "urn:ogc:def:crs:OGC:1.3:CRS84" } },
"features": [
{ "type": "Feature", "properties": { "point_type": "origin", "points_str": "45.446312, -122.63746" }, "geometry": { "type": "Point", "coordinates": [ -122.637460462012015, 45.446311990018764 ] } },
{ "type": "Feature", "properties": { "point_type": "destination", "points_str": "45.482917, -122.647976" }, "geometry": { "type": "Point", "coordinates": [ -122.647975848123693, 45.482917091720836 ] } }
]
}
