{
"type": "FeatureCollection",
"crs": { "type": "name", "properties": { "name": "urn:ogc:def:crs:OGC:1.3:CRS84" } },
"features": [
{ "type": "Feature", "properties": { "point_type": "origin", "points_str": "45.515, -122.573563" }, "geometry": { "type": "Point", "coordinates": [ -122.573563109892007, 45.51499960096308 ] } },
{ "type": "Feature", "properties": { "point_type": "destination", "points_str": "45.545475, -122.689969" }, "geometry": { "type": "Point", "coordinates": [ -122.689968506516763, 45.545475303325169 ] } }
]
}
