{
"type": "FeatureCollection",
"crs": { "type": "name", "properties": { "name": "urn:ogc:def:crs:OGC:1.3:CRS84" } },
"features": [
{ "type": "Feature", "properties": { "point_type": "origin", "points_str": "45.461425, -122.63349" }, "geometry": { "type": "Point", "coordinates": [ -122.633490254384753, 45.461425288111492 ] } },
{ "type": "Feature", "properties": { "point_type": "destination", "points_str": "45.539645, -122.64266" }, "geometry": { "type": "Point", "coordinates": [ -122.642659572132175, 45.539644990895653 ] } }
]
}
