{
"type": "FeatureCollection",
"name": "origin_destination_points",
"crs": { "type": "name", "properties": { "name": "urn:ogc:def:crs:OGC:1.3:CRS84" } },
"features": [
{ "type": "Feature", "properties": { "point_type": "origin", "points_str": "45.587688, -122.707996" }, "geometry": { "type": "Point", "coordinates": [ -122.707996206890726, 45.587688378159527 ] } },
{ "type": "Feature", "properties": { "point_type": "destination", "points_str": "45.531909, -122.486483" }, "geometry": { "type": "Point", "coordinates": [ -122.486483257769706, 45.531909196800136 ] } }
]
}
