{
"type": "FeatureCollection",
"name": "origin_destination_points",
"crs": { "type": "name", "properties": { "name": "urn:ogc:def:crs:OGC:1.3:CRS84" } },
"features": [
{ "type": "Feature", "properties": { "point_type": "origin", "points_str": "45.523772, -122.480004" }, "geometry": { "type": "Point", "coordinates": [ -122.480003743795407, 45.523772244050043 ] } },
{ "type": "Feature", "properties": { "point_type": "destination", "points_str": "45.500668, -122.635336" }, "geometry": { "type": "Point", "coordinates": [ -122.635336212156218, 45.500667830969668 ] } }
]
}
