{
"type": "FeatureCollection",
"crs": { "type": "name", "properties": { "name": "urn:ogc:def:crs:OGC:1.3:CRS84" } },
"features": [
{ "type": "Feature", "properties": { "point_type": "origin", "points_str": "45.518958, -122.432756" }, "geometry": { "type": "Point", "coordinates": [ -122.432756038383317, 45.518957970183187 ] } },
{ "type": "Feature", "properties": { "point_type": "destination", "points_str": "45.431504, -122.65516" }, "geometry": { "type": "Point", "coordinates": [ -122.65515996773081, 45.431503907870855 ] } }
]
}
