{
"type": "FeatureCollection",
"crs": { "type": "name", "properties": { "name": "urn:ogc:def:crs:OGC:1.3:CRS84" } },
"features": [
{ "type": "Feature", "properties": { "point_type": "origin", "points_str": "45.392606, -122.644384" }, "geometry": { "type": "Point", "coordinates": [ -122.644383576925151, 45.392606327443985 ] } },
{ "type": "Feature", "properties": { "point_type": "destination", "points_str": "45.347148, -122.788758" }, "geometry": { "type": "Point", "coordinates": [ -122.788757559008488, 45.347148074201655 ] } }
]
}
