{
"type": "FeatureCollection",
"name": "origin_destination_points",
"crs": { "type": "name", "properties": { "name": "urn:ogc:def:crs:OGC:1.3:CRS84" } },
"features": [
{ "type": "Feature", "properties": { "point_type": "origin", "points_str": "45.554439, -122.579992" }, "geometry": { "type": "Point", "coordinates": [ -122.579992072777131, 45.55443882837546 ] } },
{ "type": "Feature", "properties": { "point_type": "destination", "points_str": "45.467816, -122.598513" }, "geometry": { "type": "Point", "coordinates": [ -122.598513371897155, 45.46781581254627 ] } }
]
}
