{
"type": "FeatureCollection",
"name": "origin_destination_points",
"crs": { "type": "name", "properties": { "name": "urn:ogc:def:crs:OGC:1.3:CRS84" } },
"features": [
{ "type": "Feature", "properties": { "point_type": "origin", "points_str": "45.398053, -122.624122" }, "geometry": { "type": "Point", "coordinates": [ -122.624121978931512, 45.398053478563043 ] } },
{ "type": "Feature", "properties": { "point_type": "destination", "points_str": "45.345033, -122.645967" }, "geometry": { "type": "Point", "coordinates": [ -122.645967372227787, 45.345032650328704 ] } }
]
}
