{
"type": "FeatureCollection",
"name": "origin_destination_points",
"crs": { "type": "name", "properties": { "name": "urn:ogc:def:crs:OGC:1.3:CRS84" } },
"features": [
{ "type": "Feature", "properties": { "point_type": "origin", "points_str": "45.461316, -122.698333" }, "geometry": { "type": "Point", "coordinates": [ -122.698333120656983, 45.461315835873883 ] } },
{ "type": "Feature", "properties": { "point_type": "destination", "points_str": "45.466994, -122.803778" }, "geometry": { "type": "Point", "coordinates": [ -122.8037782561304, 45.466994316346621 ] } }
]
}
