{
"type": "FeatureCollection",
"crs": { "type": "name", "properties": { "name": "urn:ogc:def:crs:OGC:1.3:CRS84" } },
"features": [
{ "type": "Feature", "properties": { "point_type": "origin", "points_str": "45.589999, -122.710422" }, "geometry": { "type": "Point", "coordinates": [ -122.710422079000665, 45.589999180662815 ] } },
{ "type": "Feature", "properties": { "point_type": "destination", "points_str": "45.618903, -122.812204" }, "geometry": { "type": "Point", "coordinates": [ -122.81220439506167, 45.618903168429163 ] } }
]
}
