{
"type": "FeatureCollection",
"crs": { "type": "name", "properties": { "name": "urn:ogc:def:crs:OGC:1.3:CRS84" } },
"features": [
{ "type": "Feature", "properties": { "point_type": "origin", "points_str": "45.591843, -122.713655" }, "geometry": { "type": "Point", "coordinates": [ -122.713655173665714, 45.591842658758772 ] } },
{ "type": "Feature", "properties": { "point_type": "destination", "points_str": "45.493827, -122.824087" }, "geometry": { "type": "Point", "coordinates": [ -122.824087395136033, 45.493827478607855 ] } }
]
}
