{
"type": "FeatureCollection",
"name": "origin_destination_points",
"crs": { "type": "name", "properties": { "name": "urn:ogc:def:crs:OGC:1.3:CRS84" } },
"features": [
{ "type": "Feature", "properties": { "point_type": "origin", "points_str": "45.439707, -122.775608" }, "geometry": { "type": "Point", "coordinates": [ -122.775608280542841, 45.439707019008871 ] } },
{ "type": "Feature", "properties": { "point_type": "destination", "points_str": "45.461273, -122.789536" }, "geometry": { "type": "Point", "coordinates": [ -122.789536427325046, 45.461273106010211 ] } }
]
}
