{
"type": "FeatureCollection",
"name": "origin_destination_points",
"crs": { "type": "name", "properties": { "name": "urn:ogc:def:crs:OGC:1.3:CRS84" } },
"features": [
{ "type": "Feature", "properties": { "point_type": "origin", "points_str": "45.564817, -122.690741" }, "geometry": { "type": "Point", "coordinates": [ -122.690740981196598, 45.564816954394047 ] } },
{ "type": "Feature", "properties": { "point_type": "destination", "points_str": "45.512055, -122.575887" }, "geometry": { "type": "Point", "coordinates": [ -122.575886710799111, 45.512055399690254 ] } }
]
}
