{
"type": "FeatureCollection",
"name": "origin_destination_points",
"crs": { "type": "name", "properties": { "name": "urn:ogc:def:crs:OGC:1.3:CRS84" } },
"features": [
{ "type": "Feature", "properties": { "point_type": "origin", "points_str": "45.51402, -122.973615" }, "geometry": { "type": "Point", "coordinates": [ -122.973615311937763, 45.514019518134269 ] } },
{ "type": "Feature", "properties": { "point_type": "destination", "points_str": "45.499975, -122.429757" }, "geometry": { "type": "Point", "coordinates": [ -122.429756784645207, 45.499975461660142 ] } }
]
}
