{
"type": "FeatureCollection",
"name": "origin_destination_points",
"crs": { "type": "name", "properties": { "name": "urn:ogc:def:crs:OGC:1.3:CRS84" } },
"features": [
{ "type": "Feature", "properties": { "point_type": "origin", "points_str": "45.56432, -122.657478" }, "geometry": { "type": "Point", "coordinates": [ -122.657478072645304, 45.564319778316104 ] } },
{ "type": "Feature", "properties": { "point_type": "destination", "points_str": "45.468095, -122.579606" }, "geometry": { "type": "Point", "coordinates": [ -122.579606083400407, 45.468094626885716 ] } }
]
}
