{
"type": "FeatureCollection",
"crs": { "type": "name", "properties": { "name": "urn:ogc:def:crs:OGC:1.3:CRS84" } },
"features": [
{ "type": "Feature", "properties": { "point_type": "origin", "points_str": "45.519229, -123.032123" }, "geometry": { "type": "Point", "coordinates": [ -123.032122714514045, 45.5192286076568 ] } },
{ "type": "Feature", "properties": { "point_type": "destination", "points_str": "45.383477, -122.768026" }, "geometry": { "type": "Point", "coordinates": [ -122.768025749282501, 45.383477156826032 ] } }
]
}
