{
"type": "FeatureCollection",
"name": "origin_destination_points",
"crs": { "type": "name", "properties": { "name": "urn:ogc:def:crs:OGC:1.3:CRS84" } },
"features": [
{ "type": "Feature", "properties": { "point_type": "origin", "points_str": "45.429675, -122.655497" }, "geometry": { "type": "Point", "coordinates": [ -122.655497317264533, 45.42967485831273 ] } },
{ "type": "Feature", "properties": { "point_type": "destination", "points_str": "45.539528, -122.669026" }, "geometry": { "type": "Point", "coordinates": [ -122.669025978658979, 45.539527673437696 ] } }
]
}
