{
"type": "FeatureCollection",
"name": "origin_destination_points",
"crs": { "type": "name", "properties": { "name": "urn:ogc:def:crs:OGC:1.3:CRS84" } },
"features": [
{ "type": "Feature", "properties": { "point_type": "origin", "points_str": "45.463548, -122.616756" }, "geometry": { "type": "Point", "coordinates": [ -122.616755840382979, 45.463548118013783 ] } },
{ "type": "Feature", "properties": { "point_type": "destination", "points_str": "45.519195, -122.610883" }, "geometry": { "type": "Point", "coordinates": [ -122.610882786030615, 45.51919480868559 ] } }
]
}
