{
"type": "FeatureCollection",
"name": "origin_destination_points",
"crs": { "type": "name", "properties": { "name": "urn:ogc:def:crs:OGC:1.3:CRS84" } },
"features": [
{ "type": "Feature", "properties": { "point_type": "origin", "points_str": "45.575631, -122.680436" }, "geometry": { "type": "Point", "coordinates": [ -122.680436374237004, 45.575631154844281 ] } },
{ "type": "Feature", "properties": { "point_type": "destination", "points_str": "45.590932, -122.678756" }, "geometry": { "type": "Point", "coordinates": [ -122.678756025281515, 45.590931927727887 ] } }
]
}
