{
"type": "FeatureCollection",
"crs": { "type": "name", "properties": { "name": "urn:ogc:def:crs:OGC:1.3:CRS84" } },
"features": [
{ "type": "Feature", "properties": { "point_type": "origin", "points_str": "45.520277, -122.436141" }, "geometry": { "type": "Point", "coordinates": [ -122.436141473630798, 45.520277285870868 ] } },
{ "type": "Feature", "properties": { "point_type": "destination", "points_str": "45.519024, -122.744417" }, "geometry": { "type": "Point", "coordinates": [ -122.744416954058067, 45.519024400979973 ] } }
]
}
