{
"type": "FeatureCollection",
"crs": { "type": "name", "properties": { "name": "urn:ogc:def:crs:OGC:1.3:CRS84" } },
"features": [
{ "type": "Feature", "properties": { "point_type": "origin", "points_str": "45.533215, -122.677366" }, "geometry": { "type": "Point", "coordinates": [ -122.67736633765908, 45.533214951438971 ] } },
{ "type": "Feature", "properties": { "point_type": "destination", "points_str": "45.583501, -122.660355" }, "geometry": { "type": "Point", "coordinates": [ -122.660354661543593, 45.583500678069676 ] } }
]
}
