{
"type": "FeatureCollection",
"name": "origin_destination_points",
"crs": { "type": "name", "properties": { "name": "urn:ogc:def:crs:OGC:1.3:CRS84" } },
"features": [
{ "type": "Feature", "properties": { "point_type": "origin", "points_str": "45.518932, -122.455253" }, "geometry": { "type": "Point", "coordinates": [ -122.455252714619874, 45.518932430137212 ] } },
{ "type": "Feature", "properties": { "point_type": "destination", "points_str": "45.53142, -122.561767" }, "geometry": { "type": "Point", "coordinates": [ -122.561766623377437, 45.53142032238803 ] } }
]
}
