{
"type": "FeatureCollection",
"name": "origin_destination_points",
"crs": { "type": "name", "properties": { "name": "urn:ogc:def:crs:OGC:1.3:CRS84" } },
"features": [
{ "type": "Feature", "properties": { "point_type": "origin", "points_str": "45.498943, -122.47423" }, "geometry": { "type": "Point", "coordinates": [ -122.47423030155386, 45.498942509335087 ] } },
{ "type": "Feature", "properties": { "point_type": "destination", "points_str": "45.5171, -122.681251" }, "geometry": { "type": "Point", "coordinates": [ -122.681251144934578, 45.517099505322534 ] } }
]
}
