{
"type": "FeatureCollection",
"name": "origin_destination_points",
"crs": { "type": "name", "properties": { "name": "urn:ogc:def:crs:OGC:1.3:CRS84" } },
"features": [
{ "type": "Feature", "properties": { "point_type": "origin", "points_str": "45.363326, -122.601914" }, "geometry": { "type": "Point", "coordinates": [ -122.601913646133596, 45.36332617883167 ] } },
{ "type": "Feature", "properties": { "point_type": "destination", "points_str": "45.571711, -122.652095" }, "geometry": { "type": "Point", "coordinates": [ -122.652095000661802, 45.571710754865983 ] } }
]
}
