{
"type": "FeatureCollection",
"crs": { "type": "name", "properties": { "name": "urn:ogc:def:crs:OGC:1.3:CRS84" } },
"features": [
{ "type": "Feature", "properties": { "point_type": "origin", "points_str": "45.48242, -122.399537" }, "geometry": { "type": "Point", "coordinates": [ -122.399536610930426, 45.482419981407354 ] } },
{ "type": "Feature", "properties": { "point_type": "destination", "points_str": "45.474297, -122.713208" }, "geometry": { "type": "Point", "coordinates": [ -122.713207820479056, 45.474297247355935 ] } }
]
}
