{
"type": "FeatureCollection",
"name": "origin_destination_points",
"crs": { "type": "name", "properties": { "name": "urn:ogc:def:crs:OGC:1.3:CRS84" } },
"features": [
{ "type": "Feature", "properties": { "point_type": "origin", "points_str": "45.451958, -122.573881" }, "geometry": { "type": "Point", "coordinates": [ -122.573880986674638, 45.451957688612168 ] } },
{ "type": "Feature", "properties": { "point_type": "destination", "points_str": "45.359487, -122.605151" }, "geometry": { "type": "Point", "coordinates": [ -122.60515125731547, 45.359486780917081 ] } }
]
}
