{
"type": "FeatureCollection",
"name": "origin_destination_points",
"crs": { "type": "name", "properties": { "name": "urn:ogc:def:crs:OGC:1.3:CRS84" } },
"features": [
{ "type": "Feature", "properties": { "point_type": "origin", "points_str": "45.507194, -122.636139" }, "geometry": { "type": "Point", "coordinates": [ -122.636138878438231, 45.507194267831899 ] } },
{ "type": "Feature", "properties": { "point_type": "destination", "points_str": "45.479832, -122.555156" }, "geometry": { "type": "Point", "coordinates": [ -122.555156114192101, 45.479832479967058 ] } }
]
}
