{
"type": "FeatureCollection",
"crs": { "type": "name", "properties": { "name": "urn:ogc:def:crs:OGC:1.3:CRS84" } },
"features": [
{ "type": "Feature", "properties": { "point_type": "origin", "points_str": "45.3253, -122.564445" }, "geometry": { "type": "Point", "coordinates": [ -122.564444734371548, 45.325300437991778 ] } },
{ "type": "Feature", "properties": { "point_type": "destination", "points_str": "45.432543, -122.550277" }, "geometry": { "type": "Point", "coordinates": [ -122.550276916425645, 45.432543060961578 ] } }
]
}
