{
"type": "FeatureCollection",
"crs": { "type": "name", "properties": { "name": "urn:ogc:def:crs:OGC:1.3:CRS84" } },
"features": [
{ "type": "Feature", "properties": { "point_type": "origin", "points_str": "45.490897, -122.618371" }, "geometry": { "type": "Point", "coordinates": [ -122.618371213531404, 45.490896705591084 ] } },
{ "type": "Feature", "properties": { "point_type": "destination", "points_str": "45.557147, -122.626888" }, "geometry": { "type": "Point", "coordinates": [ -122.626887516260908, 45.557147392833677 ] } }
]
}
