{
"type": "FeatureCollection",
"name": "origin_destination_points",
"crs": { "type": "name", "properties": { "name": "urn:ogc:def:crs:OGC:1.3:CRS84" } },
"features": [
{ "type": "Feature", "properties": { "point_type": "origin", "points_str": "45.347161, -122.602726" }, "geometry": { "type": "Point", "coordinates": [ -122.602725785626234, 45.34716080818427 ] } },
{ "type": "Feature", "properties": { "point_type": "destination", "points_str": "45.481099, -122.576138" }, "geometry": { "type": "Point", "coordinates": [ -122.57613796538125, 45.481098512739045 ] } }
]
}
