{
"type": "FeatureCollection",
"name": "origin_destination_points",
"crs": { "type": "name", "properties": { "name": "urn:ogc:def:crs:OGC:1.3:CRS84" } },
"features": [
{ "type": "Feature", "properties": { "point_type": "origin", "points_str": "45.505142, -122.588181" }, "geometry": { "type": "Point", "coordinates": [ -122.588181330678594, 45.505142126849002 ] } },
{ "type": "Feature", "properties": { "point_type": "destination", "points_str": "45.557903, -122.638816" }, "geometry": { "type": "Point", "coordinates": [ -122.638815985573615, 45.557902854468843 ] } }
]
}
