{
"type": "FeatureCollection",
"name": "origin_destination_points",
"crs": { "type": "name", "properties": { "name": "urn:ogc:def:crs:OGC:1.3:CRS84" } },
"features": [
{ "type": "Feature", "properties": { "point_type": "origin", "points_str": "45.513345, -122.879946" }, "geometry": { "type": "Point", "coordinates": [ -122.879946181803973, 45.513344994567611 ] } },
{ "type": "Feature", "properties": { "point_type": "destination", "points_str": "45.484332, -122.764195" }, "geometry": { "type": "Point", "coordinates": [ -122.764194616757933, 45.484332351589451 ] } }
]
}
