{
"type": "FeatureCollection",
"crs": { "type": "name", "properties": { "name": "urn:ogc:def:crs:OGC:1.3:CRS84" } },
"features": [
{ "type": "Feature", "properties": { "point_type": "origin", "points_str": "45.577219, -122.665654" }, "geometry": { "type": "Point", "coordinates": [ -122.665654340686018, 45.577219124704484 ] } },
{ "type": "Feature", "properties": { "point_type": "destination", "points_str": "45.519344, -122.443109" }, "geometry": { "type": "Point", "coordinates": [ -122.443109102981239, 45.519344219911169 ] } }
]
}
