{
"type": "FeatureCollection",
"name": "origin_destination_points",
"crs": { "type": "name", "properties": { "name": "urn:ogc:def:crs:OGC:1.3:CRS84" } },
"features": [
{ "type": "Feature", "properties": { "point_type": "origin", "points_str": "45.486265, -122.684185" }, "geometry": { "type": "Point", "coordinates": [ -122.684185086218818, 45.486265405970975 ] } },
{ "type": "Feature", "properties": { "point_type": "destination", "points_str": "45.4628, -122.696651" }, "geometry": { "type": "Point", "coordinates": [ -122.696651494382223, 45.462800199611223 ] } }
]
}
