{
"type": "FeatureCollection",
"crs": { "type": "name", "properties": { "name": "urn:ogc:def:crs:OGC:1.3:CRS84" } },
"features": [
{ "type": "Feature", "properties": { "point_type": "origin", "points_str": "45.568794, -122.622829" }, "geometry": { "type": "Point", "coordinates": [ -122.622829250487641, 45.568794149458029 ] } },
{ "type": "Feature", "properties": { "point_type": "destination", "points_str": "45.537331, -122.521725" }, "geometry": { "type": "Point", "coordinates": [ -122.521725209517143, 45.537331301791397 ] } }
]
}
