{
"type": "FeatureCollection",
"name": "origin_destination_points",
"crs": { "type": "name", "properties": { "name": "urn:ogc:def:crs:OGC:1.3:CRS84" } },
"features": [
{ "type": "Feature", "properties": { "point_type": "origin", "points_str": "45.523033, -122.605849" }, "geometry": { "type": "Point", "coordinates": [ -122.605848583254087, 45.523033428900291 ] } },
{ "type": "Feature", "properties": { "point_type": "destination", "points_str": "45.526682, -122.709511" }, "geometry": { "type": "Point", "coordinates": [ -122.709510685161604, 45.526682030099934 ] } }
]
}
