{
"type": "FeatureCollection",
"crs": { "type": "name", "properties": { "name": "urn:ogc:def:crs:OGC:1.3:CRS84" } },
"features": [
{ "type": "Feature", "properties": { "point_type": "origin", "points_str": "45.443569, -122.649928" }, "geometry": { "type": "Point", "coordinates": [ -122.649927567126056, 45.443568584295548 ] } },
{ "type": "Feature", "properties": { "point_type": "destination", "points_str": "45.586455, -122.712154" }, "geometry": { "type": "Point", "coordinates": [ -122.712154247692482, 45.586454628299109 ] } }
]
}
