{
"type": "FeatureCollection",
"name": "origin_destination_points",
"crs": { "type": "name", "properties": { "name": "urn:ogc:def:crs:OGC:1.3:CRS84" } },
"features": [
{ "type": "Feature", "properties": { "point_type": "origin", "points_str": "45.449421, -122.582765" }, "geometry": { "type": "Point", "coordinates": [ -122.582765260170163, 45.449420763122795 ] } },
{ "type": "Feature", "properties": { "point_type": "destination", "points_str": "45.51848, -122.757224" }, "geometry": { "type": "Point", "coordinates": [ -122.757223653795421, 45.518479629158954 ] } }
]
}
