{
"type": "FeatureCollection",
"crs": { "type": "name", "properties": { "name": "urn:ogc:def:crs:OGC:1.3:CRS84" } },
"features": [
{ "type": "Feature", "properties": { "point_type": "origin", "points_str": "45.600387, -122.67368" }, "geometry": { "type": "Point", "coordinates": [ -122.673679667432879, 45.60038681965213 ] } },
{ "type": "Feature", "properties": { "point_type": "destination", "points_str": "45.500491, -122.678805" }, "geometry": { "type": "Point", "coordinates": [ -122.678804759583059, 45.500491497400006 ] } }
]
}
