{
"type": "FeatureCollection",
"name": "origin_destination_points",
"crs": { "type": "name", "properties": { "name": "urn:ogc:def:crs:OGC:1.3:CRS84" } },
"features": [
{ "type": "Feature", "properties": { "point_type": "origin", "points_str": "45.546638, -122.455005" }, "geometry": { "type": "Point", "coordinates": [ -122.455004813991607, 45.546638145791199 ] } },
{ "type": "Feature", "properties": { "point_type": "destination", "points_str": "45.55528, -122.557433" }, "geometry": { "type": "Point", "coordinates": [ -122.557432643599697, 45.555279533183423 ] } }
]
}
