{
"type": "FeatureCollection",
"crs": { "type": "name", "properties": { "name": "urn:ogc:def:crs:OGC:1.3:CRS84" } },
"features": [
{ "type": "Feature", "properties": { "point_type": "origin", "points_str": "45.540689, -122.711361" }, "geometry": { "type": "Point", "coordinates": [ -122.71136099926602, 45.540688829210012 ] } },
{ "type": "Feature", "properties": { "point_type": "destination", "points_str": "45.500382, -122.546044" }, "geometry": { "type": "Point", "coordinates": [ -122.546044075762609, 45.500381903705986 ] } }
]
}
