{
"type": "FeatureCollection",
"name": "origin_destination_points",
"crs": { "type": "name", "properties": { "name": "urn:ogc:def:crs:OGC:1.3:CRS84" } },
"features": [
{ "type": "Feature", "properties": { "point_type": "origin", "points_str": "45.429059, -122.766477" }, "geometry": { "type": "Point", "coordinates": [ -122.766477454757734, 45.429058939830945 ] } },
{ "type": "Feature", "properties": { "point_type": "destination", "points_str": "45.576083, -122.723449" }, "geometry": { "type": "Point", "coordinates": [ -122.723449094043886, 45.576082763867859 ] } }
]
}
