{
"type": "FeatureCollection",
"crs": { "type": "name", "properties": { "name": "urn:ogc:def:crs:OGC:1.3:CRS84" } },
"features": [
{ "type": "Feature", "properties": { "point_type": "origin", "points_str": "45.484167, -122.572929" }, "geometry": { "type": "Point", "coordinates": [ -122.572928641759049, 45.484167059881422 ] } },
{ "type": "Feature", "properties": { "point_type": "destination", "points_str": "45.475958, -122.618493" }, "geometry": { "type": "Point", "coordinates": [ -122.618493283837992, 45.475957750146868 ] } }
]
}
