{
"type": "FeatureCollection",
"name": "origin_destination_points",
"crs": { "type": "name", "properties": { "name": "urn:ogc:def:crs:OGC:1.3:CRS84" } },
"features": [
{ "type": "Feature", "properties": { "point_type": "origin", "points_str": "45.522966, -122.673089" }, "geometry": { "type": "Point", "coordinates": [ -122.673088925924247, 45.522965669134059 ] } },
{ "type": "Feature", "properties": { "point_type": "destination", "points_str": "45.576297, -122.716937" }, "geometry": { "type": "Point", "coordinates": [ -122.716936939144972, 45.576297114536693 ] } }
]
}
