{
"type": "FeatureCollection",
"crs": { "type": "name", "properties": { "name": "urn:ogc:def:crs:OGC:1.3:CRS84" } },
"features": [
{ "type": "Feature", "properties": { "point_type": "origin", "points_str": "45.415321, -122.633895" }, "geometry": { "type": "Point", "coordinates": [ -122.633895420406617, 45.415321347633608 ] } },
{ "type": "Feature", "properties": { "point_type": "destination", "points_str": "45.452472, -122.598291" }, "geometry": { "type": "Point", "coordinates": [ -122.598291446501321, 45.45247154395436 ] } }
]
}
