{
"type": "FeatureCollection",
"name": "origin_destination_points",
"crs": { "type": "name", "properties": { "name": "urn:ogc:def:crs:OGC:1.3:CRS84" } },
"features": [
{ "type": "Feature", "properties": { "point_type": "origin", "points_str": "45.553698, -122.574957" }, "geometry": { "type": "Point", "coordinates": [ -122.574956880148122, 45.553697747072803 ] } },
{ "type": "Feature", "properties": { "point_type": "destination", "points_str": "45.588505, -122.662184" }, "geometry": { "type": "Point", "coordinates": [ -122.662184180293195, 45.588505170803693 ] } }
]
}
