{
"type": "FeatureCollection",
"name": "origin_destination_points",
"crs": { "type": "name", "properties": { "name": "urn:ogc:def:crs:OGC:1.3:CRS84" } },
"features": [
{ "type": "Feature", "properties": { "point_type": "origin", "points_str": "45.445018, -122.757028" }, "geometry": { "type": "Point", "coordinates": [ -122.757028261190797, 45.445018375202501 ] } },
{ "type": "Feature", "properties": { "point_type": "destination", "points_str": "45.463764, -122.687353" }, "geometry": { "type": "Point", "coordinates": [ -122.68735266224661, 45.463763594645549 ] } }
]
}
