{
"type": "FeatureCollection",
"crs": { "type": "name", "properties": { "name": "urn:ogc:def:crs:OGC:1.3:CRS84" } },
"features": [
{ "type": "Feature", "properties": { "point_type": "origin", "points_str": "45.548517, -122.896624" }, "geometry": { "type": "Point", "coordinates": [ -122.896624119987067, 45.548516989926945 ] } },
{ "type": "Feature", "properties": { "point_type": "destination", "points_str": "45.522067, -122.680335" }, "geometry": { "type": "Point", "coordinates": [ -122.680335196572557, 45.522066563335557 ] } }
]
}
