{
"type": "FeatureCollection",
"crs": { "type": "name", "properties": { "name": "urn:ogc:def:crs:OGC:1.3:CRS84" } },
"features": [
{ "type": "Feature", "properties": { "point_type": "origin", "points_str": "45.436993, -122.78008" }, "geometry": { "type": "Point", "coordinates": [ -122.780079705435327, 45.436993382639322 ] } },
{ "type": "Feature", "properties": { "point_type": "destination", "points_str": "45.464809, -122.847837" }, "geometry": { "type": "Point", "coordinates": [ -122.847837441444284, 45.464808917855521 ] } }
]
}
