{
"type": "FeatureCollection",
"name": "origin_destination_points",
"crs": { "type": "name", "properties": { "name": "urn:ogc:def:crs:OGC:1.3:CRS84" } },
"features": [
{ "type": "Feature", "properties": { "point_type": "origin", "points_str": "45.42116, -122.555187" }, "geometry": { "type": "Point", "coordinates": [ -122.555186681721878, 45.421159641147909 ] } },
{ "type": "Feature", "properties": { "point_type": "destination", "points_str": "45.302566, -122.339049" }, "geometry": { "type": "Point", "coordinates": [ -122.339049076039402, 45.302565938286435 ] } }
]
}
