{
"type": "FeatureCollection",
"name": "origin_destination_points",
"crs": { "type": "name", "properties": { "name": "urn:ogc:def:crs:OGC:1.3:CRS84" } },
"features": [
{ "type": "Feature", "properties": { "point_type": "origin", "points_str": "45.481406, -122.585154" }, "geometry": { "type": "Point", "coordinates": [ -122.585154252617755, 45.481405620377622 ] } },
{ "type": "Feature", "properties": { "point_type": "destination", "points_str": "45.508776, -122.610914" }, "geometry": { "type": "Point", "coordinates": [ -122.61091419878025, 45.508776403131883 ] } }
]
}
