{
"type": "FeatureCollection",
"name": "origin_destination_points",
"crs": { "type": "name", "properties": { "name": "urn:ogc:def:crs:OGC:1.3:CRS84" } },
"features": [
{ "type": "Feature", "properties": { "point_type": "origin", "points_str": "45.518734, -123.091804" }, "geometry": { "type": "Point", "coordinates": [ -123.091804057091039, 45.518734174775815 ] } },
{ "type": "Feature", "properties": { "point_type": "destination", "points_str": "45.536375, -122.958307" }, "geometry": { "type": "Point", "coordinates": [ -122.95830669913552, 45.536375426406352 ] } }
]
}
