{
"type": "FeatureCollection",
"name": "origin_destination_points",
"crs": { "type": "name", "properties": { "name": "urn:ogc:def:crs:OGC:1.3:CRS84" } },
"features": [
{ "type": "Feature", "properties": { "point_type": "origin", "points_str": "45.527034, -122.630006" }, "geometry": { "type": "Point", "coordinates": [ -122.630006389519053, 45.527033881563355 ] } },
{ "type": "Feature", "properties": { "point_type": "destination", "points_str": "45.50121, -122.606881" }, "geometry": { "type": "Point", "coordinates": [ -122.606881258748516, 45.501209663849899 ] } }
]
}
