{
"type": "FeatureCollection",
"name": "origin_destination_points",
"crs": { "type": "name", "properties": { "name": "urn:ogc:def:crs:OGC:1.3:CRS84" } },
"features": [
{ "type": "Feature", "properties": { "point_type": "origin", "points_str": "45.529492, -122.594371" }, "geometry": { "type": "Point", "coordinates": [ -122.594371065698112, 45.52949207092967 ] } },
{ "type": "Feature", "properties": { "point_type": "destination", "points_str": "45.475195, -122.627433" }, "geometry": { "type": "Point", "coordinates": [ -122.627433487554256, 45.475194946035771 ] } }
]
}
