{
"type": "FeatureCollection",
"name": "origin_destination_points",
"crs": { "type": "name", "properties": { "name": "urn:ogc:def:crs:OGC:1.3:CRS84" } },
"features": [
{ "type": "Feature", "properties": { "point_type": "origin", "points_str": "45.412068, -122.566824" }, "geometry": { "type": "Point", "coordinates": [ -122.566823972193248, 45.412067989818986 ] } },
{ "type": "Feature", "properties": { "point_type": "destination", "points_str": "45.429471, -122.559355" }, "geometry": { "type": "Point", "coordinates": [ -122.559355027122095, 45.42947133876585 ] } }
]
}
