{
"type": "FeatureCollection",
"name": "origin_destination_points",
"crs": { "type": "name", "properties": { "name": "urn:ogc:def:crs:OGC:1.3:CRS84" } },
"features": [
{ "type": "Feature", "properties": { "point_type": "origin", "points_str": "45.57389, -122.7" }, "geometry": { "type": "Point", "coordinates": [ -122.700000032988584, 45.573889613653982 ] } },
{ "type": "Feature", "properties": { "point_type": "destination", "points_str": "45.457492, -122.712604" }, "geometry": { "type": "Point", "coordinates": [ -122.712603857863172, 45.457492147533671 ] } }
]
}
