{
"type": "FeatureCollection",
"name": "origin_destination_points",
"crs": { "type": "name", "properties": { "name": "urn:ogc:def:crs:OGC:1.3:CRS84" } },
"features": [
{ "type": "Feature", "properties": { "point_type": "origin", "points_str": "45.569969, -122.646643" }, "geometry": { "type": "Point", "coordinates": [ -122.646642833318367, 45.569968991293543 ] } },
{ "type": "Feature", "properties": { "point_type": "destination", "points_str": "45.506951, -122.49977" }, "geometry": { "type": "Point", "coordinates": [ -122.49977020498153, 45.506951254673261 ] } }
]
}
