{
"type": "FeatureCollection",
"name": "origin_destination_points",
"crs": { "type": "name", "properties": { "name": "urn:ogc:def:crs:OGC:1.3:CRS84" } },
"features": [
{ "type": "Feature", "properties": { "point_type": "origin", "points_str": "45.497249, -122.682088" }, "geometry": { "type": "Point", "coordinates": [ -122.682087546163416, 45.497249374870442 ] } },
{ "type": "Feature", "properties": { "point_type": "destination", "points_str": "45.495288, -122.640115" }, "geometry": { "type": "Point", "coordinates": [ -122.640114986176656, 45.495287871266569 ] } }
]
}
