{
"type": "FeatureCollection",
"name": "origin_destination_points",
"crs": { "type": "name", "properties": { "name": "urn:ogc:def:crs:OGC:1.3:CRS84" } },
"features": [
{ "type": "Feature", "properties": { "point_type": "origin", "points_str": "45.558938, -122.664612" }, "geometry": { "type": "Point", "coordinates": [ -122.664611544837967, 45.558938376062514 ] } },
{ "type": "Feature", "properties": { "point_type": "destination", "points_str": "45.556255, -122.62785" }, "geometry": { "type": "Point", "coordinates": [ -122.627850102384883, 45.556254702902066 ] } }
]
}
