{
"type": "FeatureCollection",
"name": "origin_destination_points",
"crs": { "type": "name", "properties": { "name": "urn:ogc:def:crs:OGC:1.3:CRS84" } },
"features": [
{ "type": "Feature", "properties": { "point_type": "origin", "points_str": "45.587679, -122.594877" }, "geometry": { "type": "Point", "coordinates": [ -122.594876751807377, 45.587678755167602 ] } },
{ "type": "Feature", "properties": { "point_type": "destination", "points_str": "45.57556, -122.650664" }, "geometry": { "type": "Point", "coordinates": [ -122.650664103238597, 45.575559926721539 ] } }
]
}
