{
"type": "FeatureCollection",
"name": "origin_destination_points",
"crs": { "type": "name", "properties": { "name": "urn:ogc:def:crs:OGC:1.3:CRS84" } },
"features": [
{ "type": "Feature", "properties": { "point_type": "origin", "points_str": "45.534019, -122.618737" }, "geometry": { "type": "Point", "coordinates": [ -122.618737046067565, 45.534018996575796 ] } },
{ "type": "Feature", "properties": { "point_type": "destination", "points_str": "45.501735, -122.586547" }, "geometry": { "type": "Point", "coordinates": [ -122.586547307178606, 45.501734561516024 ] } }
]
}
