{
"type": "FeatureCollection",
"name": "origin_destination_points",
"crs": { "type": "name", "properties": { "name": "urn:ogc:def:crs:OGC:1.3:CRS84" } },
"features": [
{ "type": "Feature", "properties": { "point_type": "origin", "points_str": "45.350337, -122.586216" }, "geometry": { "type": "Point", "coordinates": [ -122.586215792324751, 45.350336713927462 ] } },
{ "type": "Feature", "properties": { "point_type": "destination", "points_str": "45.418723, -122.623289" }, "geometry": { "type": "Point", "coordinates": [ -122.623288855366454, 45.418723042623242 ] } }
]
}
