{
"type": "FeatureCollection",
"name": "origin_destination_points",
"crs": { "type": "name", "properties": { "name": "urn:ogc:def:crs:OGC:1.3:CRS84" } },
"features": [
{ "type": "Feature", "properties": { "point_type": "origin", "points_str": "45.420906, -122.675819" }, "geometry": { "type": "Point", "coordinates": [ -122.675818759026455, 45.420905780695463 ] } },
{ "type": "Feature", "properties": { "point_type": "destination", "points_str": "45.518067, -123.067715" }, "geometry": { "type": "Point", "coordinates": [ -123.067715467545938, 45.518066895321347 ] } }
]
}
