{
"type": "FeatureCollection",
"crs": { "type": "name", "properties": { "name": "urn:ogc:def:crs:OGC:1.3:CRS84" } },
"features": [
{ "type": "Feature", "properties": { "point_type": "origin", "points_str": "45.487111, -122.604341" }, "geometry": { "type": "Point", "coordinates": [ -122.604340619956815, 45.487111180090238 ] } },
{ "type": "Feature", "properties": { "point_type": "destination", "points_str": "45.47976, -122.666741" }, "geometry": { "type": "Point", "coordinates": [ -122.666740674122593, 45.479760476069217 ] } }
]
}
