{
"type": "FeatureCollection",
"name": "origin_destination_points",
"crs": { "type": "name", "properties": { "name": "urn:ogc:def:crs:OGC:1.3:CRS84" } },
"features": [
{ "type": "Feature", "properties": { "point_type": "origin", "points_str": "45.586175, -122.722832" }, "geometry": { "type": "Point", "coordinates": [ -122.722831770612601, 45.586175413984087 ] } },
{ "type": "Feature", "properties": { "point_type": "destination", "points_str": "45.535179, -122.595442" }, "geometry": { "type": "Point", "coordinates": [ -122.595441792654725, 45.535178869343319 ] } }
]
}
