{
"type": "FeatureCollection",
"name": "origin_destination_points",
"crs": { "type": "name", "properties": { "name": "urn:ogc:def:crs:OGC:1.3:CRS84" } },
"features": [
{ "type": "Feature", "properties": { "point_type": "origin", "points_str": "45.53209, -122.647473" }, "geometry": { "type": "Point", "coordinates": [ -122.647473286733756, 45.53208974996717 ] } },
{ "type": "Feature", "properties": { "point_type": "destination", "points_str": "45.453013, -122.720754" }, "geometry": { "type": "Point", "coordinates": [ -122.720754372510001, 45.453013233405379 ] } }
]
}
