{
"type": "FeatureCollection",
"crs": { "type": "name", "properties": { "name": "urn:ogc:def:crs:OGC:1.3:CRS84" } },
"features": [
{ "type": "Feature", "properties": { "point_type": "origin", "points_str": "45.510343, -122.643687" }, "geometry": { "type": "Point", "coordinates": [ -122.643687261094328, 45.510342612687054 ] } },
{ "type": "Feature", "properties": { "point_type": "destination", "points_str": "45.520277, -122.870135" }, "geometry": { "type": "Point", "coordinates": [ -122.870135471031787, 45.520277077155185 ] } }
]
}
