{
"type": "FeatureCollection",
"name": "origin_destination_points",
"crs": { "type": "name", "properties": { "name": "urn:ogc:def:crs:OGC:1.3:CRS84" } },
"features": [
{ "type": "Feature", "properties": { "point_type": "origin", "points_str": "45.513569, -122.677133" }, "geometry": { "type": "Point", "coordinates": [ -122.677133168601571, 45.513569371634979 ] } },
{ "type": "Feature", "properties": { "point_type": "destination", "points_str": "45.395274, -122.61483" }, "geometry": { "type": "Point", "coordinates": [ -122.614830170605146, 45.395273857796091 ] } }
]
}
