{
"type": "FeatureCollection",
"crs": { "type": "name", "properties": { "name": "urn:ogc:def:crs:OGC:1.3:CRS84" } },
"features": [
{ "type": "Feature", "properties": { "point_type": "origin", "points_str": "45.521922, -122.68144" }, "geometry": { "type": "Point", "coordinates": [ -122.681439720116046, 45.521921770075501 ] } },
{ "type": "Feature", "properties": { "point_type": "destination", "points_str": "45.496822, -122.523147" }, "geometry": { "type": "Point", "coordinates": [ -122.523146666578654, 45.496821769614506 ] } }
]
}
