{
"type": "FeatureCollection",
"crs": { "type": "name", "properties": { "name": "urn:ogc:def:crs:OGC:1.3:CRS84" } },
"features": [
{ "type": "Feature", "properties": { "point_type": "origin", "points_str": "45.505309, -122.402677" }, "geometry": { "type": "Point", "coordinates": [ -122.402677456252093, 45.50530866138908 ] } },
{ "type": "Feature", "properties": { "point_type": "destination", "points_str": "45.493559, -122.454658" }, "geometry": { "type": "Point", "coordinates": [ -122.454658438696001, 45.493558888967584 ] } }
]
}
