{
"type": "FeatureCollection",
"name": "origin_destination_points",
"crs": { "type": "name", "properties": { "name": "urn:ogc:def:crs:OGC:1.3:CRS84" } },
"features": [
{ "type": "Feature", "properties": { "point_type": "origin", "points_str": "45.524535, -123.073757" }, "geometry": { "type": "Point", "coordinates": [ -123.073757352397777, 45.524535305221562 ] } },
{ "type": "Feature", "properties": { "point_type": "destination", "points_str": "45.467005, -122.841288" }, "geometry": { "type": "Point", "coordinates": [ -122.841287554985414, 45.467004523520394 ] } }
]
}
