{
"type": "FeatureCollection",
"crs": { "type": "name", "properties": { "name": "urn:ogc:def:crs:OGC:1.3:CRS84" } },
"features": [
{ "type": "Feature", "properties": { "point_type": "origin", "points_str": "45.521656, -122.469232" }, "geometry": { "type": "Point", "coordinates": [ -122.469232362163936, 45.521655567469473 ] } },
{ "type": "Feature", "properties": { "point_type": "destination", "points_str": "45.538313, -122.389107" }, "geometry": { "type": "Point", "coordinates": [ -122.389106935719568, 45.538313095447876 ] } }
]
}
