{
"type": "FeatureCollection",
"crs": { "type": "name", "properties": { "name": "urn:ogc:def:crs:OGC:1.3:CRS84" } },
"features": [
{ "type": "Feature", "properties": { "point_type": "origin", "points_str": "45.526824, -122.994511" }, "geometry": { "type": "Point", "coordinates": [ -122.99451098755425, 45.526824428641653 ] } },
{ "type": "Feature", "properties": { "point_type": "destination", "points_str": "45.346085, -122.788356" }, "geometry": { "type": "Point", "coordinates": [ -122.788355703310742, 45.346084935674703 ] } }
]
}
