{
"type": "FeatureCollection",
"name": "origin_destination_points",
"crs": { "type": "name", "properties": { "name": "urn:ogc:def:crs:OGC:1.3:CRS84" } },
"features": [
{ "type": "Feature", "properties": { "point_type": "origin", "points_str": "45.484352, -122.625911" }, "geometry": { "type": "Point", "coordinates": [ -122.625911071407216, 45.484351624279824 ] } },
{ "type": "Feature", "properties": { "point_type": "destination", "points_str": "45.519227, -122.728157" }, "geometry": { "type": "Point", "coordinates": [ -122.728156809429422, 45.519226886265137 ] } }
]
}
