{
"type": "FeatureCollection",
"name": "origin_destination_points",
"crs": { "type": "name", "properties": { "name": "urn:ogc:def:crs:OGC:1.3:CRS84" } },
"features": [
{ "type": "Feature", "properties": { "point_type": "origin", "points_str": "45.464052, -122.582064" }, "geometry": { "type": "Point", "coordinates": [ -122.582063925062954, 45.464051730645188 ] } },
{ "type": "Feature", "properties": { "point_type": "destination", "points_str": "45.569183, -122.616704" }, "geometry": { "type": "Point", "coordinates": [ -122.616704406561553, 45.569182510125287 ] } }
]
}
