{
"type": "FeatureCollection",
"name": "origin_destination_points",
"crs": { "type": "name", "properties": { "name": "urn:ogc:def:crs:OGC:1.3:CRS84" } },
"features": [
{ "type": "Feature", "properties": { "point_type": "origin", "points_str": "45.449238, -122.657155" }, "geometry": { "type": "Point", "coordinates": [ -122.657154911904314, 45.449238185122162 ] } },
{ "type": "Feature", "properties": { "point_type": "destination", "points_str": "45.515285, -122.746081" }, "geometry": { "type": "Point", "coordinates": [ -122.746080868717513, 45.515285165367757 ] } }
]
}
