{
"type": "FeatureCollection",
"name": "origin_destination_points",
"crs": { "type": "name", "properties": { "name": "urn:ogc:def:crs:OGC:1.3:CRS84" } },
"features": [
{ "type": "Feature", "properties": { "point_type": "origin", "points_str": "45.456295, -122.684505" }, "geometry": { "type": "Point", "coordinates": [ -122.684504542950123, 45.456294625717916 ] } },
{ "type": "Feature", "properties": { "point_type": "destination", "points_str": "45.496527, -122.434882" }, "geometry": { "type": "Point", "coordinates": [ -122.434881842787732, 45.496526940539461 ] } }
]
}
