{
"type": "FeatureCollection",
"name": "origin_destination_points",
"crs": { "type": "name", "properties": { "name": "urn:ogc:def:crs:OGC:1.3:CRS84" } },
"features": [
{ "type": "Feature", "properties": { "point_type": "origin", "points_str": "45.500672, -122.559821" }, "geometry": { "type": "Point", "coordinates": [ -122.559821016166268, 45.500672366569454 ] } },
{ "type": "Feature", "properties": { "point_type": "destination", "points_str": "45.577574, -122.725693" }, "geometry": { "type": "Point", "coordinates": [ -122.725692557534813, 45.577573825070139 ] } }
]
}
