{
"type": "FeatureCollection",
"name": "origin_destination_points",
"crs": { "type": "name", "properties": { "name": "urn:ogc:def:crs:OGC:1.3:CRS84" } },
"features": [
{ "type": "Feature", "properties": { "point_type": "origin", "points_str": "45.595912, -122.783738" }, "geometry": { "type": "Point", "coordinates": [ -122.783738173688477, 45.595912381965839 ] } },
{ "type": "Feature", "properties": { "point_type": "destination", "points_str": "45.439482, -122.759214" }, "geometry": { "type": "Point", "coordinates": [ -122.759214397751634, 45.43948173145192 ] } }
]
}
