{
"type": "FeatureCollection",
"name": "origin_destination_points",
"crs": { "type": "name", "properties": { "name": "urn:ogc:def:crs:OGC:1.3:CRS84" } },
"features": [
{ "type": "Feature", "properties": { "point_type": "origin", "points_str": "45.450512, -122.76772" }, "geometry": { "type": "Point", "coordinates": [ -122.767720439055253, 45.450512449559447 ] } },
{ "type": "Feature", "properties": { "point_type": "destination", "points_str": "45.402391, -122.766581" }, "geometry": { "type": "Point", "coordinates": [ -122.766581040511483, 45.402390624382505 ] } }
]
}
