{
"type": "FeatureCollection",
"name": "origin_destination_points",
"crs": { "type": "name", "properties": { "name": "urn:ogc:def:crs:OGC:1.3:CRS84" } },
"features": [
{ "type": "Feature", "properties": { "point_type": "origin", "points_str": "45.570935, -122.619864" }, "geometry": { "type": "Point", "coordinates": [ -122.619863873416591, 45.570934778980636 ] } },
{ "type": "Feature", "properties": { "point_type": "destination", "points_str": "45.57313, -122.554505" }, "geometry": { "type": "Point", "coordinates": [ -122.554504634432377, 45.573130420519782 ] } }
]
}
