{
"type": "FeatureCollection",
"name": "origin_destination_points",
"crs": { "type": "name", "properties": { "name": "urn:ogc:def:crs:OGC:1.3:CRS84" } },
"features": [
{ "type": "Feature", "properties": { "point_type": "origin", "points_str": "45.463328, -122.685904" }, "geometry": { "type": "Point", "coordinates": [ -122.68590433821592, 45.463328228785628 ] } },
{ "type": "Feature", "properties": { "point_type": "destination", "points_str": "45.36346, -122.582107" }, "geometry": { "type": "Point", "coordinates": [ -122.582107374591217, 45.363460118741749 ] } }
]
}
