{
"type": "FeatureCollection",
"name": "origin_destination_points",
"crs": { "type": "name", "properties": { "name": "urn:ogc:def:crs:OGC:1.3:CRS84" } },
"features": [
{ "type": "Feature", "properties": { "point_type": "origin", "points_str": "45.547679, -122.702117" }, "geometry": { "type": "Point", "coordinates": [ -122.702117116032767, 45.54767917630064 ] } },
{ "type": "Feature", "properties": { "point_type": "destination", "points_str": "45.587198, -122.699901" }, "geometry": { "type": "Point", "coordinates": [ -122.699900824770538, 45.58719773362364 ] } }
]
}
