{
"type": "FeatureCollection",
"crs": { "type": "name", "properties": { "name": "urn:ogc:def:crs:OGC:1.3:CRS84" } },
"features": [
{ "type": "Feature", "properties": { "point_type": "origin", "points_str": "45.487373, -122.728813" }, "geometry": { "type": "Point", "coordinates": [ -122.728813123305514, 45.487373388082062 ] } },
{ "type": "Feature", "properties": { "point_type": "destination", "points_str": "45.524611, -122.647029" }, "geometry": { "type": "Point", "coordinates": [ -122.647028965386085, 45.524611022407463 ] } }
]
}
