{
"type": "FeatureCollection",
"name": "origin_destination_points",
"crs": { "type": "name", "properties": { "name": "urn:ogc:def:crs:OGC:1.3:CRS84" } },
"features": [
{ "type": "Feature", "properties": { "point_type": "origin", "points_str": "45.572155, -122.661841" }, "geometry": { "type": "Point", "coordinates": [ -122.661840628471097, 45.572155441042121 ] } },
{ "type": "Feature", "properties": { "point_type": "destination", "points_str": "45.520753, -122.582869" }, "geometry": { "type": "Point", "coordinates": [ -122.582869437061163, 45.520753439368526 ] } }
]
}
