{
"type": "FeatureCollection",
"name": "origin_destination_points",
"crs": { "type": "name", "properties": { "name": "urn:ogc:def:crs:OGC:1.3:CRS84" } },
"features": [
{ "type": "Feature", "properties": { "point_type": "origin", "points_str": "45.531829, -122.924342" }, "geometry": { "type": "Point", "coordinates": [ -122.924342260190699, 45.531829195696154 ] } },
{ "type": "Feature", "properties": { "point_type": "destination", "points_str": "45.527862, -122.846578" }, "geometry": { "type": "Point", "coordinates": [ -122.846577792914132, 45.52786185655507 ] } }
]
}
