{
"type": "FeatureCollection",
"name": "origin_destination_points",
"crs": { "type": "name", "properties": { "name": "urn:ogc:def:crs:OGC:1.3:CRS84" } },
"features": [
{ "type": "Feature", "properties": { "point_type": "origin", "points_str": "45.532816, -122.612004" }, "geometry": { "type": "Point", "coordinates": [ -122.612004047504399, 45.532816295818982 ] } },
{ "type": "Feature", "properties": { "point_type": "destination", "points_str": "45.574718, -122.683847" }, "geometry": { "type": "Point", "coordinates": [ -122.683847417570576, 45.574717627096099 ] } }
]
}
