{
"type": "FeatureCollection",
"name": "origin_destination_points",
"crs": { "type": "name", "properties": { "name": "urn:ogc:def:crs:OGC:1.3:CRS84" } },
"features": [
{ "type": "Feature", "properties": { "point_type": "origin", "points_str": "45.533255, -122.707587" }, "geometry": { "type": "Point", "coordinates": [ -122.707586980158737, 45.533254644693542 ] } },
{ "type": "Feature", "properties": { "point_type": "destination", "points_str": "45.457809, -122.648758" }, "geometry": { "type": "Point", "coordinates": [ -122.648758263719714, 45.457808786939935 ] } }
]
}
