{
"type": "FeatureCollection",
"name": "origin_destination_points",
"crs": { "type": "name", "properties": { "name": "urn:ogc:def:crs:OGC:1.3:CRS84" } },
"features": [
{ "type": "Feature", "properties": { "point_type": "origin", "points_str": "45.512777, -122.789765" }, "geometry": { "type": "Point", "coordinates": [ -122.789764771216852, 45.512776822522035 ] } },
{ "type": "Feature", "properties": { "point_type": "destination", "points_str": "45.534641, -122.852767" }, "geometry": { "type": "Point", "coordinates": [ -122.852766918075773, 45.53464120397598 ] } }
]
}
