{
"type": "FeatureCollection",
"name": "origin_destination_points",
"crs": { "type": "name", "properties": { "name": "urn:ogc:def:crs:OGC:1.3:CRS84" } },
"features": [
{ "type": "Feature", "properties": { "point_type": "origin", "points_str": "45.505747, -122.67004" }, "geometry": { "type": "Point", "coordinates": [ -122.670040353042268, 45.505746521791401 ] } },
{ "type": "Feature", "properties": { "point_type": "destination", "points_str": "45.50551, -122.400424" }, "geometry": { "type": "Point", "coordinates": [ -122.400424259874086, 45.505509678376121 ] } }
]
}
