{
"type": "FeatureCollection",
"name": "origin_destination_points",
"crs": { "type": "name", "properties": { "name": "urn:ogc:def:crs:OGC:1.3:CRS84" } },
"features": [
{ "type": "Feature", "properties": { "point_type": "origin", "points_str": "45.531713, -122.491676" }, "geometry": { "type": "Point", "coordinates": [ -122.49167567985522, 45.531713190375356 ] } },
{ "type": "Feature", "properties": { "point_type": "destination", "points_str": "45.514884, -122.452739" }, "geometry": { "type": "Point", "coordinates": [ -122.452738679916848, 45.514884185157491 ] } }
]
}
