{
"type": "FeatureCollection",
"name": "origin_destination_points",
"crs": { "type": "name", "properties": { "name": "urn:ogc:def:crs:OGC:1.3:CRS84" } },
"features": [
{ "type": "Feature", "properties": { "point_type": "origin", "points_str": "45.47774, -122.849539" }, "geometry": { "type": "Point", "coordinates": [ -122.849538948534814, 45.477739770903234 ] } },
{ "type": "Feature", "properties": { "point_type": "destination", "points_str": "45.519614, -122.974174" }, "geometry": { "type": "Point", "coordinates": [ -122.974173530300362, 45.519613641704197 ] } }
]
}
