{
"type": "FeatureCollection",
"name": "origin_destination_points",
"crs": { "type": "name", "properties": { "name": "urn:ogc:def:crs:OGC:1.3:CRS84" } },
"features": [
{ "type": "Feature", "properties": { "point_type": "origin", "points_str": "45.501174, -122.617506" }, "geometry": { "type": "Point", "coordinates": [ -122.617505895417011, 45.501174017237282 ] } },
{ "type": "Feature", "properties": { "point_type": "destination", "points_str": "45.394916, -122.653159" }, "geometry": { "type": "Point", "coordinates": [ -122.653158811141637, 45.394916290649924 ] } }
]
}
