{
"type": "FeatureCollection",
"crs": { "type": "name", "properties": { "name": "urn:ogc:def:crs:OGC:1.3:CRS84" } },
"features": [
{ "type": "Feature", "properties": { "point_type": "origin", "points_str": "45.559513, -122.643043" }, "geometry": { "type": "Point", "coordinates": [ -122.643042844470159, 45.559512576840724 ] } },
{ "type": "Feature", "properties": { "point_type": "destination", "points_str": "45.52192, -122.586732" }, "geometry": { "type": "Point", "coordinates": [ -122.586732250110586, 45.521919794465603 ] } }
]
}
