{
"type": "FeatureCollection",
"name": "origin_destination_points",
"crs": { "type": "name", "properties": { "name": "urn:ogc:def:crs:OGC:1.3:CRS84" } },
"features": [
{ "type": "Feature", "properties": { "point_type": "origin", "points_str": "45.350424, -122.584443" }, "geometry": { "type": "Point", "coordinates": [ -122.584442628274118, 45.350424391596881 ] } },
{ "type": "Feature", "properties": { "point_type": "destination", "points_str": "45.337546, -122.605109" }, "geometry": { "type": "Point", "coordinates": [ -122.60510862172552, 45.337545718516829 ] } }
]
}
