{
"type": "FeatureCollection",
"name": "origin_destination_points",
"crs": { "type": "name", "properties": { "name": "urn:ogc:def:crs:OGC:1.3:CRS84" } },
"features": [
{ "type": "Feature", "properties": { "point_type": "origin", "points_str": "45.504518, -122.534801" }, "geometry": { "type": "Point", "coordinates": [ -122.534801428488507, 45.504517981568796 ] } },
{ "type": "Feature", "properties": { "point_type": "destination", "points_str": "45.549685, -122.506846" }, "geometry": { "type": "Point", "coordinates": [ -122.506846392317001, 45.549685417620132 ] } }
]
}
