{
"type": "FeatureCollection",
"crs": { "type": "name", "properties": { "name": "urn:ogc:def:crs:OGC:1.3:CRS84" } },
"features": [
{ "type": "Feature", "properties": { "point_type": "origin", "points_str": "45.52886, -122.606975" }, "geometry": { "type": "Point", "coordinates": [ -122.606975297000943, 45.528860419753109 ] } },
{ "type": "Feature", "properties": { "point_type": "destination", "points_str": "45.500702, -122.491528" }, "geometry": { "type": "Point", "coordinates": [ -122.491527535043389, 45.500701928764265 ] } }
]
}
