{
"type": "FeatureCollection",
"crs": { "type": "name", "properties": { "name": "urn:ogc:def:crs:OGC:1.3:CRS84" } },
"features": [
{ "type": "Feature", "properties": { "point_type": "origin", "points_str": "45.486481, -122.733177" }, "geometry": { "type": "Point", "coordinates": [ -122.733176567653473, 45.486480969952446 ] } },
{ "type": "Feature", "properties": { "point_type": "destination", "points_str": "45.471282, -122.766973" }, "geometry": { "type": "Point", "coordinates": [ -122.766972614736389, 45.471281881339166 ] } }
]
}
