{
"type": "FeatureCollection",
"crs": { "type": "name", "properties": { "name": "urn:ogc:def:crs:OGC:1.3:CRS84" } },
"features": [
{ "type": "Feature", "properties": { "point_type": "origin", "points_str": "45.462757, -122.556105" }, "geometry": { "type": "Point", "coordinates": [ -122.556104522367605, 45.462756518698093 ] } },
{ "type": "Feature", "properties": { "point_type": "destination", "points_str": "45.441076, -122.753367" }, "geometry": { "type": "Point", "coordinates": [ -122.753367182503538, 45.441076043145088 ] } }
]
}
