{
"type": "FeatureCollection",
"name": "origin_destination_points",
"crs": { "type": "name", "properties": { "name": "urn:ogc:def:crs:OGC:1.3:CRS84" } },
"features": [
{ "type": "Feature", "properties": { "point_type": "origin", "points_str": "45.541584, -122.645106" }, "geometry": { "type": "Point", "coordinates": [ -122.645106470941343, 45.541584387895512 ] } },
{ "type": "Feature", "properties": { "point_type": "destination", "points_str": "45.548837, -122.586372" }, "geometry": { "type": "Point", "coordinates": [ -122.586372392662796, 45.548837217256498 ] } }
]
}
