{
"type": "FeatureCollection",
"name": "origin_destination_points",
"crs": { "type": "name", "properties": { "name": "urn:ogc:def:crs:OGC:1.3:CRS84" } },
"features": [
{ "type": "Feature", "properties": { "point_type": "origin", "points_str": "45.538032, -122.479744" }, "geometry": { "type": "Point", "coordinates": [ -122.479743768632403, 45.538031865630231 ] } },
{ "type": "Feature", "properties": { "point_type": "destination", "points_str": "45.529428, -122.437279" }, "geometry": { "type": "Point", "coordinates": [ -122.437278716133534, 45.529427604626768 ] } }
]
}
