{
"type": "FeatureCollection",
"name": "origin_destination_points",
"crs": { "type": "name", "properties": { "name": "urn:ogc:def:crs:OGC:1.3:CRS84" } },
"features": [
{ "type": "Feature", "properties": { "point_type": "origin", "points_str": "45.43038, -122.722487" }, "geometry": { "type": "Point", "coordinates": [ -122.722487486825031, 45.430380451271205 ] } },
{ "type": "Feature", "properties": { "point_type": "destination", "points_str": "45.368994, -122.84946" }, "geometry": { "type": "Point", "coordinates": [ -122.8494602188633, 45.368994260358086 ] } }
]
}
