{
"type": "FeatureCollection",
"name": "origin_destination_points",
"crs": { "type": "name", "properties": { "name": "urn:ogc:def:crs:OGC:1.3:CRS84" } },
"features": [
{ "type": "Feature", "properties": { "point_type": "origin", "points_str": "45.54658, -122.6078" }, "geometry": { "type": "Point", "coordinates": [ -122.60779997178004, 45.546580365437279 ] } },
{ "type": "Feature", "properties": { "point_type": "destination", "points_str": "45.545893, -122.642244" }, "geometry": { "type": "Point", "coordinates": [ -122.642244414765656, 45.545892575906386 ] } }
]
}
