{
"type": "FeatureCollection",
"name": "origin_destination_points",
"crs": { "type": "name", "properties": { "name": "urn:ogc:def:crs:OGC:1.3:CRS84" } },
"features": [
{ "type": "Feature", "properties": { "point_type": "origin", "points_str": "45.478312, -122.612241" }, "geometry": { "type": "Point", "coordinates": [ -122.612240751500835, 45.47831185575204 ] } },
{ "type": "Feature", "properties": { "point_type": "destination", "points_str": "45.546125, -122.718508" }, "geometry": { "type": "Point", "coordinates": [ -122.71850837227052, 45.546125303401837 ] } }
]
}
