{
"type": "FeatureCollection",
"name": "origin_destination_points",
"crs": { "type": "name", "properties": { "name": "urn:ogc:def:crs:OGC:1.3:CRS84" } },
"features": [
{ "type": "Feature", "properties": { "point_type": "origin", "points_str": "45.468582, -122.796858" }, "geometry": { "type": "Point", "coordinates": [ -122.796857752926329, 45.468582224885147 ] } },
{ "type": "Feature", "properties": { "point_type": "destination", "points_str": "45.516123, -123.090732" }, "geometry": { "type": "Point", "coordinates": [ -123.090731781351337, 45.516123170281446 ] } }
]
}
