{
"type": "FeatureCollection",
"crs": { "type": "name", "properties": { "name": "urn:ogc:def:crs:OGC:1.3:CRS84" } },
"features": [
{ "type": "Feature", "properties": { "point_type": "origin", "points_str": "45.517748, -122.82057" }, "geometry": { "type": "Point", "coordinates": [ -122.820570478589374, 45.517748198438547 ] } },
{ "type": "Feature", "properties": { "point_type": "destination", "points_str": "45.462383, -122.842569" }, "geometry": { "type": "Point", "coordinates": [ -122.842569483493136, 45.462383212709391 ] } }
]
}
