{
"type": "FeatureCollection",
"crs": { "type": "name", "properties": { "name": "urn:ogc:def:crs:OGC:1.3:CRS84" } },
"features": [
{ "type": "Feature", "properties": { "point_type": "origin", "points_str": "45.535367, -122.611754" }, "geometry": { "type": "Point", "coordinates": [ -122.611754275801616, 45.535367372827025 ] } },
{ "type": "Feature", "properties": { "point_type": "destination", "points_str": "45.489882, -122.672748" }, "geometry": { "type": "Point", "coordinates": [ -122.672748128342633, 45.489882011226285 ] } }
]
}
