{
"type": "FeatureCollection",
"name": "origin_destination_points",
"crs": { "type": "name", "properties": { "name": "urn:ogc:def:crs:OGC:1.3:CRS84" } },
"features": [
{ "type": "Feature", "properties": { "point_type": "origin", "points_str": "45.533205, -122.60123" }, "geometry": { "type": "Point", "coordinates": [ -122.6012301589477, 45.533205493021512 ] } },
{ "type": "Feature", "properties": { "point_type": "destination", "points_str": "45.519289, -122.671691" }, "geometry": { "type": "Point", "coordinates": [ -122.671691095693319, 45.519288840300895 ] } }
]
}
