{
"type": "FeatureCollection",
"name": "origin_destination_points",
"crs": { "type": "name", "properties": { "name": "urn:ogc:def:crs:OGC:1.3:CRS84" } },
"features": [
{ "type": "Feature", "properties": { "point_type": "origin", "points_str": "45.424708, -122.583046" }, "geometry": { "type": "Point", "coordinates": [ -122.58304636581299, 45.424707967453834 ] } },
{ "type": "Feature", "properties": { "point_type": "destination", "points_str": "45.559452, -122.600023" }, "geometry": { "type": "Point", "coordinates": [ -122.600023379524117, 45.559452006232434 ] } }
]
}
