{
"type": "FeatureCollection",
"crs": { "type": "name", "properties": { "name": "urn:ogc:def:crs:OGC:1.3:CRS84" } },
"features": [
{ "type": "Feature", "properties": { "point_type": "origin", "points_str": "45.437718, -122.564149" }, "geometry": { "type": "Point", "coordinates": [ -122.564148713059438, 45.437718059499531 ] } },
{ "type": "Feature", "properties": { "point_type": "destination", "points_str": "45.565854, -122.533682" }, "geometry": { "type": "Point", "coordinates": [ -122.533682085535418, 45.56585410618635 ] } }
]
}
