{
"type": "FeatureCollection",
"name": "origin_destination_points",
"crs": { "type": "name", "properties": { "name": "urn:ogc:def:crs:OGC:1.3:CRS84" } },
"features": [
{ "type": "Feature", "properties": { "point_type": "origin", "points_str": "45.493036, -122.786885" }, "geometry": { "type": "Point", "coordinates": [ -122.786885095844909, 45.493036003212652 ] } },
{ "type": "Feature", "properties": { "point_type": "destination", "points_str": "45.499402, -122.899335" }, "geometry": { "type": "Point", "coordinates": [ -122.899334985621323, 45.499401574197513 ] } }
]
}
