{
"type": "FeatureCollection",
"name": "origin_destination_points",
"crs": { "type": "name", "properties": { "name": "urn:ogc:def:crs:OGC:1.3:CRS84" } },
"features": [
{ "type": "Feature", "properties": { "point_type": "origin", "points_str": "45.502362, -122.797715" }, "geometry": { "type": "Point", "coordinates": [ -122.797715347376709, 45.50236157478237 ] } },
{ "type": "Feature", "properties": { "point_type": "destination", "points_str": "45.559028, -122.594606" }, "geometry": { "type": "Point", "coordinates": [ -122.594606248505158, 45.559027608305932 ] } }
]
}
