{
"type": "FeatureCollection",
"crs": { "type": "name", "properties": { "name": "urn:ogc:def:crs:OGC:1.3:CRS84" } },
"features": [
{ "type": "Feature", "properties": { "point_type": "origin", "points_str": "45.495319, -122.585473" }, "geometry": { "type": "Point", "coordinates": [ -122.585472724645541, 45.495318903749762 ] } },
{ "type": "Feature", "properties": { "point_type": "destination", "points_str": "45.484383, -122.674529" }, "geometry": { "type": "Point", "coordinates": [ -122.674528992100946, 45.48438286000701 ] } }
]
}
