{
"type": "FeatureCollection",
"name": "origin_destination_points",
"crs": { "type": "name", "properties": { "name": "urn:ogc:def:crs:OGC:1.3:CRS84" } },
"features": [
{ "type": "Feature", "properties": { "point_type": "origin", "points_str": "45.462343, -122.693667" }, "geometry": { "type": "Point", "coordinates": [ -122.693666841589447, 45.46234324456718 ] } },
{ "type": "Feature", "properties": { "point_type": "destination", "points_str": "45.444902, -122.674446" }, "geometry": { "type": "Point", "coordinates": [ -122.674446469525265, 45.444901985306366 ] } }
]
}
