{
"type": "FeatureCollection",
"name": "origin_destination_points",
"crs": { "type": "name", "properties": { "name": "urn:ogc:def:crs:OGC:1.3:CRS84" } },
"features": [
{ "type": "Feature", "properties": { "point_type": "origin", "points_str": "45.461208, -122.718778" }, "geometry": { "type": "Point", "coordinates": [ -122.718778289242493, 45.461208002378285 ] } },
{ "type": "Feature", "properties": { "point_type": "destination", "points_str": "45.450233, -122.757047" }, "geometry": { "type": "Point", "coordinates": [ -122.757047417397047, 45.450232668247679 ] } }
]
}
