{
"type": "FeatureCollection",
"crs": { "type": "name", "properties": { "name": "urn:ogc:def:crs:OGC:1.3:CRS84" } },
"features": [
{ "type": "Feature", "properties": { "point_type": "origin", "points_str": "45.515667, -122.656661" }, "geometry": { "type": "Point", "coordinates": [ -122.656660636596413, 45.515667010803945 ] } },
{ "type": "Feature", "properties": { "point_type": "destination", "points_str": "45.371222, -122.625805" }, "geometry": { "type": "Point", "coordinates": [ -122.625804638998446, 45.371222402480846 ] } }
]
}
