{
"type": "FeatureCollection",
"name": "origin_destination_points",
"crs": { "type": "name", "properties": { "name": "urn:ogc:def:crs:OGC:1.3:CRS84" } },
"features": [
{ "type": "Feature", "properties": { "point_type": "origin", "points_str": "45.556743, -122.673445" }, "geometry": { "type": "Point", "coordinates": [ -122.673445087014002, 45.556743146648778 ] } },
{ "type": "Feature", "properties": { "point_type": "destination", "points_str": "45.536023, -122.533498" }, "geometry": { "type": "Point", "coordinates": [ -122.533498028882136, 45.536022991153864 ] } }
]
}
