{
"type": "FeatureCollection",
"crs": { "type": "name", "properties": { "name": "urn:ogc:def:crs:OGC:1.3:CRS84" } },
"features": [
{ "type": "Feature", "properties": { "point_type": "origin", "points_str": "45.551477, -122.657213" }, "geometry": { "type": "Point", "coordinates": [ -122.657213092301504, 45.551476587461615 ] } },
{ "type": "Feature", "properties": { "point_type": "destination", "points_str": "45.537326, -122.465754" }, "geometry": { "type": "Point", "coordinates": [ -122.465754101166056, 45.537325801417737 ] } }
]
}
