{
"type": "FeatureCollection",
"name": "origin_destination_points",
"crs": { "type": "name", "properties": { "name": "urn:ogc:def:crs:OGC:1.3:CRS84" } },
"features": [
{ "type": "Feature", "properties": { "point_type": "origin", "points_str": "45.565753, -122.646324" }, "geometry": { "type": "Point", "coordinates": [ -122.646324295675129, 45.565753212204754 ] } },
{ "type": "Feature", "properties": { "point_type": "destination", "points_str": "45.435733, -122.765196" }, "geometry": { "type": "Point", "coordinates": [ -122.765196290675306, 45.435733248476623 ] } }
]
}
