{
"type": "FeatureCollection",
"crs": { "type": "name", "properties": { "name": "urn:ogc:def:crs:OGC:1.3:CRS84" } },
"features": [
{ "type": "Feature", "properties": { "point_type": "origin", "points_str": "45.460299, -122.569036" }, "geometry": { "type": "Point", "coordinates": [ -122.569035717287576, 45.460298710225118 ] } },
{ "type": "Feature", "properties": { "point_type": "destination", "points_str": "45.51719, -122.753035" }, "geometry": { "type": "Point", "coordinates": [ -122.75303549730404, 45.517189558229319 ] } }
]
}
