{
"type": "FeatureCollection",
"name": "origin_destination_points",
"crs": { "type": "name", "properties": { "name": "urn:ogc:def:crs:OGC:1.3:CRS84" } },
"features": [
{ "type": "Feature", "properties": { "point_type": "origin", "points_str": "45.379583, -122.713103" }, "geometry": { "type": "Point", "coordinates": [ -122.713102941267735, 45.379582849938814 ] } },
{ "type": "Feature", "properties": { "point_type": "destination", "points_str": "45.547629, -122.580137" }, "geometry": { "type": "Point", "coordinates": [ -122.580137028002937, 45.547628915057871 ] } }
]
}
