{
"type": "FeatureCollection",
"crs": { "type": "name", "properties": { "name": "urn:ogc:def:crs:OGC:1.3:CRS84" } },
"features": [
{ "type": "Feature", "properties": { "point_type": "origin", "points_str": "45.538845, -122.568044" }, "geometry": { "type": "Point", "coordinates": [ -122.568043723726774, 45.538845249512505 ] } },
{ "type": "Feature", "properties": { "point_type": "destination", "points_str": "45.422539, -122.535893" }, "geometry": { "type": "Point", "coordinates": [ -122.535893408063288, 45.422538847916286 ] } }
]
}
