{
"type": "FeatureCollection",
"name": "origin_destination_points",
"crs": { "type": "name", "properties": { "name": "urn:ogc:def:crs:OGC:1.3:CRS84" } },
"features": [
{ "type": "Feature", "properties": { "point_type": "origin", "points_str": "45.506532, -122.792925" }, "geometry": { "type": "Point", "coordinates": [ -122.792924888434115, 45.506532333333084 ] } },
{ "type": "Feature", "properties": { "point_type": "destination", "points_str": "45.528595, -122.829725" }, "geometry": { "type": "Point", "coordinates": [ -122.829725275516822, 45.528594529589817 ] } }
]
}
