{
"type": "FeatureCollection",
"name": "origin_destination_points",
"crs": { "type": "name", "properties": { "name": "urn:ogc:def:crs:OGC:1.3:CRS84" } },
"features": [
{ "type": "Feature", "properties": { "point_type": "origin", "points_str": "45.486957, -122.625704" }, "geometry": { "type": "Point", "coordinates": [ -122.625703516350526, 45.486957423650765 ] } },
{ "type": "Feature", "properties": { "point_type": "destination", "points_str": "45.552491, -122.723646" }, "geometry": { "type": "Point", "coordinates": [ -122.72364621726075, 45.552490958515797 ] } }
]
}
