{
"type": "FeatureCollection",
"crs": { "type": "name", "properties": { "name": "urn:ogc:def:crs:OGC:1.3:CRS84" } },
"features": [
{ "type": "Feature", "properties": { "point_type": "origin", "points_str": "45.41118, -122.592843" }, "geometry": { "type": "Point", "coordinates": [ -122.592843305712194, 45.411180386637547 ] } },
{ "type": "Feature", "properties": { "point_type": "destination", "points_str": "45.427993, -122.517803" }, "geometry": { "type": "Point", "coordinates": [ -122.517803016011342, 45.427993395151688 ] } }
]
}
