{
"type": "FeatureCollection",
"name": "origin_destination_points",
"crs": { "type": "name", "properties": { "name": "urn:ogc:def:crs:OGC:1.3:CRS84" } },
"features": [
{ "type": "Feature", "properties": { "point_type": "origin", "points_str": "45.517916, -122.60508" }, "geometry": { "type": "Point", "coordinates": [ -122.60507981066857, 45.517915991481921 ] } },
{ "type": "Feature", "properties": { "point_type": "destination", "points_str": "45.515205, -122.639389" }, "geometry": { "type": "Point", "coordinates": [ -122.639388732646012, 45.51520454479467 ] } }
]
}
