{
"type": "FeatureCollection",
"name": "origin_destination_points",
"crs": { "type": "name", "properties": { "name": "urn:ogc:def:crs:OGC:1.3:CRS84" } },
"features": [
{ "type": "Feature", "properties": { "point_type": "origin", "points_str": "45.435604, -122.7658" }, "geometry": { "type": "Point", "coordinates": [ -122.76580012206297, 45.435603752400283 ] } },
{ "type": "Feature", "properties": { "point_type": "destination", "points_str": "45.550403, -122.590502" }, "geometry": { "type": "Point", "coordinates": [ -122.590501644640838, 45.55040252274047 ] } }
]
}
