{
"type": "FeatureCollection",
"crs": { "type": "name", "properties": { "name": "urn:ogc:def:crs:OGC:1.3:CRS84" } },
"features": [
{ "type": "Feature", "properties": { "point_type": "origin", "points_str": "45.506403, -122.404832" }, "geometry": { "type": "Point", "coordinates": [ -122.404831708264481, 45.506403337997639 ] } },
{ "type": "Feature", "properties": { "point_type": "destination", "points_str": "45.502282, -122.645922" }, "geometry": { "type": "Point", "coordinates": [ -122.645921528369556, 45.50228159308211 ] } }
]
}
