{
"type": "FeatureCollection",
"name": "origin_destination_points",
"crs": { "type": "name", "properties": { "name": "urn:ogc:def:crs:OGC:1.3:CRS84" } },
"features": [
{ "type": "Feature", "properties": { "point_type": "origin", "points_str": "45.409543, -122.540172" }, "geometry": { "type": "Point", "coordinates": [ -122.540172374934556, 45.409543096068084 ] } },
{ "type": "Feature", "properties": { "point_type": "destination", "points_str": "45.415082, -122.578259" }, "geometry": { "type": "Point", "coordinates": [ -122.578259451667563, 45.415081672102936 ] } }
]
}
