{
"type": "FeatureCollection",
"crs": { "type": "name", "properties": { "name": "urn:ogc:def:crs:OGC:1.3:CRS84" } },
"features": [
{ "type": "Feature", "properties": { "point_type": "origin", "points_str": "45.518301, -122.712232" }, "geometry": { "type": "Point", "coordinates": [ -122.712232322237313, 45.518300773116636 ] } },
{ "type": "Feature", "properties": { "point_type": "destination", "points_str": "45.547092, -122.591005" }, "geometry": { "type": "Point", "coordinates": [ -122.591005263510525, 45.547091523835576 ] } }
]
}
