{
"type": "FeatureCollection",
"name": "origin_destination_points",
"crs": { "type": "name", "properties": { "name": "urn:ogc:def:crs:OGC:1.3:CRS84" } },
"features": [
{ "type": "Feature", "properties": { "point_type": "origin", "points_str": "45.4893, -122.806736" }, "geometry": { "type": "Point", "coordinates": [ -122.806735569947676, 45.489299744247049 ] } },
{ "type": "Feature", "properties": { "point_type": "destination", "points_str": "45.442699, -122.793116" }, "geometry": { "type": "Point", "coordinates": [ -122.793115545078749, 45.442698704777058 ] } }
]
}
