{
"type": "FeatureCollection",
"name": "origin_destination_points",
"crs": { "type": "name", "properties": { "name": "urn:ogc:def:crs:OGC:1.3:CRS84" } },
"features": [
{ "type": "Feature", "properties": { "point_type": "origin", "points_str": "45.494949, -122.855099" }, "geometry": { "type": "Point", "coordinates": [ -122.855098930338784, 45.494949395862349 ] } },
{ "type": "Feature", "properties": { "point_type": "destination", "points_str": "45.486817, -122.78499" }, "geometry": { "type": "Point", "coordinates": [ -122.78499047481759, 45.486817141351828 ] } }
]
}
