{
"type": "FeatureCollection",
"name": "origin_destination_points",
"crs": { "type": "name", "properties": { "name": "urn:ogc:def:crs:OGC:1.3:CRS84" } },
"features": [
{ "type": "Feature", "properties": { "point_type": "origin", "points_str": "45.444327, -122.733392" }, "geometry": { "type": "Point", "coordinates": [ -122.733392196552941, 45.444326639092786 ] } },
{ "type": "Feature", "properties": { "point_type": "destination", "points_str": "45.480191, -122.530386" }, "geometry": { "type": "Point", "coordinates": [ -122.530385712866092, 45.480191063273608 ] } }
]
}
