{
"type": "FeatureCollection",
"name": "origin_destination_points",
"crs": { "type": "name", "properties": { "name": "urn:ogc:def:crs:OGC:1.3:CRS84" } },
"features": [
{ "type": "Feature", "properties": { "point_type": "origin", "points_str": "45.565708, -122.541315" }, "geometry": { "type": "Point", "coordinates": [ -122.541314765554333, 45.565708121791317 ] } },
{ "type": "Feature", "properties": { "point_type": "destination", "points_str": "45.502209, -122.525599" }, "geometry": { "type": "Point", "coordinates": [ -122.525599477936723, 45.502208633859802 ] } }
]
}
