{
"type": "FeatureCollection",
"name": "origin_destination_points",
"crs": { "type": "name", "properties": { "name": "urn:ogc:def:crs:OGC:1.3:CRS84" } },
"features": [
{ "type": "Feature", "properties": { "point_type": "origin", "points_str": "45.521937, -122.513904" }, "geometry": { "type": "Point", "coordinates": [ -122.513904372014238, 45.521936699520595 ] } },
{ "type": "Feature", "properties": { "point_type": "destination", "points_str": "45.566474, -122.702955" }, "geometry": { "type": "Point", "coordinates": [ -122.702955377760134, 45.566473872360589 ] } }
]
}
