{
"type": "FeatureCollection",
"crs": { "type": "name", "properties": { "name": "urn:ogc:def:crs:OGC:1.3:CRS84" } },
"features": [
{ "type": "Feature", "properties": { "point_type": "origin", "points_str": "45.368833, -122.376161" }, "geometry": { "type": "Point", "coordinates": [ -122.376160902055616, 45.36883333109737 ] } },
{ "type": "Feature", "properties": { "point_type": "destination", "points_str": "45.395287, -122.569513" }, "geometry": { "type": "Point", "coordinates": [ -122.569513206730065, 45.39528701112836 ] } }
]
}
