{
"type": "FeatureCollection",
"crs": { "type": "name", "properties": { "name": "urn:ogc:def:crs:OGC:1.3:CRS84" } },
"features": [
{ "type": "Feature", "properties": { "point_type": "origin", "points_str": "45.483678, -122.765326" }, "geometry": { "type": "Point", "coordinates": [ -122.765326262176146, 45.483677957630334 ] } },
{ "type": "Feature", "properties": { "point_type": "destination", "points_str": "45.519831, -122.436283" }, "geometry": { "type": "Point", "coordinates": [ -122.436283468310222, 45.519831460987923 ] } }
]
}
