{
"type": "FeatureCollection",
"name": "origin_destination_points",
"crs": { "type": "name", "properties": { "name": "urn:ogc:def:crs:OGC:1.3:CRS84" } },
"features": [
{ "type": "Feature", "properties": { "point_type": "origin", "points_str": "45.522422, -122.680648" }, "geometry": { "type": "Point", "coordinates": [ -122.680648055243836, 45.52242247531354 ] } },
{ "type": "Feature", "properties": { "point_type": "destination", "points_str": "45.5613, -122.687135" }, "geometry": { "type": "Point", "coordinates": [ -122.687134530736301, 45.561300410424046 ] } }
]
}
