{
"type": "FeatureCollection",
"name": "origin_destination_points",
"crs": { "type": "name", "properties": { "name": "urn:ogc:def:crs:OGC:1.3:CRS84" } },
"features": [
{ "type": "Feature", "properties": { "point_type": "origin", "points_str": "45.502777, -122.4755" }, "geometry": { "type": "Point", "coordinates": [ -122.475500431102546, 45.502776826335612 ] } },
{ "type": "Feature", "properties": { "point_type": "destination", "points_str": "45.515463, -122.578533" }, "geometry": { "type": "Point", "coordinates": [ -122.578533262067594, 45.515463361019222 ] } }
]
}
