{
"type": "FeatureCollection",
"name": "origin_destination_points",
"crs": { "type": "name", "properties": { "name": "urn:ogc:def:crs:OGC:1.3:CRS84" } },
"features": [
{ "type": "Feature", "properties": { "point_type": "origin", "points_str": "45.286421, -122.330186" }, "geometry": { "type": "Point", "coordinates": [ -122.330186478255882, 45.286420914392096 ] } },
{ "type": "Feature", "properties": { "point_type": "destination", "points_str": "45.432512, -122.576979" }, "geometry": { "type": "Point", "coordinates": [ -122.576979316363534, 45.432511691167832 ] } }
]
}
