{
"type": "FeatureCollection",
"crs": { "type": "name", "properties": { "name": "urn:ogc:def:crs:OGC:1.3:CRS84" } },
"features": [
{ "type": "Feature", "properties": { "point_type": "origin", "points_str": "45.567296, -122.607012" }, "geometry": { "type": "Point", "coordinates": [ -122.607011681566604, 45.567295651207964 ] } },
{ "type": "Feature", "properties": { "point_type": "destination", "points_str": "45.497761, -122.430036" }, "geometry": { "type": "Point", "coordinates": [ -122.430035633825042, 45.497761064468321 ] } }
]
}
