{
"type": "FeatureCollection",
"name": "origin_destination_points",
"crs": { "type": "name", "properties": { "name": "urn:ogc:def:crs:OGC:1.3:CRS84" } },
"features": [
{ "type": "Feature", "properties": { "point_type": "origin", "points_str": "45.577931, -122.722085" }, "geometry": { "type": "Point", "coordinates": [ -122.722085483701861, 45.577930879260265 ] } },
{ "type": "Feature", "properties": { "point_type": "destination", "points_str": "45.488311, -122.750838" }, "geometry": { "type": "Point", "coordinates": [ -122.750837798857887, 45.488311207893396 ] } }
]
}
