{
"type": "FeatureCollection",
"crs": { "type": "name", "properties": { "name": "urn:ogc:def:crs:OGC:1.3:CRS84" } },
"features": [
{ "type": "Feature", "properties": { "point_type": "origin", "points_str": "45.466786, -122.774199" }, "geometry": { "type": "Point", "coordinates": [ -122.774198589985218, 45.466785634701836 ] } },
{ "type": "Feature", "properties": { "point_type": "destination", "points_str": "45.520618, -123.080101" }, "geometry": { "type": "Point", "coordinates": [ -123.080101457033152, 45.520618175069771 ] } }
]
}
