{
"type": "FeatureCollection",
"name": "origin_destination_points",
"crs": { "type": "name", "properties": { "name": "urn:ogc:def:crs:OGC:1.3:CRS84" } },
"features": [
{ "type": "Feature", "properties": { "point_type": "origin", "points_str": "45.534974, -122.64943" }, "geometry": { "type": "Point", "coordinates": [ -122.64943012710674, 45.534973756702414 ] } },
{ "type": "Feature", "properties": { "point_type": "destination", "points_str": "45.54721, -122.702342" }, "geometry": { "type": "Point", "coordinates": [ -122.702341800967375, 45.547210213866627 ] } }
]
}
