{
"type": "FeatureCollection",
"name": "origin_destination_points",
"crs": { "type": "name", "properties": { "name": "urn:ogc:def:crs:OGC:1.3:CRS84" } },
"features": [
{ "type": "Feature", "properties": { "point_type": "origin", "points_str": "45.542528, -122.641324" }, "geometry": { "type": "Point", "coordinates": [ -122.64132368705512, 45.542528241922007 ] } },
{ "type": "Feature", "properties": { "point_type": "destination", "points_str": "45.508466, -122.842455" }, "geometry": { "type": "Point", "coordinates": [ -122.842454967368766, 45.50846595046788 ] } }
]
}
