{
"type": "FeatureCollection",
"name": "origin_destination_points",
"crs": { "type": "name", "properties": { "name": "urn:ogc:def:crs:OGC:1.3:CRS84" } },
"features": [
{ "type": "Feature", "properties": { "point_type": "origin", "points_str": "45.428029, -122.531082" }, "geometry": { "type": "Point", "coordinates": [ -122.531081684021885, 45.428029120551052 ] } },
{ "type": "Feature", "properties": { "point_type": "destination", "points_str": "45.388458, -122.404794" }, "geometry": { "type": "Point", "coordinates": [ -122.404793928557325, 45.38845842286662 ] } }
]
}
