{
"type": "FeatureCollection",
"crs": { "type": "name", "properties": { "name": "urn:ogc:def:crs:OGC:1.3:CRS84" } },
"features": [
{ "type": "Feature", "properties": { "point_type": "origin", "points_str": "45.44358, -122.596925" }, "geometry": { "type": "Point", "coordinates": [ -122.59692530147062, 45.443579771482625 ] } },
{ "type": "Feature", "properties": { "point_type": "destination", "points_str": "45.404265, -122.663019" }, "geometry": { "type": "Point", "coordinates": [ -122.663018987072761, 45.404265382412909 ] } }
]
}
