{
"type": "FeatureCollection",
"name": "origin_destination_points",
"crs": { "type": "name", "properties": { "name": "urn:ogc:def:crs:OGC:1.3:CRS84" } },
"features": [
{ "type": "Feature", "properties": { "point_type": "origin", "points_str": "45.594843, -122.746553" }, "geometry": { "type": "Point", "coordinates": [ -122.746552777917799, 45.594843221855498 ] } },
{ "type": "Feature", "properties": { "point_type": "destination", "points_str": "45.555039, -122.673861" }, "geometry": { "type": "Point", "coordinates": [ -122.673860970248299, 45.555038989225665 ] } }
]
}
