{
"type": "FeatureCollection",
"name": "origin_destination_points",
"crs": { "type": "name", "properties": { "name": "urn:ogc:def:crs:OGC:1.3:CRS84" } },
"features": [
{ "type": "Feature", "properties": { "point_type": "origin", "points_str": "45.526166, -122.647757" }, "geometry": { "type": "Point", "coordinates": [ -122.647756557940269, 45.526165864846938 ] } },
{ "type": "Feature", "properties": { "point_type": "destination", "points_str": "45.474791, -122.602586" }, "geometry": { "type": "Point", "coordinates": [ -122.602585569868126, 45.474791366372784 ] } }
]
}
