{
"type": "FeatureCollection",
"name": "origin_destination_points",
"crs": { "type": "name", "properties": { "name": "urn:ogc:def:crs:OGC:1.3:CRS84" } },
"features": [
{ "type": "Feature", "properties": { "point_type": "origin", "points_str": "45.510324, -122.687386" }, "geometry": { "type": "Point", "coordinates": [ -122.687385584976084, 45.510323566055156 ] } },
{ "type": "Feature", "properties": { "point_type": "destination", "points_str": "45.460566, -122.64889" }, "geometry": { "type": "Point", "coordinates": [ -122.648890100641623, 45.460565763076751 ] } }
]
}
