{
"type": "FeatureCollection",
"name": "origin_destination_points",
"crs": { "type": "name", "properties": { "name": "urn:ogc:def:crs:OGC:1.3:CRS84" } },
"features": [
{ "type": "Feature", "properties": { "point_type": "origin", "points_str": "45.476898, -122.825448" }, "geometry": { "type": "Point", "coordinates": [ -122.825447805220705, 45.476898369106635 ] } },
{ "type": "Feature", "properties": { "point_type": "destination", "points_str": "45.501558, -122.870179" }, "geometry": { "type": "Point", "coordinates": [ -122.870178786325383, 45.501557911979212 ] } }
]
}
