{
"type": "FeatureCollection",
"name": "origin_destination_points",
"crs": { "type": "name", "properties": { "name": "urn:ogc:def:crs:OGC:1.3:CRS84" } },
"features": [
{ "type": "Feature", "properties": { "point_type": "origin", "points_str": "45.498087, -122.574452" }, "geometry": { "type": "Point", "coordinates": [ -122.574452221094759, 45.498087405894807 ] } },
{ "type": "Feature", "properties": { "point_type": "destination", "points_str": "45.436767, -122.571803" }, "geometry": { "type": "Point", "coordinates": [ -122.571802656571322, 45.436766631416894 ] } }
]
}
