{
"type": "FeatureCollection",
"crs": { "type": "name", "properties": { "name": "urn:ogc:def:crs:OGC:1.3:CRS84" } },
"features": [
{ "type": "Feature", "properties": { "point_type": "origin", "points_str": "45.545792, -122.712897" }, "geometry": { "type": "Point", "coordinates": [ -122.712896830263446, 45.545792397339447 ] } },
{ "type": "Feature", "properties": { "point_type": "destination", "points_str": "45.472454, -122.614676" }, "geometry": { "type": "Point", "coordinates": [ -122.614675538616339, 45.472454163522357 ] } }
]
}
