{
"type": "FeatureCollection",
"crs": { "type": "name", "properties": { "name": "urn:ogc:def:crs:OGC:1.3:CRS84" } },
"features": [
{ "type": "Feature", "properties": { "point_type": "origin", "points_str": "45.538389, -122.492323" }, "geometry": { "type": "Point", "coordinates": [ -122.492322556284009, 45.538389416996303 ] } },
{ "type": "Feature", "properties": { "point_type": "destination", "points_str": "45.500878, -122.690508" }, "geometry": { "type": "Point", "coordinates": [ -122.690507509883901, 45.50087816455212 ] } }
]
}
