{
"type": "FeatureCollection",
"name": "origin_destination_points",
"crs": { "type": "name", "properties": { "name": "urn:ogc:def:crs:OGC:1.3:CRS84" } },
"features": [
{ "type": "Feature", "properties": { "point_type": "origin", "points_str": "45.524208, -122.860588" }, "geometry": { "type": "Point", "coordinates": [ -122.860588291287357, 45.524207832413317 ] } },
{ "type": "Feature", "properties": { "point_type": "destination", "points_str": "45.520679, -122.537378" }, "geometry": { "type": "Point", "coordinates": [ -122.537378070151618, 45.520679148339276 ] } }
]
}
