{
"type": "FeatureCollection",
"name": "origin_destination_points",
"crs": { "type": "name", "properties": { "name": "urn:ogc:def:crs:OGC:1.3:CRS84" } },
"features": [
{ "type": "Feature", "properties": { "point_type": "origin", "points_str": "45.52987, -122.584656" }, "geometry": { "type": "Point", "coordinates": [ -122.584655761780695, 45.529870396808498 ] } },
{ "type": "Feature", "properties": { "point_type": "destination", "points_str": "45.364549, -122.607315" }, "geometry": { "type": "Point", "coordinates": [ -122.60731536391576, 45.364548841994754 ] } }
]
}
