{
"type": "FeatureCollection",
"crs": { "type": "name", "properties": { "name": "urn:ogc:def:crs:OGC:1.3:CRS84" } },
"features": [
{ "type": "Feature", "properties": { "point_type": "origin", "points_str": "45.327619, -122.589894" }, "geometry": { "type": "Point", "coordinates": [ -122.589893776123404, 45.327619278888285 ] } },
{ "type": "Feature", "properties": { "point_type": "destination", "points_str": "45.528956, -122.657183" }, "geometry": { "type": "Point", "coordinates": [ -122.65718286447553, 45.528956376422911 ] } }
]
}
