{
"type": "FeatureCollection",
"name": "origin_destination_points",
"crs": { "type": "name", "properties": { "name": "urn:ogc:def:crs:OGC:1.3:CRS84" } },
"features": [
{ "type": "Feature", "properties": { "point_type": "origin", "points_str": "45.583068, -122.665304" }, "geometry": { "type": "Point", "coordinates": [ -122.665304048020715, 45.583067705198921 ] } },
{ "type": "Feature", "properties": { "point_type": "destination", "points_str": "45.526245, -122.691494" }, "geometry": { "type": "Point", "coordinates": [ -122.691494101458687, 45.526244890278576 ] } }
]
}
