{
"type": "FeatureCollection",
"name": "origin_destination_points",
"crs": { "type": "name", "properties": { "name": "urn:ogc:def:crs:OGC:1.3:CRS84" } },
"features": [
{ "type": "Feature", "properties": { "point_type": "origin", "points_str": "45.482413, -122.722712" }, "geometry": { "type": "Point", "coordinates": [ -122.72271182123167, 45.482413325972573 ] } },
{ "type": "Feature", "properties": { "point_type": "destination", "points_str": "45.506322, -122.518759" }, "geometry": { "type": "Point", "coordinates": [ -122.518759482915698, 45.506321866130897 ] } }
]
}
