{
"type": "FeatureCollection",
"name": "origin_destination_points",
"crs": { "type": "name", "properties": { "name": "urn:ogc:def:crs:OGC:1.3:CRS84" } },
"features": [
{ "type": "Feature", "properties": { "point_type": "origin", "points_str": "45.50389, -122.434739" }, "geometry": { "type": "Point", "coordinates": [ -122.434739466139376, 45.503890232005688 ] } },
{ "type": "Feature", "properties": { "point_type": "destination", "points_str": "45.5429, -122.679694" }, "geometry": { "type": "Point", "coordinates": [ -122.679693861239457, 45.542899609742165 ] } }
]
}
