{
"type": "FeatureCollection",
"crs": { "type": "name", "properties": { "name": "urn:ogc:def:crs:OGC:1.3:CRS84" } },
"features": [
{ "type": "Feature", "properties": { "point_type": "origin", "points_str": "45.580507, -122.7014" }, "geometry": { "type": "Point", "coordinates": [ -122.701400201298156, 45.580507244286551 ] } },
{ "type": "Feature", "properties": { "point_type": "destination", "points_str": "45.527622, -122.666778" }, "geometry": { "type": "Point", "coordinates": [ -122.666777619322374, 45.527621747711329 ] } }
]
}
