{
"type": "FeatureCollection",
"name": "origin_destination_points",
"crs": { "type": "name", "properties": { "name": "urn:ogc:def:crs:OGC:1.3:CRS84" } },
"features": [
{ "type": "Feature", "properties": { "point_type": "origin", "points_str": "45.532916, -122.622985" }, "geometry": { "type": "Point", "coordinates": [ -122.622985047506603, 45.532916002884413 ] } },
{ "type": "Feature", "properties": { "point_type": "destination", "points_str": "45.527861, -122.672752" }, "geometry": { "type": "Point", "coordinates": [ -122.672751676651274, 45.527860734401635 ] } }
]
}
