{
"type": "FeatureCollection",
"name": "origin_destination_points",
"crs": { "type": "name", "properties": { "name": "urn:ogc:def:crs:OGC:1.3:CRS84" } },
"features": [
{ "type": "Feature", "properties": { "point_type": "origin", "points_str": "45.53161, -122.9474" }, "geometry": { "type": "Point", "coordinates": [ -122.947400266966454, 45.531609693576762 ] } },
{ "type": "Feature", "properties": { "point_type": "destination", "points_str": "45.52718, -122.973095" }, "geometry": { "type": "Point", "coordinates": [ -122.973094935639622, 45.527179709134487 ] } }
]
}
