{
"type": "FeatureCollection",
"name": "origin_destination_points",
"crs": { "type": "name", "properties": { "name": "urn:ogc:def:crs:OGC:1.3:CRS84" } },
"features": [
{ "type": "Feature", "properties": { "point_type": "origin", "points_str": "45.523478, -122.676135" }, "geometry": { "type": "Point", "coordinates": [ -122.676135342619489, 45.523477860178104 ] } },
{ "type": "Feature", "properties": { "point_type": "destination", "points_str": "45.508682, -122.785245" }, "geometry": { "type": "Point", "coordinates": [ -122.785244742776683, 45.508682279126958 ] } }
]
}
