{
"type": "FeatureCollection",
"name": "origin_destination_points",
"crs": { "type": "name", "properties": { "name": "urn:ogc:def:crs:OGC:1.3:CRS84" } },
"features": [
{ "type": "Feature", "properties": { "point_type": "origin", "points_str": "45.522731, -123.021449" }, "geometry": { "type": "Point", "coordinates": [ -123.021449311242677, 45.522731044572986 ] } },
{ "type": "Feature", "properties": { "point_type": "destination", "points_str": "45.500453, -122.949031" }, "geometry": { "type": "Point", "coordinates": [ -122.949030888317111, 45.500452991747331 ] } }
]
}
