{
"type": "FeatureCollection",
"crs": { "type": "name", "properties": { "name": "urn:ogc:def:crs:OGC:1.3:CRS84" } },
"features": [
{ "type": "Feature", "properties": { "point_type": "origin", "points_str": "45.495307, -122.637325" }, "geometry": { "type": "Point", "coordinates": [ -122.637324954809699, 45.495306696016065 ] } },
{ "type": "Feature", "properties": { "point_type": "destination", "points_str": "45.470564, -122.671378" }, "geometry": { "type": "Point", "coordinates": [ -122.671378005156726, 45.47056362194305 ] } }
]
}
