{
"type": "FeatureCollection",
"crs": { "type": "name", "properties": { "name": "urn:ogc:def:crs:OGC:1.3:CRS84" } },
"features": [
{ "type": "Feature", "properties": { "point_type": "origin", "points_str": "45.559409, -122.492346" }, "geometry": { "type": "Point", "coordinates": [ -122.492345567460447, 45.559409268674102 ] } },
{ "type": "Feature", "properties": { "point_type": "destination", "points_str": "45.562308, -122.547653" }, "geometry": { "type": "Point", "coordinates": [ -122.54765319664547, 45.562307725031516 ] } }
]
}
