{
"type": "FeatureCollection",
"crs": { "type": "name", "properties": { "name": "urn:ogc:def:crs:OGC:1.3:CRS84" } },
"features": [
{ "type": "Feature", "properties": { "point_type": "origin", "points_str": "45.500197, -122.542983" }, "geometry": { "type": "Point", "coordinates": [ -122.542983480265406, 45.500196678132049 ] } },
{ "type": "Feature", "properties": { "point_type": "destination", "points_str": "45.44634, -122.644747" }, "geometry": { "type": "Point", "coordinates": [ -122.644747038839682, 45.446340029712914 ] } }
]
}
