{
"type": "FeatureCollection",
"crs": { "type": "name", "properties": { "name": "urn:ogc:def:crs:OGC:1.3:CRS84" } },
"features": [
{ "type": "Feature", "properties": { "point_type": "origin", "points_str": "45.572759, -122.664712" }, "geometry": { "type": "Point", "coordinates": [ -122.66471153223533, 45.572758907031435 ] } },
{ "type": "Feature", "properties": { "point_type": "destination", "points_str": "45.489862, -122.675411" }, "geometry": { "type": "Point", "coordinates": [ -122.675411441516019, 45.489862245714669 ] } }
]
}
