{
"type": "FeatureCollection",
"name": "origin_destination_points",
"crs": { "type": "name", "properties": { "name": "urn:ogc:def:crs:OGC:1.3:CRS84" } },
"features": [
{ "type": "Feature", "properties": { "point_type": "origin", "points_str": "45.589323, -122.742417" }, "geometry": { "type": "Point", "coordinates": [ -122.74241669650398, 45.589322938936057 ] } },
{ "type": "Feature", "properties": { "point_type": "destination", "points_str": "45.5044, -122.685864" }, "geometry": { "type": "Point", "coordinates": [ -122.685863982559326, 45.504400391465502 ] } }
]
}
