{
"type": "FeatureCollection",
"name": "origin_destination_points",
"crs": { "type": "name", "properties": { "name": "urn:ogc:def:crs:OGC:1.3:CRS84" } },
"features": [
{ "type": "Feature", "properties": { "point_type": "origin", "points_str": "45.454215, -122.59338" }, "geometry": { "type": "Point", "coordinates": [ -122.593379594823347, 45.454215335523486 ] } },
{ "type": "Feature", "properties": { "point_type": "destination", "points_str": "45.298107, -122.337361" }, "geometry": { "type": "Point", "coordinates": [ -122.33736092457535, 45.29810672498153 ] } }
]
}
