{
"type": "FeatureCollection",
"name": "origin_destination_points",
"crs": { "type": "name", "properties": { "name": "urn:ogc:def:crs:OGC:1.3:CRS84" } },
"features": [
{ "type": "Feature", "properties": { "point_type": "origin", "points_str": "45.519493, -122.411248" }, "geometry": { "type": "Point", "coordinates": [ -122.411247875805941, 45.519493055160872 ] } },
{ "type": "Feature", "properties": { "point_type": "destination", "points_str": "45.490276, -122.678321" }, "geometry": { "type": "Point", "coordinates": [ -122.678320535385183, 45.490275505214051 ] } }
]
}
