{
"type": "FeatureCollection",
"crs": { "type": "name", "properties": { "name": "urn:ogc:def:crs:OGC:1.3:CRS84" } },
"features": [
{ "type": "Feature", "properties": { "point_type": "origin", "points_str": "45.551771, -122.595039" }, "geometry": { "type": "Point", "coordinates": [ -122.595038791007383, 45.551771297704484 ] } },
{ "type": "Feature", "properties": { "point_type": "destination", "points_str": "45.556224, -122.642183" }, "geometry": { "type": "Point", "coordinates": [ -122.642182528337642, 45.556224210997655 ] } }
]
}
