{
"type": "FeatureCollection",
"name": "origin_destination_points",
"crs": { "type": "name", "properties": { "name": "urn:ogc:def:crs:OGC:1.3:CRS84" } },
"features": [
{ "type": "Feature", "properties": { "point_type": "origin", "points_str": "45.537869, -122.667848" }, "geometry": { "type": "Point", "coordinates": [ -122.667847949023511, 45.537869481618813 ] } },
{ "type": "Feature", "properties": { "point_type": "destination", "points_str": "45.512847, -122.613136" }, "geometry": { "type": "Point", "coordinates": [ -122.613136014933858, 45.512847097231656 ] } }
]
}
