{
"type": "FeatureCollection",
"crs": { "type": "name", "properties": { "name": "urn:ogc:def:crs:OGC:1.3:CRS84" } },
"features": [
{ "type": "Feature", "properties": { "point_type": "origin", "points_str": "45.510975, -122.795416" }, "geometry": { "type": "Point", "coordinates": [ -122.795415574503878, 45.510974656349717 ] } },
{ "type": "Feature", "properties": { "point_type": "destination", "points_str": "45.373123, -122.759923" }, "geometry": { "type": "Point", "coordinates": [ -122.759923199091887, 45.373123126631086 ] } }
]
}
