{
"type": "FeatureCollection",
"name": "origin_destination_points",
"crs": { "type": "name", "properties": { "name": "urn:ogc:def:crs:OGC:1.3:CRS84" } },
"features": [
{ "type": "Feature", "properties": { "point_type": "origin", "points_str": "45.519855, -122.409538" }, "geometry": { "type": "Point", "coordinates": [ -122.40953753115889, 45.519854964647877 ] } },
{ "type": "Feature", "properties": { "point_type": "destination", "points_str": "45.482614, -122.723787" }, "geometry": { "type": "Point", "coordinates": [ -122.723786620803594, 45.482613989943808 ] } }
]
}
