{
"type": "FeatureCollection",
"crs": { "type": "name", "properties": { "name": "urn:ogc:def:crs:OGC:1.3:CRS84" } },
"features": [
{ "type": "Feature", "properties": { "point_type": "origin", "points_str": "45.511499, -122.848766" }, "geometry": { "type": "Point", "coordinates": [ -122.848765663535957, 45.511499486720155 ] } },
{ "type": "Feature", "properties": { "point_type": "destination", "points_str": "45.502505, -122.540239" }, "geometry": { "type": "Point", "coordinates": [ -122.540239295937695, 45.502504803255178 ] } }
]
}
