{
"type": "FeatureCollection",
"crs": { "type": "name", "properties": { "name": "urn:ogc:def:crs:OGC:1.3:CRS84" } },
"features": [
{ "type": "Feature", "properties": { "point_type": "origin", "points_str": "45.464914, -122.839593" }, "geometry": { "type": "Point", "coordinates": [ -122.839592584239526, 45.464913746371657 ] } },
{ "type": "Feature", "properties": { "point_type": "destination", "points_str": "45.423834, -122.690515" }, "geometry": { "type": "Point", "coordinates": [ -122.690515244169916, 45.423834316529764 ] } }
]
}
