{
"type": "FeatureCollection",
"name": "origin_destination_points",
"crs": { "type": "name", "properties": { "name": "urn:ogc:def:crs:OGC:1.3:CRS84" } },
"features": [
{ "type": "Feature", "properties": { "point_type": "origin", "points_str": "45.476684, -122.614552" }, "geometry": { "type": "Point", "coordinates": [ -122.614552335294036, 45.476683853559734 ] } },
{ "type": "Feature", "properties": { "point_type": "destination", "points_str": "45.416291, -122.630389" }, "geometry": { "type": "Point", "coordinates": [ -122.630389363927634, 45.416291143506257 ] } }
]
}
