{
"type": "FeatureCollection",
"crs": { "type": "name", "properties": { "name": "urn:ogc:def:crs:OGC:1.3:CRS84" } },
"features": [
{ "type": "Feature", "properties": { "point_type": "origin", "points_str": "45.520687, -122.672329" }, "geometry": { "type": "Point", "coordinates": [ -122.672328568860621, 45.520687015038874 ] } },
{ "type": "Feature", "properties": { "point_type": "destination", "points_str": "45.487878, -122.673703" }, "geometry": { "type": "Point", "coordinates": [ -122.673702763716378, 45.48787830102308 ] } }
]
}
