{
"type": "FeatureCollection",
"name": "origin_destination_points",
"crs": { "type": "name", "properties": { "name": "urn:ogc:def:crs:OGC:1.3:CRS84" } },
"features": [
{ "type": "Feature", "properties": { "point_type": "origin", "points_str": "45.465684, -122.695597" }, "geometry": { "type": "Point", "coordinates": [ -122.695597090883737, 45.465683740343771 ] } },
{ "type": "Feature", "properties": { "point_type": "destination", "points_str": "45.543168, -122.688929" }, "geometry": { "type": "Point", "coordinates": [ -122.688929273577813, 45.54316849311143 ] } }
]
}
