{
"type": "FeatureCollection",
"name": "origin_destination_points",
"crs": { "type": "name", "properties": { "name": "urn:ogc:def:crs:OGC:1.3:CRS84" } },
"features": [
{ "type": "Feature", "properties": { "point_type": "origin", "points_str": "45.513745, -122.661117" }, "geometry": { "type": "Point", "coordinates": [ -122.661116606518007, 45.513745396351332 ] } },
{ "type": "Feature", "properties": { "point_type": "destination", "points_str": "45.590357, -122.688887" }, "geometry": { "type": "Point", "coordinates": [ -122.688886520356178, 45.590356803141084 ] } }
]
}
