{
"type": "FeatureCollection",
"crs": { "type": "name", "properties": { "name": "urn:ogc:def:crs:OGC:1.3:CRS84" } },
"features": [
{ "type": "Feature", "properties": { "point_type": "origin", "points_str": "45.471016, -122.600654" }, "geometry": { "type": "Point", "coordinates": [ -122.600653863139428, 45.471015778757923 ] } },
{ "type": "Feature", "properties": { "point_type": "destination", "points_str": "45.541174, -122.621554" }, "geometry": { "type": "Point", "coordinates": [ -122.621553995768309, 45.541173858272181 ] } }
]
}
