{
"type": "FeatureCollection",
"crs": { "type": "name", "properties": { "name": "urn:ogc:def:crs:OGC:1.3:CRS84" } },
"features": [
{ "type": "Feature", "properties": { "point_type": "origin", "points_str": "45.366725, -122.778773" }, "geometry": { "type": "Point", "coordinates": [ -122.77877345238258, 45.36672524124792 ] } },
{ "type": "Feature", "properties": { "point_type": "destination", "points_str": "45.459766, -122.728244" }, "geometry": { "type": "Point", "coordinates": [ -122.728243773521399, 45.459766045084514 ] } }
]
}
