{
"type": "FeatureCollection",
"name": "origin_destination_points",
"crs": { "type": "name", "properties": { "name": "urn:ogc:def:crs:OGC:1.3:CRS84" } },
"features": [
{ "type": "Feature", "properties": { "point_type": "origin", "points_str": "45.387545, -122.755674" }, "geometry": { "type": "Point", "coordinates": [ -122.7556736001617, 45.387544615349007 ] } },
{ "type": "Feature", "properties": { "point_type": "destination", "points_str": "45.612787, -122.67846" }, "geometry": { "type": "Point", "coordinates": [ -122.678460431541367, 45.612787172095672 ] } }
]
}
