{
"type": "FeatureCollection",
"name": "origin_destination_points",
"crs": { "type": "name", "properties": { "name": "urn:ogc:def:crs:OGC:1.3:CRS84" } },
"features": [
{ "type": "Feature", "properties": { "point_type": "origin", "points_str": "45.564231, -122.697898" }, "geometry": { "type": "Point", "coordinates": [ -122.697897598173697, 45.564231227025502 ] } },
{ "type": "Feature", "properties": { "point_type": "destination", "points_str": "45.495707, -122.614101" }, "geometry": { "type": "Point", "coordinates": [ -122.614100924984598, 45.495707104932798 ] } }
]
}
