{
"type": "FeatureCollection",
"crs": { "type": "name", "properties": { "name": "urn:ogc:def:crs:OGC:1.3:CRS84" } },
"features": [
{ "type": "Feature", "properties": { "point_type": "origin", "points_str": "45.579409, -122.675202" }, "geometry": { "type": "Point", "coordinates": [ -122.675202296233721, 45.579408916599924 ] } },
{ "type": "Feature", "properties": { "point_type": "destination", "points_str": "45.54832, -122.627743" }, "geometry": { "type": "Point", "coordinates": [ -122.627742671011191, 45.548320428916966 ] } }
]
}
