{
"type": "FeatureCollection",
"name": "origin_destination_points",
"crs": { "type": "name", "properties": { "name": "urn:ogc:def:crs:OGC:1.3:CRS84" } },
"features": [
{ "type": "Feature", "properties": { "point_type": "origin", "points_str": "45.447575, -122.577711" }, "geometry": { "type": "Point", "coordinates": [ -122.577711042302596, 45.447574669169832 ] } },
{ "type": "Feature", "properties": { "point_type": "destination", "points_str": "45.394881, -122.585252" }, "geometry": { "type": "Point", "coordinates": [ -122.585252146743755, 45.39488079598658 ] } }
]
}
