{
"type": "FeatureCollection",
"name": "origin_destination_points",
"crs": { "type": "name", "properties": { "name": "urn:ogc:def:crs:OGC:1.3:CRS84" } },
"features": [
{ "type": "Feature", "properties": { "point_type": "origin", "points_str": "45.390375, -122.756888" }, "geometry": { "type": "Point", "coordinates": [ -122.756887812301784, 45.39037499559187 ] } },
{ "type": "Feature", "properties": { "point_type": "destination", "points_str": "45.332422, -122.603934" }, "geometry": { "type": "Point", "coordinates": [ -122.603933709272326, 45.332421857062293 ] } }
]
}
