{
"type": "FeatureCollection",
"name": "origin_destination_points",
"crs": { "type": "name", "properties": { "name": "urn:ogc:def:crs:OGC:1.3:CRS84" } },
"features": [
{ "type": "Feature", "properties": { "point_type": "origin", "points_str": "45.506073, -122.517822" }, "geometry": { "type": "Point", "coordinates": [ -122.517821517914271, 45.506073371837843 ] } },
{ "type": "Feature", "properties": { "point_type": "destination", "points_str": "45.599636, -122.785301" }, "geometry": { "type": "Point", "coordinates": [ -122.785301407446596, 45.599636471447113 ] } }
]
}
