{
"type": "FeatureCollection",
"crs": { "type": "name", "properties": { "name": "urn:ogc:def:crs:OGC:1.3:CRS84" } },
"features": [
{ "type": "Feature", "properties": { "point_type": "origin", "points_str": "45.550931, -122.572293" }, "geometry": { "type": "Point", "coordinates": [ -122.572293198607156, 45.550930876862175 ] } },
{ "type": "Feature", "properties": { "point_type": "destination", "points_str": "45.487059, -122.583157" }, "geometry": { "type": "Point", "coordinates": [ -122.583157482577263, 45.487059057526352 ] } }
]
}
