{
"type": "FeatureCollection",
"crs": { "type": "name", "properties": { "name": "urn:ogc:def:crs:OGC:1.3:CRS84" } },
"features": [
{ "type": "Feature", "properties": { "point_type": "origin", "points_str": "45.484592, -122.875586" }, "geometry": { "type": "Point", "coordinates": [ -122.875585962245893, 45.484591895848013 ] } },
{ "type": "Feature", "properties": { "point_type": "destination", "points_str": "45.484983, -122.549083" }, "geometry": { "type": "Point", "coordinates": [ -122.5490834027473, 45.484982582270348 ] } }
]
}
