{
"type": "FeatureCollection",
"crs": { "type": "name", "properties": { "name": "urn:ogc:def:crs:OGC:1.3:CRS84" } },
"features": [
{ "type": "Feature", "properties": { "point_type": "origin", "points_str": "45.483073, -122.823091" }, "geometry": { "type": "Point", "coordinates": [ -122.823090580693972, 45.483073079521461 ] } },
{ "type": "Feature", "properties": { "point_type": "destination", "points_str": "45.42462, -122.576753" }, "geometry": { "type": "Point", "coordinates": [ -122.576753123947228, 45.424619837756069 ] } }
]
}
