{
"type": "FeatureCollection",
"crs": { "type": "name", "properties": { "name": "urn:ogc:def:crs:OGC:1.3:CRS84" } },
"features": [
{ "type": "Feature", "properties": { "point_type": "origin", "points_str": "45.457751, -122.711159" }, "geometry": { "type": "Point", "coordinates": [ -122.711158985087607, 45.457751127087739 ] } },
{ "type": "Feature", "properties": { "point_type": "destination", "points_str": "45.310625, -122.776983" }, "geometry": { "type": "Point", "coordinates": [ -122.776982954606851, 45.310624657197906 ] } }
]
}
