{
"type": "FeatureCollection",
"name": "origin_destination_points",
"crs": { "type": "name", "properties": { "name": "urn:ogc:def:crs:OGC:1.3:CRS84" } },
"features": [
{ "type": "Feature", "properties": { "point_type": "origin", "points_str": "45.512037, -122.608498" }, "geometry": { "type": "Point", "coordinates": [ -122.608497638478354, 45.512036824882998 ] } },
{ "type": "Feature", "properties": { "point_type": "destination", "points_str": "45.484814, -122.594838" }, "geometry": { "type": "Point", "coordinates": [ -122.594837611509419, 45.484813843624877 ] } }
]
}
