{
"type": "FeatureCollection",
"name": "origin_destination_points",
"crs": { "type": "name", "properties": { "name": "urn:ogc:def:crs:OGC:1.3:CRS84" } },
"features": [
{ "type": "Feature", "properties": { "point_type": "origin", "points_str": "45.409609, -122.661103" }, "geometry": { "type": "Point", "coordinates": [ -122.661103425216766, 45.409609040748265 ] } },
{ "type": "Feature", "properties": { "point_type": "destination", "points_str": "45.477251, -122.673242" }, "geometry": { "type": "Point", "coordinates": [ -122.673241798452651, 45.477250961600213 ] } }
]
}
