{
"type": "FeatureCollection",
"crs": { "type": "name", "properties": { "name": "urn:ogc:def:crs:OGC:1.3:CRS84" } },
"features": [
{ "type": "Feature", "properties": { "point_type": "origin", "points_str": "45.507911, -122.648005" }, "geometry": { "type": "Point", "coordinates": [ -122.648005360337507, 45.507910868110528 ] } },
{ "type": "Feature", "properties": { "point_type": "destination", "points_str": "45.357244, -122.607027" }, "geometry": { "type": "Point", "coordinates": [ -122.607027230194888, 45.357244289178851 ] } }
]
}
