{
"type": "FeatureCollection",
"crs": { "type": "name", "properties": { "name": "urn:ogc:def:crs:OGC:1.3:CRS84" } },
"features": [
{ "type": "Feature", "properties": { "point_type": "origin", "points_str": "45.382358, -122.7791" }, "geometry": { "type": "Point", "coordinates": [ -122.779100368216049, 45.382358015945471 ] } },
{ "type": "Feature", "properties": { "point_type": "destination", "points_str": "45.386733, -122.396108" }, "geometry": { "type": "Point", "coordinates": [ -122.396107624245815, 45.386732782939141 ] } }
]
}
