{
"type": "FeatureCollection",
"crs": { "type": "name", "properties": { "name": "urn:ogc:def:crs:OGC:1.3:CRS84" } },
"features": [
{ "type": "Feature", "properties": { "point_type": "origin", "points_str": "45.584609, -122.69142" }, "geometry": { "type": "Point", "coordinates": [ -122.69142026822378, 45.584608643624463 ] } },
{ "type": "Feature", "properties": { "point_type": "destination", "points_str": "45.574018, -122.670599" }, "geometry": { "type": "Point", "coordinates": [ -122.670598706348557, 45.574018129311227 ] } }
]
}
