{
"type": "FeatureCollection",
"crs": { "type": "name", "properties": { "name": "urn:ogc:def:crs:OGC:1.3:CRS84" } },
"features": [
{ "type": "Feature", "properties": { "point_type": "origin", "points_str": "45.398821, -122.627382" }, "geometry": { "type": "Point", "coordinates": [ -122.627382303148622, 45.398821114964825 ] } },
{ "type": "Feature", "properties": { "point_type": "destination", "points_str": "45.392641, -122.583667" }, "geometry": { "type": "Point", "coordinates": [ -122.583667471421336, 45.39264127101697 ] } }
]
}
