{
"type": "FeatureCollection",
"name": "origin_destination_points",
"crs": { "type": "name", "properties": { "name": "urn:ogc:def:crs:OGC:1.3:CRS84" } },
"features": [
{ "type": "Feature", "properties": { "point_type": "origin", "points_str": "45.44224, -122.579931" }, "geometry": { "type": "Point", "coordinates": [ -122.579931040598396, 45.442240060300328 ] } },
{ "type": "Feature", "properties": { "point_type": "destination", "points_str": "45.430025, -122.645531" }, "geometry": { "type": "Point", "coordinates": [ -122.645531286759947, 45.43002504995826 ] } }
]
}
