{
"type": "FeatureCollection",
"name": "origin_destination_points",
"crs": { "type": "name", "properties": { "name": "urn:ogc:def:crs:OGC:1.3:CRS84" } },
"features": [
{ "type": "Feature", "properties": { "point_type": "origin", "points_str": "45.524417, -122.679581" }, "geometry": { "type": "Point", "coordinates": [ -122.679581082902558, 45.524416982946079 ] } },
{ "type": "Feature", "properties": { "point_type": "destination", "points_str": "45.505057, -122.676206" }, "geometry": { "type": "Point", "coordinates": [ -122.676205595146826, 45.505056955532488 ] } }
]
}
