{
"type": "FeatureCollection",
"name": "origin_destination_points",
"crs": { "type": "name", "properties": { "name": "urn:ogc:def:crs:OGC:1.3:CRS84" } },
"features": [
{ "type": "Feature", "properties": { "point_type": "origin", "points_str": "45.557607, -122.624713" }, "geometry": { "type": "Point", "coordinates": [ -122.624713324573477, 45.557607001522797 ] } },
{ "type": "Feature", "properties": { "point_type": "destination", "points_str": "45.536101, -122.409947" }, "geometry": { "type": "Point", "coordinates": [ -122.409947175400703, 45.536100790254771 ] } }
]
}
