{
"type": "FeatureCollection",
"name": "origin_destination_points",
"crs": { "type": "name", "properties": { "name": "urn:ogc:def:crs:OGC:1.3:CRS84" } },
"features": [
{ "type": "Feature", "properties": { "point_type": "origin", "points_str": "45.518842, -123.000844" }, "geometry": { "type": "Point", "coordinates": [ -123.000844454929634, 45.518841838325756 ] } },
{ "type": "Feature", "properties": { "point_type": "destination", "points_str": "45.498557, -122.917451" }, "geometry": { "type": "Point", "coordinates": [ -122.917451443294425, 45.498556718835523 ] } }
]
}
