{
"type": "FeatureCollection",
"crs": { "type": "name", "properties": { "name": "urn:ogc:def:crs:OGC:1.3:CRS84" } },
"features": [
{ "type": "Feature", "properties": { "point_type": "origin", "points_str": "45.433654, -122.629859" }, "geometry": { "type": "Point", "coordinates": [ -122.629859483304728, 45.433654040748138 ] } },
{ "type": "Feature", "properties": { "point_type": "destination", "points_str": "45.367786, -122.583403" }, "geometry": { "type": "Point", "coordinates": [ -122.583403078138389, 45.367786163184547 ] } }
]
}
