{
"type": "FeatureCollection",
"name": "origin_destination_points",
"crs": { "type": "name", "properties": { "name": "urn:ogc:def:crs:OGC:1.3:CRS84" } },
"features": [
{ "type": "Feature", "properties": { "point_type": "origin", "points_str": "45.622628, -122.731431" }, "geometry": { "type": "Point", "coordinates": [ -122.731431314724801, 45.622627786030982 ] } },
{ "type": "Feature", "properties": { "point_type": "destination", "points_str": "45.592619, -122.761742" }, "geometry": { "type": "Point", "coordinates": [ -122.761742403804732, 45.592619238845103 ] } }
]
}
