{
"type": "FeatureCollection",
"name": "origin_destination_points",
"crs": { "type": "name", "properties": { "name": "urn:ogc:def:crs:OGC:1.3:CRS84" } },
"features": [
{ "type": "Feature", "properties": { "point_type": "origin", "points_str": "45.531652, -122.657558" }, "geometry": { "type": "Point", "coordinates": [ -122.657557648392725, 45.531651629308904 ] } },
{ "type": "Feature", "properties": { "point_type": "destination", "points_str": "45.510825, -122.403477" }, "geometry": { "type": "Point", "coordinates": [ -122.403476871941962, 45.510825461899508 ] } }
]
}
