{
"type": "FeatureCollection",
"name": "origin_destination_points",
"crs": { "type": "name", "properties": { "name": "urn:ogc:def:crs:OGC:1.3:CRS84" } },
"features": [
{ "type": "Feature", "properties": { "point_type": "origin", "points_str": "45.504156, -122.604458" }, "geometry": { "type": "Point", "coordinates": [ -122.604457588532199, 45.504156018201009 ] } },
{ "type": "Feature", "properties": { "point_type": "destination", "points_str": "45.384021, -122.640164" }, "geometry": { "type": "Point", "coordinates": [ -122.640163681489199, 45.384020808488842 ] } }
]
}
