{
"type": "FeatureCollection",
"name": "origin_destination_points",
"crs": { "type": "name", "properties": { "name": "urn:ogc:def:crs:OGC:1.3:CRS84" } },
"features": [
{ "type": "Feature", "properties": { "point_type": "origin", "points_str": "45.359187, -122.647381" }, "geometry": { "type": "Point", "coordinates": [ -122.64738080505839, 45.359186961581266 ] } },
{ "type": "Feature", "properties": { "point_type": "destination", "points_str": "45.4265, -122.705679" }, "geometry": { "type": "Point", "coordinates": [ -122.705679236119124, 45.426499752165562 ] } }
]
}
