{
"type": "FeatureCollection",
"name": "origin_destination_points",
"crs": { "type": "name", "properties": { "name": "urn:ogc:def:crs:OGC:1.3:CRS84" } },
"features": [
{ "type": "Feature", "properties": { "point_type": "origin", "points_str": "45.504845, -122.65627" }, "geometry": { "type": "Point", "coordinates": [ -122.656269509156616, 45.504845011980805 ] } },
{ "type": "Feature", "properties": { "point_type": "destination", "points_str": "45.486655, -122.748282" }, "geometry": { "type": "Point", "coordinates": [ -122.748282033432943, 45.486654609029436 ] } }
]
}
