{
"type": "FeatureCollection",
"name": "origin_destination_points",
"crs": { "type": "name", "properties": { "name": "urn:ogc:def:crs:OGC:1.3:CRS84" } },
"features": [
{ "type": "Feature", "properties": { "point_type": "origin", "points_str": "45.386548, -122.753875" }, "geometry": { "type": "Point", "coordinates": [ -122.753874867874501, 45.386548448313562 ] } },
{ "type": "Feature", "properties": { "point_type": "destination", "points_str": "45.448735, -122.82517" }, "geometry": { "type": "Point", "coordinates": [ -122.825170001152102, 45.448735407902582 ] } }
]
}
