{
"type": "FeatureCollection",
"name": "origin_destination_points",
"crs": { "type": "name", "properties": { "name": "urn:ogc:def:crs:OGC:1.3:CRS84" } },
"features": [
{ "type": "Feature", "properties": { "point_type": "origin", "points_str": "45.524027, -122.571442" }, "geometry": { "type": "Point", "coordinates": [ -122.571441531574152, 45.524026820609066 ] } },
{ "type": "Feature", "properties": { "point_type": "destination", "points_str": "45.511198, -122.493476" }, "geometry": { "type": "Point", "coordinates": [ -122.49347606728648, 45.511197785113637 ] } }
]
}
