{
"type": "FeatureCollection",
"crs": { "type": "name", "properties": { "name": "urn:ogc:def:crs:OGC:1.3:CRS84" } },
"features": [
{ "type": "Feature", "properties": { "point_type": "origin", "points_str": "45.522084, -123.072711" }, "geometry": { "type": "Point", "coordinates": [ -123.072710927993953, 45.52208401101408 ] } },
{ "type": "Feature", "properties": { "point_type": "destination", "points_str": "45.43967, -122.724512" }, "geometry": { "type": "Point", "coordinates": [ -122.724511715559672, 45.439670254007922 ] } }
]
}
