{
"type": "FeatureCollection",
"crs": { "type": "name", "properties": { "name": "urn:ogc:def:crs:OGC:1.3:CRS84" } },
"features": [
{ "type": "Feature", "properties": { "point_type": "origin", "points_str": "45.538774, -122.604886" }, "geometry": { "type": "Point", "coordinates": [ -122.604885579220436, 45.538774421435292 ] } },
{ "type": "Feature", "properties": { "point_type": "destination", "points_str": "45.57446, -122.578449" }, "geometry": { "type": "Point", "coordinates": [ -122.578448737644578, 45.574460446496261 ] } }
]
}
