{
"type": "FeatureCollection",
"name": "origin_destination_points",
"crs": { "type": "name", "properties": { "name": "urn:ogc:def:crs:OGC:1.3:CRS84" } },
"features": [
{ "type": "Feature", "properties": { "point_type": "origin", "points_str": "45.57663, -122.66631" }, "geometry": { "type": "Point", "coordinates": [ -122.666310315351453, 45.576630406361595 ] } },
{ "type": "Feature", "properties": { "point_type": "destination", "points_str": "45.563183, -122.64829" }, "geometry": { "type": "Point", "coordinates": [ -122.648289707421426, 45.563183335918389 ] } }
]
}
