{
"type": "FeatureCollection",
"name": "origin_destination_points",
"crs": { "type": "name", "properties": { "name": "urn:ogc:def:crs:OGC:1.3:CRS84" } },
"features": [
{ "type": "Feature", "properties": { "point_type": "origin", "points_str": "45.536809, -122.867322" }, "geometry": { "type": "Point", "coordinates": [ -122.86732233312965, 45.536808984810079 ] } },
{ "type": "Feature", "properties": { "point_type": "destination", "points_str": "45.517563, -123.105189" }, "geometry": { "type": "Point", "coordinates": [ -123.105189072570042, 45.517563315772385 ] } }
]
}
