{
"type": "FeatureCollection",
"crs": { "type": "name", "properties": { "name": "urn:ogc:def:crs:OGC:1.3:CRS84" } },
"features": [
{ "type": "Feature", "properties": { "point_type": "origin", "points_str": "45.500015, -122.647633" }, "geometry": { "type": "Point", "coordinates": [ -122.64763322077485, 45.500014518164576 ] } },
{ "type": "Feature", "properties": { "point_type": "destination", "points_str": "45.4996, -122.550251" }, "geometry": { "type": "Point", "coordinates": [ -122.550251460997131, 45.499599900001606 ] } }
]
}
