{
"type": "FeatureCollection",
"crs": { "type": "name", "properties": { "name": "urn:ogc:def:crs:OGC:1.3:CRS84" } },
"features": [
{ "type": "Feature", "properties": { "point_type": "origin", "points_str": "45.572304, -122.679286" }, "geometry": { "type": "Point", "coordinates": [ -122.679285574881902, 45.572303666486455 ] } },
{ "type": "Feature", "properties": { "point_type": "destination", "points_str": "45.589628, -122.667643" }, "geometry": { "type": "Point", "coordinates": [ -122.667643207298269, 45.589627509531752 ] } }
]
}
