{
"type": "FeatureCollection",
"name": "origin_destination_points",
"crs": { "type": "name", "properties": { "name": "urn:ogc:def:crs:OGC:1.3:CRS84" } },
"features": [
{ "type": "Feature", "properties": { "point_type": "origin", "points_str": "45.524225, -122.561123" }, "geometry": { "type": "Point", "coordinates": [ -122.561122912319107, 45.524224991064472 ] } },
{ "type": "Feature", "properties": { "point_type": "destination", "points_str": "45.531805, -122.684615" }, "geometry": { "type": "Point", "coordinates": [ -122.684615023518688, 45.531805073109872 ] } }
]
}
