{
"type": "FeatureCollection",
"crs": { "type": "name", "properties": { "name": "urn:ogc:def:crs:OGC:1.3:CRS84" } },
"features": [
{ "type": "Feature", "properties": { "point_type": "origin", "points_str": "45.317237, -122.342629" }, "geometry": { "type": "Point", "coordinates": [ -122.342629110726591, 45.317236759542567 ] } },
{ "type": "Feature", "properties": { "point_type": "destination", "points_str": "45.404032, -122.568438" }, "geometry": { "type": "Point", "coordinates": [ -122.568438103194893, 45.404032087086968 ] } }
]
}
