{
"type": "FeatureCollection",
"name": "origin_destination_points",
"crs": { "type": "name", "properties": { "name": "urn:ogc:def:crs:OGC:1.3:CRS84" } },
"features": [
{ "type": "Feature", "properties": { "point_type": "origin", "points_str": "45.523818, -122.54176" }, "geometry": { "type": "Point", "coordinates": [ -122.541760052038555, 45.523818078579765 ] } },
{ "type": "Feature", "properties": { "point_type": "destination", "points_str": "45.546209, -122.86825" }, "geometry": { "type": "Point", "coordinates": [ -122.868249578687937, 45.546208929588083 ] } }
]
}
