{
"type": "FeatureCollection",
"crs": { "type": "name", "properties": { "name": "urn:ogc:def:crs:OGC:1.3:CRS84" } },
"features": [
{ "type": "Feature", "properties": { "point_type": "origin", "points_str": "45.458252, -122.709804" }, "geometry": { "type": "Point", "coordinates": [ -122.709804299730806, 45.458252164484755 ] } },
{ "type": "Feature", "properties": { "point_type": "destination", "points_str": "45.416622, -122.665215" }, "geometry": { "type": "Point", "coordinates": [ -122.665214952915917, 45.416621953805056 ] } }
]
}
