{
"type": "FeatureCollection",
"name": "origin_destination_points",
"crs": { "type": "name", "properties": { "name": "urn:ogc:def:crs:OGC:1.3:CRS84" } },
"features": [
{ "type": "Feature", "properties": { "point_type": "origin", "points_str": "45.5205, -122.977638" }, "geometry": { "type": "Point", "coordinates": [ -122.977638011512681, 45.520499574791025 ] } },
{ "type": "Feature", "properties": { "point_type": "destination", "points_str": "45.52517, -122.693749" }, "geometry": { "type": "Point", "coordinates": [ -122.693748750109251, 45.525170028716488 ] } }
]
}
