{
"type": "FeatureCollection",
"name": "origin_destination_points",
"crs": { "type": "name", "properties": { "name": "urn:ogc:def:crs:OGC:1.3:CRS84" } },
"features": [
{ "type": "Feature", "properties": { "point_type": "origin", "points_str": "45.518417, -122.583566" }, "geometry": { "type": "Point", "coordinates": [ -122.583565792205007, 45.518417374770948 ] } },
{ "type": "Feature", "properties": { "point_type": "destination", "points_str": "45.471439, -122.564449" }, "geometry": { "type": "Point", "coordinates": [ -122.564449425907938, 45.471439046487959 ] } }
]
}
