{
"type": "FeatureCollection",
"name": "origin_destination_points",
"crs": { "type": "name", "properties": { "name": "urn:ogc:def:crs:OGC:1.3:CRS84" } },
"features": [
{ "type": "Feature", "properties": { "point_type": "origin", "points_str": "45.53896, -122.605038" }, "geometry": { "type": "Point", "coordinates": [ -122.60503789593534, 45.53896044837299 ] } },
{ "type": "Feature", "properties": { "point_type": "destination", "points_str": "45.425181, -122.49134" }, "geometry": { "type": "Point", "coordinates": [ -122.491339733718618, 45.42518063569986 ] } }
]
}
