{
"type": "FeatureCollection",
"name": "origin_destination_points",
"crs": { "type": "name", "properties": { "name": "urn:ogc:def:crs:OGC:1.3:CRS84" } },
"features": [
{ "type": "Feature", "properties": { "point_type": "origin", "points_str": "45.510166, -122.741314" }, "geometry": { "type": "Point", "coordinates": [ -122.741314020574777, 45.510165535222782 ] } },
{ "type": "Feature", "properties": { "point_type": "destination", "points_str": "45.489069, -122.728524" }, "geometry": { "type": "Point", "coordinates": [ -122.728524400211953, 45.489069355330763 ] } }
]
}
