{
"type": "FeatureCollection",
"name": "origin_destination_points",
"crs": { "type": "name", "properties": { "name": "urn:ogc:def:crs:OGC:1.3:CRS84" } },
"features": [
{ "type": "Feature", "properties": { "point_type": "origin", "points_str": "45.521431, -122.487935" }, "geometry": { "type": "Point", "coordinates": [ -122.487934835217132, 45.521431164220026 ] } },
{ "type": "Feature", "properties": { "point_type": "destination", "points_str": "45.513072, -122.590096" }, "geometry": { "type": "Point", "coordinates": [ -122.590095547156551, 45.513071801812742 ] } }
]
}
