{
"type": "FeatureCollection",
"name": "origin_destination_points",
"crs": { "type": "name", "properties": { "name": "urn:ogc:def:crs:OGC:1.3:CRS84" } },
"features": [
{ "type": "Feature", "properties": { "point_type": "origin", "points_str": "45.521537, -122.738668" }, "geometry": { "type": "Point", "coordinates": [ -122.738668490075796, 45.521536740534508 ] } },
{ "type": "Feature", "properties": { "point_type": "destination", "points_str": "45.520722, -122.78974" }, "geometry": { "type": "Point", "coordinates": [ -122.789740113307886, 45.520721767318001 ] } }
]
}
