{
"type": "FeatureCollection",
"crs": { "type": "name", "properties": { "name": "urn:ogc:def:crs:OGC:1.3:CRS84" } },
"features": [
{ "type": "Feature", "properties": { "point_type": "origin", "points_str": "45.487047, -122.608173" }, "geometry": { "type": "Point", "coordinates": [ -122.608173009089725, 45.487046581421048 ] } },
{ "type": "Feature", "properties": { "point_type": "destination", "points_str": "45.447443, -122.587328" }, "geometry": { "type": "Point", "coordinates": [ -122.587327948148257, 45.447442551645395 ] } }
]
}
