{
"type": "FeatureCollection",
"crs": { "type": "name", "properties": { "name": "urn:ogc:def:crs:OGC:1.3:CRS84" } },
"features": [
{ "type": "Feature", "properties": { "point_type": "origin", "points_str": "45.588661, -122.749155" }, "geometry": { "type": "Point", "coordinates": [ -122.749155262626886, 45.588660907553511 ] } },
{ "type": "Feature", "properties": { "point_type": "destination", "points_str": "45.519845, -122.5332" }, "geometry": { "type": "Point", "coordinates": [ -122.533200331056989, 45.519845486379715 ] } }
]
}
