{
"type": "FeatureCollection",
"name": "origin_destination_points",
"crs": { "type": "name", "properties": { "name": "urn:ogc:def:crs:OGC:1.3:CRS84" } },
"features": [
{ "type": "Feature", "properties": { "point_type": "origin", "points_str": "45.499465, -122.586023" }, "geometry": { "type": "Point", "coordinates": [ -122.586023149557349, 45.499465353214752 ] } },
{ "type": "Feature", "properties": { "point_type": "destination", "points_str": "45.549265, -122.62538" }, "geometry": { "type": "Point", "coordinates": [ -122.625379708723671, 45.549264840130931 ] } }
]
}
