{
"type": "FeatureCollection",
"name": "origin_destination_points",
"crs": { "type": "name", "properties": { "name": "urn:ogc:def:crs:OGC:1.3:CRS84" } },
"features": [
{ "type": "Feature", "properties": { "point_type": "origin", "points_str": "45.379396, -122.759332" }, "geometry": { "type": "Point", "coordinates": [ -122.759331796871251, 45.37939619749303 ] } },
{ "type": "Feature", "properties": { "point_type": "destination", "points_str": "45.401785, -122.795556" }, "geometry": { "type": "Point", "coordinates": [ -122.795556177707724, 45.401785343312902 ] } }
]
}
