{
"type": "FeatureCollection",
"name": "origin_destination_points",
"crs": { "type": "name", "properties": { "name": "urn:ogc:def:crs:OGC:1.3:CRS84" } },
"features": [
{ "type": "Feature", "properties": { "point_type": "origin", "points_str": "45.477149, -122.58505" }, "geometry": { "type": "Point", "coordinates": [ -122.58505045641563, 45.477149042608424 ] } },
{ "type": "Feature", "properties": { "point_type": "destination", "points_str": "45.505868, -122.627874" }, "geometry": { "type": "Point", "coordinates": [ -122.627873779679049, 45.505868236650123 ] } }
]
}
