{
"type": "FeatureCollection",
"name": "origin_destination_points",
"crs": { "type": "name", "properties": { "name": "urn:ogc:def:crs:OGC:1.3:CRS84" } },
"features": [
{ "type": "Feature", "properties": { "point_type": "origin", "points_str": "45.502658, -122.575779" }, "geometry": { "type": "Point", "coordinates": [ -122.575778703689565, 45.50265772071247 ] } },
{ "type": "Feature", "properties": { "point_type": "destination", "points_str": "45.563407, -122.701033" }, "geometry": { "type": "Point", "coordinates": [ -122.701033316696495, 45.563407062598671 ] } }
]
}
