{
"type": "FeatureCollection",
"name": "origin_destination_points",
"crs": { "type": "name", "properties": { "name": "urn:ogc:def:crs:OGC:1.3:CRS84" } },
"features": [
{ "type": "Feature", "properties": { "point_type": "origin", "points_str": "45.50763, -122.698714" }, "geometry": { "type": "Point", "coordinates": [ -122.698713844451547, 45.507630101746862 ] } },
{ "type": "Feature", "properties": { "point_type": "destination", "points_str": "45.508044, -122.734101" }, "geometry": { "type": "Point", "coordinates": [ -122.734101240592963, 45.508043960587216 ] } }
]
}
