{
"type": "FeatureCollection",
"name": "origin_destination_points",
"crs": { "type": "name", "properties": { "name": "urn:ogc:def:crs:OGC:1.3:CRS84" } },
"features": [
{ "type": "Feature", "properties": { "point_type": "origin", "points_str": "45.4547, -122.579237" }, "geometry": { "type": "Point", "coordinates": [ -122.57923747968519, 45.454700266269732 ] } },
{ "type": "Feature", "properties": { "point_type": "destination", "points_str": "45.521819, -122.651952" }, "geometry": { "type": "Point", "coordinates": [ -122.651951895856996, 45.521818567395982 ] } }
]
}
