{
"type": "FeatureCollection",
"name": "origin_destination_points",
"crs": { "type": "name", "properties": { "name": "urn:ogc:def:crs:OGC:1.3:CRS84" } },
"features": [
{ "type": "Feature", "properties": { "point_type": "origin", "points_str": "45.495889, -122.557106" }, "geometry": { "type": "Point", "coordinates": [ -122.557106174895864, 45.49588916406379 ] } },
{ "type": "Feature", "properties": { "point_type": "destination", "points_str": "45.497179, -122.580286" }, "geometry": { "type": "Point", "coordinates": [ -122.580286331851468, 45.497179107945335 ] } }
]
}
