{
"type": "FeatureCollection",
"crs": { "type": "name", "properties": { "name": "urn:ogc:def:crs:OGC:1.3:CRS84" } },
"features": [
{ "type": "Feature", "properties": { "point_type": "origin", "points_str": "45.517709, -123.066709" }, "geometry": { "type": "Point", "coordinates": [ -123.066709199487846, 45.517708882847231 ] } },
{ "type": "Feature", "properties": { "point_type": "destination", "points_str": "45.528455, -122.971083" }, "geometry": { "type": "Point", "coordinates": [ -122.971083105667262, 45.528455193058683 ] } }
]
}
