{
"type": "FeatureCollection",
"name": "origin_destination_points",
"crs": { "type": "name", "properties": { "name": "urn:ogc:def:crs:OGC:1.3:CRS84" } },
"features": [
{ "type": "Feature", "properties": { "point_type": "origin", "points_str": "45.589895, -122.737434" }, "geometry": { "type": "Point", "coordinates": [ -122.737433961778009, 45.589895374377548 ] } },
{ "type": "Feature", "properties": { "point_type": "destination", "points_str": "45.387099, -122.642449" }, "geometry": { "type": "Point", "coordinates": [ -122.642449288468981, 45.387098746111363 ] } }
]
}
