{
"type": "FeatureCollection",
"name": "origin_destination_points",
"crs": { "type": "name", "properties": { "name": "urn:ogc:def:crs:OGC:1.3:CRS84" } },
"features": [
{ "type": "Feature", "properties": { "point_type": "origin", "points_str": "45.390301, -122.64094" }, "geometry": { "type": "Point", "coordinates": [ -122.640940141828594, 45.390301392807025 ] } },
{ "type": "Feature", "properties": { "point_type": "destination", "points_str": "45.465114, -122.671355" }, "geometry": { "type": "Point", "coordinates": [ -122.671354937492652, 45.46511440364457 ] } }
]
}
