{
"type": "FeatureCollection",
"name": "origin_destination_points",
"crs": { "type": "name", "properties": { "name": "urn:ogc:def:crs:OGC:1.3:CRS84" } },
"features": [
{ "type": "Feature", "properties": { "point_type": "origin", "points_str": "45.511384, -122.626575" }, "geometry": { "type": "Point", "coordinates": [ -122.626574737961533, 45.511383660749949 ] } },
{ "type": "Feature", "properties": { "point_type": "destination", "points_str": "45.397421, -122.605829" }, "geometry": { "type": "Point", "coordinates": [ -122.605829485981715, 45.397420955965828 ] } }
]
}
