{
"type": "FeatureCollection",
"crs": { "type": "name", "properties": { "name": "urn:ogc:def:crs:OGC:1.3:CRS84" } },
"features": [
{ "type": "Feature", "properties": { "point_type": "origin", "points_str": "45.4479, -122.620799" }, "geometry": { "type": "Point", "coordinates": [ -122.620799131256064, 45.447899826714696 ] } },
{ "type": "Feature", "properties": { "point_type": "destination", "points_str": "45.613966, -122.674687" }, "geometry": { "type": "Point", "coordinates": [ -122.674686694223652, 45.613966154530083 ] } }
]
}
