{
"type": "FeatureCollection",
"name": "origin_destination_points",
"crs": { "type": "name", "properties": { "name": "urn:ogc:def:crs:OGC:1.3:CRS84" } },
"features": [
{ "type": "Feature", "properties": { "point_type": "origin", "points_str": "45.467007, -122.563199" }, "geometry": { "type": "Point", "coordinates": [ -122.563198728596944, 45.467006768559557 ] } },
{ "type": "Feature", "properties": { "point_type": "destination", "points_str": "45.516276, -122.665912" }, "geometry": { "type": "Point", "coordinates": [ -122.665912022779509, 45.516276443122607 ] } }
]
}
