{
"type": "FeatureCollection",
"name": "origin_destination_points",
"crs": { "type": "name", "properties": { "name": "urn:ogc:def:crs:OGC:1.3:CRS84" } },
"features": [
{ "type": "Feature", "properties": { "point_type": "origin", "points_str": "45.49321, -122.628824" }, "geometry": { "type": "Point", "coordinates": [ -122.628824291306685, 45.493210228265745 ] } },
{ "type": "Feature", "properties": { "point_type": "destination", "points_str": "45.52201, -122.679339" }, "geometry": { "type": "Point", "coordinates": [ -122.679338687732312, 45.522009832778998 ] } }
]
}
