{
"type": "FeatureCollection",
"name": "origin_destination_points",
"crs": { "type": "name", "properties": { "name": "urn:ogc:def:crs:OGC:1.3:CRS84" } },
"features": [
{ "type": "Feature", "properties": { "point_type": "origin", "points_str": "45.465046, -122.579677" }, "geometry": { "type": "Point", "coordinates": [ -122.579677131583139, 45.465046113180911 ] } },
{ "type": "Feature", "properties": { "point_type": "destination", "points_str": "45.563908, -122.602534" }, "geometry": { "type": "Point", "coordinates": [ -122.60253393650946, 45.563908353824992 ] } }
]
}
