{
"type": "FeatureCollection",
"crs": { "type": "name", "properties": { "name": "urn:ogc:def:crs:OGC:1.3:CRS84" } },
"features": [
{ "type": "Feature", "properties": { "point_type": "origin", "points_str": "45.504859, -122.532755" }, "geometry": { "type": "Point", "coordinates": [ -122.53275507008901, 45.50485932050092 ] } },
{ "type": "Feature", "properties": { "point_type": "destination", "points_str": "45.480958, -122.647817" }, "geometry": { "type": "Point", "coordinates": [ -122.647817379180921, 45.480958244584684 ] } }
]
}
