{
"type": "FeatureCollection",
"crs": { "type": "name", "properties": { "name": "urn:ogc:def:crs:OGC:1.3:CRS84" } },
"features": [
{ "type": "Feature", "properties": { "point_type": "origin", "points_str": "45.502328, -122.536459" }, "geometry": { "type": "Point", "coordinates": [ -122.536459482041892, 45.502327812107829 ] } },
{ "type": "Feature", "properties": { "point_type": "destination", "points_str": "45.583103, -122.678922" }, "geometry": { "type": "Point", "coordinates": [ -122.678922194957963, 45.583102997765245 ] } }
]
}
