{
"type": "FeatureCollection",
"name": "origin_destination_points",
"crs": { "type": "name", "properties": { "name": "urn:ogc:def:crs:OGC:1.3:CRS84" } },
"features": [
{ "type": "Feature", "properties": { "point_type": "origin", "points_str": "45.516962, -122.748193" }, "geometry": { "type": "Point", "coordinates": [ -122.748193210674671, 45.516962418514282 ] } },
{ "type": "Feature", "properties": { "point_type": "destination", "points_str": "45.489073, -122.580637" }, "geometry": { "type": "Point", "coordinates": [ -122.580636782463628, 45.489072581617918 ] } }
]
}
