{
"type": "FeatureCollection",
"crs": { "type": "name", "properties": { "name": "urn:ogc:def:crs:OGC:1.3:CRS84" } },
"features": [
{ "type": "Feature", "properties": { "point_type": "origin", "points_str": "45.535298, -122.676477" }, "geometry": { "type": "Point", "coordinates": [ -122.676476840612366, 45.535297555529858 ] } },
{ "type": "Feature", "properties": { "point_type": "destination", "points_str": "45.571904, -122.701678" }, "geometry": { "type": "Point", "coordinates": [ -122.701677758124205, 45.571904116036656 ] } }
]
}
