{
"type": "FeatureCollection",
"name": "origin_destination_points",
"crs": { "type": "name", "properties": { "name": "urn:ogc:def:crs:OGC:1.3:CRS84" } },
"features": [
{ "type": "Feature", "properties": { "point_type": "origin", "points_str": "45.453887, -122.674274" }, "geometry": { "type": "Point", "coordinates": [ -122.674273675957508, 45.453887249403024 ] } },
{ "type": "Feature", "properties": { "point_type": "destination", "points_str": "45.524394, -122.630315" }, "geometry": { "type": "Point", "coordinates": [ -122.630314794803283, 45.524394127535601 ] } }
]
}
