{
"type": "FeatureCollection",
"crs": { "type": "name", "properties": { "name": "urn:ogc:def:crs:OGC:1.3:CRS84" } },
"features": [
{ "type": "Feature", "properties": { "point_type": "origin", "points_str": "45.60311, -122.784604" }, "geometry": { "type": "Point", "coordinates": [ -122.784604385680737, 45.603110075324643 ] } },
{ "type": "Feature", "properties": { "point_type": "destination", "points_str": "45.52524, -122.67081" }, "geometry": { "type": "Point", "coordinates": [ -122.670810223053238, 45.525239553137915 ] } }
]
}
