{
"type": "FeatureCollection",
"crs": { "type": "name", "properties": { "name": "urn:ogc:def:crs:OGC:1.3:CRS84" } },
"features": [
{ "type": "Feature", "properties": { "point_type": "origin", "points_str": "45.462929, -122.821898" }, "geometry": { "type": "Point", "coordinates": [ -122.821898291717389, 45.462929282312302 ] } },
{ "type": "Feature", "properties": { "point_type": "destination", "points_str": "45.534731, -122.871157" }, "geometry": { "type": "Point", "coordinates": [ -122.871156595604518, 45.534731189021961 ] } }
]
}
