{
"type": "FeatureCollection",
"crs": { "type": "name", "properties": { "name": "urn:ogc:def:crs:OGC:1.3:CRS84" } },
"features": [
{ "type": "Feature", "properties": { "point_type": "origin", "points_str": "45.520166, -122.615514" }, "geometry": { "type": "Point", "coordinates": [ -122.615514212082743, 45.52016564259818 ] } },
{ "type": "Feature", "properties": { "point_type": "destination", "points_str": "45.44561, -122.617735" }, "geometry": { "type": "Point", "coordinates": [ -122.617734665966495, 45.445610213959725 ] } }
]
}
