{
"type": "FeatureCollection",
"name": "origin_destination_points",
"crs": { "type": "name", "properties": { "name": "urn:ogc:def:crs:OGC:1.3:CRS84" } },
"features": [
{ "type": "Feature", "properties": { "point_type": "origin", "points_str": "45.525815, -122.698077" }, "geometry": { "type": "Point", "coordinates": [ -122.698076745334802, 45.525815187734707 ] } },
{ "type": "Feature", "properties": { "point_type": "destination", "points_str": "45.534631, -122.423346" }, "geometry": { "type": "Point", "coordinates": [ -122.42334635497167, 45.534631153985607 ] } }
]
}
