{
"type": "FeatureCollection",
"name": "origin_destination_points",
"crs": { "type": "name", "properties": { "name": "urn:ogc:def:crs:OGC:1.3:CRS84" } },
"features": [
{ "type": "Feature", "properties": { "point_type": "origin", "points_str": "45.448831, -122.637517" }, "geometry": { "type": "Point", "coordinates": [ -122.637516870711281, 45.448830733846563 ] } },
{ "type": "Feature", "properties": { "point_type": "destination", "points_str": "45.50385, -122.618382" }, "geometry": { "type": "Point", "coordinates": [ -122.618381506114972, 45.503850117001136 ] } }
]
}
