{
"type": "FeatureCollection",
"name": "origin_destination_points",
"crs": { "type": "name", "properties": { "name": "urn:ogc:def:crs:OGC:1.3:CRS84" } },
"features": [
{ "type": "Feature", "properties": { "point_type": "origin", "points_str": "45.485955, -122.794143" }, "geometry": { "type": "Point", "coordinates": [ -122.794142682830213, 45.485955363799391 ] } },
{ "type": "Feature", "properties": { "point_type": "destination", "points_str": "45.491425, -122.626123" }, "geometry": { "type": "Point", "coordinates": [ -122.626123272543907, 45.491424969901828 ] } }
]
}
