{
"type": "FeatureCollection",
"crs": { "type": "name", "properties": { "name": "urn:ogc:def:crs:OGC:1.3:CRS84" } },
"features": [
{ "type": "Feature", "properties": { "point_type": "origin", "points_str": "45.469976, -122.587166" }, "geometry": { "type": "Point", "coordinates": [ -122.587166100392551, 45.469976340175812 ] } },
{ "type": "Feature", "properties": { "point_type": "destination", "points_str": "45.404922, -122.618671" }, "geometry": { "type": "Point", "coordinates": [ -122.61867074323969, 45.404922135630173 ] } }
]
}
