{
"type": "FeatureCollection",
"name": "origin_destination_points",
"crs": { "type": "name", "properties": { "name": "urn:ogc:def:crs:OGC:1.3:CRS84" } },
"features": [
{ "type": "Feature", "properties": { "point_type": "origin", "points_str": "45.464571, -122.678588" }, "geometry": { "type": "Point", "coordinates": [ -122.678588493950343, 45.464570999386382 ] } },
{ "type": "Feature", "properties": { "point_type": "destination", "points_str": "45.464832, -122.783283" }, "geometry": { "type": "Point", "coordinates": [ -122.783283304714033, 45.464832139422811 ] } }
]
}
