{
"type": "FeatureCollection",
"crs": { "type": "name", "properties": { "name": "urn:ogc:def:crs:OGC:1.3:CRS84" } },
"features": [
{ "type": "Feature", "properties": { "point_type": "origin", "points_str": "45.564021, -122.589925" }, "geometry": { "type": "Point", "coordinates": [ -122.589924947802004, 45.56402094960454 ] } },
{ "type": "Feature", "properties": { "point_type": "destination", "points_str": "45.402455, -122.58545" }, "geometry": { "type": "Point", "coordinates": [ -122.585449739405789, 45.402455435277616 ] } }
]
}
