{
"type": "FeatureCollection",
"name": "origin_destination_points",
"crs": { "type": "name", "properties": { "name": "urn:ogc:def:crs:OGC:1.3:CRS84" } },
"features": [
{ "type": "Feature", "properties": { "point_type": "origin", "points_str": "45.493791, -122.858983" }, "geometry": { "type": "Point", "coordinates": [ -122.858982700195384, 45.493790594000387 ] } },
{ "type": "Feature", "properties": { "point_type": "destination", "points_str": "45.531471, -122.563402" }, "geometry": { "type": "Point", "coordinates": [ -122.563402322372681, 45.531470662113314 ] } }
]
}
