{
"type": "FeatureCollection",
"name": "origin_destination_points",
"crs": { "type": "name", "properties": { "name": "urn:ogc:def:crs:OGC:1.3:CRS84" } },
"features": [
{ "type": "Feature", "properties": { "point_type": "origin", "points_str": "45.495747, -122.573646" }, "geometry": { "type": "Point", "coordinates": [ -122.573646076838685, 45.495747298978991 ] } },
{ "type": "Feature", "properties": { "point_type": "destination", "points_str": "45.466207, -122.67363" }, "geometry": { "type": "Point", "coordinates": [ -122.673629616788233, 45.466207018594694 ] } }
]
}
