{
"type": "FeatureCollection",
"crs": { "type": "name", "properties": { "name": "urn:ogc:def:crs:OGC:1.3:CRS84" } },
"features": [
{ "type": "Feature", "properties": { "point_type": "origin", "points_str": "45.492706, -122.777137" }, "geometry": { "type": "Point", "coordinates": [ -122.77713703762889, 45.492706075433489 ] } },
{ "type": "Feature", "properties": { "point_type": "destination", "points_str": "45.571134, -122.556451" }, "geometry": { "type": "Point", "coordinates": [ -122.55645104054166, 45.571134178665972 ] } }
]
}
