{
"type": "FeatureCollection",
"name": "origin_destination_points",
"crs": { "type": "name", "properties": { "name": "urn:ogc:def:crs:OGC:1.3:CRS84" } },
"features": [
{ "type": "Feature", "properties": { "point_type": "origin", "points_str": "45.514056, -122.565121" }, "geometry": { "type": "Point", "coordinates": [ -122.565120675087869, 45.51405613757705 ] } },
{ "type": "Feature", "properties": { "point_type": "destination", "points_str": "45.601289, -122.765545" }, "geometry": { "type": "Point", "coordinates": [ -122.765545137547477, 45.601288865127238 ] } }
]
}
