{
"type": "FeatureCollection",
"crs": { "type": "name", "properties": { "name": "urn:ogc:def:crs:OGC:1.3:CRS84" } },
"features": [
{ "type": "Feature", "properties": { "point_type": "origin", "points_str": "45.521653, -122.652076" }, "geometry": { "type": "Point", "coordinates": [ -122.652075603777021, 45.521653024502172 ] } },
{ "type": "Feature", "properties": { "point_type": "destination", "points_str": "45.517119, -122.822124" }, "geometry": { "type": "Point", "coordinates": [ -122.822123534787011, 45.517118671865887 ] } }
]
}
