{
"type": "FeatureCollection",
"crs": { "type": "name", "properties": { "name": "urn:ogc:def:crs:OGC:1.3:CRS84" } },
"features": [
{ "type": "Feature", "properties": { "point_type": "origin", "points_str": "45.366705, -122.846499" }, "geometry": { "type": "Point", "coordinates": [ -122.846499168255278, 45.366704688358986 ] } },
{ "type": "Feature", "properties": { "point_type": "destination", "points_str": "45.547344, -122.598759" }, "geometry": { "type": "Point", "coordinates": [ -122.598758868208662, 45.547343688683434 ] } }
]
}
