{
"type": "FeatureCollection",
"name": "origin_destination_points",
"crs": { "type": "name", "properties": { "name": "urn:ogc:def:crs:OGC:1.3:CRS84" } },
"features": [
{ "type": "Feature", "properties": { "point_type": "origin", "points_str": "45.429372, -122.762212" }, "geometry": { "type": "Point", "coordinates": [ -122.76221183309211, 45.429371745661548 ] } },
{ "type": "Feature", "properties": { "point_type": "destination", "points_str": "45.501113, -122.905103" }, "geometry": { "type": "Point", "coordinates": [ -122.905103223863861, 45.501112738820979 ] } }
]
}
