{
"type": "FeatureCollection",
"name": "origin_destination_points",
"crs": { "type": "name", "properties": { "name": "urn:ogc:def:crs:OGC:1.3:CRS84" } },
"features": [
{ "type": "Feature", "properties": { "point_type": "origin", "points_str": "45.421636, -122.580004" }, "geometry": { "type": "Point", "coordinates": [ -122.580003726623872, 45.421635608586968 ] } },
{ "type": "Feature", "properties": { "point_type": "destination", "points_str": "45.369384, -122.617835" }, "geometry": { "type": "Point", "coordinates": [ -122.617835398093504, 45.369384421916031 ] } }
]
}
