{
"type": "FeatureCollection",
"name": "origin_destination_points",
"crs": { "type": "name", "properties": { "name": "urn:ogc:def:crs:OGC:1.3:CRS84" } },
"features": [
{ "type": "Feature", "properties": { "point_type": "origin", "points_str": "45.506159, -122.536044" }, "geometry": { "type": "Point", "coordinates": [ -122.536043590180938, 45.506159374686611 ] } },
{ "type": "Feature", "properties": { "point_type": "destination", "points_str": "45.547308, -122.525806" }, "geometry": { "type": "Point", "coordinates": [ -122.525806251822516, 45.547308028828866 ] } }
]
}
