{
"type": "FeatureCollection",
"crs": { "type": "name", "properties": { "name": "urn:ogc:def:crs:OGC:1.3:CRS84" } },
"features": [
{ "type": "Feature", "properties": { "point_type": "origin", "points_str": "45.490033, -122.638829" }, "geometry": { "type": "Point", "coordinates": [ -122.63882930043367, 45.490033325872979 ] } },
{ "type": "Feature", "properties": { "point_type": "destination", "points_str": "45.486984, -122.591569" }, "geometry": { "type": "Point", "coordinates": [ -122.591568821076137, 45.486983802700486 ] } }
]
}
