{
"type": "FeatureCollection",
"name": "origin_destination_points",
"crs": { "type": "name", "properties": { "name": "urn:ogc:def:crs:OGC:1.3:CRS84" } },
"features": [
{ "type": "Feature", "properties": { "point_type": "origin", "points_str": "45.532369, -122.698697" }, "geometry": { "type": "Point", "coordinates": [ -122.698697154783034, 45.532368838024574 ] } },
{ "type": "Feature", "properties": { "point_type": "destination", "points_str": "45.484382, -122.721226" }, "geometry": { "type": "Point", "coordinates": [ -122.721225861997169, 45.484381618493039 ] } }
]
}
