{
"type": "FeatureCollection",
"name": "origin_destination_points",
"crs": { "type": "name", "properties": { "name": "urn:ogc:def:crs:OGC:1.3:CRS84" } },
"features": [
{ "type": "Feature", "properties": { "point_type": "origin", "points_str": "45.52746, -122.94923" }, "geometry": { "type": "Point", "coordinates": [ -122.949230463562358, 45.527459703785425 ] } },
{ "type": "Feature", "properties": { "point_type": "destination", "points_str": "45.491539, -122.784116" }, "geometry": { "type": "Point", "coordinates": [ -122.784115590324646, 45.491539193660792 ] } }
]
}
