{
"type": "FeatureCollection",
"crs": { "type": "name", "properties": { "name": "urn:ogc:def:crs:OGC:1.3:CRS84" } },
"features": [
{ "type": "Feature", "properties": { "point_type": "origin", "points_str": "45.483385, -122.451141" }, "geometry": { "type": "Point", "coordinates": [ -122.451141456462494, 45.483385496902216 ] } },
{ "type": "Feature", "properties": { "point_type": "destination", "points_str": "45.489566, -122.482965" }, "geometry": { "type": "Point", "coordinates": [ -122.482964878184745, 45.489565843419882 ] } }
]
}
