{
"type": "FeatureCollection",
"name": "origin_destination_points",
"crs": { "type": "name", "properties": { "name": "urn:ogc:def:crs:OGC:1.3:CRS84" } },
"features": [
{ "type": "Feature", "properties": { "point_type": "origin", "points_str": "45.546447, -122.573839" }, "geometry": { "type": "Point", "coordinates": [ -122.573839389265942, 45.546447269472054 ] } },
{ "type": "Feature", "properties": { "point_type": "destination", "points_str": "45.530301, -122.602297" }, "geometry": { "type": "Point", "coordinates": [ -122.60229685937081, 45.530300578423656 ] } }
]
}
