{
"type": "FeatureCollection",
"crs": { "type": "name", "properties": { "name": "urn:ogc:def:crs:OGC:1.3:CRS84" } },
"features": [
{ "type": "Feature", "properties": { "point_type": "origin", "points_str": "45.489123, -122.557931" }, "geometry": { "type": "Point", "coordinates": [ -122.557931357095498, 45.489122831248046 ] } },
{ "type": "Feature", "properties": { "point_type": "destination", "points_str": "45.524598, -122.708749" }, "geometry": { "type": "Point", "coordinates": [ -122.708748581326176, 45.524597599235335 ] } }
]
}
