{
"type": "FeatureCollection",
"crs": { "type": "name", "properties": { "name": "urn:ogc:def:crs:OGC:1.3:CRS84" } },
"features": [
{ "type": "Feature", "properties": { "point_type": "origin", "points_str": "45.540121, -122.688516" }, "geometry": { "type": "Point", "coordinates": [ -122.688515728970899, 45.540120615846973 ] } },
{ "type": "Feature", "properties": { "point_type": "destination", "points_str": "45.489608, -122.804854" }, "geometry": { "type": "Point", "coordinates": [ -122.804854478945842, 45.489608321051612 ] } }
]
}
