{
"type": "FeatureCollection",
"name": "origin_destination_points",
"crs": { "type": "name", "properties": { "name": "urn:ogc:def:crs:OGC:1.3:CRS84" } },
"features": [
{ "type": "Feature", "properties": { "point_type": "origin", "points_str": "45.422998, -122.58259" }, "geometry": { "type": "Point", "coordinates": [ -122.582590284197749, 45.422997602044958 ] } },
{ "type": "Feature", "properties": { "point_type": "destination", "points_str": "45.396396, -122.623527" }, "geometry": { "type": "Point", "coordinates": [ -122.623526707952209, 45.396395785180346 ] } }
]
}
