{
"type": "FeatureCollection",
"name": "origin_destination_points",
"crs": { "type": "name", "properties": { "name": "urn:ogc:def:crs:OGC:1.3:CRS84" } },
"features": [
{ "type": "Feature", "properties": { "point_type": "origin", "points_str": "45.353878, -122.614773" }, "geometry": { "type": "Point", "coordinates": [ -122.614773029844997, 45.353877726027839 ] } },
{ "type": "Feature", "properties": { "point_type": "destination", "points_str": "45.41831, -122.634995" }, "geometry": { "type": "Point", "coordinates": [ -122.634994609167578, 45.418309751838059 ] } }
]
}
