{
"type": "FeatureCollection",
"crs": { "type": "name", "properties": { "name": "urn:ogc:def:crs:OGC:1.3:CRS84" } },
"features": [
{ "type": "Feature", "properties": { "point_type": "origin", "points_str": "45.519449, -122.674633" }, "geometry": { "type": "Point", "coordinates": [ -122.674633130505953, 45.519449373622791 ] } },
{ "type": "Feature", "properties": { "point_type": "destination", "points_str": "45.530689, -122.990105" }, "geometry": { "type": "Point", "coordinates": [ -122.990105148078698, 45.530689023840182 ] } }
]
}
