{
"type": "FeatureCollection",
"name": "origin_destination_points",
"crs": { "type": "name", "properties": { "name": "urn:ogc:def:crs:OGC:1.3:CRS84" } },
"features": [
{ "type": "Feature", "properties": { "point_type": "origin", "points_str": "45.532303, -122.671394" }, "geometry": { "type": "Point", "coordinates": [ -122.671393648984079, 45.53230346872386 ] } },
{ "type": "Feature", "properties": { "point_type": "destination", "points_str": "45.503912, -122.5513" }, "geometry": { "type": "Point", "coordinates": [ -122.551300360952382, 45.503911837828127 ] } }
]
}
