{
"type": "FeatureCollection",
"name": "origin_destination_points",
"crs": { "type": "name", "properties": { "name": "urn:ogc:def:crs:OGC:1.3:CRS84" } },
"features": [
{ "type": "Feature", "properties": { "point_type": "origin", "points_str": "45.486759, -122.732637" }, "geometry": { "type": "Point", "coordinates": [ -122.732636951782808, 45.486758717650794 ] } },
{ "type": "Feature", "properties": { "point_type": "destination", "points_str": "45.492101, -122.805579" }, "geometry": { "type": "Point", "coordinates": [ -122.805579358960756, 45.492100519812027 ] } }
]
}
