{
"type": "FeatureCollection",
"name": "origin_destination_points",
"crs": { "type": "name", "properties": { "name": "urn:ogc:def:crs:OGC:1.3:CRS84" } },
"features": [
{ "type": "Feature", "properties": { "point_type": "origin", "points_str": "45.512314, -122.637709" }, "geometry": { "type": "Point", "coordinates": [ -122.637709329509207, 45.512313576107644 ] } },
{ "type": "Feature", "properties": { "point_type": "destination", "points_str": "45.503769, -122.679155" }, "geometry": { "type": "Point", "coordinates": [ -122.679154522818067, 45.503769248337534 ] } }
]
}
