{
"type": "FeatureCollection",
"crs": { "type": "name", "properties": { "name": "urn:ogc:def:crs:OGC:1.3:CRS84" } },
"features": [
{ "type": "Feature", "properties": { "point_type": "origin", "points_str": "45.475065, -122.613417" }, "geometry": { "type": "Point", "coordinates": [ -122.61341745199509, 45.475065206761343 ] } },
{ "type": "Feature", "properties": { "point_type": "destination", "points_str": "45.427421, -122.522161" }, "geometry": { "type": "Point", "coordinates": [ -122.522160646273321, 45.42742115051206 ] } }
]
}
