{
"type": "FeatureCollection",
"name": "origin_destination_points",
"crs": { "type": "name", "properties": { "name": "urn:ogc:def:crs:OGC:1.3:CRS84" } },
"features": [
{ "type": "Feature", "properties": { "point_type": "origin", "points_str": "45.518062, -122.673698" }, "geometry": { "type": "Point", "coordinates": [ -122.673698265434737, 45.518061543075532 ] } },
{ "type": "Feature", "properties": { "point_type": "destination", "points_str": "45.390492, -122.647806" }, "geometry": { "type": "Point", "coordinates": [ -122.647805530480014, 45.390492165246883 ] } }
]
}
