{
"type": "FeatureCollection",
"name": "origin_destination_points",
"crs": { "type": "name", "properties": { "name": "urn:ogc:def:crs:OGC:1.3:CRS84" } },
"features": [
{ "type": "Feature", "properties": { "point_type": "origin", "points_str": "45.475001, -122.584984" }, "geometry": { "type": "Point", "coordinates": [ -122.584983577718106, 45.47500082207489 ] } },
{ "type": "Feature", "properties": { "point_type": "destination", "points_str": "45.626494, -122.813563" }, "geometry": { "type": "Point", "coordinates": [ -122.813562503020734, 45.626494288785786 ] } }
]
}
