{
"type": "FeatureCollection",
"name": "origin_destination_points",
"crs": { "type": "name", "properties": { "name": "urn:ogc:def:crs:OGC:1.3:CRS84" } },
"features": [
{ "type": "Feature", "properties": { "point_type": "origin", "points_str": "45.49418, -122.541185" }, "geometry": { "type": "Point", "coordinates": [ -122.541184745093716, 45.494180410346537 ] } },
{ "type": "Feature", "properties": { "point_type": "destination", "points_str": "45.511633, -122.674682" }, "geometry": { "type": "Point", "coordinates": [ -122.674681964621129, 45.511633320429823 ] } }
]
}
