{
"type": "FeatureCollection",
"crs": { "type": "name", "properties": { "name": "urn:ogc:def:crs:OGC:1.3:CRS84" } },
"features": [
{ "type": "Feature", "properties": { "point_type": "origin", "points_str": "45.516374, -122.789248" }, "geometry": { "type": "Point", "coordinates": [ -122.789248182561977, 45.516374216822769 ] } },
{ "type": "Feature", "properties": { "point_type": "destination", "points_str": "45.459986, -122.580083" }, "geometry": { "type": "Point", "coordinates": [ -122.580083030794285, 45.45998607305922 ] } }
]
}
