{
"type": "FeatureCollection",
"name": "origin_destination_points",
"crs": { "type": "name", "properties": { "name": "urn:ogc:def:crs:OGC:1.3:CRS84" } },
"features": [
{ "type": "Feature", "properties": { "point_type": "origin", "points_str": "45.515438, -122.409503" }, "geometry": { "type": "Point", "coordinates": [ -122.409503020205648, 45.515438175307345 ] } },
{ "type": "Feature", "properties": { "point_type": "destination", "points_str": "45.474127, -122.612935" }, "geometry": { "type": "Point", "coordinates": [ -122.612935235628555, 45.474126800625875 ] } }
]
}
