{
"type": "FeatureCollection",
"name": "origin_destination_points",
"crs": { "type": "name", "properties": { "name": "urn:ogc:def:crs:OGC:1.3:CRS84" } },
"features": [
{ "type": "Feature", "properties": { "point_type": "origin", "points_str": "45.52285, -122.721148" }, "geometry": { "type": "Point", "coordinates": [ -122.721147678286059, 45.522850407363492 ] } },
{ "type": "Feature", "properties": { "point_type": "destination", "points_str": "45.534701, -122.834172" }, "geometry": { "type": "Point", "coordinates": [ -122.834172184594692, 45.534700998675838 ] } }
]
}
