{
"type": "FeatureCollection",
"name": "origin_destination_points",
"crs": { "type": "name", "properties": { "name": "urn:ogc:def:crs:OGC:1.3:CRS84" } },
"features": [
{ "type": "Feature", "properties": { "point_type": "origin", "points_str": "45.52231, -122.890377" }, "geometry": { "type": "Point", "coordinates": [ -122.890376614109769, 45.522310228633899 ] } },
{ "type": "Feature", "properties": { "point_type": "destination", "points_str": "45.498459, -122.893571" }, "geometry": { "type": "Point", "coordinates": [ -122.893570719843652, 45.498458924402115 ] } }
]
}
