{
"type": "FeatureCollection",
"crs": { "type": "name", "properties": { "name": "urn:ogc:def:crs:OGC:1.3:CRS84" } },
"features": [
{ "type": "Feature", "properties": { "point_type": "origin", "points_str": "45.513952, -122.721261" }, "geometry": { "type": "Point", "coordinates": [ -122.721260799042867, 45.513952012883379 ] } },
{ "type": "Feature", "properties": { "point_type": "destination", "points_str": "45.515228, -122.425768" }, "geometry": { "type": "Point", "coordinates": [ -122.425767925890909, 45.515227620187524 ] } }
]
}
