{
"type": "FeatureCollection",
"crs": { "type": "name", "properties": { "name": "urn:ogc:def:crs:OGC:1.3:CRS84" } },
"features": [
{ "type": "Feature", "properties": { "point_type": "origin", "points_str": "45.334996, -122.791535" }, "geometry": { "type": "Point", "coordinates": [ -122.791535122339965, 45.334995860652015 ] } },
{ "type": "Feature", "properties": { "point_type": "destination", "points_str": "45.420784, -122.785542" }, "geometry": { "type": "Point", "coordinates": [ -122.785542446345758, 45.420784341098383 ] } }
]
}
