{
"type": "FeatureCollection",
"crs": { "type": "name", "properties": { "name": "urn:ogc:def:crs:OGC:1.3:CRS84" } },
"features": [
{ "type": "Feature", "properties": { "point_type": "origin", "points_str": "45.387216, -122.589128" }, "geometry": { "type": "Point", "coordinates": [ -122.589127576703021, 45.387215660800997 ] } },
{ "type": "Feature", "properties": { "point_type": "destination", "points_str": "45.365922, -122.586621" }, "geometry": { "type": "Point", "coordinates": [ -122.586621091428285, 45.365922273033185 ] } }
]
}
