{
"type": "FeatureCollection",
"name": "origin_destination_points",
"crs": { "type": "name", "properties": { "name": "urn:ogc:def:crs:OGC:1.3:CRS84" } },
"features": [
{ "type": "Feature", "properties": { "point_type": "origin", "points_str": "45.554672, -122.703655" }, "geometry": { "type": "Point", "coordinates": [ -122.703655322621827, 45.554672332628783 ] } },
{ "type": "Feature", "properties": { "point_type": "destination", "points_str": "45.566238, -122.653268" }, "geometry": { "type": "Point", "coordinates": [ -122.653268019827038, 45.566238265783447 ] } }
]
}
