{
"type": "FeatureCollection",
"name": "origin_destination_points",
"crs": { "type": "name", "properties": { "name": "urn:ogc:def:crs:OGC:1.3:CRS84" } },
"features": [
{ "type": "Feature", "properties": { "point_type": "origin", "points_str": "45.492094, -122.680077" }, "geometry": { "type": "Point", "coordinates": [ -122.680077280991014, 45.492094092792975 ] } },
{ "type": "Feature", "properties": { "point_type": "destination", "points_str": "45.519294, -123.120043" }, "geometry": { "type": "Point", "coordinates": [ -123.120042893989734, 45.519294298099823 ] } }
]
}
