{
"type": "FeatureCollection",
"name": "origin_destination_points",
"crs": { "type": "name", "properties": { "name": "urn:ogc:def:crs:OGC:1.3:CRS84" } },
"features": [
{ "type": "Feature", "properties": { "point_type": "origin", "points_str": "45.552417, -122.675748" }, "geometry": { "type": "Point", "coordinates": [ -122.675748206626963, 45.552416616984992 ] } },
{ "type": "Feature", "properties": { "point_type": "destination", "points_str": "45.50285, -122.632655" }, "geometry": { "type": "Point", "coordinates": [ -122.632654667140187, 45.5028503173518 ] } }
]
}
