{
"type": "FeatureCollection",
"name": "origin_destination_points",
"crs": { "type": "name", "properties": { "name": "urn:ogc:def:crs:OGC:1.3:CRS84" } },
"features": [
{ "type": "Feature", "properties": { "point_type": "origin", "points_str": "45.573379, -122.704034" }, "geometry": { "type": "Point", "coordinates": [ -122.704034347162349, 45.573379292671149 ] } },
{ "type": "Feature", "properties": { "point_type": "destination", "points_str": "45.571285, -122.757781" }, "geometry": { "type": "Point", "coordinates": [ -122.757781172647029, 45.571285151651225 ] } }
]
}
