{
"type": "FeatureCollection",
"crs": { "type": "name", "properties": { "name": "urn:ogc:def:crs:OGC:1.3:CRS84" } },
"features": [
{ "type": "Feature", "properties": { "point_type": "origin", "points_str": "45.522272, -122.537253" }, "geometry": { "type": "Point", "coordinates": [ -122.537253153998506, 45.522272416839961 ] } },
{ "type": "Feature", "properties": { "point_type": "destination", "points_str": "45.511935, -122.680103" }, "geometry": { "type": "Point", "coordinates": [ -122.680102767989652, 45.511934616525942 ] } }
]
}
