{
"type": "FeatureCollection",
"crs": { "type": "name", "properties": { "name": "urn:ogc:def:crs:OGC:1.3:CRS84" } },
"features": [
{ "type": "Feature", "properties": { "point_type": "origin", "points_str": "45.499965, -122.42917" }, "geometry": { "type": "Point", "coordinates": [ -122.429170493063594, 45.499964585392583 ] } },
{ "type": "Feature", "properties": { "point_type": "destination", "points_str": "45.517477, -122.404369" }, "geometry": { "type": "Point", "coordinates": [ -122.404369275039556, 45.517477077593512 ] } }
]
}
