{
"type": "FeatureCollection",
"crs": { "type": "name", "properties": { "name": "urn:ogc:def:crs:OGC:1.3:CRS84" } },
"features": [
{ "type": "Feature", "properties": { "point_type": "origin", "points_str": "45.477269, -122.668951" }, "geometry": { "type": "Point", "coordinates": [ -122.668950665990621, 45.477268668673545 ] } },
{ "type": "Feature", "properties": { "point_type": "destination", "points_str": "45.442774, -122.653387" }, "geometry": { "type": "Point", "coordinates": [ -122.653387409276718, 45.442773894521032 ] } }
]
}
