{
"type": "FeatureCollection",
"name": "origin_destination_points",
"crs": { "type": "name", "properties": { "name": "urn:ogc:def:crs:OGC:1.3:CRS84" } },
"features": [
{ "type": "Feature", "properties": { "point_type": "origin", "points_str": "45.495655, -122.860851" }, "geometry": { "type": "Point", "coordinates": [ -122.860851294540026, 45.495654524402681 ] } },
{ "type": "Feature", "properties": { "point_type": "destination", "points_str": "45.426727, -122.678516" }, "geometry": { "type": "Point", "coordinates": [ -122.678516196435197, 45.426726843707222 ] } }
]
}
