{
"type": "FeatureCollection",
"name": "origin_destination_points",
"crs": { "type": "name", "properties": { "name": "urn:ogc:def:crs:OGC:1.3:CRS84" } },
"features": [
{ "type": "Feature", "properties": { "point_type": "origin", "points_str": "45.52378, -122.88601" }, "geometry": { "type": "Point", "coordinates": [ -122.886010076927761, 45.523779973006704 ] } },
{ "type": "Feature", "properties": { "point_type": "destination", "points_str": "45.494542, -122.799905" }, "geometry": { "type": "Point", "coordinates": [ -122.799904531125534, 45.494542190893071 ] } }
]
}
