{
"type": "FeatureCollection",
"crs": { "type": "name", "properties": { "name": "urn:ogc:def:crs:OGC:1.3:CRS84" } },
"features": [
{ "type": "Feature", "properties": { "point_type": "origin", "points_str": "45.523689, -122.626519" }, "geometry": { "type": "Point", "coordinates": [ -122.626519043746754, 45.523689083836054 ] } },
{ "type": "Feature", "properties": { "point_type": "destination", "points_str": "45.490739, -122.540165" }, "geometry": { "type": "Point", "coordinates": [ -122.540165348771211, 45.490738911453171 ] } }
]
}
