{
"type": "FeatureCollection",
"crs": { "type": "name", "properties": { "name": "urn:ogc:def:crs:OGC:1.3:CRS84" } },
"features": [
{ "type": "Feature", "properties": { "point_type": "origin", "points_str": "45.482073, -122.631331" }, "geometry": { "type": "Point", "coordinates": [ -122.631330504561973, 45.482072804456166 ] } },
{ "type": "Feature", "properties": { "point_type": "destination", "points_str": "45.608856, -122.679385" }, "geometry": { "type": "Point", "coordinates": [ -122.679385206915072, 45.60885558675745 ] } }
]
}
