{
"type": "FeatureCollection",
"name": "origin_destination_points",
"crs": { "type": "name", "properties": { "name": "urn:ogc:def:crs:OGC:1.3:CRS84" } },
"features": [
{ "type": "Feature", "properties": { "point_type": "origin", "points_str": "45.585044, -122.736061" }, "geometry": { "type": "Point", "coordinates": [ -122.736061111181343, 45.585044397974698 ] } },
{ "type": "Feature", "properties": { "point_type": "destination", "points_str": "45.457298, -122.647729" }, "geometry": { "type": "Point", "coordinates": [ -122.647729349304598, 45.457298417781963 ] } }
]
}
