{
"type": "FeatureCollection",
"crs": { "type": "name", "properties": { "name": "urn:ogc:def:crs:OGC:1.3:CRS84" } },
"features": [
{ "type": "Feature", "properties": { "point_type": "origin", "points_str": "45.523035, -122.561251" }, "geometry": { "type": "Point", "coordinates": [ -122.561251385767534, 45.523035464139852 ] } },
{ "type": "Feature", "properties": { "point_type": "destination", "points_str": "45.517749, -122.421749" }, "geometry": { "type": "Point", "coordinates": [ -122.421748961656135, 45.517749244715489 ] } }
]
}
