{
"type": "FeatureCollection",
"name": "origin_destination_points",
"crs": { "type": "name", "properties": { "name": "urn:ogc:def:crs:OGC:1.3:CRS84" } },
"features": [
{ "type": "Feature", "properties": { "point_type": "origin", "points_str": "45.493604, -122.805235" }, "geometry": { "type": "Point", "coordinates": [ -122.80523509519945, 45.493604157143288 ] } },
{ "type": "Feature", "properties": { "point_type": "destination", "points_str": "45.522406, -122.967311" }, "geometry": { "type": "Point", "coordinates": [ -122.967311044750701, 45.522406259306941 ] } }
]
}
