{
"type": "FeatureCollection",
"name": "origin_destination_points",
"crs": { "type": "name", "properties": { "name": "urn:ogc:def:crs:OGC:1.3:CRS84" } },
"features": [
{ "type": "Feature", "properties": { "point_type": "origin", "points_str": "45.505277, -122.579133" }, "geometry": { "type": "Point", "coordinates": [ -122.579132967756436, 45.505276807971647 ] } },
{ "type": "Feature", "properties": { "point_type": "destination", "points_str": "45.524205, -122.496976" }, "geometry": { "type": "Point", "coordinates": [ -122.496975820109569, 45.524204789565758 ] } }
]
}
