{
"type": "FeatureCollection",
"name": "origin_destination_points",
"crs": { "type": "name", "properties": { "name": "urn:ogc:def:crs:OGC:1.3:CRS84" } },
"features": [
{ "type": "Feature", "properties": { "point_type": "origin", "points_str": "45.475385, -122.806854" }, "geometry": { "type": "Point", "coordinates": [ -122.806854080138578, 45.475385433335404 ] } },
{ "type": "Feature", "properties": { "point_type": "destination", "points_str": "45.33774, -122.604948" }, "geometry": { "type": "Point", "coordinates": [ -122.604948401649892, 45.337739575325834 ] } }
]
}
