{
"type": "FeatureCollection",
"name": "origin_destination_points",
"crs": { "type": "name", "properties": { "name": "urn:ogc:def:crs:OGC:1.3:CRS84" } },
"features": [
{ "type": "Feature", "properties": { "point_type": "origin", "points_str": "45.517681, -122.867738" }, "geometry": { "type": "Point", "coordinates": [ -122.86773804830915, 45.517681087137113 ] } },
{ "type": "Feature", "properties": { "point_type": "destination", "points_str": "45.497802, -122.888713" }, "geometry": { "type": "Point", "coordinates": [ -122.888713108691775, 45.497801518494789 ] } }
]
}
