{
"type": "FeatureCollection",
"crs": { "type": "name", "properties": { "name": "urn:ogc:def:crs:OGC:1.3:CRS84" } },
"features": [
{ "type": "Feature", "properties": { "point_type": "origin", "points_str": "45.542442, -122.709941" }, "geometry": { "type": "Point", "coordinates": [ -122.709940519119286, 45.542442295942628 ] } },
{ "type": "Feature", "properties": { "point_type": "destination", "points_str": "45.48313, -122.672244" }, "geometry": { "type": "Point", "coordinates": [ -122.672243557971214, 45.48313046135867 ] } }
]
}
