{
"type": "FeatureCollection",
"name": "origin_destination_points",
"crs": { "type": "name", "properties": { "name": "urn:ogc:def:crs:OGC:1.3:CRS84" } },
"features": [
{ "type": "Feature", "properties": { "point_type": "origin", "points_str": "45.498664, -122.624753" }, "geometry": { "type": "Point", "coordinates": [ -122.624752904569362, 45.498663849362551 ] } },
{ "type": "Feature", "properties": { "point_type": "destination", "points_str": "45.474133, -122.614628" }, "geometry": { "type": "Point", "coordinates": [ -122.614628076843331, 45.474132622145575 ] } }
]
}
