{
"type": "FeatureCollection",
"name": "origin_destination_points",
"crs": { "type": "name", "properties": { "name": "urn:ogc:def:crs:OGC:1.3:CRS84" } },
"features": [
{ "type": "Feature", "properties": { "point_type": "origin", "points_str": "45.527915, -122.94943" }, "geometry": { "type": "Point", "coordinates": [ -122.949429748624368, 45.527914701922555 ] } },
{ "type": "Feature", "properties": { "point_type": "destination", "points_str": "45.47332, -122.851438" }, "geometry": { "type": "Point", "coordinates": [ -122.851438278512802, 45.473319692506571 ] } }
]
}
