{
"type": "FeatureCollection",
"name": "origin_destination_points",
"crs": { "type": "name", "properties": { "name": "urn:ogc:def:crs:OGC:1.3:CRS84" } },
"features": [
{ "type": "Feature", "properties": { "point_type": "origin", "points_str": "45.391569, -122.645322" }, "geometry": { "type": "Point", "coordinates": [ -122.645322480522935, 45.391568866545441 ] } },
{ "type": "Feature", "properties": { "point_type": "destination", "points_str": "45.502475, -122.673538" }, "geometry": { "type": "Point", "coordinates": [ -122.673538118286729, 45.502475265516416 ] } }
]
}
