{
"type": "FeatureCollection",
"name": "origin_destination_points",
"crs": { "type": "name", "properties": { "name": "urn:ogc:def:crs:OGC:1.3:CRS84" } },
"features": [
{ "type": "Feature", "properties": { "point_type": "origin", "points_str": "45.497903, -122.608634" }, "geometry": { "type": "Point", "coordinates": [ -122.608634181466925, 45.497903454824694 ] } },
{ "type": "Feature", "properties": { "point_type": "destination", "points_str": "45.471028, -122.618294" }, "geometry": { "type": "Point", "coordinates": [ -122.618294481954422, 45.47102769254812 ] } }
]
}
