{
"type": "FeatureCollection",
"crs": { "type": "name", "properties": { "name": "urn:ogc:def:crs:OGC:1.3:CRS84" } },
"features": [
{ "type": "Feature", "properties": { "point_type": "origin", "points_str": "45.592984, -122.786106" }, "geometry": { "type": "Point", "coordinates": [ -122.786105970507293, 45.592983655886144 ] } },
{ "type": "Feature", "properties": { "point_type": "destination", "points_str": "45.56405, -122.696779" }, "geometry": { "type": "Point", "coordinates": [ -122.696778747714731, 45.564049979869438 ] } }
]
}
