{
"type": "FeatureCollection",
"crs": { "type": "name", "properties": { "name": "urn:ogc:def:crs:OGC:1.3:CRS84" } },
"features": [
{ "type": "Feature", "properties": { "point_type": "origin", "points_str": "45.514668, -122.746409" }, "geometry": { "type": "Point", "coordinates": [ -122.746408739260161, 45.514668049965636 ] } },
{ "type": "Feature", "properties": { "point_type": "destination", "points_str": "45.504012, -122.408391" }, "geometry": { "type": "Point", "coordinates": [ -122.408390645429591, 45.504012298754581 ] } }
]
}
