{
"type": "FeatureCollection",
"name": "origin_destination_points",
"crs": { "type": "name", "properties": { "name": "urn:ogc:def:crs:OGC:1.3:CRS84" } },
"features": [
{ "type": "Feature", "properties": { "point_type": "origin", "points_str": "45.352018, -122.618189" }, "geometry": { "type": "Point", "coordinates": [ -122.618189111443215, 45.352017677221227 ] } },
{ "type": "Feature", "properties": { "point_type": "destination", "points_str": "45.465168, -122.616355" }, "geometry": { "type": "Point", "coordinates": [ -122.616354589957083, 45.465168300386154 ] } }
]
}
