{
"type": "FeatureCollection",
"name": "origin_destination_points",
"crs": { "type": "name", "properties": { "name": "urn:ogc:def:crs:OGC:1.3:CRS84" } },
"features": [
{ "type": "Feature", "properties": { "point_type": "origin", "points_str": "45.477745, -122.525634" }, "geometry": { "type": "Point", "coordinates": [ -122.525634095390558, 45.477745388109049 ] } },
{ "type": "Feature", "properties": { "point_type": "destination", "points_str": "45.51841, -122.658683" }, "geometry": { "type": "Point", "coordinates": [ -122.658683133305075, 45.518409871217393 ] } }
]
}
