{
"type": "FeatureCollection",
"name": "origin_destination_points",
"crs": { "type": "name", "properties": { "name": "urn:ogc:def:crs:OGC:1.3:CRS84" } },
"features": [
{ "type": "Feature", "properties": { "point_type": "origin", "points_str": "45.460781, -122.57911" }, "geometry": { "type": "Point", "coordinates": [ -122.579110420418445, 45.460780525335707 ] } },
{ "type": "Feature", "properties": { "point_type": "destination", "points_str": "45.496705, -122.56566" }, "geometry": { "type": "Point", "coordinates": [ -122.565659846885126, 45.496705417523231 ] } }
]
}
