{
"type": "FeatureCollection",
"crs": { "type": "name", "properties": { "name": "urn:ogc:def:crs:OGC:1.3:CRS84" } },
"features": [
{ "type": "Feature", "properties": { "point_type": "origin", "points_str": "45.468883, -122.560059" }, "geometry": { "type": "Point", "coordinates": [ -122.560058997134277, 45.468883136743322 ] } },
{ "type": "Feature", "properties": { "point_type": "destination", "points_str": "45.478249, -122.628125" }, "geometry": { "type": "Point", "coordinates": [ -122.628125220531317, 45.478248762356138 ] } }
]
}
