{
"type": "FeatureCollection",
"crs": { "type": "name", "properties": { "name": "urn:ogc:def:crs:OGC:1.3:CRS84" } },
"features": [
{ "type": "Feature", "properties": { "point_type": "origin", "points_str": "45.455988, -122.607065" }, "geometry": { "type": "Point", "coordinates": [ -122.607065267627064, 45.455988201977675 ] } },
{ "type": "Feature", "properties": { "point_type": "destination", "points_str": "45.43162, -122.546614" }, "geometry": { "type": "Point", "coordinates": [ -122.546613814396522, 45.431620234263178 ] } }
]
}
