{
"type": "FeatureCollection",
"name": "origin_destination_points",
"crs": { "type": "name", "properties": { "name": "urn:ogc:def:crs:OGC:1.3:CRS84" } },
"features": [
{ "type": "Feature", "properties": { "point_type": "origin", "points_str": "45.518201, -122.647385" }, "geometry": { "type": "Point", "coordinates": [ -122.647384626321966, 45.518200819357972 ] } },
{ "type": "Feature", "properties": { "point_type": "destination", "points_str": "45.445092, -122.812835" }, "geometry": { "type": "Point", "coordinates": [ -122.812834767028122, 45.445091747376374 ] } }
]
}
