{
"type": "FeatureCollection",
"crs": { "type": "name", "properties": { "name": "urn:ogc:def:crs:OGC:1.3:CRS84" } },
"features": [
{ "type": "Feature", "properties": { "point_type": "origin", "points_str": "45.562379, -122.524107" }, "geometry": { "type": "Point", "coordinates": [ -122.524106867384631, 45.56237935197867 ] } },
{ "type": "Feature", "properties": { "point_type": "destination", "points_str": "45.549679, -122.473048" }, "geometry": { "type": "Point", "coordinates": [ -122.473048390420445, 45.549678628872826 ] } }
]
}
