{
"type": "FeatureCollection",
"crs": { "type": "name", "properties": { "name": "urn:ogc:def:crs:OGC:1.3:CRS84" } },
"features": [
{ "type": "Feature", "properties": { "point_type": "origin", "points_str": "45.448786, -122.576149" }, "geometry": { "type": "Point", "coordinates": [ -122.576148863196991, 45.448785571055545 ] } },
{ "type": "Feature", "properties": { "point_type": "destination", "points_str": "45.588428, -122.703982" }, "geometry": { "type": "Point", "coordinates": [ -122.703982017565338, 45.588428238982729 ] } }
]
}
