{
"type": "FeatureCollection",
"name": "origin_destination_points",
"crs": { "type": "name", "properties": { "name": "urn:ogc:def:crs:OGC:1.3:CRS84" } },
"features": [
{ "type": "Feature", "properties": { "point_type": "origin", "points_str": "45.565449, -122.616577" }, "geometry": { "type": "Point", "coordinates": [ -122.616576919597804, 45.565449379407163 ] } },
{ "type": "Feature", "properties": { "point_type": "destination", "points_str": "45.465368, -122.578748" }, "geometry": { "type": "Point", "coordinates": [ -122.578747643233129, 45.465367945204534 ] } }
]
}
