{
"type": "FeatureCollection",
"crs": { "type": "name", "properties": { "name": "urn:ogc:def:crs:OGC:1.3:CRS84" } },
"features": [
{ "type": "Feature", "properties": { "point_type": "origin", "points_str": "45.378934, -122.762672" }, "geometry": { "type": "Point", "coordinates": [ -122.762672254043963, 45.378933780516384 ] } },
{ "type": "Feature", "properties": { "point_type": "destination", "points_str": "45.46142, -122.701674" }, "geometry": { "type": "Point", "coordinates": [ -122.701674253894552, 45.461420407844656 ] } }
]
}
