{
"type": "FeatureCollection",
"name": "origin_destination_points",
"crs": { "type": "name", "properties": { "name": "urn:ogc:def:crs:OGC:1.3:CRS84" } },
"features": [
{ "type": "Feature", "properties": { "point_type": "origin", "points_str": "45.505281, -122.559035" }, "geometry": { "type": "Point", "coordinates": [ -122.559034773375231, 45.505281360198538 ] } },
{ "type": "Feature", "properties": { "point_type": "destination", "points_str": "45.542114, -122.618774" }, "geometry": { "type": "Point", "coordinates": [ -122.618773744951639, 45.542114115591644 ] } }
]
}
