{
"type": "FeatureCollection",
"name": "origin_destination_points",
"crs": { "type": "name", "properties": { "name": "urn:ogc:def:crs:OGC:1.3:CRS84" } },
"features": [
{ "type": "Feature", "properties": { "point_type": "origin", "points_str": "45.523204, -122.913231" }, "geometry": { "type": "Point", "coordinates": [ -122.913231319096823, 45.523203995752823 ] } },
{ "type": "Feature", "properties": { "point_type": "destination", "points_str": "45.530062, -122.949435" }, "geometry": { "type": "Point", "coordinates": [ -122.949435475480271, 45.530061524916135 ] } }
]
}
