{
"type": "FeatureCollection",
"crs": { "type": "name", "properties": { "name": "urn:ogc:def:crs:OGC:1.3:CRS84" } },
"features": [
{ "type": "Feature", "properties": { "point_type": "origin", "points_str": "45.56807, -122.667923" }, "geometry": { "type": "Point", "coordinates": [ -122.667923133053648, 45.568070360975511 ] } },
{ "type": "Feature", "properties": { "point_type": "destination", "points_str": "45.38675, -122.640434" }, "geometry": { "type": "Point", "coordinates": [ -122.640433772817417, 45.386750074169179 ] } }
]
}
