{
"type": "FeatureCollection",
"name": "origin_destination_points",
"crs": { "type": "name", "properties": { "name": "urn:ogc:def:crs:OGC:1.3:CRS84" } },
"features": [
{ "type": "Feature", "properties": { "point_type": "origin", "points_str": "45.39397, -122.621097" }, "geometry": { "type": "Point", "coordinates": [ -122.621097340239857, 45.393970034073774 ] } },
{ "type": "Feature", "properties": { "point_type": "destination", "points_str": "45.385972, -122.410092" }, "geometry": { "type": "Point", "coordinates": [ -122.410091961055329, 45.38597233400246 ] } }
]
}
