{
"type": "FeatureCollection",
"name": "origin_destination_points",
"crs": { "type": "name", "properties": { "name": "urn:ogc:def:crs:OGC:1.3:CRS84" } },
"features": [
{ "type": "Feature", "properties": { "point_type": "origin", "points_str": "45.511374, -122.605102" }, "geometry": { "type": "Point", "coordinates": [ -122.605101505954806, 45.511373861363936 ] } },
{ "type": "Feature", "properties": { "point_type": "destination", "points_str": "45.506827, -122.561438" }, "geometry": { "type": "Point", "coordinates": [ -122.561437917461745, 45.50682705752758 ] } }
]
}
