{
"type": "FeatureCollection",
"name": "origin_destination_points",
"crs": { "type": "name", "properties": { "name": "urn:ogc:def:crs:OGC:1.3:CRS84" } },
"features": [
{ "type": "Feature", "properties": { "point_type": "origin", "points_str": "45.516011, -122.881834" }, "geometry": { "type": "Point", "coordinates": [ -122.881833908311421, 45.516010566668761 ] } },
{ "type": "Feature", "properties": { "point_type": "destination", "points_str": "45.551054, -122.87032" }, "geometry": { "type": "Point", "coordinates": [ -122.870320358805785, 45.551053952041329 ] } }
]
}
