{
"type": "FeatureCollection",
"name": "origin_destination_points",
"crs": { "type": "name", "properties": { "name": "urn:ogc:def:crs:OGC:1.3:CRS84" } },
"features": [
{ "type": "Feature", "properties": { "point_type": "origin", "points_str": "45.490991, -122.764743" }, "geometry": { "type": "Point", "coordinates": [ -122.764743307051106, 45.49099113226584 ] } },
{ "type": "Feature", "properties": { "point_type": "destination", "points_str": "45.494, -122.508042" }, "geometry": { "type": "Point", "coordinates": [ -122.508041770181848, 45.493999500760907 ] } }
]
}
