{
"type": "FeatureCollection",
"name": "origin_destination_points",
"crs": { "type": "name", "properties": { "name": "urn:ogc:def:crs:OGC:1.3:CRS84" } },
"features": [
{ "type": "Feature", "properties": { "point_type": "origin", "points_str": "45.457325, -122.685915" }, "geometry": { "type": "Point", "coordinates": [ -122.685914624716204, 45.457325243467523 ] } },
{ "type": "Feature", "properties": { "point_type": "destination", "points_str": "45.507493, -122.677088" }, "geometry": { "type": "Point", "coordinates": [ -122.677087644574499, 45.507493035506556 ] } }
]
}
