{
"type": "FeatureCollection",
"name": "origin_destination_points",
"crs": { "type": "name", "properties": { "name": "urn:ogc:def:crs:OGC:1.3:CRS84" } },
"features": [
{ "type": "Feature", "properties": { "point_type": "origin", "points_str": "45.530108, -122.560669" }, "geometry": { "type": "Point", "coordinates": [ -122.560668664491516, 45.530107873782974 ] } },
{ "type": "Feature", "properties": { "point_type": "destination", "points_str": "45.52606, -122.683763" }, "geometry": { "type": "Point", "coordinates": [ -122.683763088775891, 45.526060086923046 ] } }
]
}
