{
"type": "FeatureCollection",
"name": "origin_destination_points",
"crs": { "type": "name", "properties": { "name": "urn:ogc:def:crs:OGC:1.3:CRS84" } },
"features": [
{ "type": "Feature", "properties": { "point_type": "origin", "points_str": "45.551899, -122.40419" }, "geometry": { "type": "Point", "coordinates": [ -122.404190219103654, 45.551899411942571 ] } },
{ "type": "Feature", "properties": { "point_type": "destination", "points_str": "45.525246, -122.944148" }, "geometry": { "type": "Point", "coordinates": [ -122.944148315170423, 45.525245717386746 ] } }
]
}
