{
"type": "FeatureCollection",
"name": "origin_destination_points",
"crs": { "type": "name", "properties": { "name": "urn:ogc:def:crs:OGC:1.3:CRS84" } },
"features": [
{ "type": "Feature", "properties": { "point_type": "origin", "points_str": "45.517807, -122.553674" }, "geometry": { "type": "Point", "coordinates": [ -122.553674190252423, 45.517806998889462 ] } },
{ "type": "Feature", "properties": { "point_type": "destination", "points_str": "45.529565, -122.847773" }, "geometry": { "type": "Point", "coordinates": [ -122.84777300687783, 45.529564816364477 ] } }
]
}
