{
"type": "FeatureCollection",
"name": "origin_destination_points",
"crs": { "type": "name", "properties": { "name": "urn:ogc:def:crs:OGC:1.3:CRS84" } },
"features": [
{ "type": "Feature", "properties": { "point_type": "origin", "points_str": "45.514169, -122.792742" }, "geometry": { "type": "Point", "coordinates": [ -122.792741985247261, 45.514169022063825 ] } },
{ "type": "Feature", "properties": { "point_type": "destination", "points_str": "45.52132, -122.653155" }, "geometry": { "type": "Point", "coordinates": [ -122.653155133984953, 45.521319654533315 ] } }
]
}
