{
"type": "FeatureCollection",
"crs": { "type": "name", "properties": { "name": "urn:ogc:def:crs:OGC:1.3:CRS84" } },
"features": [
{ "type": "Feature", "properties": { "point_type": "origin", "points_str": "45.449065, -122.594412" }, "geometry": { "type": "Point", "coordinates": [ -122.594411934069214, 45.44906485676556 ] } },
{ "type": "Feature", "properties": { "point_type": "destination", "points_str": "45.506286, -122.496769" }, "geometry": { "type": "Point", "coordinates": [ -122.496769437246158, 45.50628584689489 ] } }
]
}
