{
"type": "FeatureCollection",
"name": "origin_destination_points",
"crs": { "type": "name", "properties": { "name": "urn:ogc:def:crs:OGC:1.3:CRS84" } },
"features": [
{ "type": "Feature", "properties": { "point_type": "origin", "points_str": "45.407372, -122.723779" }, "geometry": { "type": "Point", "coordinates": [ -122.723779476531675, 45.407372209338121 ] } },
{ "type": "Feature", "properties": { "point_type": "destination", "points_str": "45.340148, -122.777759" }, "geometry": { "type": "Point", "coordinates": [ -122.777759476889074, 45.340148016373419 ] } }
]
}
