{
"type": "FeatureCollection",
"name": "origin_destination_points",
"crs": { "type": "name", "properties": { "name": "urn:ogc:def:crs:OGC:1.3:CRS84" } },
"features": [
{ "type": "Feature", "properties": { "point_type": "origin", "points_str": "45.518288, -122.673269" }, "geometry": { "type": "Point", "coordinates": [ -122.673268996992263, 45.518287730497079 ] } },
{ "type": "Feature", "properties": { "point_type": "destination", "points_str": "45.547643, -122.556228" }, "geometry": { "type": "Point", "coordinates": [ -122.556227988579963, 45.547642989236344 ] } }
]
}
