{
"type": "FeatureCollection",
"name": "origin_destination_points",
"crs": { "type": "name", "properties": { "name": "urn:ogc:def:crs:OGC:1.3:CRS84" } },
"features": [
{ "type": "Feature", "properties": { "point_type": "origin", "points_str": "45.4431, -122.685008" }, "geometry": { "type": "Point", "coordinates": [ -122.68500807135257, 45.443099971118663 ] } },
{ "type": "Feature", "properties": { "point_type": "destination", "points_str": "45.414486, -122.746422" }, "geometry": { "type": "Point", "coordinates": [ -122.74642155552722, 45.414486482935466 ] } }
]
}
