{
"type": "FeatureCollection",
"name": "origin_destination_points",
"crs": { "type": "name", "properties": { "name": "urn:ogc:def:crs:OGC:1.3:CRS84" } },
"features": [
{ "type": "Feature", "properties": { "point_type": "origin", "points_str": "45.460291, -122.641868" }, "geometry": { "type": "Point", "coordinates": [ -122.641867643021499, 45.460290694515201 ] } },
{ "type": "Feature", "properties": { "point_type": "destination", "points_str": "45.322851, -122.576769" }, "geometry": { "type": "Point", "coordinates": [ -122.57676896490905, 45.322850600101638 ] } }
]
}
