{
"type": "FeatureCollection",
"crs": { "type": "name", "properties": { "name": "urn:ogc:def:crs:OGC:1.3:CRS84" } },
"features": [
{ "type": "Feature", "properties": { "point_type": "origin", "points_str": "45.466383, -122.613132" }, "geometry": { "type": "Point", "coordinates": [ -122.613131664745538, 45.466382778668709 ] } },
{ "type": "Feature", "properties": { "point_type": "destination", "points_str": "45.381772, -122.584837" }, "geometry": { "type": "Point", "coordinates": [ -122.584836768435906, 45.381772413581864 ] } }
]
}
