{
"type": "FeatureCollection",
"name": "origin_destination_points",
"crs": { "type": "name", "properties": { "name": "urn:ogc:def:crs:OGC:1.3:CRS84" } },
"features": [
{ "type": "Feature", "properties": { "point_type": "origin", "points_str": "45.539572, -122.619562" }, "geometry": { "type": "Point", "coordinates": [ -122.619562358864258, 45.539572349909577 ] } },
{ "type": "Feature", "properties": { "point_type": "destination", "points_str": "45.461199, -122.764521" }, "geometry": { "type": "Point", "coordinates": [ -122.764520856240466, 45.461199024618246 ] } }
]
}
