{
"type": "FeatureCollection",
"crs": { "type": "name", "properties": { "name": "urn:ogc:def:crs:OGC:1.3:CRS84" } },
"features": [
{ "type": "Feature", "properties": { "point_type": "origin", "points_str": "45.5774, -122.707053" }, "geometry": { "type": "Point", "coordinates": [ -122.707053430775346, 45.57739965592431 ] } },
{ "type": "Feature", "properties": { "point_type": "destination", "points_str": "45.594034, -122.745832" }, "geometry": { "type": "Point", "coordinates": [ -122.745832405641309, 45.594033672372056 ] } }
]
}
