{
"type": "FeatureCollection",
"name": "origin_destination_points",
"crs": { "type": "name", "properties": { "name": "urn:ogc:def:crs:OGC:1.3:CRS84" } },
"features": [
{ "type": "Feature", "properties": { "point_type": "origin", "points_str": "45.553255, -122.640761" }, "geometry": { "type": "Point", "coordinates": [ -122.640761264704167, 45.553254665805071 ] } },
{ "type": "Feature", "properties": { "point_type": "destination", "points_str": "45.481347, -122.703562" }, "geometry": { "type": "Point", "coordinates": [ -122.703561535180853, 45.48134693243221 ] } }
]
}
