{
"type": "FeatureCollection",
"crs": { "type": "name", "properties": { "name": "urn:ogc:def:crs:OGC:1.3:CRS84" } },
"features": [
{ "type": "Feature", "properties": { "point_type": "origin", "points_str": "45.532824, -122.619932" }, "geometry": { "type": "Point", "coordinates": [ -122.619931804936272, 45.532824389013768 ] } },
{ "type": "Feature", "properties": { "point_type": "destination", "points_str": "45.567628, -122.695125" }, "geometry": { "type": "Point", "coordinates": [ -122.695124792516737, 45.567628434443144 ] } }
]
}
