{
"type": "FeatureCollection",
"crs": { "type": "name", "properties": { "name": "urn:ogc:def:crs:OGC:1.3:CRS84" } },
"features": [
{ "type": "Feature", "properties": { "point_type": "origin", "points_str": "45.502411, -122.667915" }, "geometry": { "type": "Point", "coordinates": [ -122.66791468901063, 45.502411372113386 ] } },
{ "type": "Feature", "properties": { "point_type": "destination", "points_str": "45.451246, -122.630628" }, "geometry": { "type": "Point", "coordinates": [ -122.630628442315057, 45.45124554889275 ] } }
]
}
