{
"type": "FeatureCollection",
"name": "origin_destination_points",
"crs": { "type": "name", "properties": { "name": "urn:ogc:def:crs:OGC:1.3:CRS84" } },
"features": [
{ "type": "Feature", "properties": { "point_type": "origin", "points_str": "45.565399, -122.618517" }, "geometry": { "type": "Point", "coordinates": [ -122.618516901376182, 45.56539850832111 ] } },
{ "type": "Feature", "properties": { "point_type": "destination", "points_str": "45.505723, -122.459711" }, "geometry": { "type": "Point", "coordinates": [ -122.459711473844621, 45.505723164877075 ] } }
]
}
