{
"type": "FeatureCollection",
"name": "origin_destination_points",
"crs": { "type": "name", "properties": { "name": "urn:ogc:def:crs:OGC:1.3:CRS84" } },
"features": [
{ "type": "Feature", "properties": { "point_type": "origin", "points_str": "45.526025, -122.584023" }, "geometry": { "type": "Point", "coordinates": [ -122.584022636236512, 45.526025048359593 ] } },
{ "type": "Feature", "properties": { "point_type": "destination", "points_str": "45.558094, -122.569168" }, "geometry": { "type": "Point", "coordinates": [ -122.569168236361932, 45.558093864484263 ] } }
]
}
