{
"type": "FeatureCollection",
"name": "origin_destination_points",
"crs": { "type": "name", "properties": { "name": "urn:ogc:def:crs:OGC:1.3:CRS84" } },
"features": [
{ "type": "Feature", "properties": { "point_type": "origin", "points_str": "45.529584, -122.947935" }, "geometry": { "type": "Point", "coordinates": [ -122.947935497242668, 45.529583548757572 ] } },
{ "type": "Feature", "properties": { "point_type": "destination", "points_str": "45.533393, -122.388375" }, "geometry": { "type": "Point", "coordinates": [ -122.388374901431533, 45.533393418598472 ] } }
]
}
