{
"type": "FeatureCollection",
"crs": { "type": "name", "properties": { "name": "urn:ogc:def:crs:OGC:1.3:CRS84" } },
"features": [
{ "type": "Feature", "properties": { "point_type": "origin", "points_str": "45.569474, -122.69015" }, "geometry": { "type": "Point", "coordinates": [ -122.690149765444076, 45.569474032039466 ] } },
{ "type": "Feature", "properties": { "point_type": "destination", "points_str": "45.519238, -122.680961" }, "geometry": { "type": "Point", "coordinates": [ -122.680961498167008, 45.519237542824783 ] } }
]
}
