{
"type": "FeatureCollection",
"name": "origin_destination_points",
"crs": { "type": "name", "properties": { "name": "urn:ogc:def:crs:OGC:1.3:CRS84" } },
"features": [
{ "type": "Feature", "properties": { "point_type": "origin", "points_str": "45.546588, -122.523854" }, "geometry": { "type": "Point", "coordinates": [ -122.523853595428008, 45.54658820407645 ] } },
{ "type": "Feature", "properties": { "point_type": "destination", "points_str": "45.530903, -122.556154" }, "geometry": { "type": "Point", "coordinates": [ -122.556153760444857, 45.530902591465846 ] } }
]
}
