{
"type": "FeatureCollection",
"name": "origin_destination_points",
"crs": { "type": "name", "properties": { "name": "urn:ogc:def:crs:OGC:1.3:CRS84" } },
"features": [
{ "type": "Feature", "properties": { "point_type": "origin", "points_str": "45.557591, -122.601463" }, "geometry": { "type": "Point", "coordinates": [ -122.601463469672524, 45.557590639759958 ] } },
{ "type": "Feature", "properties": { "point_type": "destination", "points_str": "45.398301, -122.614975" }, "geometry": { "type": "Point", "coordinates": [ -122.614975353150655, 45.39830070316826 ] } }
]
}
