{
"type": "FeatureCollection",
"crs": { "type": "name", "properties": { "name": "urn:ogc:def:crs:OGC:1.3:CRS84" } },
"features": [
{ "type": "Feature", "properties": { "point_type": "origin", "points_str": "45.465853, -122.639916" }, "geometry": { "type": "Point", "coordinates": [ -122.639915914721144, 45.465852980851096 ] } },
{ "type": "Feature", "properties": { "point_type": "destination", "points_str": "45.406784, -122.622426" }, "geometry": { "type": "Point", "coordinates": [ -122.622426149450249, 45.406783723096332 ] } }
]
}
