{
"type": "FeatureCollection",
"crs": { "type": "name", "properties": { "name": "urn:ogc:def:crs:OGC:1.3:CRS84" } },
"features": [
{ "type": "Feature", "properties": { "point_type": "origin", "points_str": "45.456276, -122.59179" }, "geometry": { "type": "Point", "coordinates": [ -122.591790081704474, 45.456275737884326 ] } },
{ "type": "Feature", "properties": { "point_type": "destination", "points_str": "45.293517, -122.337508" }, "geometry": { "type": "Point", "coordinates": [ -122.337508262301682, 45.293517304679519 ] } }
]
}
