{
"type": "FeatureCollection",
"name": "origin_destination_points",
"crs": { "type": "name", "properties": { "name": "urn:ogc:def:crs:OGC:1.3:CRS84" } },
"features": [
{ "type": "Feature", "properties": { "point_type": "origin", "points_str": "45.392436, -122.578799" }, "geometry": { "type": "Point", "coordinates": [ -122.578799132027768, 45.392435874689724 ] } },
{ "type": "Feature", "properties": { "point_type": "destination", "points_str": "45.408619, -122.627061" }, "geometry": { "type": "Point", "coordinates": [ -122.627060557510561, 45.408619301513099 ] } }
]
}
