{
"type": "FeatureCollection",
"crs": { "type": "name", "properties": { "name": "urn:ogc:def:crs:OGC:1.3:CRS84" } },
"features": [
{ "type": "Feature", "properties": { "point_type": "origin", "points_str": "45.518849, -122.676812" }, "geometry": { "type": "Point", "coordinates": [ -122.67681152239831, 45.518849136329457 ] } },
{ "type": "Feature", "properties": { "point_type": "destination", "points_str": "45.538277, -122.602013" }, "geometry": { "type": "Point", "coordinates": [ -122.602013131362966, 45.538276835354928 ] } }
]
}
