{
"type": "FeatureCollection",
"crs": { "type": "name", "properties": { "name": "urn:ogc:def:crs:OGC:1.3:CRS84" } },
"features": [
{ "type": "Feature", "properties": { "point_type": "origin", "points_str": "45.592358, -122.6389" }, "geometry": { "type": "Point", "coordinates": [ -122.638900423450892, 45.592358054376426 ] } },
{ "type": "Feature", "properties": { "point_type": "destination", "points_str": "45.488745, -122.64788" }, "geometry": { "type": "Point", "coordinates": [ -122.647880169603752, 45.488745070110745 ] } }
]
}
