{
"type": "FeatureCollection",
"crs": { "type": "name", "properties": { "name": "urn:ogc:def:crs:OGC:1.3:CRS84" } },
"features": [
{ "type": "Feature", "properties": { "point_type": "origin", "points_str": "45.574013, -122.64486" }, "geometry": { "type": "Point", "coordinates": [ -122.644860213960484, 45.574012988419248 ] } },
{ "type": "Feature", "properties": { "point_type": "destination", "points_str": "45.501113, -122.635814" }, "geometry": { "type": "Point", "coordinates": [ -122.635813701383768, 45.501113384278746 ] } }
]
}
