{
"type": "FeatureCollection",
"crs": { "type": "name", "properties": { "name": "urn:ogc:def:crs:OGC:1.3:CRS84" } },
"features": [
{ "type": "Feature", "properties": { "point_type": "origin", "points_str": "45.488639, -122.720353" }, "geometry": { "type": "Point", "coordinates": [ -122.720352534834049, 45.488638572747249 ] } },
{ "type": "Feature", "properties": { "point_type": "destination", "points_str": "45.58665, -122.71458" }, "geometry": { "type": "Point", "coordinates": [ -122.714580287122359, 45.586649791119754 ] } }
]
}
