{
"type": "FeatureCollection",
"name": "origin_destination_points",
"crs": { "type": "name", "properties": { "name": "urn:ogc:def:crs:OGC:1.3:CRS84" } },
"features": [
{ "type": "Feature", "properties": { "point_type": "origin", "points_str": "45.494919, -122.775568" }, "geometry": { "type": "Point", "coordinates": [ -122.775568097842822, 45.494918890171988 ] } },
{ "type": "Feature", "properties": { "point_type": "destination", "points_str": "45.613104, -122.683348" }, "geometry": { "type": "Point", "coordinates": [ -122.683348010226695, 45.613103671220777 ] } }
]
}
