{
"type": "FeatureCollection",
"name": "origin_destination_points",
"crs": { "type": "name", "properties": { "name": "urn:ogc:def:crs:OGC:1.3:CRS84" } },
"features": [
{ "type": "Feature", "properties": { "point_type": "origin", "points_str": "45.497074, -122.542151" }, "geometry": { "type": "Point", "coordinates": [ -122.542151447574824, 45.497073855124547 ] } },
{ "type": "Feature", "properties": { "point_type": "destination", "points_str": "45.544504, -122.448718" }, "geometry": { "type": "Point", "coordinates": [ -122.448718269250449, 45.544503928080559 ] } }
]
}
