{
"type": "FeatureCollection",
"name": "origin_destination_points",
"crs": { "type": "name", "properties": { "name": "urn:ogc:def:crs:OGC:1.3:CRS84" } },
"features": [
{ "type": "Feature", "properties": { "point_type": "origin", "points_str": "45.590226, -122.707029" }, "geometry": { "type": "Point", "coordinates": [ -122.707028909975861, 45.590225619325963 ] } },
{ "type": "Feature", "properties": { "point_type": "destination", "points_str": "45.509524, -122.847521" }, "geometry": { "type": "Point", "coordinates": [ -122.847521238516123, 45.509524425375787 ] } }
]
}
