{
"type": "FeatureCollection",
"name": "origin_destination_points",
"crs": { "type": "name", "properties": { "name": "urn:ogc:def:crs:OGC:1.3:CRS84" } },
"features": [
{ "type": "Feature", "properties": { "point_type": "origin", "points_str": "45.573673, -122.63312" }, "geometry": { "type": "Point", "coordinates": [ -122.633120444438291, 45.573672527069235 ] } },
{ "type": "Feature", "properties": { "point_type": "destination", "points_str": "45.48406, -122.571053" }, "geometry": { "type": "Point", "coordinates": [ -122.571053233634899, 45.484060010358213 ] } }
]
}
