{
"type": "FeatureCollection",
"crs": { "type": "name", "properties": { "name": "urn:ogc:def:crs:OGC:1.3:CRS84" } },
"features": [
{ "type": "Feature", "properties": { "point_type": "origin", "points_str": "45.53187, -122.571712" }, "geometry": { "type": "Point", "coordinates": [ -122.571712437194407, 45.531869990304862 ] } },
{ "type": "Feature", "properties": { "point_type": "destination", "points_str": "45.588067, -122.583675" }, "geometry": { "type": "Point", "coordinates": [ -122.583675077964187, 45.588067070835827 ] } }
]
}
