{
"type": "FeatureCollection",
"name": "origin_destination_points",
"crs": { "type": "name", "properties": { "name": "urn:ogc:def:crs:OGC:1.3:CRS84" } },
"features": [
{ "type": "Feature", "properties": { "point_type": "origin", "points_str": "45.478167, -122.672151" }, "geometry": { "type": "Point", "coordinates": [ -122.672150567308492, 45.478167052305999 ] } },
{ "type": "Feature", "properties": { "point_type": "destination", "points_str": "45.575813, -122.571492" }, "geometry": { "type": "Point", "coordinates": [ -122.571491617345188, 45.575813149173051 ] } }
]
}
