{
"type": "FeatureCollection",
"crs": { "type": "name", "properties": { "name": "urn:ogc:def:crs:OGC:1.3:CRS84" } },
"features": [
{ "type": "Feature", "properties": { "point_type": "origin", "points_str": "45.471747, -122.576391" }, "geometry": { "type": "Point", "coordinates": [ -122.576391433949368, 45.471747424992678 ] } },
{ "type": "Feature", "properties": { "point_type": "destination", "points_str": "45.507718, -122.464395" }, "geometry": { "type": "Point", "coordinates": [ -122.464394671380703, 45.507718074984318 ] } }
]
}
