{
"type": "FeatureCollection",
"name": "origin_destination_points",
"crs": { "type": "name", "properties": { "name": "urn:ogc:def:crs:OGC:1.3:CRS84" } },
"features": [
{ "type": "Feature", "properties": { "point_type": "origin", "points_str": "45.527428, -122.930731" }, "geometry": { "type": "Point", "coordinates": [ -122.930731305034683, 45.527428448659187 ] } },
{ "type": "Feature", "properties": { "point_type": "destination", "points_str": "45.470099, -122.670313" }, "geometry": { "type": "Point", "coordinates": [ -122.670313033932572, 45.470098806755658 ] } }
]
}
