{
"type": "FeatureCollection",
"name": "origin_destination_points",
"crs": { "type": "name", "properties": { "name": "urn:ogc:def:crs:OGC:1.3:CRS84" } },
"features": [
{ "type": "Feature", "properties": { "point_type": "origin", "points_str": "45.521263, -122.68506" }, "geometry": { "type": "Point", "coordinates": [ -122.685060251091016, 45.5212625326226 ] } },
{ "type": "Feature", "properties": { "point_type": "destination", "points_str": "45.464441, -122.662512" }, "geometry": { "type": "Point", "coordinates": [ -122.662512117746104, 45.464441020708072 ] } }
]
}
