{
"type": "FeatureCollection",
"name": "origin_destination_points",
"crs": { "type": "name", "properties": { "name": "urn:ogc:def:crs:OGC:1.3:CRS84" } },
"features": [
{ "type": "Feature", "properties": { "point_type": "origin", "points_str": "45.564444, -122.594205" }, "geometry": { "type": "Point", "coordinates": [ -122.594204885852349, 45.564443997987851 ] } },
{ "type": "Feature", "properties": { "point_type": "destination", "points_str": "45.521279, -122.646559" }, "geometry": { "type": "Point", "coordinates": [ -122.646559003683194, 45.521278950367211 ] } }
]
}
