{
"type": "FeatureCollection",
"name": "origin_destination_points",
"crs": { "type": "name", "properties": { "name": "urn:ogc:def:crs:OGC:1.3:CRS84" } },
"features": [
{ "type": "Feature", "properties": { "point_type": "origin", "points_str": "45.490325, -122.592936" }, "geometry": { "type": "Point", "coordinates": [ -122.592936149065437, 45.490325006498352 ] } },
{ "type": "Feature", "properties": { "point_type": "destination", "points_str": "45.464239, -122.718414" }, "geometry": { "type": "Point", "coordinates": [ -122.718413676742429, 45.46423870205696 ] } }
]
}
