{
"type": "FeatureCollection",
"crs": { "type": "name", "properties": { "name": "urn:ogc:def:crs:OGC:1.3:CRS84" } },
"features": [
{ "type": "Feature", "properties": { "point_type": "origin", "points_str": "45.531517, -122.875354" }, "geometry": { "type": "Point", "coordinates": [ -122.875353564166701, 45.531516664580941 ] } },
{ "type": "Feature", "properties": { "point_type": "destination", "points_str": "45.517471, -122.734962" }, "geometry": { "type": "Point", "coordinates": [ -122.734961563305944, 45.517471358828864 ] } }
]
}
