{
"type": "FeatureCollection",
"name": "origin_destination_points",
"crs": { "type": "name", "properties": { "name": "urn:ogc:def:crs:OGC:1.3:CRS84" } },
"features": [
{ "type": "Feature", "properties": { "point_type": "origin", "points_str": "45.586403, -122.773688" }, "geometry": { "type": "Point", "coordinates": [ -122.773687626451206, 45.5864026857667 ] } },
{ "type": "Feature", "properties": { "point_type": "destination", "points_str": "45.413165, -122.662465" }, "geometry": { "type": "Point", "coordinates": [ -122.662464630465578, 45.413164896258102 ] } }
]
}
