{
"type": "FeatureCollection",
"crs": { "type": "name", "properties": { "name": "urn:ogc:def:crs:OGC:1.3:CRS84" } },
"features": [
{ "type": "Feature", "properties": { "point_type": "origin", "points_str": "45.399445, -122.659634" }, "geometry": { "type": "Point", "coordinates": [ -122.659633846504633, 45.399444868396408 ] } },
{ "type": "Feature", "properties": { "point_type": "destination", "points_str": "45.457311, -122.574757" }, "geometry": { "type": "Point", "coordinates": [ -122.574756620768028, 45.457310907195435 ] } }
]
}
