{
"type": "FeatureCollection",
"crs": { "type": "name", "properties": { "name": "urn:ogc:def:crs:OGC:1.3:CRS84" } },
"features": [
{ "type": "Feature", "properties": { "point_type": "origin", "points_str": "45.434387, -122.772004" }, "geometry": { "type": "Point", "coordinates": [ -122.772004384963537, 45.434386813942226 ] } },
{ "type": "Feature", "properties": { "point_type": "destination", "points_str": "45.496383, -122.888633" }, "geometry": { "type": "Point", "coordinates": [ -122.888632902946625, 45.496383272373912 ] } }
]
}
