{
"type": "FeatureCollection",
"name": "origin_destination_points",
"crs": { "type": "name", "properties": { "name": "urn:ogc:def:crs:OGC:1.3:CRS84" } },
"features": [
{ "type": "Feature", "properties": { "point_type": "origin", "points_str": "45.505985, -122.744071" }, "geometry": { "type": "Point", "coordinates": [ -122.744070578750382, 45.505984887283134 ] } },
{ "type": "Feature", "properties": { "point_type": "destination", "points_str": "45.531986, -122.565164" }, "geometry": { "type": "Point", "coordinates": [ -122.565164138224716, 45.531985769695609 ] } }
]
}
