{
"type": "FeatureCollection",
"crs": { "type": "name", "properties": { "name": "urn:ogc:def:crs:OGC:1.3:CRS84" } },
"features": [
{ "type": "Feature", "properties": { "point_type": "origin", "points_str": "45.467351, -122.642342" }, "geometry": { "type": "Point", "coordinates": [ -122.642341771926397, 45.46735085170743 ] } },
{ "type": "Feature", "properties": { "point_type": "destination", "points_str": "45.547141, -122.720706" }, "geometry": { "type": "Point", "coordinates": [ -122.720706021170955, 45.547140797287746 ] } }
]
}
