{
"type": "FeatureCollection",
"crs": { "type": "name", "properties": { "name": "urn:ogc:def:crs:OGC:1.3:CRS84" } },
"features": [
{ "type": "Feature", "properties": { "point_type": "origin", "points_str": "45.520858, -122.604345" }, "geometry": { "type": "Point", "coordinates": [ -122.60434518080406, 45.520857735587199 ] } },
{ "type": "Feature", "properties": { "point_type": "destination", "points_str": "45.496106, -122.636242" }, "geometry": { "type": "Point", "coordinates": [ -122.636242349971553, 45.496105518711644 ] } }
]
}
