{
"type": "FeatureCollection",
"crs": { "type": "name", "properties": { "name": "urn:ogc:def:crs:OGC:1.3:CRS84" } },
"features": [
{ "type": "Feature", "properties": { "point_type": "origin", "points_str": "45.529639, -122.933134" }, "geometry": { "type": "Point", "coordinates": [ -122.933133703579514, 45.529639046602043 ] } },
{ "type": "Feature", "properties": { "point_type": "destination", "points_str": "45.464611, -122.801326" }, "geometry": { "type": "Point", "coordinates": [ -122.801325561953931, 45.464611091581958 ] } }
]
}
