{
"type": "FeatureCollection",
"name": "origin_destination_points",
"crs": { "type": "name", "properties": { "name": "urn:ogc:def:crs:OGC:1.3:CRS84" } },
"features": [
{ "type": "Feature", "properties": { "point_type": "origin", "points_str": "45.525489, -122.698029" }, "geometry": { "type": "Point", "coordinates": [ -122.698028610734653, 45.525489259555158 ] } },
{ "type": "Feature", "properties": { "point_type": "destination", "points_str": "45.499601, -122.495698" }, "geometry": { "type": "Point", "coordinates": [ -122.495697521025789, 45.499601055929212 ] } }
]
}
