{
"type": "FeatureCollection",
"name": "origin_destination_points",
"crs": { "type": "name", "properties": { "name": "urn:ogc:def:crs:OGC:1.3:CRS84" } },
"features": [
{ "type": "Feature", "properties": { "point_type": "origin", "points_str": "45.510512, -122.780877" }, "geometry": { "type": "Point", "coordinates": [ -122.780877453953849, 45.510512307705959 ] } },
{ "type": "Feature", "properties": { "point_type": "destination", "points_str": "45.484565, -122.730472" }, "geometry": { "type": "Point", "coordinates": [ -122.730472154370702, 45.484565053168609 ] } }
]
}
