{
"type": "FeatureCollection",
"crs": { "type": "name", "properties": { "name": "urn:ogc:def:crs:OGC:1.3:CRS84" } },
"features": [
{ "type": "Feature", "properties": { "point_type": "origin", "points_str": "45.490438, -122.874353" }, "geometry": { "type": "Point", "coordinates": [ -122.874352597974919, 45.490437940493209 ] } },
{ "type": "Feature", "properties": { "point_type": "destination", "points_str": "45.518314, -122.64649" }, "geometry": { "type": "Point", "coordinates": [ -122.646489631578149, 45.518314447704434 ] } }
]
}
