{
"type": "FeatureCollection",
"name": "origin_destination_points",
"crs": { "type": "name", "properties": { "name": "urn:ogc:def:crs:OGC:1.3:CRS84" } },
"features": [
{ "type": "Feature", "properties": { "point_type": "origin", "points_str": "45.524818, -122.555104" }, "geometry": { "type": "Point", "coordinates": [ -122.55510377413313, 45.524818298339312 ] } },
{ "type": "Feature", "properties": { "point_type": "destination", "points_str": "45.517309, -122.58379" }, "geometry": { "type": "Point", "coordinates": [ -122.583789555818072, 45.517308605092467 ] } }
]
}
