{
"type": "FeatureCollection",
"name": "origin_destination_points",
"crs": { "type": "name", "properties": { "name": "urn:ogc:def:crs:OGC:1.3:CRS84" } },
"features": [
{ "type": "Feature", "properties": { "point_type": "origin", "points_str": "45.557046, -122.644884" }, "geometry": { "type": "Point", "coordinates": [ -122.644884031609266, 45.557045523326657 ] } },
{ "type": "Feature", "properties": { "point_type": "destination", "points_str": "45.294419, -122.329249" }, "geometry": { "type": "Point", "coordinates": [ -122.329249028499504, 45.294419383060479 ] } }
]
}
