{
"type": "FeatureCollection",
"name": "origin_destination_points",
"crs": { "type": "name", "properties": { "name": "urn:ogc:def:crs:OGC:1.3:CRS84" } },
"features": [
{ "type": "Feature", "properties": { "point_type": "origin", "points_str": "45.519072, -122.485604" }, "geometry": { "type": "Point", "coordinates": [ -122.485604004631682, 45.519071700969469 ] } },
{ "type": "Feature", "properties": { "point_type": "destination", "points_str": "45.49644, -122.447714" }, "geometry": { "type": "Point", "coordinates": [ -122.447714013502818, 45.496439809858408 ] } }
]
}
