{
"type": "FeatureCollection",
"name": "origin_destination_points",
"crs": { "type": "name", "properties": { "name": "urn:ogc:def:crs:OGC:1.3:CRS84" } },
"features": [
{ "type": "Feature", "properties": { "point_type": "origin", "points_str": "45.58669, -122.732902" }, "geometry": { "type": "Point", "coordinates": [ -122.732902157201764, 45.58668996292721 ] } },
{ "type": "Feature", "properties": { "point_type": "destination", "points_str": "45.53156, -122.471043" }, "geometry": { "type": "Point", "coordinates": [ -122.471042774818812, 45.531559950750648 ] } }
]
}
