{
"type": "FeatureCollection",
"name": "origin_destination_points",
"crs": { "type": "name", "properties": { "name": "urn:ogc:def:crs:OGC:1.3:CRS84" } },
"features": [
{ "type": "Feature", "properties": { "point_type": "origin", "points_str": "45.530543, -122.673484" }, "geometry": { "type": "Point", "coordinates": [ -122.673484299258732, 45.530542927681928 ] } },
{ "type": "Feature", "properties": { "point_type": "destination", "points_str": "45.516298, -122.639612" }, "geometry": { "type": "Point", "coordinates": [ -122.639612049139032, 45.516297656879331 ] } }
]
}
