{
"type": "FeatureCollection",
"crs": { "type": "name", "properties": { "name": "urn:ogc:def:crs:OGC:1.3:CRS84" } },
"features": [
{ "type": "Feature", "properties": { "point_type": "origin", "points_str": "45.498522, -122.912738" }, "geometry": { "type": "Point", "coordinates": [ -122.912737600513424, 45.498522006617947 ] } },
{ "type": "Feature", "properties": { "point_type": "destination", "points_str": "45.53067, -122.960307" }, "geometry": { "type": "Point", "coordinates": [ -122.960307052291455, 45.530669888979602 ] } }
]
}
