{
"type": "FeatureCollection",
"name": "origin_destination_points",
"crs": { "type": "name", "properties": { "name": "urn:ogc:def:crs:OGC:1.3:CRS84" } },
"features": [
{ "type": "Feature", "properties": { "point_type": "origin", "points_str": "45.570702, -122.612568" }, "geometry": { "type": "Point", "coordinates": [ -122.612568014585804, 45.570701637272485 ] } },
{ "type": "Feature", "properties": { "point_type": "destination", "points_str": "45.516997, -122.550202" }, "geometry": { "type": "Point", "coordinates": [ -122.550201686203309, 45.516996879136066 ] } }
]
}
