{
"type": "FeatureCollection",
"crs": { "type": "name", "properties": { "name": "urn:ogc:def:crs:OGC:1.3:CRS84" } },
"features": [
{ "type": "Feature", "properties": { "point_type": "origin", "points_str": "45.528134, -122.562861" }, "geometry": { "type": "Point", "coordinates": [ -122.562860714754223, 45.52813415441333 ] } },
{ "type": "Feature", "properties": { "point_type": "destination", "points_str": "45.497586, -122.871514" }, "geometry": { "type": "Point", "coordinates": [ -122.871513763542296, 45.497585569097275 ] } }
]
}
