{
"type": "FeatureCollection",
"name": "origin_destination_points",
"crs": { "type": "name", "properties": { "name": "urn:ogc:def:crs:OGC:1.3:CRS84" } },
"features": [
{ "type": "Feature", "properties": { "point_type": "origin", "points_str": "45.497124, -122.554139" }, "geometry": { "type": "Point", "coordinates": [ -122.554138587130183, 45.497124419559007 ] } },
{ "type": "Feature", "properties": { "point_type": "destination", "points_str": "45.469088, -122.583508" }, "geometry": { "type": "Point", "coordinates": [ -122.58350843377788, 45.469087777358055 ] } }
]
}
