{
"type": "FeatureCollection",
"name": "origin_destination_points",
"crs": { "type": "name", "properties": { "name": "urn:ogc:def:crs:OGC:1.3:CRS84" } },
"features": [
{ "type": "Feature", "properties": { "point_type": "origin", "points_str": "45.523823, -122.554512" }, "geometry": { "type": "Point", "coordinates": [ -122.554512228856595, 45.523822742812726 ] } },
{ "type": "Feature", "properties": { "point_type": "destination", "points_str": "45.589944, -122.711794" }, "geometry": { "type": "Point", "coordinates": [ -122.711794402726568, 45.589944351576101 ] } }
]
}
