{
"type": "FeatureCollection",
"name": "origin_destination_points",
"crs": { "type": "name", "properties": { "name": "urn:ogc:def:crs:OGC:1.3:CRS84" } },
"features": [
{ "type": "Feature", "properties": { "point_type": "origin", "points_str": "45.517563, -122.73561" }, "geometry": { "type": "Point", "coordinates": [ -122.735609680962341, 45.517562895315166 ] } },
{ "type": "Feature", "properties": { "point_type": "destination", "points_str": "45.529469, -122.453358" }, "geometry": { "type": "Point", "coordinates": [ -122.453358417619256, 45.529469380805459 ] } }
]
}
