{
"type": "FeatureCollection",
"name": "origin_destination_points",
"crs": { "type": "name", "properties": { "name": "urn:ogc:def:crs:OGC:1.3:CRS84" } },
"features": [
{ "type": "Feature", "properties": { "point_type": "origin", "points_str": "45.536471, -122.685247" }, "geometry": { "type": "Point", "coordinates": [ -122.685246790465428, 45.536471010825672 ] } },
{ "type": "Feature", "properties": { "point_type": "destination", "points_str": "45.612998, -122.686019" }, "geometry": { "type": "Point", "coordinates": [ -122.686018816248989, 45.612998449249055 ] } }
]
}
