{
"type": "FeatureCollection",
"name": "origin_destination_points",
"crs": { "type": "name", "properties": { "name": "urn:ogc:def:crs:OGC:1.3:CRS84" } },
"features": [
{ "type": "Feature", "properties": { "point_type": "origin", "points_str": "45.522481, -123.116957" }, "geometry": { "type": "Point", "coordinates": [ -123.116957477472639, 45.522480747892494 ] } },
{ "type": "Feature", "properties": { "point_type": "destination", "points_str": "45.550978, -122.865079" }, "geometry": { "type": "Point", "coordinates": [ -122.865079496664151, 45.550978393211139 ] } }
]
}
