{
"type": "FeatureCollection",
"name": "origin_destination_points",
"crs": { "type": "name", "properties": { "name": "urn:ogc:def:crs:OGC:1.3:CRS84" } },
"features": [
{ "type": "Feature", "properties": { "point_type": "origin", "points_str": "45.508444, -122.853431" }, "geometry": { "type": "Point", "coordinates": [ -122.853431158153711, 45.508443803540636 ] } },
{ "type": "Feature", "properties": { "point_type": "destination", "points_str": "45.488347, -122.536943" }, "geometry": { "type": "Point", "coordinates": [ -122.536943000051792, 45.488346843293797 ] } }
]
}
