{
"type": "FeatureCollection",
"crs": { "type": "name", "properties": { "name": "urn:ogc:def:crs:OGC:1.3:CRS84" } },
"features": [
{ "type": "Feature", "properties": { "point_type": "origin", "points_str": "45.483684, -122.712141" }, "geometry": { "type": "Point", "coordinates": [ -122.712141213734213, 45.483683778754383 ] } },
{ "type": "Feature", "properties": { "point_type": "destination", "points_str": "45.503458, -122.847219" }, "geometry": { "type": "Point", "coordinates": [ -122.847219370314207, 45.503457966742857 ] } }
]
}
