{
"type": "FeatureCollection",
"crs": { "type": "name", "properties": { "name": "urn:ogc:def:crs:OGC:1.3:CRS84" } },
"features": [
{ "type": "Feature", "properties": { "point_type": "origin", "points_str": "45.517337, -122.655272" }, "geometry": { "type": "Point", "coordinates": [ -122.65527180281758, 45.517336906373451 ] } },
{ "type": "Feature", "properties": { "point_type": "destination", "points_str": "45.549887, -122.629284" }, "geometry": { "type": "Point", "coordinates": [ -122.629283828294732, 45.549887151791289 ] } }
]
}
