{
"type": "FeatureCollection",
"name": "origin_destination_points",
"crs": { "type": "name", "properties": { "name": "urn:ogc:def:crs:OGC:1.3:CRS84" } },
"features": [
{ "type": "Feature", "properties": { "point_type": "origin", "points_str": "45.490595, -122.598733" }, "geometry": { "type": "Point", "coordinates": [ -122.598732728490376, 45.490595136029576 ] } },
{ "type": "Feature", "properties": { "point_type": "destination", "points_str": "45.586176, -122.666246" }, "geometry": { "type": "Point", "coordinates": [ -122.666246477823094, 45.586176185672826 ] } }
]
}
