{
"type": "FeatureCollection",
"name": "origin_destination_points",
"crs": { "type": "name", "properties": { "name": "urn:ogc:def:crs:OGC:1.3:CRS84" } },
"features": [
{ "type": "Feature", "properties": { "point_type": "origin", "points_str": "45.477854, -122.675374" }, "geometry": { "type": "Point", "coordinates": [ -122.675373997067538, 45.47785367230432 ] } },
{ "type": "Feature", "properties": { "point_type": "destination", "points_str": "45.529408, -122.928156" }, "geometry": { "type": "Point", "coordinates": [ -122.928156292868579, 45.529408305591872 ] } }
]
}
