{
"type": "FeatureCollection",
"name": "origin_destination_points",
"crs": { "type": "name", "properties": { "name": "urn:ogc:def:crs:OGC:1.3:CRS84" } },
"features": [
{ "type": "Feature", "properties": { "point_type": "origin", "points_str": "45.594779, -122.747739" }, "geometry": { "type": "Point", "coordinates": [ -122.747739287221691, 45.594779456170969 ] } },
{ "type": "Feature", "properties": { "point_type": "destination", "points_str": "45.628709, -122.818682" }, "geometry": { "type": "Point", "coordinates": [ -122.818682018942312, 45.628708976675675 ] } }
]
}
