{
"type": "FeatureCollection",
"name": "origin_destination_points",
"crs": { "type": "name", "properties": { "name": "urn:ogc:def:crs:OGC:1.3:CRS84" } },
"features": [
{ "type": "Feature", "properties": { "point_type": "origin", "points_str": "45.433644, -122.654009" }, "geometry": { "type": "Point", "coordinates": [ -122.654008953653744, 45.433643588169964 ] } },
{ "type": "Feature", "properties": { "point_type": "destination", "points_str": "45.578482, -122.69356" }, "geometry": { "type": "Point", "coordinates": [ -122.693559966621109, 45.578481769767308 ] } }
]
}
