{
"type": "FeatureCollection",
"name": "origin_destination_points",
"crs": { "type": "name", "properties": { "name": "urn:ogc:def:crs:OGC:1.3:CRS84" } },
"features": [
{ "type": "Feature", "properties": { "point_type": "origin", "points_str": "45.516815, -122.662573" }, "geometry": { "type": "Point", "coordinates": [ -122.662572618325044, 45.516815404628971 ] } },
{ "type": "Feature", "properties": { "point_type": "destination", "points_str": "45.479938, -122.702532" }, "geometry": { "type": "Point", "coordinates": [ -122.702531600743285, 45.479938473911176 ] } }
]
}
