{
"type": "FeatureCollection",
"name": "origin_destination_points",
"crs": { "type": "name", "properties": { "name": "urn:ogc:def:crs:OGC:1.3:CRS84" } },
"features": [
{ "type": "Feature", "properties": { "point_type": "origin", "points_str": "45.434887, -122.656284" }, "geometry": { "type": "Point", "coordinates": [ -122.656284438888861, 45.434887344181128 ] } },
{ "type": "Feature", "properties": { "point_type": "destination", "points_str": "45.570509, -122.717947" }, "geometry": { "type": "Point", "coordinates": [ -122.717946501853532, 45.570509340358285 ] } }
]
}
