{
"type": "FeatureCollection",
"name": "origin_destination_points",
"crs": { "type": "name", "properties": { "name": "urn:ogc:def:crs:OGC:1.3:CRS84" } },
"features": [
{ "type": "Feature", "properties": { "point_type": "origin", "points_str": "45.565529, -122.600599" }, "geometry": { "type": "Point", "coordinates": [ -122.600599308639815, 45.565529416503878 ] } },
{ "type": "Feature", "properties": { "point_type": "destination", "points_str": "45.591674, -122.721125" }, "geometry": { "type": "Point", "coordinates": [ -122.72112539345494, 45.591673797043285 ] } }
]
}
