{
"type": "FeatureCollection",
"name": "origin_destination_points",
"crs": { "type": "name", "properties": { "name": "urn:ogc:def:crs:OGC:1.3:CRS84" } },
"features": [
{ "type": "Feature", "properties": { "point_type": "origin", "points_str": "45.513396, -122.610931" }, "geometry": { "type": "Point", "coordinates": [ -122.610930614384259, 45.513395853993309 ] } },
{ "type": "Feature", "properties": { "point_type": "destination", "points_str": "45.526968, -122.656138" }, "geometry": { "type": "Point", "coordinates": [ -122.656138014061156, 45.526967972924332 ] } }
]
}
