{
"type": "FeatureCollection",
"crs": { "type": "name", "properties": { "name": "urn:ogc:def:crs:OGC:1.3:CRS84" } },
"features": [
{ "type": "Feature", "properties": { "point_type": "origin", "points_str": "45.568434, -122.657786" }, "geometry": { "type": "Point", "coordinates": [ -122.65778635462982, 45.568434257766441 ] } },
{ "type": "Feature", "properties": { "point_type": "destination", "points_str": "45.412435, -122.668182" }, "geometry": { "type": "Point", "coordinates": [ -122.668181783436864, 45.412434853853043 ] } }
]
}
