{
"type": "FeatureCollection",
"name": "origin_destination_points",
"crs": { "type": "name", "properties": { "name": "urn:ogc:def:crs:OGC:1.3:CRS84" } },
"features": [
{ "type": "Feature", "properties": { "point_type": "origin", "points_str": "45.548468, -122.508755" }, "geometry": { "type": "Point", "coordinates": [ -122.508755450614217, 45.548467941544367 ] } },
{ "type": "Feature", "properties": { "point_type": "destination", "points_str": "45.428366, -122.767871" }, "geometry": { "type": "Point", "coordinates": [ -122.767871338167723, 45.428365944964398 ] } }
]
}
