{
"type": "FeatureCollection",
"name": "origin_destination_points",
"crs": { "type": "name", "properties": { "name": "urn:ogc:def:crs:OGC:1.3:CRS84" } },
"features": [
{ "type": "Feature", "properties": { "point_type": "origin", "points_str": "45.583735, -122.663162" }, "geometry": { "type": "Point", "coordinates": [ -122.663162443412034, 45.58373453044581 ] } },
{ "type": "Feature", "properties": { "point_type": "destination", "points_str": "45.540914, -122.622851" }, "geometry": { "type": "Point", "coordinates": [ -122.622851163555097, 45.540914152554386 ] } }
]
}
