{
"type": "FeatureCollection",
"name": "origin_destination_points",
"crs": { "type": "name", "properties": { "name": "urn:ogc:def:crs:OGC:1.3:CRS84" } },
"features": [
{ "type": "Feature", "properties": { "point_type": "origin", "points_str": "45.382007, -122.817713" }, "geometry": { "type": "Point", "coordinates": [ -122.817713487182871, 45.382007268872691 ] } },
{ "type": "Feature", "properties": { "point_type": "destination", "points_str": "45.547188, -122.5974" }, "geometry": { "type": "Point", "coordinates": [ -122.597400214961198, 45.547188142258086 ] } }
]
}
