{
"type": "FeatureCollection",
"name": "origin_destination_points",
"crs": { "type": "name", "properties": { "name": "urn:ogc:def:crs:OGC:1.3:CRS84" } },
"features": [
{ "type": "Feature", "properties": { "point_type": "origin", "points_str": "45.572072, -122.678122" }, "geometry": { "type": "Point", "coordinates": [ -122.678121792265259, 45.572071664824712 ] } },
{ "type": "Feature", "properties": { "point_type": "destination", "points_str": "45.443563, -122.729869" }, "geometry": { "type": "Point", "coordinates": [ -122.729868971408351, 45.443562938709697 ] } }
]
}
