{
"type": "FeatureCollection",
"name": "origin_destination_points",
"crs": { "type": "name", "properties": { "name": "urn:ogc:def:crs:OGC:1.3:CRS84" } },
"features": [
{ "type": "Feature", "properties": { "point_type": "origin", "points_str": "45.442308, -122.659709" }, "geometry": { "type": "Point", "coordinates": [ -122.659709129465654, 45.442308450115206 ] } },
{ "type": "Feature", "properties": { "point_type": "destination", "points_str": "45.476727, -122.699247" }, "geometry": { "type": "Point", "coordinates": [ -122.699246962859462, 45.476727326287623 ] } }
]
}
