{
"type": "FeatureCollection",
"name": "origin_destination_points",
"crs": { "type": "name", "properties": { "name": "urn:ogc:def:crs:OGC:1.3:CRS84" } },
"features": [
{ "type": "Feature", "properties": { "point_type": "origin", "points_str": "45.591906, -122.593013" }, "geometry": { "type": "Point", "coordinates": [ -122.5930129920702, 45.591905531045455 ] } },
{ "type": "Feature", "properties": { "point_type": "destination", "points_str": "45.55537, -122.578598" }, "geometry": { "type": "Point", "coordinates": [ -122.578597944656451, 45.555369620248726 ] } }
]
}
