{
"type": "FeatureCollection",
"name": "origin_destination_points",
"crs": { "type": "name", "properties": { "name": "urn:ogc:def:crs:OGC:1.3:CRS84" } },
"features": [
{ "type": "Feature", "properties": { "point_type": "origin", "points_str": "45.530992, -122.916297" }, "geometry": { "type": "Point", "coordinates": [ -122.916297238918659, 45.530991901417934 ] } },
{ "type": "Feature", "properties": { "point_type": "destination", "points_str": "45.525539, -122.650449" }, "geometry": { "type": "Point", "coordinates": [ -122.650448970234862, 45.525539374276676 ] } }
]
}
