{
"type": "FeatureCollection",
"name": "origin_destination_points",
"crs": { "type": "name", "properties": { "name": "urn:ogc:def:crs:OGC:1.3:CRS84" } },
"features": [
{ "type": "Feature", "properties": { "point_type": "origin", "points_str": "45.397524, -122.571103" }, "geometry": { "type": "Point", "coordinates": [ -122.571103130172062, 45.397524262866618 ] } },
{ "type": "Feature", "properties": { "point_type": "destination", "points_str": "45.389233, -122.641241" }, "geometry": { "type": "Point", "coordinates": [ -122.6412406018962, 45.3892326691455 ] } }
]
}
