{
"type": "FeatureCollection",
"crs": { "type": "name", "properties": { "name": "urn:ogc:def:crs:OGC:1.3:CRS84" } },
"features": [
{ "type": "Feature", "properties": { "point_type": "origin", "points_str": "45.545229, -122.477122" }, "geometry": { "type": "Point", "coordinates": [ -122.477122064220495, 45.545229487423867 ] } },
{ "type": "Feature", "properties": { "point_type": "destination", "points_str": "45.496708, -122.494726" }, "geometry": { "type": "Point", "coordinates": [ -122.494725952991303, 45.496708425845569 ] } }
]
}
