{
"type": "FeatureCollection",
"name": "origin_destination_points",
"crs": { "type": "name", "properties": { "name": "urn:ogc:def:crs:OGC:1.3:CRS84" } },
"features": [
{ "type": "Feature", "properties": { "point_type": "origin", "points_str": "45.53568, -122.641225" }, "geometry": { "type": "Point", "coordinates": [ -122.641225422943251, 45.535679559715845 ] } },
{ "type": "Feature", "properties": { "point_type": "destination", "points_str": "45.465438, -122.612281" }, "geometry": { "type": "Point", "coordinates": [ -122.612280843912671, 45.465437752220524 ] } }
]
}
