{
"type": "FeatureCollection",
"name": "origin_destination_points",
"crs": { "type": "name", "properties": { "name": "urn:ogc:def:crs:OGC:1.3:CRS84" } },
"features": [
{ "type": "Feature", "properties": { "point_type": "origin", "points_str": "45.511124, -122.616689" }, "geometry": { "type": "Point", "coordinates": [ -122.616689265379904, 45.511124032890287 ] } },
{ "type": "Feature", "properties": { "point_type": "destination", "points_str": "45.493331, -122.559858" }, "geometry": { "type": "Point", "coordinates": [ -122.559858425577559, 45.49333118250928 ] } }
]
}
