{
"type": "FeatureCollection",
"name": "origin_destination_points",
"crs": { "type": "name", "properties": { "name": "urn:ogc:def:crs:OGC:1.3:CRS84" } },
"features": [
{ "type": "Feature", "properties": { "point_type": "origin", "points_str": "45.521511, -122.520185" }, "geometry": { "type": "Point", "coordinates": [ -122.520185134561359, 45.521510712009167 ] } },
{ "type": "Feature", "properties": { "point_type": "destination", "points_str": "45.509641, -122.853699" }, "geometry": { "type": "Point", "coordinates": [ -122.853698735742029, 45.509641027528481 ] } }
]
}
