{
"type": "FeatureCollection",
"name": "origin_destination_points",
"crs": { "type": "name", "properties": { "name": "urn:ogc:def:crs:OGC:1.3:CRS84" } },
"features": [
{ "type": "Feature", "properties": { "point_type": "origin", "points_str": "45.458102, -122.685014" }, "geometry": { "type": "Point", "coordinates": [ -122.685014083962372, 45.458102317619982 ] } },
{ "type": "Feature", "properties": { "point_type": "destination", "points_str": "45.570729, -122.65566" }, "geometry": { "type": "Point", "coordinates": [ -122.655660357994023, 45.570728687404277 ] } }
]
}
