{
"type": "FeatureCollection",
"name": "origin_destination_points",
"crs": { "type": "name", "properties": { "name": "urn:ogc:def:crs:OGC:1.3:CRS84" } },
"features": [
{ "type": "Feature", "properties": { "point_type": "origin", "points_str": "45.526533, -122.61625" }, "geometry": { "type": "Point", "coordinates": [ -122.616249720614036, 45.526532971591088 ] } },
{ "type": "Feature", "properties": { "point_type": "destination", "points_str": "45.521955, -122.819794" }, "geometry": { "type": "Point", "coordinates": [ -122.81979446826459, 45.521954613533062 ] } }
]
}
