{
"type": "FeatureCollection",
"name": "origin_destination_points",
"crs": { "type": "name", "properties": { "name": "urn:ogc:def:crs:OGC:1.3:CRS84" } },
"features": [
{ "type": "Feature", "properties": { "point_type": "origin", "points_str": "45.547971, -122.64823" }, "geometry": { "type": "Point", "coordinates": [ -122.648230320738435, 45.547970716162688 ] } },
{ "type": "Feature", "properties": { "point_type": "destination", "points_str": "45.479999, -122.675463" }, "geometry": { "type": "Point", "coordinates": [ -122.675462518153466, 45.479999338651247 ] } }
]
}
