{
"type": "FeatureCollection",
"name": "origin_destination_points",
"crs": { "type": "name", "properties": { "name": "urn:ogc:def:crs:OGC:1.3:CRS84" } },
"features": [
{ "type": "Feature", "properties": { "point_type": "origin", "points_str": "45.477589, -122.577179" }, "geometry": { "type": "Point", "coordinates": [ -122.577179013757828, 45.477588590467775 ] } },
{ "type": "Feature", "properties": { "point_type": "destination", "points_str": "45.524107, -122.679702" }, "geometry": { "type": "Point", "coordinates": [ -122.679701536808182, 45.524107475906504 ] } }
]
}
