{
"type": "FeatureCollection",
"name": "origin_destination_points",
"crs": { "type": "name", "properties": { "name": "urn:ogc:def:crs:OGC:1.3:CRS84" } },
"features": [
{ "type": "Feature", "properties": { "point_type": "origin", "points_str": "45.505355, -122.667544" }, "geometry": { "type": "Point", "coordinates": [ -122.667544105732773, 45.505354816456943 ] } },
{ "type": "Feature", "properties": { "point_type": "destination", "points_str": "45.465719, -122.61724" }, "geometry": { "type": "Point", "coordinates": [ -122.617239587382102, 45.465718953594475 ] } }
]
}
