{
"type": "FeatureCollection",
"name": "origin_destination_points",
"crs": { "type": "name", "properties": { "name": "urn:ogc:def:crs:OGC:1.3:CRS84" } },
"features": [
{ "type": "Feature", "properties": { "point_type": "origin", "points_str": "45.461753, -122.779325" }, "geometry": { "type": "Point", "coordinates": [ -122.779325120169574, 45.461753456236821 ] } },
{ "type": "Feature", "properties": { "point_type": "destination", "points_str": "45.495433, -122.817002" }, "geometry": { "type": "Point", "coordinates": [ -122.817001730346263, 45.495433466432658 ] } }
]
}
