{
"type": "FeatureCollection",
"name": "origin_destination_points",
"crs": { "type": "name", "properties": { "name": "urn:ogc:def:crs:OGC:1.3:CRS84" } },
"features": [
{ "type": "Feature", "properties": { "point_type": "origin", "points_str": "45.578137, -122.675602" }, "geometry": { "type": "Point", "coordinates": [ -122.675601558925223, 45.578136524852447 ] } },
{ "type": "Feature", "properties": { "point_type": "destination", "points_str": "45.501515, -122.579534" }, "geometry": { "type": "Point", "coordinates": [ -122.579534483157957, 45.50151501309734 ] } }
]
}
