{
"type": "FeatureCollection",
"name": "origin_destination_points",
"crs": { "type": "name", "properties": { "name": "urn:ogc:def:crs:OGC:1.3:CRS84" } },
"features": [
{ "type": "Feature", "properties": { "point_type": "origin", "points_str": "45.493387, -122.805894" }, "geometry": { "type": "Point", "coordinates": [ -122.805894029340223, 45.493386634847802 ] } },
{ "type": "Feature", "properties": { "point_type": "destination", "points_str": "45.540078, -122.475889" }, "geometry": { "type": "Point", "coordinates": [ -122.475889040843356, 45.540078225517654 ] } }
]
}
