{
"type": "FeatureCollection",
"name": "origin_destination_points",
"crs": { "type": "name", "properties": { "name": "urn:ogc:def:crs:OGC:1.3:CRS84" } },
"features": [
{ "type": "Feature", "properties": { "point_type": "origin", "points_str": "45.392866, -122.648451" }, "geometry": { "type": "Point", "coordinates": [ -122.64845149603174, 45.392865659451815 ] } },
{ "type": "Feature", "properties": { "point_type": "destination", "points_str": "45.56226, -122.686854" }, "geometry": { "type": "Point", "coordinates": [ -122.686854353114398, 45.562259988742653 ] } }
]
}
