{
"type": "FeatureCollection",
"name": "origin_destination_points",
"crs": { "type": "name", "properties": { "name": "urn:ogc:def:crs:OGC:1.3:CRS84" } },
"features": [
{ "type": "Feature", "properties": { "point_type": "origin", "points_str": "45.494483, -122.540882" }, "geometry": { "type": "Point", "coordinates": [ -122.540882212061788, 45.494482618185813 ] } },
{ "type": "Feature", "properties": { "point_type": "destination", "points_str": "45.482824, -122.676031" }, "geometry": { "type": "Point", "coordinates": [ -122.676030827787088, 45.482823733762444 ] } }
]
}
