{
"type": "FeatureCollection",
"name": "origin_destination_points",
"crs": { "type": "name", "properties": { "name": "urn:ogc:def:crs:OGC:1.3:CRS84" } },
"features": [
{ "type": "Feature", "properties": { "point_type": "origin", "points_str": "45.477851, -122.793656" }, "geometry": { "type": "Point", "coordinates": [ -122.7936560162494, 45.477850501692892 ] } },
{ "type": "Feature", "properties": { "point_type": "destination", "points_str": "45.309396, -122.778137" }, "geometry": { "type": "Point", "coordinates": [ -122.778136861428834, 45.309395699386528 ] } }
]
}
