{
"type": "FeatureCollection",
"name": "origin_destination_points",
"crs": { "type": "name", "properties": { "name": "urn:ogc:def:crs:OGC:1.3:CRS84" } },
"features": [
{ "type": "Feature", "properties": { "point_type": "origin", "points_str": "45.524016, -122.512062" }, "geometry": { "type": "Point", "coordinates": [ -122.512062255247471, 45.524015816788022 ] } },
{ "type": "Feature", "properties": { "point_type": "destination", "points_str": "45.538881, -122.713272" }, "geometry": { "type": "Point", "coordinates": [ -122.713272009100365, 45.538881481883998 ] } }
]
}
