{
"type": "FeatureCollection",
"name": "origin_destination_points",
"crs": { "type": "name", "properties": { "name": "urn:ogc:def:crs:OGC:1.3:CRS84" } },
"features": [
{ "type": "Feature", "properties": { "point_type": "origin", "points_str": "45.57188, -122.560498" }, "geometry": { "type": "Point", "coordinates": [ -122.560497779620732, 45.571880235012294 ] } },
{ "type": "Feature", "properties": { "point_type": "destination", "points_str": "45.510973, -122.807399" }, "geometry": { "type": "Point", "coordinates": [ -122.807398956642572, 45.510972558481527 ] } }
]
}
