{
"type": "FeatureCollection",
"name": "origin_destination_points",
"crs": { "type": "name", "properties": { "name": "urn:ogc:def:crs:OGC:1.3:CRS84" } },
"features": [
{ "type": "Feature", "properties": { "point_type": "origin", "points_str": "45.46612, -122.840186" }, "geometry": { "type": "Point", "coordinates": [ -122.840186450375768, 45.466120235999256 ] } },
{ "type": "Feature", "properties": { "point_type": "destination", "points_str": "45.488673, -122.678323" }, "geometry": { "type": "Point", "coordinates": [ -122.678322984464756, 45.488672949988654 ] } }
]
}
