{
"type": "FeatureCollection",
"name": "origin_destination_points",
"crs": { "type": "name", "properties": { "name": "urn:ogc:def:crs:OGC:1.3:CRS84" } },
"features": [
{ "type": "Feature", "properties": { "point_type": "origin", "points_str": "45.460546, -122.711763" }, "geometry": { "type": "Point", "coordinates": [ -122.711763322013326, 45.460546024755303 ] } },
{ "type": "Feature", "properties": { "point_type": "destination", "points_str": "45.516795, -122.463678" }, "geometry": { "type": "Point", "coordinates": [ -122.463677756157338, 45.516795071884481 ] } }
]
}
