{
"type": "FeatureCollection",
"name": "origin_destination_points",
"crs": { "type": "name", "properties": { "name": "urn:ogc:def:crs:OGC:1.3:CRS84" } },
"features": [
{ "type": "Feature", "properties": { "point_type": "origin", "points_str": "45.551911, -122.548419" }, "geometry": { "type": "Point", "coordinates": [ -122.548419333687733, 45.551911429545669 ] } },
{ "type": "Feature", "properties": { "point_type": "destination", "points_str": "45.54684, -122.479055" }, "geometry": { "type": "Point", "coordinates": [ -122.479054976110362, 45.546839730396989 ] } }
]
}
