{
"type": "FeatureCollection",
"name": "origin_destination_points",
"crs": { "type": "name", "properties": { "name": "urn:ogc:def:crs:OGC:1.3:CRS84" } },
"features": [
{ "type": "Feature", "properties": { "point_type": "origin", "points_str": "45.471193, -122.69233" }, "geometry": { "type": "Point", "coordinates": [ -122.692329579259564, 45.471193484428433 ] } },
{ "type": "Feature", "properties": { "point_type": "destination", "points_str": "45.540967, -122.457294" }, "geometry": { "type": "Point", "coordinates": [ -122.457293592854398, 45.540967446060783 ] } }
]
}
