{
"type": "FeatureCollection",
"crs": { "type": "name", "properties": { "name": "urn:ogc:def:crs:OGC:1.3:CRS84" } },
"features": [
{ "type": "Feature", "properties": { "point_type": "origin", "points_str": "45.536952, -123.001146" }, "geometry": { "type": "Point", "coordinates": [ -123.001146251959383, 45.53695199023246 ] } },
{ "type": "Feature", "properties": { "point_type": "destination", "points_str": "45.448676, -122.646439" }, "geometry": { "type": "Point", "coordinates": [ -122.646438966984292, 45.448675903987429 ] } }
]
}
