{
"type": "FeatureCollection",
"crs": { "type": "name", "properties": { "name": "urn:ogc:def:crs:OGC:1.3:CRS84" } },
"features": [
{ "type": "Feature", "properties": { "point_type": "origin", "points_str": "45.517895, -122.738312" }, "geometry": { "type": "Point", "coordinates": [ -122.738312182471489, 45.517894808736244 ] } },
{ "type": "Feature", "properties": { "point_type": "destination", "points_str": "45.374265, -122.758648" }, "geometry": { "type": "Point", "coordinates": [ -122.758648143839665, 45.374265051777471 ] } }
]
}
