{
"type": "FeatureCollection",
"name": "origin_destination_points",
"crs": { "type": "name", "properties": { "name": "urn:ogc:def:crs:OGC:1.3:CRS84" } },
"features": [
{ "type": "Feature", "properties": { "point_type": "origin", "points_str": "45.503068, -122.607809" }, "geometry": { "type": "Point", "coordinates": [ -122.607809042475054, 45.503067527193366 ] } },
{ "type": "Feature", "properties": { "point_type": "destination", "points_str": "45.5416, -122.433459" }, "geometry": { "type": "Point", "coordinates": [ -122.433459460706175, 45.541599514620685 ] } }
]
}
