{
"type": "FeatureCollection",
"name": "origin_destination_points",
"crs": { "type": "name", "properties": { "name": "urn:ogc:def:crs:OGC:1.3:CRS84" } },
"features": [
{ "type": "Feature", "properties": { "point_type": "origin", "points_str": "45.560547, -122.632178" }, "geometry": { "type": "Point", "coordinates": [ -122.632178142372055, 45.560546788233857 ] } },
{ "type": "Feature", "properties": { "point_type": "destination", "points_str": "45.573648, -122.675638" }, "geometry": { "type": "Point", "coordinates": [ -122.67563837148073, 45.573648217655446 ] } }
]
}
