{
"type": "FeatureCollection",
"name": "origin_destination_points",
"crs": { "type": "name", "properties": { "name": "urn:ogc:def:crs:OGC:1.3:CRS84" } },
"features": [
{ "type": "Feature", "properties": { "point_type": "origin", "points_str": "45.50646, -122.480594" }, "geometry": { "type": "Point", "coordinates": [ -122.480594149394392, 45.506460037585775 ] } },
{ "type": "Feature", "properties": { "point_type": "destination", "points_str": "45.571009, -122.611877" }, "geometry": { "type": "Point", "coordinates": [ -122.611877193080403, 45.571008604947266 ] } }
]
}
