{
"type": "FeatureCollection",
"crs": { "type": "name", "properties": { "name": "urn:ogc:def:crs:OGC:1.3:CRS84" } },
"features": [
{ "type": "Feature", "properties": { "point_type": "origin", "points_str": "45.514189, -122.607006" }, "geometry": { "type": "Point", "coordinates": [ -122.607005706951611, 45.514188654865109 ] } },
{ "type": "Feature", "properties": { "point_type": "destination", "points_str": "45.398391, -122.499755" }, "geometry": { "type": "Point", "coordinates": [ -122.499755031317122, 45.398391119649951 ] } }
]
}
