{
"type": "FeatureCollection",
"name": "origin_destination_points",
"crs": { "type": "name", "properties": { "name": "urn:ogc:def:crs:OGC:1.3:CRS84" } },
"features": [
{ "type": "Feature", "properties": { "point_type": "origin", "points_str": "45.598223, -122.762872" }, "geometry": { "type": "Point", "coordinates": [ -122.7628716154545, 45.598223460767549 ] } },
{ "type": "Feature", "properties": { "point_type": "destination", "points_str": "45.5286, -122.949947" }, "geometry": { "type": "Point", "coordinates": [ -122.949946853724342, 45.528599900792564 ] } }
]
}
