{
"type": "FeatureCollection",
"crs": { "type": "name", "properties": { "name": "urn:ogc:def:crs:OGC:1.3:CRS84" } },
"features": [
{ "type": "Feature", "properties": { "point_type": "origin", "points_str": "45.471411, -122.634026" }, "geometry": { "type": "Point", "coordinates": [ -122.63402550800447, 45.471411145604172 ] } },
{ "type": "Feature", "properties": { "point_type": "destination", "points_str": "45.487811, -122.725031" }, "geometry": { "type": "Point", "coordinates": [ -122.725030545691169, 45.487811066994041 ] } }
]
}
