{
"type": "FeatureCollection",
"name": "origin_destination_points",
"crs": { "type": "name", "properties": { "name": "urn:ogc:def:crs:OGC:1.3:CRS84" } },
"features": [
{ "type": "Feature", "properties": { "point_type": "origin", "points_str": "45.38043, -122.762906" }, "geometry": { "type": "Point", "coordinates": [ -122.762906202127624, 45.380430173204054 ] } },
{ "type": "Feature", "properties": { "point_type": "destination", "points_str": "45.420166, -122.660771" }, "geometry": { "type": "Point", "coordinates": [ -122.660771493172021, 45.420165787486212 ] } }
]
}
