{
"type": "FeatureCollection",
"name": "origin_destination_points",
"crs": { "type": "name", "properties": { "name": "urn:ogc:def:crs:OGC:1.3:CRS84" } },
"features": [
{ "type": "Feature", "properties": { "point_type": "origin", "points_str": "45.446353, -122.575576" }, "geometry": { "type": "Point", "coordinates": [ -122.575576120682101, 45.446352752302886 ] } },
{ "type": "Feature", "properties": { "point_type": "destination", "points_str": "45.56591, -122.623652" }, "geometry": { "type": "Point", "coordinates": [ -122.623652062464359, 45.565910292681153 ] } }
]
}
