{
"type": "FeatureCollection",
"name": "origin_destination_points",
"crs": { "type": "name", "properties": { "name": "urn:ogc:def:crs:OGC:1.3:CRS84" } },
"features": [
{ "type": "Feature", "properties": { "point_type": "origin", "points_str": "45.560015, -122.500138" }, "geometry": { "type": "Point", "coordinates": [ -122.500137864534608, 45.560015430287606 ] } },
{ "type": "Feature", "properties": { "point_type": "destination", "points_str": "45.512556, -122.436478" }, "geometry": { "type": "Point", "coordinates": [ -122.436477640718451, 45.512556103981019 ] } }
]
}
