{
"type": "FeatureCollection",
"name": "origin_destination_points",
"crs": { "type": "name", "properties": { "name": "urn:ogc:def:crs:OGC:1.3:CRS84" } },
"features": [
{ "type": "Feature", "properties": { "point_type": "origin", "points_str": "45.517295, -122.675108" }, "geometry": { "type": "Point", "coordinates": [ -122.675108395775354, 45.517295150505802 ] } },
{ "type": "Feature", "properties": { "point_type": "destination", "points_str": "45.534809, -122.669282" }, "geometry": { "type": "Point", "coordinates": [ -122.669281557943222, 45.534809400120729 ] } }
]
}
