{
"type": "FeatureCollection",
"crs": { "type": "name", "properties": { "name": "urn:ogc:def:crs:OGC:1.3:CRS84" } },
"features": [
{ "type": "Feature", "properties": { "point_type": "origin", "points_str": "45.487689, -122.818795" }, "geometry": { "type": "Point", "coordinates": [ -122.818794754385209, 45.487688907831789 ] } },
{ "type": "Feature", "properties": { "point_type": "destination", "points_str": "45.517676, -122.649362" }, "geometry": { "type": "Point", "coordinates": [ -122.649362426383348, 45.517676342750079 ] } }
]
}
