{
"type": "FeatureCollection",
"name": "origin_destination_points",
"crs": { "type": "name", "properties": { "name": "urn:ogc:def:crs:OGC:1.3:CRS84" } },
"features": [
{ "type": "Feature", "properties": { "point_type": "origin", "points_str": "45.502022, -122.683629" }, "geometry": { "type": "Point", "coordinates": [ -122.683629105538998, 45.50202154971452 ] } },
{ "type": "Feature", "properties": { "point_type": "destination", "points_str": "45.610984, -122.795486" }, "geometry": { "type": "Point", "coordinates": [ -122.795486385672319, 45.61098414618921 ] } }
]
}
