{
"type": "FeatureCollection",
"name": "origin_destination_points",
"crs": { "type": "name", "properties": { "name": "urn:ogc:def:crs:OGC:1.3:CRS84" } },
"features": [
{ "type": "Feature", "properties": { "point_type": "origin", "points_str": "45.509751, -122.681673" }, "geometry": { "type": "Point", "coordinates": [ -122.681673108224587, 45.509750605524175 ] } },
{ "type": "Feature", "properties": { "point_type": "destination", "points_str": "45.557343, -122.582446" }, "geometry": { "type": "Point", "coordinates": [ -122.582446432687277, 45.557342518807218 ] } }
]
}
