{
"type": "FeatureCollection",
"name": "origin_destination_points",
"crs": { "type": "name", "properties": { "name": "urn:ogc:def:crs:OGC:1.3:CRS84" } },
"features": [
{ "type": "Feature", "properties": { "point_type": "origin", "points_str": "45.575085, -122.713509" }, "geometry": { "type": "Point", "coordinates": [ -122.713509321473765, 45.575084704925189 ] } },
{ "type": "Feature", "properties": { "point_type": "destination", "points_str": "45.530143, -122.664702" }, "geometry": { "type": "Point", "coordinates": [ -122.664702044639796, 45.530143434800877 ] } }
]
}
