{
"type": "FeatureCollection",
"name": "origin_destination_points",
"crs": { "type": "name", "properties": { "name": "urn:ogc:def:crs:OGC:1.3:CRS84" } },
"features": [
{ "type": "Feature", "properties": { "point_type": "origin", "points_str": "45.520257, -122.494875" }, "geometry": { "type": "Point", "coordinates": [ -122.494875349011281, 45.520256717786204 ] } },
{ "type": "Feature", "properties": { "point_type": "destination", "points_str": "45.513155, -122.869302" }, "geometry": { "type": "Point", "coordinates": [ -122.869301603056527, 45.513155358416213 ] } }
]
}
