{
"type": "FeatureCollection",
"crs": { "type": "name", "properties": { "name": "urn:ogc:def:crs:OGC:1.3:CRS84" } },
"features": [
{ "type": "Feature", "properties": { "point_type": "origin", "points_str": "45.477696, -122.784765" }, "geometry": { "type": "Point", "coordinates": [ -122.78476510983316, 45.477695703393458 ] } },
{ "type": "Feature", "properties": { "point_type": "destination", "points_str": "45.498564, -122.916302" }, "geometry": { "type": "Point", "coordinates": [ -122.916301995385439, 45.498563588474155 ] } }
]
}
