{
"type": "FeatureCollection",
"crs": { "type": "name", "properties": { "name": "urn:ogc:def:crs:OGC:1.3:CRS84" } },
"features": [
{ "type": "Feature", "properties": { "point_type": "origin", "points_str": "45.533091, -122.437831" }, "geometry": { "type": "Point", "coordinates": [ -122.437830995330117, 45.533090916502324 ] } },
{ "type": "Feature", "properties": { "point_type": "destination", "points_str": "45.517374, -122.387855" }, "geometry": { "type": "Point", "coordinates": [ -122.38785480687271, 45.517374213308834 ] } }
]
}
