{
"type": "FeatureCollection",
"crs": { "type": "name", "properties": { "name": "urn:ogc:def:crs:OGC:1.3:CRS84" } },
"features": [
{ "type": "Feature", "properties": { "point_type": "origin", "points_str": "45.524665, -122.599" }, "geometry": { "type": "Point", "coordinates": [ -122.598999702096975, 45.52466452661794 ] } },
{ "type": "Feature", "properties": { "point_type": "destination", "points_str": "45.492893, -122.410978" }, "geometry": { "type": "Point", "coordinates": [ -122.410977864960785, 45.492893172749433 ] } }
]
}
