{
"type": "FeatureCollection",
"crs": { "type": "name", "properties": { "name": "urn:ogc:def:crs:OGC:1.3:CRS84" } },
"features": [
{ "type": "Feature", "properties": { "point_type": "origin", "points_str": "45.501297, -122.718423" }, "geometry": { "type": "Point", "coordinates": [ -122.718423131277007, 45.501296856167471 ] } },
{ "type": "Feature", "properties": { "point_type": "destination", "points_str": "45.538606, -122.404919" }, "geometry": { "type": "Point", "coordinates": [ -122.404918968275169, 45.538606013713874 ] } }
]
}
