{
"type": "FeatureCollection",
"crs": { "type": "name", "properties": { "name": "urn:ogc:def:crs:OGC:1.3:CRS84" } },
"features": [
{ "type": "Feature", "properties": { "point_type": "origin", "points_str": "45.444953, -122.659432" }, "geometry": { "type": "Point", "coordinates": [ -122.659432432194066, 45.44495261023453 ] } },
{ "type": "Feature", "properties": { "point_type": "destination", "points_str": "45.475033, -122.519743" }, "geometry": { "type": "Point", "coordinates": [ -122.519743106915143, 45.475033083857383 ] } }
]
}
