{
"type": "FeatureCollection",
"crs": { "type": "name", "properties": { "name": "urn:ogc:def:crs:OGC:1.3:CRS84" } },
"features": [
{ "type": "Feature", "properties": { "point_type": "origin", "points_str": "45.531502, -122.517572" }, "geometry": { "type": "Point", "coordinates": [ -122.517572402430545, 45.531501750694062 ] } },
{ "type": "Feature", "properties": { "point_type": "destination", "points_str": "45.4907, -122.612037" }, "geometry": { "type": "Point", "coordinates": [ -122.612036575226611, 45.490700226194704 ] } }
]
}
