{
"type": "FeatureCollection",
"name": "origin_destination_points",
"crs": { "type": "name", "properties": { "name": "urn:ogc:def:crs:OGC:1.3:CRS84" } },
"features": [
{ "type": "Feature", "properties": { "point_type": "origin", "points_str": "45.401925, -122.583399" }, "geometry": { "type": "Point", "coordinates": [ -122.583399146724418, 45.401924583017426 ] } },
{ "type": "Feature", "properties": { "point_type": "destination", "points_str": "45.562177, -122.605982" }, "geometry": { "type": "Point", "coordinates": [ -122.605981799981166, 45.562177390241743 ] } }
]
}
