{
"type": "FeatureCollection",
"name": "origin_destination_points",
"crs": { "type": "name", "properties": { "name": "urn:ogc:def:crs:OGC:1.3:CRS84" } },
"features": [
{ "type": "Feature", "properties": { "point_type": "origin", "points_str": "45.585467, -122.715356" }, "geometry": { "type": "Point", "coordinates": [ -122.715355807903663, 45.585466642566402 ] } },
{ "type": "Feature", "properties": { "point_type": "destination", "points_str": "45.537567, -122.477404" }, "geometry": { "type": "Point", "coordinates": [ -122.477403672178397, 45.537566925097295 ] } }
]
}
