{
"type": "FeatureCollection",
"name": "origin_destination_points",
"crs": { "type": "name", "properties": { "name": "urn:ogc:def:crs:OGC:1.3:CRS84" } },
"features": [
{ "type": "Feature", "properties": { "point_type": "origin", "points_str": "45.53338, -122.682145" }, "geometry": { "type": "Point", "coordinates": [ -122.682144761859192, 45.533379921923995 ] } },
{ "type": "Feature", "properties": { "point_type": "destination", "points_str": "45.515956, -122.61777" }, "geometry": { "type": "Point", "coordinates": [ -122.61777004185258, 45.515956350226126 ] } }
]
}
