{
"type": "FeatureCollection",
"name": "origin_destination_points",
"crs": { "type": "name", "properties": { "name": "urn:ogc:def:crs:OGC:1.3:CRS84" } },
"features": [
{ "type": "Feature", "properties": { "point_type": "origin", "points_str": "45.411923, -122.616311" }, "geometry": { "type": "Point", "coordinates": [ -122.616311049438792, 45.411922750742541 ] } },
{ "type": "Feature", "properties": { "point_type": "destination", "points_str": "45.577556, -122.647346" }, "geometry": { "type": "Point", "coordinates": [ -122.647346100231943, 45.577555973118713 ] } }
]
}
