{
"type": "FeatureCollection",
"crs": { "type": "name", "properties": { "name": "urn:ogc:def:crs:OGC:1.3:CRS84" } },
"features": [
{ "type": "Feature", "properties": { "point_type": "origin", "points_str": "45.524084, -122.474626" }, "geometry": { "type": "Point", "coordinates": [ -122.474626441233553, 45.524083953201867 ] } },
{ "type": "Feature", "properties": { "point_type": "destination", "points_str": "45.541988, -122.420205" }, "geometry": { "type": "Point", "coordinates": [ -122.420205252934082, 45.54198808941684 ] } }
]
}
