{
"type": "FeatureCollection",
"name": "origin_destination_points",
"crs": { "type": "name", "properties": { "name": "urn:ogc:def:crs:OGC:1.3:CRS84" } },
"features": [
{ "type": "Feature", "properties": { "point_type": "origin", "points_str": "45.51815, -122.522592" }, "geometry": { "type": "Point", "coordinates": [ -122.522592311603091, 45.518150461220493 ] } },
{ "type": "Feature", "properties": { "point_type": "destination", "points_str": "45.546992, -122.701885" }, "geometry": { "type": "Point", "coordinates": [ -122.701884969769793, 45.546992197677866 ] } }
]
}
