{
"type": "FeatureCollection",
"name": "origin_destination_points",
"crs": { "type": "name", "properties": { "name": "urn:ogc:def:crs:OGC:1.3:CRS84" } },
"features": [
{ "type": "Feature", "properties": { "point_type": "origin", "points_str": "45.483064, -122.825765" }, "geometry": { "type": "Point", "coordinates": [ -122.825765026536502, 45.483063546438821 ] } },
{ "type": "Feature", "properties": { "point_type": "destination", "points_str": "45.516623, -123.075565" }, "geometry": { "type": "Point", "coordinates": [ -123.075565277380321, 45.516623254782175 ] } }
]
}
