{
"type": "FeatureCollection",
"name": "origin_destination_points",
"crs": { "type": "name", "properties": { "name": "urn:ogc:def:crs:OGC:1.3:CRS84" } },
"features": [
{ "type": "Feature", "properties": { "point_type": "origin", "points_str": "45.520678, -122.66187" }, "geometry": { "type": "Point", "coordinates": [ -122.661869513312894, 45.520677673085245 ] } },
{ "type": "Feature", "properties": { "point_type": "destination", "points_str": "45.519021, -122.493997" }, "geometry": { "type": "Point", "coordinates": [ -122.493996630292742, 45.519021301996446 ] } }
]
}
