{
"type": "FeatureCollection",
"name": "origin_destination_points",
"crs": { "type": "name", "properties": { "name": "urn:ogc:def:crs:OGC:1.3:CRS84" } },
"features": [
{ "type": "Feature", "properties": { "point_type": "origin", "points_str": "45.48357, -122.56176" }, "geometry": { "type": "Point", "coordinates": [ -122.561759567766941, 45.483570188088336 ] } },
{ "type": "Feature", "properties": { "point_type": "destination", "points_str": "45.5791, -122.701883" }, "geometry": { "type": "Point", "coordinates": [ -122.701882518797305, 45.579099814858864 ] } }
]
}
