{
"type": "FeatureCollection",
"name": "origin_destination_points",
"crs": { "type": "name", "properties": { "name": "urn:ogc:def:crs:OGC:1.3:CRS84" } },
"features": [
{ "type": "Feature", "properties": { "point_type": "origin", "points_str": "45.400781, -122.653544" }, "geometry": { "type": "Point", "coordinates": [ -122.653544406266164, 45.400780766548742 ] } },
{ "type": "Feature", "properties": { "point_type": "destination", "points_str": "45.431009, -122.710626" }, "geometry": { "type": "Point", "coordinates": [ -122.710626261150239, 45.431008650446692 ] } }
]
}
