{
"type": "FeatureCollection",
"crs": { "type": "name", "properties": { "name": "urn:ogc:def:crs:OGC:1.3:CRS84" } },
"features": [
{ "type": "Feature", "properties": { "point_type": "origin", "points_str": "45.591041, -122.6589" }, "geometry": { "type": "Point", "coordinates": [ -122.658899657507604, 45.591041498591117 ] } },
{ "type": "Feature", "properties": { "point_type": "destination", "points_str": "45.520974, -122.480791" }, "geometry": { "type": "Point", "coordinates": [ -122.480790824513065, 45.520973624480895 ] } }
]
}
