{
"type": "FeatureCollection",
"crs": { "type": "name", "properties": { "name": "urn:ogc:def:crs:OGC:1.3:CRS84" } },
"features": [
{ "type": "Feature", "properties": { "point_type": "origin", "points_str": "45.516184, -122.524723" }, "geometry": { "type": "Point", "coordinates": [ -122.524722920668779, 45.516183767682193 ] } },
{ "type": "Feature", "properties": { "point_type": "destination", "points_str": "45.556547, -122.693559" }, "geometry": { "type": "Point", "coordinates": [ -122.693559075356049, 45.556547141446927 ] } }
]
}
