{
"type": "FeatureCollection",
"crs": { "type": "name", "properties": { "name": "urn:ogc:def:crs:OGC:1.3:CRS84" } },
"features": [
{ "type": "Feature", "properties": { "point_type": "origin", "points_str": "45.555137, -122.616328" }, "geometry": { "type": "Point", "coordinates": [ -122.616327933922136, 45.555137124856294 ] } },
{ "type": "Feature", "properties": { "point_type": "destination", "points_str": "45.557235, -122.648529" }, "geometry": { "type": "Point", "coordinates": [ -122.648528512848273, 45.557234744580292 ] } }
]
}
