{
"type": "FeatureCollection",
"name": "origin_destination_points",
"crs": { "type": "name", "properties": { "name": "urn:ogc:def:crs:OGC:1.3:CRS84" } },
"features": [
{ "type": "Feature", "properties": { "point_type": "origin", "points_str": "45.541983, -122.414262" }, "geometry": { "type": "Point", "coordinates": [ -122.414262370463376, 45.541983110248431 ] } },
{ "type": "Feature", "properties": { "point_type": "destination", "points_str": "45.543113, -122.609477" }, "geometry": { "type": "Point", "coordinates": [ -122.609476903100756, 45.543113304714986 ] } }
]
}
