{
"type": "FeatureCollection",
"name": "origin_destination_points",
"crs": { "type": "name", "properties": { "name": "urn:ogc:def:crs:OGC:1.3:CRS84" } },
"features": [
{ "type": "Feature", "properties": { "point_type": "origin", "points_str": "45.51763, -122.644938" }, "geometry": { "type": "Point", "coordinates": [ -122.644937667065932, 45.51763019060175 ] } },
{ "type": "Feature", "properties": { "point_type": "destination", "points_str": "45.469979, -122.595896" }, "geometry": { "type": "Point", "coordinates": [ -122.59589631604041, 45.469979335602005 ] } }
]
}
