{
"type": "FeatureCollection",
"crs": { "type": "name", "properties": { "name": "urn:ogc:def:crs:OGC:1.3:CRS84" } },
"features": [
{ "type": "Feature", "properties": { "point_type": "origin", "points_str": "45.494579, -122.806677" }, "geometry": { "type": "Point", "coordinates": [ -122.806676903033832, 45.494578721669221 ] } },
{ "type": "Feature", "properties": { "point_type": "destination", "points_str": "45.512377, -122.789003" }, "geometry": { "type": "Point", "coordinates": [ -122.789002642653358, 45.512376551092451 ] } }
]
}
