{
"type": "FeatureCollection",
"name": "origin_destination_points",
"crs": { "type": "name", "properties": { "name": "urn:ogc:def:crs:OGC:1.3:CRS84" } },
"features": [
{ "type": "Feature", "properties": { "point_type": "origin", "points_str": "45.521878, -122.981026" }, "geometry": { "type": "Point", "coordinates": [ -122.981026272138024, 45.521878372152898 ] } },
{ "type": "Feature", "properties": { "point_type": "destination", "points_str": "45.488349, -122.466667" }, "geometry": { "type": "Point", "coordinates": [ -122.466667202959812, 45.488348505982131 ] } }
]
}
