{
"type": "FeatureCollection",
"crs": { "type": "name", "properties": { "name": "urn:ogc:def:crs:OGC:1.3:CRS84" } },
"features": [
{ "type": "Feature", "properties": { "point_type": "origin", "points_str": "45.488058, -122.552297" }, "geometry": { "type": "Point", "coordinates": [ -122.552297072704661, 45.488058248675181 ] } },
{ "type": "Feature", "properties": { "point_type": "destination", "points_str": "45.499209, -122.416815" }, "geometry": { "type": "Point", "coordinates": [ -122.416815402160935, 45.499209312832072 ] } }
]
}
