{
"type": "FeatureCollection",
"crs": { "type": "name", "properties": { "name": "urn:ogc:def:crs:OGC:1.3:CRS84" } },
"features": [
{ "type": "Feature", "properties": { "point_type": "origin", "points_str": "45.550355, -122.664393" }, "geometry": { "type": "Point", "coordinates": [ -122.664393317027503, 45.550355127852292 ] } },
{ "type": "Feature", "properties": { "point_type": "destination", "points_str": "45.571017, -122.554263" }, "geometry": { "type": "Point", "coordinates": [ -122.55426304423429, 45.571016918890649 ] } }
]
}
