{
"type": "FeatureCollection",
"name": "origin_destination_points",
"crs": { "type": "name", "properties": { "name": "urn:ogc:def:crs:OGC:1.3:CRS84" } },
"features": [
{ "type": "Feature", "properties": { "point_type": "origin", "points_str": "45.521312, -122.648805" }, "geometry": { "type": "Point", "coordinates": [ -122.648805069181833, 45.521312331115922 ] } },
{ "type": "Feature", "properties": { "point_type": "destination", "points_str": "45.462937, -122.64804" }, "geometry": { "type": "Point", "coordinates": [ -122.648040128596023, 45.46293691412837 ] } }
]
}
