{
"type": "FeatureCollection",
"name": "origin_destination_points",
"crs": { "type": "name", "properties": { "name": "urn:ogc:def:crs:OGC:1.3:CRS84" } },
"features": [
{ "type": "Feature", "properties": { "point_type": "origin", "points_str": "45.53179, -122.392413" }, "geometry": { "type": "Point", "coordinates": [ -122.392412952189233, 45.531789808899475 ] } },
{ "type": "Feature", "properties": { "point_type": "destination", "points_str": "45.527943, -122.527147" }, "geometry": { "type": "Point", "coordinates": [ -122.527147068802549, 45.527942961516928 ] } }
]
}
