{
"type": "FeatureCollection",
"name": "origin_destination_points",
"crs": { "type": "name", "properties": { "name": "urn:ogc:def:crs:OGC:1.3:CRS84" } },
"features": [
{ "type": "Feature", "properties": { "point_type": "origin", "points_str": "45.519463, -122.677116" }, "geometry": { "type": "Point", "coordinates": [ -122.6771161569593, 45.519463198176929 ] } },
{ "type": "Feature", "properties": { "point_type": "destination", "points_str": "45.520171, -122.989312" }, "geometry": { "type": "Point", "coordinates": [ -122.989311824493498, 45.520170741272217 ] } }
]
}
