{
"type": "FeatureCollection",
"name": "origin_destination_points",
"crs": { "type": "name", "properties": { "name": "urn:ogc:def:crs:OGC:1.3:CRS84" } },
"features": [
{ "type": "Feature", "properties": { "point_type": "origin", "points_str": "45.582713, -122.724732" }, "geometry": { "type": "Point", "coordinates": [ -122.724731719128783, 45.582712994899936 ] } },
{ "type": "Feature", "properties": { "point_type": "destination", "points_str": "45.531822, -122.611916" }, "geometry": { "type": "Point", "coordinates": [ -122.611916113807823, 45.531821847540975 ] } }
]
}
