{
"type": "FeatureCollection",
"name": "origin_destination_points",
"crs": { "type": "name", "properties": { "name": "urn:ogc:def:crs:OGC:1.3:CRS84" } },
"features": [
{ "type": "Feature", "properties": { "point_type": "origin", "points_str": "45.499867, -122.547836" }, "geometry": { "type": "Point", "coordinates": [ -122.547836394536773, 45.499867266250732 ] } },
{ "type": "Feature", "properties": { "point_type": "destination", "points_str": "45.489363, -122.738434" }, "geometry": { "type": "Point", "coordinates": [ -122.738433564288144, 45.489362562094364 ] } }
]
}
