{
"type": "FeatureCollection",
"name": "origin_destination_points",
"crs": { "type": "name", "properties": { "name": "urn:ogc:def:crs:OGC:1.3:CRS84" } },
"features": [
{ "type": "Feature", "properties": { "point_type": "origin", "points_str": "45.548139, -122.628926" }, "geometry": { "type": "Point", "coordinates": [ -122.628925608469501, 45.548139265152301 ] } },
{ "type": "Feature", "properties": { "point_type": "destination", "points_str": "45.548918, -122.57904" }, "geometry": { "type": "Point", "coordinates": [ -122.579039527448501, 45.548918158973628 ] } }
]
}
