{
"type": "FeatureCollection",
"name": "origin_destination_points",
"crs": { "type": "name", "properties": { "name": "urn:ogc:def:crs:OGC:1.3:CRS84" } },
"features": [
{ "type": "Feature", "properties": { "point_type": "origin", "points_str": "45.427514, -122.630335" }, "geometry": { "type": "Point", "coordinates": [ -122.630334837127137, 45.427514304552496 ] } },
{ "type": "Feature", "properties": { "point_type": "destination", "points_str": "45.433797, -122.598777" }, "geometry": { "type": "Point", "coordinates": [ -122.598777195459462, 45.433797069273197 ] } }
]
}
