{
"type": "FeatureCollection",
"crs": { "type": "name", "properties": { "name": "urn:ogc:def:crs:OGC:1.3:CRS84" } },
"features": [
{ "type": "Feature", "properties": { "point_type": "origin", "points_str": "45.379474, -122.386199" }, "geometry": { "type": "Point", "coordinates": [ -122.386198960712363, 45.379474345311309 ] } },
{ "type": "Feature", "properties": { "point_type": "destination", "points_str": "45.38335, -122.457948" }, "geometry": { "type": "Point", "coordinates": [ -122.457947710461326, 45.383350377329137 ] } }
]
}
