{
"type": "FeatureCollection",
"name": "origin_destination_points",
"crs": { "type": "name", "properties": { "name": "urn:ogc:def:crs:OGC:1.3:CRS84" } },
"features": [
{ "type": "Feature", "properties": { "point_type": "origin", "points_str": "45.554896, -122.729356" }, "geometry": { "type": "Point", "coordinates": [ -122.729356479290203, 45.554896437820233 ] } },
{ "type": "Feature", "properties": { "point_type": "destination", "points_str": "45.521848, -122.504566" }, "geometry": { "type": "Point", "coordinates": [ -122.504566120610704, 45.521847737542714 ] } }
]
}
