{
"type": "FeatureCollection",
"name": "origin_destination_points",
"crs": { "type": "name", "properties": { "name": "urn:ogc:def:crs:OGC:1.3:CRS84" } },
"features": [
{ "type": "Feature", "properties": { "point_type": "origin", "points_str": "45.487779, -122.870769" }, "geometry": { "type": "Point", "coordinates": [ -122.870768794883162, 45.487778921983043 ] } },
{ "type": "Feature", "properties": { "point_type": "destination", "points_str": "45.519304, -123.096442" }, "geometry": { "type": "Point", "coordinates": [ -123.096442105434861, 45.519304170717511 ] } }
]
}
