{
"type": "FeatureCollection",
"name": "origin_destination_points",
"crs": { "type": "name", "properties": { "name": "urn:ogc:def:crs:OGC:1.3:CRS84" } },
"features": [
{ "type": "Feature", "properties": { "point_type": "origin", "points_str": "45.522462, -122.577915" }, "geometry": { "type": "Point", "coordinates": [ -122.577915329673971, 45.52246152902017 ] } },
{ "type": "Feature", "properties": { "point_type": "destination", "points_str": "45.490925, -122.556919" }, "geometry": { "type": "Point", "coordinates": [ -122.556919432074608, 45.490924620106028 ] } }
]
}
