{
"type": "FeatureCollection",
"name": "origin_destination_points",
"crs": { "type": "name", "properties": { "name": "urn:ogc:def:crs:OGC:1.3:CRS84" } },
"features": [
{ "type": "Feature", "properties": { "point_type": "origin", "points_str": "45.519454, -122.515966" }, "geometry": { "type": "Point", "coordinates": [ -122.515966005236578, 45.519453549412198 ] } },
{ "type": "Feature", "properties": { "point_type": "destination", "points_str": "45.557284, -122.736511" }, "geometry": { "type": "Point", "coordinates": [ -122.736510607476347, 45.557283666067335 ] } }
]
}
