{
"type": "FeatureCollection",
"crs": { "type": "name", "properties": { "name": "urn:ogc:def:crs:OGC:1.3:CRS84" } },
"features": [
{ "type": "Feature", "properties": { "point_type": "origin", "points_str": "45.575516, -122.714716" }, "geometry": { "type": "Point", "coordinates": [ -122.714715900418966, 45.575515969317173 ] } },
{ "type": "Feature", "properties": { "point_type": "destination", "points_str": "45.48364, -122.712965" }, "geometry": { "type": "Point", "coordinates": [ -122.712964960338454, 45.483640008131189 ] } }
]
}
