{
"type": "FeatureCollection",
"name": "origin_destination_points",
"crs": { "type": "name", "properties": { "name": "urn:ogc:def:crs:OGC:1.3:CRS84" } },
"features": [
{ "type": "Feature", "properties": { "point_type": "origin", "points_str": "45.507505, -122.587101" }, "geometry": { "type": "Point", "coordinates": [ -122.587101117720337, 45.507504785253474 ] } },
{ "type": "Feature", "properties": { "point_type": "destination", "points_str": "45.469177, -122.710202" }, "geometry": { "type": "Point", "coordinates": [ -122.710201906102611, 45.469176937170509 ] } }
]
}
