{
"type": "FeatureCollection",
"crs": { "type": "name", "properties": { "name": "urn:ogc:def:crs:OGC:1.3:CRS84" } },
"features": [
{ "type": "Feature", "properties": { "point_type": "origin", "points_str": "45.498524, -122.552672" }, "geometry": { "type": "Point", "coordinates": [ -122.552671979589377, 45.498523527049571 ] } },
{ "type": "Feature", "properties": { "point_type": "destination", "points_str": "45.504641, -122.432451" }, "geometry": { "type": "Point", "coordinates": [ -122.432450622041344, 45.504640738863955 ] } }
]
}
