{
"type": "FeatureCollection",
"name": "origin_destination_points",
"crs": { "type": "name", "properties": { "name": "urn:ogc:def:crs:OGC:1.3:CRS84" } },
"features": [
{ "type": "Feature", "properties": { "point_type": "origin", "points_str": "45.462044, -122.68282" }, "geometry": { "type": "Point", "coordinates": [ -122.682819838037915, 45.462043979458223 ] } },
{ "type": "Feature", "properties": { "point_type": "destination", "points_str": "45.50907, -122.670078" }, "geometry": { "type": "Point", "coordinates": [ -122.670078474550081, 45.509069678546076 ] } }
]
}
