{
"type": "FeatureCollection",
"name": "origin_destination_points",
"crs": { "type": "name", "properties": { "name": "urn:ogc:def:crs:OGC:1.3:CRS84" } },
"features": [
{ "type": "Feature", "properties": { "point_type": "origin", "points_str": "45.379008, -122.753676" }, "geometry": { "type": "Point", "coordinates": [ -122.753676121473987, 45.379007645427293 ] } },
{ "type": "Feature", "properties": { "point_type": "destination", "points_str": "45.398175, -122.801179" }, "geometry": { "type": "Point", "coordinates": [ -122.801179137941631, 45.398175357303174 ] } }
]
}
