{
"type": "FeatureCollection",
"name": "origin_destination_points",
"crs": { "type": "name", "properties": { "name": "urn:ogc:def:crs:OGC:1.3:CRS84" } },
"features": [
{ "type": "Feature", "properties": { "point_type": "origin", "points_str": "45.464802, -122.685708" }, "geometry": { "type": "Point", "coordinates": [ -122.685707606029681, 45.464802288248926 ] } },
{ "type": "Feature", "properties": { "point_type": "destination", "points_str": "45.570467, -122.691339" }, "geometry": { "type": "Point", "coordinates": [ -122.691338976877958, 45.570466935583852 ] } }
]
}
