{
"type": "FeatureCollection",
"name": "origin_destination_points",
"crs": { "type": "name", "properties": { "name": "urn:ogc:def:crs:OGC:1.3:CRS84" } },
"features": [
{ "type": "Feature", "properties": { "point_type": "origin", "points_str": "45.526899, -122.536461" }, "geometry": { "type": "Point", "coordinates": [ -122.536460635666757, 45.526898984619002 ] } },
{ "type": "Feature", "properties": { "point_type": "destination", "points_str": "45.51812, -122.672127" }, "geometry": { "type": "Point", "coordinates": [ -122.672126656234852, 45.518119665408477 ] } }
]
}
