{
"type": "FeatureCollection",
"name": "origin_destination_points",
"crs": { "type": "name", "properties": { "name": "urn:ogc:def:crs:OGC:1.3:CRS84" } },
"features": [
{ "type": "Feature", "properties": { "point_type": "origin", "points_str": "45.433731, -122.655492" }, "geometry": { "type": "Point", "coordinates": [ -122.655492112557354, 45.433730695785698 ] } },
{ "type": "Feature", "properties": { "point_type": "destination", "points_str": "45.544439, -122.397367" }, "geometry": { "type": "Point", "coordinates": [ -122.397366971970172, 45.544439350419822 ] } }
]
}
