{
"type": "FeatureCollection",
"name": "origin_destination_points",
"crs": { "type": "name", "properties": { "name": "urn:ogc:def:crs:OGC:1.3:CRS84" } },
"features": [
{ "type": "Feature", "properties": { "point_type": "origin", "points_str": "45.583418, -122.751298" }, "geometry": { "type": "Point", "coordinates": [ -122.751298292575427, 45.583417958226178 ] } },
{ "type": "Feature", "properties": { "point_type": "destination", "points_str": "45.510993, -122.733806" }, "geometry": { "type": "Point", "coordinates": [ -122.733806426660635, 45.510992947340142 ] } }
]
}
