{
"type": "FeatureCollection",
"name": "origin_destination_points",
"crs": { "type": "name", "properties": { "name": "urn:ogc:def:crs:OGC:1.3:CRS84" } },
"features": [
{ "type": "Feature", "properties": { "point_type": "origin", "points_str": "45.425527, -122.529894" }, "geometry": { "type": "Point", "coordinates": [ -122.529893871373432, 45.425527291174127 ] } },
{ "type": "Feature", "properties": { "point_type": "destination", "points_str": "45.497942, -122.563462" }, "geometry": { "type": "Point", "coordinates": [ -122.563461828165231, 45.497942019781782 ] } }
]
}
