{
"type": "FeatureCollection",
"name": "origin_destination_points",
"crs": { "type": "name", "properties": { "name": "urn:ogc:def:crs:OGC:1.3:CRS84" } },
"features": [
{ "type": "Feature", "properties": { "point_type": "origin", "points_str": "45.447961, -122.612772" }, "geometry": { "type": "Point", "coordinates": [ -122.612772323255314, 45.447961114578369 ] } },
{ "type": "Feature", "properties": { "point_type": "destination", "points_str": "45.518228, -122.624572" }, "geometry": { "type": "Point", "coordinates": [ -122.624572022857578, 45.518227606588781 ] } }
]
}
