{
"type": "FeatureCollection",
"name": "origin_destination_points",
"crs": { "type": "name", "properties": { "name": "urn:ogc:def:crs:OGC:1.3:CRS84" } },
"features": [
{ "type": "Feature", "properties": { "point_type": "origin", "points_str": "45.518484, -122.728949" }, "geometry": { "type": "Point", "coordinates": [ -122.728949286860043, 45.518483659583687 ] } },
{ "type": "Feature", "properties": { "point_type": "destination", "points_str": "45.486892, -122.534355" }, "geometry": { "type": "Point", "coordinates": [ -122.534354780963625, 45.486891757184367 ] } }
]
}
