{
"type": "FeatureCollection",
"name": "origin_destination_points",
"crs": { "type": "name", "properties": { "name": "urn:ogc:def:crs:OGC:1.3:CRS84" } },
"features": [
{ "type": "Feature", "properties": { "point_type": "origin", "points_str": "45.490968, -122.831968" }, "geometry": { "type": "Point", "coordinates": [ -122.831968431655127, 45.490967637820255 ] } },
{ "type": "Feature", "properties": { "point_type": "destination", "points_str": "45.455829, -122.825712" }, "geometry": { "type": "Point", "coordinates": [ -122.825712429497358, 45.455829435335438 ] } }
]
}
