{
"type": "FeatureCollection",
"crs": { "type": "name", "properties": { "name": "urn:ogc:def:crs:OGC:1.3:CRS84" } },
"features": [
{ "type": "Feature", "properties": { "point_type": "origin", "points_str": "45.55473, -122.625684" }, "geometry": { "type": "Point", "coordinates": [ -122.625684176942642, 45.55472979748837 ] } },
{ "type": "Feature", "properties": { "point_type": "destination", "points_str": "45.455334, -122.634636" }, "geometry": { "type": "Point", "coordinates": [ -122.634636318691165, 45.455334156424961 ] } }
]
}
