{
"type": "FeatureCollection",
"crs": { "type": "name", "properties": { "name": "urn:ogc:def:crs:OGC:1.3:CRS84" } },
"features": [
{ "type": "Feature", "properties": { "point_type": "origin", "points_str": "45.472249, -122.802995" }, "geometry": { "type": "Point", "coordinates": [ -122.802995056780901, 45.472248969039988 ] } },
{ "type": "Feature", "properties": { "point_type": "destination", "points_str": "45.437294, -122.775435" }, "geometry": { "type": "Point", "coordinates": [ -122.775435244871829, 45.43729419359024 ] } }
]
}
