{
"type": "FeatureCollection",
"crs": { "type": "name", "properties": { "name": "urn:ogc:def:crs:OGC:1.3:CRS84" } },
"features": [
{ "type": "Feature", "properties": { "point_type": "origin", "points_str": "45.488448, -122.777424" }, "geometry": { "type": "Point", "coordinates": [ -122.777423688655162, 45.488448492674351 ] } },
{ "type": "Feature", "properties": { "point_type": "destination", "points_str": "45.503129, -122.429181" }, "geometry": { "type": "Point", "coordinates": [ -122.429181083332523, 45.503128886460914 ] } }
]
}
