{
"type": "FeatureCollection",
"name": "origin_destination_points",
"crs": { "type": "name", "properties": { "name": "urn:ogc:def:crs:OGC:1.3:CRS84" } },
"features": [
{ "type": "Feature", "properties": { "point_type": "origin", "points_str": "45.475482, -122.633734" }, "geometry": { "type": "Point", "coordinates": [ -122.633733649073434, 45.47548208961117 ] } },
{ "type": "Feature", "properties": { "point_type": "destination", "points_str": "45.545819, -122.701179" }, "geometry": { "type": "Point", "coordinates": [ -122.701178932236132, 45.545818740209299 ] } }
]
}
