{
"type": "FeatureCollection",
"crs": { "type": "name", "properties": { "name": "urn:ogc:def:crs:OGC:1.3:CRS84" } },
"features": [
{ "type": "Feature", "properties": { "point_type": "origin", "points_str": "45.362321, -122.601008" }, "geometry": { "type": "Point", "coordinates": [ -122.601008238541567, 45.362320781163589 ] } },
{ "type": "Feature", "properties": { "point_type": "destination", "points_str": "45.470977, -122.698905" }, "geometry": { "type": "Point", "coordinates": [ -122.698905194069326, 45.470976686878373 ] } }
]
}
