{
"type": "FeatureCollection",
"crs": { "type": "name", "properties": { "name": "urn:ogc:def:crs:OGC:1.3:CRS84" } },
"features": [
{ "type": "Feature", "properties": { "point_type": "origin", "points_str": "45.533541, -122.557963" }, "geometry": { "type": "Point", "coordinates": [ -122.557962516771383, 45.533540846383261 ] } },
{ "type": "Feature", "properties": { "point_type": "destination", "points_str": "45.492418, -122.594291" }, "geometry": { "type": "Point", "coordinates": [ -122.594291431207367, 45.492417550088682 ] } }
]
}
