{
"type": "FeatureCollection",
"name": "origin_destination_points",
"crs": { "type": "name", "properties": { "name": "urn:ogc:def:crs:OGC:1.3:CRS84" } },
"features": [
{ "type": "Feature", "properties": { "point_type": "origin", "points_str": "45.486021, -122.628308" }, "geometry": { "type": "Point", "coordinates": [ -122.628308113474745, 45.486020839474364 ] } },
{ "type": "Feature", "properties": { "point_type": "destination", "points_str": "45.398472, -122.619533" }, "geometry": { "type": "Point", "coordinates": [ -122.61953256716383, 45.39847187576315 ] } }
]
}
