{
"type": "FeatureCollection",
"crs": { "type": "name", "properties": { "name": "urn:ogc:def:crs:OGC:1.3:CRS84" } },
"features": [
{ "type": "Feature", "properties": { "point_type": "origin", "points_str": "45.521993, -122.572066" }, "geometry": { "type": "Point", "coordinates": [ -122.572066369495559, 45.521992909920513 ] } },
{ "type": "Feature", "properties": { "point_type": "destination", "points_str": "45.516602, -122.544" }, "geometry": { "type": "Point", "coordinates": [ -122.544000109334291, 45.51660162986316 ] } }
]
}
