{
"type": "FeatureCollection",
"name": "origin_destination_points",
"crs": { "type": "name", "properties": { "name": "urn:ogc:def:crs:OGC:1.3:CRS84" } },
"features": [
{ "type": "Feature", "properties": { "point_type": "origin", "points_str": "45.521836, -122.974141" }, "geometry": { "type": "Point", "coordinates": [ -122.974140899676016, 45.521836115594191 ] } },
{ "type": "Feature", "properties": { "point_type": "destination", "points_str": "45.464684, -122.825314" }, "geometry": { "type": "Point", "coordinates": [ -122.825314298502605, 45.464684159458933 ] } }
]
}
