{
"type": "FeatureCollection",
"crs": { "type": "name", "properties": { "name": "urn:ogc:def:crs:OGC:1.3:CRS84" } },
"features": [
{ "type": "Feature", "properties": { "point_type": "origin", "points_str": "45.501824, -122.511048" }, "geometry": { "type": "Point", "coordinates": [ -122.511048145758778, 45.501824131995832 ] } },
{ "type": "Feature", "properties": { "point_type": "destination", "points_str": "45.524671, -122.687489" }, "geometry": { "type": "Point", "coordinates": [ -122.687488655079065, 45.524671104629476 ] } }
]
}
