{
"type": "FeatureCollection",
"crs": { "type": "name", "properties": { "name": "urn:ogc:def:crs:OGC:1.3:CRS84" } },
"features": [
{ "type": "Feature", "properties": { "point_type": "origin", "points_str": "45.466263, -122.617115" }, "geometry": { "type": "Point", "coordinates": [ -122.617115256606183, 45.466262746904071 ] } },
{ "type": "Feature", "properties": { "point_type": "destination", "points_str": "45.602553, -122.663342" }, "geometry": { "type": "Point", "coordinates": [ -122.6633421709994, 45.602552778890583 ] } }
]
}
