{
"type": "FeatureCollection",
"name": "origin_destination_points",
"crs": { "type": "name", "properties": { "name": "urn:ogc:def:crs:OGC:1.3:CRS84" } },
"features": [
{ "type": "Feature", "properties": { "point_type": "origin", "points_str": "45.501866, -122.636783" }, "geometry": { "type": "Point", "coordinates": [ -122.636783104073587, 45.501865833989818 ] } },
{ "type": "Feature", "properties": { "point_type": "destination", "points_str": "45.472857, -122.620086" }, "geometry": { "type": "Point", "coordinates": [ -122.620085915921592, 45.472857185994847 ] } }
]
}
