{
"type": "FeatureCollection",
"name": "origin_destination_points",
"crs": { "type": "name", "properties": { "name": "urn:ogc:def:crs:OGC:1.3:CRS84" } },
"features": [
{ "type": "Feature", "properties": { "point_type": "origin", "points_str": "45.534896, -122.385916" }, "geometry": { "type": "Point", "coordinates": [ -122.385916484866456, 45.534896449000968 ] } },
{ "type": "Feature", "properties": { "point_type": "destination", "points_str": "45.508247, -122.480518" }, "geometry": { "type": "Point", "coordinates": [ -122.480517560800052, 45.508246576424042 ] } }
]
}
