{
"type": "FeatureCollection",
"name": "origin_destination_points",
"crs": { "type": "name", "properties": { "name": "urn:ogc:def:crs:OGC:1.3:CRS84" } },
"features": [
{ "type": "Feature", "properties": { "point_type": "origin", "points_str": "45.485424, -122.542129" }, "geometry": { "type": "Point", "coordinates": [ -122.542129064482324, 45.485424414816009 ] } },
{ "type": "Feature", "properties": { "point_type": "destination", "points_str": "45.568737, -122.634629" }, "geometry": { "type": "Point", "coordinates": [ -122.63462868476158, 45.568737032575889 ] } }
]
}
