{
"type": "FeatureCollection",
"name": "origin_destination_points",
"crs": { "type": "name", "properties": { "name": "urn:ogc:def:crs:OGC:1.3:CRS84" } },
"features": [
{ "type": "Feature", "properties": { "point_type": "origin", "points_str": "45.527709, -122.691611" }, "geometry": { "type": "Point", "coordinates": [ -122.691611261133829, 45.527709373697057 ] } },
{ "type": "Feature", "properties": { "point_type": "destination", "points_str": "45.438912, -122.667994" }, "geometry": { "type": "Point", "coordinates": [ -122.667994389766889, 45.438911885484451 ] } }
]
}
