{
"type": "FeatureCollection",
"name": "origin_destination_points",
"crs": { "type": "name", "properties": { "name": "urn:ogc:def:crs:OGC:1.3:CRS84" } },
"features": [
{ "type": "Feature", "properties": { "point_type": "origin", "points_str": "45.345628, -122.641381" }, "geometry": { "type": "Point", "coordinates": [ -122.641381315709822, 45.345627874470345 ] } },
{ "type": "Feature", "properties": { "point_type": "destination", "points_str": "45.400418, -122.635442" }, "geometry": { "type": "Point", "coordinates": [ -122.63544231840784, 45.400417556149229 ] } }
]
}
