{
"type": "FeatureCollection",
"name": "origin_destination_points",
"crs": { "type": "name", "properties": { "name": "urn:ogc:def:crs:OGC:1.3:CRS84" } },
"features": [
{ "type": "Feature", "properties": { "point_type": "origin", "points_str": "45.460739, -122.58023" }, "geometry": { "type": "Point", "coordinates": [ -122.580230379472383, 45.46073874251627 ] } },
{ "type": "Feature", "properties": { "point_type": "destination", "points_str": "45.51877, -122.612411" }, "geometry": { "type": "Point", "coordinates": [ -122.612411167625126, 45.518769990138388 ] } }
]
}
