{
"type": "FeatureCollection",
"name": "origin_destination_points",
"crs": { "type": "name", "properties": { "name": "urn:ogc:def:crs:OGC:1.3:CRS84" } },
"features": [
{ "type": "Feature", "properties": { "point_type": "origin", "points_str": "45.457741, -122.711503" }, "geometry": { "type": "Point", "coordinates": [ -122.71150297460342, 45.457741495206733 ] } },
{ "type": "Feature", "properties": { "point_type": "destination", "points_str": "45.492712, -122.720856" }, "geometry": { "type": "Point", "coordinates": [ -122.72085589802019, 45.49271207455314 ] } }
]
}
