{
"type": "FeatureCollection",
"name": "origin_destination_points",
"crs": { "type": "name", "properties": { "name": "urn:ogc:def:crs:OGC:1.3:CRS84" } },
"features": [
{ "type": "Feature", "properties": { "point_type": "origin", "points_str": "45.532722, -122.929069" }, "geometry": { "type": "Point", "coordinates": [ -122.929068656351063, 45.532722351263196 ] } },
{ "type": "Feature", "properties": { "point_type": "destination", "points_str": "45.501034, -122.816544" }, "geometry": { "type": "Point", "coordinates": [ -122.816543702931142, 45.501033519642526 ] } }
]
}
