{
"type": "FeatureCollection",
"name": "origin_destination_points",
"crs": { "type": "name", "properties": { "name": "urn:ogc:def:crs:OGC:1.3:CRS84" } },
"features": [
{ "type": "Feature", "properties": { "point_type": "origin", "points_str": "45.523097, -122.656945" }, "geometry": { "type": "Point", "coordinates": [ -122.656945038297707, 45.523096752429119 ] } },
{ "type": "Feature", "properties": { "point_type": "destination", "points_str": "45.539796, -122.664708" }, "geometry": { "type": "Point", "coordinates": [ -122.664708232934558, 45.539795870454341 ] } }
]
}
