{
"type": "FeatureCollection",
"crs": { "type": "name", "properties": { "name": "urn:ogc:def:crs:OGC:1.3:CRS84" } },
"features": [
{ "type": "Feature", "properties": { "point_type": "origin", "points_str": "45.339108, -122.59691" }, "geometry": { "type": "Point", "coordinates": [ -122.596909696441344, 45.339107847757099 ] } },
{ "type": "Feature", "properties": { "point_type": "destination", "points_str": "45.424871, -122.659609" }, "geometry": { "type": "Point", "coordinates": [ -122.659608921757041, 45.424871279236349 ] } }
]
}
