{
"type": "FeatureCollection",
"name": "origin_destination_points",
"crs": { "type": "name", "properties": { "name": "urn:ogc:def:crs:OGC:1.3:CRS84" } },
"features": [
{ "type": "Feature", "properties": { "point_type": "origin", "points_str": "45.378635, -122.756237" }, "geometry": { "type": "Point", "coordinates": [ -122.756237488701061, 45.378635179308624 ] } },
{ "type": "Feature", "properties": { "point_type": "destination", "points_str": "45.446504, -122.760079" }, "geometry": { "type": "Point", "coordinates": [ -122.760078849836731, 45.446504268609232 ] } }
]
}
