{
"type": "FeatureCollection",
"crs": { "type": "name", "properties": { "name": "urn:ogc:def:crs:OGC:1.3:CRS84" } },
"features": [
{ "type": "Feature", "properties": { "point_type": "origin", "points_str": "45.457873, -122.627251" }, "geometry": { "type": "Point", "coordinates": [ -122.627251042125479, 45.457873142148486 ] } },
{ "type": "Feature", "properties": { "point_type": "destination", "points_str": "45.5862, -122.713762" }, "geometry": { "type": "Point", "coordinates": [ -122.71376194839921, 45.5862001755035 ] } }
]
}
