{
"type": "FeatureCollection",
"crs": { "type": "name", "properties": { "name": "urn:ogc:def:crs:OGC:1.3:CRS84" } },
"features": [
{ "type": "Feature", "properties": { "point_type": "origin", "points_str": "45.581056, -122.712546" }, "geometry": { "type": "Point", "coordinates": [ -122.71254600855535, 45.581056299960665 ] } },
{ "type": "Feature", "properties": { "point_type": "destination", "points_str": "45.366383, -122.585343" }, "geometry": { "type": "Point", "coordinates": [ -122.585343140258743, 45.36638339301475 ] } }
]
}
