{
"type": "FeatureCollection",
"name": "origin_destination_points",
"crs": { "type": "name", "properties": { "name": "urn:ogc:def:crs:OGC:1.3:CRS84" } },
"features": [
{ "type": "Feature", "properties": { "point_type": "origin", "points_str": "45.516796, -122.929854" }, "geometry": { "type": "Point", "coordinates": [ -122.929853542482391, 45.516795785093763 ] } },
{ "type": "Feature", "properties": { "point_type": "destination", "points_str": "45.516444, -123.030138" }, "geometry": { "type": "Point", "coordinates": [ -123.030138293240213, 45.516444188674001 ] } }
]
}
