{
"type": "FeatureCollection",
"crs": { "type": "name", "properties": { "name": "urn:ogc:def:crs:OGC:1.3:CRS84" } },
"features": [
{ "type": "Feature", "properties": { "point_type": "origin", "points_str": "45.542466, -122.604342" }, "geometry": { "type": "Point", "coordinates": [ -122.604342354423935, 45.542466300776432 ] } },
{ "type": "Feature", "properties": { "point_type": "destination", "points_str": "45.384769, -122.769815" }, "geometry": { "type": "Point", "coordinates": [ -122.769814502419479, 45.384769325026056 ] } }
]
}
