{
"type": "FeatureCollection",
"name": "origin_destination_points",
"crs": { "type": "name", "properties": { "name": "urn:ogc:def:crs:OGC:1.3:CRS84" } },
"features": [
{ "type": "Feature", "properties": { "point_type": "origin", "points_str": "45.489959, -122.555582" }, "geometry": { "type": "Point", "coordinates": [ -122.555582053021652, 45.489959202151468 ] } },
{ "type": "Feature", "properties": { "point_type": "destination", "points_str": "45.442711, -122.65544" }, "geometry": { "type": "Point", "coordinates": [ -122.655440036491058, 45.442711352578669 ] } }
]
}
