{
"type": "FeatureCollection",
"name": "origin_destination_points",
"crs": { "type": "name", "properties": { "name": "urn:ogc:def:crs:OGC:1.3:CRS84" } },
"features": [
{ "type": "Feature", "properties": { "point_type": "origin", "points_str": "45.442619, -122.627462" }, "geometry": { "type": "Point", "coordinates": [ -122.627461600048761, 45.442619200309288 ] } },
{ "type": "Feature", "properties": { "point_type": "destination", "points_str": "45.337396, -122.610254" }, "geometry": { "type": "Point", "coordinates": [ -122.610254181479192, 45.337396401276429 ] } }
]
}
