{
"type": "FeatureCollection",
"crs": { "type": "name", "properties": { "name": "urn:ogc:def:crs:OGC:1.3:CRS84" } },
"features": [
{ "type": "Feature", "properties": { "point_type": "origin", "points_str": "45.518221, -122.580376" }, "geometry": { "type": "Point", "coordinates": [ -122.580375783622557, 45.518221133283163 ] } },
{ "type": "Feature", "properties": { "point_type": "destination", "points_str": "45.563278, -122.692461" }, "geometry": { "type": "Point", "coordinates": [ -122.692460721752141, 45.563278089766499 ] } }
]
}
