{
"type": "FeatureCollection",
"name": "origin_destination_points",
"crs": { "type": "name", "properties": { "name": "urn:ogc:def:crs:OGC:1.3:CRS84" } },
"features": [
{ "type": "Feature", "properties": { "point_type": "origin", "points_str": "45.507136, -122.68073" }, "geometry": { "type": "Point", "coordinates": [ -122.680729679953473, 45.507136193580848 ] } },
{ "type": "Feature", "properties": { "point_type": "destination", "points_str": "45.449709, -122.75923" }, "geometry": { "type": "Point", "coordinates": [ -122.759229598764961, 45.449708521901236 ] } }
]
}
