{
"type": "FeatureCollection",
"name": "origin_destination_points",
"crs": { "type": "name", "properties": { "name": "urn:ogc:def:crs:OGC:1.3:CRS84" } },
"features": [
{ "type": "Feature", "properties": { "point_type": "origin", "points_str": "45.497743, -122.761169" }, "geometry": { "type": "Point", "coordinates": [ -122.761169324677454, 45.4977427707 ] } },
{ "type": "Feature", "properties": { "point_type": "destination", "points_str": "45.419937, -122.765653" }, "geometry": { "type": "Point", "coordinates": [ -122.765652566384887, 45.419937414673065 ] } }
]
}
