{
"type": "FeatureCollection",
"name": "origin_destination_points",
"crs": { "type": "name", "properties": { "name": "urn:ogc:def:crs:OGC:1.3:CRS84" } },
"features": [
{ "type": "Feature", "properties": { "point_type": "origin", "points_str": "45.526109, -122.463015" }, "geometry": { "type": "Point", "coordinates": [ -122.463014890530658, 45.526108982619554 ] } },
{ "type": "Feature", "properties": { "point_type": "destination", "points_str": "45.520351, -122.563667" }, "geometry": { "type": "Point", "coordinates": [ -122.56366662574564, 45.520351417185211 ] } }
]
}
