{
"type": "FeatureCollection",
"crs": { "type": "name", "properties": { "name": "urn:ogc:def:crs:OGC:1.3:CRS84" } },
"features": [
{ "type": "Feature", "properties": { "point_type": "origin", "points_str": "45.552631, -122.723154" }, "geometry": { "type": "Point", "coordinates": [ -122.723153615995002, 45.552630989444864 ] } },
{ "type": "Feature", "properties": { "point_type": "destination", "points_str": "45.520211, -122.544152" }, "geometry": { "type": "Point", "coordinates": [ -122.544152323672137, 45.520210877387555 ] } }
]
}
