{
"type": "FeatureCollection",
"name": "origin_destination_points",
"crs": { "type": "name", "properties": { "name": "urn:ogc:def:crs:OGC:1.3:CRS84" } },
"features": [
{ "type": "Feature", "properties": { "point_type": "origin", "points_str": "45.565207, -122.601268" }, "geometry": { "type": "Point", "coordinates": [ -122.601268431018397, 45.565206583322102 ] } },
{ "type": "Feature", "properties": { "point_type": "destination", "points_str": "45.499104, -122.606875" }, "geometry": { "type": "Point", "coordinates": [ -122.606874924074319, 45.499103718807049 ] } }
]
}
