{
"type": "FeatureCollection",
"name": "origin_destination_points",
"crs": { "type": "name", "properties": { "name": "urn:ogc:def:crs:OGC:1.3:CRS84" } },
"features": [
{ "type": "Feature", "properties": { "point_type": "origin", "points_str": "45.594318, -122.680015" }, "geometry": { "type": "Point", "coordinates": [ -122.680015338982102, 45.594317701658419 ] } },
{ "type": "Feature", "properties": { "point_type": "destination", "points_str": "45.5474, -122.583711" }, "geometry": { "type": "Point", "coordinates": [ -122.583711283113459, 45.547400004490555 ] } }
]
}
