{
"type": "FeatureCollection",
"name": "origin_destination_points",
"crs": { "type": "name", "properties": { "name": "urn:ogc:def:crs:OGC:1.3:CRS84" } },
"features": [
{ "type": "Feature", "properties": { "point_type": "origin", "points_str": "45.450882, -122.665149" }, "geometry": { "type": "Point", "coordinates": [ -122.665149150794051, 45.450882387939998 ] } },
{ "type": "Feature", "properties": { "point_type": "destination", "points_str": "45.534377, -122.653081" }, "geometry": { "type": "Point", "coordinates": [ -122.653081451646145, 45.534376893892123 ] } }
]
}
