{
"type": "FeatureCollection",
"name": "origin_destination_points",
"crs": { "type": "name", "properties": { "name": "urn:ogc:def:crs:OGC:1.3:CRS84" } },
"features": [
{ "type": "Feature", "properties": { "point_type": "origin", "points_str": "45.470213, -122.373503" }, "geometry": { "type": "Point", "coordinates": [ -122.373502527103128, 45.47021312533294 ] } },
{ "type": "Feature", "properties": { "point_type": "destination", "points_str": "45.487747, -122.37303" }, "geometry": { "type": "Point", "coordinates": [ -122.373029804641092, 45.487746838018587 ] } }
]
}
