{
"type": "FeatureCollection",
"name": "origin_destination_points",
"crs": { "type": "name", "properties": { "name": "urn:ogc:def:crs:OGC:1.3:CRS84" } },
"features": [
{ "type": "Feature", "properties": { "point_type": "origin", "points_str": "45.512043, -122.628978" }, "geometry": { "type": "Point", "coordinates": [ -122.628978306297682, 45.512043003774508 ] } },
{ "type": "Feature", "properties": { "point_type": "destination", "points_str": "45.571079, -122.708633" }, "geometry": { "type": "Point", "coordinates": [ -122.708633350666673, 45.571078713898572 ] } }
]
}
