{
"type": "FeatureCollection",
"name": "origin_destination_points",
"crs": { "type": "name", "properties": { "name": "urn:ogc:def:crs:OGC:1.3:CRS84" } },
"features": [
{ "type": "Feature", "properties": { "point_type": "origin", "points_str": "45.511105, -122.681905" }, "geometry": { "type": "Point", "coordinates": [ -122.681905413737439, 45.51110457413462 ] } },
{ "type": "Feature", "properties": { "point_type": "destination", "points_str": "45.541646, -122.66679" }, "geometry": { "type": "Point", "coordinates": [ -122.666789846154714, 45.541645830025473 ] } }
]
}
