{
"type": "FeatureCollection",
"name": "origin_destination_points",
"crs": { "type": "name", "properties": { "name": "urn:ogc:def:crs:OGC:1.3:CRS84" } },
"features": [
{ "type": "Feature", "properties": { "point_type": "origin", "points_str": "45.477893, -122.856245" }, "geometry": { "type": "Point", "coordinates": [ -122.856244971796912, 45.477892964060352 ] } },
{ "type": "Feature", "properties": { "point_type": "destination", "points_str": "45.532358, -122.561695" }, "geometry": { "type": "Point", "coordinates": [ -122.561695496374639, 45.532357533904168 ] } }
]
}
