{
"type": "FeatureCollection",
"crs": { "type": "name", "properties": { "name": "urn:ogc:def:crs:OGC:1.3:CRS84" } },
"features": [
{ "type": "Feature", "properties": { "point_type": "origin", "points_str": "45.504246, -122.532587" }, "geometry": { "type": "Point", "coordinates": [ -122.532586930747783, 45.504246097165627 ] } },
{ "type": "Feature", "properties": { "point_type": "destination", "points_str": "45.490501, -122.77094" }, "geometry": { "type": "Point", "coordinates": [ -122.770939610934875, 45.490500903939093 ] } }
]
}
