{
"type": "FeatureCollection",
"crs": { "type": "name", "properties": { "name": "urn:ogc:def:crs:OGC:1.3:CRS84" } },
"features": [
{ "type": "Feature", "properties": { "point_type": "origin", "points_str": "45.488596, -122.747993" }, "geometry": { "type": "Point", "coordinates": [ -122.747993085054219, 45.488596268522649 ] } },
{ "type": "Feature", "properties": { "point_type": "destination", "points_str": "45.430557, -122.638413" }, "geometry": { "type": "Point", "coordinates": [ -122.638412922967845, 45.430557386504738 ] } }
]
}
