{
"type": "FeatureCollection",
"name": "origin_destination_points",
"crs": { "type": "name", "properties": { "name": "urn:ogc:def:crs:OGC:1.3:CRS84" } },
"features": [
{ "type": "Feature", "properties": { "point_type": "origin", "points_str": "45.479409, -122.52288" }, "geometry": { "type": "Point", "coordinates": [ -122.522880419992902, 45.479408896694494 ] } },
{ "type": "Feature", "properties": { "point_type": "destination", "points_str": "45.429125, -122.63991" }, "geometry": { "type": "Point", "coordinates": [ -122.639910143037028, 45.429125398041563 ] } }
]
}
