{
"type": "FeatureCollection",
"name": "origin_destination_points",
"crs": { "type": "name", "properties": { "name": "urn:ogc:def:crs:OGC:1.3:CRS84" } },
"features": [
{ "type": "Feature", "properties": { "point_type": "origin", "points_str": "45.429159, -122.711074" }, "geometry": { "type": "Point", "coordinates": [ -122.711073613386176, 45.429159168851811 ] } },
{ "type": "Feature", "properties": { "point_type": "destination", "points_str": "45.487125, -122.743898" }, "geometry": { "type": "Point", "coordinates": [ -122.743897911191141, 45.487124594523799 ] } }
]
}
