{
"type": "FeatureCollection",
"crs": { "type": "name", "properties": { "name": "urn:ogc:def:crs:OGC:1.3:CRS84" } },
"features": [
{ "type": "Feature", "properties": { "point_type": "origin", "points_str": "45.319251, -122.554892" }, "geometry": { "type": "Point", "coordinates": [ -122.554891942996818, 45.319251490254068 ] } },
{ "type": "Feature", "properties": { "point_type": "destination", "points_str": "45.350463, -122.587904" }, "geometry": { "type": "Point", "coordinates": [ -122.58790383177552, 45.350462884299709 ] } }
]
}
