{
"type": "FeatureCollection",
"crs": { "type": "name", "properties": { "name": "urn:ogc:def:crs:OGC:1.3:CRS84" } },
"features": [
{ "type": "Feature", "properties": { "point_type": "origin", "points_str": "45.452742, -122.591875" }, "geometry": { "type": "Point", "coordinates": [ -122.59187513557427, 45.452742448552094 ] } },
{ "type": "Feature", "properties": { "point_type": "destination", "points_str": "45.508648, -122.612266" }, "geometry": { "type": "Point", "coordinates": [ -122.61226577092792, 45.508648340650311 ] } }
]
}
