{
"type": "FeatureCollection",
"name": "origin_destination_points",
"crs": { "type": "name", "properties": { "name": "urn:ogc:def:crs:OGC:1.3:CRS84" } },
"features": [
{ "type": "Feature", "properties": { "point_type": "origin", "points_str": "45.481319, -122.711127" }, "geometry": { "type": "Point", "coordinates": [ -122.711127462869001, 45.481318945188583 ] } },
{ "type": "Feature", "properties": { "point_type": "destination", "points_str": "45.373088, -122.751539" }, "geometry": { "type": "Point", "coordinates": [ -122.751538729714738, 45.373088196546085 ] } }
]
}
