{
"type": "FeatureCollection",
"name": "origin_destination_points",
"crs": { "type": "name", "properties": { "name": "urn:ogc:def:crs:OGC:1.3:CRS84" } },
"features": [
{ "type": "Feature", "properties": { "point_type": "origin", "points_str": "45.455478, -122.575802" }, "geometry": { "type": "Point", "coordinates": [ -122.575802051414783, 45.455477566481122 ] } },
{ "type": "Feature", "properties": { "point_type": "destination", "points_str": "45.521773, -122.736994" }, "geometry": { "type": "Point", "coordinates": [ -122.736994165566131, 45.521773371253431 ] } }
]
}
