{
"type": "FeatureCollection",
"name": "origin_destination_points",
"crs": { "type": "name", "properties": { "name": "urn:ogc:def:crs:OGC:1.3:CRS84" } },
"features": [
{ "type": "Feature", "properties": { "point_type": "origin", "points_str": "45.546995, -122.590048" }, "geometry": { "type": "Point", "coordinates": [ -122.590048008712472, 45.546994958850341 ] } },
{ "type": "Feature", "properties": { "point_type": "destination", "points_str": "45.490608, -122.811531" }, "geometry": { "type": "Point", "coordinates": [ -122.811531001641114, 45.490608326429758 ] } }
]
}
