{
"type": "FeatureCollection",
"name": "origin_destination_points",
"crs": { "type": "name", "properties": { "name": "urn:ogc:def:crs:OGC:1.3:CRS84" } },
"features": [
{ "type": "Feature", "properties": { "point_type": "origin", "points_str": "45.436129, -122.668859" }, "geometry": { "type": "Point", "coordinates": [ -122.668858659145442, 45.436129456181007 ] } },
{ "type": "Feature", "properties": { "point_type": "destination", "points_str": "45.519652, -122.478229" }, "geometry": { "type": "Point", "coordinates": [ -122.478229427193867, 45.519652265176958 ] } }
]
}
