{
"type": "FeatureCollection",
"crs": { "type": "name", "properties": { "name": "urn:ogc:def:crs:OGC:1.3:CRS84" } },
"features": [
{ "type": "Feature", "properties": { "point_type": "origin", "points_str": "45.507016, -122.605306" }, "geometry": { "type": "Point", "coordinates": [ -122.6053059191063, 45.507015635400535 ] } },
{ "type": "Feature", "properties": { "point_type": "destination", "points_str": "45.378782, -122.589287" }, "geometry": { "type": "Point", "coordinates": [ -122.589287413913937, 45.378782455723815 ] } }
]
}
