{
"type": "FeatureCollection",
"name": "origin_destination_points",
"crs": { "type": "name", "properties": { "name": "urn:ogc:def:crs:OGC:1.3:CRS84" } },
"features": [
{ "type": "Feature", "properties": { "point_type": "origin", "points_str": "45.554927, -122.724754" }, "geometry": { "type": "Point", "coordinates": [ -122.724753755910669, 45.554927319148952 ] } },
{ "type": "Feature", "properties": { "point_type": "destination", "points_str": "45.521881, -122.692893" }, "geometry": { "type": "Point", "coordinates": [ -122.692893162515034, 45.521881335941565 ] } }
]
}
