{
"type": "FeatureCollection",
"name": "origin_destination_points",
"crs": { "type": "name", "properties": { "name": "urn:ogc:def:crs:OGC:1.3:CRS84" } },
"features": [
{ "type": "Feature", "properties": { "point_type": "origin", "points_str": "45.339083, -122.602552" }, "geometry": { "type": "Point", "coordinates": [ -122.602551663893635, 45.339083014400458 ] } },
{ "type": "Feature", "properties": { "point_type": "destination", "points_str": "45.386541, -122.589659" }, "geometry": { "type": "Point", "coordinates": [ -122.589659019265895, 45.386541008027812 ] } }
]
}
