{
"type": "FeatureCollection",
"name": "origin_destination_points",
"crs": { "type": "name", "properties": { "name": "urn:ogc:def:crs:OGC:1.3:CRS84" } },
"features": [
{ "type": "Feature", "properties": { "point_type": "origin", "points_str": "45.511481, -122.7191" }, "geometry": { "type": "Point", "coordinates": [ -122.719100312498412, 45.511480554977496 ] } },
{ "type": "Feature", "properties": { "point_type": "destination", "points_str": "45.555021, -122.521751" }, "geometry": { "type": "Point", "coordinates": [ -122.521751152105637, 45.55502078109037 ] } }
]
}
