{
"type": "FeatureCollection",
"name": "origin_destination_points",
"crs": { "type": "name", "properties": { "name": "urn:ogc:def:crs:OGC:1.3:CRS84" } },
"features": [
{ "type": "Feature", "properties": { "point_type": "origin", "points_str": "45.545357, -122.600665" }, "geometry": { "type": "Point", "coordinates": [ -122.600664816943748, 45.545356921278724 ] } },
{ "type": "Feature", "properties": { "point_type": "destination", "points_str": "45.460611, -122.681975" }, "geometry": { "type": "Point", "coordinates": [ -122.681975275988236, 45.460611164955147 ] } }
]
}
