{
"type": "FeatureCollection",
"name": "origin_destination_points",
"crs": { "type": "name", "properties": { "name": "urn:ogc:def:crs:OGC:1.3:CRS84" } },
"features": [
{ "type": "Feature", "properties": { "point_type": "origin", "points_str": "45.541236, -122.424253" }, "geometry": { "type": "Point", "coordinates": [ -122.424252527868092, 45.541235924594325 ] } },
{ "type": "Feature", "properties": { "point_type": "destination", "points_str": "45.50367, -122.490492" }, "geometry": { "type": "Point", "coordinates": [ -122.490492444577683, 45.503670189879202 ] } }
]
}
