{
"type": "FeatureCollection",
"crs": { "type": "name", "properties": { "name": "urn:ogc:def:crs:OGC:1.3:CRS84" } },
"features": [
{ "type": "Feature", "properties": { "point_type": "origin", "points_str": "45.591655, -122.664184" }, "geometry": { "type": "Point", "coordinates": [ -122.664184320062176, 45.591655091615976 ] } },
{ "type": "Feature", "properties": { "point_type": "destination", "points_str": "45.523228, -122.982067" }, "geometry": { "type": "Point", "coordinates": [ -122.982067030319968, 45.523227962053845 ] } }
]
}
