{
"type": "FeatureCollection",
"name": "origin_destination_points",
"crs": { "type": "name", "properties": { "name": "urn:ogc:def:crs:OGC:1.3:CRS84" } },
"features": [
{ "type": "Feature", "properties": { "point_type": "origin", "points_str": "45.519989, -122.418462" }, "geometry": { "type": "Point", "coordinates": [ -122.418462206329849, 45.519988534410942 ] } },
{ "type": "Feature", "properties": { "point_type": "destination", "points_str": "45.503137, -122.555468" }, "geometry": { "type": "Point", "coordinates": [ -122.555467656512263, 45.503137187764423 ] } }
]
}
