{
"type": "FeatureCollection",
"crs": { "type": "name", "properties": { "name": "urn:ogc:def:crs:OGC:1.3:CRS84" } },
"features": [
{ "type": "Feature", "properties": { "point_type": "origin", "points_str": "45.480762, -122.589377" }, "geometry": { "type": "Point", "coordinates": [ -122.589376630688761, 45.48076155507303 ] } },
{ "type": "Feature", "properties": { "point_type": "destination", "points_str": "45.42457, -122.677346" }, "geometry": { "type": "Point", "coordinates": [ -122.677345667091032, 45.424570047124305 ] } }
]
}
