{
"type": "FeatureCollection",
"name": "origin_destination_points",
"crs": { "type": "name", "properties": { "name": "urn:ogc:def:crs:OGC:1.3:CRS84" } },
"features": [
{ "type": "Feature", "properties": { "point_type": "origin", "points_str": "45.508631, -122.657197" }, "geometry": { "type": "Point", "coordinates": [ -122.657196673071823, 45.508631087400005 ] } },
{ "type": "Feature", "properties": { "point_type": "destination", "points_str": "45.450658, -122.785318" }, "geometry": { "type": "Point", "coordinates": [ -122.785317863368107, 45.450657500953945 ] } }
]
}
