{
"type": "FeatureCollection",
"crs": { "type": "name", "properties": { "name": "urn:ogc:def:crs:OGC:1.3:CRS84" } },
"features": [
{ "type": "Feature", "properties": { "point_type": "origin", "points_str": "45.52022, -122.583735" }, "geometry": { "type": "Point", "coordinates": [ -122.583734516594149, 45.520219597501381 ] } },
{ "type": "Feature", "properties": { "point_type": "destination", "points_str": "45.5293, -122.817559" }, "geometry": { "type": "Point", "coordinates": [ -122.817558579167482, 45.529300317425438 ] } }
]
}
