{
"type": "FeatureCollection",
"name": "origin_destination_points",
"crs": { "type": "name", "properties": { "name": "urn:ogc:def:crs:OGC:1.3:CRS84" } },
"features": [
{ "type": "Feature", "properties": { "point_type": "origin", "points_str": "45.570112, -122.669744" }, "geometry": { "type": "Point", "coordinates": [ -122.669743568944952, 45.570112377272444 ] } },
{ "type": "Feature", "properties": { "point_type": "destination", "points_str": "45.476984, -122.673598" }, "geometry": { "type": "Point", "coordinates": [ -122.673597847103409, 45.476984261410152 ] } }
]
}
