{
"type": "FeatureCollection",
"name": "origin_destination_points",
"crs": { "type": "name", "properties": { "name": "urn:ogc:def:crs:OGC:1.3:CRS84" } },
"features": [
{ "type": "Feature", "properties": { "point_type": "origin", "points_str": "45.356195, -122.772492" }, "geometry": { "type": "Point", "coordinates": [ -122.772491898805313, 45.356194618567301 ] } },
{ "type": "Feature", "properties": { "point_type": "destination", "points_str": "45.587485, -122.714907" }, "geometry": { "type": "Point", "coordinates": [ -122.714906526873932, 45.587485047769725 ] } }
]
}
