{
"type": "FeatureCollection",
"crs": { "type": "name", "properties": { "name": "urn:ogc:def:crs:OGC:1.3:CRS84" } },
"features": [
{ "type": "Feature", "properties": { "point_type": "origin", "points_str": "45.544023, -122.639089" }, "geometry": { "type": "Point", "coordinates": [ -122.639089114573423, 45.544023458631251 ] } },
{ "type": "Feature", "properties": { "point_type": "destination", "points_str": "45.430785, -122.637479" }, "geometry": { "type": "Point", "coordinates": [ -122.637478623462414, 45.430785050170336 ] } }
]
}
