{
"type": "FeatureCollection",
"name": "origin_destination_points",
"crs": { "type": "name", "properties": { "name": "urn:ogc:def:crs:OGC:1.3:CRS84" } },
"features": [
{ "type": "Feature", "properties": { "point_type": "origin", "points_str": "45.428137, -122.503144" }, "geometry": { "type": "Point", "coordinates": [ -122.503143872467263, 45.428136647716414 ] } },
{ "type": "Feature", "properties": { "point_type": "destination", "points_str": "45.565918, -122.591578" }, "geometry": { "type": "Point", "coordinates": [ -122.591577667268851, 45.565918417906921 ] } }
]
}
