{
"type": "FeatureCollection",
"name": "origin_destination_points",
"crs": { "type": "name", "properties": { "name": "urn:ogc:def:crs:OGC:1.3:CRS84" } },
"features": [
{ "type": "Feature", "properties": { "point_type": "origin", "points_str": "45.484094, -122.620329" }, "geometry": { "type": "Point", "coordinates": [ -122.620329082833479, 45.484093859237674 ] } },
{ "type": "Feature", "properties": { "point_type": "destination", "points_str": "45.366796, -122.775971" }, "geometry": { "type": "Point", "coordinates": [ -122.775971444669267, 45.366796437642762 ] } }
]
}
