{
"type": "FeatureCollection",
"name": "origin_destination_points",
"crs": { "type": "name", "properties": { "name": "urn:ogc:def:crs:OGC:1.3:CRS84" } },
"features": [
{ "type": "Feature", "properties": { "point_type": "origin", "points_str": "45.570702, -122.627555" }, "geometry": { "type": "Point", "coordinates": [ -122.62755541079251, 45.570701740622845 ] } },
{ "type": "Feature", "properties": { "point_type": "destination", "points_str": "45.346727, -122.608352" }, "geometry": { "type": "Point", "coordinates": [ -122.608351599047836, 45.346727384801142 ] } }
]
}
