{
"type": "FeatureCollection",
"name": "origin_destination_points",
"crs": { "type": "name", "properties": { "name": "urn:ogc:def:crs:OGC:1.3:CRS84" } },
"features": [
{ "type": "Feature", "properties": { "point_type": "origin", "points_str": "45.565035, -122.678647" }, "geometry": { "type": "Point", "coordinates": [ -122.678646828300984, 45.565034760539568 ] } },
{ "type": "Feature", "properties": { "point_type": "destination", "points_str": "45.577495, -122.764869" }, "geometry": { "type": "Point", "coordinates": [ -122.764869465436846, 45.577495361690524 ] } }
]
}
