{
"type": "FeatureCollection",
"name": "origin_destination_points",
"crs": { "type": "name", "properties": { "name": "urn:ogc:def:crs:OGC:1.3:CRS84" } },
"features": [
{ "type": "Feature", "properties": { "point_type": "origin", "points_str": "45.560392, -122.591169" }, "geometry": { "type": "Point", "coordinates": [ -122.591168845575268, 45.560392281153099 ] } },
{ "type": "Feature", "properties": { "point_type": "destination", "points_str": "45.424414, -122.528557" }, "geometry": { "type": "Point", "coordinates": [ -122.528557308226695, 45.424414040269198 ] } }
]
}
