{
"type": "FeatureCollection",
"name": "origin_destination_points",
"crs": { "type": "name", "properties": { "name": "urn:ogc:def:crs:OGC:1.3:CRS84" } },
"features": [
{ "type": "Feature", "properties": { "point_type": "origin", "points_str": "45.511114, -122.43042" }, "geometry": { "type": "Point", "coordinates": [ -122.430419916295989, 45.511113574505025 ] } },
{ "type": "Feature", "properties": { "point_type": "destination", "points_str": "45.507107, -122.46482" }, "geometry": { "type": "Point", "coordinates": [ -122.464819550914811, 45.507107114032934 ] } }
]
}
