{
"type": "FeatureCollection",
"name": "origin_destination_points",
"crs": { "type": "name", "properties": { "name": "urn:ogc:def:crs:OGC:1.3:CRS84" } },
"features": [
{ "type": "Feature", "properties": { "point_type": "origin", "points_str": "45.500919, -122.595879" }, "geometry": { "type": "Point", "coordinates": [ -122.595878841526414, 45.500919185185616 ] } },
{ "type": "Feature", "properties": { "point_type": "destination", "points_str": "45.593342, -122.763703" }, "geometry": { "type": "Point", "coordinates": [ -122.763703447840754, 45.593342152729136 ] } }
]
}
