{
"type": "FeatureCollection",
"crs": { "type": "name", "properties": { "name": "urn:ogc:def:crs:OGC:1.3:CRS84" } },
"features": [
{ "type": "Feature", "properties": { "point_type": "origin", "points_str": "45.493883, -122.85512" }, "geometry": { "type": "Point", "coordinates": [ -122.855119524815265, 45.49388263447311 ] } },
{ "type": "Feature", "properties": { "point_type": "destination", "points_str": "45.423209, -122.689546" }, "geometry": { "type": "Point", "coordinates": [ -122.68954558926886, 45.423208535582745 ] } }
]
}
