{
"type": "FeatureCollection",
"crs": { "type": "name", "properties": { "name": "urn:ogc:def:crs:OGC:1.3:CRS84" } },
"features": [
{ "type": "Feature", "properties": { "point_type": "origin", "points_str": "45.408339, -122.681849" }, "geometry": { "type": "Point", "coordinates": [ -122.681849168529439, 45.408339481115142 ] } },
{ "type": "Feature", "properties": { "point_type": "destination", "points_str": "45.569035, -122.667679" }, "geometry": { "type": "Point", "coordinates": [ -122.667679008227367, 45.569035378509163 ] } }
]
}
