{
"type": "FeatureCollection",
"name": "origin_destination_points",
"crs": { "type": "name", "properties": { "name": "urn:ogc:def:crs:OGC:1.3:CRS84" } },
"features": [
{ "type": "Feature", "properties": { "point_type": "origin", "points_str": "45.498995, -122.655243" }, "geometry": { "type": "Point", "coordinates": [ -122.655242749116525, 45.49899525152658 ] } },
{ "type": "Feature", "properties": { "point_type": "destination", "points_str": "45.461437, -122.579834" }, "geometry": { "type": "Point", "coordinates": [ -122.57983395254486, 45.461437010815494 ] } }
]
}
