{
"type": "FeatureCollection",
"name": "origin_destination_points",
"crs": { "type": "name", "properties": { "name": "urn:ogc:def:crs:OGC:1.3:CRS84" } },
"features": [
{ "type": "Feature", "properties": { "point_type": "origin", "points_str": "45.555008, -122.654586" }, "geometry": { "type": "Point", "coordinates": [ -122.654586432212696, 45.55500805337681 ] } },
{ "type": "Feature", "properties": { "point_type": "destination", "points_str": "45.496842, -122.575753" }, "geometry": { "type": "Point", "coordinates": [ -122.575753008018438, 45.496842118915602 ] } }
]
}
