{
"type": "FeatureCollection",
"name": "origin_destination_points",
"crs": { "type": "name", "properties": { "name": "urn:ogc:def:crs:OGC:1.3:CRS84" } },
"features": [
{ "type": "Feature", "properties": { "point_type": "origin", "points_str": "45.530734, -122.826644" }, "geometry": { "type": "Point", "coordinates": [ -122.826644305897887, 45.53073389384101 ] } },
{ "type": "Feature", "properties": { "point_type": "destination", "points_str": "45.526147, -122.992007" }, "geometry": { "type": "Point", "coordinates": [ -122.99200730295712, 45.526146805434855 ] } }
]
}
