{
"type": "FeatureCollection",
"crs": { "type": "name", "properties": { "name": "urn:ogc:def:crs:OGC:1.3:CRS84" } },
"features": [
{ "type": "Feature", "properties": { "point_type": "origin", "points_str": "45.540937, -122.604638" }, "geometry": { "type": "Point", "coordinates": [ -122.604638225146473, 45.540936534403144 ] } },
{ "type": "Feature", "properties": { "point_type": "destination", "points_str": "45.475484, -122.679975" }, "geometry": { "type": "Point", "coordinates": [ -122.679974838119648, 45.475484139635405 ] } }
]
}
