{
"type": "FeatureCollection",
"crs": { "type": "name", "properties": { "name": "urn:ogc:def:crs:OGC:1.3:CRS84" } },
"features": [
{ "type": "Feature", "properties": { "point_type": "origin", "points_str": "45.323699, -122.347019" }, "geometry": { "type": "Point", "coordinates": [ -122.347018606506296, 45.323699432526872 ] } },
{ "type": "Feature", "properties": { "point_type": "destination", "points_str": "45.397586, -122.486724" }, "geometry": { "type": "Point", "coordinates": [ -122.486723825067827, 45.397585730090796 ] } }
]
}
