{
"type": "FeatureCollection",
"name": "origin_destination_points",
"crs": { "type": "name", "properties": { "name": "urn:ogc:def:crs:OGC:1.3:CRS84" } },
"features": [
{ "type": "Feature", "properties": { "point_type": "origin", "points_str": "45.507404, -122.410819" }, "geometry": { "type": "Point", "coordinates": [ -122.410818994467547, 45.507404018299518 ] } },
{ "type": "Feature", "properties": { "point_type": "destination", "points_str": "45.516651, -122.750872" }, "geometry": { "type": "Point", "coordinates": [ -122.750872048242286, 45.516650510389617 ] } }
]
}
