{
"type": "FeatureCollection",
"crs": { "type": "name", "properties": { "name": "urn:ogc:def:crs:OGC:1.3:CRS84" } },
"features": [
{ "type": "Feature", "properties": { "point_type": "origin", "points_str": "45.38858, -122.590282" }, "geometry": { "type": "Point", "coordinates": [ -122.590282443396219, 45.388579555231757 ] } },
{ "type": "Feature", "properties": { "point_type": "destination", "points_str": "45.430061, -122.487927" }, "geometry": { "type": "Point", "coordinates": [ -122.487926595497626, 45.430060875444703 ] } }
]
}
