{
"type": "FeatureCollection",
"name": "origin_destination_points",
"crs": { "type": "name", "properties": { "name": "urn:ogc:def:crs:OGC:1.3:CRS84" } },
"features": [
{ "type": "Feature", "properties": { "point_type": "origin", "points_str": "45.514086, -122.794884" }, "geometry": { "type": "Point", "coordinates": [ -122.794884200321917, 45.514086431777969 ] } },
{ "type": "Feature", "properties": { "point_type": "destination", "points_str": "45.532127, -122.456071" }, "geometry": { "type": "Point", "coordinates": [ -122.456070826938486, 45.532127432616868 ] } }
]
}
