{
"type": "FeatureCollection",
"name": "origin_destination_points",
"crs": { "type": "name", "properties": { "name": "urn:ogc:def:crs:OGC:1.3:CRS84" } },
"features": [
{ "type": "Feature", "properties": { "point_type": "origin", "points_str": "45.493206, -122.598167" }, "geometry": { "type": "Point", "coordinates": [ -122.598167054513013, 45.49320565940446 ] } },
{ "type": "Feature", "properties": { "point_type": "destination", "points_str": "45.527337, -122.668097" }, "geometry": { "type": "Point", "coordinates": [ -122.668096669427001, 45.527336985022458 ] } }
]
}
