{
"type": "FeatureCollection",
"name": "origin_destination_points",
"crs": { "type": "name", "properties": { "name": "urn:ogc:def:crs:OGC:1.3:CRS84" } },
"features": [
{ "type": "Feature", "properties": { "point_type": "origin", "points_str": "45.538573, -122.999416" }, "geometry": { "type": "Point", "coordinates": [ -122.999415748011231, 45.538573240328375 ] } },
{ "type": "Feature", "properties": { "point_type": "destination", "points_str": "45.491978, -122.804794" }, "geometry": { "type": "Point", "coordinates": [ -122.804794318796425, 45.491977644364326 ] } }
]
}
