{
"type": "FeatureCollection",
"crs": { "type": "name", "properties": { "name": "urn:ogc:def:crs:OGC:1.3:CRS84" } },
"features": [
{ "type": "Feature", "properties": { "point_type": "origin", "points_str": "45.494018, -122.686983" }, "geometry": { "type": "Point", "coordinates": [ -122.686983270110517, 45.494018399446816 ] } },
{ "type": "Feature", "properties": { "point_type": "destination", "points_str": "45.486792, -122.566071" }, "geometry": { "type": "Point", "coordinates": [ -122.56607116888776, 45.486791610016489 ] } }
]
}
