{
"type": "FeatureCollection",
"crs": { "type": "name", "properties": { "name": "urn:ogc:def:crs:OGC:1.3:CRS84" } },
"features": [
{ "type": "Feature", "properties": { "point_type": "origin", "points_str": "45.535858, -122.585231" }, "geometry": { "type": "Point", "coordinates": [ -122.585230756287885, 45.535858078634668 ] } },
{ "type": "Feature", "properties": { "point_type": "destination", "points_str": "45.566037, -122.720491" }, "geometry": { "type": "Point", "coordinates": [ -122.720491449392696, 45.566037200614524 ] } }
]
}
