{
"type": "FeatureCollection",
"crs": { "type": "name", "properties": { "name": "urn:ogc:def:crs:OGC:1.3:CRS84" } },
"features": [
{ "type": "Feature", "properties": { "point_type": "origin", "points_str": "45.434375, -122.571963" }, "geometry": { "type": "Point", "coordinates": [ -122.571963309961376, 45.434375076775403 ] } },
{ "type": "Feature", "properties": { "point_type": "destination", "points_str": "45.478301, -122.523538" }, "geometry": { "type": "Point", "coordinates": [ -122.523538169772593, 45.478301195912294 ] } }
]
}
