{
"type": "FeatureCollection",
"name": "origin_destination_points",
"crs": { "type": "name", "properties": { "name": "urn:ogc:def:crs:OGC:1.3:CRS84" } },
"features": [
{ "type": "Feature", "properties": { "point_type": "origin", "points_str": "45.373944, -122.599883" }, "geometry": { "type": "Point", "coordinates": [ -122.599883372997368, 45.373944280820055 ] } },
{ "type": "Feature", "properties": { "point_type": "destination", "points_str": "45.409997, -122.591776" }, "geometry": { "type": "Point", "coordinates": [ -122.591776225761834, 45.409997046114832 ] } }
]
}
