{
"type": "FeatureCollection",
"name": "origin_destination_points",
"crs": { "type": "name", "properties": { "name": "urn:ogc:def:crs:OGC:1.3:CRS84" } },
"features": [
{ "type": "Feature", "properties": { "point_type": "origin", "points_str": "45.478436, -122.696323" }, "geometry": { "type": "Point", "coordinates": [ -122.696323472346918, 45.47843594294396 ] } },
{ "type": "Feature", "properties": { "point_type": "destination", "points_str": "45.562825, -122.86743" }, "geometry": { "type": "Point", "coordinates": [ -122.867429664400063, 45.562824928963551 ] } }
]
}
