{
"type": "FeatureCollection",
"name": "origin_destination_points",
"crs": { "type": "name", "properties": { "name": "urn:ogc:def:crs:OGC:1.3:CRS84" } },
"features": [
{ "type": "Feature", "properties": { "point_type": "origin", "points_str": "45.416645, -122.634288" }, "geometry": { "type": "Point", "coordinates": [ -122.634288297698788, 45.416644656558908 ] } },
{ "type": "Feature", "properties": { "point_type": "destination", "points_str": "45.38642, -122.44171" }, "geometry": { "type": "Point", "coordinates": [ -122.441709867173969, 45.386420358752858 ] } }
]
}
