{
"type": "FeatureCollection",
"name": "origin_destination_points",
"crs": { "type": "name", "properties": { "name": "urn:ogc:def:crs:OGC:1.3:CRS84" } },
"features": [
{ "type": "Feature", "properties": { "point_type": "origin", "points_str": "45.462339, -122.618174" }, "geometry": { "type": "Point", "coordinates": [ -122.618174482610968, 45.462338804233326 ] } },
{ "type": "Feature", "properties": { "point_type": "destination", "points_str": "45.510397, -122.647305" }, "geometry": { "type": "Point", "coordinates": [ -122.64730467785364, 45.510397495441261 ] } }
]
}
