{
"type": "FeatureCollection",
"name": "origin_destination_points",
"crs": { "type": "name", "properties": { "name": "urn:ogc:def:crs:OGC:1.3:CRS84" } },
"features": [
{ "type": "Feature", "properties": { "point_type": "origin", "points_str": "45.590099, -122.740888" }, "geometry": { "type": "Point", "coordinates": [ -122.740888215391408, 45.590099137904581 ] } },
{ "type": "Feature", "properties": { "point_type": "destination", "points_str": "45.629897, -122.775561" }, "geometry": { "type": "Point", "coordinates": [ -122.775560840874249, 45.629896832097003 ] } }
]
}
