{
"type": "FeatureCollection",
"crs": { "type": "name", "properties": { "name": "urn:ogc:def:crs:OGC:1.3:CRS84" } },
"features": [
{ "type": "Feature", "properties": { "point_type": "origin", "points_str": "45.528305, -122.432968" }, "geometry": { "type": "Point", "coordinates": [ -122.43296761812158, 45.528305410872683 ] } },
{ "type": "Feature", "properties": { "point_type": "destination", "points_str": "45.422244, -122.67881" }, "geometry": { "type": "Point", "coordinates": [ -122.678810245168151, 45.422243973982816 ] } }
]
}
