{
"type": "FeatureCollection",
"crs": { "type": "name", "properties": { "name": "urn:ogc:def:crs:OGC:1.3:CRS84" } },
"features": [
{ "type": "Feature", "properties": { "point_type": "origin", "points_str": "45.504906, -122.435372" }, "geometry": { "type": "Point", "coordinates": [ -122.435372484035597, 45.504906350224125 ] } },
{ "type": "Feature", "properties": { "point_type": "destination", "points_str": "45.565107, -122.617941" }, "geometry": { "type": "Point", "coordinates": [ -122.617940703730881, 45.565106630672808 ] } }
]
}
