{
"type": "FeatureCollection",
"name": "origin_destination_points",
"crs": { "type": "name", "properties": { "name": "urn:ogc:def:crs:OGC:1.3:CRS84" } },
"features": [
{ "type": "Feature", "properties": { "point_type": "origin", "points_str": "45.532708, -122.467628" }, "geometry": { "type": "Point", "coordinates": [ -122.467628435407576, 45.532708407730794 ] } },
{ "type": "Feature", "properties": { "point_type": "destination", "points_str": "45.370393, -122.628163" }, "geometry": { "type": "Point", "coordinates": [ -122.628163461258538, 45.370393372347138 ] } }
]
}
