{
"type": "FeatureCollection",
"crs": { "type": "name", "properties": { "name": "urn:ogc:def:crs:OGC:1.3:CRS84" } },
"features": [
{ "type": "Feature", "properties": { "point_type": "origin", "points_str": "45.556561, -122.617951" }, "geometry": { "type": "Point", "coordinates": [ -122.617951475711152, 45.556560656584857 ] } },
{ "type": "Feature", "properties": { "point_type": "destination", "points_str": "45.436313, -122.63585" }, "geometry": { "type": "Point", "coordinates": [ -122.635849806161431, 45.436312563242986 ] } }
]
}
