{
"type": "FeatureCollection",
"name": "origin_destination_points",
"crs": { "type": "name", "properties": { "name": "urn:ogc:def:crs:OGC:1.3:CRS84" } },
"features": [
{ "type": "Feature", "properties": { "point_type": "origin", "points_str": "45.419448, -122.663609" }, "geometry": { "type": "Point", "coordinates": [ -122.663608883940441, 45.419448185072063 ] } },
{ "type": "Feature", "properties": { "point_type": "destination", "points_str": "45.568907, -122.647684" }, "geometry": { "type": "Point", "coordinates": [ -122.647684215174962, 45.568907414566858 ] } }
]
}
