{
"type": "FeatureCollection",
"crs": { "type": "name", "properties": { "name": "urn:ogc:def:crs:OGC:1.3:CRS84" } },
"features": [
{ "type": "Feature", "properties": { "point_type": "origin", "points_str": "45.436114, -122.572565" }, "geometry": { "type": "Point", "coordinates": [ -122.572565074388592, 45.436113931085501 ] } },
{ "type": "Feature", "properties": { "point_type": "destination", "points_str": "45.408214, -122.524015" }, "geometry": { "type": "Point", "coordinates": [ -122.524015120497339, 45.408214186845008 ] } }
]
}
