{
"type": "FeatureCollection",
"name": "origin_destination_points",
"crs": { "type": "name", "properties": { "name": "urn:ogc:def:crs:OGC:1.3:CRS84" } },
"features": [
{ "type": "Feature", "properties": { "point_type": "origin", "points_str": "45.363863, -122.613926" }, "geometry": { "type": "Point", "coordinates": [ -122.613925799592593, 45.363863194582059 ] } },
{ "type": "Feature", "properties": { "point_type": "destination", "points_str": "45.429576, -122.667104" }, "geometry": { "type": "Point", "coordinates": [ -122.667104019641855, 45.429576411232077 ] } }
]
}
