{
"type": "FeatureCollection",
"crs": { "type": "name", "properties": { "name": "urn:ogc:def:crs:OGC:1.3:CRS84" } },
"features": [
{ "type": "Feature", "properties": { "point_type": "origin", "points_str": "45.431502, -122.770232" }, "geometry": { "type": "Point", "coordinates": [ -122.770232450582157, 45.431502188255784 ] } },
{ "type": "Feature", "properties": { "point_type": "destination", "points_str": "45.423455, -122.68176" }, "geometry": { "type": "Point", "coordinates": [ -122.681760465235044, 45.423455245757843 ] } }
]
}
