{
"type": "FeatureCollection",
"name": "origin_destination_points",
"crs": { "type": "name", "properties": { "name": "urn:ogc:def:crs:OGC:1.3:CRS84" } },
"features": [
{ "type": "Feature", "properties": { "point_type": "origin", "points_str": "45.503755, -122.496645" }, "geometry": { "type": "Point", "coordinates": [ -122.496644783387794, 45.503755196473151 ] } },
{ "type": "Feature", "properties": { "point_type": "destination", "points_str": "45.565006, -122.691264" }, "geometry": { "type": "Point", "coordinates": [ -122.691263701497903, 45.565005761010838 ] } }
]
}
