{
"type": "FeatureCollection",
"name": "origin_destination_points",
"crs": { "type": "name", "properties": { "name": "urn:ogc:def:crs:OGC:1.3:CRS84" } },
"features": [
{ "type": "Feature", "properties": { "point_type": "origin", "points_str": "45.518042, -122.865645" }, "geometry": { "type": "Point", "coordinates": [ -122.865645396932763, 45.518042374841841 ] } },
{ "type": "Feature", "properties": { "point_type": "destination", "points_str": "45.563946, -122.53103" }, "geometry": { "type": "Point", "coordinates": [ -122.531029951405699, 45.56394581315714 ] } }
]
}
