{
"type": "FeatureCollection",
"name": "origin_destination_points",
"crs": { "type": "name", "properties": { "name": "urn:ogc:def:crs:OGC:1.3:CRS84" } },
"features": [
{ "type": "Feature", "properties": { "point_type": "origin", "points_str": "45.532714, -122.681098" }, "geometry": { "type": "Point", "coordinates": [ -122.681097642375804, 45.532714243880122 ] } },
{ "type": "Feature", "properties": { "point_type": "destination", "points_str": "45.536571, -122.657913" }, "geometry": { "type": "Point", "coordinates": [ -122.657912808901813, 45.536570697797615 ] } }
]
}
