{
"type": "FeatureCollection",
"name": "origin_destination_points",
"crs": { "type": "name", "properties": { "name": "urn:ogc:def:crs:OGC:1.3:CRS84" } },
"features": [
{ "type": "Feature", "properties": { "point_type": "origin", "points_str": "45.515348, -122.681696" }, "geometry": { "type": "Point", "coordinates": [ -122.681695707661248, 45.515347770782171 ] } },
{ "type": "Feature", "properties": { "point_type": "destination", "points_str": "45.534853, -122.913648" }, "geometry": { "type": "Point", "coordinates": [ -122.913648395914976, 45.534853474813893 ] } }
]
}
