{
"type": "FeatureCollection",
"name": "origin_destination_points",
"crs": { "type": "name", "properties": { "name": "urn:ogc:def:crs:OGC:1.3:CRS84" } },
"features": [
{ "type": "Feature", "properties": { "point_type": "origin", "points_str": "45.450207, -122.613071" }, "geometry": { "type": "Point", "coordinates": [ -122.613070784394282, 45.450206590174275 ] } },
{ "type": "Feature", "properties": { "point_type": "destination", "points_str": "45.531404, -122.584498" }, "geometry": { "type": "Point", "coordinates": [ -122.584497875048655, 45.531404387436041 ] } }
]
}
