{
"type": "FeatureCollection",
"name": "origin_destination_points",
"crs": { "type": "name", "properties": { "name": "urn:ogc:def:crs:OGC:1.3:CRS84" } },
"features": [
{ "type": "Feature", "properties": { "point_type": "origin", "points_str": "45.492561, -122.469777" }, "geometry": { "type": "Point", "coordinates": [ -122.469776935411886, 45.492561324139459 ] } },
{ "type": "Feature", "properties": { "point_type": "destination", "points_str": "45.470567, -122.685956" }, "geometry": { "type": "Point", "coordinates": [ -122.685956099966702, 45.470566659597651 ] } }
]
}
