{
"type": "FeatureCollection",
"name": "origin_destination_points",
"crs": { "type": "name", "properties": { "name": "urn:ogc:def:crs:OGC:1.3:CRS84" } },
"features": [
{ "type": "Feature", "properties": { "point_type": "origin", "points_str": "45.450604, -122.675826" }, "geometry": { "type": "Point", "coordinates": [ -122.675826216351822, 45.450603555103747 ] } },
{ "type": "Feature", "properties": { "point_type": "destination", "points_str": "45.488896, -122.783457" }, "geometry": { "type": "Point", "coordinates": [ -122.783456894525912, 45.488895522452268 ] } }
]
}
