{
"type": "FeatureCollection",
"crs": { "type": "name", "properties": { "name": "urn:ogc:def:crs:OGC:1.3:CRS84" } },
"features": [
{ "type": "Feature", "properties": { "point_type": "origin", "points_str": "45.526761, -122.584523" }, "geometry": { "type": "Point", "coordinates": [ -122.584523108903952, 45.526761107816618 ] } },
{ "type": "Feature", "properties": { "point_type": "destination", "points_str": "45.523367, -122.608182" }, "geometry": { "type": "Point", "coordinates": [ -122.608182291570799, 45.523366696143164 ] } }
]
}
