{
"type": "FeatureCollection",
"name": "origin_destination_points",
"crs": { "type": "name", "properties": { "name": "urn:ogc:def:crs:OGC:1.3:CRS84" } },
"features": [
{ "type": "Feature", "properties": { "point_type": "origin", "points_str": "45.555055, -122.575719" }, "geometry": { "type": "Point", "coordinates": [ -122.575719194390317, 45.555055035258896 ] } },
{ "type": "Feature", "properties": { "point_type": "destination", "points_str": "45.534251, -122.610953" }, "geometry": { "type": "Point", "coordinates": [ -122.610953008866431, 45.534250662572674 ] } }
]
}
