{
"type": "FeatureCollection",
"name": "origin_destination_points",
"crs": { "type": "name", "properties": { "name": "urn:ogc:def:crs:OGC:1.3:CRS84" } },
"features": [
{ "type": "Feature", "properties": { "point_type": "origin", "points_str": "45.49124, -122.592617" }, "geometry": { "type": "Point", "coordinates": [ -122.592616529314668, 45.491240499368168 ] } },
{ "type": "Feature", "properties": { "point_type": "destination", "points_str": "45.462066, -122.578259" }, "geometry": { "type": "Point", "coordinates": [ -122.578258913886216, 45.462065640732661 ] } }
]
}
