{
"type": "FeatureCollection",
"crs": { "type": "name", "properties": { "name": "urn:ogc:def:crs:OGC:1.3:CRS84" } },
"features": [
{ "type": "Feature", "properties": { "point_type": "origin", "points_str": "45.488014, -122.595152" }, "geometry": { "type": "Point", "coordinates": [ -122.595151627358902, 45.488013627686549 ] } },
{ "type": "Feature", "properties": { "point_type": "destination", "points_str": "45.431346, -122.482992" }, "geometry": { "type": "Point", "coordinates": [ -122.482992022226895, 45.431345844503241 ] } }
]
}
