{
"type": "FeatureCollection",
"name": "origin_destination_points",
"crs": { "type": "name", "properties": { "name": "urn:ogc:def:crs:OGC:1.3:CRS84" } },
"features": [
{ "type": "Feature", "properties": { "point_type": "origin", "points_str": "45.557854, -122.647459" }, "geometry": { "type": "Point", "coordinates": [ -122.647458830900803, 45.557853923901256 ] } },
{ "type": "Feature", "properties": { "point_type": "destination", "points_str": "45.491482, -122.547525" }, "geometry": { "type": "Point", "coordinates": [ -122.547525104712349, 45.491482223675952 ] } }
]
}
