{
"type": "FeatureCollection",
"name": "origin_destination_points",
"crs": { "type": "name", "properties": { "name": "urn:ogc:def:crs:OGC:1.3:CRS84" } },
"features": [
{ "type": "Feature", "properties": { "point_type": "origin", "points_str": "45.45344, -122.587174" }, "geometry": { "type": "Point", "coordinates": [ -122.587174420111054, 45.453439796376948 ] } },
{ "type": "Feature", "properties": { "point_type": "destination", "points_str": "45.515142, -122.611053" }, "geometry": { "type": "Point", "coordinates": [ -122.611052598970375, 45.515142104026815 ] } }
]
}
