{
"type": "FeatureCollection",
"name": "origin_destination_points",
"crs": { "type": "name", "properties": { "name": "urn:ogc:def:crs:OGC:1.3:CRS84" } },
"features": [
{ "type": "Feature", "properties": { "point_type": "origin", "points_str": "45.488109, -122.680332" }, "geometry": { "type": "Point", "coordinates": [ -122.680331745176801, 45.488108594072912 ] } },
{ "type": "Feature", "properties": { "point_type": "destination", "points_str": "45.514761, -122.652945" }, "geometry": { "type": "Point", "coordinates": [ -122.652944962635701, 45.514760956685087 ] } }
]
}
