{
"type": "FeatureCollection",
"crs": { "type": "name", "properties": { "name": "urn:ogc:def:crs:OGC:1.3:CRS84" } },
"features": [
{ "type": "Feature", "properties": { "point_type": "origin", "points_str": "45.499838, -122.671453" }, "geometry": { "type": "Point", "coordinates": [ -122.671453026658796, 45.49983809933633 ] } },
{ "type": "Feature", "properties": { "point_type": "destination", "points_str": "45.395561, -122.734703" }, "geometry": { "type": "Point", "coordinates": [ -122.73470295865647, 45.395560781361738 ] } }
]
}
