{
"type": "FeatureCollection",
"crs": { "type": "name", "properties": { "name": "urn:ogc:def:crs:OGC:1.3:CRS84" } },
"features": [
{ "type": "Feature", "properties": { "point_type": "origin", "points_str": "45.34771, -122.606748" }, "geometry": { "type": "Point", "coordinates": [ -122.606748036312723, 45.347709861922269 ] } },
{ "type": "Feature", "properties": { "point_type": "destination", "points_str": "45.310242, -122.34304" }, "geometry": { "type": "Point", "coordinates": [ -122.343040117120779, 45.310241924977419 ] } }
]
}
