{
"type": "FeatureCollection",
"name": "origin_destination_points",
"crs": { "type": "name", "properties": { "name": "urn:ogc:def:crs:OGC:1.3:CRS84" } },
"features": [
{ "type": "Feature", "properties": { "point_type": "origin", "points_str": "45.514461, -122.646717" }, "geometry": { "type": "Point", "coordinates": [ -122.646716835898957, 45.514461374420243 ] } },
{ "type": "Feature", "properties": { "point_type": "destination", "points_str": "45.529535, -122.701812" }, "geometry": { "type": "Point", "coordinates": [ -122.701812431689149, 45.529535404005415 ] } }
]
}
