{
"type": "FeatureCollection",
"name": "origin_destination_points",
"crs": { "type": "name", "properties": { "name": "urn:ogc:def:crs:OGC:1.3:CRS84" } },
"features": [
{ "type": "Feature", "properties": { "point_type": "origin", "points_str": "45.430745, -122.712082" }, "geometry": { "type": "Point", "coordinates": [ -122.71208231097053, 45.430744577775805 ] } },
{ "type": "Feature", "properties": { "point_type": "destination", "points_str": "45.408148, -122.661176" }, "geometry": { "type": "Point", "coordinates": [ -122.661175918520883, 45.408148324331862 ] } }
]
}
