{
"type": "FeatureCollection",
"crs": { "type": "name", "properties": { "name": "urn:ogc:def:crs:OGC:1.3:CRS84" } },
"features": [
{ "type": "Feature", "properties": { "point_type": "origin", "points_str": "45.464484, -122.803571" }, "geometry": { "type": "Point", "coordinates": [ -122.80357057593865, 45.464484476469423 ] } },
{ "type": "Feature", "properties": { "point_type": "destination", "points_str": "45.472409, -122.874305" }, "geometry": { "type": "Point", "coordinates": [ -122.874305261692825, 45.472409121382412 ] } }
]
}
