{
"type": "FeatureCollection",
"crs": { "type": "name", "properties": { "name": "urn:ogc:def:crs:OGC:1.3:CRS84" } },
"features": [
{ "type": "Feature", "properties": { "point_type": "origin", "points_str": "45.520059, -123.032751" }, "geometry": { "type": "Point", "coordinates": [ -123.032751279228677, 45.520059407010685 ] } },
{ "type": "Feature", "properties": { "point_type": "destination", "points_str": "45.510169, -122.968682" }, "geometry": { "type": "Point", "coordinates": [ -122.968682099646358, 45.510168995784163 ] } }
]
}
