{
"type": "FeatureCollection",
"crs": { "type": "name", "properties": { "name": "urn:ogc:def:crs:OGC:1.3:CRS84" } },
"features": [
{ "type": "Feature", "properties": { "point_type": "origin", "points_str": "45.478777, -122.697524" }, "geometry": { "type": "Point", "coordinates": [ -122.697523541550069, 45.478776860244757 ] } },
{ "type": "Feature", "properties": { "point_type": "destination", "points_str": "45.355622, -122.844345" }, "geometry": { "type": "Point", "coordinates": [ -122.844345222578596, 45.355622302540056 ] } }
]
}
