{
"type": "FeatureCollection",
"crs": { "type": "name", "properties": { "name": "urn:ogc:def:crs:OGC:1.3:CRS84" } },
"features": [
{ "type": "Feature", "properties": { "point_type": "origin", "points_str": "45.511493, -122.669965" }, "geometry": { "type": "Point", "coordinates": [ -122.66996476196519, 45.511493068300744 ] } },
{ "type": "Feature", "properties": { "point_type": "destination", "points_str": "45.555622, -122.671439" }, "geometry": { "type": "Point", "coordinates": [ -122.671439183385175, 45.555621685988392 ] } }
]
}
