{
"type": "FeatureCollection",
"name": "origin_destination_points",
"crs": { "type": "name", "properties": { "name": "urn:ogc:def:crs:OGC:1.3:CRS84" } },
"features": [
{ "type": "Feature", "properties": { "point_type": "origin", "points_str": "45.495782, -122.551657" }, "geometry": { "type": "Point", "coordinates": [ -122.551656791157342, 45.49578234598517 ] } },
{ "type": "Feature", "properties": { "point_type": "destination", "points_str": "45.477384, -122.60735" }, "geometry": { "type": "Point", "coordinates": [ -122.607350273041263, 45.47738394691558 ] } }
]
}
