{
"type": "FeatureCollection",
"crs": { "type": "name", "properties": { "name": "urn:ogc:def:crs:OGC:1.3:CRS84" } },
"features": [
{ "type": "Feature", "properties": { "point_type": "origin", "points_str": "45.417149, -122.714472" }, "geometry": { "type": "Point", "coordinates": [ -122.714472346849973, 45.417148702881576 ] } },
{ "type": "Feature", "properties": { "point_type": "destination", "points_str": "45.379188, -122.767081" }, "geometry": { "type": "Point", "coordinates": [ -122.767080972263969, 45.379188405612645 ] } }
]
}
