{
"type": "FeatureCollection",
"name": "origin_destination_points",
"crs": { "type": "name", "properties": { "name": "urn:ogc:def:crs:OGC:1.3:CRS84" } },
"features": [
{ "type": "Feature", "properties": { "point_type": "origin", "points_str": "45.354035, -122.592844" }, "geometry": { "type": "Point", "coordinates": [ -122.59284403689459, 45.354034761205398 ] } },
{ "type": "Feature", "properties": { "point_type": "destination", "points_str": "45.397089, -122.598777" }, "geometry": { "type": "Point", "coordinates": [ -122.59877692799482, 45.397089284054964 ] } }
]
}
