{
"type": "FeatureCollection",
"name": "origin_destination_points",
"crs": { "type": "name", "properties": { "name": "urn:ogc:def:crs:OGC:1.3:CRS84" } },
"features": [
{ "type": "Feature", "properties": { "point_type": "origin", "points_str": "45.520687, -122.690611" }, "geometry": { "type": "Point", "coordinates": [ -122.690610876680608, 45.520686736325906 ] } },
{ "type": "Feature", "properties": { "point_type": "destination", "points_str": "45.53172, -122.876156" }, "geometry": { "type": "Point", "coordinates": [ -122.876155947912494, 45.531720377999747 ] } }
]
}
