{
"type": "FeatureCollection",
"name": "origin_destination_points",
"crs": { "type": "name", "properties": { "name": "urn:ogc:def:crs:OGC:1.3:CRS84" } },
"features": [
{ "type": "Feature", "properties": { "point_type": "origin", "points_str": "45.506211, -122.591343" }, "geometry": { "type": "Point", "coordinates": [ -122.591342787795554, 45.506210766499997 ] } },
{ "type": "Feature", "properties": { "point_type": "destination", "points_str": "45.504511, -122.67954" }, "geometry": { "type": "Point", "coordinates": [ -122.6795401790027, 45.50451142578342 ] } }
]
}
