{
"type": "FeatureCollection",
"crs": { "type": "name", "properties": { "name": "urn:ogc:def:crs:OGC:1.3:CRS84" } },
"features": [
{ "type": "Feature", "properties": { "point_type": "origin", "points_str": "45.535319, -122.384952" }, "geometry": { "type": "Point", "coordinates": [ -122.384952335719518, 45.535318929347376 ] } },
{ "type": "Feature", "properties": { "point_type": "destination", "points_str": "45.545639, -122.592499" }, "geometry": { "type": "Point", "coordinates": [ -122.592499195562681, 45.545638882889577 ] } }
]
}
