{
"type": "FeatureCollection",
"name": "origin_destination_points",
"crs": { "type": "name", "properties": { "name": "urn:ogc:def:crs:OGC:1.3:CRS84" } },
"features": [
{ "type": "Feature", "properties": { "point_type": "origin", "points_str": "45.535115, -122.630895" }, "geometry": { "type": "Point", "coordinates": [ -122.630894842056051, 45.535115073403055 ] } },
{ "type": "Feature", "properties": { "point_type": "destination", "points_str": "45.570254, -122.661504" }, "geometry": { "type": "Point", "coordinates": [ -122.661504103470236, 45.570253655393991 ] } }
]
}
