{
"type": "FeatureCollection",
"name": "origin_destination_points",
"crs": { "type": "name", "properties": { "name": "urn:ogc:def:crs:OGC:1.3:CRS84" } },
"features": [
{ "type": "Feature", "properties": { "point_type": "origin", "points_str": "45.568704, -122.5302" }, "geometry": { "type": "Point", "coordinates": [ -122.530199955239794, 45.568703742491664 ] } },
{ "type": "Feature", "properties": { "point_type": "destination", "points_str": "45.545322, -122.527267" }, "geometry": { "type": "Point", "coordinates": [ -122.527267296489896, 45.545322479255631 ] } }
]
}
