{
"type": "FeatureCollection",
"name": "origin_destination_points",
"crs": { "type": "name", "properties": { "name": "urn:ogc:def:crs:OGC:1.3:CRS84" } },
"features": [
{ "type": "Feature", "properties": { "point_type": "origin", "points_str": "45.499177, -122.419037" }, "geometry": { "type": "Point", "coordinates": [ -122.419037388803829, 45.49917706195221 ] } },
{ "type": "Feature", "properties": { "point_type": "destination", "points_str": "45.531182, -122.386894" }, "geometry": { "type": "Point", "coordinates": [ -122.386893781873525, 45.531181874944721 ] } }
]
}
