{
"type": "FeatureCollection",
"crs": { "type": "name", "properties": { "name": "urn:ogc:def:crs:OGC:1.3:CRS84" } },
"features": [
{ "type": "Feature", "properties": { "point_type": "origin", "points_str": "45.590911, -122.725791" }, "geometry": { "type": "Point", "coordinates": [ -122.725791237390879, 45.590911380139872 ] } },
{ "type": "Feature", "properties": { "point_type": "destination", "points_str": "45.564806, -122.603854" }, "geometry": { "type": "Point", "coordinates": [ -122.603853551175291, 45.564806477405718 ] } }
]
}
