{
"type": "FeatureCollection",
"name": "origin_destination_points",
"crs": { "type": "name", "properties": { "name": "urn:ogc:def:crs:OGC:1.3:CRS84" } },
"features": [
{ "type": "Feature", "properties": { "point_type": "origin", "points_str": "45.568445, -122.533381" }, "geometry": { "type": "Point", "coordinates": [ -122.533380935207845, 45.568444512771066 ] } },
{ "type": "Feature", "properties": { "point_type": "destination", "points_str": "45.534979, -122.561567" }, "geometry": { "type": "Point", "coordinates": [ -122.561566505711497, 45.534979316607938 ] } }
]
}
