{
"type": "FeatureCollection",
"name": "origin_destination_points",
"crs": { "type": "name", "properties": { "name": "urn:ogc:def:crs:OGC:1.3:CRS84" } },
"features": [
{ "type": "Feature", "properties": { "point_type": "origin", "points_str": "45.409246, -122.631502" }, "geometry": { "type": "Point", "coordinates": [ -122.631502052923736, 45.409246368502345 ] } },
{ "type": "Feature", "properties": { "point_type": "destination", "points_str": "45.393947, -122.574421" }, "geometry": { "type": "Point", "coordinates": [ -122.574421498730601, 45.393947440428171 ] } }
]
}
