{
"type": "FeatureCollection",
"name": "origin_destination_points",
"crs": { "type": "name", "properties": { "name": "urn:ogc:def:crs:OGC:1.3:CRS84" } },
"features": [
{ "type": "Feature", "properties": { "point_type": "origin", "points_str": "45.384836, -122.754977" }, "geometry": { "type": "Point", "coordinates": [ -122.754976553228261, 45.384836268603074 ] } },
{ "type": "Feature", "properties": { "point_type": "destination", "points_str": "45.521772, -123.098136" }, "geometry": { "type": "Point", "coordinates": [ -123.098136132058173, 45.521771876892004 ] } }
]
}
