{
"type": "FeatureCollection",
"name": "origin_destination_points",
"crs": { "type": "name", "properties": { "name": "urn:ogc:def:crs:OGC:1.3:CRS84" } },
"features": [
{ "type": "Feature", "properties": { "point_type": "origin", "points_str": "45.5267, -122.471885" }, "geometry": { "type": "Point", "coordinates": [ -122.471884756859993, 45.526699657222586 ] } },
{ "type": "Feature", "properties": { "point_type": "destination", "points_str": "45.522024, -122.539106" }, "geometry": { "type": "Point", "coordinates": [ -122.539106026901379, 45.522024430868527 ] } }
]
}
