{
"type": "FeatureCollection",
"crs": { "type": "name", "properties": { "name": "urn:ogc:def:crs:OGC:1.3:CRS84" } },
"features": [
{ "type": "Feature", "properties": { "point_type": "origin", "points_str": "45.569062, -122.656111" }, "geometry": { "type": "Point", "coordinates": [ -122.656111349583867, 45.56906162675309 ] } },
{ "type": "Feature", "properties": { "point_type": "destination", "points_str": "45.476242, -122.623996" }, "geometry": { "type": "Point", "coordinates": [ -122.623996128455531, 45.476242254417144 ] } }
]
}
