{
"type": "FeatureCollection",
"crs": { "type": "name", "properties": { "name": "urn:ogc:def:crs:OGC:1.3:CRS84" } },
"features": [
{ "type": "Feature", "properties": { "point_type": "origin", "points_str": "45.572256, -122.631656" }, "geometry": { "type": "Point", "coordinates": [ -122.631656414738444, 45.57225598498583 ] } },
{ "type": "Feature", "properties": { "point_type": "destination", "points_str": "45.498378, -122.591906" }, "geometry": { "type": "Point", "coordinates": [ -122.591905988345928, 45.498377528838503 ] } }
]
}
