{
"type": "FeatureCollection",
"name": "origin_destination_points",
"crs": { "type": "name", "properties": { "name": "urn:ogc:def:crs:OGC:1.3:CRS84" } },
"features": [
{ "type": "Feature", "properties": { "point_type": "origin", "points_str": "45.569055, -122.703598" }, "geometry": { "type": "Point", "coordinates": [ -122.703597894219897, 45.569054680292815 ] } },
{ "type": "Feature", "properties": { "point_type": "destination", "points_str": "45.533726, -122.458508" }, "geometry": { "type": "Point", "coordinates": [ -122.458508179907454, 45.533726003570884 ] } }
]
}
