{
"type": "FeatureCollection",
"name": "origin_destination_points",
"crs": { "type": "name", "properties": { "name": "urn:ogc:def:crs:OGC:1.3:CRS84" } },
"features": [
{ "type": "Feature", "properties": { "point_type": "origin", "points_str": "45.519416, -122.486214" }, "geometry": { "type": "Point", "coordinates": [ -122.486214057371029, 45.519416421860768 ] } },
{ "type": "Feature", "properties": { "point_type": "destination", "points_str": "45.476792, -122.531304" }, "geometry": { "type": "Point", "coordinates": [ -122.53130406598514, 45.476792287122926 ] } }
]
}
