{
"type": "FeatureCollection",
"name": "origin_destination_points",
"crs": { "type": "name", "properties": { "name": "urn:ogc:def:crs:OGC:1.3:CRS84" } },
"features": [
{ "type": "Feature", "properties": { "point_type": "origin", "points_str": "45.374333, -122.737426" }, "geometry": { "type": "Point", "coordinates": [ -122.737426401704894, 45.374332782719193 ] } },
{ "type": "Feature", "properties": { "point_type": "destination", "points_str": "45.497329, -122.931179" }, "geometry": { "type": "Point", "coordinates": [ -122.931179099655907, 45.497328680409325 ] } }
]
}
