{
"type": "FeatureCollection",
"name": "origin_destination_points",
"crs": { "type": "name", "properties": { "name": "urn:ogc:def:crs:OGC:1.3:CRS84" } },
"features": [
{ "type": "Feature", "properties": { "point_type": "origin", "points_str": "45.445164, -122.644748" }, "geometry": { "type": "Point", "coordinates": [ -122.644748258766754, 45.445164175330838 ] } },
{ "type": "Feature", "properties": { "point_type": "destination", "points_str": "45.342871, -122.597579" }, "geometry": { "type": "Point", "coordinates": [ -122.597579007330523, 45.342871442545203 ] } }
]
}
