{
"type": "FeatureCollection",
"name": "origin_destination_points",
"crs": { "type": "name", "properties": { "name": "urn:ogc:def:crs:OGC:1.3:CRS84" } },
"features": [
{ "type": "Feature", "properties": { "point_type": "origin", "points_str": "45.575788, -122.668349" }, "geometry": { "type": "Point", "coordinates": [ -122.668348620409745, 45.575788128794954 ] } },
{ "type": "Feature", "properties": { "point_type": "destination", "points_str": "45.5846, -122.685072" }, "geometry": { "type": "Point", "coordinates": [ -122.685072359476621, 45.584599554646068 ] } }
]
}
