{
"type": "FeatureCollection",
"crs": { "type": "name", "properties": { "name": "urn:ogc:def:crs:OGC:1.3:CRS84" } },
"features": [
{ "type": "Feature", "properties": { "point_type": "origin", "points_str": "45.478605, -122.374254" }, "geometry": { "type": "Point", "coordinates": [ -122.374253524881112, 45.478605142176711 ] } },
{ "type": "Feature", "properties": { "point_type": "destination", "points_str": "45.534233, -122.427375" }, "geometry": { "type": "Point", "coordinates": [ -122.427374886144349, 45.534232746413679 ] } }
]
}
