{
"type": "FeatureCollection",
"name": "origin_destination_points",
"crs": { "type": "name", "properties": { "name": "urn:ogc:def:crs:OGC:1.3:CRS84" } },
"features": [
{ "type": "Feature", "properties": { "point_type": "origin", "points_str": "45.521669, -123.049021" }, "geometry": { "type": "Point", "coordinates": [ -123.049021193320726, 45.521669362618574 ] } },
{ "type": "Feature", "properties": { "point_type": "destination", "points_str": "45.522865, -122.973773" }, "geometry": { "type": "Point", "coordinates": [ -122.973772873097744, 45.522865294313505 ] } }
]
}
