{
"type": "FeatureCollection",
"name": "origin_destination_points",
"crs": { "type": "name", "properties": { "name": "urn:ogc:def:crs:OGC:1.3:CRS84" } },
"features": [
{ "type": "Feature", "properties": { "point_type": "origin", "points_str": "45.4903, -122.492513" }, "geometry": { "type": "Point", "coordinates": [ -122.492513249705752, 45.490300267193575 ] } },
{ "type": "Feature", "properties": { "point_type": "destination", "points_str": "45.48841, -122.802091" }, "geometry": { "type": "Point", "coordinates": [ -122.802091423838164, 45.48841011272588 ] } }
]
}
