{
"type": "FeatureCollection",
"crs": { "type": "name", "properties": { "name": "urn:ogc:def:crs:OGC:1.3:CRS84" } },
"features": [
{ "type": "Feature", "properties": { "point_type": "origin", "points_str": "45.532029, -122.466107" }, "geometry": { "type": "Point", "coordinates": [ -122.466107163936186, 45.532028516384251 ] } },
{ "type": "Feature", "properties": { "point_type": "destination", "points_str": "45.520881, -122.649443" }, "geometry": { "type": "Point", "coordinates": [ -122.649442510323468, 45.520880904080954 ] } }
]
}
