{
"type": "FeatureCollection",
"crs": { "type": "name", "properties": { "name": "urn:ogc:def:crs:OGC:1.3:CRS84" } },
"features": [
{ "type": "Feature", "properties": { "point_type": "origin", "points_str": "45.513878, -122.579889" }, "geometry": { "type": "Point", "coordinates": [ -122.579888604343282, 45.51387785818423 ] } },
{ "type": "Feature", "properties": { "point_type": "destination", "points_str": "45.52955, -122.586551" }, "geometry": { "type": "Point", "coordinates": [ -122.586550528232806, 45.529550020056256 ] } }
]
}
