{
"type": "FeatureCollection",
"name": "origin_destination_points",
"crs": { "type": "name", "properties": { "name": "urn:ogc:def:crs:OGC:1.3:CRS84" } },
"features": [
{ "type": "Feature", "properties": { "point_type": "origin", "points_str": "45.482933, -122.618431" }, "geometry": { "type": "Point", "coordinates": [ -122.618431095334955, 45.482932610692963 ] } },
{ "type": "Feature", "properties": { "point_type": "destination", "points_str": "45.551692, -122.623832" }, "geometry": { "type": "Point", "coordinates": [ -122.623832059174617, 45.551692124731112 ] } }
]
}
