{
"type": "FeatureCollection",
"name": "origin_destination_points",
"crs": { "type": "name", "properties": { "name": "urn:ogc:def:crs:OGC:1.3:CRS84" } },
"features": [
{ "type": "Feature", "properties": { "point_type": "origin", "points_str": "45.48813, -122.621706" }, "geometry": { "type": "Point", "coordinates": [ -122.621706385419827, 45.488129634292925 ] } },
{ "type": "Feature", "properties": { "point_type": "destination", "points_str": "45.455145, -122.68906" }, "geometry": { "type": "Point", "coordinates": [ -122.689060255492436, 45.45514454672454 ] } }
]
}
