{
"type": "FeatureCollection",
"name": "origin_destination_points",
"crs": { "type": "name", "properties": { "name": "urn:ogc:def:crs:OGC:1.3:CRS84" } },
"features": [
{ "type": "Feature", "properties": { "point_type": "origin", "points_str": "45.580778, -122.66578" }, "geometry": { "type": "Point", "coordinates": [ -122.665779682370385, 45.580778147375653 ] } },
{ "type": "Feature", "properties": { "point_type": "destination", "points_str": "45.384391, -122.641595" }, "geometry": { "type": "Point", "coordinates": [ -122.641595342350627, 45.384391384245099 ] } }
]
}
