{
"type": "FeatureCollection",
"name": "origin_destination_points",
"crs": { "type": "name", "properties": { "name": "urn:ogc:def:crs:OGC:1.3:CRS84" } },
"features": [
{ "type": "Feature", "properties": { "point_type": "origin", "points_str": "45.50078, -122.644471" }, "geometry": { "type": "Point", "coordinates": [ -122.644470733293005, 45.500779913586584 ] } },
{ "type": "Feature", "properties": { "point_type": "destination", "points_str": "45.523289, -122.638419" }, "geometry": { "type": "Point", "coordinates": [ -122.63841915435674, 45.523289326723464 ] } }
]
}
