{
"type": "FeatureCollection",
"name": "origin_destination_points",
"crs": { "type": "name", "properties": { "name": "urn:ogc:def:crs:OGC:1.3:CRS84" } },
"features": [
{ "type": "Feature", "properties": { "point_type": "origin", "points_str": "45.501641, -122.836192" }, "geometry": { "type": "Point", "coordinates": [ -122.836191540177794, 45.501641426806941 ] } },
{ "type": "Feature", "properties": { "point_type": "destination", "points_str": "45.51974, -122.738809" }, "geometry": { "type": "Point", "coordinates": [ -122.738808883990174, 45.519739564095566 ] } }
]
}
