{
"type": "FeatureCollection",
"name": "origin_destination_points",
"crs": { "type": "name", "properties": { "name": "urn:ogc:def:crs:OGC:1.3:CRS84" } },
"features": [
{ "type": "Feature", "properties": { "point_type": "origin", "points_str": "45.522398, -122.968851" }, "geometry": { "type": "Point", "coordinates": [ -122.96885118142626, 45.522398105150906 ] } },
{ "type": "Feature", "properties": { "point_type": "destination", "points_str": "45.556463, -122.579424" }, "geometry": { "type": "Point", "coordinates": [ -122.5794243244965, 45.55646300298951 ] } }
]
}
