{
"type": "FeatureCollection",
"crs": { "type": "name", "properties": { "name": "urn:ogc:def:crs:OGC:1.3:CRS84" } },
"features": [
{ "type": "Feature", "properties": { "point_type": "origin", "points_str": "45.508718, -122.820644" }, "geometry": { "type": "Point", "coordinates": [ -122.820644037732194, 45.508717709153231 ] } },
{ "type": "Feature", "properties": { "point_type": "destination", "points_str": "45.549693, -122.986321" }, "geometry": { "type": "Point", "coordinates": [ -122.986321297107608, 45.549693407636205 ] } }
]
}
