{
"type": "FeatureCollection",
"name": "origin_destination_points",
"crs": { "type": "name", "properties": { "name": "urn:ogc:def:crs:OGC:1.3:CRS84" } },
"features": [
{ "type": "Feature", "properties": { "point_type": "origin", "points_str": "45.523726, -122.575721" }, "geometry": { "type": "Point", "coordinates": [ -122.575721249208499, 45.523725871847503 ] } },
{ "type": "Feature", "properties": { "point_type": "destination", "points_str": "45.446222, -122.653451" }, "geometry": { "type": "Point", "coordinates": [ -122.653450567262141, 45.446222420728212 ] } }
]
}
