{
"type": "FeatureCollection",
"name": "origin_destination_points",
"crs": { "type": "name", "properties": { "name": "urn:ogc:def:crs:OGC:1.3:CRS84" } },
"features": [
{ "type": "Feature", "properties": { "point_type": "origin", "points_str": "45.493311, -122.669676" }, "geometry": { "type": "Point", "coordinates": [ -122.669676444151932, 45.493310535632773 ] } },
{ "type": "Feature", "properties": { "point_type": "destination", "points_str": "45.503702, -122.458556" }, "geometry": { "type": "Point", "coordinates": [ -122.458556089159586, 45.503701797127952 ] } }
]
}
