{
"type": "FeatureCollection",
"name": "origin_destination_points",
"crs": { "type": "name", "properties": { "name": "urn:ogc:def:crs:OGC:1.3:CRS84" } },
"features": [
{ "type": "Feature", "properties": { "point_type": "origin", "points_str": "45.377495, -122.600681" }, "geometry": { "type": "Point", "coordinates": [ -122.60068138563598, 45.377494500240225 ] } },
{ "type": "Feature", "properties": { "point_type": "destination", "points_str": "45.354274, -122.595819" }, "geometry": { "type": "Point", "coordinates": [ -122.595818575676461, 45.354273815348883 ] } }
]
}
