{
"type": "FeatureCollection",
"crs": { "type": "name", "properties": { "name": "urn:ogc:def:crs:OGC:1.3:CRS84" } },
"features": [
{ "type": "Feature", "properties": { "point_type": "origin", "points_str": "45.514708, -122.607447" }, "geometry": { "type": "Point", "coordinates": [ -122.607446520954667, 45.514708053437346 ] } },
{ "type": "Feature", "properties": { "point_type": "destination", "points_str": "45.458616, -122.635237" }, "geometry": { "type": "Point", "coordinates": [ -122.635236868738659, 45.458616479170765 ] } }
]
}
