{
"type": "FeatureCollection",
"crs": { "type": "name", "properties": { "name": "urn:ogc:def:crs:OGC:1.3:CRS84" } },
"features": [
{ "type": "Feature", "properties": { "point_type": "origin", "points_str": "45.456385, -122.586236" }, "geometry": { "type": "Point", "coordinates": [ -122.586235964202771, 45.456385497926952 ] } },
{ "type": "Feature", "properties": { "point_type": "destination", "points_str": "45.517438, -122.737049" }, "geometry": { "type": "Point", "coordinates": [ -122.737049200142138, 45.517437651867269 ] } }
]
}
