{
"type": "FeatureCollection",
"crs": { "type": "name", "properties": { "name": "urn:ogc:def:crs:OGC:1.3:CRS84" } },
"features": [
{ "type": "Feature", "properties": { "point_type": "origin", "points_str": "45.411561, -122.668961" }, "geometry": { "type": "Point", "coordinates": [ -122.668961322952114, 45.411561187841194 ] } },
{ "type": "Feature", "properties": { "point_type": "destination", "points_str": "45.520213, -122.558358" }, "geometry": { "type": "Point", "coordinates": [ -122.558357658849872, 45.520212986602793 ] } }
]
}
