{
"type": "FeatureCollection",
"name": "origin_destination_points",
"crs": { "type": "name", "properties": { "name": "urn:ogc:def:crs:OGC:1.3:CRS84" } },
"features": [
{ "type": "Feature", "properties": { "point_type": "origin", "points_str": "45.520843, -122.642885" }, "geometry": { "type": "Point", "coordinates": [ -122.64288480330741, 45.520842871371194 ] } },
{ "type": "Feature", "properties": { "point_type": "destination", "points_str": "45.521163, -123.060954" }, "geometry": { "type": "Point", "coordinates": [ -123.060954175471366, 45.521162922510563 ] } }
]
}
