{
"type": "FeatureCollection",
"crs": { "type": "name", "properties": { "name": "urn:ogc:def:crs:OGC:1.3:CRS84" } },
"features": [
{ "type": "Feature", "properties": { "point_type": "origin", "points_str": "45.545682, -122.588871" }, "geometry": { "type": "Point", "coordinates": [ -122.588870513299582, 45.545682049816818 ] } },
{ "type": "Feature", "properties": { "point_type": "destination", "points_str": "45.504207, -122.650317" }, "geometry": { "type": "Point", "coordinates": [ -122.65031684833076, 45.504206836922357 ] } }
]
}
