{
"type": "FeatureCollection",
"name": "origin_destination_points",
"crs": { "type": "name", "properties": { "name": "urn:ogc:def:crs:OGC:1.3:CRS84" } },
"features": [
{ "type": "Feature", "properties": { "point_type": "origin", "points_str": "45.500246, -122.624108" }, "geometry": { "type": "Point", "coordinates": [ -122.624108089993229, 45.500246141504675 ] } },
{ "type": "Feature", "properties": { "point_type": "destination", "points_str": "45.507161, -122.604386" }, "geometry": { "type": "Point", "coordinates": [ -122.604386197932712, 45.507160986589653 ] } }
]
}
