{
"type": "FeatureCollection",
"name": "origin_destination_points",
"crs": { "type": "name", "properties": { "name": "urn:ogc:def:crs:OGC:1.3:CRS84" } },
"features": [
{ "type": "Feature", "properties": { "point_type": "origin", "points_str": "45.51847, -122.452115" }, "geometry": { "type": "Point", "coordinates": [ -122.452115434234656, 45.518470057238261 ] } },
{ "type": "Feature", "properties": { "point_type": "destination", "points_str": "45.448008, -122.579787" }, "geometry": { "type": "Point", "coordinates": [ -122.579786800684872, 45.448007948970364 ] } }
]
}
