{
"type": "FeatureCollection",
"name": "origin_destination_points",
"crs": { "type": "name", "properties": { "name": "urn:ogc:def:crs:OGC:1.3:CRS84" } },
"features": [
{ "type": "Feature", "properties": { "point_type": "origin", "points_str": "45.59179, -122.761969" }, "geometry": { "type": "Point", "coordinates": [ -122.761968733699689, 45.591789939347031 ] } },
{ "type": "Feature", "properties": { "point_type": "destination", "points_str": "45.565706, -122.681786" }, "geometry": { "type": "Point", "coordinates": [ -122.681785697653382, 45.565705855253299 ] } }
]
}
