{
"type": "FeatureCollection",
"name": "origin_destination_points",
"crs": { "type": "name", "properties": { "name": "urn:ogc:def:crs:OGC:1.3:CRS84" } },
"features": [
{ "type": "Feature", "properties": { "point_type": "origin", "points_str": "45.516388, -122.793928" }, "geometry": { "type": "Point", "coordinates": [ -122.793927965377861, 45.516387842814467 ] } },
{ "type": "Feature", "properties": { "point_type": "destination", "points_str": "45.519069, -122.607245" }, "geometry": { "type": "Point", "coordinates": [ -122.607245462845285, 45.519069165994139 ] } }
]
}
