{
"type": "FeatureCollection",
"name": "origin_destination_points",
"crs": { "type": "name", "properties": { "name": "urn:ogc:def:crs:OGC:1.3:CRS84" } },
"features": [
{ "type": "Feature", "properties": { "point_type": "origin", "points_str": "45.520394, -122.47036" }, "geometry": { "type": "Point", "coordinates": [ -122.470360165778416, 45.520394163710783 ] } },
{ "type": "Feature", "properties": { "point_type": "destination", "points_str": "45.517539, -122.401262" }, "geometry": { "type": "Point", "coordinates": [ -122.401262109656869, 45.51753875682941 ] } }
]
}
