{
"type": "FeatureCollection",
"name": "origin_destination_points",
"crs": { "type": "name", "properties": { "name": "urn:ogc:def:crs:OGC:1.3:CRS84" } },
"features": [
{ "type": "Feature", "properties": { "point_type": "origin", "points_str": "45.512925, -122.671742" }, "geometry": { "type": "Point", "coordinates": [ -122.671742259246955, 45.512924764340916 ] } },
{ "type": "Feature", "properties": { "point_type": "destination", "points_str": "45.436499, -122.712719" }, "geometry": { "type": "Point", "coordinates": [ -122.712719070679569, 45.436498677409958 ] } }
]
}
