{
"type": "FeatureCollection",
"crs": { "type": "name", "properties": { "name": "urn:ogc:def:crs:OGC:1.3:CRS84" } },
"features": [
{ "type": "Feature", "properties": { "point_type": "origin", "points_str": "45.532645, -122.662862" }, "geometry": { "type": "Point", "coordinates": [ -122.662862010539669, 45.532644515419882 ] } },
{ "type": "Feature", "properties": { "point_type": "destination", "points_str": "45.48484, -122.743309" }, "geometry": { "type": "Point", "coordinates": [ -122.743308869425618, 45.484839652083267 ] } }
]
}
