{
"type": "FeatureCollection",
"name": "origin_destination_points",
"crs": { "type": "name", "properties": { "name": "urn:ogc:def:crs:OGC:1.3:CRS84" } },
"features": [
{ "type": "Feature", "properties": { "point_type": "origin", "points_str": "45.52866, -122.656782" }, "geometry": { "type": "Point", "coordinates": [ -122.656781747022933, 45.528659963095421 ] } },
{ "type": "Feature", "properties": { "point_type": "destination", "points_str": "45.518221, -123.062539" }, "geometry": { "type": "Point", "coordinates": [ -123.062538582246475, 45.51822148666561 ] } }
]
}
