{
"type": "FeatureCollection",
"name": "origin_destination_points",
"crs": { "type": "name", "properties": { "name": "urn:ogc:def:crs:OGC:1.3:CRS84" } },
"features": [
{ "type": "Feature", "properties": { "point_type": "origin", "points_str": "45.505087, -122.527645" }, "geometry": { "type": "Point", "coordinates": [ -122.527644548882222, 45.505086651526462 ] } },
{ "type": "Feature", "properties": { "point_type": "destination", "points_str": "45.457473, -122.68791" }, "geometry": { "type": "Point", "coordinates": [ -122.687909508485973, 45.457473238828157 ] } }
]
}
