{
"type": "FeatureCollection",
"name": "origin_destination_points",
"crs": { "type": "name", "properties": { "name": "urn:ogc:def:crs:OGC:1.3:CRS84" } },
"features": [
{ "type": "Feature", "properties": { "point_type": "origin", "points_str": "45.563629, -122.856766" }, "geometry": { "type": "Point", "coordinates": [ -122.856766337901419, 45.563628847709928 ] } },
{ "type": "Feature", "properties": { "point_type": "destination", "points_str": "45.521332, -122.839146" }, "geometry": { "type": "Point", "coordinates": [ -122.839145718022223, 45.521331607169031 ] } }
]
}
