{
"type": "FeatureCollection",
"crs": { "type": "name", "properties": { "name": "urn:ogc:def:crs:OGC:1.3:CRS84" } },
"features": [
{ "type": "Feature", "properties": { "point_type": "origin", "points_str": "45.487721, -122.595623" }, "geometry": { "type": "Point", "coordinates": [ -122.595623445055509, 45.487721324023305 ] } },
{ "type": "Feature", "properties": { "point_type": "destination", "points_str": "45.47915, -122.739164" }, "geometry": { "type": "Point", "coordinates": [ -122.739164402146713, 45.479150160211297 ] } }
]
}
