{
"type": "FeatureCollection",
"name": "origin_destination_points",
"crs": { "type": "name", "properties": { "name": "urn:ogc:def:crs:OGC:1.3:CRS84" } },
"features": [
{ "type": "Feature", "properties": { "point_type": "origin", "points_str": "45.525142, -122.60783" }, "geometry": { "type": "Point", "coordinates": [ -122.607830189267887, 45.525142138338126 ] } },
{ "type": "Feature", "properties": { "point_type": "destination", "points_str": "45.525123, -122.525793" }, "geometry": { "type": "Point", "coordinates": [ -122.525793208045343, 45.525123257612684 ] } }
]
}
