{
"type": "FeatureCollection",
"name": "origin_destination_points",
"crs": { "type": "name", "properties": { "name": "urn:ogc:def:crs:OGC:1.3:CRS84" } },
"features": [
{ "type": "Feature", "properties": { "point_type": "origin", "points_str": "45.471323, -122.706586" }, "geometry": { "type": "Point", "coordinates": [ -122.706585876797007, 45.471322658839291 ] } },
{ "type": "Feature", "properties": { "point_type": "destination", "points_str": "45.564252, -122.679672" }, "geometry": { "type": "Point", "coordinates": [ -122.679671842655623, 45.56425228134961 ] } }
]
}
