{
"type": "FeatureCollection",
"name": "origin_destination_points",
"crs": { "type": "name", "properties": { "name": "urn:ogc:def:crs:OGC:1.3:CRS84" } },
"features": [
{ "type": "Feature", "properties": { "point_type": "origin", "points_str": "45.474872, -122.703377" }, "geometry": { "type": "Point", "coordinates": [ -122.703376524520024, 45.474872298318417 ] } },
{ "type": "Feature", "properties": { "point_type": "destination", "points_str": "45.571369, -122.724875" }, "geometry": { "type": "Point", "coordinates": [ -122.724874765342818, 45.57136895276949 ] } }
]
}
