{
"type": "FeatureCollection",
"name": "origin_destination_points",
"crs": { "type": "name", "properties": { "name": "urn:ogc:def:crs:OGC:1.3:CRS84" } },
"features": [
{ "type": "Feature", "properties": { "point_type": "origin", "points_str": "45.503427, -122.627277" }, "geometry": { "type": "Point", "coordinates": [ -122.627277290847076, 45.503427032288812 ] } },
{ "type": "Feature", "properties": { "point_type": "destination", "points_str": "45.524617, -122.681802" }, "geometry": { "type": "Point", "coordinates": [ -122.681801700018326, 45.524617008056573 ] } }
]
}
