{
"type": "FeatureCollection",
"name": "origin_destination_points",
"crs": { "type": "name", "properties": { "name": "urn:ogc:def:crs:OGC:1.3:CRS84" } },
"features": [
{ "type": "Feature", "properties": { "point_type": "origin", "points_str": "45.438833, -122.581304" }, "geometry": { "type": "Point", "coordinates": [ -122.581303785236855, 45.438833005737102 ] } },
{ "type": "Feature", "properties": { "point_type": "destination", "points_str": "45.427996, -122.508219" }, "geometry": { "type": "Point", "coordinates": [ -122.50821919017676, 45.427995985298956 ] } }
]
}
