{
"type": "FeatureCollection",
"crs": { "type": "name", "properties": { "name": "urn:ogc:def:crs:OGC:1.3:CRS84" } },
"features": [
{ "type": "Feature", "properties": { "point_type": "origin", "points_str": "45.418149, -122.587109" }, "geometry": { "type": "Point", "coordinates": [ -122.58710876843007, 45.418148976357088 ] } },
{ "type": "Feature", "properties": { "point_type": "destination", "points_str": "45.33179, -122.593842" }, "geometry": { "type": "Point", "coordinates": [ -122.593842415735992, 45.331790277497085 ] } }
]
}
