{
"type": "FeatureCollection",
"name": "origin_destination_points",
"crs": { "type": "name", "properties": { "name": "urn:ogc:def:crs:OGC:1.3:CRS84" } },
"features": [
{ "type": "Feature", "properties": { "point_type": "origin", "points_str": "45.522916, -122.538706" }, "geometry": { "type": "Point", "coordinates": [ -122.538705886867575, 45.522915985454254 ] } },
{ "type": "Feature", "properties": { "point_type": "destination", "points_str": "45.310596, -122.776048" }, "geometry": { "type": "Point", "coordinates": [ -122.776048080821525, 45.310596418936861 ] } }
]
}
