{
"type": "FeatureCollection",
"crs": { "type": "name", "properties": { "name": "urn:ogc:def:crs:OGC:1.3:CRS84" } },
"features": [
{ "type": "Feature", "properties": { "point_type": "origin", "points_str": "45.531252, -122.587" }, "geometry": { "type": "Point", "coordinates": [ -122.586999610378868, 45.531252305351174 ] } },
{ "type": "Feature", "properties": { "point_type": "destination", "points_str": "45.563471, -122.646874" }, "geometry": { "type": "Point", "coordinates": [ -122.646873965706575, 45.563471424346808 ] } }
]
}
