{
"type": "FeatureCollection",
"crs": { "type": "name", "properties": { "name": "urn:ogc:def:crs:OGC:1.3:CRS84" } },
"features": [
{ "type": "Feature", "properties": { "point_type": "origin", "points_str": "45.476437, -122.705287" }, "geometry": { "type": "Point", "coordinates": [ -122.705286567176529, 45.476436772922796 ] } },
{ "type": "Feature", "properties": { "point_type": "destination", "points_str": "45.498208, -122.672397" }, "geometry": { "type": "Point", "coordinates": [ -122.672396969933601, 45.498207668551814 ] } }
]
}
