{
"type": "FeatureCollection",
"crs": { "type": "name", "properties": { "name": "urn:ogc:def:crs:OGC:1.3:CRS84" } },
"features": [
{ "type": "Feature", "properties": { "point_type": "origin", "points_str": "45.555155, -122.573247" }, "geometry": { "type": "Point", "coordinates": [ -122.5732466986898, 45.555155339910499 ] } },
{ "type": "Feature", "properties": { "point_type": "destination", "points_str": "45.526735, -122.55052" }, "geometry": { "type": "Point", "coordinates": [ -122.550519508717898, 45.526734907506309 ] } }
]
}
