{
"type": "FeatureCollection",
"name": "origin_destination_points",
"crs": { "type": "name", "properties": { "name": "urn:ogc:def:crs:OGC:1.3:CRS84" } },
"features": [
{ "type": "Feature", "properties": { "point_type": "origin", "points_str": "45.523941, -122.80733" }, "geometry": { "type": "Point", "coordinates": [ -122.807329723746122, 45.523940649437897 ] } },
{ "type": "Feature", "properties": { "point_type": "destination", "points_str": "45.514663, -122.832881" }, "geometry": { "type": "Point", "coordinates": [ -122.832881078513836, 45.514663017803663 ] } }
]
}
