{
"type": "FeatureCollection",
"name": "origin_destination_points",
"crs": { "type": "name", "properties": { "name": "urn:ogc:def:crs:OGC:1.3:CRS84" } },
"features": [
{ "type": "Feature", "properties": { "point_type": "origin", "points_str": "45.504402, -122.962023" }, "geometry": { "type": "Point", "coordinates": [ -122.962023031266227, 45.504401612501489 ] } },
{ "type": "Feature", "properties": { "point_type": "destination", "points_str": "45.484686, -122.852292" }, "geometry": { "type": "Point", "coordinates": [ -122.852292284093707, 45.484685513705251 ] } }
]
}
