{
"type": "FeatureCollection",
"crs": { "type": "name", "properties": { "name": "urn:ogc:def:crs:OGC:1.3:CRS84" } },
"features": [
{ "type": "Feature", "properties": { "point_type": "origin", "points_str": "45.334748, -122.589785" }, "geometry": { "type": "Point", "coordinates": [ -122.589785138149864, 45.334747542851254 ] } },
{ "type": "Feature", "properties": { "point_type": "destination", "points_str": "45.40802, -122.523134" }, "geometry": { "type": "Point", "coordinates": [ -122.523133694148257, 45.408019501441238 ] } }
]
}
