{
"type": "FeatureCollection",
"name": "origin_destination_points",
"crs": { "type": "name", "properties": { "name": "urn:ogc:def:crs:OGC:1.3:CRS84" } },
"features": [
{ "type": "Feature", "properties": { "point_type": "origin", "points_str": "45.490317, -122.806221" }, "geometry": { "type": "Point", "coordinates": [ -122.806221036149481, 45.490317257858123 ] } },
{ "type": "Feature", "properties": { "point_type": "destination", "points_str": "45.519423, -122.465216" }, "geometry": { "type": "Point", "coordinates": [ -122.465216455028326, 45.519422683237799 ] } }
]
}
