{
"type": "FeatureCollection",
"name": "origin_destination_points",
"crs": { "type": "name", "properties": { "name": "urn:ogc:def:crs:OGC:1.3:CRS84" } },
"features": [
{ "type": "Feature", "properties": { "point_type": "origin", "points_str": "45.49627, -122.536373" }, "geometry": { "type": "Point", "coordinates": [ -122.53637265272917, 45.496270088412196 ] } },
{ "type": "Feature", "properties": { "point_type": "destination", "points_str": "45.550883, -122.555725" }, "geometry": { "type": "Point", "coordinates": [ -122.555725376108029, 45.550883419983222 ] } }
]
}
