{
"type": "FeatureCollection",
"name": "origin_destination_points",
"crs": { "type": "name", "properties": { "name": "urn:ogc:def:crs:OGC:1.3:CRS84" } },
"features": [
{ "type": "Feature", "properties": { "point_type": "origin", "points_str": "45.52254, -122.61183" }, "geometry": { "type": "Point", "coordinates": [ -122.611830371967798, 45.522539852975044 ] } },
{ "type": "Feature", "properties": { "point_type": "destination", "points_str": "45.509173, -122.793248" }, "geometry": { "type": "Point", "coordinates": [ -122.793248050487861, 45.509172506214497 ] } }
]
}
