{
"type": "FeatureCollection",
"name": "origin_destination_points",
"crs": { "type": "name", "properties": { "name": "urn:ogc:def:crs:OGC:1.3:CRS84" } },
"features": [
{ "type": "Feature", "properties": { "point_type": "origin", "points_str": "45.539511, -122.881237" }, "geometry": { "type": "Point", "coordinates": [ -122.881236944581929, 45.539510742720189 ] } },
{ "type": "Feature", "properties": { "point_type": "destination", "points_str": "45.522225, -122.706256" }, "geometry": { "type": "Point", "coordinates": [ -122.706255899377666, 45.52222460174778 ] } }
]
}
