{
"type": "FeatureCollection",
"name": "origin_destination_points",
"crs": { "type": "name", "properties": { "name": "urn:ogc:def:crs:OGC:1.3:CRS84" } },
"features": [
{ "type": "Feature", "properties": { "point_type": "origin", "points_str": "45.446464, -122.744145" }, "geometry": { "type": "Point", "coordinates": [ -122.744145176719158, 45.44646396035656 ] } },
{ "type": "Feature", "properties": { "point_type": "destination", "points_str": "45.515132, -122.754646" }, "geometry": { "type": "Point", "coordinates": [ -122.754646467127344, 45.515132022495173 ] } }
]
}
