{
"type": "FeatureCollection",
"name": "origin_destination_points",
"crs": { "type": "name", "properties": { "name": "urn:ogc:def:crs:OGC:1.3:CRS84" } },
"features": [
{ "type": "Feature", "properties": { "point_type": "origin", "points_str": "45.532037, -122.454427" }, "geometry": { "type": "Point", "coordinates": [ -122.454427240624526, 45.532037107287252 ] } },
{ "type": "Feature", "properties": { "point_type": "destination", "points_str": "45.544901, -122.387123" }, "geometry": { "type": "Point", "coordinates": [ -122.387123282537544, 45.544901435145334 ] } }
]
}
