{
"type": "FeatureCollection",
"name": "origin_destination_points",
"crs": { "type": "name", "properties": { "name": "urn:ogc:def:crs:OGC:1.3:CRS84" } },
"features": [
{ "type": "Feature", "properties": { "point_type": "origin", "points_str": "45.527486, -122.484801" }, "geometry": { "type": "Point", "coordinates": [ -122.4848010440205, 45.527485886551275 ] } },
{ "type": "Feature", "properties": { "point_type": "destination", "points_str": "45.494594, -122.801997" }, "geometry": { "type": "Point", "coordinates": [ -122.801996563233288, 45.494593992698391 ] } }
]
}
