{
"type": "FeatureCollection",
"crs": { "type": "name", "properties": { "name": "urn:ogc:def:crs:OGC:1.3:CRS84" } },
"features": [
{ "type": "Feature", "properties": { "point_type": "origin", "points_str": "45.500761, -122.414833" }, "geometry": { "type": "Point", "coordinates": [ -122.414833348657282, 45.500761226947574 ] } },
{ "type": "Feature", "properties": { "point_type": "destination", "points_str": "45.548734, -122.701055" }, "geometry": { "type": "Point", "coordinates": [ -122.701055173154359, 45.548734253164284 ] } }
]
}
