{
"type": "FeatureCollection",
"name": "origin_destination_points",
"crs": { "type": "name", "properties": { "name": "urn:ogc:def:crs:OGC:1.3:CRS84" } },
"features": [
{ "type": "Feature", "properties": { "point_type": "origin", "points_str": "45.58298, -122.703346" }, "geometry": { "type": "Point", "coordinates": [ -122.703346217673754, 45.582980198571065 ] } },
{ "type": "Feature", "properties": { "point_type": "destination", "points_str": "45.354476, -122.605895" }, "geometry": { "type": "Point", "coordinates": [ -122.605895362379201, 45.354476481308055 ] } }
]
}
