{
"type": "FeatureCollection",
"name": "origin_destination_points",
"crs": { "type": "name", "properties": { "name": "urn:ogc:def:crs:OGC:1.3:CRS84" } },
"features": [
{ "type": "Feature", "properties": { "point_type": "origin", "points_str": "45.537953, -122.44215" }, "geometry": { "type": "Point", "coordinates": [ -122.442149583316194, 45.537953233299284 ] } },
{ "type": "Feature", "properties": { "point_type": "destination", "points_str": "45.52171, -122.887887" }, "geometry": { "type": "Point", "coordinates": [ -122.887886632193258, 45.521710238783086 ] } }
]
}
