{
"type": "FeatureCollection",
"name": "origin_destination_points",
"crs": { "type": "name", "properties": { "name": "urn:ogc:def:crs:OGC:1.3:CRS84" } },
"features": [
{ "type": "Feature", "properties": { "point_type": "origin", "points_str": "45.483286, -122.756802" }, "geometry": { "type": "Point", "coordinates": [ -122.756801969979989, 45.483285722989329 ] } },
{ "type": "Feature", "properties": { "point_type": "destination", "points_str": "45.496079, -122.5157" }, "geometry": { "type": "Point", "coordinates": [ -122.515699815274914, 45.496079005946896 ] } }
]
}
