{
"type": "FeatureCollection",
"name": "origin_destination_points",
"crs": { "type": "name", "properties": { "name": "urn:ogc:def:crs:OGC:1.3:CRS84" } },
"features": [
{ "type": "Feature", "properties": { "point_type": "origin", "points_str": "45.534206, -122.917484" }, "geometry": { "type": "Point", "coordinates": [ -122.91748353639916, 45.53420617437866 ] } },
{ "type": "Feature", "properties": { "point_type": "destination", "points_str": "45.537682, -122.861563" }, "geometry": { "type": "Point", "coordinates": [ -122.861563316591997, 45.537682118547757 ] } }
]
}
