{
"type": "FeatureCollection",
"name": "origin_destination_points",
"crs": { "type": "name", "properties": { "name": "urn:ogc:def:crs:OGC:1.3:CRS84" } },
"features": [
{ "type": "Feature", "properties": { "point_type": "origin", "points_str": "45.472269, -122.679911" }, "geometry": { "type": "Point", "coordinates": [ -122.679910727276024, 45.472269434740753 ] } },
{ "type": "Feature", "properties": { "point_type": "destination", "points_str": "45.521949, -122.643204" }, "geometry": { "type": "Point", "coordinates": [ -122.643203778694797, 45.521949373705908 ] } }
]
}
