{
"type": "FeatureCollection",
"crs": { "type": "name", "properties": { "name": "urn:ogc:def:crs:OGC:1.3:CRS84" } },
"features": [
{ "type": "Feature", "properties": { "point_type": "origin", "points_str": "45.461995, -122.590038" }, "geometry": { "type": "Point", "coordinates": [ -122.590037725779098, 45.461995474386725 ] } },
{ "type": "Feature", "properties": { "point_type": "destination", "points_str": "45.517175, -122.731145" }, "geometry": { "type": "Point", "coordinates": [ -122.731145240414008, 45.517175335959735 ] } }
]
}
