{
"type": "FeatureCollection",
"name": "origin_destination_points",
"crs": { "type": "name", "properties": { "name": "urn:ogc:def:crs:OGC:1.3:CRS84" } },
"features": [
{ "type": "Feature", "properties": { "point_type": "origin", "points_str": "45.520621, -122.736052" }, "geometry": { "type": "Point", "coordinates": [ -122.736051697331305, 45.520620574959977 ] } },
{ "type": "Feature", "properties": { "point_type": "destination", "points_str": "45.520017, -122.626858" }, "geometry": { "type": "Point", "coordinates": [ -122.626858014064723, 45.520017087447705 ] } }
]
}
