{
"type": "FeatureCollection",
"crs": { "type": "name", "properties": { "name": "urn:ogc:def:crs:OGC:1.3:CRS84" } },
"features": [
{ "type": "Feature", "properties": { "point_type": "origin", "points_str": "45.486358, -122.619485" }, "geometry": { "type": "Point", "coordinates": [ -122.619484731293156, 45.48635786236261 ] } },
{ "type": "Feature", "properties": { "point_type": "destination", "points_str": "45.488756, -122.592427" }, "geometry": { "type": "Point", "coordinates": [ -122.592426941498715, 45.488756140295251 ] } }
]
}
