{
"type": "FeatureCollection",
"crs": { "type": "name", "properties": { "name": "urn:ogc:def:crs:OGC:1.3:CRS84" } },
"features": [
{ "type": "Feature", "properties": { "point_type": "origin", "points_str": "45.504915, -122.556702" }, "geometry": { "type": "Point", "coordinates": [ -122.556702031584535, 45.504914697083066 ] } },
{ "type": "Feature", "properties": { "point_type": "destination", "points_str": "45.402952, -122.566264" }, "geometry": { "type": "Point", "coordinates": [ -122.566264000953069, 45.402952348012057 ] } }
]
}
