{
"type": "FeatureCollection",
"name": "origin_destination_points",
"crs": { "type": "name", "properties": { "name": "urn:ogc:def:crs:OGC:1.3:CRS84" } },
"features": [
{ "type": "Feature", "properties": { "point_type": "origin", "points_str": "45.503531, -122.648026" }, "geometry": { "type": "Point", "coordinates": [ -122.648025928953231, 45.503530725535533 ] } },
{ "type": "Feature", "properties": { "point_type": "destination", "points_str": "45.483384, -122.729478" }, "geometry": { "type": "Point", "coordinates": [ -122.729478273447569, 45.483384166329721 ] } }
]
}
