{
"type": "FeatureCollection",
"name": "origin_destination_points",
"crs": { "type": "name", "properties": { "name": "urn:ogc:def:crs:OGC:1.3:CRS84" } },
"features": [
{ "type": "Feature", "properties": { "point_type": "origin", "points_str": "45.497948, -122.889733" }, "geometry": { "type": "Point", "coordinates": [ -122.889732971267208, 45.497947675913622 ] } },
{ "type": "Feature", "properties": { "point_type": "destination", "points_str": "45.430887, -122.748924" }, "geometry": { "type": "Point", "coordinates": [ -122.748923662551633, 45.430887455160459 ] } }
]
}
