{
"type": "FeatureCollection",
"name": "origin_destination_points",
"crs": { "type": "name", "properties": { "name": "urn:ogc:def:crs:OGC:1.3:CRS84" } },
"features": [
{ "type": "Feature", "properties": { "point_type": "origin", "points_str": "45.380718, -122.635638" }, "geometry": { "type": "Point", "coordinates": [ -122.635637743749129, 45.380718308463997 ] } },
{ "type": "Feature", "properties": { "point_type": "destination", "points_str": "45.36741, -122.581637" }, "geometry": { "type": "Point", "coordinates": [ -122.581637210108383, 45.367410292497027 ] } }
]
}
