{
"type": "FeatureCollection",
"name": "origin_destination_points",
"crs": { "type": "name", "properties": { "name": "urn:ogc:def:crs:OGC:1.3:CRS84" } },
"features": [
{ "type": "Feature", "properties": { "point_type": "origin", "points_str": "45.497073, -122.88828" }, "geometry": { "type": "Point", "coordinates": [ -122.888280286155052, 45.497073239661702 ] } },
{ "type": "Feature", "properties": { "point_type": "destination", "points_str": "45.548531, -122.997129" }, "geometry": { "type": "Point", "coordinates": [ -122.997129376589186, 45.548531282076468 ] } }
]
}
