{
"type": "FeatureCollection",
"name": "origin_destination_points",
"crs": { "type": "name", "properties": { "name": "urn:ogc:def:crs:OGC:1.3:CRS84" } },
"features": [
{ "type": "Feature", "properties": { "point_type": "origin", "points_str": "45.547777, -122.585199" }, "geometry": { "type": "Point", "coordinates": [ -122.585198597517532, 45.547776725048664 ] } },
{ "type": "Feature", "properties": { "point_type": "destination", "points_str": "45.515575, -122.735518" }, "geometry": { "type": "Point", "coordinates": [ -122.735518008975944, 45.515574740969356 ] } }
]
}
