{
"type": "FeatureCollection",
"crs": { "type": "name", "properties": { "name": "urn:ogc:def:crs:OGC:1.3:CRS84" } },
"features": [
{ "type": "Feature", "properties": { "point_type": "origin", "points_str": "45.314608, -122.337512" }, "geometry": { "type": "Point", "coordinates": [ -122.337511897945802, 45.314608405997973 ] } },
{ "type": "Feature", "properties": { "point_type": "destination", "points_str": "45.43241, -122.55164" }, "geometry": { "type": "Point", "coordinates": [ -122.55163997306002, 45.432410303956964 ] } }
]
}
