{
"type": "FeatureCollection",
"name": "origin_destination_points",
"crs": { "type": "name", "properties": { "name": "urn:ogc:def:crs:OGC:1.3:CRS84" } },
"features": [
{ "type": "Feature", "properties": { "point_type": "origin", "points_str": "45.377306, -122.753873" }, "geometry": { "type": "Point", "coordinates": [ -122.753873058030493, 45.377306239207165 ] } },
{ "type": "Feature", "properties": { "point_type": "destination", "points_str": "45.52053, -123.038364" }, "geometry": { "type": "Point", "coordinates": [ -123.03836355105372, 45.520530269810656 ] } }
]
}
