{
"type": "FeatureCollection",
"name": "origin_destination_points",
"crs": { "type": "name", "properties": { "name": "urn:ogc:def:crs:OGC:1.3:CRS84" } },
"features": [
{ "type": "Feature", "properties": { "point_type": "origin", "points_str": "45.496905, -122.54197" }, "geometry": { "type": "Point", "coordinates": [ -122.541970326064757, 45.496904866662952 ] } },
{ "type": "Feature", "properties": { "point_type": "destination", "points_str": "45.468292, -122.722413" }, "geometry": { "type": "Point", "coordinates": [ -122.722412970204871, 45.468291542303575 ] } }
]
}
