{
"type": "FeatureCollection",
"name": "origin_destination_points",
"crs": { "type": "name", "properties": { "name": "urn:ogc:def:crs:OGC:1.3:CRS84" } },
"features": [
{ "type": "Feature", "properties": { "point_type": "origin", "points_str": "45.371132, -122.594996" }, "geometry": { "type": "Point", "coordinates": [ -122.594996456587936, 45.371132059439596 ] } },
{ "type": "Feature", "properties": { "point_type": "destination", "points_str": "45.39886, -122.585999" }, "geometry": { "type": "Point", "coordinates": [ -122.585999042170002, 45.39886048896954 ] } }
]
}
