{
"type": "FeatureCollection",
"crs": { "type": "name", "properties": { "name": "urn:ogc:def:crs:OGC:1.3:CRS84" } },
"features": [
{ "type": "Feature", "properties": { "point_type": "origin", "points_str": "45.449898, -122.621413" }, "geometry": { "type": "Point", "coordinates": [ -122.6214126481009, 45.449897813701554 ] } },
{ "type": "Feature", "properties": { "point_type": "destination", "points_str": "45.49096, -122.64953" }, "geometry": { "type": "Point", "coordinates": [ -122.649529770356352, 45.490960498023121 ] } }
]
}
