{
"type": "FeatureCollection",
"crs": { "type": "name", "properties": { "name": "urn:ogc:def:crs:OGC:1.3:CRS84" } },
"features": [
{ "type": "Feature", "properties": { "point_type": "origin", "points_str": "45.469259, -122.59303" }, "geometry": { "type": "Point", "coordinates": [ -122.593029993939112, 45.469258526054645 ] } },
{ "type": "Feature", "properties": { "point_type": "destination", "points_str": "45.532941, -122.559565" }, "geometry": { "type": "Point", "coordinates": [ -122.559564738988698, 45.532941238332334 ] } }
]
}
