{
"type": "FeatureCollection",
"name": "origin_destination_points",
"crs": { "type": "name", "properties": { "name": "urn:ogc:def:crs:OGC:1.3:CRS84" } },
"features": [
{ "type": "Feature", "properties": { "point_type": "origin", "points_str": "45.488803, -122.821576" }, "geometry": { "type": "Point", "coordinates": [ -122.821575595432876, 45.4888025958725 ] } },
{ "type": "Feature", "properties": { "point_type": "destination", "points_str": "45.541222, -122.952034" }, "geometry": { "type": "Point", "coordinates": [ -122.952034394359359, 45.541221889700694 ] } }
]
}
