{
"type": "FeatureCollection",
"name": "origin_destination_points",
"crs": { "type": "name", "properties": { "name": "urn:ogc:def:crs:OGC:1.3:CRS84" } },
"features": [
{ "type": "Feature", "properties": { "point_type": "origin", "points_str": "45.594963, -122.735557" }, "geometry": { "type": "Point", "coordinates": [ -122.73555659132154, 45.594963274045753 ] } },
{ "type": "Feature", "properties": { "point_type": "destination", "points_str": "45.513293, -122.582042" }, "geometry": { "type": "Point", "coordinates": [ -122.582041612197713, 45.51329348776764 ] } }
]
}
