{
"type": "FeatureCollection",
"name": "origin_destination_points",
"crs": { "type": "name", "properties": { "name": "urn:ogc:def:crs:OGC:1.3:CRS84" } },
"features": [
{ "type": "Feature", "properties": { "point_type": "origin", "points_str": "45.573282, -122.615791" }, "geometry": { "type": "Point", "coordinates": [ -122.615791476579005, 45.573281789230116 ] } },
{ "type": "Feature", "properties": { "point_type": "destination", "points_str": "45.479583, -122.615153" }, "geometry": { "type": "Point", "coordinates": [ -122.615153492821932, 45.479583069057291 ] } }
]
}
