{
"type": "FeatureCollection",
"name": "origin_destination_points",
"crs": { "type": "name", "properties": { "name": "urn:ogc:def:crs:OGC:1.3:CRS84" } },
"features": [
{ "type": "Feature", "properties": { "point_type": "origin", "points_str": "45.535163, -122.626352" }, "geometry": { "type": "Point", "coordinates": [ -122.626352252815195, 45.535163063016611 ] } },
{ "type": "Feature", "properties": { "point_type": "destination", "points_str": "45.50353, -122.417853" }, "geometry": { "type": "Point", "coordinates": [ -122.417852935116045, 45.503530284552554 ] } }
]
}
