{
"type": "FeatureCollection",
"name": "origin_destination_points",
"crs": { "type": "name", "properties": { "name": "urn:ogc:def:crs:OGC:1.3:CRS84" } },
"features": [
{ "type": "Feature", "properties": { "point_type": "origin", "points_str": "45.516758, -122.674084" }, "geometry": { "type": "Point", "coordinates": [ -122.674084416259234, 45.516758130556163 ] } },
{ "type": "Feature", "properties": { "point_type": "destination", "points_str": "45.484737, -122.683546" }, "geometry": { "type": "Point", "coordinates": [ -122.683545710224834, 45.484736723756356 ] } }
]
}
