{
"type": "FeatureCollection",
"crs": { "type": "name", "properties": { "name": "urn:ogc:def:crs:OGC:1.3:CRS84" } },
"features": [
{ "type": "Feature", "properties": { "point_type": "origin", "points_str": "45.509322, -122.579916" }, "geometry": { "type": "Point", "coordinates": [ -122.579915591100345, 45.509322379198153 ] } },
{ "type": "Feature", "properties": { "point_type": "destination", "points_str": "45.475937, -122.577741" }, "geometry": { "type": "Point", "coordinates": [ -122.577741293955597, 45.475937378616223 ] } }
]
}
