{
"type": "FeatureCollection",
"name": "origin_destination_points",
"crs": { "type": "name", "properties": { "name": "urn:ogc:def:crs:OGC:1.3:CRS84" } },
"features": [
{ "type": "Feature", "properties": { "point_type": "origin", "points_str": "45.502304, -122.448031" }, "geometry": { "type": "Point", "coordinates": [ -122.448031109877491, 45.50230377716624 ] } },
{ "type": "Feature", "properties": { "point_type": "destination", "points_str": "45.513317, -122.66277" }, "geometry": { "type": "Point", "coordinates": [ -122.662769866998559, 45.513317412130114 ] } }
]
}
