{
"type": "FeatureCollection",
"crs": { "type": "name", "properties": { "name": "urn:ogc:def:crs:OGC:1.3:CRS84" } },
"features": [
{ "type": "Feature", "properties": { "point_type": "origin", "points_str": "45.582637, -122.754038" }, "geometry": { "type": "Point", "coordinates": [ -122.754038398619869, 45.582636991250709 ] } },
{ "type": "Feature", "properties": { "point_type": "destination", "points_str": "45.512894, -122.656701" }, "geometry": { "type": "Point", "coordinates": [ -122.656700674366562, 45.512894059110337 ] } }
]
}
