{
"type": "FeatureCollection",
"name": "origin_destination_points",
"crs": { "type": "name", "properties": { "name": "urn:ogc:def:crs:OGC:1.3:CRS84" } },
"features": [
{ "type": "Feature", "properties": { "point_type": "origin", "points_str": "45.527057, -122.661335" }, "geometry": { "type": "Point", "coordinates": [ -122.66133498844674, 45.52705701203805 ] } },
{ "type": "Feature", "properties": { "point_type": "destination", "points_str": "45.513475, -122.64267" }, "geometry": { "type": "Point", "coordinates": [ -122.642669900246517, 45.513475242181244 ] } }
]
}
