{
"type": "FeatureCollection",
"crs": { "type": "name", "properties": { "name": "urn:ogc:def:crs:OGC:1.3:CRS84" } },
"features": [
{ "type": "Feature", "properties": { "point_type": "origin", "points_str": "45.396387, -122.613135" }, "geometry": { "type": "Point", "coordinates": [ -122.613135031093748, 45.396387322548861 ] } },
{ "type": "Feature", "properties": { "point_type": "destination", "points_str": "45.430842, -122.542105" }, "geometry": { "type": "Point", "coordinates": [ -122.542105010093493, 45.43084178731646 ] } }
]
}
