{
"type": "FeatureCollection",
"name": "origin_destination_points",
"crs": { "type": "name", "properties": { "name": "urn:ogc:def:crs:OGC:1.3:CRS84" } },
"features": [
{ "type": "Feature", "properties": { "point_type": "origin", "points_str": "45.402241, -122.586999" }, "geometry": { "type": "Point", "coordinates": [ -122.586999066203376, 45.402240863701479 ] } },
{ "type": "Feature", "properties": { "point_type": "destination", "points_str": "45.459638, -122.577568" }, "geometry": { "type": "Point", "coordinates": [ -122.577567905320905, 45.459637954908075 ] } }
]
}
