{
"type": "FeatureCollection",
"crs": { "type": "name", "properties": { "name": "urn:ogc:def:crs:OGC:1.3:CRS84" } },
"features": [
{ "type": "Feature", "properties": { "point_type": "origin", "points_str": "45.510598, -122.772282" }, "geometry": { "type": "Point", "coordinates": [ -122.772281616879994, 45.51059791691997 ] } },
{ "type": "Feature", "properties": { "point_type": "destination", "points_str": "45.553801, -122.680854" }, "geometry": { "type": "Point", "coordinates": [ -122.680854321892866, 45.553801111175154 ] } }
]
}
