{
"type": "FeatureCollection",
"name": "origin_destination_points",
"crs": { "type": "name", "properties": { "name": "urn:ogc:def:crs:OGC:1.3:CRS84" } },
"features": [
{ "type": "Feature", "properties": { "point_type": "origin", "points_str": "45.589588, -122.777791" }, "geometry": { "type": "Point", "coordinates": [ -122.777791364618238, 45.589587602810042 ] } },
{ "type": "Feature", "properties": { "point_type": "destination", "points_str": "45.444676, -122.724092" }, "geometry": { "type": "Point", "coordinates": [ -122.724092350221554, 45.444676091986452 ] } }
]
}
