{
"type": "FeatureCollection",
"crs": { "type": "name", "properties": { "name": "urn:ogc:def:crs:OGC:1.3:CRS84" } },
"features": [
{ "type": "Feature", "properties": { "point_type": "origin", "points_str": "45.455594, -122.644877" }, "geometry": { "type": "Point", "coordinates": [ -122.64487703101878, 45.455594468264906 ] } },
{ "type": "Feature", "properties": { "point_type": "destination", "points_str": "45.46158, -122.624479" }, "geometry": { "type": "Point", "coordinates": [ -122.624479004076861, 45.461579722315854 ] } }
]
}
