{
"type": "FeatureCollection",
"crs": { "type": "name", "properties": { "name": "urn:ogc:def:crs:OGC:1.3:CRS84" } },
"features": [
{ "type": "Feature", "properties": { "point_type": "origin", "points_str": "45.519559, -122.887177" }, "geometry": { "type": "Point", "coordinates": [ -122.887176756992801, 45.519559362797068 ] } },
{ "type": "Feature", "properties": { "point_type": "destination", "points_str": "45.520338, -122.990485" }, "geometry": { "type": "Point", "coordinates": [ -122.990485122751693, 45.520337600039113 ] } }
]
}
