{
"type": "FeatureCollection",
"name": "origin_destination_points",
"crs": { "type": "name", "properties": { "name": "urn:ogc:def:crs:OGC:1.3:CRS84" } },
"features": [
{ "type": "Feature", "properties": { "point_type": "origin", "points_str": "45.489139, -122.711267" }, "geometry": { "type": "Point", "coordinates": [ -122.711266558220984, 45.489139371829914 ] } },
{ "type": "Feature", "properties": { "point_type": "destination", "points_str": "45.537055, -122.715118" }, "geometry": { "type": "Point", "coordinates": [ -122.715117711834452, 45.537054920071682 ] } }
]
}
