{
"type": "FeatureCollection",
"crs": { "type": "name", "properties": { "name": "urn:ogc:def:crs:OGC:1.3:CRS84" } },
"features": [
{ "type": "Feature", "properties": { "point_type": "origin", "points_str": "45.557592, -122.556126" }, "geometry": { "type": "Point", "coordinates": [ -122.556126468430776, 45.557592106600545 ] } },
{ "type": "Feature", "properties": { "point_type": "destination", "points_str": "45.5317, -122.883517" }, "geometry": { "type": "Point", "coordinates": [ -122.883516637483666, 45.531700384851952 ] } }
]
}
