{
"type": "FeatureCollection",
"name": "origin_destination_points",
"crs": { "type": "name", "properties": { "name": "urn:ogc:def:crs:OGC:1.3:CRS84" } },
"features": [
{ "type": "Feature", "properties": { "point_type": "origin", "points_str": "45.446999, -122.777909" }, "geometry": { "type": "Point", "coordinates": [ -122.777908576374671, 45.446999133399338 ] } },
{ "type": "Feature", "properties": { "point_type": "destination", "points_str": "45.369489, -122.646952" }, "geometry": { "type": "Point", "coordinates": [ -122.646952208897744, 45.369489160053583 ] } }
]
}
