{
"type": "FeatureCollection",
"name": "origin_destination_points",
"crs": { "type": "name", "properties": { "name": "urn:ogc:def:crs:OGC:1.3:CRS84" } },
"features": [
{ "type": "Feature", "properties": { "point_type": "origin", "points_str": "45.549398, -122.667833" }, "geometry": { "type": "Point", "coordinates": [ -122.667833109388553, 45.549398195896799 ] } },
{ "type": "Feature", "properties": { "point_type": "destination", "points_str": "45.459314, -122.771926" }, "geometry": { "type": "Point", "coordinates": [ -122.771926158415525, 45.459314180715374 ] } }
]
}
