{
"type": "FeatureCollection",
"name": "origin_destination_points",
"crs": { "type": "name", "properties": { "name": "urn:ogc:def:crs:OGC:1.3:CRS84" } },
"features": [
{ "type": "Feature", "properties": { "point_type": "origin", "points_str": "45.49945, -122.417659" }, "geometry": { "type": "Point", "coordinates": [ -122.417659492492987, 45.499450098455839 ] } },
{ "type": "Feature", "properties": { "point_type": "destination", "points_str": "45.517895, -122.551417" }, "geometry": { "type": "Point", "coordinates": [ -122.551416681360777, 45.517894647505329 ] } }
]
}
