{
"type": "FeatureCollection",
"name": "origin_destination_points",
"crs": { "type": "name", "properties": { "name": "urn:ogc:def:crs:OGC:1.3:CRS84" } },
"features": [
{ "type": "Feature", "properties": { "point_type": "origin", "points_str": "45.521189, -122.979858" }, "geometry": { "type": "Point", "coordinates": [ -122.97985773879428, 45.521188862902441 ] } },
{ "type": "Feature", "properties": { "point_type": "destination", "points_str": "45.475236, -122.830092" }, "geometry": { "type": "Point", "coordinates": [ -122.830092036788258, 45.475236465320485 ] } }
]
}
