{
"type": "FeatureCollection",
"name": "origin_destination_points",
"crs": { "type": "name", "properties": { "name": "urn:ogc:def:crs:OGC:1.3:CRS84" } },
"features": [
{ "type": "Feature", "properties": { "point_type": "origin", "points_str": "45.584511, -122.740102" }, "geometry": { "type": "Point", "coordinates": [ -122.740101569335948, 45.584510577170285 ] } },
{ "type": "Feature", "properties": { "point_type": "destination", "points_str": "45.51146, -122.719091" }, "geometry": { "type": "Point", "coordinates": [ -122.719090696574895, 45.511459685256895 ] } }
]
}
