{
"type": "FeatureCollection",
"crs": { "type": "name", "properties": { "name": "urn:ogc:def:crs:OGC:1.3:CRS84" } },
"features": [
{ "type": "Feature", "properties": { "point_type": "origin", "points_str": "45.528546, -122.558628" }, "geometry": { "type": "Point", "coordinates": [ -122.55862818217625, 45.528545879554919 ] } },
{ "type": "Feature", "properties": { "point_type": "destination", "points_str": "45.527497, -122.626632" }, "geometry": { "type": "Point", "coordinates": [ -122.626631864780137, 45.527497431408904 ] } }
]
}
