{
"type": "FeatureCollection",
"name": "origin_destination_points",
"crs": { "type": "name", "properties": { "name": "urn:ogc:def:crs:OGC:1.3:CRS84" } },
"features": [
{ "type": "Feature", "properties": { "point_type": "origin", "points_str": "45.587982, -122.732765" }, "geometry": { "type": "Point", "coordinates": [ -122.732764961859104, 45.587981870232468 ] } },
{ "type": "Feature", "properties": { "point_type": "destination", "points_str": "45.506133, -122.632483" }, "geometry": { "type": "Point", "coordinates": [ -122.632482566777696, 45.506133213853538 ] } }
]
}
