{
"type": "FeatureCollection",
"name": "origin_destination_points",
"crs": { "type": "name", "properties": { "name": "urn:ogc:def:crs:OGC:1.3:CRS84" } },
"features": [
{ "type": "Feature", "properties": { "point_type": "origin", "points_str": "45.546427, -122.858185" }, "geometry": { "type": "Point", "coordinates": [ -122.858184979493274, 45.546426642927329 ] } },
{ "type": "Feature", "properties": { "point_type": "destination", "points_str": "45.543591, -122.998913" }, "geometry": { "type": "Point", "coordinates": [ -122.99891340554035, 45.543591459384395 ] } }
]
}
