{
"type": "FeatureCollection",
"crs": { "type": "name", "properties": { "name": "urn:ogc:def:crs:OGC:1.3:CRS84" } },
"features": [
{ "type": "Feature", "properties": { "point_type": "origin", "points_str": "45.544641, -122.587758" }, "geometry": { "type": "Point", "coordinates": [ -122.587758343334258, 45.544641153089422 ] } },
{ "type": "Feature", "properties": { "point_type": "destination", "points_str": "45.515609, -122.476932" }, "geometry": { "type": "Point", "coordinates": [ -122.476931930818196, 45.515609156289095 ] } }
]
}
