{
"type": "FeatureCollection",
"crs": { "type": "name", "properties": { "name": "urn:ogc:def:crs:OGC:1.3:CRS84" } },
"features": [
{ "type": "Feature", "properties": { "point_type": "origin", "points_str": "45.438326, -122.795839" }, "geometry": { "type": "Point", "coordinates": [ -122.795839162354397, 45.438325533455 ] } },
{ "type": "Feature", "properties": { "point_type": "destination", "points_str": "45.495713, -122.533354" }, "geometry": { "type": "Point", "coordinates": [ -122.533354143630476, 45.495712691831692 ] } }
]
}
