{
"type": "FeatureCollection",
"crs": { "type": "name", "properties": { "name": "urn:ogc:def:crs:OGC:1.3:CRS84" } },
"features": [
{ "type": "Feature", "properties": { "point_type": "origin", "points_str": "45.576863, -122.714116" }, "geometry": { "type": "Point", "coordinates": [ -122.714115595633714, 45.576862752123077 ] } },
{ "type": "Feature", "properties": { "point_type": "destination", "points_str": "45.447736, -122.595327" }, "geometry": { "type": "Point", "coordinates": [ -122.595327403293524, 45.44773626455116 ] } }
]
}
