{
"type": "FeatureCollection",
"name": "origin_destination_points",
"crs": { "type": "name", "properties": { "name": "urn:ogc:def:crs:OGC:1.3:CRS84" } },
"features": [
{ "type": "Feature", "properties": { "point_type": "origin", "points_str": "45.558475, -122.654803" }, "geometry": { "type": "Point", "coordinates": [ -122.654802880290191, 45.558474736592494 ] } },
{ "type": "Feature", "properties": { "point_type": "destination", "points_str": "45.479482, -122.61491" }, "geometry": { "type": "Point", "coordinates": [ -122.614910196700677, 45.479481862083389 ] } }
]
}
