{
"type": "FeatureCollection",
"name": "origin_destination_points",
"crs": { "type": "name", "properties": { "name": "urn:ogc:def:crs:OGC:1.3:CRS84" } },
"features": [
{ "type": "Feature", "properties": { "point_type": "origin", "points_str": "45.502803, -122.547697" }, "geometry": { "type": "Point", "coordinates": [ -122.547696899350953, 45.502803257410719 ] } },
{ "type": "Feature", "properties": { "point_type": "destination", "points_str": "45.464405, -122.741387" }, "geometry": { "type": "Point", "coordinates": [ -122.74138655121169, 45.464404787233015 ] } }
]
}
