{
"type": "FeatureCollection",
"name": "origin_destination_points",
"crs": { "type": "name", "properties": { "name": "urn:ogc:def:crs:OGC:1.3:CRS84" } },
"features": [
{ "type": "Feature", "properties": { "point_type": "origin", "points_str": "45.519211, -122.986574" }, "geometry": { "type": "Point", "coordinates": [ -122.986574466143082, 45.519211367590316 ] } },
{ "type": "Feature", "properties": { "point_type": "destination", "points_str": "45.569864, -122.559849" }, "geometry": { "type": "Point", "coordinates": [ -122.55984857679293, 45.569863748229359 ] } }
]
}
