{
"type": "FeatureCollection",
"name": "origin_destination_points",
"crs": { "type": "name", "properties": { "name": "urn:ogc:def:crs:OGC:1.3:CRS84" } },
"features": [
{ "type": "Feature", "properties": { "point_type": "origin", "points_str": "45.496298, -122.552714" }, "geometry": { "type": "Point", "coordinates": [ -122.552713750543631, 45.496297808669212 ] } },
{ "type": "Feature", "properties": { "point_type": "destination", "points_str": "45.498917, -122.831251" }, "geometry": { "type": "Point", "coordinates": [ -122.831250762569155, 45.498916659644451 ] } }
]
}
