{
"type": "FeatureCollection",
"name": "origin_destination_points",
"crs": { "type": "name", "properties": { "name": "urn:ogc:def:crs:OGC:1.3:CRS84" } },
"features": [
{ "type": "Feature", "properties": { "point_type": "origin", "points_str": "45.484072, -122.854604" }, "geometry": { "type": "Point", "coordinates": [ -122.854604267152268, 45.484071907712035 ] } },
{ "type": "Feature", "properties": { "point_type": "destination", "points_str": "45.440651, -122.773813" }, "geometry": { "type": "Point", "coordinates": [ -122.773812907346183, 45.440650881569319 ] } }
]
}
