{
"type": "FeatureCollection",
"name": "origin_destination_points",
"crs": { "type": "name", "properties": { "name": "urn:ogc:def:crs:OGC:1.3:CRS84" } },
"features": [
{ "type": "Feature", "properties": { "point_type": "origin", "points_str": "45.523808, -122.616791" }, "geometry": { "type": "Point", "coordinates": [ -122.616790502551183, 45.523808055787299 ] } },
{ "type": "Feature", "properties": { "point_type": "destination", "points_str": "45.580606, -122.667947" }, "geometry": { "type": "Point", "coordinates": [ -122.667946993033496, 45.58060579149614 ] } }
]
}
