{
"type": "FeatureCollection",
"name": "origin_destination_points",
"crs": { "type": "name", "properties": { "name": "urn:ogc:def:crs:OGC:1.3:CRS84" } },
"features": [
{ "type": "Feature", "properties": { "point_type": "origin", "points_str": "45.53257, -122.907783" }, "geometry": { "type": "Point", "coordinates": [ -122.907783419244026, 45.532570458290515 ] } },
{ "type": "Feature", "properties": { "point_type": "destination", "points_str": "45.535217, -122.885261" }, "geometry": { "type": "Point", "coordinates": [ -122.885261288178484, 45.535217435951971 ] } }
]
}
