{
"type": "FeatureCollection",
"name": "origin_destination_points",
"crs": { "type": "name", "properties": { "name": "urn:ogc:def:crs:OGC:1.3:CRS84" } },
"features": [
{ "type": "Feature", "properties": { "point_type": "origin", "points_str": "45.539801, -122.390084" }, "geometry": { "type": "Point", "coordinates": [ -122.390083798073576, 45.539800547187397 ] } },
{ "type": "Feature", "properties": { "point_type": "destination", "points_str": "45.533289, -122.598958" }, "geometry": { "type": "Point", "coordinates": [ -122.598958307900531, 45.53328915093639 ] } }
]
}
