{
"type": "FeatureCollection",
"name": "origin_destination_points",
"crs": { "type": "name", "properties": { "name": "urn:ogc:def:crs:OGC:1.3:CRS84" } },
"features": [
{ "type": "Feature", "properties": { "point_type": "origin", "points_str": "45.574236, -122.641621" }, "geometry": { "type": "Point", "coordinates": [ -122.641620965286307, 45.574235999452938 ] } },
{ "type": "Feature", "properties": { "point_type": "destination", "points_str": "45.572114, -122.759414" }, "geometry": { "type": "Point", "coordinates": [ -122.759413893611026, 45.572114019885817 ] } }
]
}
