{
"type": "FeatureCollection",
"name": "origin_destination_points",
"crs": { "type": "name", "properties": { "name": "urn:ogc:def:crs:OGC:1.3:CRS84" } },
"features": [
{ "type": "Feature", "properties": { "point_type": "origin", "points_str": "45.531747, -122.637745" }, "geometry": { "type": "Point", "coordinates": [ -122.637744741565015, 45.531746527855773 ] } },
{ "type": "Feature", "properties": { "point_type": "destination", "points_str": "45.53955, -122.571105" }, "geometry": { "type": "Point", "coordinates": [ -122.571105105314629, 45.539549744108832 ] } }
]
}
