{
"type": "FeatureCollection",
"name": "origin_destination_points",
"crs": { "type": "name", "properties": { "name": "urn:ogc:def:crs:OGC:1.3:CRS84" } },
"features": [
{ "type": "Feature", "properties": { "point_type": "origin", "points_str": "45.369697, -122.57233" }, "geometry": { "type": "Point", "coordinates": [ -122.572329983361058, 45.369697373219068 ] } },
{ "type": "Feature", "properties": { "point_type": "destination", "points_str": "45.421045, -122.637013" }, "geometry": { "type": "Point", "coordinates": [ -122.637013247122383, 45.421045452769391 ] } }
]
}
