{
"type": "FeatureCollection",
"crs": { "type": "name", "properties": { "name": "urn:ogc:def:crs:OGC:1.3:CRS84" } },
"features": [
{ "type": "Feature", "properties": { "point_type": "origin", "points_str": "45.351766, -122.610116" }, "geometry": { "type": "Point", "coordinates": [ -122.610115754293048, 45.351765918196655 ] } },
{ "type": "Feature", "properties": { "point_type": "destination", "points_str": "45.601734, -122.758915" }, "geometry": { "type": "Point", "coordinates": [ -122.758914974853724, 45.601734177841244 ] } }
]
}
