{
"type": "FeatureCollection",
"crs": { "type": "name", "properties": { "name": "urn:ogc:def:crs:OGC:1.3:CRS84" } },
"features": [
{ "type": "Feature", "properties": { "point_type": "origin", "points_str": "45.511635, -122.440025" }, "geometry": { "type": "Point", "coordinates": [ -122.44002477190368, 45.511634907473393 ] } },
{ "type": "Feature", "properties": { "point_type": "destination", "points_str": "45.523623, -122.625108" }, "geometry": { "type": "Point", "coordinates": [ -122.625108174317631, 45.523623213641791 ] } }
]
}
