{
"type": "FeatureCollection",
"crs": { "type": "name", "properties": { "name": "urn:ogc:def:crs:OGC:1.3:CRS84" } },
"features": [
{ "type": "Feature", "properties": { "point_type": "origin", "points_str": "45.480607, -122.822864" }, "geometry": { "type": "Point", "coordinates": [ -122.822863868643068, 45.480607112507379 ] } },
{ "type": "Feature", "properties": { "point_type": "destination", "points_str": "45.487115, -122.68917" }, "geometry": { "type": "Point", "coordinates": [ -122.689170414643144, 45.487114545832725 ] } }
]
}
