{
"type": "FeatureCollection",
"name": "origin_destination_points",
"crs": { "type": "name", "properties": { "name": "urn:ogc:def:crs:OGC:1.3:CRS84" } },
"features": [
{ "type": "Feature", "properties": { "point_type": "origin", "points_str": "45.555911, -122.557185" }, "geometry": { "type": "Point", "coordinates": [ -122.557185353916395, 45.555910561744405 ] } },
{ "type": "Feature", "properties": { "point_type": "destination", "points_str": "45.499391, -122.542418" }, "geometry": { "type": "Point", "coordinates": [ -122.542418403732029, 45.499391069305027 ] } }
]
}
