{
"type": "FeatureCollection",
"crs": { "type": "name", "properties": { "name": "urn:ogc:def:crs:OGC:1.3:CRS84" } },
"features": [
{ "type": "Feature", "properties": { "point_type": "origin", "points_str": "45.589151, -122.662112" }, "geometry": { "type": "Point", "coordinates": [ -122.662112214209571, 45.589150894645037 ] } },
{ "type": "Feature", "properties": { "point_type": "destination", "points_str": "45.496461, -122.803274" }, "geometry": { "type": "Point", "coordinates": [ -122.803273785237764, 45.49646109093387 ] } }
]
}
