{
"type": "FeatureCollection",
"name": "origin_destination_points",
"crs": { "type": "name", "properties": { "name": "urn:ogc:def:crs:OGC:1.3:CRS84" } },
"features": [
{ "type": "Feature", "properties": { "point_type": "origin", "points_str": "45.484041, -122.805265" }, "geometry": { "type": "Point", "coordinates": [ -122.805264554905293, 45.484041424173022 ] } },
{ "type": "Feature", "properties": { "point_type": "destination", "points_str": "45.411358, -122.747612" }, "geometry": { "type": "Point", "coordinates": [ -122.747611844360321, 45.411358270785094 ] } }
]
}
