{
"type": "FeatureCollection",
"name": "origin_destination_points",
"crs": { "type": "name", "properties": { "name": "urn:ogc:def:crs:OGC:1.3:CRS84" } },
"features": [
{ "type": "Feature", "properties": { "point_type": "origin", "points_str": "45.482989, -122.681478" }, "geometry": { "type": "Point", "coordinates": [ -122.681478416858525, 45.482989235280385 ] } },
{ "type": "Feature", "properties": { "point_type": "destination", "points_str": "45.518451, -122.616727" }, "geometry": { "type": "Point", "coordinates": [ -122.616727479927931, 45.51845060568585 ] } }
]
}
