{
"type": "FeatureCollection",
"crs": { "type": "name", "properties": { "name": "urn:ogc:def:crs:OGC:1.3:CRS84" } },
"features": [
{ "type": "Feature", "properties": { "point_type": "origin", "points_str": "45.424081, -122.585061" }, "geometry": { "type": "Point", "coordinates": [ -122.585061229231499, 45.424081458734655 ] } },
{ "type": "Feature", "properties": { "point_type": "destination", "points_str": "45.523031, -122.506229" }, "geometry": { "type": "Point", "coordinates": [ -122.506228666311742, 45.523030697193185 ] } }
]
}
