{
"type": "FeatureCollection",
"name": "origin_destination_points",
"crs": { "type": "name", "properties": { "name": "urn:ogc:def:crs:OGC:1.3:CRS84" } },
"features": [
{ "type": "Feature", "properties": { "point_type": "origin", "points_str": "45.487162, -122.750045" }, "geometry": { "type": "Point", "coordinates": [ -122.750045469787267, 45.487161724635882 ] } },
{ "type": "Feature", "properties": { "point_type": "destination", "points_str": "45.561393, -122.649512" }, "geometry": { "type": "Point", "coordinates": [ -122.64951151369938, 45.561393476003282 ] } }
]
}
