{
"type": "FeatureCollection",
"name": "origin_destination_points",
"crs": { "type": "name", "properties": { "name": "urn:ogc:def:crs:OGC:1.3:CRS84" } },
"features": [
{ "type": "Feature", "properties": { "point_type": "origin", "points_str": "45.499208, -122.440935" }, "geometry": { "type": "Point", "coordinates": [ -122.440934684826644, 45.499208132085556 ] } },
{ "type": "Feature", "properties": { "point_type": "destination", "points_str": "45.411796, -122.660998" }, "geometry": { "type": "Point", "coordinates": [ -122.660997938397159, 45.411795857922975 ] } }
]
}
