{
"type": "FeatureCollection",
"name": "origin_destination_points",
"crs": { "type": "name", "properties": { "name": "urn:ogc:def:crs:OGC:1.3:CRS84" } },
"features": [
{ "type": "Feature", "properties": { "point_type": "origin", "points_str": "45.32818, -122.584765" }, "geometry": { "type": "Point", "coordinates": [ -122.584765014249669, 45.328179727353522 ] } },
{ "type": "Feature", "properties": { "point_type": "destination", "points_str": "45.468429, -122.576274" }, "geometry": { "type": "Point", "coordinates": [ -122.576273620491207, 45.468429225709194 ] } }
]
}
