{
"type": "FeatureCollection",
"crs": { "type": "name", "properties": { "name": "urn:ogc:def:crs:OGC:1.3:CRS84" } },
"features": [
{ "type": "Feature", "properties": { "point_type": "origin", "points_str": "45.49263, -122.481618" }, "geometry": { "type": "Point", "coordinates": [ -122.481618161406587, 45.492629575335386 ] } },
{ "type": "Feature", "properties": { "point_type": "destination", "points_str": "45.484087, -122.461356" }, "geometry": { "type": "Point", "coordinates": [ -122.461356279640682, 45.484086780803985 ] } }
]
}
