{
"type": "FeatureCollection",
"name": "origin_destination_points",
"crs": { "type": "name", "properties": { "name": "urn:ogc:def:crs:OGC:1.3:CRS84" } },
"features": [
{ "type": "Feature", "properties": { "point_type": "origin", "points_str": "45.509588, -122.849535" }, "geometry": { "type": "Point", "coordinates": [ -122.849535311012872, 45.509588237020516 ] } },
{ "type": "Feature", "properties": { "point_type": "destination", "points_str": "45.575622, -122.568494" }, "geometry": { "type": "Point", "coordinates": [ -122.56849439982075, 45.575621500326776 ] } }
]
}
