{
"type": "FeatureCollection",
"crs": { "type": "name", "properties": { "name": "urn:ogc:def:crs:OGC:1.3:CRS84" } },
"features": [
{ "type": "Feature", "properties": { "point_type": "origin", "points_str": "45.529939, -122.688544" }, "geometry": { "type": "Point", "coordinates": [ -122.688543684748382, 45.529938799837957 ] } },
{ "type": "Feature", "properties": { "point_type": "destination", "points_str": "45.471493, -122.677817" }, "geometry": { "type": "Point", "coordinates": [ -122.677816874354775, 45.471492590779135 ] } }
]
}
