{
"type": "FeatureCollection",
"name": "origin_destination_points",
"crs": { "type": "name", "properties": { "name": "urn:ogc:def:crs:OGC:1.3:CRS84" } },
"features": [
{ "type": "Feature", "properties": { "point_type": "origin", "points_str": "45.511293, -122.779731" }, "geometry": { "type": "Point", "coordinates": [ -122.779730925170682, 45.511293371968527 ] } },
{ "type": "Feature", "properties": { "point_type": "destination", "points_str": "45.552959, -122.575717" }, "geometry": { "type": "Point", "coordinates": [ -122.575716876010262, 45.552958614188 ] } }
]
}
