{
"type": "FeatureCollection",
"crs": { "type": "name", "properties": { "name": "urn:ogc:def:crs:OGC:1.3:CRS84" } },
"features": [
{ "type": "Feature", "properties": { "point_type": "origin", "points_str": "45.465208, -122.792656" }, "geometry": { "type": "Point", "coordinates": [ -122.792656031895348, 45.465207760564184 ] } },
{ "type": "Feature", "properties": { "point_type": "destination", "points_str": "45.382372, -122.742013" }, "geometry": { "type": "Point", "coordinates": [ -122.742013434342311, 45.382372376520088 ] } }
]
}
