{
"type": "FeatureCollection",
"crs": { "type": "name", "properties": { "name": "urn:ogc:def:crs:OGC:1.3:CRS84" } },
"features": [
{ "type": "Feature", "properties": { "point_type": "origin", "points_str": "45.471267, -122.694227" }, "geometry": { "type": "Point", "coordinates": [ -122.694226548055497, 45.471267316839622 ] } },
{ "type": "Feature", "properties": { "point_type": "destination", "points_str": "45.538501, -122.659748" }, "geometry": { "type": "Point", "coordinates": [ -122.659747897771851, 45.53850130686002 ] } }
]
}
