{
"type": "FeatureCollection",
"name": "origin_destination_points",
"crs": { "type": "name", "properties": { "name": "urn:ogc:def:crs:OGC:1.3:CRS84" } },
"features": [
{ "type": "Feature", "properties": { "point_type": "origin", "points_str": "45.372723, -122.745788" }, "geometry": { "type": "Point", "coordinates": [ -122.74578781551601, 45.372722884342203 ] } },
{ "type": "Feature", "properties": { "point_type": "destination", "points_str": "45.376986, -122.603823" }, "geometry": { "type": "Point", "coordinates": [ -122.603823410731223, 45.376986372260816 ] } }
]
}
