{
"type": "FeatureCollection",
"crs": { "type": "name", "properties": { "name": "urn:ogc:def:crs:OGC:1.3:CRS84" } },
"features": [
{ "type": "Feature", "properties": { "point_type": "origin", "points_str": "45.472329, -122.686484" }, "geometry": { "type": "Point", "coordinates": [ -122.686484343899451, 45.472328634747775 ] } },
{ "type": "Feature", "properties": { "point_type": "destination", "points_str": "45.502733, -122.448645" }, "geometry": { "type": "Point", "coordinates": [ -122.448645147168421, 45.502732976833904 ] } }
]
}
