{
"type": "FeatureCollection",
"name": "origin_destination_points",
"crs": { "type": "name", "properties": { "name": "urn:ogc:def:crs:OGC:1.3:CRS84" } },
"features": [
{ "type": "Feature", "properties": { "point_type": "origin", "points_str": "45.460196, -122.651911" }, "geometry": { "type": "Point", "coordinates": [ -122.651911430489477, 45.460196399064401 ] } },
{ "type": "Feature", "properties": { "point_type": "destination", "points_str": "45.330021, -122.576718" }, "geometry": { "type": "Point", "coordinates": [ -122.576718135186354, 45.330021294466469 ] } }
]
}
