{
"type": "FeatureCollection",
"name": "origin_destination_points",
"crs": { "type": "name", "properties": { "name": "urn:ogc:def:crs:OGC:1.3:CRS84" } },
"features": [
{ "type": "Feature", "properties": { "point_type": "origin", "points_str": "45.524459, -122.60536" }, "geometry": { "type": "Point", "coordinates": [ -122.605360222888066, 45.524459195258714 ] } },
{ "type": "Feature", "properties": { "point_type": "destination", "points_str": "45.532823, -122.563724" }, "geometry": { "type": "Point", "coordinates": [ -122.563724266542565, 45.532822689511718 ] } }
]
}
