{
"type": "FeatureCollection",
"crs": { "type": "name", "properties": { "name": "urn:ogc:def:crs:OGC:1.3:CRS84" } },
"features": [
{ "type": "Feature", "properties": { "point_type": "origin", "points_str": "45.519877, -123.052227" }, "geometry": { "type": "Point", "coordinates": [ -123.052227094828368, 45.519877243937074 ] } },
{ "type": "Feature", "properties": { "point_type": "destination", "points_str": "45.548888, -122.911285" }, "geometry": { "type": "Point", "coordinates": [ -122.91128487619514, 45.548888126673738 ] } }
]
}
