{
"type": "FeatureCollection",
"crs": { "type": "name", "properties": { "name": "urn:ogc:def:crs:OGC:1.3:CRS84" } },
"features": [
{ "type": "Feature", "properties": { "point_type": "origin", "points_str": "45.509758, -122.536868" }, "geometry": { "type": "Point", "coordinates": [ -122.536868336980859, 45.50975844763304 ] } },
{ "type": "Feature", "properties": { "point_type": "destination", "points_str": "45.470717, -122.69795" }, "geometry": { "type": "Point", "coordinates": [ -122.69795013411499, 45.470717322215684 ] } }
]
}
