{
"type": "FeatureCollection",
"crs": { "type": "name", "properties": { "name": "urn:ogc:def:crs:OGC:1.3:CRS84" } },
"features": [
{ "type": "Feature", "properties": { "point_type": "origin", "points_str": "45.555159, -122.643338" }, "geometry": { "type": "Point", "coordinates": [ -122.643338367413705, 45.555158627742962 ] } },
{ "type": "Feature", "properties": { "point_type": "destination", "points_str": "45.50113, -122.748103" }, "geometry": { "type": "Point", "coordinates": [ -122.748103494507276, 45.501129645705298 ] } }
]
}
