{
"type": "FeatureCollection",
"name": "origin_destination_points",
"crs": { "type": "name", "properties": { "name": "urn:ogc:def:crs:OGC:1.3:CRS84" } },
"features": [
{ "type": "Feature", "properties": { "point_type": "origin", "points_str": "45.525628, -122.683124" }, "geometry": { "type": "Point", "coordinates": [ -122.683123857833465, 45.52562845310095 ] } },
{ "type": "Feature", "properties": { "point_type": "destination", "points_str": "45.534002, -122.464215" }, "geometry": { "type": "Point", "coordinates": [ -122.464214752755552, 45.534001838772362 ] } }
]
}
