{
"type": "FeatureCollection",
"name": "origin_destination_points",
"crs": { "type": "name", "properties": { "name": "urn:ogc:def:crs:OGC:1.3:CRS84" } },
"features": [
{ "type": "Feature", "properties": { "point_type": "origin", "points_str": "45.517471, -122.427385" }, "geometry": { "type": "Point", "coordinates": [ -122.427385037626763, 45.517471013155998 ] } },
{ "type": "Feature", "properties": { "point_type": "destination", "points_str": "45.523796, -122.668721" }, "geometry": { "type": "Point", "coordinates": [ -122.668721132744423, 45.523796477190515 ] } }
]
}
