{
"type": "FeatureCollection",
"name": "origin_destination_points",
"crs": { "type": "name", "properties": { "name": "urn:ogc:def:crs:OGC:1.3:CRS84" } },
"features": [
{ "type": "Feature", "properties": { "point_type": "origin", "points_str": "45.532623, -122.616995" }, "geometry": { "type": "Point", "coordinates": [ -122.616995107828473, 45.532622548553604 ] } },
{ "type": "Feature", "properties": { "point_type": "destination", "points_str": "45.518741, -122.747993" }, "geometry": { "type": "Point", "coordinates": [ -122.74799348268202, 45.518740695341606 ] } }
]
}
