{
"type": "FeatureCollection",
"crs": { "type": "name", "properties": { "name": "urn:ogc:def:crs:OGC:1.3:CRS84" } },
"features": [
{ "type": "Feature", "properties": { "point_type": "origin", "points_str": "45.490165, -122.577663" }, "geometry": { "type": "Point", "coordinates": [ -122.577662902538393, 45.49016453280003 ] } },
{ "type": "Feature", "properties": { "point_type": "destination", "points_str": "45.433976, -122.559467" }, "geometry": { "type": "Point", "coordinates": [ -122.559467439888309, 45.433976283091894 ] } }
]
}
