{
"type": "FeatureCollection",
"crs": { "type": "name", "properties": { "name": "urn:ogc:def:crs:OGC:1.3:CRS84" } },
"features": [
{ "type": "Feature", "properties": { "point_type": "origin", "points_str": "45.516687, -122.457848" }, "geometry": { "type": "Point", "coordinates": [ -122.457847775931199, 45.516687390669325 ] } },
{ "type": "Feature", "properties": { "point_type": "destination", "points_str": "45.443686, -122.656765" }, "geometry": { "type": "Point", "coordinates": [ -122.656764750353204, 45.443686034115473 ] } }
]
}
