{
"type": "FeatureCollection",
"crs": { "type": "name", "properties": { "name": "urn:ogc:def:crs:OGC:1.3:CRS84" } },
"features": [
{ "type": "Feature", "properties": { "point_type": "origin", "points_str": "45.496486, -122.619002" }, "geometry": { "type": "Point", "coordinates": [ -122.619002462660177, 45.496485911347861 ] } },
{ "type": "Feature", "properties": { "point_type": "destination", "points_str": "45.412096, -122.624276" }, "geometry": { "type": "Point", "coordinates": [ -122.624275822429013, 45.412096426959408 ] } }
]
}
