{
"type": "FeatureCollection",
"crs": { "type": "name", "properties": { "name": "urn:ogc:def:crs:OGC:1.3:CRS84" } },
"features": [
{ "type": "Feature", "properties": { "point_type": "origin", "points_str": "45.482747, -122.620946" }, "geometry": { "type": "Point", "coordinates": [ -122.620946055818308, 45.48274726060793 ] } },
{ "type": "Feature", "properties": { "point_type": "destination", "points_str": "45.500742, -122.434215" }, "geometry": { "type": "Point", "coordinates": [ -122.434214631325133, 45.500742477757221 ] } }
]
}
