{
"type": "FeatureCollection",
"name": "origin_destination_points",
"crs": { "type": "name", "properties": { "name": "urn:ogc:def:crs:OGC:1.3:CRS84" } },
"features": [
{ "type": "Feature", "properties": { "point_type": "origin", "points_str": "45.524532, -122.993621" }, "geometry": { "type": "Point", "coordinates": [ -122.993620570683049, 45.524531829132314 ] } },
{ "type": "Feature", "properties": { "point_type": "destination", "points_str": "45.589065, -122.591318" }, "geometry": { "type": "Point", "coordinates": [ -122.591318364764561, 45.589064998671752 ] } }
]
}
