{
"type": "FeatureCollection",
"name": "origin_destination_points",
"crs": { "type": "name", "properties": { "name": "urn:ogc:def:crs:OGC:1.3:CRS84" } },
"features": [
{ "type": "Feature", "properties": { "point_type": "origin", "points_str": "45.572757, -122.553445" }, "geometry": { "type": "Point", "coordinates": [ -122.553444719441302, 45.572757329648383 ] } },
{ "type": "Feature", "properties": { "point_type": "destination", "points_str": "45.534502, -122.868708" }, "geometry": { "type": "Point", "coordinates": [ -122.868707987515279, 45.534501949681179 ] } }
]
}
