{
"type": "FeatureCollection",
"name": "origin_destination_points",
"crs": { "type": "name", "properties": { "name": "urn:ogc:def:crs:OGC:1.3:CRS84" } },
"features": [
{ "type": "Feature", "properties": { "point_type": "origin", "points_str": "45.437252, -122.577476" }, "geometry": { "type": "Point", "coordinates": [ -122.577475637153569, 45.437251664075617 ] } },
{ "type": "Feature", "properties": { "point_type": "destination", "points_str": "45.493658, -122.610772" }, "geometry": { "type": "Point", "coordinates": [ -122.610771698323305, 45.493658157216451 ] } }
]
}
