{
"type": "FeatureCollection",
"crs": { "type": "name", "properties": { "name": "urn:ogc:def:crs:OGC:1.3:CRS84" } },
"features": [
{ "type": "Feature", "properties": { "point_type": "origin", "points_str": "45.559203, -122.507636" }, "geometry": { "type": "Point", "coordinates": [ -122.507635956918705, 45.559203188461325 ] } },
{ "type": "Feature", "properties": { "point_type": "destination", "points_str": "45.522768, -122.870762" }, "geometry": { "type": "Point", "coordinates": [ -122.870762488479713, 45.522767733779304 ] } }
]
}
