{
"type": "FeatureCollection",
"crs": { "type": "name", "properties": { "name": "urn:ogc:def:crs:OGC:1.3:CRS84" } },
"features": [
{ "type": "Feature", "properties": { "point_type": "origin", "points_str": "45.476233, -122.804916" }, "geometry": { "type": "Point", "coordinates": [ -122.804916132397906, 45.47623319467003 ] } },
{ "type": "Feature", "properties": { "point_type": "destination", "points_str": "45.509959, -122.967793" }, "geometry": { "type": "Point", "coordinates": [ -122.967792945056743, 45.509958808675428 ] } }
]
}
