{
"type": "FeatureCollection",
"name": "origin_destination_points",
"crs": { "type": "name", "properties": { "name": "urn:ogc:def:crs:OGC:1.3:CRS84" } },
"features": [
{ "type": "Feature", "properties": { "point_type": "origin", "points_str": "45.582128, -122.681377" }, "geometry": { "type": "Point", "coordinates": [ -122.68137744577426, 45.582128075198767 ] } },
{ "type": "Feature", "properties": { "point_type": "destination", "points_str": "45.398945, -122.654567" }, "geometry": { "type": "Point", "coordinates": [ -122.654566531487376, 45.398944942569436 ] } }
]
}
