{
"type": "FeatureCollection",
"crs": { "type": "name", "properties": { "name": "urn:ogc:def:crs:OGC:1.3:CRS84" } },
"features": [
{ "type": "Feature", "properties": { "point_type": "origin", "points_str": "45.3917, -122.748043" }, "geometry": { "type": "Point", "coordinates": [ -122.748043142356892, 45.391699617685262 ] } },
{ "type": "Feature", "properties": { "point_type": "destination", "points_str": "45.404322, -122.736945" }, "geometry": { "type": "Point", "coordinates": [ -122.73694450121819, 45.404322221903364 ] } }
]
}
