{
"type": "FeatureCollection",
"crs": { "type": "name", "properties": { "name": "urn:ogc:def:crs:OGC:1.3:CRS84" } },
"features": [
{ "type": "Feature", "properties": { "point_type": "origin", "points_str": "45.394913, -122.755254" }, "geometry": { "type": "Point", "coordinates": [ -122.755254223593184, 45.394913161479685 ] } },
{ "type": "Feature", "properties": { "point_type": "destination", "points_str": "45.499125, -122.910088" }, "geometry": { "type": "Point", "coordinates": [ -122.910088330130307, 45.499124814385333 ] } }
]
}
