{
"type": "FeatureCollection",
"name": "origin_destination_points",
"crs": { "type": "name", "properties": { "name": "urn:ogc:def:crs:OGC:1.3:CRS84" } },
"features": [
{ "type": "Feature", "properties": { "point_type": "origin", "points_str": "45.498453, -122.806142" }, "geometry": { "type": "Point", "coordinates": [ -122.806142405022456, 45.498452907006268 ] } },
{ "type": "Feature", "properties": { "point_type": "destination", "points_str": "45.504327, -122.954078" }, "geometry": { "type": "Point", "coordinates": [ -122.95407795336483, 45.504327459081004 ] } }
]
}
