{
"type": "FeatureCollection",
"name": "origin_destination_points",
"crs": { "type": "name", "properties": { "name": "urn:ogc:def:crs:OGC:1.3:CRS84" } },
"features": [
{ "type": "Feature", "properties": { "point_type": "origin", "points_str": "45.51509, -122.975717" }, "geometry": { "type": "Point", "coordinates": [ -122.975717263570573, 45.515090347005149 ] } },
{ "type": "Feature", "properties": { "point_type": "destination", "points_str": "45.520048, -122.47685" }, "geometry": { "type": "Point", "coordinates": [ -122.476850047009904, 45.520047668146198 ] } }
]
}
