{
"type": "FeatureCollection",
"crs": { "type": "name", "properties": { "name": "urn:ogc:def:crs:OGC:1.3:CRS84" } },
"features": [
{ "type": "Feature", "properties": { "point_type": "origin", "points_str": "45.389397, -122.648955" }, "geometry": { "type": "Point", "coordinates": [ -122.648954512779042, 45.389396840057472 ] } },
{ "type": "Feature", "properties": { "point_type": "destination", "points_str": "45.558732, -122.663434" }, "geometry": { "type": "Point", "coordinates": [ -122.663433875595246, 45.558731712325077 ] } }
]
}
