{
"type": "FeatureCollection",
"crs": { "type": "name", "properties": { "name": "urn:ogc:def:crs:OGC:1.3:CRS84" } },
"features": [
{ "type": "Feature", "properties": { "point_type": "origin", "points_str": "45.474491, -122.851558" }, "geometry": { "type": "Point", "coordinates": [ -122.851558357958496, 45.474490530187524 ] } },
{ "type": "Feature", "properties": { "point_type": "destination", "points_str": "45.495784, -122.801799" }, "geometry": { "type": "Point", "coordinates": [ -122.801799262312059, 45.495784069364106 ] } }
]
}
