{
"type": "FeatureCollection",
"name": "origin_destination_points",
"crs": { "type": "name", "properties": { "name": "urn:ogc:def:crs:OGC:1.3:CRS84" } },
"features": [
{ "type": "Feature", "properties": { "point_type": "origin", "points_str": "45.50375, -122.518221" }, "geometry": { "type": "Point", "coordinates": [ -122.518220567861093, 45.503750003963773 ] } },
{ "type": "Feature", "properties": { "point_type": "destination", "points_str": "45.540299, -122.536802" }, "geometry": { "type": "Point", "coordinates": [ -122.536801976698257, 45.540299493787643 ] } }
]
}
