{
"type": "FeatureCollection",
"crs": { "type": "name", "properties": { "name": "urn:ogc:def:crs:OGC:1.3:CRS84" } },
"features": [
{ "type": "Feature", "properties": { "point_type": "origin", "points_str": "45.505983, -122.437194" }, "geometry": { "type": "Point", "coordinates": [ -122.437194120034988, 45.505982647055511 ] } },
{ "type": "Feature", "properties": { "point_type": "destination", "points_str": "45.488056, -122.718526" }, "geometry": { "type": "Point", "coordinates": [ -122.718525988214566, 45.488055751631535 ] } }
]
}
