{
"type": "FeatureCollection",
"name": "origin_destination_points",
"crs": { "type": "name", "properties": { "name": "urn:ogc:def:crs:OGC:1.3:CRS84" } },
"features": [
{ "type": "Feature", "properties": { "point_type": "origin", "points_str": "45.567993, -122.672943" }, "geometry": { "type": "Point", "coordinates": [ -122.672943308691998, 45.567993365877328 ] } },
{ "type": "Feature", "properties": { "point_type": "destination", "points_str": "45.506555, -122.767134" }, "geometry": { "type": "Point", "coordinates": [ -122.767133530053243, 45.506555482717516 ] } }
]
}
