{
"type": "FeatureCollection",
"crs": { "type": "name", "properties": { "name": "urn:ogc:def:crs:OGC:1.3:CRS84" } },
"features": [
{ "type": "Feature", "properties": { "point_type": "origin", "points_str": "45.468397, -122.585621" }, "geometry": { "type": "Point", "coordinates": [ -122.585621233017434, 45.468397343095255 ] } },
{ "type": "Feature", "properties": { "point_type": "destination", "points_str": "45.543393, -122.908454" }, "geometry": { "type": "Point", "coordinates": [ -122.908454453517592, 45.543392764599275 ] } }
]
}
