{
"type": "FeatureCollection",
"name": "origin_destination_points",
"crs": { "type": "name", "properties": { "name": "urn:ogc:def:crs:OGC:1.3:CRS84" } },
"features": [
{ "type": "Feature", "properties": { "point_type": "origin", "points_str": "45.516695, -122.980352" }, "geometry": { "type": "Point", "coordinates": [ -122.980352181223225, 45.51669486456931 ] } },
{ "type": "Feature", "properties": { "point_type": "destination", "points_str": "45.533317, -122.836815" }, "geometry": { "type": "Point", "coordinates": [ -122.836815011461397, 45.533317141420248 ] } }
]
}
