{
"type": "FeatureCollection",
"name": "origin_destination_points",
"crs": { "type": "name", "properties": { "name": "urn:ogc:def:crs:OGC:1.3:CRS84" } },
"features": [
{ "type": "Feature", "properties": { "point_type": "origin", "points_str": "45.523978, -122.597163" }, "geometry": { "type": "Point", "coordinates": [ -122.597163457525653, 45.52397841382902 ] } },
{ "type": "Feature", "properties": { "point_type": "destination", "points_str": "45.555698, -122.497643" }, "geometry": { "type": "Point", "coordinates": [ -122.497642989284316, 45.555698152180099 ] } }
]
}
