{
"type": "FeatureCollection",
"name": "origin_destination_points",
"crs": { "type": "name", "properties": { "name": "urn:ogc:def:crs:OGC:1.3:CRS84" } },
"features": [
{ "type": "Feature", "properties": { "point_type": "origin", "points_str": "45.39257, -122.617127" }, "geometry": { "type": "Point", "coordinates": [ -122.617127429539224, 45.392569982381652 ] } },
{ "type": "Feature", "properties": { "point_type": "destination", "points_str": "45.525516, -122.622105" }, "geometry": { "type": "Point", "coordinates": [ -122.622105383117713, 45.525515557638123 ] } }
]
}
