{
"type": "FeatureCollection",
"name": "origin_destination_points",
"crs": { "type": "name", "properties": { "name": "urn:ogc:def:crs:OGC:1.3:CRS84" } },
"features": [
{ "type": "Feature", "properties": { "point_type": "origin", "points_str": "45.500081, -122.543363" }, "geometry": { "type": "Point", "coordinates": [ -122.543362734174607, 45.500080598440505 ] } },
{ "type": "Feature", "properties": { "point_type": "destination", "points_str": "45.508732, -122.579256" }, "geometry": { "type": "Point", "coordinates": [ -122.579255508602387, 45.508731810451728 ] } }
]
}
