{
"type": "FeatureCollection",
"name": "origin_destination_points",
"crs": { "type": "name", "properties": { "name": "urn:ogc:def:crs:OGC:1.3:CRS84" } },
"features": [
{ "type": "Feature", "properties": { "point_type": "origin", "points_str": "45.444292, -122.604485" }, "geometry": { "type": "Point", "coordinates": [ -122.60448548409363, 45.444291687105938 ] } },
{ "type": "Feature", "properties": { "point_type": "destination", "points_str": "45.468101, -122.588843" }, "geometry": { "type": "Point", "coordinates": [ -122.588842778278973, 45.46810118869513 ] } }
]
}
