{
"type": "FeatureCollection",
"name": "origin_destination_points",
"crs": { "type": "name", "properties": { "name": "urn:ogc:def:crs:OGC:1.3:CRS84" } },
"features": [
{ "type": "Feature", "properties": { "point_type": "origin", "points_str": "45.491252, -122.799152" }, "geometry": { "type": "Point", "coordinates": [ -122.799152209933425, 45.491251932323841 ] } },
{ "type": "Feature", "properties": { "point_type": "destination", "points_str": "45.47585, -122.630578" }, "geometry": { "type": "Point", "coordinates": [ -122.630577689469135, 45.475849808873413 ] } }
]
}
