{
"type": "FeatureCollection",
"name": "origin_destination_points",
"crs": { "type": "name", "properties": { "name": "urn:ogc:def:crs:OGC:1.3:CRS84" } },
"features": [
{ "type": "Feature", "properties": { "point_type": "origin", "points_str": "45.525395, -122.984712" }, "geometry": { "type": "Point", "coordinates": [ -122.984711917027994, 45.525395064664302 ] } },
{ "type": "Feature", "properties": { "point_type": "destination", "points_str": "45.422931, -122.752858" }, "geometry": { "type": "Point", "coordinates": [ -122.752857525197456, 45.422931316550077 ] } }
]
}
