{
"type": "FeatureCollection",
"name": "origin_destination_points",
"crs": { "type": "name", "properties": { "name": "urn:ogc:def:crs:OGC:1.3:CRS84" } },
"features": [
{ "type": "Feature", "properties": { "point_type": "origin", "points_str": "45.476556, -122.745645" }, "geometry": { "type": "Point", "coordinates": [ -122.745645226706259, 45.476555741787195 ] } },
{ "type": "Feature", "properties": { "point_type": "destination", "points_str": "45.568064, -122.686752" }, "geometry": { "type": "Point", "coordinates": [ -122.686752072942042, 45.568064198391681 ] } }
]
}
