{
"type": "FeatureCollection",
"name": "origin_destination_points",
"crs": { "type": "name", "properties": { "name": "urn:ogc:def:crs:OGC:1.3:CRS84" } },
"features": [
{ "type": "Feature", "properties": { "point_type": "origin", "points_str": "45.50887, -122.969341" }, "geometry": { "type": "Point", "coordinates": [ -122.969340794480956, 45.508870285556029 ] } },
{ "type": "Feature", "properties": { "point_type": "destination", "points_str": "45.486746, -122.847761" }, "geometry": { "type": "Point", "coordinates": [ -122.847761377397816, 45.486746292278468 ] } }
]
}
