{
"type": "FeatureCollection",
"name": "origin_destination_points",
"crs": { "type": "name", "properties": { "name": "urn:ogc:def:crs:OGC:1.3:CRS84" } },
"features": [
{ "type": "Feature", "properties": { "point_type": "origin", "points_str": "45.525055, -122.560523" }, "geometry": { "type": "Point", "coordinates": [ -122.560523002914962, 45.525054808028329 ] } },
{ "type": "Feature", "properties": { "point_type": "destination", "points_str": "45.611911, -122.678333" }, "geometry": { "type": "Point", "coordinates": [ -122.678332800209134, 45.611911221738211 ] } }
]
}
