{
"type": "FeatureCollection",
"name": "origin_destination_points",
"crs": { "type": "name", "properties": { "name": "urn:ogc:def:crs:OGC:1.3:CRS84" } },
"features": [
{ "type": "Feature", "properties": { "point_type": "origin", "points_str": "45.518778, -122.646101" }, "geometry": { "type": "Point", "coordinates": [ -122.646101301994364, 45.518777712805267 ] } },
{ "type": "Feature", "properties": { "point_type": "destination", "points_str": "45.534998, -122.689034" }, "geometry": { "type": "Point", "coordinates": [ -122.689034431669938, 45.534998415927809 ] } }
]
}
