{
"type": "FeatureCollection",
"name": "origin_destination_points",
"crs": { "type": "name", "properties": { "name": "urn:ogc:def:crs:OGC:1.3:CRS84" } },
"features": [
{ "type": "Feature", "properties": { "point_type": "origin", "points_str": "45.518901, -122.489877" }, "geometry": { "type": "Point", "coordinates": [ -122.489876903876393, 45.518900623655703 ] } },
{ "type": "Feature", "properties": { "point_type": "destination", "points_str": "45.501017, -122.822024" }, "geometry": { "type": "Point", "coordinates": [ -122.822024016252186, 45.501016584495673 ] } }
]
}
