{
"type": "FeatureCollection",
"crs": { "type": "name", "properties": { "name": "urn:ogc:def:crs:OGC:1.3:CRS84" } },
"features": [
{ "type": "Feature", "properties": { "point_type": "origin", "points_str": "45.434149, -122.755631" }, "geometry": { "type": "Point", "coordinates": [ -122.755630582603672, 45.434148967193117 ] } },
{ "type": "Feature", "properties": { "point_type": "destination", "points_str": "45.478184, -122.53282" }, "geometry": { "type": "Point", "coordinates": [ -122.532819546086316, 45.478184356722402 ] } }
]
}
