{
"type": "FeatureCollection",
"name": "origin_destination_points",
"crs": { "type": "name", "properties": { "name": "urn:ogc:def:crs:OGC:1.3:CRS84" } },
"features": [
{ "type": "Feature", "properties": { "point_type": "origin", "points_str": "45.541983, -122.542931" }, "geometry": { "type": "Point", "coordinates": [ -122.542931012369607, 45.541982580332565 ] } },
{ "type": "Feature", "properties": { "point_type": "destination", "points_str": "45.520467, -122.518671" }, "geometry": { "type": "Point", "coordinates": [ -122.518671438844152, 45.520467406563988 ] } }
]
}
