{
"type": "FeatureCollection",
"name": "origin_destination_points",
"crs": { "type": "name", "properties": { "name": "urn:ogc:def:crs:OGC:1.3:CRS84" } },
"features": [
{ "type": "Feature", "properties": { "point_type": "origin", "points_str": "45.497573, -122.563599" }, "geometry": { "type": "Point", "coordinates": [ -122.563599258550184, 45.497573243403259 ] } },
{ "type": "Feature", "properties": { "point_type": "destination", "points_str": "45.581121, -122.637662" }, "geometry": { "type": "Point", "coordinates": [ -122.637661667889205, 45.58112115078486 ] } }
]
}
