{
"type": "FeatureCollection",
"name": "origin_destination_points",
"crs": { "type": "name", "properties": { "name": "urn:ogc:def:crs:OGC:1.3:CRS84" } },
"features": [
{ "type": "Feature", "properties": { "point_type": "origin", "points_str": "45.55362, -122.410859" }, "geometry": { "type": "Point", "coordinates": [ -122.410858802526462, 45.553619547922963 ] } },
{ "type": "Feature", "properties": { "point_type": "destination", "points_str": "45.509082, -122.584737" }, "geometry": { "type": "Point", "coordinates": [ -122.584736576456791, 45.509081931301587 ] } }
]
}
