{
"type": "FeatureCollection",
"crs": { "type": "name", "properties": { "name": "urn:ogc:def:crs:OGC:1.3:CRS84" } },
"features": [
{ "type": "Feature", "properties": { "point_type": "origin", "points_str": "45.515383, -122.651299" }, "geometry": { "type": "Point", "coordinates": [ -122.651298910229229, 45.515382773749359 ] } },
{ "type": "Feature", "properties": { "point_type": "destination", "points_str": "45.561569, -122.547451" }, "geometry": { "type": "Point", "coordinates": [ -122.547451184588709, 45.561568668690931 ] } }
]
}
