{
"type": "FeatureCollection",
"name": "origin_destination_points",
"crs": { "type": "name", "properties": { "name": "urn:ogc:def:crs:OGC:1.3:CRS84" } },
"features": [
{ "type": "Feature", "properties": { "point_type": "origin", "points_str": "45.584575, -122.75356" }, "geometry": { "type": "Point", "coordinates": [ -122.753560497915132, 45.584574946522004 ] } },
{ "type": "Feature", "properties": { "point_type": "destination", "points_str": "45.541165, -122.701132" }, "geometry": { "type": "Point", "coordinates": [ -122.701132343260326, 45.541165394259068 ] } }
]
}
