{
"type": "FeatureCollection",
"name": "origin_destination_points",
"crs": { "type": "name", "properties": { "name": "urn:ogc:def:crs:OGC:1.3:CRS84" } },
"features": [
{ "type": "Feature", "properties": { "point_type": "origin", "points_str": "45.317331, -122.341966" }, "geometry": { "type": "Point", "coordinates": [ -122.341965761847689, 45.317330618734537 ] } },
{ "type": "Feature", "properties": { "point_type": "destination", "points_str": "45.386583, -122.445076" }, "geometry": { "type": "Point", "coordinates": [ -122.445075772883371, 45.386583385045064 ] } }
]
}
