{
"type": "FeatureCollection",
"name": "origin_destination_points",
"crs": { "type": "name", "properties": { "name": "urn:ogc:def:crs:OGC:1.3:CRS84" } },
"features": [
{ "type": "Feature", "properties": { "point_type": "origin", "points_str": "45.400452, -122.652432" }, "geometry": { "type": "Point", "coordinates": [ -122.652431716224228, 45.400452063266229 ] } },
{ "type": "Feature", "properties": { "point_type": "destination", "points_str": "45.507171, -122.771111" }, "geometry": { "type": "Point", "coordinates": [ -122.771111342324289, 45.507170970747943 ] } }
]
}
