{
"type": "FeatureCollection",
"name": "origin_destination_points",
"crs": { "type": "name", "properties": { "name": "urn:ogc:def:crs:OGC:1.3:CRS84" } },
"features": [
{ "type": "Feature", "properties": { "point_type": "origin", "points_str": "45.468574, -122.573738" }, "geometry": { "type": "Point", "coordinates": [ -122.573738400593584, 45.468573799236566 ] } },
{ "type": "Feature", "properties": { "point_type": "destination", "points_str": "45.563285, -122.71873" }, "geometry": { "type": "Point", "coordinates": [ -122.718729927240659, 45.563284985910954 ] } }
]
}
