{
"type": "FeatureCollection",
"name": "origin_destination_points",
"crs": { "type": "name", "properties": { "name": "urn:ogc:def:crs:OGC:1.3:CRS84" } },
"features": [
{ "type": "Feature", "properties": { "point_type": "origin", "points_str": "45.483452, -122.671358" }, "geometry": { "type": "Point", "coordinates": [ -122.671358447994407, 45.483452116757675 ] } },
{ "type": "Feature", "properties": { "point_type": "destination", "points_str": "45.49777, -122.635614" }, "geometry": { "type": "Point", "coordinates": [ -122.635614381093092, 45.497770417043959 ] } }
]
}
