{
"type": "FeatureCollection",
"crs": { "type": "name", "properties": { "name": "urn:ogc:def:crs:OGC:1.3:CRS84" } },
"features": [
{ "type": "Feature", "properties": { "point_type": "origin", "points_str": "45.47601, -122.639668" }, "geometry": { "type": "Point", "coordinates": [ -122.639668323486134, 45.476010412873393 ] } },
{ "type": "Feature", "properties": { "point_type": "destination", "points_str": "45.502819, -122.653699" }, "geometry": { "type": "Point", "coordinates": [ -122.65369868413751, 45.502819420135722 ] } }
]
}
