{
"type": "FeatureCollection",
"crs": { "type": "name", "properties": { "name": "urn:ogc:def:crs:OGC:1.3:CRS84" } },
"features": [
{ "type": "Feature", "properties": { "point_type": "origin", "points_str": "45.504666, -122.631298" }, "geometry": { "type": "Point", "coordinates": [ -122.63129795646833, 45.504666433039596 ] } },
{ "type": "Feature", "properties": { "point_type": "destination", "points_str": "45.548536, -122.602094" }, "geometry": { "type": "Point", "coordinates": [ -122.602094153932242, 45.548536036678392 ] } }
]
}
