{
"type": "FeatureCollection",
"crs": { "type": "name", "properties": { "name": "urn:ogc:def:crs:OGC:1.3:CRS84" } },
"features": [
{ "type": "Feature", "properties": { "point_type": "origin", "points_str": "45.468276, -122.557469" }, "geometry": { "type": "Point", "coordinates": [ -122.557468756168504, 45.468276426917214 ] } },
{ "type": "Feature", "properties": { "point_type": "destination", "points_str": "45.501399, -122.479278" }, "geometry": { "type": "Point", "coordinates": [ -122.479277858106911, 45.501398702730626 ] } }
]
}
