{
"type": "FeatureCollection",
"crs": { "type": "name", "properties": { "name": "urn:ogc:def:crs:OGC:1.3:CRS84" } },
"features": [
{ "type": "Feature", "properties": { "point_type": "origin", "points_str": "45.550165, -122.722819" }, "geometry": { "type": "Point", "coordinates": [ -122.722818551774324, 45.550165489660465 ] } },
{ "type": "Feature", "properties": { "point_type": "destination", "points_str": "45.392602, -122.648089" }, "geometry": { "type": "Point", "coordinates": [ -122.648089458787027, 45.392602049651231 ] } }
]
}
