{
"type": "FeatureCollection",
"crs": { "type": "name", "properties": { "name": "urn:ogc:def:crs:OGC:1.3:CRS84" } },
"features": [
{ "type": "Feature", "properties": { "point_type": "origin", "points_str": "45.530042, -122.620541" }, "geometry": { "type": "Point", "coordinates": [ -122.620540843388554, 45.530042152094829 ] } },
{ "type": "Feature", "properties": { "point_type": "destination", "points_str": "45.391774, -122.462616" }, "geometry": { "type": "Point", "coordinates": [ -122.462615985740513, 45.391773634999446 ] } }
]
}
