{
"type": "FeatureCollection",
"crs": { "type": "name", "properties": { "name": "urn:ogc:def:crs:OGC:1.3:CRS84" } },
"features": [
{ "type": "Feature", "properties": { "point_type": "origin", "points_str": "45.556378, -122.605472" }, "geometry": { "type": "Point", "coordinates": [ -122.60547223939858, 45.556377550456709 ] } },
{ "type": "Feature", "properties": { "point_type": "destination", "points_str": "45.506428, -122.57299" }, "geometry": { "type": "Point", "coordinates": [ -122.572990494834514, 45.506428291683747 ] } }
]
}
