{
"type": "FeatureCollection",
"name": "origin_destination_points",
"crs": { "type": "name", "properties": { "name": "urn:ogc:def:crs:OGC:1.3:CRS84" } },
"features": [
{ "type": "Feature", "properties": { "point_type": "origin", "points_str": "45.543301, -122.697916" }, "geometry": { "type": "Point", "coordinates": [ -122.697915768698522, 45.543300531812086 ] } },
{ "type": "Feature", "properties": { "point_type": "destination", "points_str": "45.505389, -122.442193" }, "geometry": { "type": "Point", "coordinates": [ -122.44219280485423, 45.505388693630962 ] } }
]
}
