{
"type": "FeatureCollection",
"name": "origin_destination_points",
"crs": { "type": "name", "properties": { "name": "urn:ogc:def:crs:OGC:1.3:CRS84" } },
"features": [
{ "type": "Feature", "properties": { "point_type": "origin", "points_str": "45.515678, -122.627809" }, "geometry": { "type": "Point", "coordinates": [ -122.627809108795731, 45.515678091660035 ] } },
{ "type": "Feature", "properties": { "point_type": "destination", "points_str": "45.507251, -122.441401" }, "geometry": { "type": "Point", "coordinates": [ -122.441401496338983, 45.507251222096109 ] } }
]
}
