{
"type": "FeatureCollection",
"crs": { "type": "name", "properties": { "name": "urn:ogc:def:crs:OGC:1.3:CRS84" } },
"features": [
{ "type": "Feature", "properties": { "point_type": "origin", "points_str": "45.466808, -122.792889" }, "geometry": { "type": "Point", "coordinates": [ -122.792889258590876, 45.466807539310956 ] } },
{ "type": "Feature", "properties": { "point_type": "destination", "points_str": "45.462297, -122.7547" }, "geometry": { "type": "Point", "coordinates": [ -122.754700144934418, 45.46229724900379 ] } }
]
}
