{
"type": "FeatureCollection",
"crs": { "type": "name", "properties": { "name": "urn:ogc:def:crs:OGC:1.3:CRS84" } },
"features": [
{ "type": "Feature", "properties": { "point_type": "origin", "points_str": "45.540501, -122.656746" }, "geometry": { "type": "Point", "coordinates": [ -122.656745774355429, 45.540500821908992 ] } },
{ "type": "Feature", "properties": { "point_type": "destination", "points_str": "45.503205, -122.616869" }, "geometry": { "type": "Point", "coordinates": [ -122.616868919632793, 45.503205456593101 ] } }
]
}
