{
"type": "FeatureCollection",
"name": "origin_destination_points",
"crs": { "type": "name", "properties": { "name": "urn:ogc:def:crs:OGC:1.3:CRS84" } },
"features": [
{ "type": "Feature", "properties": { "point_type": "origin", "points_str": "45.4978, -122.886871" }, "geometry": { "type": "Point", "coordinates": [ -122.886870585776933, 45.497799632071974 ] } },
{ "type": "Feature", "properties": { "point_type": "destination", "points_str": "45.502502, -122.923573" }, "geometry": { "type": "Point", "coordinates": [ -122.923573471246414, 45.502502162219855 ] } }
]
}
