{
"type": "FeatureCollection",
"crs": { "type": "name", "properties": { "name": "urn:ogc:def:crs:OGC:1.3:CRS84" } },
"features": [
{ "type": "Feature", "properties": { "point_type": "origin", "points_str": "45.505915, -122.779338" }, "geometry": { "type": "Point", "coordinates": [ -122.779338134795694, 45.505915212307315 ] } },
{ "type": "Feature", "properties": { "point_type": "destination", "points_str": "45.483747, -122.694933" }, "geometry": { "type": "Point", "coordinates": [ -122.694933256498473, 45.483747440753348 ] } }
]
}
