{
"type": "FeatureCollection",
"crs": { "type": "name", "properties": { "name": "urn:ogc:def:crs:OGC:1.3:CRS84" } },
"features": [
{ "type": "Feature", "properties": { "point_type": "origin", "points_str": "45.484426, -122.756488" }, "geometry": { "type": "Point", "coordinates": [ -122.756487670394819, 45.484426173068208 ] } },
{ "type": "Feature", "properties": { "point_type": "destination", "points_str": "45.532828, -122.479889" }, "geometry": { "type": "Point", "coordinates": [ -122.479889202960052, 45.532828498131039 ] } }
]
}
