{
"type": "FeatureCollection",
"crs": { "type": "name", "properties": { "name": "urn:ogc:def:crs:OGC:1.3:CRS84" } },
"features": [
{ "type": "Feature", "properties": { "point_type": "origin", "points_str": "45.580093, -122.665895" }, "geometry": { "type": "Point", "coordinates": [ -122.665894730897264, 45.580092995538195 ] } },
{ "type": "Feature", "properties": { "point_type": "destination", "points_str": "45.554711, -122.568628" }, "geometry": { "type": "Point", "coordinates": [ -122.568628196790158, 45.554710999323959 ] } }
]
}
