{
"type": "FeatureCollection",
"name": "origin_destination_points",
"crs": { "type": "name", "properties": { "name": "urn:ogc:def:crs:OGC:1.3:CRS84" } },
"features": [
{ "type": "Feature", "properties": { "point_type": "origin", "points_str": "45.52394, -122.571015" }, "geometry": { "type": "Point", "coordinates": [ -122.571014667127301, 45.523939564616946 ] } },
{ "type": "Feature", "properties": { "point_type": "destination", "points_str": "45.541687, -122.70925" }, "geometry": { "type": "Point", "coordinates": [ -122.709250129785516, 45.541686974470061 ] } }
]
}
