{
"type": "FeatureCollection",
"name": "origin_destination_points",
"crs": { "type": "name", "properties": { "name": "urn:ogc:def:crs:OGC:1.3:CRS84" } },
"features": [
{ "type": "Feature", "properties": { "point_type": "origin", "points_str": "45.481031, -122.617166" }, "geometry": { "type": "Point", "coordinates": [ -122.617165537103418, 45.481030995341214 ] } },
{ "type": "Feature", "properties": { "point_type": "destination", "points_str": "45.591559, -122.636817" }, "geometry": { "type": "Point", "coordinates": [ -122.636816948592809, 45.591559161035015 ] } }
]
}
