{
"type": "FeatureCollection",
"name": "origin_destination_points",
"crs": { "type": "name", "properties": { "name": "urn:ogc:def:crs:OGC:1.3:CRS84" } },
"features": [
{ "type": "Feature", "properties": { "point_type": "origin", "points_str": "45.358931, -122.606577" }, "geometry": { "type": "Point", "coordinates": [ -122.606577352355373, 45.358931183731137 ] } },
{ "type": "Feature", "properties": { "point_type": "destination", "points_str": "45.43802, -122.797805" }, "geometry": { "type": "Point", "coordinates": [ -122.797805365535169, 45.438020298930802 ] } }
]
}
