{
"type": "FeatureCollection",
"crs": { "type": "name", "properties": { "name": "urn:ogc:def:crs:OGC:1.3:CRS84" } },
"features": [
{ "type": "Feature", "properties": { "point_type": "origin", "points_str": "45.47928, -122.708578" }, "geometry": { "type": "Point", "coordinates": [ -122.708578394488271, 45.47927953173609 ] } },
{ "type": "Feature", "properties": { "point_type": "destination", "points_str": "45.456579, -122.749259" }, "geometry": { "type": "Point", "coordinates": [ -122.749258942544159, 45.456578977191491 ] } }
]
}
