{
"type": "FeatureCollection",
"name": "origin_destination_points",
"crs": { "type": "name", "properties": { "name": "urn:ogc:def:crs:OGC:1.3:CRS84" } },
"features": [
{ "type": "Feature", "properties": { "point_type": "origin", "points_str": "45.50463, -122.49219" }, "geometry": { "type": "Point", "coordinates": [ -122.492190013990978, 45.504629844999791 ] } },
{ "type": "Feature", "properties": { "point_type": "destination", "points_str": "45.517993, -122.468093" }, "geometry": { "type": "Point", "coordinates": [ -122.468093293756652, 45.517993425137568 ] } }
]
}
