{
"type": "FeatureCollection",
"name": "origin_destination_points",
"crs": { "type": "name", "properties": { "name": "urn:ogc:def:crs:OGC:1.3:CRS84" } },
"features": [
{ "type": "Feature", "properties": { "point_type": "origin", "points_str": "45.505544, -122.571037" }, "geometry": { "type": "Point", "coordinates": [ -122.571037401342025, 45.505544448453627 ] } },
{ "type": "Feature", "properties": { "point_type": "destination", "points_str": "45.521749, -122.540957" }, "geometry": { "type": "Point", "coordinates": [ -122.540957017908127, 45.521748919963549 ] } }
]
}
