{
"type": "FeatureCollection",
"crs": { "type": "name", "properties": { "name": "urn:ogc:def:crs:OGC:1.3:CRS84" } },
"features": [
{ "type": "Feature", "properties": { "point_type": "origin", "points_str": "45.584624, -122.709204" }, "geometry": { "type": "Point", "coordinates": [ -122.709203645033114, 45.584623595550113 ] } },
{ "type": "Feature", "properties": { "point_type": "destination", "points_str": "45.366624, -122.619243" }, "geometry": { "type": "Point", "coordinates": [ -122.619242684641804, 45.366624339138646 ] } }
]
}
