{
"type": "FeatureCollection",
"crs": { "type": "name", "properties": { "name": "urn:ogc:def:crs:OGC:1.3:CRS84" } },
"features": [
{ "type": "Feature", "properties": { "point_type": "origin", "points_str": "45.58184, -122.744688" }, "geometry": { "type": "Point", "coordinates": [ -122.744688237039298, 45.581840373875622 ] } },
{ "type": "Feature", "properties": { "point_type": "destination", "points_str": "45.394705, -122.60544" }, "geometry": { "type": "Point", "coordinates": [ -122.605440366352923, 45.394705427846148 ] } }
]
}
