{
"type": "FeatureCollection",
"crs": { "type": "name", "properties": { "name": "urn:ogc:def:crs:OGC:1.3:CRS84" } },
"features": [
{ "type": "Feature", "properties": { "point_type": "origin", "points_str": "45.470237, -122.583629" }, "geometry": { "type": "Point", "coordinates": [ -122.583629428525626, 45.47023693449345 ] } },
{ "type": "Feature", "properties": { "point_type": "destination", "points_str": "45.587545, -122.74893" }, "geometry": { "type": "Point", "coordinates": [ -122.748930034497477, 45.587544968804039 ] } }
]
}
