{
"type": "FeatureCollection",
"name": "origin_destination_points",
"crs": { "type": "name", "properties": { "name": "urn:ogc:def:crs:OGC:1.3:CRS84" } },
"features": [
{ "type": "Feature", "properties": { "point_type": "origin", "points_str": "45.427388, -122.57714" }, "geometry": { "type": "Point", "coordinates": [ -122.577140499249523, 45.427387667993507 ] } },
{ "type": "Feature", "properties": { "point_type": "destination", "points_str": "45.404898, -122.763536" }, "geometry": { "type": "Point", "coordinates": [ -122.763535652702998, 45.404897704820442 ] } }
]
}
