{
"type": "FeatureCollection",
"name": "origin_destination_points",
"crs": { "type": "name", "properties": { "name": "urn:ogc:def:crs:OGC:1.3:CRS84" } },
"features": [
{ "type": "Feature", "properties": { "point_type": "origin", "points_str": "45.517966, -123.083144" }, "geometry": { "type": "Point", "coordinates": [ -123.083143785313624, 45.517966294799628 ] } },
{ "type": "Feature", "properties": { "point_type": "destination", "points_str": "45.504696, -122.959347" }, "geometry": { "type": "Point", "coordinates": [ -122.95934713771608, 45.504696391668332 ] } }
]
}
