{
"type": "FeatureCollection",
"crs": { "type": "name", "properties": { "name": "urn:ogc:def:crs:OGC:1.3:CRS84" } },
"features": [
{ "type": "Feature", "properties": { "point_type": "origin", "points_str": "45.580787, -122.653283" }, "geometry": { "type": "Point", "coordinates": [ -122.65328330193816, 45.580787036232977 ] } },
{ "type": "Feature", "properties": { "point_type": "destination", "points_str": "45.521735, -123.063359" }, "geometry": { "type": "Point", "coordinates": [ -123.063359067872426, 45.521735277893377 ] } }
]
}
