{
"type": "FeatureCollection",
"crs": { "type": "name", "properties": { "name": "urn:ogc:def:crs:OGC:1.3:CRS84" } },
"features": [
{ "type": "Feature", "properties": { "point_type": "origin", "points_str": "45.503327, -122.629404" }, "geometry": { "type": "Point", "coordinates": [ -122.6294040154839, 45.503326921251556 ] } },
{ "type": "Feature", "properties": { "point_type": "destination", "points_str": "45.508083, -122.50043" }, "geometry": { "type": "Point", "coordinates": [ -122.500429849324391, 45.508082960203538 ] } }
]
}
