{
"type": "FeatureCollection",
"crs": { "type": "name", "properties": { "name": "urn:ogc:def:crs:OGC:1.3:CRS84" } },
"features": [
{ "type": "Feature", "properties": { "point_type": "origin", "points_str": "45.512332, -122.97693" }, "geometry": { "type": "Point", "coordinates": [ -122.976929589688325, 45.512332337130069 ] } },
{ "type": "Feature", "properties": { "point_type": "destination", "points_str": "45.440123, -122.633865" }, "geometry": { "type": "Point", "coordinates": [ -122.633865399216347, 45.44012293243032 ] } }
]
}
