{
"type": "FeatureCollection",
"name": "origin_destination_points",
"crs": { "type": "name", "properties": { "name": "urn:ogc:def:crs:OGC:1.3:CRS84" } },
"features": [
{ "type": "Feature", "properties": { "point_type": "origin", "points_str": "45.48602, -122.795244" }, "geometry": { "type": "Point", "coordinates": [ -122.795243613531383, 45.486019758548373 ] } },
{ "type": "Feature", "properties": { "point_type": "destination", "points_str": "45.492001, -122.841476" }, "geometry": { "type": "Point", "coordinates": [ -122.841475909598685, 45.492000751811638 ] } }
]
}
