{
"type": "FeatureCollection",
"name": "origin_destination_points",
"crs": { "type": "name", "properties": { "name": "urn:ogc:def:crs:OGC:1.3:CRS84" } },
"features": [
{ "type": "Feature", "properties": { "point_type": "origin", "points_str": "45.492238, -122.807571" }, "geometry": { "type": "Point", "coordinates": [ -122.807571494569729, 45.492237554295691 ] } },
{ "type": "Feature", "properties": { "point_type": "destination", "points_str": "45.520535, -123.054297" }, "geometry": { "type": "Point", "coordinates": [ -123.054297266447833, 45.520535170929698 ] } }
]
}
