{
"type": "FeatureCollection",
"name": "origin_destination_points",
"crs": { "type": "name", "properties": { "name": "urn:ogc:def:crs:OGC:1.3:CRS84" } },
"features": [
{ "type": "Feature", "properties": { "point_type": "origin", "points_str": "45.440281, -122.772663" }, "geometry": { "type": "Point", "coordinates": [ -122.77266313370005, 45.440281383692714 ] } },
{ "type": "Feature", "properties": { "point_type": "destination", "points_str": "45.450969, -122.757097" }, "geometry": { "type": "Point", "coordinates": [ -122.75709744715553, 45.45096855427802 ] } }
]
}
