{
"type": "FeatureCollection",
"name": "origin_destination_points",
"crs": { "type": "name", "properties": { "name": "urn:ogc:def:crs:OGC:1.3:CRS84" } },
"features": [
{ "type": "Feature", "properties": { "point_type": "origin", "points_str": "45.487695, -122.608457" }, "geometry": { "type": "Point", "coordinates": [ -122.608456546576264, 45.487695290815594 ] } },
{ "type": "Feature", "properties": { "point_type": "destination", "points_str": "45.423061, -122.516496" }, "geometry": { "type": "Point", "coordinates": [ -122.516496468738623, 45.423060818462474 ] } }
]
}
