{
"type": "FeatureCollection",
"crs": { "type": "name", "properties": { "name": "urn:ogc:def:crs:OGC:1.3:CRS84" } },
"features": [
{ "type": "Feature", "properties": { "point_type": "origin", "points_str": "45.557133, -122.563303" }, "geometry": { "type": "Point", "coordinates": [ -122.563303166984284, 45.557132947311942 ] } },
{ "type": "Feature", "properties": { "point_type": "destination", "points_str": "45.504319, -122.808291" }, "geometry": { "type": "Point", "coordinates": [ -122.80829085396789, 45.504319238260372 ] } }
]
}
