{
"type": "FeatureCollection",
"crs": { "type": "name", "properties": { "name": "urn:ogc:def:crs:OGC:1.3:CRS84" } },
"features": [
{ "type": "Feature", "properties": { "point_type": "origin", "points_str": "45.387964, -122.604454" }, "geometry": { "type": "Point", "coordinates": [ -122.604453771491222, 45.387964253043201 ] } },
{ "type": "Feature", "properties": { "point_type": "destination", "points_str": "45.440239, -122.596664" }, "geometry": { "type": "Point", "coordinates": [ -122.596664008991198, 45.440238961140821 ] } }
]
}
