{
"type": "FeatureCollection",
"name": "origin_destination_points",
"crs": { "type": "name", "properties": { "name": "urn:ogc:def:crs:OGC:1.3:CRS84" } },
"features": [
{ "type": "Feature", "properties": { "point_type": "origin", "points_str": "45.41742, -122.74333" }, "geometry": { "type": "Point", "coordinates": [ -122.743329898344371, 45.417420153126777 ] } },
{ "type": "Feature", "properties": { "point_type": "destination", "points_str": "45.426728, -122.764021" }, "geometry": { "type": "Point", "coordinates": [ -122.764021195445835, 45.426728271325501 ] } }
]
}
