{
"type": "FeatureCollection",
"name": "origin_destination_points",
"crs": { "type": "name", "properties": { "name": "urn:ogc:def:crs:OGC:1.3:CRS84" } },
"features": [
{ "type": "Feature", "properties": { "point_type": "origin", "points_str": "45.459932, -122.632669" }, "geometry": { "type": "Point", "coordinates": [ -122.632669020978526, 45.459932322587633 ] } },
{ "type": "Feature", "properties": { "point_type": "destination", "points_str": "45.520324, -122.542406" }, "geometry": { "type": "Point", "coordinates": [ -122.54240602810934, 45.520324339432271 ] } }
]
}
