{
"type": "FeatureCollection",
"crs": { "type": "name", "properties": { "name": "urn:ogc:def:crs:OGC:1.3:CRS84" } },
"features": [
{ "type": "Feature", "properties": { "point_type": "origin", "points_str": "45.432579, -122.632202" }, "geometry": { "type": "Point", "coordinates": [ -122.632202309917275, 45.432578589831593 ] } },
{ "type": "Feature", "properties": { "point_type": "destination", "points_str": "45.582403, -122.699118" }, "geometry": { "type": "Point", "coordinates": [ -122.69911767320518, 45.582403203138981 ] } }
]
}
