{
"type": "FeatureCollection",
"name": "origin_destination_points",
"crs": { "type": "name", "properties": { "name": "urn:ogc:def:crs:OGC:1.3:CRS84" } },
"features": [
{ "type": "Feature", "properties": { "point_type": "origin", "points_str": "45.546964, -122.668136" }, "geometry": { "type": "Point", "coordinates": [ -122.668135606533255, 45.546963549739232 ] } },
{ "type": "Feature", "properties": { "point_type": "destination", "points_str": "45.54755, -122.696026" }, "geometry": { "type": "Point", "coordinates": [ -122.696026328060569, 45.547549700501179 ] } }
]
}
