{
"type": "FeatureCollection",
"name": "origin_destination_points",
"crs": { "type": "name", "properties": { "name": "urn:ogc:def:crs:OGC:1.3:CRS84" } },
"features": [
{ "type": "Feature", "properties": { "point_type": "origin", "points_str": "45.47871, -122.606781" }, "geometry": { "type": "Point", "coordinates": [ -122.606780616581815, 45.478709821961679 ] } },
{ "type": "Feature", "properties": { "point_type": "destination", "points_str": "45.291611, -122.33144" }, "geometry": { "type": "Point", "coordinates": [ -122.331439714684876, 45.291610905225802 ] } }
]
}
