{
"type": "FeatureCollection",
"name": "origin_destination_points",
"crs": { "type": "name", "properties": { "name": "urn:ogc:def:crs:OGC:1.3:CRS84" } },
"features": [
{ "type": "Feature", "properties": { "point_type": "origin", "points_str": "45.541749, -122.578164" }, "geometry": { "type": "Point", "coordinates": [ -122.578164367091475, 45.541748810790338 ] } },
{ "type": "Feature", "properties": { "point_type": "destination", "points_str": "45.52826, -122.570472" }, "geometry": { "type": "Point", "coordinates": [ -122.570471980210229, 45.528259583673801 ] } }
]
}
