{
"type": "FeatureCollection",
"name": "origin_destination_points",
"crs": { "type": "name", "properties": { "name": "urn:ogc:def:crs:OGC:1.3:CRS84" } },
"features": [
{ "type": "Feature", "properties": { "point_type": "origin", "points_str": "45.485069, -122.617701" }, "geometry": { "type": "Point", "coordinates": [ -122.617701096841344, 45.485068922511921 ] } },
{ "type": "Feature", "properties": { "point_type": "destination", "points_str": "45.576135, -122.695686" }, "geometry": { "type": "Point", "coordinates": [ -122.695685570847729, 45.576134875459047 ] } }
]
}
