{
"type": "FeatureCollection",
"name": "origin_destination_points",
"crs": { "type": "name", "properties": { "name": "urn:ogc:def:crs:OGC:1.3:CRS84" } },
"features": [
{ "type": "Feature", "properties": { "point_type": "origin", "points_str": "45.533911, -122.631508" }, "geometry": { "type": "Point", "coordinates": [ -122.631507659759436, 45.533910601699532 ] } },
{ "type": "Feature", "properties": { "point_type": "destination", "points_str": "45.434305, -122.696138" }, "geometry": { "type": "Point", "coordinates": [ -122.696138357349383, 45.434305275174175 ] } }
]
}
