{
"type": "FeatureCollection",
"crs": { "type": "name", "properties": { "name": "urn:ogc:def:crs:OGC:1.3:CRS84" } },
"features": [
{ "type": "Feature", "properties": { "point_type": "origin", "points_str": "45.509346, -122.856968" }, "geometry": { "type": "Point", "coordinates": [ -122.856967558166971, 45.509346352283323 ] } },
{ "type": "Feature", "properties": { "point_type": "destination", "points_str": "45.531716, -122.817513" }, "geometry": { "type": "Point", "coordinates": [ -122.817513255955632, 45.531716109994868 ] } }
]
}
