{
"type": "FeatureCollection",
"name": "origin_destination_points",
"crs": { "type": "name", "properties": { "name": "urn:ogc:def:crs:OGC:1.3:CRS84" } },
"features": [
{ "type": "Feature", "properties": { "point_type": "origin", "points_str": "45.500194, -122.617652" }, "geometry": { "type": "Point", "coordinates": [ -122.617651727080982, 45.500194268912686 ] } },
{ "type": "Feature", "properties": { "point_type": "destination", "points_str": "45.508077, -122.770505" }, "geometry": { "type": "Point", "coordinates": [ -122.770504716939826, 45.508076851748207 ] } }
]
}
