{
"type": "FeatureCollection",
"crs": { "type": "name", "properties": { "name": "urn:ogc:def:crs:OGC:1.3:CRS84" } },
"features": [
{ "type": "Feature", "properties": { "point_type": "origin", "points_str": "45.505168, -122.503827" }, "geometry": { "type": "Point", "coordinates": [ -122.503826507101451, 45.505167647884413 ] } },
{ "type": "Feature", "properties": { "point_type": "destination", "points_str": "45.531078, -122.386529" }, "geometry": { "type": "Point", "coordinates": [ -122.386529381731833, 45.531077971379219 ] } }
]
}
