{
"type": "FeatureCollection",
"name": "origin_destination_points",
"crs": { "type": "name", "properties": { "name": "urn:ogc:def:crs:OGC:1.3:CRS84" } },
"features": [
{ "type": "Feature", "properties": { "point_type": "origin", "points_str": "45.520476, -122.417688" }, "geometry": { "type": "Point", "coordinates": [ -122.417687524187585, 45.520475647849644 ] } },
{ "type": "Feature", "properties": { "point_type": "destination", "points_str": "45.517125, -122.391644" }, "geometry": { "type": "Point", "coordinates": [ -122.39164426279774, 45.517124612029185 ] } }
]
}
