{
"type": "FeatureCollection",
"name": "origin_destination_points",
"crs": { "type": "name", "properties": { "name": "urn:ogc:def:crs:OGC:1.3:CRS84" } },
"features": [
{ "type": "Feature", "properties": { "point_type": "origin", "points_str": "45.342011, -122.600505" }, "geometry": { "type": "Point", "coordinates": [ -122.600504833784584, 45.342011388036376 ] } },
{ "type": "Feature", "properties": { "point_type": "destination", "points_str": "45.518504, -122.65308" }, "geometry": { "type": "Point", "coordinates": [ -122.653079781931396, 45.518503509666701 ] } }
]
}
