{
"type": "FeatureCollection",
"crs": { "type": "name", "properties": { "name": "urn:ogc:def:crs:OGC:1.3:CRS84" } },
"features": [
{ "type": "Feature", "properties": { "point_type": "origin", "points_str": "45.369483, -122.842322" }, "geometry": { "type": "Point", "coordinates": [ -122.842321513896891, 45.369482848721034 ] } },
{ "type": "Feature", "properties": { "point_type": "destination", "points_str": "45.605416, -122.746363" }, "geometry": { "type": "Point", "coordinates": [ -122.746363093134931, 45.605415855580802 ] } }
]
}
