{
"type": "FeatureCollection",
"name": "origin_destination_points",
"crs": { "type": "name", "properties": { "name": "urn:ogc:def:crs:OGC:1.3:CRS84" } },
"features": [
{ "type": "Feature", "properties": { "point_type": "origin", "points_str": "45.524723, -122.677785" }, "geometry": { "type": "Point", "coordinates": [ -122.677785334304517, 45.524722556341537 ] } },
{ "type": "Feature", "properties": { "point_type": "destination", "points_str": "45.527151, -122.407006" }, "geometry": { "type": "Point", "coordinates": [ -122.407006076675174, 45.527150740835324 ] } }
]
}
