{
"type": "FeatureCollection",
"name": "origin_destination_points",
"crs": { "type": "name", "properties": { "name": "urn:ogc:def:crs:OGC:1.3:CRS84" } },
"features": [
{ "type": "Feature", "properties": { "point_type": "origin", "points_str": "45.524827, -122.55941" }, "geometry": { "type": "Point", "coordinates": [ -122.559410191917536, 45.524826845318302 ] } },
{ "type": "Feature", "properties": { "point_type": "destination", "points_str": "45.544309, -122.385097" }, "geometry": { "type": "Point", "coordinates": [ -122.385096536805648, 45.544309334038026 ] } }
]
}
