{
"type": "FeatureCollection",
"name": "origin_destination_points",
"crs": { "type": "name", "properties": { "name": "urn:ogc:def:crs:OGC:1.3:CRS84" } },
"features": [
{ "type": "Feature", "properties": { "point_type": "origin", "points_str": "45.5574, -122.703271" }, "geometry": { "type": "Point", "coordinates": [ -122.703271069723371, 45.557399551854182 ] } },
{ "type": "Feature", "properties": { "point_type": "destination", "points_str": "45.52863, -122.947654" }, "geometry": { "type": "Point", "coordinates": [ -122.947654172812207, 45.528629595056898 ] } }
]
}
