{
"type": "FeatureCollection",
"crs": { "type": "name", "properties": { "name": "urn:ogc:def:crs:OGC:1.3:CRS84" } },
"features": [
{ "type": "Feature", "properties": { "point_type": "origin", "points_str": "45.534469, -122.47577" }, "geometry": { "type": "Point", "coordinates": [ -122.47576986489473, 45.534468754255634 ] } },
{ "type": "Feature", "properties": { "point_type": "destination", "points_str": "45.52811, -122.395287" }, "geometry": { "type": "Point", "coordinates": [ -122.395286835128957, 45.528109573691339 ] } }
]
}
