{
"type": "FeatureCollection",
"name": "origin_destination_points",
"crs": { "type": "name", "properties": { "name": "urn:ogc:def:crs:OGC:1.3:CRS84" } },
"features": [
{ "type": "Feature", "properties": { "point_type": "origin", "points_str": "45.497038, -122.821217" }, "geometry": { "type": "Point", "coordinates": [ -122.821217112993509, 45.49703836987878 ] } },
{ "type": "Feature", "properties": { "point_type": "destination", "points_str": "45.588551, -122.760484" }, "geometry": { "type": "Point", "coordinates": [ -122.760484151077108, 45.588550850959514 ] } }
]
}
