{
"type": "FeatureCollection",
"name": "origin_destination_points",
"crs": { "type": "name", "properties": { "name": "urn:ogc:def:crs:OGC:1.3:CRS84" } },
"features": [
{ "type": "Feature", "properties": { "point_type": "origin", "points_str": "45.533064, -122.598416" }, "geometry": { "type": "Point", "coordinates": [ -122.598416341634248, 45.533063820882781 ] } },
{ "type": "Feature", "properties": { "point_type": "destination", "points_str": "45.39328, -122.409303" }, "geometry": { "type": "Point", "coordinates": [ -122.409303237113363, 45.393280422753143 ] } }
]
}
