{
"type": "FeatureCollection",
"crs": { "type": "name", "properties": { "name": "urn:ogc:def:crs:OGC:1.3:CRS84" } },
"features": [
{ "type": "Feature", "properties": { "point_type": "origin", "points_str": "45.551017, -122.647813" }, "geometry": { "type": "Point", "coordinates": [ -122.647812648190836, 45.551017035492478 ] } },
{ "type": "Feature", "properties": { "point_type": "destination", "points_str": "45.507239, -122.751879" }, "geometry": { "type": "Point", "coordinates": [ -122.751879472716396, 45.507238993107627 ] } }
]
}
