{
"type": "FeatureCollection",
"name": "origin_destination_points",
"crs": { "type": "name", "properties": { "name": "urn:ogc:def:crs:OGC:1.3:CRS84" } },
"features": [
{ "type": "Feature", "properties": { "point_type": "origin", "points_str": "45.534245, -122.442981" }, "geometry": { "type": "Point", "coordinates": [ -122.442980515635185, 45.534244927691816 ] } },
{ "type": "Feature", "properties": { "point_type": "destination", "points_str": "45.432246, -122.671302" }, "geometry": { "type": "Point", "coordinates": [ -122.671301571294421, 45.432245892804225 ] } }
]
}
