{
"type": "FeatureCollection",
"name": "origin_destination_points",
"crs": { "type": "name", "properties": { "name": "urn:ogc:def:crs:OGC:1.3:CRS84" } },
"features": [
{ "type": "Feature", "properties": { "point_type": "origin", "points_str": "45.502429, -122.425573" }, "geometry": { "type": "Point", "coordinates": [ -122.425572665264838, 45.502428914277395 ] } },
{ "type": "Feature", "properties": { "point_type": "destination", "points_str": "45.543417, -122.452742" }, "geometry": { "type": "Point", "coordinates": [ -122.452741895063696, 45.543416943844704 ] } }
]
}
