{
"type": "FeatureCollection",
"name": "origin_destination_points",
"crs": { "type": "name", "properties": { "name": "urn:ogc:def:crs:OGC:1.3:CRS84" } },
"features": [
{ "type": "Feature", "properties": { "point_type": "origin", "points_str": "45.516393, -122.408436" }, "geometry": { "type": "Point", "coordinates": [ -122.408435863489643, 45.516392844328109 ] } },
{ "type": "Feature", "properties": { "point_type": "destination", "points_str": "45.444099, -122.654194" }, "geometry": { "type": "Point", "coordinates": [ -122.654194379417021, 45.444098944353492 ] } }
]
}
