{
"type": "FeatureCollection",
"name": "origin_destination_points",
"crs": { "type": "name", "properties": { "name": "urn:ogc:def:crs:OGC:1.3:CRS84" } },
"features": [
{ "type": "Feature", "properties": { "point_type": "origin", "points_str": "45.519669, -122.595355" }, "geometry": { "type": "Point", "coordinates": [ -122.595355417865889, 45.519669356910008 ] } },
{ "type": "Feature", "properties": { "point_type": "destination", "points_str": "45.590559, -122.672612" }, "geometry": { "type": "Point", "coordinates": [ -122.672612219520275, 45.590559307923741 ] } }
]
}
