{
"type": "FeatureCollection",
"name": "origin_destination_points",
"crs": { "type": "name", "properties": { "name": "urn:ogc:def:crs:OGC:1.3:CRS84" } },
"features": [
{ "type": "Feature", "properties": { "point_type": "origin", "points_str": "45.450931, -122.671748" }, "geometry": { "type": "Point", "coordinates": [ -122.671747846793266, 45.450930993775806 ] } },
{ "type": "Feature", "properties": { "point_type": "destination", "points_str": "45.476877, -122.673033" }, "geometry": { "type": "Point", "coordinates": [ -122.673032789554057, 45.476877288196405 ] } }
]
}
