{
"type": "FeatureCollection",
"crs": { "type": "name", "properties": { "name": "urn:ogc:def:crs:OGC:1.3:CRS84" } },
"features": [
{ "type": "Feature", "properties": { "point_type": "origin", "points_str": "45.425282, -122.523256" }, "geometry": { "type": "Point", "coordinates": [ -122.523255872639808, 45.425281769629358 ] } },
{ "type": "Feature", "properties": { "point_type": "destination", "points_str": "45.395423, -122.598715" }, "geometry": { "type": "Point", "coordinates": [ -122.598714700461031, 45.395423123200942 ] } }
]
}
