{
"type": "FeatureCollection",
"crs": { "type": "name", "properties": { "name": "urn:ogc:def:crs:OGC:1.3:CRS84" } },
"features": [
{ "type": "Feature", "properties": { "point_type": "origin", "points_str": "45.502182, -122.523008" }, "geometry": { "type": "Point", "coordinates": [ -122.523007518164235, 45.502182006581158 ] } },
{ "type": "Feature", "properties": { "point_type": "destination", "points_str": "45.542064, -122.905538" }, "geometry": { "type": "Point", "coordinates": [ -122.905537996303792, 45.542063575139302 ] } }
]
}
