{
"type": "FeatureCollection",
"name": "origin_destination_points",
"crs": { "type": "name", "properties": { "name": "urn:ogc:def:crs:OGC:1.3:CRS84" } },
"features": [
{ "type": "Feature", "properties": { "point_type": "origin", "points_str": "45.453105, -122.769156" }, "geometry": { "type": "Point", "coordinates": [ -122.769156003830545, 45.453104777886601 ] } },
{ "type": "Feature", "properties": { "point_type": "destination", "points_str": "45.494728, -122.885347" }, "geometry": { "type": "Point", "coordinates": [ -122.885346610963921, 45.494728010593448 ] } }
]
}
