{
"type": "FeatureCollection",
"crs": { "type": "name", "properties": { "name": "urn:ogc:def:crs:OGC:1.3:CRS84" } },
"features": [
{ "type": "Feature", "properties": { "point_type": "origin", "points_str": "45.562335, -122.846132" }, "geometry": { "type": "Point", "coordinates": [ -122.846131516060609, 45.562335043775882 ] } },
{ "type": "Feature", "properties": { "point_type": "destination", "points_str": "45.503325, -122.822333" }, "geometry": { "type": "Point", "coordinates": [ -122.822332539993553, 45.503325260836114 ] } }
]
}
