{
"type": "FeatureCollection",
"name": "origin_destination_points",
"crs": { "type": "name", "properties": { "name": "urn:ogc:def:crs:OGC:1.3:CRS84" } },
"features": [
{ "type": "Feature", "properties": { "point_type": "origin", "points_str": "45.476945, -122.600649" }, "geometry": { "type": "Point", "coordinates": [ -122.600648772809137, 45.476944678156109 ] } },
{ "type": "Feature", "properties": { "point_type": "destination", "points_str": "45.497021, -122.693854" }, "geometry": { "type": "Point", "coordinates": [ -122.693854078880889, 45.497021362504171 ] } }
]
}
