{
"type": "FeatureCollection",
"crs": { "type": "name", "properties": { "name": "urn:ogc:def:crs:OGC:1.3:CRS84" } },
"features": [
{ "type": "Feature", "properties": { "point_type": "origin", "points_str": "45.528618, -122.674263" }, "geometry": { "type": "Point", "coordinates": [ -122.674262523779944, 45.528618302348313 ] } },
{ "type": "Feature", "properties": { "point_type": "destination", "points_str": "45.519104, -122.51793" }, "geometry": { "type": "Point", "coordinates": [ -122.517930452706693, 45.519103926343035 ] } }
]
}
