{
"type": "FeatureCollection",
"crs": { "type": "name", "properties": { "name": "urn:ogc:def:crs:OGC:1.3:CRS84" } },
"features": [
{ "type": "Feature", "properties": { "point_type": "origin", "points_str": "45.520769, -122.688627" }, "geometry": { "type": "Point", "coordinates": [ -122.688626587991223, 45.520769444489005 ] } },
{ "type": "Feature", "properties": { "point_type": "destination", "points_str": "45.500359, -122.879367" }, "geometry": { "type": "Point", "coordinates": [ -122.879366531262789, 45.500359413058021 ] } }
]
}
