{
"type": "FeatureCollection",
"name": "origin_destination_points",
"crs": { "type": "name", "properties": { "name": "urn:ogc:def:crs:OGC:1.3:CRS84" } },
"features": [
{ "type": "Feature", "properties": { "point_type": "origin", "points_str": "45.46939, -122.777003" }, "geometry": { "type": "Point", "coordinates": [ -122.777002592890298, 45.469389927627667 ] } },
{ "type": "Feature", "properties": { "point_type": "destination", "points_str": "45.48706, -122.73578" }, "geometry": { "type": "Point", "coordinates": [ -122.73577991536547, 45.487059658975632 ] } }
]
}
