{
"type": "FeatureCollection",
"name": "origin_destination_points",
"crs": { "type": "name", "properties": { "name": "urn:ogc:def:crs:OGC:1.3:CRS84" } },
"features": [
{ "type": "Feature", "properties": { "point_type": "origin", "points_str": "45.517919, -122.927314" }, "geometry": { "type": "Point", "coordinates": [ -122.927314330180863, 45.517919015059249 ] } },
{ "type": "Feature", "properties": { "point_type": "destination", "points_str": "45.561002, -122.870295" }, "geometry": { "type": "Point", "coordinates": [ -122.870295164050631, 45.561001816639468 ] } }
]
}
