{
"type": "FeatureCollection",
"crs": { "type": "name", "properties": { "name": "urn:ogc:def:crs:OGC:1.3:CRS84" } },
"features": [
{ "type": "Feature", "properties": { "point_type": "origin", "points_str": "45.440076, -122.726282" }, "geometry": { "type": "Point", "coordinates": [ -122.726281841845804, 45.440076004901904 ] } },
{ "type": "Feature", "properties": { "point_type": "destination", "points_str": "45.454122, -122.712079" }, "geometry": { "type": "Point", "coordinates": [ -122.712079123594322, 45.454122494164942 ] } }
]
}
