{
"type": "FeatureCollection",
"name": "origin_destination_points",
"crs": { "type": "name", "properties": { "name": "urn:ogc:def:crs:OGC:1.3:CRS84" } },
"features": [
{ "type": "Feature", "properties": { "point_type": "origin", "points_str": "45.501914, -122.532304" }, "geometry": { "type": "Point", "coordinates": [ -122.532304136007625, 45.501913771687683 ] } },
{ "type": "Feature", "properties": { "point_type": "destination", "points_str": "45.459048, -122.715997" }, "geometry": { "type": "Point", "coordinates": [ -122.715996549229544, 45.459047533282231 ] } }
]
}
