{
"type": "FeatureCollection",
"name": "origin_destination_points",
"crs": { "type": "name", "properties": { "name": "urn:ogc:def:crs:OGC:1.3:CRS84" } },
"features": [
{ "type": "Feature", "properties": { "point_type": "origin", "points_str": "45.522978, -122.618395" }, "geometry": { "type": "Point", "coordinates": [ -122.618395057438804, 45.522977749286028 ] } },
{ "type": "Feature", "properties": { "point_type": "destination", "points_str": "45.543054, -122.397733" }, "geometry": { "type": "Point", "coordinates": [ -122.397732844348525, 45.543053659713983 ] } }
]
}
