{
"type": "FeatureCollection",
"name": "origin_destination_points",
"crs": { "type": "name", "properties": { "name": "urn:ogc:def:crs:OGC:1.3:CRS84" } },
"features": [
{ "type": "Feature", "properties": { "point_type": "origin", "points_str": "45.336562, -122.589173" }, "geometry": { "type": "Point", "coordinates": [ -122.589172881196177, 45.336561735722775 ] } },
{ "type": "Feature", "properties": { "point_type": "destination", "points_str": "45.420778, -122.626078" }, "geometry": { "type": "Point", "coordinates": [ -122.626078134064016, 45.420778164933559 ] } }
]
}
