{
"type": "FeatureCollection",
"crs": { "type": "name", "properties": { "name": "urn:ogc:def:crs:OGC:1.3:CRS84" } },
"features": [
{ "type": "Feature", "properties": { "point_type": "origin", "points_str": "45.455617, -122.57548" }, "geometry": { "type": "Point", "coordinates": [ -122.57547970780989, 45.455616812043289 ] } },
{ "type": "Feature", "properties": { "point_type": "destination", "points_str": "45.51255, -122.683067" }, "geometry": { "type": "Point", "coordinates": [ -122.683066582283217, 45.512550253753062 ] } }
]
}
