{
"type": "FeatureCollection",
"crs": { "type": "name", "properties": { "name": "urn:ogc:def:crs:OGC:1.3:CRS84" } },
"features": [
{ "type": "Feature", "properties": { "point_type": "origin", "points_str": "45.430338, -122.630761" }, "geometry": { "type": "Point", "coordinates": [ -122.630761044826144, 45.430337578128736 ] } },
{ "type": "Feature", "properties": { "point_type": "destination", "points_str": "45.403157, -122.618311" }, "geometry": { "type": "Point", "coordinates": [ -122.618310893708369, 45.403156504149763 ] } }
]
}
