{
"type": "FeatureCollection",
"crs": { "type": "name", "properties": { "name": "urn:ogc:def:crs:OGC:1.3:CRS84" } },
"features": [
{ "type": "Feature", "properties": { "point_type": "origin", "points_str": "45.551409, -122.981316" }, "geometry": { "type": "Point", "coordinates": [ -122.981315932160797, 45.55140938430781 ] } },
{ "type": "Feature", "properties": { "point_type": "destination", "points_str": "45.515138, -122.844085" }, "geometry": { "type": "Point", "coordinates": [ -122.844084955876681, 45.515137636116563 ] } }
]
}
