{
"type": "FeatureCollection",
"name": "origin_destination_points",
"crs": { "type": "name", "properties": { "name": "urn:ogc:def:crs:OGC:1.3:CRS84" } },
"features": [
{ "type": "Feature", "properties": { "point_type": "origin", "points_str": "45.399611, -122.568624" }, "geometry": { "type": "Point", "coordinates": [ -122.56862402223652, 45.39961073770332 ] } },
{ "type": "Feature", "properties": { "point_type": "destination", "points_str": "45.462298, -122.678887" }, "geometry": { "type": "Point", "coordinates": [ -122.678886895090656, 45.462297806786566 ] } }
]
}
