{
"type": "FeatureCollection",
"crs": { "type": "name", "properties": { "name": "urn:ogc:def:crs:OGC:1.3:CRS84" } },
"features": [
{ "type": "Feature", "properties": { "point_type": "origin", "points_str": "45.51271, -122.666489" }, "geometry": { "type": "Point", "coordinates": [ -122.666489370596182, 45.512709535749615 ] } },
{ "type": "Feature", "properties": { "point_type": "destination", "points_str": "45.41447, -122.723018" }, "geometry": { "type": "Point", "coordinates": [ -122.723018145763604, 45.414470236241222 ] } }
]
}
