{
"type": "FeatureCollection",
"name": "origin_destination_points",
"crs": { "type": "name", "properties": { "name": "urn:ogc:def:crs:OGC:1.3:CRS84" } },
"features": [
{ "type": "Feature", "properties": { "point_type": "origin", "points_str": "45.322767, -122.338508" }, "geometry": { "type": "Point", "coordinates": [ -122.338508164282672, 45.32276747284071 ] } },
{ "type": "Feature", "properties": { "point_type": "destination", "points_str": "45.465026, -122.60744" }, "geometry": { "type": "Point", "coordinates": [ -122.607440489270644, 45.465026286184333 ] } }
]
}
