{
"type": "FeatureCollection",
"crs": { "type": "name", "properties": { "name": "urn:ogc:def:crs:OGC:1.3:CRS84" } },
"features": [
{ "type": "Feature", "properties": { "point_type": "origin", "points_str": "45.557202, -122.670993" }, "geometry": { "type": "Point", "coordinates": [ -122.670992972035407, 45.557202092087714 ] } },
{ "type": "Feature", "properties": { "point_type": "destination", "points_str": "45.552969, -122.701185" }, "geometry": { "type": "Point", "coordinates": [ -122.701185425870634, 45.552968911275613 ] } }
]
}
