{
"type": "FeatureCollection",
"name": "origin_destination_points",
"crs": { "type": "name", "properties": { "name": "urn:ogc:def:crs:OGC:1.3:CRS84" } },
"features": [
{ "type": "Feature", "properties": { "point_type": "origin", "points_str": "45.519881, -122.55632" }, "geometry": { "type": "Point", "coordinates": [ -122.556319592461065, 45.519880635390948 ] } },
{ "type": "Feature", "properties": { "point_type": "destination", "points_str": "45.466835, -122.855982" }, "geometry": { "type": "Point", "coordinates": [ -122.855982169640797, 45.46683519188646 ] } }
]
}
