{
"type": "FeatureCollection",
"name": "origin_destination_points",
"crs": { "type": "name", "properties": { "name": "urn:ogc:def:crs:OGC:1.3:CRS84" } },
"features": [
{ "type": "Feature", "properties": { "point_type": "origin", "points_str": "45.440294, -122.777107" }, "geometry": { "type": "Point", "coordinates": [ -122.777107436707539, 45.440293505457575 ] } },
{ "type": "Feature", "properties": { "point_type": "destination", "points_str": "45.523094, -123.028007" }, "geometry": { "type": "Point", "coordinates": [ -123.028006616848103, 45.523093661703442 ] } }
]
}
