{
"type": "FeatureCollection",
"name": "origin_destination_points",
"crs": { "type": "name", "properties": { "name": "urn:ogc:def:crs:OGC:1.3:CRS84" } },
"features": [
{ "type": "Feature", "properties": { "point_type": "origin", "points_str": "45.538697, -122.701699" }, "geometry": { "type": "Point", "coordinates": [ -122.701699059843691, 45.538697044873629 ] } },
{ "type": "Feature", "properties": { "point_type": "destination", "points_str": "45.517874, -122.689967" }, "geometry": { "type": "Point", "coordinates": [ -122.689967485848399, 45.517873879968413 ] } }
]
}
