{
"type": "FeatureCollection",
"crs": { "type": "name", "properties": { "name": "urn:ogc:def:crs:OGC:1.3:CRS84" } },
"features": [
{ "type": "Feature", "properties": { "point_type": "origin", "points_str": "45.488227, -122.780469" }, "geometry": { "type": "Point", "coordinates": [ -122.780469431388724, 45.488226597801606 ] } },
{ "type": "Feature", "properties": { "point_type": "destination", "points_str": "45.482563, -122.522954" }, "geometry": { "type": "Point", "coordinates": [ -122.522953689260845, 45.482563132606828 ] } }
]
}
