{
"type": "FeatureCollection",
"crs": { "type": "name", "properties": { "name": "urn:ogc:def:crs:OGC:1.3:CRS84" } },
"features": [
{ "type": "Feature", "properties": { "point_type": "origin", "points_str": "45.547637, -122.50368" }, "geometry": { "type": "Point", "coordinates": [ -122.503679511729729, 45.547637372215434 ] } },
{ "type": "Feature", "properties": { "point_type": "destination", "points_str": "45.535781, -122.380005" }, "geometry": { "type": "Point", "coordinates": [ -122.380004607553815, 45.535781305821125 ] } }
]
}
