{
"type": "FeatureCollection",
"name": "origin_destination_points",
"crs": { "type": "name", "properties": { "name": "urn:ogc:def:crs:OGC:1.3:CRS84" } },
"features": [
{ "type": "Feature", "properties": { "point_type": "origin", "points_str": "45.569391, -122.650171" }, "geometry": { "type": "Point", "coordinates": [ -122.650171036606679, 45.569391241357756 ] } },
{ "type": "Feature", "properties": { "point_type": "destination", "points_str": "45.532245, -122.506236" }, "geometry": { "type": "Point", "coordinates": [ -122.506236232898445, 45.532245362449402 ] } }
]
}
