{
"type": "FeatureCollection",
"name": "origin_destination_points",
"crs": { "type": "name", "properties": { "name": "urn:ogc:def:crs:OGC:1.3:CRS84" } },
"features": [
{ "type": "Feature", "properties": { "point_type": "origin", "points_str": "45.420111, -122.647571" }, "geometry": { "type": "Point", "coordinates": [ -122.647570879258268, 45.420110513731316 ] } },
{ "type": "Feature", "properties": { "point_type": "destination", "points_str": "45.39439, -122.418182" }, "geometry": { "type": "Point", "coordinates": [ -122.418181531015236, 45.394389788801064 ] } }
]
}
