{
"type": "FeatureCollection",
"name": "origin_destination_points",
"crs": { "type": "name", "properties": { "name": "urn:ogc:def:crs:OGC:1.3:CRS84" } },
"features": [
{ "type": "Feature", "properties": { "point_type": "origin", "points_str": "45.564273, -122.671748" }, "geometry": { "type": "Point", "coordinates": [ -122.671748011102721, 45.564272581025804 ] } },
{ "type": "Feature", "properties": { "point_type": "destination", "points_str": "45.528933, -122.686334" }, "geometry": { "type": "Point", "coordinates": [ -122.686334095166004, 45.528932961508033 ] } }
]
}
