{
"type": "FeatureCollection",
"crs": { "type": "name", "properties": { "name": "urn:ogc:def:crs:OGC:1.3:CRS84" } },
"features": [
{ "type": "Feature", "properties": { "point_type": "origin", "points_str": "45.561226, -122.856088" }, "geometry": { "type": "Point", "coordinates": [ -122.856088227857938, 45.561226361263408 ] } },
{ "type": "Feature", "properties": { "point_type": "destination", "points_str": "45.484312, -122.849338" }, "geometry": { "type": "Point", "coordinates": [ -122.849338220231061, 45.484312116068438 ] } }
]
}
