{
"type": "FeatureCollection",
"crs": { "type": "name", "properties": { "name": "urn:ogc:def:crs:OGC:1.3:CRS84" } },
"features": [
{ "type": "Feature", "properties": { "point_type": "origin", "points_str": "45.53036, -122.901292" }, "geometry": { "type": "Point", "coordinates": [ -122.901292208386337, 45.530359778583168 ] } },
{ "type": "Feature", "properties": { "point_type": "destination", "points_str": "45.448596, -122.733418" }, "geometry": { "type": "Point", "coordinates": [ -122.733417845775563, 45.448595845302918 ] } }
]
}
