{
"type": "FeatureCollection",
"name": "origin_destination_points",
"crs": { "type": "name", "properties": { "name": "urn:ogc:def:crs:OGC:1.3:CRS84" } },
"features": [
{ "type": "Feature", "properties": { "point_type": "origin", "points_str": "45.550934, -122.681155" }, "geometry": { "type": "Point", "coordinates": [ -122.681155230705926, 45.550934447832994 ] } },
{ "type": "Feature", "properties": { "point_type": "destination", "points_str": "45.525333, -122.673221" }, "geometry": { "type": "Point", "coordinates": [ -122.673221069627218, 45.525332967651437 ] } }
]
}
