{
"type": "FeatureCollection",
"name": "origin_destination_points",
"crs": { "type": "name", "properties": { "name": "urn:ogc:def:crs:OGC:1.3:CRS84" } },
"features": [
{ "type": "Feature", "properties": { "point_type": "origin", "points_str": "45.51799, -123.067002" }, "geometry": { "type": "Point", "coordinates": [ -123.067001815390128, 45.517990081238956 ] } },
{ "type": "Feature", "properties": { "point_type": "destination", "points_str": "45.521988, -123.115175" }, "geometry": { "type": "Point", "coordinates": [ -123.11517490345075, 45.521988178394416 ] } }
]
}
