{
"type": "FeatureCollection",
"name": "origin_destination_points",
"crs": { "type": "name", "properties": { "name": "urn:ogc:def:crs:OGC:1.3:CRS84" } },
"features": [
{ "type": "Feature", "properties": { "point_type": "origin", "points_str": "45.557667, -122.638989" }, "geometry": { "type": "Point", "coordinates": [ -122.63898850849489, 45.557666561516506 ] } },
{ "type": "Feature", "properties": { "point_type": "destination", "points_str": "45.564141, -122.601649" }, "geometry": { "type": "Point", "coordinates": [ -122.601648963716826, 45.564141427475008 ] } }
]
}
