{
"type": "FeatureCollection",
"crs": { "type": "name", "properties": { "name": "urn:ogc:def:crs:OGC:1.3:CRS84" } },
"features": [
{ "type": "Feature", "properties": { "point_type": "origin", "points_str": "45.51035, -122.695131" }, "geometry": { "type": "Point", "coordinates": [ -122.695131439098404, 45.51035010338574 ] } },
{ "type": "Feature", "properties": { "point_type": "destination", "points_str": "45.533877, -122.437787" }, "geometry": { "type": "Point", "coordinates": [ -122.437787256472575, 45.533877352360939 ] } }
]
}
