{
"type": "FeatureCollection",
"crs": { "type": "name", "properties": { "name": "urn:ogc:def:crs:OGC:1.3:CRS84" } },
"features": [
{ "type": "Feature", "properties": { "point_type": "origin", "points_str": "45.350732, -122.611401" }, "geometry": { "type": "Point", "coordinates": [ -122.611401144700835, 45.350732379670099 ] } },
{ "type": "Feature", "properties": { "point_type": "destination", "points_str": "45.389523, -122.583626" }, "geometry": { "type": "Point", "coordinates": [ -122.583626365861107, 45.389522762499354 ] } }
]
}
