{
"type": "FeatureCollection",
"name": "origin_destination_points",
"crs": { "type": "name", "properties": { "name": "urn:ogc:def:crs:OGC:1.3:CRS84" } },
"features": [
{ "type": "Feature", "properties": { "point_type": "origin", "points_str": "45.513211, -122.970414" }, "geometry": { "type": "Point", "coordinates": [ -122.970414339845064, 45.513211494027203 ] } },
{ "type": "Feature", "properties": { "point_type": "destination", "points_str": "45.533681, -122.864034" }, "geometry": { "type": "Point", "coordinates": [ -122.864034174517045, 45.533680543242554 ] } }
]
}
