{
"type": "FeatureCollection",
"crs": { "type": "name", "properties": { "name": "urn:ogc:def:crs:OGC:1.3:CRS84" } },
"features": [
{ "type": "Feature", "properties": { "point_type": "origin", "points_str": "45.465915, -122.717028" }, "geometry": { "type": "Point", "coordinates": [ -122.717028023999632, 45.465914707971258 ] } },
{ "type": "Feature", "properties": { "point_type": "destination", "points_str": "45.540476, -122.664144" }, "geometry": { "type": "Point", "coordinates": [ -122.664143776428531, 45.540475782230011 ] } }
]
}
