{
"type": "FeatureCollection",
"name": "origin_destination_points",
"crs": { "type": "name", "properties": { "name": "urn:ogc:def:crs:OGC:1.3:CRS84" } },
"features": [
{ "type": "Feature", "properties": { "point_type": "origin", "points_str": "45.455425, -122.771268" }, "geometry": { "type": "Point", "coordinates": [ -122.771268155923963, 45.455424915364858 ] } },
{ "type": "Feature", "properties": { "point_type": "destination", "points_str": "45.468098, -122.718133" }, "geometry": { "type": "Point", "coordinates": [ -122.718133196519091, 45.468097503913562 ] } }
]
}
