{
"type": "FeatureCollection",
"name": "origin_destination_points",
"crs": { "type": "name", "properties": { "name": "urn:ogc:def:crs:OGC:1.3:CRS84" } },
"features": [
{ "type": "Feature", "properties": { "point_type": "origin", "points_str": "45.485377, -122.766197" }, "geometry": { "type": "Point", "coordinates": [ -122.766197484957843, 45.485376730532835 ] } },
{ "type": "Feature", "properties": { "point_type": "destination", "points_str": "45.5247, -122.647301" }, "geometry": { "type": "Point", "coordinates": [ -122.647300986951862, 45.524700322516416 ] } }
]
}
