{
"type": "FeatureCollection",
"name": "origin_destination_points",
"crs": { "type": "name", "properties": { "name": "urn:ogc:def:crs:OGC:1.3:CRS84" } },
"features": [
{ "type": "Feature", "properties": { "point_type": "origin", "points_str": "45.528006, -122.56564" }, "geometry": { "type": "Point", "coordinates": [ -122.565640185833473, 45.528005778066806 ] } },
{ "type": "Feature", "properties": { "point_type": "destination", "points_str": "45.556911, -122.566415" }, "geometry": { "type": "Point", "coordinates": [ -122.566414805133348, 45.556910791069349 ] } }
]
}
