{
"type": "FeatureCollection",
"crs": { "type": "name", "properties": { "name": "urn:ogc:def:crs:OGC:1.3:CRS84" } },
"features": [
{ "type": "Feature", "properties": { "point_type": "origin", "points_str": "45.453003, -122.577285" }, "geometry": { "type": "Point", "coordinates": [ -122.577284508198701, 45.45300330516573 ] } },
{ "type": "Feature", "properties": { "point_type": "destination", "points_str": "45.419642, -122.53776" }, "geometry": { "type": "Point", "coordinates": [ -122.537760014783231, 45.419642256055766 ] } }
]
}
