{
"type": "FeatureCollection",
"name": "origin_destination_points",
"crs": { "type": "name", "properties": { "name": "urn:ogc:def:crs:OGC:1.3:CRS84" } },
"features": [
{ "type": "Feature", "properties": { "point_type": "origin", "points_str": "45.440522, -122.578921" }, "geometry": { "type": "Point", "coordinates": [ -122.578920784164325, 45.440521771871254 ] } },
{ "type": "Feature", "properties": { "point_type": "destination", "points_str": "45.324771, -122.564144" }, "geometry": { "type": "Point", "coordinates": [ -122.564143949660604, 45.32477126941729 ] } }
]
}
