{
"type": "FeatureCollection",
"name": "origin_destination_points",
"crs": { "type": "name", "properties": { "name": "urn:ogc:def:crs:OGC:1.3:CRS84" } },
"features": [
{ "type": "Feature", "properties": { "point_type": "origin", "points_str": "45.499497, -122.687935" }, "geometry": { "type": "Point", "coordinates": [ -122.687935461992979, 45.499497453642618 ] } },
{ "type": "Feature", "properties": { "point_type": "destination", "points_str": "45.503712, -122.66043" }, "geometry": { "type": "Point", "coordinates": [ -122.660429863735033, 45.503712054243302 ] } }
]
}
