{
"type": "FeatureCollection",
"crs": { "type": "name", "properties": { "name": "urn:ogc:def:crs:OGC:1.3:CRS84" } },
"features": [
{ "type": "Feature", "properties": { "point_type": "origin", "points_str": "45.507483, -122.800413" }, "geometry": { "type": "Point", "coordinates": [ -122.800412876771446, 45.507482615458343 ] } },
{ "type": "Feature", "properties": { "point_type": "destination", "points_str": "45.478339, -122.795852" }, "geometry": { "type": "Point", "coordinates": [ -122.795852338034265, 45.478338804949935 ] } }
]
}
