{
"type": "FeatureCollection",
"crs": { "type": "name", "properties": { "name": "urn:ogc:def:crs:OGC:1.3:CRS84" } },
"features": [
{ "type": "Feature", "properties": { "point_type": "origin", "points_str": "45.438948, -122.579878" }, "geometry": { "type": "Point", "coordinates": [ -122.579878441782597, 45.438947546408869 ] } },
{ "type": "Feature", "properties": { "point_type": "destination", "points_str": "45.333232, -122.579681" }, "geometry": { "type": "Point", "coordinates": [ -122.579681278446515, 45.333232358460663 ] } }
]
}
