{
"type": "FeatureCollection",
"name": "origin_destination_points",
"crs": { "type": "name", "properties": { "name": "urn:ogc:def:crs:OGC:1.3:CRS84" } },
"features": [
{ "type": "Feature", "properties": { "point_type": "origin", "points_str": "45.520729, -122.478122" }, "geometry": { "type": "Point", "coordinates": [ -122.478121582880888, 45.520728678877113 ] } },
{ "type": "Feature", "properties": { "point_type": "destination", "points_str": "45.557118, -122.846787" }, "geometry": { "type": "Point", "coordinates": [ -122.846786828323104, 45.557117636776162 ] } }
]
}
