{
"type": "FeatureCollection",
"name": "origin_destination_points",
"crs": { "type": "name", "properties": { "name": "urn:ogc:def:crs:OGC:1.3:CRS84" } },
"features": [
{ "type": "Feature", "properties": { "point_type": "origin", "points_str": "45.557677, -122.573914" }, "geometry": { "type": "Point", "coordinates": [ -122.573913581493287, 45.557676575978221 ] } },
{ "type": "Feature", "properties": { "point_type": "destination", "points_str": "45.527174, -122.584001" }, "geometry": { "type": "Point", "coordinates": [ -122.584001383534186, 45.527173847223708 ] } }
]
}
