{
"type": "FeatureCollection",
"name": "origin_destination_points",
"crs": { "type": "name", "properties": { "name": "urn:ogc:def:crs:OGC:1.3:CRS84" } },
"features": [
{ "type": "Feature", "properties": { "point_type": "origin", "points_str": "45.380349, -122.591393" }, "geometry": { "type": "Point", "coordinates": [ -122.591392559367932, 45.380348634261715 ] } },
{ "type": "Feature", "properties": { "point_type": "destination", "points_str": "45.420529, -122.575242" }, "geometry": { "type": "Point", "coordinates": [ -122.575242046208515, 45.420528784872623 ] } }
]
}
