{
"type": "FeatureCollection",
"name": "origin_destination_points",
"crs": { "type": "name", "properties": { "name": "urn:ogc:def:crs:OGC:1.3:CRS84" } },
"features": [
{ "type": "Feature", "properties": { "point_type": "origin", "points_str": "45.461669, -122.643349" }, "geometry": { "type": "Point", "coordinates": [ -122.643348557305856, 45.461669234765708 ] } },
{ "type": "Feature", "properties": { "point_type": "destination", "points_str": "45.499847, -122.519153" }, "geometry": { "type": "Point", "coordinates": [ -122.519152724741843, 45.499847364127163 ] } }
]
}
