{
"type": "FeatureCollection",
"name": "origin_destination_points",
"crs": { "type": "name", "properties": { "name": "urn:ogc:def:crs:OGC:1.3:CRS84" } },
"features": [
{ "type": "Feature", "properties": { "point_type": "origin", "points_str": "45.356331, -122.356638" }, "geometry": { "type": "Point", "coordinates": [ -122.356638350234547, 45.356331152004245 ] } },
{ "type": "Feature", "properties": { "point_type": "destination", "points_str": "45.453899, -122.593628" }, "geometry": { "type": "Point", "coordinates": [ -122.593627883991488, 45.45389939048686 ] } }
]
}
