{
"type": "FeatureCollection",
"crs": { "type": "name", "properties": { "name": "urn:ogc:def:crs:OGC:1.3:CRS84" } },
"features": [
{ "type": "Feature", "properties": { "point_type": "origin", "points_str": "45.528879, -122.945127" }, "geometry": { "type": "Point", "coordinates": [ -122.945127488010272, 45.528878995176669 ] } },
{ "type": "Feature", "properties": { "point_type": "destination", "points_str": "45.477679, -122.879502" }, "geometry": { "type": "Point", "coordinates": [ -122.879502167704445, 45.477679359140993 ] } }
]
}
