{
"type": "FeatureCollection",
"name": "origin_destination_points",
"crs": { "type": "name", "properties": { "name": "urn:ogc:def:crs:OGC:1.3:CRS84" } },
"features": [
{ "type": "Feature", "properties": { "point_type": "origin", "points_str": "45.442282, -122.741195" }, "geometry": { "type": "Point", "coordinates": [ -122.741195321287591, 45.442282433477374 ] } },
{ "type": "Feature", "properties": { "point_type": "destination", "points_str": "45.517518, -122.682756" }, "geometry": { "type": "Point", "coordinates": [ -122.682755551406046, 45.517518409948416 ] } }
]
}
