{
"type": "FeatureCollection",
"crs": { "type": "name", "properties": { "name": "urn:ogc:def:crs:OGC:1.3:CRS84" } },
"features": [
{ "type": "Feature", "properties": { "point_type": "origin", "points_str": "45.490759, -122.575541" }, "geometry": { "type": "Point", "coordinates": [ -122.575540755623464, 45.490758877932059 ] } },
{ "type": "Feature", "properties": { "point_type": "destination", "points_str": "45.508362, -122.629978" }, "geometry": { "type": "Point", "coordinates": [ -122.629978318236624, 45.508361689687277 ] } }
]
}
