{
"type": "FeatureCollection",
"crs": { "type": "name", "properties": { "name": "urn:ogc:def:crs:OGC:1.3:CRS84" } },
"features": [
{ "type": "Feature", "properties": { "point_type": "origin", "points_str": "45.409393, -122.645276" }, "geometry": { "type": "Point", "coordinates": [ -122.645275841952611, 45.409393103515576 ] } },
{ "type": "Feature", "properties": { "point_type": "destination", "points_str": "45.342911, -122.659205" }, "geometry": { "type": "Point", "coordinates": [ -122.659204603274901, 45.342910835918005 ] } }
]
}
