{
"type": "FeatureCollection",
"name": "origin_destination_points",
"crs": { "type": "name", "properties": { "name": "urn:ogc:def:crs:OGC:1.3:CRS84" } },
"features": [
{ "type": "Feature", "properties": { "point_type": "origin", "points_str": "45.535379, -122.384438" }, "geometry": { "type": "Point", "coordinates": [ -122.384438206007388, 45.535378595663694 ] } },
{ "type": "Feature", "properties": { "point_type": "destination", "points_str": "45.510703, -122.781141" }, "geometry": { "type": "Point", "coordinates": [ -122.781141393211144, 45.510703442706664 ] } }
]
}
