{
"type": "FeatureCollection",
"crs": { "type": "name", "properties": { "name": "urn:ogc:def:crs:OGC:1.3:CRS84" } },
"features": [
{ "type": "Feature", "properties": { "point_type": "origin", "points_str": "45.386894, -122.453308" }, "geometry": { "type": "Point", "coordinates": [ -122.453308324376977, 45.386894170344505 ] } },
{ "type": "Feature", "properties": { "point_type": "destination", "points_str": "45.428787, -122.637789" }, "geometry": { "type": "Point", "coordinates": [ -122.637789306658362, 45.428787014191109 ] } }
]
}
