{
"type": "FeatureCollection",
"name": "origin_destination_points",
"crs": { "type": "name", "properties": { "name": "urn:ogc:def:crs:OGC:1.3:CRS84" } },
"features": [
{ "type": "Feature", "properties": { "point_type": "origin", "points_str": "45.525612, -122.587607" }, "geometry": { "type": "Point", "coordinates": [ -122.587606595275602, 45.525611870161313 ] } },
{ "type": "Feature", "properties": { "point_type": "destination", "points_str": "45.555158, -122.620641" }, "geometry": { "type": "Point", "coordinates": [ -122.620640796895799, 45.555157794105263 ] } }
]
}
