{
"type": "FeatureCollection",
"name": "origin_destination_points",
"crs": { "type": "name", "properties": { "name": "urn:ogc:def:crs:OGC:1.3:CRS84" } },
"features": [
{ "type": "Feature", "properties": { "point_type": "origin", "points_str": "45.510774, -122.534532" }, "geometry": { "type": "Point", "coordinates": [ -122.534531560391514, 45.510773525021271 ] } },
{ "type": "Feature", "properties": { "point_type": "destination", "points_str": "45.520205, -122.607364" }, "geometry": { "type": "Point", "coordinates": [ -122.60736360632167, 45.520205292320554 ] } }
]
}
