{
"type": "FeatureCollection",
"name": "origin_destination_points",
"crs": { "type": "name", "properties": { "name": "urn:ogc:def:crs:OGC:1.3:CRS84" } },
"features": [
{ "type": "Feature", "properties": { "point_type": "origin", "points_str": "45.557257, -122.634583" }, "geometry": { "type": "Point", "coordinates": [ -122.634583152267183, 45.55725710117396 ] } },
{ "type": "Feature", "properties": { "point_type": "destination", "points_str": "45.523169, -122.515693" }, "geometry": { "type": "Point", "coordinates": [ -122.515692645860639, 45.523169435294683 ] } }
]
}
