{
"type": "FeatureCollection",
"name": "origin_destination_points",
"crs": { "type": "name", "properties": { "name": "urn:ogc:def:crs:OGC:1.3:CRS84" } },
"features": [
{ "type": "Feature", "properties": { "point_type": "origin", "points_str": "45.577257, -122.701082" }, "geometry": { "type": "Point", "coordinates": [ -122.701081951967495, 45.577257129592439 ] } },
{ "type": "Feature", "properties": { "point_type": "destination", "points_str": "45.337343, -122.604085" }, "geometry": { "type": "Point", "coordinates": [ -122.604084764559602, 45.337342668083032 ] } }
]
}
