{
"type": "FeatureCollection",
"name": "origin_destination_points",
"crs": { "type": "name", "properties": { "name": "urn:ogc:def:crs:OGC:1.3:CRS84" } },
"features": [
{ "type": "Feature", "properties": { "point_type": "origin", "points_str": "45.474986, -122.695334" }, "geometry": { "type": "Point", "coordinates": [ -122.695333838129073, 45.474986088762897 ] } },
{ "type": "Feature", "properties": { "point_type": "destination", "points_str": "45.461944, -122.759137" }, "geometry": { "type": "Point", "coordinates": [ -122.759136526232837, 45.461943779196183 ] } }
]
}
