{
"type": "FeatureCollection",
"name": "origin_destination_points",
"crs": { "type": "name", "properties": { "name": "urn:ogc:def:crs:OGC:1.3:CRS84" } },
"features": [
{ "type": "Feature", "properties": { "point_type": "origin", "points_str": "45.524454, -122.704778" }, "geometry": { "type": "Point", "coordinates": [ -122.704777937454537, 45.524453728285955 ] } },
{ "type": "Feature", "properties": { "point_type": "destination", "points_str": "45.525416, -122.609888" }, "geometry": { "type": "Point", "coordinates": [ -122.609887748127136, 45.525416008012328 ] } }
]
}
