{
"type": "FeatureCollection",
"name": "origin_destination_points",
"crs": { "type": "name", "properties": { "name": "urn:ogc:def:crs:OGC:1.3:CRS84" } },
"features": [
{ "type": "Feature", "properties": { "point_type": "origin", "points_str": "45.572325, -122.702221" }, "geometry": { "type": "Point", "coordinates": [ -122.702221220292671, 45.572324721588629 ] } },
{ "type": "Feature", "properties": { "point_type": "destination", "points_str": "45.463282, -122.673416" }, "geometry": { "type": "Point", "coordinates": [ -122.673416084532477, 45.463281957418957 ] } }
]
}
