{
"type": "FeatureCollection",
"crs": { "type": "name", "properties": { "name": "urn:ogc:def:crs:OGC:1.3:CRS84" } },
"features": [
{ "type": "Feature", "properties": { "point_type": "origin", "points_str": "45.383833, -122.605982" }, "geometry": { "type": "Point", "coordinates": [ -122.605981574316999, 45.383832643345869 ] } },
{ "type": "Feature", "properties": { "point_type": "destination", "points_str": "45.396301, -122.647764" }, "geometry": { "type": "Point", "coordinates": [ -122.647764154159361, 45.396300945083965 ] } }
]
}
