{
"type": "FeatureCollection",
"name": "origin_destination_points",
"crs": { "type": "name", "properties": { "name": "urn:ogc:def:crs:OGC:1.3:CRS84" } },
"features": [
{ "type": "Feature", "properties": { "point_type": "origin", "points_str": "45.345359, -122.64313" }, "geometry": { "type": "Point", "coordinates": [ -122.643129633981857, 45.345358949845846 ] } },
{ "type": "Feature", "properties": { "point_type": "destination", "points_str": "45.483856, -122.862302" }, "geometry": { "type": "Point", "coordinates": [ -122.862301927093171, 45.483856037743038 ] } }
]
}
