{
"type": "FeatureCollection",
"name": "origin_destination_points",
"crs": { "type": "name", "properties": { "name": "urn:ogc:def:crs:OGC:1.3:CRS84" } },
"features": [
{ "type": "Feature", "properties": { "point_type": "origin", "points_str": "45.527071, -122.657894" }, "geometry": { "type": "Point", "coordinates": [ -122.657893739256039, 45.527071109166577 ] } },
{ "type": "Feature", "properties": { "point_type": "destination", "points_str": "45.514587, -122.60106" }, "geometry": { "type": "Point", "coordinates": [ -122.601059650797154, 45.514586635566417 ] } }
]
}
