{
"type": "FeatureCollection",
"name": "origin_destination_points",
"crs": { "type": "name", "properties": { "name": "urn:ogc:def:crs:OGC:1.3:CRS84" } },
"features": [
{ "type": "Feature", "properties": { "point_type": "origin", "points_str": "45.483042, -122.756691" }, "geometry": { "type": "Point", "coordinates": [ -122.75669054208953, 45.483042477218653 ] } },
{ "type": "Feature", "properties": { "point_type": "destination", "points_str": "45.491722, -122.481417" }, "geometry": { "type": "Point", "coordinates": [ -122.481416766921541, 45.491722250069152 ] } }
]
}
