{
"type": "FeatureCollection",
"crs": { "type": "name", "properties": { "name": "urn:ogc:def:crs:OGC:1.3:CRS84" } },
"features": [
{ "type": "Feature", "properties": { "point_type": "origin", "points_str": "45.464804, -122.610893" }, "geometry": { "type": "Point", "coordinates": [ -122.610893179951788, 45.464803536818074 ] } },
{ "type": "Feature", "properties": { "point_type": "destination", "points_str": "45.390399, -122.408759" }, "geometry": { "type": "Point", "coordinates": [ -122.408758988281591, 45.390399388865752 ] } }
]
}
