{
"type": "FeatureCollection",
"name": "origin_destination_points",
"crs": { "type": "name", "properties": { "name": "urn:ogc:def:crs:OGC:1.3:CRS84" } },
"features": [
{ "type": "Feature", "properties": { "point_type": "origin", "points_str": "45.442784, -122.736809" }, "geometry": { "type": "Point", "coordinates": [ -122.736809143935929, 45.442784262316493 ] } },
{ "type": "Feature", "properties": { "point_type": "destination", "points_str": "45.528277, -122.598697" }, "geometry": { "type": "Point", "coordinates": [ -122.598696731639876, 45.528276938950171 ] } }
]
}
