{
"type": "FeatureCollection",
"name": "origin_destination_points",
"crs": { "type": "name", "properties": { "name": "urn:ogc:def:crs:OGC:1.3:CRS84" } },
"features": [
{ "type": "Feature", "properties": { "point_type": "origin", "points_str": "45.508423, -122.640673" }, "geometry": { "type": "Point", "coordinates": [ -122.640672646760521, 45.50842325100048 ] } },
{ "type": "Feature", "properties": { "point_type": "destination", "points_str": "45.59317, -122.762688" }, "geometry": { "type": "Point", "coordinates": [ -122.762687941859937, 45.593169975091811 ] } }
]
}
