{
"type": "FeatureCollection",
"crs": { "type": "name", "properties": { "name": "urn:ogc:def:crs:OGC:1.3:CRS84" } },
"features": [
{ "type": "Feature", "properties": { "point_type": "origin", "points_str": "45.547256, -122.395369" }, "geometry": { "type": "Point", "coordinates": [ -122.395369049075882, 45.54725558425627 ] } },
{ "type": "Feature", "properties": { "point_type": "destination", "points_str": "45.52984, -122.553745" }, "geometry": { "type": "Point", "coordinates": [ -122.553745280179086, 45.529840132365273 ] } }
]
}
