{
"type": "FeatureCollection",
"name": "origin_destination_points",
"crs": { "type": "name", "properties": { "name": "urn:ogc:def:crs:OGC:1.3:CRS84" } },
"features": [
{ "type": "Feature", "properties": { "point_type": "origin", "points_str": "45.498146, -122.427727" }, "geometry": { "type": "Point", "coordinates": [ -122.427727365096217, 45.498146005839672 ] } },
{ "type": "Feature", "properties": { "point_type": "destination", "points_str": "45.494636, -122.569884" }, "geometry": { "type": "Point", "coordinates": [ -122.569883517241578, 45.494635754157237 ] } }
]
}
