{
"type": "FeatureCollection",
"name": "origin_destination_points",
"crs": { "type": "name", "properties": { "name": "urn:ogc:def:crs:OGC:1.3:CRS84" } },
"features": [
{ "type": "Feature", "properties": { "point_type": "origin", "points_str": "45.585474, -122.691871" }, "geometry": { "type": "Point", "coordinates": [ -122.691871294171278, 45.585474436407821 ] } },
{ "type": "Feature", "properties": { "point_type": "destination", "points_str": "45.573463, -122.639279" }, "geometry": { "type": "Point", "coordinates": [ -122.639279466856038, 45.573462857263607 ] } }
]
}
