{
"type": "FeatureCollection",
"crs": { "type": "name", "properties": { "name": "urn:ogc:def:crs:OGC:1.3:CRS84" } },
"features": [
{ "type": "Feature", "properties": { "point_type": "origin", "points_str": "45.521637, -122.735047" }, "geometry": { "type": "Point", "coordinates": [ -122.735046512322981, 45.521637202250098 ] } },
{ "type": "Feature", "properties": { "point_type": "destination", "points_str": "45.484573, -122.842984" }, "geometry": { "type": "Point", "coordinates": [ -122.842983785576095, 45.484572699421669 ] } }
]
}
