{
"type": "FeatureCollection",
"name": "origin_destination_points",
"crs": { "type": "name", "properties": { "name": "urn:ogc:def:crs:OGC:1.3:CRS84" } },
"features": [
{ "type": "Feature", "properties": { "point_type": "origin", "points_str": "45.529114, -122.642593" }, "geometry": { "type": "Point", "coordinates": [ -122.642593288876228, 45.529113568605766 ] } },
{ "type": "Feature", "properties": { "point_type": "destination", "points_str": "45.611206, -122.795082" }, "geometry": { "type": "Point", "coordinates": [ -122.795082365728945, 45.611205689757831 ] } }
]
}
