{
"type": "FeatureCollection",
"name": "origin_destination_points",
"crs": { "type": "name", "properties": { "name": "urn:ogc:def:crs:OGC:1.3:CRS84" } },
"features": [
{ "type": "Feature", "properties": { "point_type": "origin", "points_str": "45.456124, -122.68501" }, "geometry": { "type": "Point", "coordinates": [ -122.685010338081497, 45.456123640610762 ] } },
{ "type": "Feature", "properties": { "point_type": "destination", "points_str": "45.42521, -122.663392" }, "geometry": { "type": "Point", "coordinates": [ -122.663391877747856, 45.425209974173015 ] } }
]
}
