{
"type": "FeatureCollection",
"crs": { "type": "name", "properties": { "name": "urn:ogc:def:crs:OGC:1.3:CRS84" } },
"features": [
{ "type": "Feature", "properties": { "point_type": "origin", "points_str": "45.34295, -122.772118" }, "geometry": { "type": "Point", "coordinates": [ -122.77211793709418, 45.342950454789168 ] } },
{ "type": "Feature", "properties": { "point_type": "destination", "points_str": "45.583866, -122.656607" }, "geometry": { "type": "Point", "coordinates": [ -122.656606747973782, 45.583866382708116 ] } }
]
}
