{
"type": "FeatureCollection",
"crs": { "type": "name", "properties": { "name": "urn:ogc:def:crs:OGC:1.3:CRS84" } },
"features": [
{ "type": "Feature", "properties": { "point_type": "origin", "points_str": "45.542739, -122.462741" }, "geometry": { "type": "Point", "coordinates": [ -122.462740807907622, 45.542739298112451 ] } },
{ "type": "Feature", "properties": { "point_type": "destination", "points_str": "45.477185, -122.370489" }, "geometry": { "type": "Point", "coordinates": [ -122.370489120150438, 45.477185187421654 ] } }
]
}
