{
"type": "FeatureCollection",
"crs": { "type": "name", "properties": { "name": "urn:ogc:def:crs:OGC:1.3:CRS84" } },
"features": [
{ "type": "Feature", "properties": { "point_type": "origin", "points_str": "45.522623, -122.639267" }, "geometry": { "type": "Point", "coordinates": [ -122.63926749898647, 45.522623039278869 ] } },
{ "type": "Feature", "properties": { "point_type": "destination", "points_str": "45.543912, -122.643846" }, "geometry": { "type": "Point", "coordinates": [ -122.643846153050347, 45.543911727889608 ] } }
]
}
