{
"type": "FeatureCollection",
"name": "origin_destination_points",
"crs": { "type": "name", "properties": { "name": "urn:ogc:def:crs:OGC:1.3:CRS84" } },
"features": [
{ "type": "Feature", "properties": { "point_type": "origin", "points_str": "45.518597, -122.527256" }, "geometry": { "type": "Point", "coordinates": [ -122.527256269175709, 45.51859717895114 ] } },
{ "type": "Feature", "properties": { "point_type": "destination", "points_str": "45.528723, -122.473426" }, "geometry": { "type": "Point", "coordinates": [ -122.4734261675233, 45.52872302199745 ] } }
]
}
