{
"type": "FeatureCollection",
"name": "origin_destination_points",
"crs": { "type": "name", "properties": { "name": "urn:ogc:def:crs:OGC:1.3:CRS84" } },
"features": [
{ "type": "Feature", "properties": { "point_type": "origin", "points_str": "45.497091, -122.873063" }, "geometry": { "type": "Point", "coordinates": [ -122.873062732545392, 45.497090808058438 ] } },
{ "type": "Feature", "properties": { "point_type": "destination", "points_str": "45.482309, -122.870191" }, "geometry": { "type": "Point", "coordinates": [ -122.870190570863258, 45.482309202990621 ] } }
]
}
