{
"type": "FeatureCollection",
"crs": { "type": "name", "properties": { "name": "urn:ogc:def:crs:OGC:1.3:CRS84" } },
"features": [
{ "type": "Feature", "properties": { "point_type": "origin", "points_str": "45.507867, -122.792951" }, "geometry": { "type": "Point", "coordinates": [ -122.792950573462562, 45.507867282693972 ] } },
{ "type": "Feature", "properties": { "point_type": "destination", "points_str": "45.387515, -122.752662" }, "geometry": { "type": "Point", "coordinates": [ -122.752661550017635, 45.387515408217567 ] } }
]
}
