{
"type": "FeatureCollection",
"name": "origin_destination_points",
"crs": { "type": "name", "properties": { "name": "urn:ogc:def:crs:OGC:1.3:CRS84" } },
"features": [
{ "type": "Feature", "properties": { "point_type": "origin", "points_str": "45.523447, -122.650833" }, "geometry": { "type": "Point", "coordinates": [ -122.650833440601716, 45.523446946097266 ] } },
{ "type": "Feature", "properties": { "point_type": "destination", "points_str": "45.555657, -122.666308" }, "geometry": { "type": "Point", "coordinates": [ -122.666307933217652, 45.555656656668148 ] } }
]
}
