{
"type": "FeatureCollection",
"crs": { "type": "name", "properties": { "name": "urn:ogc:def:crs:OGC:1.3:CRS84" } },
"features": [
{ "type": "Feature", "properties": { "point_type": "origin", "points_str": "45.528673, -122.917692" }, "geometry": { "type": "Point", "coordinates": [ -122.917692378486635, 45.528673119683972 ] } },
{ "type": "Feature", "properties": { "point_type": "destination", "points_str": "45.522825, -122.452871" }, "geometry": { "type": "Point", "coordinates": [ -122.452870730791076, 45.522824943933287 ] } }
]
}
