{
"type": "FeatureCollection",
"crs": { "type": "name", "properties": { "name": "urn:ogc:def:crs:OGC:1.3:CRS84" } },
"features": [
{ "type": "Feature", "properties": { "point_type": "origin", "points_str": "45.519567, -122.640127" }, "geometry": { "type": "Point", "coordinates": [ -122.640127084030254, 45.519566700436208 ] } },
{ "type": "Feature", "properties": { "point_type": "destination", "points_str": "45.525274, -122.801714" }, "geometry": { "type": "Point", "coordinates": [ -122.801714497551316, 45.525273904488998 ] } }
]
}
