{
"type": "FeatureCollection",
"crs": { "type": "name", "properties": { "name": "urn:ogc:def:crs:OGC:1.3:CRS84" } },
"features": [
{ "type": "Feature", "properties": { "point_type": "origin", "points_str": "45.426339, -122.491713" }, "geometry": { "type": "Point", "coordinates": [ -122.491712751852432, 45.426338788340267 ] } },
{ "type": "Feature", "properties": { "point_type": "destination", "points_str": "45.359127, -122.606677" }, "geometry": { "type": "Point", "coordinates": [ -122.606677161314096, 45.359127126537494 ] } }
]
}
