{
"type": "FeatureCollection",
"name": "origin_destination_points",
"crs": { "type": "name", "properties": { "name": "urn:ogc:def:crs:OGC:1.3:CRS84" } },
"features": [
{ "type": "Feature", "properties": { "point_type": "origin", "points_str": "45.432172, -122.554239" }, "geometry": { "type": "Point", "coordinates": [ -122.554239349980989, 45.432172297282861 ] } },
{ "type": "Feature", "properties": { "point_type": "destination", "points_str": "45.561429, -122.5942" }, "geometry": { "type": "Point", "coordinates": [ -122.594200082486822, 45.561429490335783 ] } }
]
}
