{
"type": "FeatureCollection",
"name": "origin_destination_points",
"crs": { "type": "name", "properties": { "name": "urn:ogc:def:crs:OGC:1.3:CRS84" } },
"features": [
{ "type": "Feature", "properties": { "point_type": "origin", "points_str": "45.52014, -122.682456" }, "geometry": { "type": "Point", "coordinates": [ -122.682456355799459, 45.520140036964442 ] } },
{ "type": "Feature", "properties": { "point_type": "destination", "points_str": "45.571585, -122.642148" }, "geometry": { "type": "Point", "coordinates": [ -122.642148008917303, 45.571585252957021 ] } }
]
}
