{
"type": "FeatureCollection",
"crs": { "type": "name", "properties": { "name": "urn:ogc:def:crs:OGC:1.3:CRS84" } },
"features": [
{ "type": "Feature", "properties": { "point_type": "origin", "points_str": "45.492459, -122.846721" }, "geometry": { "type": "Point", "coordinates": [ -122.846720724023299, 45.49245916390965 ] } },
{ "type": "Feature", "properties": { "point_type": "destination", "points_str": "45.499726, -122.931471" }, "geometry": { "type": "Point", "coordinates": [ -122.931471392910311, 45.499725903082705 ] } }
]
}
