{
"type": "FeatureCollection",
"crs": { "type": "name", "properties": { "name": "urn:ogc:def:crs:OGC:1.3:CRS84" } },
"features": [
{ "type": "Feature", "properties": { "point_type": "origin", "points_str": "45.530206, -122.539102" }, "geometry": { "type": "Point", "coordinates": [ -122.539102462859447, 45.530206436496933 ] } },
{ "type": "Feature", "properties": { "point_type": "destination", "points_str": "45.52228, -122.51391" }, "geometry": { "type": "Point", "coordinates": [ -122.513909679787972, 45.522280176508652 ] } }
]
}
