{
"type": "FeatureCollection",
"name": "origin_destination_points",
"crs": { "type": "name", "properties": { "name": "urn:ogc:def:crs:OGC:1.3:CRS84" } },
"features": [
{ "type": "Feature", "properties": { "point_type": "origin", "points_str": "45.519797, -122.997027" }, "geometry": { "type": "Point", "coordinates": [ -122.997026641886833, 45.519796569660201 ] } },
{ "type": "Feature", "properties": { "point_type": "destination", "points_str": "45.379078, -122.761906" }, "geometry": { "type": "Point", "coordinates": [ -122.761905843134514, 45.379078142740667 ] } }
]
}
