{
"type": "FeatureCollection",
"name": "origin_destination_points",
"crs": { "type": "name", "properties": { "name": "urn:ogc:def:crs:OGC:1.3:CRS84" } },
"features": [
{ "type": "Feature", "properties": { "point_type": "origin", "points_str": "45.508053, -122.587867" }, "geometry": { "type": "Point", "coordinates": [ -122.587866705858005, 45.508053051365579 ] } },
{ "type": "Feature", "properties": { "point_type": "destination", "points_str": "45.439305, -122.567569" }, "geometry": { "type": "Point", "coordinates": [ -122.56756926862468, 45.439305377419593 ] } }
]
}
