{
"type": "FeatureCollection",
"crs": { "type": "name", "properties": { "name": "urn:ogc:def:crs:OGC:1.3:CRS84" } },
"features": [
{ "type": "Feature", "properties": { "point_type": "origin", "points_str": "45.592451, -122.719209" }, "geometry": { "type": "Point", "coordinates": [ -122.719208652005392, 45.592450935384868 ] } },
{ "type": "Feature", "properties": { "point_type": "destination", "points_str": "45.533028, -122.665253" }, "geometry": { "type": "Point", "coordinates": [ -122.665253235678549, 45.533028260351593 ] } }
]
}
