{
"type": "FeatureCollection",
"crs": { "type": "name", "properties": { "name": "urn:ogc:def:crs:OGC:1.3:CRS84" } },
"features": [
{ "type": "Feature", "properties": { "point_type": "origin", "points_str": "45.587626, -122.746642" }, "geometry": { "type": "Point", "coordinates": [ -122.746642299107791, 45.587625912112216 ] } },
{ "type": "Feature", "properties": { "point_type": "destination", "points_str": "45.528745, -122.92962" }, "geometry": { "type": "Point", "coordinates": [ -122.929620385035776, 45.528745411464989 ] } }
]
}
