{
"type": "FeatureCollection",
"crs": { "type": "name", "properties": { "name": "urn:ogc:def:crs:OGC:1.3:CRS84" } },
"features": [
{ "type": "Feature", "properties": { "point_type": "origin", "points_str": "45.409865, -122.499017" }, "geometry": { "type": "Point", "coordinates": [ -122.499016941797905, 45.409864876526484 ] } },
{ "type": "Feature", "properties": { "point_type": "destination", "points_str": "45.422286, -122.525135" }, "geometry": { "type": "Point", "coordinates": [ -122.525135428535378, 45.422286035975944 ] } }
]
}
