{
"type": "FeatureCollection",
"crs": { "type": "name", "properties": { "name": "urn:ogc:def:crs:OGC:1.3:CRS84" } },
"features": [
{ "type": "Feature", "properties": { "point_type": "origin", "points_str": "45.379244, -122.742609" }, "geometry": { "type": "Point", "coordinates": [ -122.742609310317221, 45.379243843895502 ] } },
{ "type": "Feature", "properties": { "point_type": "destination", "points_str": "45.488197, -122.80102" }, "geometry": { "type": "Point", "coordinates": [ -122.801019788527853, 45.488196845098052 ] } }
]
}
