{
"type": "FeatureCollection",
"crs": { "type": "name", "properties": { "name": "urn:ogc:def:crs:OGC:1.3:CRS84" } },
"features": [
{ "type": "Feature", "properties": { "point_type": "origin", "points_str": "45.521793, -122.42747" }, "geometry": { "type": "Point", "coordinates": [ -122.427470319858571, 45.521793317953559 ] } },
{ "type": "Feature", "properties": { "point_type": "destination", "points_str": "45.549832, -122.681157" }, "geometry": { "type": "Point", "coordinates": [ -122.681157427755423, 45.549832487190216 ] } }
]
}
