{
"type": "FeatureCollection",
"crs": { "type": "name", "properties": { "name": "urn:ogc:def:crs:OGC:1.3:CRS84" } },
"features": [
{ "type": "Feature", "properties": { "point_type": "origin", "points_str": "45.418544, -122.646887" }, "geometry": { "type": "Point", "coordinates": [ -122.646886618454033, 45.418544349053995 ] } },
{ "type": "Feature", "properties": { "point_type": "destination", "points_str": "45.547491, -122.667196" }, "geometry": { "type": "Point", "coordinates": [ -122.667196409198169, 45.547491309733651 ] } }
]
}
