{
"type": "FeatureCollection",
"name": "origin_destination_points",
"crs": { "type": "name", "properties": { "name": "urn:ogc:def:crs:OGC:1.3:CRS84" } },
"features": [
{ "type": "Feature", "properties": { "point_type": "origin", "points_str": "45.503897, -122.468307" }, "geometry": { "type": "Point", "coordinates": [ -122.468306570766146, 45.503896884390954 ] } },
{ "type": "Feature", "properties": { "point_type": "destination", "points_str": "45.482187, -122.613685" }, "geometry": { "type": "Point", "coordinates": [ -122.613685414957928, 45.482187002762466 ] } }
]
}
