{
"type": "FeatureCollection",
"name": "origin_destination_points",
"crs": { "type": "name", "properties": { "name": "urn:ogc:def:crs:OGC:1.3:CRS84" } },
"features": [
{ "type": "Feature", "properties": { "point_type": "origin", "points_str": "45.530361, -122.819565" }, "geometry": { "type": "Point", "coordinates": [ -122.819564901865945, 45.53036064393136 ] } },
{ "type": "Feature", "properties": { "point_type": "destination", "points_str": "45.492567, -122.809598" }, "geometry": { "type": "Point", "coordinates": [ -122.809597568692311, 45.492566681967695 ] } }
]
}
