{
"type": "FeatureCollection",
"name": "origin_destination_points",
"crs": { "type": "name", "properties": { "name": "urn:ogc:def:crs:OGC:1.3:CRS84" } },
"features": [
{ "type": "Feature", "properties": { "point_type": "origin", "points_str": "45.452094, -122.672405" }, "geometry": { "type": "Point", "coordinates": [ -122.672405230470133, 45.452094128943187 ] } },
{ "type": "Feature", "properties": { "point_type": "destination", "points_str": "45.5385, -122.702769" }, "geometry": { "type": "Point", "coordinates": [ -122.702768835457732, 45.538499768869976 ] } }
]
}
