{
"type": "FeatureCollection",
"name": "origin_destination_points",
"crs": { "type": "name", "properties": { "name": "urn:ogc:def:crs:OGC:1.3:CRS84" } },
"features": [
{ "type": "Feature", "properties": { "point_type": "origin", "points_str": "45.495758, -122.450589" }, "geometry": { "type": "Point", "coordinates": [ -122.450589400920833, 45.49575768429596 ] } },
{ "type": "Feature", "properties": { "point_type": "destination", "points_str": "45.528893, -122.94576" }, "geometry": { "type": "Point", "coordinates": [ -122.945759701075715, 45.528893450410827 ] } }
]
}
