{
"type": "FeatureCollection",
"name": "origin_destination_points",
"crs": { "type": "name", "properties": { "name": "urn:ogc:def:crs:OGC:1.3:CRS84" } },
"features": [
{ "type": "Feature", "properties": { "point_type": "origin", "points_str": "45.379199, -122.743187" }, "geometry": { "type": "Point", "coordinates": [ -122.743186866750008, 45.379199121425756 ] } },
{ "type": "Feature", "properties": { "point_type": "destination", "points_str": "45.501069, -122.831724" }, "geometry": { "type": "Point", "coordinates": [ -122.831723944386923, 45.501068653226547 ] } }
]
}
