{
"type": "FeatureCollection",
"crs": { "type": "name", "properties": { "name": "urn:ogc:def:crs:OGC:1.3:CRS84" } },
"features": [
{ "type": "Feature", "properties": { "point_type": "origin", "points_str": "45.516671, -122.492051" }, "geometry": { "type": "Point", "coordinates": [ -122.492051379696306, 45.516671385877288 ] } },
{ "type": "Feature", "properties": { "point_type": "destination", "points_str": "45.512543, -122.76153" }, "geometry": { "type": "Point", "coordinates": [ -122.761530484407601, 45.512542623696376 ] } }
]
}
