{
"type": "FeatureCollection",
"crs": { "type": "name", "properties": { "name": "urn:ogc:def:crs:OGC:1.3:CRS84" } },
"features": [
{ "type": "Feature", "properties": { "point_type": "origin", "points_str": "45.540738, -122.619165" }, "geometry": { "type": "Point", "coordinates": [ -122.619165304696111, 45.540738050298671 ] } },
{ "type": "Feature", "properties": { "point_type": "destination", "points_str": "45.562585, -122.615681" }, "geometry": { "type": "Point", "coordinates": [ -122.615681009691642, 45.562585005701379 ] } }
]
}
