{
"type": "FeatureCollection",
"name": "origin_destination_points",
"crs": { "type": "name", "properties": { "name": "urn:ogc:def:crs:OGC:1.3:CRS84" } },
"features": [
{ "type": "Feature", "properties": { "point_type": "origin", "points_str": "45.602513, -122.791292" }, "geometry": { "type": "Point", "coordinates": [ -122.791291561638559, 45.602512702436258 ] } },
{ "type": "Feature", "properties": { "point_type": "destination", "points_str": "45.40255, -122.656017" }, "geometry": { "type": "Point", "coordinates": [ -122.656017370126449, 45.402550066918074 ] } }
]
}
