{
"type": "FeatureCollection",
"crs": { "type": "name", "properties": { "name": "urn:ogc:def:crs:OGC:1.3:CRS84" } },
"features": [
{ "type": "Feature", "properties": { "point_type": "origin", "points_str": "45.542851, -122.938834" }, "geometry": { "type": "Point", "coordinates": [ -122.938833735458388, 45.542850699936558 ] } },
{ "type": "Feature", "properties": { "point_type": "destination", "points_str": "45.51721, -123.078091" }, "geometry": { "type": "Point", "coordinates": [ -123.078090712450674, 45.517209625074543 ] } }
]
}
