{
"type": "FeatureCollection",
"crs": { "type": "name", "properties": { "name": "urn:ogc:def:crs:OGC:1.3:CRS84" } },
"features": [
{ "type": "Feature", "properties": { "point_type": "origin", "points_str": "45.488263, -122.755558" }, "geometry": { "type": "Point", "coordinates": [ -122.75555809950751, 45.48826295584621 ] } },
{ "type": "Feature", "properties": { "point_type": "destination", "points_str": "45.41146, -122.764323" }, "geometry": { "type": "Point", "coordinates": [ -122.76432274567513, 45.411460281665136 ] } }
]
}
