{
"type": "FeatureCollection",
"name": "origin_destination_points",
"crs": { "type": "name", "properties": { "name": "urn:ogc:def:crs:OGC:1.3:CRS84" } },
"features": [
{ "type": "Feature", "properties": { "point_type": "origin", "points_str": "45.461804, -122.625855" }, "geometry": { "type": "Point", "coordinates": [ -122.625855307671031, 45.461803542339993 ] } },
{ "type": "Feature", "properties": { "point_type": "destination", "points_str": "45.429435, -122.629614" }, "geometry": { "type": "Point", "coordinates": [ -122.629614323909095, 45.429434860714345 ] } }
]
}
