{
"type": "FeatureCollection",
"name": "origin_destination_points",
"crs": { "type": "name", "properties": { "name": "urn:ogc:def:crs:OGC:1.3:CRS84" } },
"features": [
{ "type": "Feature", "properties": { "point_type": "origin", "points_str": "45.492618, -122.443783" }, "geometry": { "type": "Point", "coordinates": [ -122.443783304541199, 45.492617792903843 ] } },
{ "type": "Feature", "properties": { "point_type": "destination", "points_str": "45.501471, -122.575094" }, "geometry": { "type": "Point", "coordinates": [ -122.57509372974458, 45.50147113636109 ] } }
]
}
