{
"type": "FeatureCollection",
"name": "origin_destination_points",
"crs": { "type": "name", "properties": { "name": "urn:ogc:def:crs:OGC:1.3:CRS84" } },
"features": [
{ "type": "Feature", "properties": { "point_type": "origin", "points_str": "45.514021, -122.455177" }, "geometry": { "type": "Point", "coordinates": [ -122.455176772663137, 45.51402122833386 ] } },
{ "type": "Feature", "properties": { "point_type": "destination", "points_str": "45.520944, -122.605105" }, "geometry": { "type": "Point", "coordinates": [ -122.605105403967016, 45.520943943901564 ] } }
]
}
