{
"type": "FeatureCollection",
"name": "origin_destination_points",
"crs": { "type": "name", "properties": { "name": "urn:ogc:def:crs:OGC:1.3:CRS84" } },
"features": [
{ "type": "Feature", "properties": { "point_type": "origin", "points_str": "45.495896, -122.650217" }, "geometry": { "type": "Point", "coordinates": [ -122.650216997415455, 45.495895654437554 ] } },
{ "type": "Feature", "properties": { "point_type": "destination", "points_str": "45.325542, -122.5758" }, "geometry": { "type": "Point", "coordinates": [ -122.575799552629761, 45.32554166519067 ] } }
]
}
