{
"type": "FeatureCollection",
"name": "origin_destination_points",
"crs": { "type": "name", "properties": { "name": "urn:ogc:def:crs:OGC:1.3:CRS84" } },
"features": [
{ "type": "Feature", "properties": { "point_type": "origin", "points_str": "45.51037, -122.874972" }, "geometry": { "type": "Point", "coordinates": [ -122.874971781335773, 45.510370250884009 ] } },
{ "type": "Feature", "properties": { "point_type": "destination", "points_str": "45.507047, -122.441199" }, "geometry": { "type": "Point", "coordinates": [ -122.44119916726153, 45.507046783657337 ] } }
]
}
