{
"type": "FeatureCollection",
"crs": { "type": "name", "properties": { "name": "urn:ogc:def:crs:OGC:1.3:CRS84" } },
"features": [
{ "type": "Feature", "properties": { "point_type": "origin", "points_str": "45.448853, -122.578195" }, "geometry": { "type": "Point", "coordinates": [ -122.578194759976455, 45.448852576833531 ] } },
{ "type": "Feature", "properties": { "point_type": "destination", "points_str": "45.512372, -122.565578" }, "geometry": { "type": "Point", "coordinates": [ -122.565578466124009, 45.512372104201368 ] } }
]
}
