{
"type": "FeatureCollection",
"crs": { "type": "name", "properties": { "name": "urn:ogc:def:crs:OGC:1.3:CRS84" } },
"features": [
{ "type": "Feature", "properties": { "point_type": "origin", "points_str": "45.429378, -122.764289" }, "geometry": { "type": "Point", "coordinates": [ -122.764289011785436, 45.429377910652313 ] } },
{ "type": "Feature", "properties": { "point_type": "destination", "points_str": "45.487565, -122.746798" }, "geometry": { "type": "Point", "coordinates": [ -122.746797851429918, 45.487564914924043 ] } }
]
}
