{
"type": "FeatureCollection",
"name": "origin_destination_points",
"crs": { "type": "name", "properties": { "name": "urn:ogc:def:crs:OGC:1.3:CRS84" } },
"features": [
{ "type": "Feature", "properties": { "point_type": "origin", "points_str": "45.496427, -122.881755" }, "geometry": { "type": "Point", "coordinates": [ -122.881754764772751, 45.49642745652249 ] } },
{ "type": "Feature", "properties": { "point_type": "destination", "points_str": "45.436437, -122.719418" }, "geometry": { "type": "Point", "coordinates": [ -122.71941807380199, 45.436437198519521 ] } }
]
}
