{
"type": "FeatureCollection",
"name": "origin_destination_points",
"crs": { "type": "name", "properties": { "name": "urn:ogc:def:crs:OGC:1.3:CRS84" } },
"features": [
{ "type": "Feature", "properties": { "point_type": "origin", "points_str": "45.499388, -122.835287" }, "geometry": { "type": "Point", "coordinates": [ -122.835287121215572, 45.499387994816836 ] } },
{ "type": "Feature", "properties": { "point_type": "destination", "points_str": "45.470042, -122.848405" }, "geometry": { "type": "Point", "coordinates": [ -122.848404664516252, 45.470041969676252 ] } }
]
}
