{
"type": "FeatureCollection",
"name": "origin_destination_points",
"crs": { "type": "name", "properties": { "name": "urn:ogc:def:crs:OGC:1.3:CRS84" } },
"features": [
{ "type": "Feature", "properties": { "point_type": "origin", "points_str": "45.448586, -122.593346" }, "geometry": { "type": "Point", "coordinates": [ -122.593345827669125, 45.448585788927133 ] } },
{ "type": "Feature", "properties": { "point_type": "destination", "points_str": "45.559557, -122.644497" }, "geometry": { "type": "Point", "coordinates": [ -122.644497022507494, 45.559556829200048 ] } }
]
}
