{
"type": "FeatureCollection",
"name": "origin_destination_points",
"crs": { "type": "name", "properties": { "name": "urn:ogc:def:crs:OGC:1.3:CRS84" } },
"features": [
{ "type": "Feature", "properties": { "point_type": "origin", "points_str": "45.449425, -122.784478" }, "geometry": { "type": "Point", "coordinates": [ -122.78447783120599, 45.449425398449968 ] } },
{ "type": "Feature", "properties": { "point_type": "destination", "points_str": "45.389925, -122.804119" }, "geometry": { "type": "Point", "coordinates": [ -122.804119002275087, 45.389924889731532 ] } }
]
}
