{
"type": "FeatureCollection",
"crs": { "type": "name", "properties": { "name": "urn:ogc:def:crs:OGC:1.3:CRS84" } },
"features": [
{ "type": "Feature", "properties": { "point_type": "origin", "points_str": "45.513311, -122.637809" }, "geometry": { "type": "Point", "coordinates": [ -122.637808641550052, 45.51331142409623 ] } },
{ "type": "Feature", "properties": { "point_type": "destination", "points_str": "45.51578, -122.594034" }, "geometry": { "type": "Point", "coordinates": [ -122.594033595477157, 45.515780298621038 ] } }
]
}
