{
"type": "FeatureCollection",
"crs": { "type": "name", "properties": { "name": "urn:ogc:def:crs:OGC:1.3:CRS84" } },
"features": [
{ "type": "Feature", "properties": { "point_type": "origin", "points_str": "45.499877, -122.802052" }, "geometry": { "type": "Point", "coordinates": [ -122.802052386636305, 45.499876527234093 ] } },
{ "type": "Feature", "properties": { "point_type": "destination", "points_str": "45.546589, -122.676489" }, "geometry": { "type": "Point", "coordinates": [ -122.676488719093499, 45.546588785239443 ] } }
]
}
