{
"type": "FeatureCollection",
"crs": { "type": "name", "properties": { "name": "urn:ogc:def:crs:OGC:1.3:CRS84" } },
"features": [
{ "type": "Feature", "properties": { "point_type": "origin", "points_str": "45.572659, -122.692189" }, "geometry": { "type": "Point", "coordinates": [ -122.692188908124777, 45.572658798155658 ] } },
{ "type": "Feature", "properties": { "point_type": "destination", "points_str": "45.620362, -122.764989" }, "geometry": { "type": "Point", "coordinates": [ -122.764989493599145, 45.620361902476375 ] } }
]
}
