{
"type": "FeatureCollection",
"crs": { "type": "name", "properties": { "name": "urn:ogc:def:crs:OGC:1.3:CRS84" } },
"features": [
{ "type": "Feature", "properties": { "point_type": "origin", "points_str": "45.516774, -122.583151" }, "geometry": { "type": "Point", "coordinates": [ -122.583151499794013, 45.516774263910804 ] } },
{ "type": "Feature", "properties": { "point_type": "destination", "points_str": "45.590857, -122.65937" }, "geometry": { "type": "Point", "coordinates": [ -122.659369694907696, 45.590857329829419 ] } }
]
}
