{
"type": "FeatureCollection",
"crs": { "type": "name", "properties": { "name": "urn:ogc:def:crs:OGC:1.3:CRS84" } },
"features": [
{ "type": "Feature", "properties": { "point_type": "origin", "points_str": "45.43928, -122.56851" }, "geometry": { "type": "Point", "coordinates": [ -122.568510049036433, 45.439280056288005 ] } },
{ "type": "Feature", "properties": { "point_type": "destination", "points_str": "45.396968, -122.602672" }, "geometry": { "type": "Point", "coordinates": [ -122.602672361115182, 45.396967969776668 ] } }
]
}
