{
"type": "FeatureCollection",
"name": "origin_destination_points",
"crs": { "type": "name", "properties": { "name": "urn:ogc:def:crs:OGC:1.3:CRS84" } },
"features": [
{ "type": "Feature", "properties": { "point_type": "origin", "points_str": "45.380297, -122.739679" }, "geometry": { "type": "Point", "coordinates": [ -122.739678849355656, 45.380296943325142 ] } },
{ "type": "Feature", "properties": { "point_type": "destination", "points_str": "45.492677, -122.868049" }, "geometry": { "type": "Point", "coordinates": [ -122.868048711046157, 45.492676906586929 ] } }
]
}
