{
"type": "FeatureCollection",
"name": "origin_destination_points",
"crs": { "type": "name", "properties": { "name": "urn:ogc:def:crs:OGC:1.3:CRS84" } },
"features": [
{ "type": "Feature", "properties": { "point_type": "origin", "points_str": "45.521308, -122.49412" }, "geometry": { "type": "Point", "coordinates": [ -122.494120095438035, 45.521308079553584 ] } },
{ "type": "Feature", "properties": { "point_type": "destination", "points_str": "45.477036, -122.618252" }, "geometry": { "type": "Point", "coordinates": [ -122.618252113300684, 45.477035995089601 ] } }
]
}
