{
"type": "FeatureCollection",
"name": "origin_destination_points",
"crs": { "type": "name", "properties": { "name": "urn:ogc:def:crs:OGC:1.3:CRS84" } },
"features": [
{ "type": "Feature", "properties": { "point_type": "origin", "points_str": "45.593629, -122.662075" }, "geometry": { "type": "Point", "coordinates": [ -122.662075150956767, 45.593628970983261 ] } },
{ "type": "Feature", "properties": { "point_type": "destination", "points_str": "45.505071, -122.426149" }, "geometry": { "type": "Point", "coordinates": [ -122.426149390052117, 45.505071393378081 ] } }
]
}
