{
"type": "FeatureCollection",
"crs": { "type": "name", "properties": { "name": "urn:ogc:def:crs:OGC:1.3:CRS84" } },
"features": [
{ "type": "Feature", "properties": { "point_type": "origin", "points_str": "45.518901, -122.551985" }, "geometry": { "type": "Point", "coordinates": [ -122.551985309711398, 45.518900834378023 ] } },
{ "type": "Feature", "properties": { "point_type": "destination", "points_str": "45.52232, -122.662405" }, "geometry": { "type": "Point", "coordinates": [ -122.662405050828056, 45.52232028823861 ] } }
]
}
