{
"type": "FeatureCollection",
"crs": { "type": "name", "properties": { "name": "urn:ogc:def:crs:OGC:1.3:CRS84" } },
"features": [
{ "type": "Feature", "properties": { "point_type": "origin", "points_str": "45.544301, -122.667735" }, "geometry": { "type": "Point", "coordinates": [ -122.667734905183522, 45.544301292727013 ] } },
{ "type": "Feature", "properties": { "point_type": "destination", "points_str": "45.512927, -122.400712" }, "geometry": { "type": "Point", "coordinates": [ -122.40071184413344, 45.512927408599502 ] } }
]
}
