{
"type": "FeatureCollection",
"name": "origin_destination_points",
"crs": { "type": "name", "properties": { "name": "urn:ogc:def:crs:OGC:1.3:CRS84" } },
"features": [
{ "type": "Feature", "properties": { "point_type": "origin", "points_str": "45.47394, -122.682311" }, "geometry": { "type": "Point", "coordinates": [ -122.682311240001283, 45.47394042431727 ] } },
{ "type": "Feature", "properties": { "point_type": "destination", "points_str": "45.597673, -122.678631" }, "geometry": { "type": "Point", "coordinates": [ -122.678631073108875, 45.597672572148099 ] } }
]
}
