{
"type": "FeatureCollection",
"name": "origin_destination_points",
"crs": { "type": "name", "properties": { "name": "urn:ogc:def:crs:OGC:1.3:CRS84" } },
"features": [
{ "type": "Feature", "properties": { "point_type": "origin", "points_str": "45.478993, -122.645092" }, "geometry": { "type": "Point", "coordinates": [ -122.645092450595612, 45.478992519525669 ] } },
{ "type": "Feature", "properties": { "point_type": "destination", "points_str": "45.555733, -122.660129" }, "geometry": { "type": "Point", "coordinates": [ -122.660129001748601, 45.555732588893008 ] } }
]
}
