{
"type": "FeatureCollection",
"name": "origin_destination_points",
"crs": { "type": "name", "properties": { "name": "urn:ogc:def:crs:OGC:1.3:CRS84" } },
"features": [
{ "type": "Feature", "properties": { "point_type": "origin", "points_str": "45.522171, -122.9827" }, "geometry": { "type": "Point", "coordinates": [ -122.982700086541129, 45.522170718464608 ] } },
{ "type": "Feature", "properties": { "point_type": "destination", "points_str": "45.508475, -122.395981" }, "geometry": { "type": "Point", "coordinates": [ -122.395981109134524, 45.508475487243452 ] } }
]
}
