{
"type": "FeatureCollection",
"name": "origin_destination_points",
"crs": { "type": "name", "properties": { "name": "urn:ogc:def:crs:OGC:1.3:CRS84" } },
"features": [
{ "type": "Feature", "properties": { "point_type": "origin", "points_str": "45.487734, -122.717762" }, "geometry": { "type": "Point", "coordinates": [ -122.717761938837356, 45.48773444393003 ] } },
{ "type": "Feature", "properties": { "point_type": "destination", "points_str": "45.484933, -122.740649" }, "geometry": { "type": "Point", "coordinates": [ -122.740648544355537, 45.48493276780907 ] } }
]
}
