{
"type": "FeatureCollection",
"name": "origin_destination_points",
"crs": { "type": "name", "properties": { "name": "urn:ogc:def:crs:OGC:1.3:CRS84" } },
"features": [
{ "type": "Feature", "properties": { "point_type": "origin", "points_str": "45.504904, -122.84858" }, "geometry": { "type": "Point", "coordinates": [ -122.848580308515636, 45.50490424775878 ] } },
{ "type": "Feature", "properties": { "point_type": "destination", "points_str": "45.531545, -122.682494" }, "geometry": { "type": "Point", "coordinates": [ -122.682493773029705, 45.531545497719158 ] } }
]
}
