{
"type": "FeatureCollection",
"name": "origin_destination_points",
"crs": { "type": "name", "properties": { "name": "urn:ogc:def:crs:OGC:1.3:CRS84" } },
"features": [
{ "type": "Feature", "properties": { "point_type": "origin", "points_str": "45.564302, -122.530652" }, "geometry": { "type": "Point", "coordinates": [ -122.530651569114241, 45.564302042487761 ] } },
{ "type": "Feature", "properties": { "point_type": "destination", "points_str": "45.53243, -122.47899" }, "geometry": { "type": "Point", "coordinates": [ -122.478989972540504, 45.532430354913245 ] } }
]
}
