{
"type": "FeatureCollection",
"crs": { "type": "name", "properties": { "name": "urn:ogc:def:crs:OGC:1.3:CRS84" } },
"features": [
{ "type": "Feature", "properties": { "point_type": "origin", "points_str": "45.546958, -122.617263" }, "geometry": { "type": "Point", "coordinates": [ -122.617263329893063, 45.546958028134533 ] } },
{ "type": "Feature", "properties": { "point_type": "destination", "points_str": "45.533076, -122.588817" }, "geometry": { "type": "Point", "coordinates": [ -122.588816887775664, 45.533075518072422 ] } }
]
}
