{
"type": "FeatureCollection",
"name": "origin_destination_points",
"crs": { "type": "name", "properties": { "name": "urn:ogc:def:crs:OGC:1.3:CRS84" } },
"features": [
{ "type": "Feature", "properties": { "point_type": "origin", "points_str": "45.578859, -122.706222" }, "geometry": { "type": "Point", "coordinates": [ -122.706221979650607, 45.578859372525542 ] } },
{ "type": "Feature", "properties": { "point_type": "destination", "points_str": "45.5085, -122.407317" }, "geometry": { "type": "Point", "coordinates": [ -122.407317372200566, 45.508500151379437 ] } }
]
}
