{
"type": "FeatureCollection",
"name": "origin_destination_points",
"crs": { "type": "name", "properties": { "name": "urn:ogc:def:crs:OGC:1.3:CRS84" } },
"features": [
{ "type": "Feature", "properties": { "point_type": "origin", "points_str": "45.563179, -122.744547" }, "geometry": { "type": "Point", "coordinates": [ -122.744546606827598, 45.563179322679517 ] } },
{ "type": "Feature", "properties": { "point_type": "destination", "points_str": "45.469545, -122.675391" }, "geometry": { "type": "Point", "coordinates": [ -122.675390959081454, 45.469545469980183 ] } }
]
}
