{
"type": "FeatureCollection",
"name": "origin_destination_points",
"crs": { "type": "name", "properties": { "name": "urn:ogc:def:crs:OGC:1.3:CRS84" } },
"features": [
{ "type": "Feature", "properties": { "point_type": "origin", "points_str": "45.504643, -122.476612" }, "geometry": { "type": "Point", "coordinates": [ -122.476612303825618, 45.504642701539986 ] } },
{ "type": "Feature", "properties": { "point_type": "destination", "points_str": "45.484152, -122.613939" }, "geometry": { "type": "Point", "coordinates": [ -122.613938953205547, 45.484152222673004 ] } }
]
}
