{
"type": "FeatureCollection",
"crs": { "type": "name", "properties": { "name": "urn:ogc:def:crs:OGC:1.3:CRS84" } },
"features": [
{ "type": "Feature", "properties": { "point_type": "origin", "points_str": "45.521477, -123.068402" }, "geometry": { "type": "Point", "coordinates": [ -123.068401712074561, 45.521477183982824 ] } },
{ "type": "Feature", "properties": { "point_type": "destination", "points_str": "45.473826, -122.806929" }, "geometry": { "type": "Point", "coordinates": [ -122.806928998242569, 45.473826400806274 ] } }
]
}
