{
"type": "FeatureCollection",
"name": "origin_destination_points",
"crs": { "type": "name", "properties": { "name": "urn:ogc:def:crs:OGC:1.3:CRS84" } },
"features": [
{ "type": "Feature", "properties": { "point_type": "origin", "points_str": "45.479836, -122.65142" }, "geometry": { "type": "Point", "coordinates": [ -122.651420434336956, 45.479835857525245 ] } },
{ "type": "Feature", "properties": { "point_type": "destination", "points_str": "45.570605, -122.637879" }, "geometry": { "type": "Point", "coordinates": [ -122.637878676765382, 45.570605258605504 ] } }
]
}
