{
"type": "FeatureCollection",
"name": "origin_destination_points",
"crs": { "type": "name", "properties": { "name": "urn:ogc:def:crs:OGC:1.3:CRS84" } },
"features": [
{ "type": "Feature", "properties": { "point_type": "origin", "points_str": "45.422417, -122.639468" }, "geometry": { "type": "Point", "coordinates": [ -122.639467764952371, 45.422417234940518 ] } },
{ "type": "Feature", "properties": { "point_type": "destination", "points_str": "45.511712, -122.646893" }, "geometry": { "type": "Point", "coordinates": [ -122.646892895976052, 45.511711602401782 ] } }
]
}
