{
"type": "FeatureCollection",
"name": "origin_destination_points",
"crs": { "type": "name", "properties": { "name": "urn:ogc:def:crs:OGC:1.3:CRS84" } },
"features": [
{ "type": "Feature", "properties": { "point_type": "origin", "points_str": "45.521149, -123.025091" }, "geometry": { "type": "Point", "coordinates": [ -123.025091406861932, 45.521148698802499 ] } },
{ "type": "Feature", "properties": { "point_type": "destination", "points_str": "45.545051, -122.931114" }, "geometry": { "type": "Point", "coordinates": [ -122.931113885119274, 45.545050874006222 ] } }
]
}
