{
"type": "FeatureCollection",
"name": "origin_destination_points",
"crs": { "type": "name", "properties": { "name": "urn:ogc:def:crs:OGC:1.3:CRS84" } },
"features": [
{ "type": "Feature", "properties": { "point_type": "origin", "points_str": "45.484052, -122.728914" }, "geometry": { "type": "Point", "coordinates": [ -122.728913984743542, 45.484051560223257 ] } },
{ "type": "Feature", "properties": { "point_type": "destination", "points_str": "45.594869, -122.721575" }, "geometry": { "type": "Point", "coordinates": [ -122.721574717719818, 45.594868748704158 ] } }
]
}
