{
"type": "FeatureCollection",
"name": "origin_destination_points",
"crs": { "type": "name", "properties": { "name": "urn:ogc:def:crs:OGC:1.3:CRS84" } },
"features": [
{ "type": "Feature", "properties": { "point_type": "origin", "points_str": "45.458675, -122.631658" }, "geometry": { "type": "Point", "coordinates": [ -122.631657637632685, 45.458675326150264 ] } },
{ "type": "Feature", "properties": { "point_type": "destination", "points_str": "45.453416, -122.601796" }, "geometry": { "type": "Point", "coordinates": [ -122.601795744437808, 45.453416165004647 ] } }
]
}
