{
"type": "FeatureCollection",
"name": "origin_destination_points",
"crs": { "type": "name", "properties": { "name": "urn:ogc:def:crs:OGC:1.3:CRS84" } },
"features": [
{ "type": "Feature", "properties": { "point_type": "origin", "points_str": "45.510523, -122.626032" }, "geometry": { "type": "Point", "coordinates": [ -122.626032418611288, 45.510522679013896 ] } },
{ "type": "Feature", "properties": { "point_type": "destination", "points_str": "45.595992, -122.765072" }, "geometry": { "type": "Point", "coordinates": [ -122.76507181964466, 45.595991711899131 ] } }
]
}
