{
"type": "FeatureCollection",
"name": "origin_destination_points",
"crs": { "type": "name", "properties": { "name": "urn:ogc:def:crs:OGC:1.3:CRS84" } },
"features": [
{ "type": "Feature", "properties": { "point_type": "origin", "points_str": "45.501448, -122.603337" }, "geometry": { "type": "Point", "coordinates": [ -122.603336798028664, 45.501447599121796 ] } },
{ "type": "Feature", "properties": { "point_type": "destination", "points_str": "45.4907, -122.654894" }, "geometry": { "type": "Point", "coordinates": [ -122.654894102408505, 45.490700048568819 ] } }
]
}
