{
"type": "FeatureCollection",
"crs": { "type": "name", "properties": { "name": "urn:ogc:def:crs:OGC:1.3:CRS84" } },
"features": [
{ "type": "Feature", "properties": { "point_type": "origin", "points_str": "45.536665, -122.625319" }, "geometry": { "type": "Point", "coordinates": [ -122.625319497757815, 45.536664781409975 ] } },
{ "type": "Feature", "properties": { "point_type": "destination", "points_str": "45.490202, -122.720662" }, "geometry": { "type": "Point", "coordinates": [ -122.720661865933224, 45.490201835455437 ] } }
]
}
