{
"type": "FeatureCollection",
"name": "origin_destination_points",
"crs": { "type": "name", "properties": { "name": "urn:ogc:def:crs:OGC:1.3:CRS84" } },
"features": [
{ "type": "Feature", "properties": { "point_type": "origin", "points_str": "45.436983, -122.756039" }, "geometry": { "type": "Point", "coordinates": [ -122.756039341083579, 45.436983400452966 ] } },
{ "type": "Feature", "properties": { "point_type": "destination", "points_str": "45.404499, -122.761852" }, "geometry": { "type": "Point", "coordinates": [ -122.761852308080051, 45.404498847026453 ] } }
]
}
