{
"type": "FeatureCollection",
"name": "origin_destination_points",
"crs": { "type": "name", "properties": { "name": "urn:ogc:def:crs:OGC:1.3:CRS84" } },
"features": [
{ "type": "Feature", "properties": { "point_type": "origin", "points_str": "45.505111, -122.846625" }, "geometry": { "type": "Point", "coordinates": [ -122.846625149883366, 45.50511086274301 ] } },
{ "type": "Feature", "properties": { "point_type": "destination", "points_str": "45.47663, -122.697772" }, "geometry": { "type": "Point", "coordinates": [ -122.697771833469588, 45.476630060681963 ] } }
]
}
