{
"type": "FeatureCollection",
"crs": { "type": "name", "properties": { "name": "urn:ogc:def:crs:OGC:1.3:CRS84" } },
"features": [
{ "type": "Feature", "properties": { "point_type": "origin", "points_str": "45.597805, -122.657284" }, "geometry": { "type": "Point", "coordinates": [ -122.657284494289541, 45.597804830424138 ] } },
{ "type": "Feature", "properties": { "point_type": "destination", "points_str": "45.517035, -122.986336" }, "geometry": { "type": "Point", "coordinates": [ -122.986335888702371, 45.517035093039276 ] } }
]
}
