{
"type": "FeatureCollection",
"name": "origin_destination_points",
"crs": { "type": "name", "properties": { "name": "urn:ogc:def:crs:OGC:1.3:CRS84" } },
"features": [
{ "type": "Feature", "properties": { "point_type": "origin", "points_str": "45.330653, -122.600053" }, "geometry": { "type": "Point", "coordinates": [ -122.600053014910458, 45.330653362178523 ] } },
{ "type": "Feature", "properties": { "point_type": "destination", "points_str": "45.511472, -122.579015" }, "geometry": { "type": "Point", "coordinates": [ -122.579015306239128, 45.51147226195404 ] } }
]
}
