{
"type": "FeatureCollection",
"crs": { "type": "name", "properties": { "name": "urn:ogc:def:crs:OGC:1.3:CRS84" } },
"features": [
{ "type": "Feature", "properties": { "point_type": "origin", "points_str": "45.511425, -122.788233" }, "geometry": { "type": "Point", "coordinates": [ -122.788232664799281, 45.511425366548835 ] } },
{ "type": "Feature", "properties": { "point_type": "destination", "points_str": "45.436115, -122.587389" }, "geometry": { "type": "Point", "coordinates": [ -122.587389125204794, 45.436115158631978 ] } }
]
}
