{
"type": "FeatureCollection",
"crs": { "type": "name", "properties": { "name": "urn:ogc:def:crs:OGC:1.3:CRS84" } },
"features": [
{ "type": "Feature", "properties": { "point_type": "origin", "points_str": "45.527661, -122.518195" }, "geometry": { "type": "Point", "coordinates": [ -122.518195189062226, 45.527661169059762 ] } },
{ "type": "Feature", "properties": { "point_type": "destination", "points_str": "45.588635, -122.635608" }, "geometry": { "type": "Point", "coordinates": [ -122.635608451020147, 45.588634629460145 ] } }
]
}
