{
"type": "FeatureCollection",
"crs": { "type": "name", "properties": { "name": "urn:ogc:def:crs:OGC:1.3:CRS84" } },
"features": [
{ "type": "Feature", "properties": { "point_type": "origin", "points_str": "45.442577, -122.801742" }, "geometry": { "type": "Point", "coordinates": [ -122.801742119775753, 45.44257684181926 ] } },
{ "type": "Feature", "properties": { "point_type": "destination", "points_str": "45.375281, -122.764997" }, "geometry": { "type": "Point", "coordinates": [ -122.764996912104593, 45.375281409990691 ] } }
]
}
