{
"type": "FeatureCollection",
"crs": { "type": "name", "properties": { "name": "urn:ogc:def:crs:OGC:1.3:CRS84" } },
"features": [
{ "type": "Feature", "properties": { "point_type": "origin", "points_str": "45.336465, -122.595113" }, "geometry": { "type": "Point", "coordinates": [ -122.595113176325569, 45.336465271252223 ] } },
{ "type": "Feature", "properties": { "point_type": "destination", "points_str": "45.426761, -122.657184" }, "geometry": { "type": "Point", "coordinates": [ -122.657183791295068, 45.426761303888483 ] } }
]
}
