{
"type": "FeatureCollection",
"name": "origin_destination_points",
"crs": { "type": "name", "properties": { "name": "urn:ogc:def:crs:OGC:1.3:CRS84" } },
"features": [
{ "type": "Feature", "properties": { "point_type": "origin", "points_str": "45.528429, -122.663863" }, "geometry": { "type": "Point", "coordinates": [ -122.663862994123619, 45.528428737657805 ] } },
{ "type": "Feature", "properties": { "point_type": "destination", "points_str": "45.522461, -123.038426" }, "geometry": { "type": "Point", "coordinates": [ -123.038425771796796, 45.522460682519288 ] } }
]
}
