{
"type": "FeatureCollection",
"name": "origin_destination_points",
"crs": { "type": "name", "properties": { "name": "urn:ogc:def:crs:OGC:1.3:CRS84" } },
"features": [
{ "type": "Feature", "properties": { "point_type": "origin", "points_str": "45.40302, -122.76457" }, "geometry": { "type": "Point", "coordinates": [ -122.764570112351421, 45.403020176279114 ] } },
{ "type": "Feature", "properties": { "point_type": "destination", "points_str": "45.558214, -122.564934" }, "geometry": { "type": "Point", "coordinates": [ -122.564933815612207, 45.558213574707146 ] } }
]
}
