{
"type": "FeatureCollection",
"name": "origin_destination_points",
"crs": { "type": "name", "properties": { "name": "urn:ogc:def:crs:OGC:1.3:CRS84" } },
"features": [
{ "type": "Feature", "properties": { "point_type": "origin", "points_str": "45.526863, -122.651124" }, "geometry": { "type": "Point", "coordinates": [ -122.651124145357372, 45.526862659359644 ] } },
{ "type": "Feature", "properties": { "point_type": "destination", "points_str": "45.523821, -122.493651" }, "geometry": { "type": "Point", "coordinates": [ -122.493651244851236, 45.523820858518626 ] } }
]
}
