{
"type": "FeatureCollection",
"name": "origin_destination_points",
"crs": { "type": "name", "properties": { "name": "urn:ogc:def:crs:OGC:1.3:CRS84" } },
"features": [
{ "type": "Feature", "properties": { "point_type": "origin", "points_str": "45.499139, -122.619591" }, "geometry": { "type": "Point", "coordinates": [ -122.619591305647219, 45.499139065988963 ] } },
{ "type": "Feature", "properties": { "point_type": "destination", "points_str": "45.503456, -122.750678" }, "geometry": { "type": "Point", "coordinates": [ -122.750678409848476, 45.503456324647438 ] } }
]
}
