{
"type": "FeatureCollection",
"name": "origin_destination_points",
"crs": { "type": "name", "properties": { "name": "urn:ogc:def:crs:OGC:1.3:CRS84" } },
"features": [
{ "type": "Feature", "properties": { "point_type": "origin", "points_str": "45.460389, -122.620519" }, "geometry": { "type": "Point", "coordinates": [ -122.620518899322164, 45.460389361304408 ] } },
{ "type": "Feature", "properties": { "point_type": "destination", "points_str": "45.492726, -122.616525" }, "geometry": { "type": "Point", "coordinates": [ -122.616524505901822, 45.492726006381716 ] } }
]
}
