{
"type": "FeatureCollection",
"name": "origin_destination_points",
"crs": { "type": "name", "properties": { "name": "urn:ogc:def:crs:OGC:1.3:CRS84" } },
"features": [
{ "type": "Feature", "properties": { "point_type": "origin", "points_str": "45.560373, -122.499364" }, "geometry": { "type": "Point", "coordinates": [ -122.499364042744759, 45.560373337539083 ] } },
{ "type": "Feature", "properties": { "point_type": "destination", "points_str": "45.493714, -122.491511" }, "geometry": { "type": "Point", "coordinates": [ -122.491511353474849, 45.493713667277497 ] } }
]
}
