{
"type": "FeatureCollection",
"crs": { "type": "name", "properties": { "name": "urn:ogc:def:crs:OGC:1.3:CRS84" } },
"features": [
{ "type": "Feature", "properties": { "point_type": "origin", "points_str": "45.459406, -122.798549" }, "geometry": { "type": "Point", "coordinates": [ -122.798548932283126, 45.459405797479903 ] } },
{ "type": "Feature", "properties": { "point_type": "destination", "points_str": "45.433524, -122.708374" }, "geometry": { "type": "Point", "coordinates": [ -122.708373798162626, 45.433523925369371 ] } }
]
}
