{
"type": "FeatureCollection",
"name": "origin_destination_points",
"crs": { "type": "name", "properties": { "name": "urn:ogc:def:crs:OGC:1.3:CRS84" } },
"features": [
{ "type": "Feature", "properties": { "point_type": "origin", "points_str": "45.597415, -122.783109" }, "geometry": { "type": "Point", "coordinates": [ -122.783108539543107, 45.597414700082886 ] } },
{ "type": "Feature", "properties": { "point_type": "destination", "points_str": "45.52134, -122.451416" }, "geometry": { "type": "Point", "coordinates": [ -122.451415900901537, 45.521340031811199 ] } }
]
}
