{
"type": "FeatureCollection",
"name": "origin_destination_points",
"crs": { "type": "name", "properties": { "name": "urn:ogc:def:crs:OGC:1.3:CRS84" } },
"features": [
{ "type": "Feature", "properties": { "point_type": "origin", "points_str": "45.556417, -122.670112" }, "geometry": { "type": "Point", "coordinates": [ -122.670111707297352, 45.556417324705002 ] } },
{ "type": "Feature", "properties": { "point_type": "destination", "points_str": "45.450449, -122.675059" }, "geometry": { "type": "Point", "coordinates": [ -122.675058624643256, 45.450448591775178 ] } }
]
}
