{
"type": "FeatureCollection",
"name": "origin_destination_points",
"crs": { "type": "name", "properties": { "name": "urn:ogc:def:crs:OGC:1.3:CRS84" } },
"features": [
{ "type": "Feature", "properties": { "point_type": "origin", "points_str": "45.490058, -122.522005" }, "geometry": { "type": "Point", "coordinates": [ -122.522005178022695, 45.490057802617777 ] } },
{ "type": "Feature", "properties": { "point_type": "destination", "points_str": "45.496479, -122.669711" }, "geometry": { "type": "Point", "coordinates": [ -122.669711384653851, 45.496479039550948 ] } }
]
}
