{
"type": "FeatureCollection",
"crs": { "type": "name", "properties": { "name": "urn:ogc:def:crs:OGC:1.3:CRS84" } },
"features": [
{ "type": "Feature", "properties": { "point_type": "origin", "points_str": "45.488842, -122.586972" }, "geometry": { "type": "Point", "coordinates": [ -122.58697190401945, 45.488841873840371 ] } },
{ "type": "Feature", "properties": { "point_type": "destination", "points_str": "45.382704, -122.387064" }, "geometry": { "type": "Point", "coordinates": [ -122.387063544379018, 45.382704060717259 ] } }
]
}
