{
"type": "FeatureCollection",
"name": "origin_destination_points",
"crs": { "type": "name", "properties": { "name": "urn:ogc:def:crs:OGC:1.3:CRS84" } },
"features": [
{ "type": "Feature", "properties": { "point_type": "origin", "points_str": "45.575895, -122.728342" }, "geometry": { "type": "Point", "coordinates": [ -122.728341987868504, 45.575895350104616 ] } },
{ "type": "Feature", "properties": { "point_type": "destination", "points_str": "45.565439, -122.681917" }, "geometry": { "type": "Point", "coordinates": [ -122.681917463194381, 45.565439270165434 ] } }
]
}
