{
"type": "FeatureCollection",
"name": "origin_destination_points",
"crs": { "type": "name", "properties": { "name": "urn:ogc:def:crs:OGC:1.3:CRS84" } },
"features": [
{ "type": "Feature", "properties": { "point_type": "origin", "points_str": "45.51212, -122.774792" }, "geometry": { "type": "Point", "coordinates": [ -122.774792008401278, 45.512120070048127 ] } },
{ "type": "Feature", "properties": { "point_type": "destination", "points_str": "45.490464, -122.470889" }, "geometry": { "type": "Point", "coordinates": [ -122.470888781749693, 45.490463888383339 ] } }
]
}
