{
"type": "FeatureCollection",
"crs": { "type": "name", "properties": { "name": "urn:ogc:def:crs:OGC:1.3:CRS84" } },
"features": [
{ "type": "Feature", "properties": { "point_type": "origin", "points_str": "45.470796, -122.631877" }, "geometry": { "type": "Point", "coordinates": [ -122.631876537493028, 45.470795961976833 ] } },
{ "type": "Feature", "properties": { "point_type": "destination", "points_str": "45.574121, -122.612656" }, "geometry": { "type": "Point", "coordinates": [ -122.612656289973131, 45.574120741022995 ] } }
]
}
