{
"type": "FeatureCollection",
"crs": { "type": "name", "properties": { "name": "urn:ogc:def:crs:OGC:1.3:CRS84" } },
"features": [
{ "type": "Feature", "properties": { "point_type": "origin", "points_str": "45.462227, -122.827251" }, "geometry": { "type": "Point", "coordinates": [ -122.827250566355659, 45.462227340817179 ] } },
{ "type": "Feature", "properties": { "point_type": "destination", "points_str": "45.428357, -122.744488" }, "geometry": { "type": "Point", "coordinates": [ -122.74448841328983, 45.428357052021902 ] } }
]
}
