{
"type": "FeatureCollection",
"crs": { "type": "name", "properties": { "name": "urn:ogc:def:crs:OGC:1.3:CRS84" } },
"features": [
{ "type": "Feature", "properties": { "point_type": "origin", "points_str": "45.53416, -122.648992" }, "geometry": { "type": "Point", "coordinates": [ -122.648991957751434, 45.534159744704709 ] } },
{ "type": "Feature", "properties": { "point_type": "destination", "points_str": "45.506562, -122.683447" }, "geometry": { "type": "Point", "coordinates": [ -122.68344734628225, 45.506561738048973 ] } }
]
}
