{
"type": "FeatureCollection",
"crs": { "type": "name", "properties": { "name": "urn:ogc:def:crs:OGC:1.3:CRS84" } },
"features": [
{ "type": "Feature", "properties": { "point_type": "origin", "points_str": "45.500896, -122.399977" }, "geometry": { "type": "Point", "coordinates": [ -122.399977368312335, 45.500895959678211 ] } },
{ "type": "Feature", "properties": { "point_type": "destination", "points_str": "45.536269, -122.424054" }, "geometry": { "type": "Point", "coordinates": [ -122.424053879017166, 45.536268601240835 ] } }
]
}
