{
"type": "FeatureCollection",
"name": "origin_destination_points",
"crs": { "type": "name", "properties": { "name": "urn:ogc:def:crs:OGC:1.3:CRS84" } },
"features": [
{ "type": "Feature", "properties": { "point_type": "origin", "points_str": "45.484089, -122.720519" }, "geometry": { "type": "Point", "coordinates": [ -122.720518831502602, 45.484088835525874 ] } },
{ "type": "Feature", "properties": { "point_type": "destination", "points_str": "45.487875, -122.772797" }, "geometry": { "type": "Point", "coordinates": [ -122.772797278692025, 45.48787482266227 ] } }
]
}
