{
"type": "FeatureCollection",
"name": "origin_destination_points",
"crs": { "type": "name", "properties": { "name": "urn:ogc:def:crs:OGC:1.3:CRS84" } },
"features": [
{ "type": "Feature", "properties": { "point_type": "origin", "points_str": "45.542882, -122.608824" }, "geometry": { "type": "Point", "coordinates": [ -122.608824438243246, 45.542882356224368 ] } },
{ "type": "Feature", "properties": { "point_type": "destination", "points_str": "45.405957, -122.800479" }, "geometry": { "type": "Point", "coordinates": [ -122.800479211206749, 45.405957334800107 ] } }
]
}
