{
"type": "FeatureCollection",
"name": "origin_destination_points",
"crs": { "type": "name", "properties": { "name": "urn:ogc:def:crs:OGC:1.3:CRS84" } },
"features": [
{ "type": "Feature", "properties": { "point_type": "origin", "points_str": "45.464948, -122.778342" }, "geometry": { "type": "Point", "coordinates": [ -122.77834217316078, 45.464948055625527 ] } },
{ "type": "Feature", "properties": { "point_type": "destination", "points_str": "45.440231, -122.776003" }, "geometry": { "type": "Point", "coordinates": [ -122.77600280498848, 45.440230960449213 ] } }
]
}
