{
"type": "FeatureCollection",
"name": "origin_destination_points",
"crs": { "type": "name", "properties": { "name": "urn:ogc:def:crs:OGC:1.3:CRS84" } },
"features": [
{ "type": "Feature", "properties": { "point_type": "origin", "points_str": "45.520317, -122.888737" }, "geometry": { "type": "Point", "coordinates": [ -122.888736706976445, 45.520317107968125 ] } },
{ "type": "Feature", "properties": { "point_type": "destination", "points_str": "45.49554, -122.643311" }, "geometry": { "type": "Point", "coordinates": [ -122.643310821901068, 45.495539894475002 ] } }
]
}
