{
"type": "FeatureCollection",
"name": "origin_destination_points",
"crs": { "type": "name", "properties": { "name": "urn:ogc:def:crs:OGC:1.3:CRS84" } },
"features": [
{ "type": "Feature", "properties": { "point_type": "origin", "points_str": "45.545905, -122.711517" }, "geometry": { "type": "Point", "coordinates": [ -122.711517141147823, 45.545904765478888 ] } },
{ "type": "Feature", "properties": { "point_type": "destination", "points_str": "45.491087, -122.59983" }, "geometry": { "type": "Point", "coordinates": [ -122.599829588901571, 45.491087187818444 ] } }
]
}
