{
"type": "FeatureCollection",
"name": "origin_destination_points",
"crs": { "type": "name", "properties": { "name": "urn:ogc:def:crs:OGC:1.3:CRS84" } },
"features": [
{ "type": "Feature", "properties": { "point_type": "origin", "points_str": "45.522629, -122.712165" }, "geometry": { "type": "Point", "coordinates": [ -122.71216544713559, 45.522629412024166 ] } },
{ "type": "Feature", "properties": { "point_type": "destination", "points_str": "45.583635, -122.643127" }, "geometry": { "type": "Point", "coordinates": [ -122.643127223597887, 45.583634614407586 ] } }
]
}
