{
"type": "FeatureCollection",
"name": "origin_destination_points",
"crs": { "type": "name", "properties": { "name": "urn:ogc:def:crs:OGC:1.3:CRS84" } },
"features": [
{ "type": "Feature", "properties": { "point_type": "origin", "points_str": "45.498751, -122.433699" }, "geometry": { "type": "Point", "coordinates": [ -122.4336993526735, 45.498750958576984 ] } },
{ "type": "Feature", "properties": { "point_type": "destination", "points_str": "45.530364, -122.912871" }, "geometry": { "type": "Point", "coordinates": [ -122.912871022549538, 45.530363970355324 ] } }
]
}
