{
"type": "FeatureCollection",
"name": "origin_destination_points",
"crs": { "type": "name", "properties": { "name": "urn:ogc:def:crs:OGC:1.3:CRS84" } },
"features": [
{ "type": "Feature", "properties": { "point_type": "origin", "points_str": "45.388442, -122.608412" }, "geometry": { "type": "Point", "coordinates": [ -122.608411725306297, 45.388441723213909 ] } },
{ "type": "Feature", "properties": { "point_type": "destination", "points_str": "45.323314, -122.577127" }, "geometry": { "type": "Point", "coordinates": [ -122.577127494377123, 45.323313761250553 ] } }
]
}
