{
"type": "FeatureCollection",
"crs": { "type": "name", "properties": { "name": "urn:ogc:def:crs:OGC:1.3:CRS84" } },
"features": [
{ "type": "Feature", "properties": { "point_type": "origin", "points_str": "45.47977, -122.651028" }, "geometry": { "type": "Point", "coordinates": [ -122.651028368405761, 45.479770147623988 ] } },
{ "type": "Feature", "properties": { "point_type": "destination", "points_str": "45.513828, -122.620823" }, "geometry": { "type": "Point", "coordinates": [ -122.620823404824407, 45.513828166988894 ] } }
]
}
