{
"type": "FeatureCollection",
"name": "origin_destination_points",
"crs": { "type": "name", "properties": { "name": "urn:ogc:def:crs:OGC:1.3:CRS84" } },
"features": [
{ "type": "Feature", "properties": { "point_type": "origin", "points_str": "45.509414, -122.839931" }, "geometry": { "type": "Point", "coordinates": [ -122.839930567959783, 45.509414341180872 ] } },
{ "type": "Feature", "properties": { "point_type": "destination", "points_str": "45.522123, -122.675077" }, "geometry": { "type": "Point", "coordinates": [ -122.675076908496251, 45.522123305785684 ] } }
]
}
