{
"type": "FeatureCollection",
"name": "origin_destination_points",
"crs": { "type": "name", "properties": { "name": "urn:ogc:def:crs:OGC:1.3:CRS84" } },
"features": [
{ "type": "Feature", "properties": { "point_type": "origin", "points_str": "45.525191, -122.80468" }, "geometry": { "type": "Point", "coordinates": [ -122.804680352113991, 45.525191042102072 ] } },
{ "type": "Feature", "properties": { "point_type": "destination", "points_str": "45.529683, -122.990717" }, "geometry": { "type": "Point", "coordinates": [ -122.990716958657089, 45.529682562994068 ] } }
]
}
