{
"type": "FeatureCollection",
"name": "origin_destination_points",
"crs": { "type": "name", "properties": { "name": "urn:ogc:def:crs:OGC:1.3:CRS84" } },
"features": [
{ "type": "Feature", "properties": { "point_type": "origin", "points_str": "45.465072, -122.641122" }, "geometry": { "type": "Point", "coordinates": [ -122.641122314828564, 45.46507151354578 ] } },
{ "type": "Feature", "properties": { "point_type": "destination", "points_str": "45.546261, -122.708448" }, "geometry": { "type": "Point", "coordinates": [ -122.70844833913074, 45.546261459535202 ] } }
]
}
