{
"type": "FeatureCollection",
"name": "origin_destination_points",
"crs": { "type": "name", "properties": { "name": "urn:ogc:def:crs:OGC:1.3:CRS84" } },
"features": [
{ "type": "Feature", "properties": { "point_type": "origin", "points_str": "45.325253, -122.582035" }, "geometry": { "type": "Point", "coordinates": [ -122.582035084038694, 45.325253183545911 ] } },
{ "type": "Feature", "properties": { "point_type": "destination", "points_str": "45.351911, -122.604325" }, "geometry": { "type": "Point", "coordinates": [ -122.604324505212972, 45.351911268052618 ] } }
]
}
