{
"type": "FeatureCollection",
"name": "origin_destination_points",
"crs": { "type": "name", "properties": { "name": "urn:ogc:def:crs:OGC:1.3:CRS84" } },
"features": [
{ "type": "Feature", "properties": { "point_type": "origin", "points_str": "45.523476, -122.482601" }, "geometry": { "type": "Point", "coordinates": [ -122.482601230257899, 45.523475605990043 ] } },
{ "type": "Feature", "properties": { "point_type": "destination", "points_str": "45.520943, -123.014996" }, "geometry": { "type": "Point", "coordinates": [ -123.014996065628395, 45.520943178153161 ] } }
]
}
