{
"type": "FeatureCollection",
"name": "origin_destination_points",
"crs": { "type": "name", "properties": { "name": "urn:ogc:def:crs:OGC:1.3:CRS84" } },
"features": [
{ "type": "Feature", "properties": { "point_type": "origin", "points_str": "45.467537, -122.707924" }, "geometry": { "type": "Point", "coordinates": [ -122.707923773524769, 45.467537134139846 ] } },
{ "type": "Feature", "properties": { "point_type": "destination", "points_str": "45.494851, -122.587107" }, "geometry": { "type": "Point", "coordinates": [ -122.587106838136407, 45.494851229382647 ] } }
]
}
