{
"type": "FeatureCollection",
"crs": { "type": "name", "properties": { "name": "urn:ogc:def:crs:OGC:1.3:CRS84" } },
"features": [
{ "type": "Feature", "properties": { "point_type": "origin", "points_str": "45.427732, -122.764831" }, "geometry": { "type": "Point", "coordinates": [ -122.76483113713816, 45.427731932167156 ] } },
{ "type": "Feature", "properties": { "point_type": "destination", "points_str": "45.46426, -122.754129" }, "geometry": { "type": "Point", "coordinates": [ -122.75412949023125, 45.46426013795832 ] } }
]
}
