{
"type": "FeatureCollection",
"crs": { "type": "name", "properties": { "name": "urn:ogc:def:crs:OGC:1.3:CRS84" } },
"features": [
{ "type": "Feature", "properties": { "point_type": "origin", "points_str": "45.376697, -122.750832" }, "geometry": { "type": "Point", "coordinates": [ -122.750831584479613, 45.376696908669025 ] } },
{ "type": "Feature", "properties": { "point_type": "destination", "points_str": "45.488154, -122.79202" }, "geometry": { "type": "Point", "coordinates": [ -122.792020333279709, 45.48815367485193 ] } }
]
}
