{
"type": "FeatureCollection",
"name": "origin_destination_points",
"crs": { "type": "name", "properties": { "name": "urn:ogc:def:crs:OGC:1.3:CRS84" } },
"features": [
{ "type": "Feature", "properties": { "point_type": "origin", "points_str": "45.521755, -122.966606" }, "geometry": { "type": "Point", "coordinates": [ -122.966606430447385, 45.521754683269442 ] } },
{ "type": "Feature", "properties": { "point_type": "destination", "points_str": "45.395604, -122.651855" }, "geometry": { "type": "Point", "coordinates": [ -122.651854823476, 45.39560394861784 ] } }
]
}
