{
"type": "FeatureCollection",
"name": "origin_destination_points",
"crs": { "type": "name", "properties": { "name": "urn:ogc:def:crs:OGC:1.3:CRS84" } },
"features": [
{ "type": "Feature", "properties": { "point_type": "origin", "points_str": "45.589184, -122.709769" }, "geometry": { "type": "Point", "coordinates": [ -122.709769203788809, 45.589184151323806 ] } },
{ "type": "Feature", "properties": { "point_type": "destination", "points_str": "45.572498, -122.623745" }, "geometry": { "type": "Point", "coordinates": [ -122.623745421988673, 45.572497875497774 ] } }
]
}
