{
"type": "FeatureCollection",
"crs": { "type": "name", "properties": { "name": "urn:ogc:def:crs:OGC:1.3:CRS84" } },
"features": [
{ "type": "Feature", "properties": { "point_type": "origin", "points_str": "45.539901, -122.693665" }, "geometry": { "type": "Point", "coordinates": [ -122.693665375739656, 45.539901308640665 ] } },
{ "type": "Feature", "properties": { "point_type": "destination", "points_str": "45.503788, -122.715943" }, "geometry": { "type": "Point", "coordinates": [ -122.715943281690443, 45.503787881914235 ] } }
]
}
