{
"type": "FeatureCollection",
"crs": { "type": "name", "properties": { "name": "urn:ogc:def:crs:OGC:1.3:CRS84" } },
"features": [
{ "type": "Feature", "properties": { "point_type": "origin", "points_str": "45.473649, -122.77726" }, "geometry": { "type": "Point", "coordinates": [ -122.777259697172212, 45.473648933660762 ] } },
{ "type": "Feature", "properties": { "point_type": "destination", "points_str": "45.381776, -122.760295" }, "geometry": { "type": "Point", "coordinates": [ -122.76029514051298, 45.381776134696295 ] } }
]
}
