{
"type": "FeatureCollection",
"name": "origin_destination_points",
"crs": { "type": "name", "properties": { "name": "urn:ogc:def:crs:OGC:1.3:CRS84" } },
"features": [
{ "type": "Feature", "properties": { "point_type": "origin", "points_str": "45.568483, -122.752478" }, "geometry": { "type": "Point", "coordinates": [ -122.752478014250698, 45.568483122493262 ] } },
{ "type": "Feature", "properties": { "point_type": "destination", "points_str": "45.547579, -122.395886" }, "geometry": { "type": "Point", "coordinates": [ -122.395885527573853, 45.547578943666615 ] } }
]
}
