{
"type": "FeatureCollection",
"crs": { "type": "name", "properties": { "name": "urn:ogc:def:crs:OGC:1.3:CRS84" } },
"features": [
{ "type": "Feature", "properties": { "point_type": "origin", "points_str": "45.525073, -122.612258" }, "geometry": { "type": "Point", "coordinates": [ -122.612258103927019, 45.525072711553257 ] } },
{ "type": "Feature", "properties": { "point_type": "destination", "points_str": "45.55511, -122.732746" }, "geometry": { "type": "Point", "coordinates": [ -122.732745737664942, 45.55510975000665 ] } }
]
}
