{
"type": "FeatureCollection",
"name": "origin_destination_points",
"crs": { "type": "name", "properties": { "name": "urn:ogc:def:crs:OGC:1.3:CRS84" } },
"features": [
{ "type": "Feature", "properties": { "point_type": "origin", "points_str": "45.614211, -122.681485" }, "geometry": { "type": "Point", "coordinates": [ -122.681484505893224, 45.614211424534382 ] } },
{ "type": "Feature", "properties": { "point_type": "destination", "points_str": "45.542377, -122.650879" }, "geometry": { "type": "Point", "coordinates": [ -122.650878743543302, 45.542377338522783 ] } }
]
}
