{
"type": "FeatureCollection",
"name": "origin_destination_points",
"crs": { "type": "name", "properties": { "name": "urn:ogc:def:crs:OGC:1.3:CRS84" } },
"features": [
{ "type": "Feature", "properties": { "point_type": "origin", "points_str": "45.518173, -123.004627" }, "geometry": { "type": "Point", "coordinates": [ -123.004627394634866, 45.518172723175958 ] } },
{ "type": "Feature", "properties": { "point_type": "destination", "points_str": "45.515776, -123.110811" }, "geometry": { "type": "Point", "coordinates": [ -123.110811274792013, 45.515776487825576 ] } }
]
}
