{
"type": "FeatureCollection",
"name": "origin_destination_points",
"crs": { "type": "name", "properties": { "name": "urn:ogc:def:crs:OGC:1.3:CRS84" } },
"features": [
{ "type": "Feature", "properties": { "point_type": "origin", "points_str": "45.558496, -122.548891" }, "geometry": { "type": "Point", "coordinates": [ -122.548890563966765, 45.558495800927055 ] } },
{ "type": "Feature", "properties": { "point_type": "destination", "points_str": "45.501587, -122.547542" }, "geometry": { "type": "Point", "coordinates": [ -122.547541914707793, 45.5015865221784 ] } }
]
}
