{
"type": "FeatureCollection",
"crs": { "type": "name", "properties": { "name": "urn:ogc:def:crs:OGC:1.3:CRS84" } },
"features": [
{ "type": "Feature", "properties": { "point_type": "origin", "points_str": "45.447991, -122.685982" }, "geometry": { "type": "Point", "coordinates": [ -122.685981947713486, 45.447991381911734 ] } },
{ "type": "Feature", "properties": { "point_type": "destination", "points_str": "45.488221, -122.566596" }, "geometry": { "type": "Point", "coordinates": [ -122.566595869561979, 45.488221085568256 ] } }
]
}
