{
"type": "FeatureCollection",
"name": "origin_destination_points",
"crs": { "type": "name", "properties": { "name": "urn:ogc:def:crs:OGC:1.3:CRS84" } },
"features": [
{ "type": "Feature", "properties": { "point_type": "origin", "points_str": "45.573023, -122.658485" }, "geometry": { "type": "Point", "coordinates": [ -122.658484530975471, 45.573023067765575 ] } },
{ "type": "Feature", "properties": { "point_type": "destination", "points_str": "45.592815, -122.719057" }, "geometry": { "type": "Point", "coordinates": [ -122.719056963693831, 45.592815335826117 ] } }
]
}
