{
"type": "FeatureCollection",
"name": "origin_destination_points",
"crs": { "type": "name", "properties": { "name": "urn:ogc:def:crs:OGC:1.3:CRS84" } },
"features": [
{ "type": "Feature", "properties": { "point_type": "origin", "points_str": "45.562999, -122.529254" }, "geometry": { "type": "Point", "coordinates": [ -122.529254130517359, 45.562998847292093 ] } },
{ "type": "Feature", "properties": { "point_type": "destination", "points_str": "45.509318, -122.600774" }, "geometry": { "type": "Point", "coordinates": [ -122.600774387276189, 45.509318254916387 ] } }
]
}
