{
"type": "FeatureCollection",
"crs": { "type": "name", "properties": { "name": "urn:ogc:def:crs:OGC:1.3:CRS84" } },
"features": [
{ "type": "Feature", "properties": { "point_type": "origin", "points_str": "45.384212, -122.579544" }, "geometry": { "type": "Point", "coordinates": [ -122.579544383105159, 45.384212158200476 ] } },
{ "type": "Feature", "properties": { "point_type": "destination", "points_str": "45.558156, -122.586053" }, "geometry": { "type": "Point", "coordinates": [ -122.586052654836024, 45.55815568167349 ] } }
]
}
