{
"type": "FeatureCollection",
"crs": { "type": "name", "properties": { "name": "urn:ogc:def:crs:OGC:1.3:CRS84" } },
"features": [
{ "type": "Feature", "properties": { "point_type": "origin", "points_str": "45.550377, -122.591914" }, "geometry": { "type": "Point", "coordinates": [ -122.59191356482215, 45.550377456656022 ] } },
{ "type": "Feature", "properties": { "point_type": "destination", "points_str": "45.457571, -122.583516" }, "geometry": { "type": "Point", "coordinates": [ -122.583516449445113, 45.45757089535546 ] } }
]
}
