{
"type": "FeatureCollection",
"name": "origin_destination_points",
"crs": { "type": "name", "properties": { "name": "urn:ogc:def:crs:OGC:1.3:CRS84" } },
"features": [
{ "type": "Feature", "properties": { "point_type": "origin", "points_str": "45.478173, -122.569368" }, "geometry": { "type": "Point", "coordinates": [ -122.56936752628468, 45.478172564371029 ] } },
{ "type": "Feature", "properties": { "point_type": "destination", "points_str": "45.408125, -122.657686" }, "geometry": { "type": "Point", "coordinates": [ -122.65768571424519, 45.408124508542713 ] } }
]
}
