{
"type": "FeatureCollection",
"name": "origin_destination_points",
"crs": { "type": "name", "properties": { "name": "urn:ogc:def:crs:OGC:1.3:CRS84" } },
"features": [
{ "type": "Feature", "properties": { "point_type": "origin", "points_str": "45.493207, -122.804554" }, "geometry": { "type": "Point", "coordinates": [ -122.804554297623724, 45.493207290702692 ] } },
{ "type": "Feature", "properties": { "point_type": "destination", "points_str": "45.358381, -122.844474" }, "geometry": { "type": "Point", "coordinates": [ -122.844474392351728, 45.358380555411095 ] } }
]
}
