{
"type": "FeatureCollection",
"name": "origin_destination_points",
"crs": { "type": "name", "properties": { "name": "urn:ogc:def:crs:OGC:1.3:CRS84" } },
"features": [
{ "type": "Feature", "properties": { "point_type": "origin", "points_str": "45.423101, -122.538935" }, "geometry": { "type": "Point", "coordinates": [ -122.538935029508494, 45.423100909352286 ] } },
{ "type": "Feature", "properties": { "point_type": "destination", "points_str": "45.406551, -122.556267" }, "geometry": { "type": "Point", "coordinates": [ -122.556266856013835, 45.406550705077407 ] } }
]
}
