{
"type": "FeatureCollection",
"crs": { "type": "name", "properties": { "name": "urn:ogc:def:crs:OGC:1.3:CRS84" } },
"features": [
{ "type": "Feature", "properties": { "point_type": "origin", "points_str": "45.464437, -122.551934" }, "geometry": { "type": "Point", "coordinates": [ -122.551933988244471, 45.464437434783882 ] } },
{ "type": "Feature", "properties": { "point_type": "destination", "points_str": "45.469893, -122.732738" }, "geometry": { "type": "Point", "coordinates": [ -122.732737615946661, 45.469893275216577 ] } }
]
}
