{
"type": "FeatureCollection",
"name": "origin_destination_points",
"crs": { "type": "name", "properties": { "name": "urn:ogc:def:crs:OGC:1.3:CRS84" } },
"features": [
{ "type": "Feature", "properties": { "point_type": "origin", "points_str": "45.535511, -122.698003" }, "geometry": { "type": "Point", "coordinates": [ -122.6980031846862, 45.535511119253073 ] } },
{ "type": "Feature", "properties": { "point_type": "destination", "points_str": "45.515692, -122.55587" }, "geometry": { "type": "Point", "coordinates": [ -122.555869759142212, 45.515692265745784 ] } }
]
}
