{
"type": "FeatureCollection",
"name": "origin_destination_points",
"crs": { "type": "name", "properties": { "name": "urn:ogc:def:crs:OGC:1.3:CRS84" } },
"features": [
{ "type": "Feature", "properties": { "point_type": "origin", "points_str": "45.519413, -122.641055" }, "geometry": { "type": "Point", "coordinates": [ -122.641054958381602, 45.519412749002562 ] } },
{ "type": "Feature", "properties": { "point_type": "destination", "points_str": "45.541471, -122.671744" }, "geometry": { "type": "Point", "coordinates": [ -122.671743648228031, 45.541471306040165 ] } }
]
}
