{
"type": "FeatureCollection",
"crs": { "type": "name", "properties": { "name": "urn:ogc:def:crs:OGC:1.3:CRS84" } },
"features": [
{ "type": "Feature", "properties": { "point_type": "origin", "points_str": "45.483717, -122.802937" }, "geometry": { "type": "Point", "coordinates": [ -122.802936934278677, 45.483716791260647 ] } },
{ "type": "Feature", "properties": { "point_type": "destination", "points_str": "45.604417, -122.688411" }, "geometry": { "type": "Point", "coordinates": [ -122.688411306794023, 45.604417002787159 ] } }
]
}
