{
"type": "FeatureCollection",
"name": "origin_destination_points",
"crs": { "type": "name", "properties": { "name": "urn:ogc:def:crs:OGC:1.3:CRS84" } },
"features": [
{ "type": "Feature", "properties": { "point_type": "origin", "points_str": "45.574994, -122.635516" }, "geometry": { "type": "Point", "coordinates": [ -122.635515884242963, 45.574993883400722 ] } },
{ "type": "Feature", "properties": { "point_type": "destination", "points_str": "45.603037, -122.758037" }, "geometry": { "type": "Point", "coordinates": [ -122.758037019020122, 45.603037467507598 ] } }
]
}
