{
"type": "FeatureCollection",
"name": "origin_destination_points",
"crs": { "type": "name", "properties": { "name": "urn:ogc:def:crs:OGC:1.3:CRS84" } },
"features": [
{ "type": "Feature", "properties": { "point_type": "origin", "points_str": "45.491123, -122.823937" }, "geometry": { "type": "Point", "coordinates": [ -122.82393738021527, 45.491122619307596 ] } },
{ "type": "Feature", "properties": { "point_type": "destination", "points_str": "45.415826, -122.763044" }, "geometry": { "type": "Point", "coordinates": [ -122.763043666254319, 45.415825841489145 ] } }
]
}
