{
"type": "FeatureCollection",
"name": "origin_destination_points",
"crs": { "type": "name", "properties": { "name": "urn:ogc:def:crs:OGC:1.3:CRS84" } },
"features": [
{ "type": "Feature", "properties": { "point_type": "origin", "points_str": "45.476222, -122.815054" }, "geometry": { "type": "Point", "coordinates": [ -122.815053571021451, 45.476222490638527 ] } },
{ "type": "Feature", "properties": { "point_type": "destination", "points_str": "45.374467, -122.712378" }, "geometry": { "type": "Point", "coordinates": [ -122.712378182403683, 45.374466820083356 ] } }
]
}
