{
"type": "FeatureCollection",
"name": "origin_destination_points",
"crs": { "type": "name", "properties": { "name": "urn:ogc:def:crs:OGC:1.3:CRS84" } },
"features": [
{ "type": "Feature", "properties": { "point_type": "origin", "points_str": "45.497596, -122.933237" }, "geometry": { "type": "Point", "coordinates": [ -122.933236581139084, 45.497596003568482 ] } },
{ "type": "Feature", "properties": { "point_type": "destination", "points_str": "45.527595, -122.561063" }, "geometry": { "type": "Point", "coordinates": [ -122.561062939022904, 45.527594638696662 ] } }
]
}
