{
"type": "FeatureCollection",
"name": "origin_destination_points",
"crs": { "type": "name", "properties": { "name": "urn:ogc:def:crs:OGC:1.3:CRS84" } },
"features": [
{ "type": "Feature", "properties": { "point_type": "origin", "points_str": "45.427088, -122.656742" }, "geometry": { "type": "Point", "coordinates": [ -122.656741611347996, 45.42708774818594 ] } },
{ "type": "Feature", "properties": { "point_type": "destination", "points_str": "45.374427, -122.717198" }, "geometry": { "type": "Point", "coordinates": [ -122.717198313383548, 45.374427303044307 ] } }
]
}
