{
"type": "FeatureCollection",
"name": "origin_destination_points",
"crs": { "type": "name", "properties": { "name": "urn:ogc:def:crs:OGC:1.3:CRS84" } },
"features": [
{ "type": "Feature", "properties": { "point_type": "origin", "points_str": "45.584297, -122.727348" }, "geometry": { "type": "Point", "coordinates": [ -122.727347729909354, 45.584296762378095 ] } },
{ "type": "Feature", "properties": { "point_type": "destination", "points_str": "45.516103, -122.86731" }, "geometry": { "type": "Point", "coordinates": [ -122.867310221609003, 45.516103118129358 ] } }
]
}
