{
"type": "FeatureCollection",
"name": "origin_destination_points",
"crs": { "type": "name", "properties": { "name": "urn:ogc:def:crs:OGC:1.3:CRS84" } },
"features": [
{ "type": "Feature", "properties": { "point_type": "origin", "points_str": "45.524107, -122.550689" }, "geometry": { "type": "Point", "coordinates": [ -122.550688825373996, 45.524106895410263 ] } },
{ "type": "Feature", "properties": { "point_type": "destination", "points_str": "45.549611, -122.541781" }, "geometry": { "type": "Point", "coordinates": [ -122.541781237584033, 45.549610529951174 ] } }
]
}
