{
"type": "FeatureCollection",
"name": "origin_destination_points",
"crs": { "type": "name", "properties": { "name": "urn:ogc:def:crs:OGC:1.3:CRS84" } },
"features": [
{ "type": "Feature", "properties": { "point_type": "origin", "points_str": "45.532245, -122.951738" }, "geometry": { "type": "Point", "coordinates": [ -122.951737834187412, 45.532244646322432 ] } },
{ "type": "Feature", "properties": { "point_type": "destination", "points_str": "45.522565, -122.987198" }, "geometry": { "type": "Point", "coordinates": [ -122.987197737849669, 45.522565461328796 ] } }
]
}
