{
"type": "FeatureCollection",
"name": "origin_destination_points",
"crs": { "type": "name", "properties": { "name": "urn:ogc:def:crs:OGC:1.3:CRS84" } },
"features": [
{ "type": "Feature", "properties": { "point_type": "origin", "points_str": "45.501014, -122.927345" }, "geometry": { "type": "Point", "coordinates": [ -122.927345159814095, 45.501013518556931 ] } },
{ "type": "Feature", "properties": { "point_type": "destination", "points_str": "45.458664, -122.825838" }, "geometry": { "type": "Point", "coordinates": [ -122.825837868100891, 45.458664266054932 ] } }
]
}
