{
"type": "FeatureCollection",
"name": "origin_destination_points",
"crs": { "type": "name", "properties": { "name": "urn:ogc:def:crs:OGC:1.3:CRS84" } },
"features": [
{ "type": "Feature", "properties": { "point_type": "origin", "points_str": "45.504006, -122.628247" }, "geometry": { "type": "Point", "coordinates": [ -122.628247066561315, 45.504005934746552 ] } },
{ "type": "Feature", "properties": { "point_type": "destination", "points_str": "45.498469, -122.574568" }, "geometry": { "type": "Point", "coordinates": [ -122.57456840817845, 45.498469439741761 ] } }
]
}
