{
"type": "FeatureCollection",
"crs": { "type": "name", "properties": { "name": "urn:ogc:def:crs:OGC:1.3:CRS84" } },
"features": [
{ "type": "Feature", "properties": { "point_type": "origin", "points_str": "45.542305, -122.605957" }, "geometry": { "type": "Point", "coordinates": [ -122.605956738684867, 45.542304517668363 ] } },
{ "type": "Feature", "properties": { "point_type": "destination", "points_str": "45.510526, -122.612067" }, "geometry": { "type": "Point", "coordinates": [ -122.612067273281639, 45.510526050449648 ] } }
]
}
