{
"type": "FeatureCollection",
"name": "origin_destination_points",
"crs": { "type": "name", "properties": { "name": "urn:ogc:def:crs:OGC:1.3:CRS84" } },
"features": [
{ "type": "Feature", "properties": { "point_type": "origin", "points_str": "45.539519, -122.61661" }, "geometry": { "type": "Point", "coordinates": [ -122.616609711557061, 45.539518514998505 ] } },
{ "type": "Feature", "properties": { "point_type": "destination", "points_str": "45.467321, -122.719602" }, "geometry": { "type": "Point", "coordinates": [ -122.719602179543514, 45.46732061033638 ] } }
]
}
