{
"type": "FeatureCollection",
"crs": { "type": "name", "properties": { "name": "urn:ogc:def:crs:OGC:1.3:CRS84" } },
"features": [
{ "type": "Feature", "properties": { "point_type": "origin", "points_str": "45.413925, -122.50676" }, "geometry": { "type": "Point", "coordinates": [ -122.506759756125348, 45.413925191189392 ] } },
{ "type": "Feature", "properties": { "point_type": "destination", "points_str": "45.396323, -122.500046" }, "geometry": { "type": "Point", "coordinates": [ -122.500045517978791, 45.396322546058997 ] } }
]
}
