{
"type": "FeatureCollection",
"name": "origin_destination_points",
"crs": { "type": "name", "properties": { "name": "urn:ogc:def:crs:OGC:1.3:CRS84" } },
"features": [
{ "type": "Feature", "properties": { "point_type": "origin", "points_str": "45.491029, -122.679068" }, "geometry": { "type": "Point", "coordinates": [ -122.679067858873253, 45.491029478705265 ] } },
{ "type": "Feature", "properties": { "point_type": "destination", "points_str": "45.443693, -122.729969" }, "geometry": { "type": "Point", "coordinates": [ -122.729969244671011, 45.443693106834004 ] } }
]
}
