{
"type": "FeatureCollection",
"name": "origin_destination_points",
"crs": { "type": "name", "properties": { "name": "urn:ogc:def:crs:OGC:1.3:CRS84" } },
"features": [
{ "type": "Feature", "properties": { "point_type": "origin", "points_str": "45.527523, -122.675087" }, "geometry": { "type": "Point", "coordinates": [ -122.675086859621075, 45.527523311470645 ] } },
{ "type": "Feature", "properties": { "point_type": "destination", "points_str": "45.578462, -122.6319" }, "geometry": { "type": "Point", "coordinates": [ -122.631899869386515, 45.578461518267666 ] } }
]
}
