{
"type": "FeatureCollection",
"crs": { "type": "name", "properties": { "name": "urn:ogc:def:crs:OGC:1.3:CRS84" } },
"features": [
{ "type": "Feature", "properties": { "point_type": "origin", "points_str": "45.445252, -122.72762" }, "geometry": { "type": "Point", "coordinates": [ -122.727619538504669, 45.445251752872636 ] } },
{ "type": "Feature", "properties": { "point_type": "destination", "points_str": "45.506056, -122.557494" }, "geometry": { "type": "Point", "coordinates": [ -122.557494281504987, 45.506055781628994 ] } }
]
}
