{
"type": "FeatureCollection",
"name": "origin_destination_points",
"crs": { "type": "name", "properties": { "name": "urn:ogc:def:crs:OGC:1.3:CRS84" } },
"features": [
{ "type": "Feature", "properties": { "point_type": "origin", "points_str": "45.559159, -122.673264" }, "geometry": { "type": "Point", "coordinates": [ -122.673264404627702, 45.559159324242287 ] } },
{ "type": "Feature", "properties": { "point_type": "destination", "points_str": "45.515274, -122.613281" }, "geometry": { "type": "Point", "coordinates": [ -122.613280847044734, 45.51527372780248 ] } }
]
}
