{
"type": "FeatureCollection",
"name": "origin_destination_points",
"crs": { "type": "name", "properties": { "name": "urn:ogc:def:crs:OGC:1.3:CRS84" } },
"features": [
{ "type": "Feature", "properties": { "point_type": "origin", "points_str": "45.521347, -122.809956" }, "geometry": { "type": "Point", "coordinates": [ -122.809956292320479, 45.521346610338497 ] } },
{ "type": "Feature", "properties": { "point_type": "destination", "points_str": "45.520206, -122.989666" }, "geometry": { "type": "Point", "coordinates": [ -122.989666354861725, 45.520206352945465 ] } }
]
}
