{
"type": "FeatureCollection",
"crs": { "type": "name", "properties": { "name": "urn:ogc:def:crs:OGC:1.3:CRS84" } },
"features": [
{ "type": "Feature", "properties": { "point_type": "origin", "points_str": "45.385213, -122.589875" }, "geometry": { "type": "Point", "coordinates": [ -122.589875230695526, 45.385212505575673 ] } },
{ "type": "Feature", "properties": { "point_type": "destination", "points_str": "45.37322, -122.62136" }, "geometry": { "type": "Point", "coordinates": [ -122.621360469528327, 45.37322045031906 ] } }
]
}
