{
"type": "FeatureCollection",
"name": "origin_destination_points",
"crs": { "type": "name", "properties": { "name": "urn:ogc:def:crs:OGC:1.3:CRS84" } },
"features": [
{ "type": "Feature", "properties": { "point_type": "origin", "points_str": "45.555955, -122.662258" }, "geometry": { "type": "Point", "coordinates": [ -122.662258246498226, 45.555955307858099 ] } },
{ "type": "Feature", "properties": { "point_type": "destination", "points_str": "45.486523, -122.632596" }, "geometry": { "type": "Point", "coordinates": [ -122.632596476031679, 45.486523348715799 ] } }
]
}
