{
"type": "FeatureCollection",
"name": "origin_destination_points",
"crs": { "type": "name", "properties": { "name": "urn:ogc:def:crs:OGC:1.3:CRS84" } },
"features": [
{ "type": "Feature", "properties": { "point_type": "origin", "points_str": "45.596787, -122.75534" }, "geometry": { "type": "Point", "coordinates": [ -122.755340188666423, 45.596786994043079 ] } },
{ "type": "Feature", "properties": { "point_type": "destination", "points_str": "45.526846, -122.66559" }, "geometry": { "type": "Point", "coordinates": [ -122.665589875421915, 45.526845950958041 ] } }
]
}
