{
"type": "FeatureCollection",
"name": "origin_destination_points",
"crs": { "type": "name", "properties": { "name": "urn:ogc:def:crs:OGC:1.3:CRS84" } },
"features": [
{ "type": "Feature", "properties": { "point_type": "origin", "points_str": "45.496891, -122.557202" }, "geometry": { "type": "Point", "coordinates": [ -122.557202039765471, 45.496890620207331 ] } },
{ "type": "Feature", "properties": { "point_type": "destination", "points_str": "45.599019, -122.764524" }, "geometry": { "type": "Point", "coordinates": [ -122.764523788303734, 45.599019185626176 ] } }
]
}
