{
"type": "FeatureCollection",
"crs": { "type": "name", "properties": { "name": "urn:ogc:def:crs:OGC:1.3:CRS84" } },
"features": [
{ "type": "Feature", "properties": { "point_type": "origin", "points_str": "45.493196, -122.773757" }, "geometry": { "type": "Point", "coordinates": [ -122.773756516355533, 45.493196334685386 ] } },
{ "type": "Feature", "properties": { "point_type": "destination", "points_str": "45.498085, -122.606987" }, "geometry": { "type": "Point", "coordinates": [ -122.606986858364323, 45.498084788833957 ] } }
]
}
