{
"type": "FeatureCollection",
"name": "origin_destination_points",
"crs": { "type": "name", "properties": { "name": "urn:ogc:def:crs:OGC:1.3:CRS84" } },
"features": [
{ "type": "Feature", "properties": { "point_type": "origin", "points_str": "45.498548, -122.628071" }, "geometry": { "type": "Point", "coordinates": [ -122.628071486617728, 45.498548170559545 ] } },
{ "type": "Feature", "properties": { "point_type": "destination", "points_str": "45.498498, -122.754315" }, "geometry": { "type": "Point", "coordinates": [ -122.754315357173226, 45.49849788089336 ] } }
]
}
