{
"type": "FeatureCollection",
"crs": { "type": "name", "properties": { "name": "urn:ogc:def:crs:OGC:1.3:CRS84" } },
"features": [
{ "type": "Feature", "properties": { "point_type": "origin", "points_str": "45.497649, -122.894497" }, "geometry": { "type": "Point", "coordinates": [ -122.894496874898365, 45.497648619729539 ] } },
{ "type": "Feature", "properties": { "point_type": "destination", "points_str": "45.518234, -123.08449" }, "geometry": { "type": "Point", "coordinates": [ -123.084490202631173, 45.518233867219841 ] } }
]
}
