{
"type": "FeatureCollection",
"crs": { "type": "name", "properties": { "name": "urn:ogc:def:crs:OGC:1.3:CRS84" } },
"features": [
{ "type": "Feature", "properties": { "point_type": "origin", "points_str": "45.473591, -122.579774" }, "geometry": { "type": "Point", "coordinates": [ -122.579774395135502, 45.473590913204944 ] } },
{ "type": "Feature", "properties": { "point_type": "destination", "points_str": "45.530583, -122.93494" }, "geometry": { "type": "Point", "coordinates": [ -122.934939597898989, 45.530582870925507 ] } }
]
}
