{
"type": "FeatureCollection",
"name": "origin_destination_points",
"crs": { "type": "name", "properties": { "name": "urn:ogc:def:crs:OGC:1.3:CRS84" } },
"features": [
{ "type": "Feature", "properties": { "point_type": "origin", "points_str": "45.528183, -122.910102" }, "geometry": { "type": "Point", "coordinates": [ -122.910102398142129, 45.528183133192115 ] } },
{ "type": "Feature", "properties": { "point_type": "destination", "points_str": "45.575851, -122.56897" }, "geometry": { "type": "Point", "coordinates": [ -122.568970253806611, 45.57585120219774 ] } }
]
}
