{
"type": "FeatureCollection",
"name": "origin_destination_points",
"crs": { "type": "name", "properties": { "name": "urn:ogc:def:crs:OGC:1.3:CRS84" } },
"features": [
{ "type": "Feature", "properties": { "point_type": "origin", "points_str": "45.453842, -122.602448" }, "geometry": { "type": "Point", "coordinates": [ -122.602447545363461, 45.453841908301179 ] } },
{ "type": "Feature", "properties": { "point_type": "destination", "points_str": "45.386173, -122.453361" }, "geometry": { "type": "Point", "coordinates": [ -122.453360681990077, 45.386173353888516 ] } }
]
}
