{
"type": "FeatureCollection",
"name": "origin_destination_points",
"crs": { "type": "name", "properties": { "name": "urn:ogc:def:crs:OGC:1.3:CRS84" } },
"features": [
{ "type": "Feature", "properties": { "point_type": "origin", "points_str": "45.353526, -122.769699" }, "geometry": { "type": "Point", "coordinates": [ -122.769698587376368, 45.353525541226887 ] } },
{ "type": "Feature", "properties": { "point_type": "destination", "points_str": "45.525819, -122.67136" }, "geometry": { "type": "Point", "coordinates": [ -122.671360145540646, 45.525818702912723 ] } }
]
}
