{
"type": "FeatureCollection",
"name": "origin_destination_points",
"crs": { "type": "name", "properties": { "name": "urn:ogc:def:crs:OGC:1.3:CRS84" } },
"features": [
{ "type": "Feature", "properties": { "point_type": "origin", "points_str": "45.533774, -122.860267" }, "geometry": { "type": "Point", "coordinates": [ -122.860266872372407, 45.5337744092664 ] } },
{ "type": "Feature", "properties": { "point_type": "destination", "points_str": "45.521882, -123.041869" }, "geometry": { "type": "Point", "coordinates": [ -123.041868791994105, 45.521882052504886 ] } }
]
}
