{
"type": "FeatureCollection",
"crs": { "type": "name", "properties": { "name": "urn:ogc:def:crs:OGC:1.3:CRS84" } },
"features": [
{ "type": "Feature", "properties": { "point_type": "origin", "points_str": "45.42352, -122.633194" }, "geometry": { "type": "Point", "coordinates": [ -122.633194275847558, 45.423520086089539 ] } },
{ "type": "Feature", "properties": { "point_type": "destination", "points_str": "45.435276, -122.734709" }, "geometry": { "type": "Point", "coordinates": [ -122.734708543120533, 45.435275984935245 ] } }
]
}
