{
"type": "FeatureCollection",
"crs": { "type": "name", "properties": { "name": "urn:ogc:def:crs:OGC:1.3:CRS84" } },
"features": [
{ "type": "Feature", "properties": { "point_type": "origin", "points_str": "45.522735, -122.615511" }, "geometry": { "type": "Point", "coordinates": [ -122.615510755089346, 45.522735281209471 ] } },
{ "type": "Feature", "properties": { "point_type": "destination", "points_str": "45.416223, -122.543777" }, "geometry": { "type": "Point", "coordinates": [ -122.543776828908918, 45.416223156121561 ] } }
]
}
