{
"type": "FeatureCollection",
"crs": { "type": "name", "properties": { "name": "urn:ogc:def:crs:OGC:1.3:CRS84" } },
"features": [
{ "type": "Feature", "properties": { "point_type": "origin", "points_str": "45.518225, -122.524971" }, "geometry": { "type": "Point", "coordinates": [ -122.52497073297765, 45.518225350112644 ] } },
{ "type": "Feature", "properties": { "point_type": "destination", "points_str": "45.396476, -122.657059" }, "geometry": { "type": "Point", "coordinates": [ -122.657059470499149, 45.396475617804285 ] } }
]
}
