{
"type": "FeatureCollection",
"name": "origin_destination_points",
"crs": { "type": "name", "properties": { "name": "urn:ogc:def:crs:OGC:1.3:CRS84" } },
"features": [
{ "type": "Feature", "properties": { "point_type": "origin", "points_str": "45.427944, -122.704231" }, "geometry": { "type": "Point", "coordinates": [ -122.704230553670513, 45.427943896694345 ] } },
{ "type": "Feature", "properties": { "point_type": "destination", "points_str": "45.413727, -122.76527" }, "geometry": { "type": "Point", "coordinates": [ -122.765269660333857, 45.413726890562018 ] } }
]
}
