{
"type": "FeatureCollection",
"crs": { "type": "name", "properties": { "name": "urn:ogc:def:crs:OGC:1.3:CRS84" } },
"features": [
{ "type": "Feature", "properties": { "point_type": "origin", "points_str": "45.436816, -122.577744" }, "geometry": { "type": "Point", "coordinates": [ -122.577743819160986, 45.436815994304602 ] } },
{ "type": "Feature", "properties": { "point_type": "destination", "points_str": "45.519131, -122.465402" }, "geometry": { "type": "Point", "coordinates": [ -122.465401927961182, 45.519130723865288 ] } }
]
}
