{
"type": "FeatureCollection",
"name": "origin_destination_points",
"crs": { "type": "name", "properties": { "name": "urn:ogc:def:crs:OGC:1.3:CRS84" } },
"features": [
{ "type": "Feature", "properties": { "point_type": "origin", "points_str": "45.463761, -122.825446" }, "geometry": { "type": "Point", "coordinates": [ -122.825446369864494, 45.463761152789886 ] } },
{ "type": "Feature", "properties": { "point_type": "destination", "points_str": "45.504866, -122.882223" }, "geometry": { "type": "Point", "coordinates": [ -122.882222793585001, 45.504866345941316 ] } }
]
}
