{
"type": "FeatureCollection",
"name": "origin_destination_points",
"crs": { "type": "name", "properties": { "name": "urn:ogc:def:crs:OGC:1.3:CRS84" } },
"features": [
{ "type": "Feature", "properties": { "point_type": "origin", "points_str": "45.520356, -122.550432" }, "geometry": { "type": "Point", "coordinates": [ -122.550432318337585, 45.520356321311745 ] } },
{ "type": "Feature", "properties": { "point_type": "destination", "points_str": "45.454235, -122.633724" }, "geometry": { "type": "Point", "coordinates": [ -122.633724487332429, 45.454234824816794 ] } }
]
}
