{
"type": "FeatureCollection",
"name": "origin_destination_points",
"crs": { "type": "name", "properties": { "name": "urn:ogc:def:crs:OGC:1.3:CRS84" } },
"features": [
{ "type": "Feature", "properties": { "point_type": "origin", "points_str": "45.520966, -122.499102" }, "geometry": { "type": "Point", "coordinates": [ -122.499101822177394, 45.520965595397335 ] } },
{ "type": "Feature", "properties": { "point_type": "destination", "points_str": "45.517025, -122.558878" }, "geometry": { "type": "Point", "coordinates": [ -122.558878463581067, 45.517024540589645 ] } }
]
}
