{
"type": "FeatureCollection",
"crs": { "type": "name", "properties": { "name": "urn:ogc:def:crs:OGC:1.3:CRS84" } },
"features": [
{ "type": "Feature", "properties": { "point_type": "origin", "points_str": "45.535629, -122.611239" }, "geometry": { "type": "Point", "coordinates": [ -122.611239054524347, 45.535629035132523 ] } },
{ "type": "Feature", "properties": { "point_type": "destination", "points_str": "45.493784, -122.707112" }, "geometry": { "type": "Point", "coordinates": [ -122.707112200126971, 45.493783521120761 ] } }
]
}
