{
"type": "FeatureCollection",
"name": "origin_destination_points",
"crs": { "type": "name", "properties": { "name": "urn:ogc:def:crs:OGC:1.3:CRS84" } },
"features": [
{ "type": "Feature", "properties": { "point_type": "origin", "points_str": "45.514438, -122.798251" }, "geometry": { "type": "Point", "coordinates": [ -122.798251288496459, 45.514438079523345 ] } },
{ "type": "Feature", "properties": { "point_type": "destination", "points_str": "45.519165, -122.638206" }, "geometry": { "type": "Point", "coordinates": [ -122.638205903729272, 45.519164795508381 ] } }
]
}
