{
"type": "FeatureCollection",
"crs": { "type": "name", "properties": { "name": "urn:ogc:def:crs:OGC:1.3:CRS84" } },
"features": [
{ "type": "Feature", "properties": { "point_type": "origin", "points_str": "45.529616, -122.646879" }, "geometry": { "type": "Point", "coordinates": [ -122.646878810975693, 45.529616209893916 ] } },
{ "type": "Feature", "properties": { "point_type": "destination", "points_str": "45.49707, -122.657872" }, "geometry": { "type": "Point", "coordinates": [ -122.65787222052225, 45.497070113085364 ] } }
]
}
