{
"type": "FeatureCollection",
"name": "origin_destination_points",
"crs": { "type": "name", "properties": { "name": "urn:ogc:def:crs:OGC:1.3:CRS84" } },
"features": [
{ "type": "Feature", "properties": { "point_type": "origin", "points_str": "45.543414, -122.608106" }, "geometry": { "type": "Point", "coordinates": [ -122.608106213778058, 45.543414271175372 ] } },
{ "type": "Feature", "properties": { "point_type": "destination", "points_str": "45.549782, -122.670633" }, "geometry": { "type": "Point", "coordinates": [ -122.67063272202607, 45.549781670404556 ] } }
]
}
