{
"type": "FeatureCollection",
"name": "origin_destination_points",
"crs": { "type": "name", "properties": { "name": "urn:ogc:def:crs:OGC:1.3:CRS84" } },
"features": [
{ "type": "Feature", "properties": { "point_type": "origin", "points_str": "45.533281, -122.873461" }, "geometry": { "type": "Point", "coordinates": [ -122.873461397123478, 45.533280860991098 ] } },
{ "type": "Feature", "properties": { "point_type": "destination", "points_str": "45.510823, -122.796912" }, "geometry": { "type": "Point", "coordinates": [ -122.796911715272827, 45.510822886097174 ] } }
]
}
