{
"type": "FeatureCollection",
"name": "origin_destination_points",
"crs": { "type": "name", "properties": { "name": "urn:ogc:def:crs:OGC:1.3:CRS84" } },
"features": [
{ "type": "Feature", "properties": { "point_type": "origin", "points_str": "45.513171, -122.456984" }, "geometry": { "type": "Point", "coordinates": [ -122.456983563005679, 45.513171457160347 ] } },
{ "type": "Feature", "properties": { "point_type": "destination", "points_str": "45.547167, -122.898131" }, "geometry": { "type": "Point", "coordinates": [ -122.898131379658565, 45.547167345445686 ] } }
]
}
