{
"type": "FeatureCollection",
"crs": { "type": "name", "properties": { "name": "urn:ogc:def:crs:OGC:1.3:CRS84" } },
"features": [
{ "type": "Feature", "properties": { "point_type": "origin", "points_str": "45.569081, -122.621631" }, "geometry": { "type": "Point", "coordinates": [ -122.621631147361398, 45.569080683391377 ] } },
{ "type": "Feature", "properties": { "point_type": "destination", "points_str": "45.394374, -122.592199" }, "geometry": { "type": "Point", "coordinates": [ -122.592199188794083, 45.394373675787115 ] } }
]
}
