{
"type": "FeatureCollection",
"name": "origin_destination_points",
"crs": { "type": "name", "properties": { "name": "urn:ogc:def:crs:OGC:1.3:CRS84" } },
"features": [
{ "type": "Feature", "properties": { "point_type": "origin", "points_str": "45.586373, -122.718698" }, "geometry": { "type": "Point", "coordinates": [ -122.718697978118996, 45.586372745597906 ] } },
{ "type": "Feature", "properties": { "point_type": "destination", "points_str": "45.533501, -122.686486" }, "geometry": { "type": "Point", "coordinates": [ -122.686485968047307, 45.53350051772594 ] } }
]
}
