{
"type": "FeatureCollection",
"name": "origin_destination_points",
"crs": { "type": "name", "properties": { "name": "urn:ogc:def:crs:OGC:1.3:CRS84" } },
"features": [
{ "type": "Feature", "properties": { "point_type": "origin", "points_str": "45.491874, -122.849083" }, "geometry": { "type": "Point", "coordinates": [ -122.849082825505846, 45.491874074188843 ] } },
{ "type": "Feature", "properties": { "point_type": "destination", "points_str": "45.514395, -122.457439" }, "geometry": { "type": "Point", "coordinates": [ -122.457438583610724, 45.514394909820794 ] } }
]
}
