{
"type": "FeatureCollection",
"name": "origin_destination_points",
"crs": { "type": "name", "properties": { "name": "urn:ogc:def:crs:OGC:1.3:CRS84" } },
"features": [
{ "type": "Feature", "properties": { "point_type": "origin", "points_str": "45.510052, -122.782746" }, "geometry": { "type": "Point", "coordinates": [ -122.782746336763282, 45.510051726724321 ] } },
{ "type": "Feature", "properties": { "point_type": "destination", "points_str": "45.551504, -122.834966" }, "geometry": { "type": "Point", "coordinates": [ -122.834966031047287, 45.551503940103323 ] } }
]
}
