{
"type": "FeatureCollection",
"name": "origin_destination_points",
"crs": { "type": "name", "properties": { "name": "urn:ogc:def:crs:OGC:1.3:CRS84" } },
"features": [
{ "type": "Feature", "properties": { "point_type": "origin", "points_str": "45.523645, -122.606108" }, "geometry": { "type": "Point", "coordinates": [ -122.606108342559821, 45.523645464242811 ] } },
{ "type": "Feature", "properties": { "point_type": "destination", "points_str": "45.614555, -122.685642" }, "geometry": { "type": "Point", "coordinates": [ -122.685641856120355, 45.614555181629491 ] } }
]
}
