{
"type": "FeatureCollection",
"name": "origin_destination_points",
"crs": { "type": "name", "properties": { "name": "urn:ogc:def:crs:OGC:1.3:CRS84" } },
"features": [
{ "type": "Feature", "properties": { "point_type": "origin", "points_str": "45.400175, -122.634063" }, "geometry": { "type": "Point", "coordinates": [ -122.634062756881193, 45.40017540790609 ] } },
{ "type": "Feature", "properties": { "point_type": "destination", "points_str": "45.465629, -122.647657" }, "geometry": { "type": "Point", "coordinates": [ -122.647656906241622, 45.465629151483284 ] } }
]
}
