{
"type": "FeatureCollection",
"crs": { "type": "name", "properties": { "name": "urn:ogc:def:crs:OGC:1.3:CRS84" } },
"features": [
{ "type": "Feature", "properties": { "point_type": "origin", "points_str": "45.51824, -122.507727" }, "geometry": { "type": "Point", "coordinates": [ -122.507727159798407, 45.518239936152646 ] } },
{ "type": "Feature", "properties": { "point_type": "destination", "points_str": "45.449443, -122.663093" }, "geometry": { "type": "Point", "coordinates": [ -122.663093109763182, 45.44944302331686 ] } }
]
}
