{
"type": "FeatureCollection",
"name": "origin_destination_points",
"crs": { "type": "name", "properties": { "name": "urn:ogc:def:crs:OGC:1.3:CRS84" } },
"features": [
{ "type": "Feature", "properties": { "point_type": "origin", "points_str": "45.550503, -122.909387" }, "geometry": { "type": "Point", "coordinates": [ -122.90938689726471, 45.55050328035388 ] } },
{ "type": "Feature", "properties": { "point_type": "destination", "points_str": "45.523033, -123.073179" }, "geometry": { "type": "Point", "coordinates": [ -123.073179021160286, 45.523033049800169 ] } }
]
}
