{
"type": "FeatureCollection",
"name": "origin_destination_points",
"crs": { "type": "name", "properties": { "name": "urn:ogc:def:crs:OGC:1.3:CRS84" } },
"features": [
{ "type": "Feature", "properties": { "point_type": "origin", "points_str": "45.522557, -122.792816" }, "geometry": { "type": "Point", "coordinates": [ -122.792815731047781, 45.522556809905865 ] } },
{ "type": "Feature", "properties": { "point_type": "destination", "points_str": "45.512449, -122.458174" }, "geometry": { "type": "Point", "coordinates": [ -122.458174326038915, 45.512448606579696 ] } }
]
}
