{
"type": "FeatureCollection",
"crs": { "type": "name", "properties": { "name": "urn:ogc:def:crs:OGC:1.3:CRS84" } },
"features": [
{ "type": "Feature", "properties": { "point_type": "origin", "points_str": "45.44473, -122.778647" }, "geometry": { "type": "Point", "coordinates": [ -122.778646781549796, 45.444730066351887 ] } },
{ "type": "Feature", "properties": { "point_type": "destination", "points_str": "45.41704, -122.732729" }, "geometry": { "type": "Point", "coordinates": [ -122.73272880551545, 45.41703959677816 ] } }
]
}
