{
"type": "FeatureCollection",
"name": "origin_destination_points",
"crs": { "type": "name", "properties": { "name": "urn:ogc:def:crs:OGC:1.3:CRS84" } },
"features": [
{ "type": "Feature", "properties": { "point_type": "origin", "points_str": "45.529712, -122.654051" }, "geometry": { "type": "Point", "coordinates": [ -122.654050840766416, 45.529711704839762 ] } },
{ "type": "Feature", "properties": { "point_type": "destination", "points_str": "45.477199, -122.676952" }, "geometry": { "type": "Point", "coordinates": [ -122.676952035122369, 45.477198683454652 ] } }
]
}
