{
"type": "FeatureCollection",
"crs": { "type": "name", "properties": { "name": "urn:ogc:def:crs:OGC:1.3:CRS84" } },
"features": [
{ "type": "Feature", "properties": { "point_type": "origin", "points_str": "45.561247, -122.642067" }, "geometry": { "type": "Point", "coordinates": [ -122.64206717828084, 45.561247007124386 ] } },
{ "type": "Feature", "properties": { "point_type": "destination", "points_str": "45.483948, -122.551404" }, "geometry": { "type": "Point", "coordinates": [ -122.551404301109159, 45.483948176134355 ] } }
]
}
