{
"type": "FeatureCollection",
"name": "origin_destination_points",
"crs": { "type": "name", "properties": { "name": "urn:ogc:def:crs:OGC:1.3:CRS84" } },
"features": [
{ "type": "Feature", "properties": { "point_type": "origin", "points_str": "45.47226, -122.805816" }, "geometry": { "type": "Point", "coordinates": [ -122.805815733956493, 45.472260389122987 ] } },
{ "type": "Feature", "properties": { "point_type": "destination", "points_str": "45.521505, -123.012999" }, "geometry": { "type": "Point", "coordinates": [ -123.012998629026697, 45.521505407454363 ] } }
]
}
