{
"type": "FeatureCollection",
"crs": { "type": "name", "properties": { "name": "urn:ogc:def:crs:OGC:1.3:CRS84" } },
"features": [
{ "type": "Feature", "properties": { "point_type": "origin", "points_str": "45.489864, -122.583825" }, "geometry": { "type": "Point", "coordinates": [ -122.583824712619048, 45.489864009390047 ] } },
{ "type": "Feature", "properties": { "point_type": "destination", "points_str": "45.559505, -122.608446" }, "geometry": { "type": "Point", "coordinates": [ -122.608446433287511, 45.559504737249362 ] } }
]
}
