{
"type": "FeatureCollection",
"crs": { "type": "name", "properties": { "name": "urn:ogc:def:crs:OGC:1.3:CRS84" } },
"features": [
{ "type": "Feature", "properties": { "point_type": "origin", "points_str": "45.581226, -122.690614" }, "geometry": { "type": "Point", "coordinates": [ -122.690613565292949, 45.581226004020081 ] } },
{ "type": "Feature", "properties": { "point_type": "destination", "points_str": "45.419643, -122.739526" }, "geometry": { "type": "Point", "coordinates": [ -122.739526056212895, 45.419643311591223 ] } }
]
}
