{
"type": "FeatureCollection",
"name": "origin_destination_points",
"crs": { "type": "name", "properties": { "name": "urn:ogc:def:crs:OGC:1.3:CRS84" } },
"features": [
{ "type": "Feature", "properties": { "point_type": "origin", "points_str": "45.444622, -122.588099" }, "geometry": { "type": "Point", "coordinates": [ -122.588098684520546, 45.444622101122093 ] } },
{ "type": "Feature", "properties": { "point_type": "destination", "points_str": "45.434318, -122.615827" }, "geometry": { "type": "Point", "coordinates": [ -122.615827075512399, 45.434318498041215 ] } }
]
}
