{
"type": "FeatureCollection",
"crs": { "type": "name", "properties": { "name": "urn:ogc:def:crs:OGC:1.3:CRS84" } },
"features": [
{ "type": "Feature", "properties": { "point_type": "origin", "points_str": "45.507038, -122.596361" }, "geometry": { "type": "Point", "coordinates": [ -122.59636141620247, 45.507037737147499 ] } },
{ "type": "Feature", "properties": { "point_type": "destination", "points_str": "45.504461, -122.643059" }, "geometry": { "type": "Point", "coordinates": [ -122.64305916643444, 45.504460741065323 ] } }
]
}
