{
"type": "FeatureCollection",
"name": "origin_destination_points",
"crs": { "type": "name", "properties": { "name": "urn:ogc:def:crs:OGC:1.3:CRS84" } },
"features": [
{ "type": "Feature", "properties": { "point_type": "origin", "points_str": "45.51732, -122.657868" }, "geometry": { "type": "Point", "coordinates": [ -122.657867569407188, 45.517319524097033 ] } },
{ "type": "Feature", "properties": { "point_type": "destination", "points_str": "45.505868, -122.60662" }, "geometry": { "type": "Point", "coordinates": [ -122.606620215625455, 45.505867715558345 ] } }
]
}
