{
"type": "FeatureCollection",
"name": "origin_destination_points",
"crs": { "type": "name", "properties": { "name": "urn:ogc:def:crs:OGC:1.3:CRS84" } },
"features": [
{ "type": "Feature", "properties": { "point_type": "origin", "points_str": "45.517139, -122.674623" }, "geometry": { "type": "Point", "coordinates": [ -122.674623186080169, 45.517139191682531 ] } },
{ "type": "Feature", "properties": { "point_type": "destination", "points_str": "45.508103, -122.559186" }, "geometry": { "type": "Point", "coordinates": [ -122.559186218508657, 45.508103406587928 ] } }
]
}
