{
"type": "FeatureCollection",
"crs": { "type": "name", "properties": { "name": "urn:ogc:def:crs:OGC:1.3:CRS84" } },
"features": [
{ "type": "Feature", "properties": { "point_type": "origin", "points_str": "45.519376, -122.99061" }, "geometry": { "type": "Point", "coordinates": [ -122.990609596476446, 45.519375702479422 ] } },
{ "type": "Feature", "properties": { "point_type": "destination", "points_str": "45.528613, -122.53153" }, "geometry": { "type": "Point", "coordinates": [ -122.53152997861892, 45.528613033011226 ] } }
]
}
