{
"type": "FeatureCollection",
"crs": { "type": "name", "properties": { "name": "urn:ogc:def:crs:OGC:1.3:CRS84" } },
"features": [
{ "type": "Feature", "properties": { "point_type": "origin", "points_str": "45.529595, -122.551072" }, "geometry": { "type": "Point", "coordinates": [ -122.551071870732002, 45.529595003594622 ] } },
{ "type": "Feature", "properties": { "point_type": "destination", "points_str": "45.543963, -122.558626" }, "geometry": { "type": "Point", "coordinates": [ -122.558625798229173, 45.543963458304731 ] } }
]
}
