{
"type": "FeatureCollection",
"name": "origin_destination_points",
"crs": { "type": "name", "properties": { "name": "urn:ogc:def:crs:OGC:1.3:CRS84" } },
"features": [
{ "type": "Feature", "properties": { "point_type": "origin", "points_str": "45.564544, -122.521875" }, "geometry": { "type": "Point", "coordinates": [ -122.521875498963709, 45.56454362613038 ] } },
{ "type": "Feature", "properties": { "point_type": "destination", "points_str": "45.528165, -122.447285" }, "geometry": { "type": "Point", "coordinates": [ -122.447284816494175, 45.528164936388926 ] } }
]
}
