{
"type": "FeatureCollection",
"name": "origin_destination_points",
"crs": { "type": "name", "properties": { "name": "urn:ogc:def:crs:OGC:1.3:CRS84" } },
"features": [
{ "type": "Feature", "properties": { "point_type": "origin", "points_str": "45.5156, -123.001426" }, "geometry": { "type": "Point", "coordinates": [ -123.001426488629576, 45.515600216233615 ] } },
{ "type": "Feature", "properties": { "point_type": "destination", "points_str": "45.519869, -122.471366" }, "geometry": { "type": "Point", "coordinates": [ -122.471365949064733, 45.519868531791793 ] } }
]
}
