{
"type": "FeatureCollection",
"name": "origin_destination_points",
"crs": { "type": "name", "properties": { "name": "urn:ogc:def:crs:OGC:1.3:CRS84" } },
"features": [
{ "type": "Feature", "properties": { "point_type": "origin", "points_str": "45.514326, -122.676307" }, "geometry": { "type": "Point", "coordinates": [ -122.676307354678954, 45.514325754163842 ] } },
{ "type": "Feature", "properties": { "point_type": "destination", "points_str": "45.522807, -123.074528" }, "geometry": { "type": "Point", "coordinates": [ -123.074528435763412, 45.522806958585932 ] } }
]
}
