{
"type": "FeatureCollection",
"name": "origin_destination_points",
"crs": { "type": "name", "properties": { "name": "urn:ogc:def:crs:OGC:1.3:CRS84" } },
"features": [
{ "type": "Feature", "properties": { "point_type": "origin", "points_str": "45.530113, -122.501123" }, "geometry": { "type": "Point", "coordinates": [ -122.501122754543829, 45.530113022989731 ] } },
{ "type": "Feature", "properties": { "point_type": "destination", "points_str": "45.506751, -122.473289" }, "geometry": { "type": "Point", "coordinates": [ -122.473288885894561, 45.506750844710034 ] } }
]
}
