{
"type": "FeatureCollection",
"crs": { "type": "name", "properties": { "name": "urn:ogc:def:crs:OGC:1.3:CRS84" } },
"features": [
{ "type": "Feature", "properties": { "point_type": "origin", "points_str": "45.500581, -122.65973" }, "geometry": { "type": "Point", "coordinates": [ -122.659729880716284, 45.500581480405991 ] } },
{ "type": "Feature", "properties": { "point_type": "destination", "points_str": "45.476955, -122.557944" }, "geometry": { "type": "Point", "coordinates": [ -122.557943725108345, 45.476954596478116 ] } }
]
}
