{
"type": "FeatureCollection",
"name": "origin_destination_points",
"crs": { "type": "name", "properties": { "name": "urn:ogc:def:crs:OGC:1.3:CRS84" } },
"features": [
{ "type": "Feature", "properties": { "point_type": "origin", "points_str": "45.454719, -122.783672" }, "geometry": { "type": "Point", "coordinates": [ -122.78367178110291, 45.454719347680047 ] } },
{ "type": "Feature", "properties": { "point_type": "destination", "points_str": "45.421059, -122.768936" }, "geometry": { "type": "Point", "coordinates": [ -122.768936125033832, 45.421059074325555 ] } }
]
}
