{
"type": "FeatureCollection",
"crs": { "type": "name", "properties": { "name": "urn:ogc:def:crs:OGC:1.3:CRS84" } },
"features": [
{ "type": "Feature", "properties": { "point_type": "origin", "points_str": "45.561996, -122.589509" }, "geometry": { "type": "Point", "coordinates": [ -122.589509251451418, 45.561995940076557 ] } },
{ "type": "Feature", "properties": { "point_type": "destination", "points_str": "45.527233, -122.597898" }, "geometry": { "type": "Point", "coordinates": [ -122.597898170075851, 45.527232753021167 ] } }
]
}
