{
"type": "FeatureCollection",
"name": "origin_destination_points",
"crs": { "type": "name", "properties": { "name": "urn:ogc:def:crs:OGC:1.3:CRS84" } },
"features": [
{ "type": "Feature", "properties": { "point_type": "origin", "points_str": "45.419137, -122.662668" }, "geometry": { "type": "Point", "coordinates": [ -122.662668149070839, 45.419136807225591 ] } },
{ "type": "Feature", "properties": { "point_type": "destination", "points_str": "45.46154, -122.71897" }, "geometry": { "type": "Point", "coordinates": [ -122.718970033565313, 45.461540292447189 ] } }
]
}
