{
"type": "FeatureCollection",
"name": "origin_destination_points",
"crs": { "type": "name", "properties": { "name": "urn:ogc:def:crs:OGC:1.3:CRS84" } },
"features": [
{ "type": "Feature", "properties": { "point_type": "origin", "points_str": "45.492239, -122.799893" }, "geometry": { "type": "Point", "coordinates": [ -122.799892665423897, 45.492238918807807 ] } },
{ "type": "Feature", "properties": { "point_type": "destination", "points_str": "45.42969, -122.706744" }, "geometry": { "type": "Point", "coordinates": [ -122.706744018433866, 45.429690094067489 ] } }
]
}
