{
"type": "FeatureCollection",
"name": "origin_destination_points",
"crs": { "type": "name", "properties": { "name": "urn:ogc:def:crs:OGC:1.3:CRS84" } },
"features": [
{ "type": "Feature", "properties": { "point_type": "origin", "points_str": "45.440805, -122.750127" }, "geometry": { "type": "Point", "coordinates": [ -122.750127124046045, 45.440804655446499 ] } },
{ "type": "Feature", "properties": { "point_type": "destination", "points_str": "45.381199, -122.755628" }, "geometry": { "type": "Point", "coordinates": [ -122.755628223664502, 45.381198594640253 ] } }
]
}
