{
"type": "FeatureCollection",
"name": "origin_destination_points",
"crs": { "type": "name", "properties": { "name": "urn:ogc:def:crs:OGC:1.3:CRS84" } },
"features": [
{ "type": "Feature", "properties": { "point_type": "origin", "points_str": "45.519119, -122.384901" }, "geometry": { "type": "Point", "coordinates": [ -122.384900955164269, 45.519119296126952 ] } },
{ "type": "Feature", "properties": { "point_type": "destination", "points_str": "45.521474, -122.452996" }, "geometry": { "type": "Point", "coordinates": [ -122.452996111018791, 45.521474444468581 ] } }
]
}
