{
"type": "FeatureCollection",
"crs": { "type": "name", "properties": { "name": "urn:ogc:def:crs:OGC:1.3:CRS84" } },
"features": [
{ "type": "Feature", "properties": { "point_type": "origin", "points_str": "45.522171, -122.419909" }, "geometry": { "type": "Point", "coordinates": [ -122.419909321086266, 45.522170768795682 ] } },
{ "type": "Feature", "properties": { "point_type": "destination", "points_str": "45.504254, -122.500125" }, "geometry": { "type": "Point", "coordinates": [ -122.500124858605162, 45.504254290071557 ] } }
]
}
