{
"type": "FeatureCollection",
"crs": { "type": "name", "properties": { "name": "urn:ogc:def:crs:OGC:1.3:CRS84" } },
"features": [
{ "type": "Feature", "properties": { "point_type": "origin", "points_str": "45.500595, -122.530652" }, "geometry": { "type": "Point", "coordinates": [ -122.530651948023007, 45.500594977942761 ] } },
{ "type": "Feature", "properties": { "point_type": "destination", "points_str": "45.454881, -122.67449" }, "geometry": { "type": "Point", "coordinates": [ -122.674490352319836, 45.45488120994689 ] } }
]
}
