{
"type": "FeatureCollection",
"name": "origin_destination_points",
"crs": { "type": "name", "properties": { "name": "urn:ogc:def:crs:OGC:1.3:CRS84" } },
"features": [
{ "type": "Feature", "properties": { "point_type": "origin", "points_str": "45.435972, -122.798139" }, "geometry": { "type": "Point", "coordinates": [ -122.798138934307801, 45.43597176105289 ] } },
{ "type": "Feature", "properties": { "point_type": "destination", "points_str": "45.470462, -122.800962" }, "geometry": { "type": "Point", "coordinates": [ -122.800962016624823, 45.470462083844758 ] } }
]
}
