{
"type": "FeatureCollection",
"crs": { "type": "name", "properties": { "name": "urn:ogc:def:crs:OGC:1.3:CRS84" } },
"features": [
{ "type": "Feature", "properties": { "point_type": "origin", "points_str": "45.421226, -122.694709" }, "geometry": { "type": "Point", "coordinates": [ -122.694708510352584, 45.421226161503078 ] } },
{ "type": "Feature", "properties": { "point_type": "destination", "points_str": "45.476204, -122.825901" }, "geometry": { "type": "Point", "coordinates": [ -122.825901250360843, 45.476204384425046 ] } }
]
}
