{
"type": "FeatureCollection",
"crs": { "type": "name", "properties": { "name": "urn:ogc:def:crs:OGC:1.3:CRS84" } },
"features": [
{ "type": "Feature", "properties": { "point_type": "origin", "points_str": "45.535524, -122.681952" }, "geometry": { "type": "Point", "coordinates": [ -122.681952027341453, 45.535523513239184 ] } },
{ "type": "Feature", "properties": { "point_type": "destination", "points_str": "45.524197, -122.389642" }, "geometry": { "type": "Point", "coordinates": [ -122.389641995553177, 45.52419716996976 ] } }
]
}
