{
"type": "FeatureCollection",
"crs": { "type": "name", "properties": { "name": "urn:ogc:def:crs:OGC:1.3:CRS84" } },
"features": [
{ "type": "Feature", "properties": { "point_type": "origin", "points_str": "45.37366, -122.784538" }, "geometry": { "type": "Point", "coordinates": [ -122.784538210782557, 45.373660126497143 ] } },
{ "type": "Feature", "properties": { "point_type": "destination", "points_str": "45.577023, -122.729816" }, "geometry": { "type": "Point", "coordinates": [ -122.729816282216248, 45.577023161803993 ] } }
]
}
