{
"type": "FeatureCollection",
"name": "origin_destination_points",
"crs": { "type": "name", "properties": { "name": "urn:ogc:def:crs:OGC:1.3:CRS84" } },
"features": [
{ "type": "Feature", "properties": { "point_type": "origin", "points_str": "45.341972, -122.770692" }, "geometry": { "type": "Point", "coordinates": [ -122.770692248719939, 45.341972407659348 ] } },
{ "type": "Feature", "properties": { "point_type": "destination", "points_str": "45.527217, -122.665502" }, "geometry": { "type": "Point", "coordinates": [ -122.665502032592983, 45.527217292025227 ] } }
]
}
