{
"type": "FeatureCollection",
"name": "origin_destination_points",
"crs": { "type": "name", "properties": { "name": "urn:ogc:def:crs:OGC:1.3:CRS84" } },
"features": [
{ "type": "Feature", "properties": { "point_type": "origin", "points_str": "45.526612, -122.614042" }, "geometry": { "type": "Point", "coordinates": [ -122.614041968608092, 45.526611833978947 ] } },
{ "type": "Feature", "properties": { "point_type": "destination", "points_str": "45.556413, -122.59548" }, "geometry": { "type": "Point", "coordinates": [ -122.595480073092475, 45.556412772323739 ] } }
]
}
