{
"type": "FeatureCollection",
"name": "origin_destination_points",
"crs": { "type": "name", "properties": { "name": "urn:ogc:def:crs:OGC:1.3:CRS84" } },
"features": [
{ "type": "Feature", "properties": { "point_type": "origin", "points_str": "45.539953, -122.40108" }, "geometry": { "type": "Point", "coordinates": [ -122.401080187574252, 45.539952604293539 ] } },
{ "type": "Feature", "properties": { "point_type": "destination", "points_str": "45.516469, -122.683231" }, "geometry": { "type": "Point", "coordinates": [ -122.683230844307886, 45.516469265888794 ] } }
]
}
