{
"type": "FeatureCollection",
"name": "origin_destination_points",
"crs": { "type": "name", "properties": { "name": "urn:ogc:def:crs:OGC:1.3:CRS84" } },
"features": [
{ "type": "Feature", "properties": { "point_type": "origin", "points_str": "45.58291, -122.709266" }, "geometry": { "type": "Point", "coordinates": [ -122.709266006725144, 45.582910381936642 ] } },
{ "type": "Feature", "properties": { "point_type": "destination", "points_str": "45.503485, -122.830224" }, "geometry": { "type": "Point", "coordinates": [ -122.830224007838297, 45.503484958820344 ] } }
]
}
