{
"type": "FeatureCollection",
"name": "origin_destination_points",
"crs": { "type": "name", "properties": { "name": "urn:ogc:def:crs:OGC:1.3:CRS84" } },
"features": [
{ "type": "Feature", "properties": { "point_type": "origin", "points_str": "45.511995, -122.791502" }, "geometry": { "type": "Point", "coordinates": [ -122.791501947486381, 45.511995235160924 ] } },
{ "type": "Feature", "properties": { "point_type": "destination", "points_str": "45.460854, -122.618071" }, "geometry": { "type": "Point", "coordinates": [ -122.618070667749251, 45.46085374209256 ] } }
]
}
