{
"type": "FeatureCollection",
"name": "origin_destination_points",
"crs": { "type": "name", "properties": { "name": "urn:ogc:def:crs:OGC:1.3:CRS84" } },
"features": [
{ "type": "Feature", "properties": { "point_type": "origin", "points_str": "45.516299, -122.666601" }, "geometry": { "type": "Point", "coordinates": [ -122.666601194349553, 45.516298703999077 ] } },
{ "type": "Feature", "properties": { "point_type": "destination", "points_str": "45.575006, -122.728113" }, "geometry": { "type": "Point", "coordinates": [ -122.728113203676813, 45.575005700919093 ] } }
]
}
