{
"type": "FeatureCollection",
"name": "origin_destination_points",
"crs": { "type": "name", "properties": { "name": "urn:ogc:def:crs:OGC:1.3:CRS84" } },
"features": [
{ "type": "Feature", "properties": { "point_type": "origin", "points_str": "45.52158, -122.616551" }, "geometry": { "type": "Point", "coordinates": [ -122.616551456097852, 45.521579986347618 ] } },
{ "type": "Feature", "properties": { "point_type": "destination", "points_str": "45.371622, -122.628315" }, "geometry": { "type": "Point", "coordinates": [ -122.628314832761248, 45.371621635517258 ] } }
]
}
