{
"type": "FeatureCollection",
"crs": { "type": "name", "properties": { "name": "urn:ogc:def:crs:OGC:1.3:CRS84" } },
"features": [
{ "type": "Feature", "properties": { "point_type": "origin", "points_str": "45.529397, -122.608592" }, "geometry": { "type": "Point", "coordinates": [ -122.608591961460334, 45.529396827564042 ] } },
{ "type": "Feature", "properties": { "point_type": "destination", "points_str": "45.498572, -122.653333" }, "geometry": { "type": "Point", "coordinates": [ -122.653332797364925, 45.498572300073803 ] } }
]
}
