{
"type": "FeatureCollection",
"crs": { "type": "name", "properties": { "name": "urn:ogc:def:crs:OGC:1.3:CRS84" } },
"features": [
{ "type": "Feature", "properties": { "point_type": "origin", "points_str": "45.585638, -122.637342" }, "geometry": { "type": "Point", "coordinates": [ -122.637341907628553, 45.585638256103131 ] } },
{ "type": "Feature", "properties": { "point_type": "destination", "points_str": "45.496027, -122.695545" }, "geometry": { "type": "Point", "coordinates": [ -122.695545141395442, 45.49602707427772 ] } }
]
}
