{
"type": "FeatureCollection",
"crs": { "type": "name", "properties": { "name": "urn:ogc:def:crs:OGC:1.3:CRS84" } },
"features": [
{ "type": "Feature", "properties": { "point_type": "origin", "points_str": "45.398609, -122.600085" }, "geometry": { "type": "Point", "coordinates": [ -122.600085280593888, 45.398608512845705 ] } },
{ "type": "Feature", "properties": { "point_type": "destination", "points_str": "45.456499, -122.629915" }, "geometry": { "type": "Point", "coordinates": [ -122.629915166168459, 45.456499412564625 ] } }
]
}
