{
"type": "FeatureCollection",
"name": "origin_destination_points",
"crs": { "type": "name", "properties": { "name": "urn:ogc:def:crs:OGC:1.3:CRS84" } },
"features": [
{ "type": "Feature", "properties": { "point_type": "origin", "points_str": "45.518387, -122.471318" }, "geometry": { "type": "Point", "coordinates": [ -122.471318043419387, 45.518387218531707 ] } },
{ "type": "Feature", "properties": { "point_type": "destination", "points_str": "45.482106, -122.694169" }, "geometry": { "type": "Point", "coordinates": [ -122.69416918251315, 45.482105772614261 ] } }
]
}
