{
"type": "FeatureCollection",
"name": "origin_destination_points",
"crs": { "type": "name", "properties": { "name": "urn:ogc:def:crs:OGC:1.3:CRS84" } },
"features": [
{ "type": "Feature", "properties": { "point_type": "origin", "points_str": "45.374307, -122.635279" }, "geometry": { "type": "Point", "coordinates": [ -122.635279286129375, 45.374306744510235 ] } },
{ "type": "Feature", "properties": { "point_type": "destination", "points_str": "45.489829, -122.786157" }, "geometry": { "type": "Point", "coordinates": [ -122.786157374672712, 45.489828972460714 ] } }
]
}
