{
"type": "FeatureCollection",
"crs": { "type": "name", "properties": { "name": "urn:ogc:def:crs:OGC:1.3:CRS84" } },
"features": [
{ "type": "Feature", "properties": { "point_type": "origin", "points_str": "45.545996, -122.485502" }, "geometry": { "type": "Point", "coordinates": [ -122.4855020786393, 45.545995884207763 ] } },
{ "type": "Feature", "properties": { "point_type": "destination", "points_str": "45.546647, -122.52588" }, "geometry": { "type": "Point", "coordinates": [ -122.525880260040125, 45.546646877124623 ] } }
]
}
