{
"type": "FeatureCollection",
"name": "origin_destination_points",
"crs": { "type": "name", "properties": { "name": "urn:ogc:def:crs:OGC:1.3:CRS84" } },
"features": [
{ "type": "Feature", "properties": { "point_type": "origin", "points_str": "45.506518, -122.593895" }, "geometry": { "type": "Point", "coordinates": [ -122.593894869879151, 45.506518463651403 ] } },
{ "type": "Feature", "properties": { "point_type": "destination", "points_str": "45.475838, -122.680216" }, "geometry": { "type": "Point", "coordinates": [ -122.680215614235067, 45.47583805046348 ] } }
]
}
