{
"type": "FeatureCollection",
"name": "origin_destination_points",
"crs": { "type": "name", "properties": { "name": "urn:ogc:def:crs:OGC:1.3:CRS84" } },
"features": [
{ "type": "Feature", "properties": { "point_type": "origin", "points_str": "45.474353, -122.55205" }, "geometry": { "type": "Point", "coordinates": [ -122.552049656133903, 45.474352860240558 ] } },
{ "type": "Feature", "properties": { "point_type": "destination", "points_str": "45.540005, -122.540013" }, "geometry": { "type": "Point", "coordinates": [ -122.540013431066242, 45.540005114568196 ] } }
]
}
