{
"type": "FeatureCollection",
"crs": { "type": "name", "properties": { "name": "urn:ogc:def:crs:OGC:1.3:CRS84" } },
"features": [
{ "type": "Feature", "properties": { "point_type": "origin", "points_str": "45.497088, -122.889518" }, "geometry": { "type": "Point", "coordinates": [ -122.889517937398665, 45.497088064617415 ] } },
{ "type": "Feature", "properties": { "point_type": "destination", "points_str": "45.492226, -122.728106" }, "geometry": { "type": "Point", "coordinates": [ -122.728106153323566, 45.492226317289109 ] } }
]
}
