{
"type": "FeatureCollection",
"name": "origin_destination_points",
"crs": { "type": "name", "properties": { "name": "urn:ogc:def:crs:OGC:1.3:CRS84" } },
"features": [
{ "type": "Feature", "properties": { "point_type": "origin", "points_str": "45.376448, -122.751655" }, "geometry": { "type": "Point", "coordinates": [ -122.751654923487209, 45.376448034017059 ] } },
{ "type": "Feature", "properties": { "point_type": "destination", "points_str": "45.354044, -122.842005" }, "geometry": { "type": "Point", "coordinates": [ -122.842004884053395, 45.354043982605361 ] } }
]
}
