{
"type": "FeatureCollection",
"name": "origin_destination_points",
"crs": { "type": "name", "properties": { "name": "urn:ogc:def:crs:OGC:1.3:CRS84" } },
"features": [
{ "type": "Feature", "properties": { "point_type": "origin", "points_str": "45.454801, -122.732815" }, "geometry": { "type": "Point", "coordinates": [ -122.732815388985358, 45.454801385033022 ] } },
{ "type": "Feature", "properties": { "point_type": "destination", "points_str": "45.380214, -122.745485" }, "geometry": { "type": "Point", "coordinates": [ -122.745484868897648, 45.380213900579236 ] } }
]
}
