{
"type": "FeatureCollection",
"name": "origin_destination_points",
"crs": { "type": "name", "properties": { "name": "urn:ogc:def:crs:OGC:1.3:CRS84" } },
"features": [
{ "type": "Feature", "properties": { "point_type": "origin", "points_str": "45.437467, -122.638678" }, "geometry": { "type": "Point", "coordinates": [ -122.638677733869301, 45.437467269414654 ] } },
{ "type": "Feature", "properties": { "point_type": "destination", "points_str": "45.503108, -122.58249" }, "geometry": { "type": "Point", "coordinates": [ -122.582489686122614, 45.503108212765632 ] } }
]
}
