{
"type": "FeatureCollection",
"crs": { "type": "name", "properties": { "name": "urn:ogc:def:crs:OGC:1.3:CRS84" } },
"features": [
{ "type": "Feature", "properties": { "point_type": "origin", "points_str": "45.350651, -122.588132" }, "geometry": { "type": "Point", "coordinates": [ -122.588131780266551, 45.350650678660386 ] } },
{ "type": "Feature", "properties": { "point_type": "destination", "points_str": "45.575958, -122.625175" }, "geometry": { "type": "Point", "coordinates": [ -122.625175294457549, 45.575958446129071 ] } }
]
}
