{
"type": "FeatureCollection",
"crs": { "type": "name", "properties": { "name": "urn:ogc:def:crs:OGC:1.3:CRS84" } },
"features": [
{ "type": "Feature", "properties": { "point_type": "origin", "points_str": "45.535248, -122.690292" }, "geometry": { "type": "Point", "coordinates": [ -122.690291727010859, 45.535248086016885 ] } },
{ "type": "Feature", "properties": { "point_type": "destination", "points_str": "45.536608, -122.628582" }, "geometry": { "type": "Point", "coordinates": [ -122.62858197586155, 45.536607670198528 ] } }
]
}
