{
"type": "FeatureCollection",
"crs": { "type": "name", "properties": { "name": "urn:ogc:def:crs:OGC:1.3:CRS84" } },
"features": [
{ "type": "Feature", "properties": { "point_type": "origin", "points_str": "45.517521, -122.672049" }, "geometry": { "type": "Point", "coordinates": [ -122.672048897551861, 45.517521368691582 ] } },
{ "type": "Feature", "properties": { "point_type": "destination", "points_str": "45.492123, -122.473666" }, "geometry": { "type": "Point", "coordinates": [ -122.473666156098375, 45.492122516948761 ] } }
]
}
