{
"type": "FeatureCollection",
"name": "origin_destination_points",
"crs": { "type": "name", "properties": { "name": "urn:ogc:def:crs:OGC:1.3:CRS84" } },
"features": [
{ "type": "Feature", "properties": { "point_type": "origin", "points_str": "45.55701, -122.587534" }, "geometry": { "type": "Point", "coordinates": [ -122.587534158707371, 45.557009796094945 ] } },
{ "type": "Feature", "properties": { "point_type": "destination", "points_str": "45.52292, -122.628677" }, "geometry": { "type": "Point", "coordinates": [ -122.628677108995888, 45.522920183197279 ] } }
]
}
