{
"type": "FeatureCollection",
"name": "origin_destination_points",
"crs": { "type": "name", "properties": { "name": "urn:ogc:def:crs:OGC:1.3:CRS84" } },
"features": [
{ "type": "Feature", "properties": { "point_type": "origin", "points_str": "45.552536, -122.723842" }, "geometry": { "type": "Point", "coordinates": [ -122.723841831781712, 45.55253634731428 ] } },
{ "type": "Feature", "properties": { "point_type": "destination", "points_str": "45.535716, -122.646031" }, "geometry": { "type": "Point", "coordinates": [ -122.646030847209545, 45.535716335763361 ] } }
]
}
