{
"type": "FeatureCollection",
"crs": { "type": "name", "properties": { "name": "urn:ogc:def:crs:OGC:1.3:CRS84" } },
"features": [
{ "type": "Feature", "properties": { "point_type": "origin", "points_str": "45.477017, -122.869399" }, "geometry": { "type": "Point", "coordinates": [ -122.86939862939353, 45.477017410788662 ] } },
{ "type": "Feature", "properties": { "point_type": "destination", "points_str": "45.516975, -122.879333" }, "geometry": { "type": "Point", "coordinates": [ -122.879332568993874, 45.516975396435157 ] } }
]
}
