{
"type": "FeatureCollection",
"crs": { "type": "name", "properties": { "name": "urn:ogc:def:crs:OGC:1.3:CRS84" } },
"features": [
{ "type": "Feature", "properties": { "point_type": "origin", "points_str": "45.453549, -122.755865" }, "geometry": { "type": "Point", "coordinates": [ -122.755865445963593, 45.453548962444295 ] } },
{ "type": "Feature", "properties": { "point_type": "destination", "points_str": "45.453219, -122.784367" }, "geometry": { "type": "Point", "coordinates": [ -122.784366752455355, 45.453219269950793 ] } }
]
}
