{
"type": "FeatureCollection",
"name": "origin_destination_points",
"crs": { "type": "name", "properties": { "name": "urn:ogc:def:crs:OGC:1.3:CRS84" } },
"features": [
{ "type": "Feature", "properties": { "point_type": "origin", "points_str": "45.533623, -122.618001" }, "geometry": { "type": "Point", "coordinates": [ -122.618000668094965, 45.533622518463467 ] } },
{ "type": "Feature", "properties": { "point_type": "destination", "points_str": "45.547837, -122.577079" }, "geometry": { "type": "Point", "coordinates": [ -122.577078809354276, 45.547837272553338 ] } }
]
}
