{
"type": "FeatureCollection",
"name": "origin_destination_points",
"crs": { "type": "name", "properties": { "name": "urn:ogc:def:crs:OGC:1.3:CRS84" } },
"features": [
{ "type": "Feature", "properties": { "point_type": "origin", "points_str": "45.562285, -122.631212" }, "geometry": { "type": "Point", "coordinates": [ -122.631212395528905, 45.562285248797778 ] } },
{ "type": "Feature", "properties": { "point_type": "destination", "points_str": "45.560746, -122.697649" }, "geometry": { "type": "Point", "coordinates": [ -122.697649059764402, 45.560745947506057 ] } }
]
}
