{
"type": "FeatureCollection",
"crs": { "type": "name", "properties": { "name": "urn:ogc:def:crs:OGC:1.3:CRS84" } },
"features": [
{ "type": "Feature", "properties": { "point_type": "origin", "points_str": "45.560107, -122.831328" }, "geometry": { "type": "Point", "coordinates": [ -122.831327518353575, 45.560106850696052 ] } },
{ "type": "Feature", "properties": { "point_type": "destination", "points_str": "45.551712, -122.965377" }, "geometry": { "type": "Point", "coordinates": [ -122.965376971096546, 45.551712357454754 ] } }
]
}
