{
"type": "FeatureCollection",
"name": "origin_destination_points",
"crs": { "type": "name", "properties": { "name": "urn:ogc:def:crs:OGC:1.3:CRS84" } },
"features": [
{ "type": "Feature", "properties": { "point_type": "origin", "points_str": "45.510304, -122.79837" }, "geometry": { "type": "Point", "coordinates": [ -122.798370304762031, 45.510304406711505 ] } },
{ "type": "Feature", "properties": { "point_type": "destination", "points_str": "45.520259, -122.733161" }, "geometry": { "type": "Point", "coordinates": [ -122.733160904374586, 45.520258647859862 ] } }
]
}
