{
"type": "FeatureCollection",
"name": "origin_destination_points",
"crs": { "type": "name", "properties": { "name": "urn:ogc:def:crs:OGC:1.3:CRS84" } },
"features": [
{ "type": "Feature", "properties": { "point_type": "origin", "points_str": "45.485295, -122.818416" }, "geometry": { "type": "Point", "coordinates": [ -122.818416058687433, 45.485295410505451 ] } },
{ "type": "Feature", "properties": { "point_type": "destination", "points_str": "45.503101, -122.865055" }, "geometry": { "type": "Point", "coordinates": [ -122.865055474437057, 45.503101295731405 ] } }
]
}
