{
"type": "FeatureCollection",
"name": "origin_destination_points",
"crs": { "type": "name", "properties": { "name": "urn:ogc:def:crs:OGC:1.3:CRS84" } },
"features": [
{ "type": "Feature", "properties": { "point_type": "origin", "points_str": "45.508499, -122.58078" }, "geometry": { "type": "Point", "coordinates": [ -122.580779979191831, 45.508498842151454 ] } },
{ "type": "Feature", "properties": { "point_type": "destination", "points_str": "45.500308, -122.645838" }, "geometry": { "type": "Point", "coordinates": [ -122.64583846557548, 45.500308401885512 ] } }
]
}
