{
"type": "FeatureCollection",
"name": "origin_destination_points",
"crs": { "type": "name", "properties": { "name": "urn:ogc:def:crs:OGC:1.3:CRS84" } },
"features": [
{ "type": "Feature", "properties": { "point_type": "origin", "points_str": "45.5508, -122.636086" }, "geometry": { "type": "Point", "coordinates": [ -122.636085717712916, 45.550799971654179 ] } },
{ "type": "Feature", "properties": { "point_type": "destination", "points_str": "45.526793, -122.917011" }, "geometry": { "type": "Point", "coordinates": [ -122.917011075144401, 45.526792803061667 ] } }
]
}
