{
"type": "FeatureCollection",
"name": "origin_destination_points",
"crs": { "type": "name", "properties": { "name": "urn:ogc:def:crs:OGC:1.3:CRS84" } },
"features": [
{ "type": "Feature", "properties": { "point_type": "origin", "points_str": "45.530333, -122.681687" }, "geometry": { "type": "Point", "coordinates": [ -122.68168705239593, 45.530332697009648 ] } },
{ "type": "Feature", "properties": { "point_type": "destination", "points_str": "45.575488, -122.75862" }, "geometry": { "type": "Point", "coordinates": [ -122.758620231015939, 45.575488373432663 ] } }
]
}
