{
"type": "FeatureCollection",
"name": "origin_destination_points",
"crs": { "type": "name", "properties": { "name": "urn:ogc:def:crs:OGC:1.3:CRS84" } },
"features": [
{ "type": "Feature", "properties": { "point_type": "origin", "points_str": "45.471797, -122.706116" }, "geometry": { "type": "Point", "coordinates": [ -122.70611632336589, 45.471796602663581 ] } },
{ "type": "Feature", "properties": { "point_type": "destination", "points_str": "45.455934, -122.717494" }, "geometry": { "type": "Point", "coordinates": [ -122.717494310084348, 45.455934396456293 ] } }
]
}
