{
"type": "FeatureCollection",
"crs": { "type": "name", "properties": { "name": "urn:ogc:def:crs:OGC:1.3:CRS84" } },
"features": [
{ "type": "Feature", "properties": { "point_type": "origin", "points_str": "45.520259, -122.518814" }, "geometry": { "type": "Point", "coordinates": [ -122.518814335325331, 45.520258819845161 ] } },
{ "type": "Feature", "properties": { "point_type": "destination", "points_str": "45.520791, -122.97087" }, "geometry": { "type": "Point", "coordinates": [ -122.970870104874351, 45.520790713739437 ] } }
]
}
