{
"type": "FeatureCollection",
"crs": { "type": "name", "properties": { "name": "urn:ogc:def:crs:OGC:1.3:CRS84" } },
"features": [
{ "type": "Feature", "properties": { "point_type": "origin", "points_str": "45.512908, -122.711987" }, "geometry": { "type": "Point", "coordinates": [ -122.711987130587545, 45.51290810498822 ] } },
{ "type": "Feature", "properties": { "point_type": "destination", "points_str": "45.510896, -122.611478" }, "geometry": { "type": "Point", "coordinates": [ -122.611477807905644, 45.51089636399886 ] } }
]
}
