{
"type": "FeatureCollection",
"crs": { "type": "name", "properties": { "name": "urn:ogc:def:crs:OGC:1.3:CRS84" } },
"features": [
{ "type": "Feature", "properties": { "point_type": "origin", "points_str": "45.445566, -122.723521" }, "geometry": { "type": "Point", "coordinates": [ -122.72352069290028, 45.44556594775257 ] } },
{ "type": "Feature", "properties": { "point_type": "destination", "points_str": "45.515774, -122.697959" }, "geometry": { "type": "Point", "coordinates": [ -122.69795879457098, 45.515773796978984 ] } }
]
}
