{
"type": "FeatureCollection",
"name": "origin_destination_points",
"crs": { "type": "name", "properties": { "name": "urn:ogc:def:crs:OGC:1.3:CRS84" } },
"features": [
{ "type": "Feature", "properties": { "point_type": "origin", "points_str": "45.575805, -122.569043" }, "geometry": { "type": "Point", "coordinates": [ -122.56904272685459, 45.575804569719018 ] } },
{ "type": "Feature", "properties": { "point_type": "destination", "points_str": "45.55023, -122.610172" }, "geometry": { "type": "Point", "coordinates": [ -122.610171547810154, 45.550230240516782 ] } }
]
}
