{
"type": "FeatureCollection",
"name": "origin_destination_points",
"crs": { "type": "name", "properties": { "name": "urn:ogc:def:crs:OGC:1.3:CRS84" } },
"features": [
{ "type": "Feature", "properties": { "point_type": "origin", "points_str": "45.445365, -122.591504" }, "geometry": { "type": "Point", "coordinates": [ -122.591504388171685, 45.445365239582138 ] } },
{ "type": "Feature", "properties": { "point_type": "destination", "points_str": "45.434927, -122.638918" }, "geometry": { "type": "Point", "coordinates": [ -122.638918271598712, 45.43492666564557 ] } }
]
}
