{
"type": "FeatureCollection",
"name": "origin_destination_points",
"crs": { "type": "name", "properties": { "name": "urn:ogc:def:crs:OGC:1.3:CRS84" } },
"features": [
{ "type": "Feature", "properties": { "point_type": "origin", "points_str": "45.47609, -122.644578" }, "geometry": { "type": "Point", "coordinates": [ -122.644578073984192, 45.476089580409521 ] } },
{ "type": "Feature", "properties": { "point_type": "destination", "points_str": "45.500155, -122.833566" }, "geometry": { "type": "Point", "coordinates": [ -122.833566034412328, 45.500154809160982 ] } }
]
}
