{
"type": "FeatureCollection",
"crs": { "type": "name", "properties": { "name": "urn:ogc:def:crs:OGC:1.3:CRS84" } },
"features": [
{ "type": "Feature", "properties": { "point_type": "origin", "points_str": "45.477136, -122.564726" }, "geometry": { "type": "Point", "coordinates": [ -122.564726068445026, 45.477135938075882 ] } },
{ "type": "Feature", "properties": { "point_type": "destination", "points_str": "45.50586, -122.671754" }, "geometry": { "type": "Point", "coordinates": [ -122.671753823443808, 45.505860408705836 ] } }
]
}
