{
"type": "FeatureCollection",
"crs": { "type": "name", "properties": { "name": "urn:ogc:def:crs:OGC:1.3:CRS84" } },
"features": [
{ "type": "Feature", "properties": { "point_type": "origin", "points_str": "45.488137, -122.552644" }, "geometry": { "type": "Point", "coordinates": [ -122.552644249300414, 45.48813683939855 ] } },
{ "type": "Feature", "properties": { "point_type": "destination", "points_str": "45.542648, -122.387974" }, "geometry": { "type": "Point", "coordinates": [ -122.387973504758506, 45.542647577502848 ] } }
]
}
