{
"type": "FeatureCollection",
"crs": { "type": "name", "properties": { "name": "urn:ogc:def:crs:OGC:1.3:CRS84" } },
"features": [
{ "type": "Feature", "properties": { "point_type": "origin", "points_str": "45.434695, -122.758459" }, "geometry": { "type": "Point", "coordinates": [ -122.758458925410608, 45.43469459926547 ] } },
{ "type": "Feature", "properties": { "point_type": "destination", "points_str": "45.469594, -122.572571" }, "geometry": { "type": "Point", "coordinates": [ -122.572571158519423, 45.469593631622296 ] } }
]
}
