{
"type": "FeatureCollection",
"name": "origin_destination_points",
"crs": { "type": "name", "properties": { "name": "urn:ogc:def:crs:OGC:1.3:CRS84" } },
"features": [
{ "type": "Feature", "properties": { "point_type": "origin", "points_str": "45.465206, -122.676099" }, "geometry": { "type": "Point", "coordinates": [ -122.676098948604675, 45.465206058844117 ] } },
{ "type": "Feature", "properties": { "point_type": "destination", "points_str": "45.521074, -122.660909" }, "geometry": { "type": "Point", "coordinates": [ -122.660909216972001, 45.521074009388393 ] } }
]
}
