{
"type": "FeatureCollection",
"name": "origin_destination_points",
"crs": { "type": "name", "properties": { "name": "urn:ogc:def:crs:OGC:1.3:CRS84" } },
"features": [
{ "type": "Feature", "properties": { "point_type": "origin", "points_str": "45.522204, -122.434787" }, "geometry": { "type": "Point", "coordinates": [ -122.434786668621129, 45.522203669357133 ] } },
{ "type": "Feature", "properties": { "point_type": "destination", "points_str": "45.517873, -122.621129" }, "geometry": { "type": "Point", "coordinates": [ -122.621129123448213, 45.517873088874779 ] } }
]
}
