{
"type": "FeatureCollection",
"crs": { "type": "name", "properties": { "name": "urn:ogc:def:crs:OGC:1.3:CRS84" } },
"features": [
{ "type": "Feature", "properties": { "point_type": "origin", "points_str": "45.527167, -122.671035" }, "geometry": { "type": "Point", "coordinates": [ -122.671035446795031, 45.527167373254983 ] } },
{ "type": "Feature", "properties": { "point_type": "destination", "points_str": "45.597288, -122.747276" }, "geometry": { "type": "Point", "coordinates": [ -122.747275723220113, 45.597287902941034 ] } }
]
}
