{
"type": "FeatureCollection",
"name": "origin_destination_points",
"crs": { "type": "name", "properties": { "name": "urn:ogc:def:crs:OGC:1.3:CRS84" } },
"features": [
{ "type": "Feature", "properties": { "point_type": "origin", "points_str": "45.536005, -122.603807" }, "geometry": { "type": "Point", "coordinates": [ -122.603806531077737, 45.53600465794635 ] } },
{ "type": "Feature", "properties": { "point_type": "destination", "points_str": "45.562462, -122.628783" }, "geometry": { "type": "Point", "coordinates": [ -122.628783172831803, 45.562461991102587 ] } }
]
}
