{
"type": "FeatureCollection",
"crs": { "type": "name", "properties": { "name": "urn:ogc:def:crs:OGC:1.3:CRS84" } },
"features": [
{ "type": "Feature", "properties": { "point_type": "origin", "points_str": "45.510634, -122.84669" }, "geometry": { "type": "Point", "coordinates": [ -122.846689824533897, 45.510634162002034 ] } },
{ "type": "Feature", "properties": { "point_type": "destination", "points_str": "45.560598, -122.74287" }, "geometry": { "type": "Point", "coordinates": [ -122.742869979238336, 45.560597528986911 ] } }
]
}
