{
"type": "FeatureCollection",
"crs": { "type": "name", "properties": { "name": "urn:ogc:def:crs:OGC:1.3:CRS84" } },
"features": [
{ "type": "Feature", "properties": { "point_type": "origin", "points_str": "45.509948, -122.798135" }, "geometry": { "type": "Point", "coordinates": [ -122.798134859469457, 45.509948098317189 ] } },
{ "type": "Feature", "properties": { "point_type": "destination", "points_str": "45.405806, -122.75753" }, "geometry": { "type": "Point", "coordinates": [ -122.7575299092032, 45.405805681049991 ] } }
]
}
