{
"type": "FeatureCollection",
"name": "origin_destination_points",
"crs": { "type": "name", "properties": { "name": "urn:ogc:def:crs:OGC:1.3:CRS84" } },
"features": [
{ "type": "Feature", "properties": { "point_type": "origin", "points_str": "45.484158, -122.826808" }, "geometry": { "type": "Point", "coordinates": [ -122.82680826348566, 45.484158019602454 ] } },
{ "type": "Feature", "properties": { "point_type": "destination", "points_str": "45.526881, -122.793385" }, "geometry": { "type": "Point", "coordinates": [ -122.793385113225909, 45.526880911348549 ] } }
]
}
