{
"type": "FeatureCollection",
"crs": { "type": "name", "properties": { "name": "urn:ogc:def:crs:OGC:1.3:CRS84" } },
"features": [
{ "type": "Feature", "properties": { "point_type": "origin", "points_str": "45.448257, -122.754692" }, "geometry": { "type": "Point", "coordinates": [ -122.754691721112508, 45.44825703482644 ] } },
{ "type": "Feature", "properties": { "point_type": "destination", "points_str": "45.557041, -122.596628" }, "geometry": { "type": "Point", "coordinates": [ -122.596628441717598, 45.55704119154678 ] } }
]
}
