{
"type": "FeatureCollection",
"name": "origin_destination_points",
"crs": { "type": "name", "properties": { "name": "urn:ogc:def:crs:OGC:1.3:CRS84" } },
"features": [
{ "type": "Feature", "properties": { "point_type": "origin", "points_str": "45.545046, -122.894926" }, "geometry": { "type": "Point", "coordinates": [ -122.894926130035174, 45.545045780863234 ] } },
{ "type": "Feature", "properties": { "point_type": "destination", "points_str": "45.520218, -123.081974" }, "geometry": { "type": "Point", "coordinates": [ -123.08197415573423, 45.520217571730768 ] } }
]
}
