{
"type": "FeatureCollection",
"crs": { "type": "name", "properties": { "name": "urn:ogc:def:crs:OGC:1.3:CRS84" } },
"features": [
{ "type": "Feature", "properties": { "point_type": "origin", "points_str": "45.5595, -122.696014" }, "geometry": { "type": "Point", "coordinates": [ -122.696014213566812, 45.559499939183446 ] } },
{ "type": "Feature", "properties": { "point_type": "destination", "points_str": "45.477325, -122.581559" }, "geometry": { "type": "Point", "coordinates": [ -122.581558856972691, 45.477325273100035 ] } }
]
}
