{
"type": "FeatureCollection",
"crs": { "type": "name", "properties": { "name": "urn:ogc:def:crs:OGC:1.3:CRS84" } },
"features": [
{ "type": "Feature", "properties": { "point_type": "origin", "points_str": "45.519938, -122.537484" }, "geometry": { "type": "Point", "coordinates": [ -122.537484384202742, 45.519938192241334 ] } },
{ "type": "Feature", "properties": { "point_type": "destination", "points_str": "45.490031, -122.650762" }, "geometry": { "type": "Point", "coordinates": [ -122.650762023852039, 45.490031133682436 ] } }
]
}
