{
"type": "FeatureCollection",
"name": "origin_destination_points",
"crs": { "type": "name", "properties": { "name": "urn:ogc:def:crs:OGC:1.3:CRS84" } },
"features": [
{ "type": "Feature", "properties": { "point_type": "origin", "points_str": "45.536799, -122.711311" }, "geometry": { "type": "Point", "coordinates": [ -122.711311420043174, 45.536798541030137 ] } },
{ "type": "Feature", "properties": { "point_type": "destination", "points_str": "45.465601, -122.598299" }, "geometry": { "type": "Point", "coordinates": [ -122.598298611241006, 45.465600718616621 ] } }
]
}
