{
"type": "FeatureCollection",
"crs": { "type": "name", "properties": { "name": "urn:ogc:def:crs:OGC:1.3:CRS84" } },
"features": [
{ "type": "Feature", "properties": { "point_type": "origin", "points_str": "45.526549, -122.924935" }, "geometry": { "type": "Point", "coordinates": [ -122.924934798545962, 45.526549306574914 ] } },
{ "type": "Feature", "properties": { "point_type": "destination", "points_str": "45.518736, -122.446336" }, "geometry": { "type": "Point", "coordinates": [ -122.446335519006638, 45.518735824860478 ] } }
]
}
