{
"type": "FeatureCollection",
"crs": { "type": "name", "properties": { "name": "urn:ogc:def:crs:OGC:1.3:CRS84" } },
"features": [
{ "type": "Feature", "properties": { "point_type": "origin", "points_str": "45.521612, -122.55697" }, "geometry": { "type": "Point", "coordinates": [ -122.556970201516904, 45.521612284249336 ] } },
{ "type": "Feature", "properties": { "point_type": "destination", "points_str": "45.410706, -122.726493" }, "geometry": { "type": "Point", "coordinates": [ -122.72649265982075, 45.410705630939624 ] } }
]
}
