{
"type": "FeatureCollection",
"name": "origin_destination_points",
"crs": { "type": "name", "properties": { "name": "urn:ogc:def:crs:OGC:1.3:CRS84" } },
"features": [
{ "type": "Feature", "properties": { "point_type": "origin", "points_str": "45.506361, -122.505506" }, "geometry": { "type": "Point", "coordinates": [ -122.505506115126053, 45.506361236606132 ] } },
{ "type": "Feature", "properties": { "point_type": "destination", "points_str": "45.503615, -122.572" }, "geometry": { "type": "Point", "coordinates": [ -122.571999718330673, 45.503615059514516 ] } }
]
}
