{
"type": "FeatureCollection",
"name": "origin_destination_points",
"crs": { "type": "name", "properties": { "name": "urn:ogc:def:crs:OGC:1.3:CRS84" } },
"features": [
{ "type": "Feature", "properties": { "point_type": "origin", "points_str": "45.452352, -122.777472" }, "geometry": { "type": "Point", "coordinates": [ -122.777471711067747, 45.452351946608289 ] } },
{ "type": "Feature", "properties": { "point_type": "destination", "points_str": "45.373522, -122.765531" }, "geometry": { "type": "Point", "coordinates": [ -122.765531471468179, 45.373522393177261 ] } }
]
}
