{
"type": "FeatureCollection",
"crs": { "type": "name", "properties": { "name": "urn:ogc:def:crs:OGC:1.3:CRS84" } },
"features": [
{ "type": "Feature", "properties": { "point_type": "origin", "points_str": "45.450576, -122.65716" }, "geometry": { "type": "Point", "coordinates": [ -122.65715984743143, 45.450575845791057 ] } },
{ "type": "Feature", "properties": { "point_type": "destination", "points_str": "45.372254, -122.764209" }, "geometry": { "type": "Point", "coordinates": [ -122.764209334585644, 45.372253679735216 ] } }
]
}
