{
"type": "FeatureCollection",
"name": "origin_destination_points",
"crs": { "type": "name", "properties": { "name": "urn:ogc:def:crs:OGC:1.3:CRS84" } },
"features": [
{ "type": "Feature", "properties": { "point_type": "origin", "points_str": "45.524272, -122.986384" }, "geometry": { "type": "Point", "coordinates": [ -122.986384379436373, 45.524271802034292 ] } },
{ "type": "Feature", "properties": { "point_type": "destination", "points_str": "45.535652, -122.485112" }, "geometry": { "type": "Point", "coordinates": [ -122.48511153857541, 45.535651827815947 ] } }
]
}
