{
"type": "FeatureCollection",
"name": "origin_destination_points",
"crs": { "type": "name", "properties": { "name": "urn:ogc:def:crs:OGC:1.3:CRS84" } },
"features": [
{ "type": "Feature", "properties": { "point_type": "origin", "points_str": "45.356317, -122.352138" }, "geometry": { "type": "Point", "coordinates": [ -122.352138374274546, 45.356316694091795 ] } },
{ "type": "Feature", "properties": { "point_type": "destination", "points_str": "45.37315, -122.571685" }, "geometry": { "type": "Point", "coordinates": [ -122.571685063358359, 45.373149742494675 ] } }
]
}
