{
"type": "FeatureCollection",
"crs": { "type": "name", "properties": { "name": "urn:ogc:def:crs:OGC:1.3:CRS84" } },
"features": [
{ "type": "Feature", "properties": { "point_type": "origin", "points_str": "45.542787, -122.881788" }, "geometry": { "type": "Point", "coordinates": [ -122.881787948596781, 45.542787336622688 ] } },
{ "type": "Feature", "properties": { "point_type": "destination", "points_str": "45.463759, -122.79254" }, "geometry": { "type": "Point", "coordinates": [ -122.792539640509148, 45.463758831424578 ] } }
]
}
