{
"type": "FeatureCollection",
"crs": { "type": "name", "properties": { "name": "urn:ogc:def:crs:OGC:1.3:CRS84" } },
"features": [
{ "type": "Feature", "properties": { "point_type": "origin", "points_str": "45.557786, -122.561315" }, "geometry": { "type": "Point", "coordinates": [ -122.561315466279822, 45.557785971078545 ] } },
{ "type": "Feature", "properties": { "point_type": "destination", "points_str": "45.54159, -122.538586" }, "geometry": { "type": "Point", "coordinates": [ -122.538586352029967, 45.541589733814966 ] } }
]
}
