{
"type": "FeatureCollection",
"name": "origin_destination_points",
"crs": { "type": "name", "properties": { "name": "urn:ogc:def:crs:OGC:1.3:CRS84" } },
"features": [
{ "type": "Feature", "properties": { "point_type": "origin", "points_str": "45.505191, -122.475733" }, "geometry": { "type": "Point", "coordinates": [ -122.475732548961687, 45.505190566512375 ] } },
{ "type": "Feature", "properties": { "point_type": "destination", "points_str": "45.493043, -122.458968" }, "geometry": { "type": "Point", "coordinates": [ -122.458968372800499, 45.493042678071149 ] } }
]
}
