{
"type": "FeatureCollection",
"name": "origin_destination_points",
"crs": { "type": "name", "properties": { "name": "urn:ogc:def:crs:OGC:1.3:CRS84" } },
"features": [
{ "type": "Feature", "properties": { "point_type": "origin", "points_str": "45.495023, -122.785812" }, "geometry": { "type": "Point", "coordinates": [ -122.78581226938914, 45.495023401288108 ] } },
{ "type": "Feature", "properties": { "point_type": "destination", "points_str": "45.48077, -122.601647" }, "geometry": { "type": "Point", "coordinates": [ -122.601647176486892, 45.480769873857497 ] } }
]
}
