{
"type": "FeatureCollection",
"name": "origin_destination_points",
"crs": { "type": "name", "properties": { "name": "urn:ogc:def:crs:OGC:1.3:CRS84" } },
"features": [
{ "type": "Feature", "properties": { "point_type": "origin", "points_str": "45.534932, -122.491686" }, "geometry": { "type": "Point", "coordinates": [ -122.491686075537189, 45.534931570089611 ] } },
{ "type": "Feature", "properties": { "point_type": "destination", "points_str": "45.516539, -122.493556" }, "geometry": { "type": "Point", "coordinates": [ -122.493555613506587, 45.516539300354594 ] } }
]
}
