{
"type": "FeatureCollection",
"name": "origin_destination_points",
"crs": { "type": "name", "properties": { "name": "urn:ogc:def:crs:OGC:1.3:CRS84" } },
"features": [
{ "type": "Feature", "properties": { "point_type": "origin", "points_str": "45.537485, -122.684934" }, "geometry": { "type": "Point", "coordinates": [ -122.684934402845442, 45.537484992646391 ] } },
{ "type": "Feature", "properties": { "point_type": "destination", "points_str": "45.367129, -122.620257" }, "geometry": { "type": "Point", "coordinates": [ -122.620256780852202, 45.367129369846396 ] } }
]
}
