{
"type": "FeatureCollection",
"name": "origin_destination_points",
"crs": { "type": "name", "properties": { "name": "urn:ogc:def:crs:OGC:1.3:CRS84" } },
"features": [
{ "type": "Feature", "properties": { "point_type": "origin", "points_str": "45.450066, -122.590773" }, "geometry": { "type": "Point", "coordinates": [ -122.590772696835572, 45.450066126332821 ] } },
{ "type": "Feature", "properties": { "point_type": "destination", "points_str": "45.519538, -122.612488" }, "geometry": { "type": "Point", "coordinates": [ -122.61248785478918, 45.519538296373938 ] } }
]
}
