{
"type": "FeatureCollection",
"name": "origin_destination_points",
"crs": { "type": "name", "properties": { "name": "urn:ogc:def:crs:OGC:1.3:CRS84" } },
"features": [
{ "type": "Feature", "properties": { "point_type": "origin", "points_str": "45.547795, -122.627651" }, "geometry": { "type": "Point", "coordinates": [ -122.627650574319304, 45.547795027385021 ] } },
{ "type": "Feature", "properties": { "point_type": "destination", "points_str": "45.525172, -122.688478" }, "geometry": { "type": "Point", "coordinates": [ -122.688478485732773, 45.525172460484349 ] } }
]
}
