{
"type": "FeatureCollection",
"name": "origin_destination_points",
"crs": { "type": "name", "properties": { "name": "urn:ogc:def:crs:OGC:1.3:CRS84" } },
"features": [
{ "type": "Feature", "properties": { "point_type": "origin", "points_str": "45.482078, -122.648044" }, "geometry": { "type": "Point", "coordinates": [ -122.648043781692891, 45.482077756630837 ] } },
{ "type": "Feature", "properties": { "point_type": "destination", "points_str": "45.563072, -122.645764" }, "geometry": { "type": "Point", "coordinates": [ -122.645763779543003, 45.563071957854632 ] } }
]
}
