{
"type": "FeatureCollection",
"name": "origin_destination_points",
"crs": { "type": "name", "properties": { "name": "urn:ogc:def:crs:OGC:1.3:CRS84" } },
"features": [
{ "type": "Feature", "properties": { "point_type": "origin", "points_str": "45.501399, -122.802857" }, "geometry": { "type": "Point", "coordinates": [ -122.802856544106845, 45.501399480182954 ] } },
{ "type": "Feature", "properties": { "point_type": "destination", "points_str": "45.468163, -122.786376" }, "geometry": { "type": "Point", "coordinates": [ -122.786376450344221, 45.468163132994576 ] } }
]
}
