{
"type": "FeatureCollection",
"name": "origin_destination_points",
"crs": { "type": "name", "properties": { "name": "urn:ogc:def:crs:OGC:1.3:CRS84" } },
"features": [
{ "type": "Feature", "properties": { "point_type": "origin", "points_str": "45.486488, -122.768564" }, "geometry": { "type": "Point", "coordinates": [ -122.768564410001943, 45.48648768899259 ] } },
{ "type": "Feature", "properties": { "point_type": "destination", "points_str": "45.437521, -122.734523" }, "geometry": { "type": "Point", "coordinates": [ -122.734523185580429, 45.43752078024162 ] } }
]
}
