{
"type": "FeatureCollection",
"name": "origin_destination_points",
"crs": { "type": "name", "properties": { "name": "urn:ogc:def:crs:OGC:1.3:CRS84" } },
"features": [
{ "type": "Feature", "properties": { "point_type": "origin", "points_str": "45.50964, -122.686415" }, "geometry": { "type": "Point", "coordinates": [ -122.686415081375884, 45.509640229528124 ] } },
{ "type": "Feature", "properties": { "point_type": "destination", "points_str": "45.528471, -122.946328" }, "geometry": { "type": "Point", "coordinates": [ -122.946327891796273, 45.528470789737561 ] } }
]
}
