{
"type": "FeatureCollection",
"name": "origin_destination_points",
"crs": { "type": "name", "properties": { "name": "urn:ogc:def:crs:OGC:1.3:CRS84" } },
"features": [
{ "type": "Feature", "properties": { "point_type": "origin", "points_str": "45.453524, -122.680281" }, "geometry": { "type": "Point", "coordinates": [ -122.680280698508213, 45.453524134959906 ] } },
{ "type": "Feature", "properties": { "point_type": "destination", "points_str": "45.502705, -122.583602" }, "geometry": { "type": "Point", "coordinates": [ -122.583601799080498, 45.502705363446054 ] } }
]
}
