{
"type": "FeatureCollection",
"name": "origin_destination_points",
"crs": { "type": "name", "properties": { "name": "urn:ogc:def:crs:OGC:1.3:CRS84" } },
"features": [
{ "type": "Feature", "properties": { "point_type": "origin", "points_str": "45.52285, -122.678402" }, "geometry": { "type": "Point", "coordinates": [ -122.678401874132234, 45.522850042969459 ] } },
{ "type": "Feature", "properties": { "point_type": "destination", "points_str": "45.469001, -122.565205" }, "geometry": { "type": "Point", "coordinates": [ -122.565205182661245, 45.469001022822312 ] } }
]
}
