{
"type": "FeatureCollection",
"crs": { "type": "name", "properties": { "name": "urn:ogc:def:crs:OGC:1.3:CRS84" } },
"features": [
{ "type": "Feature", "properties": { "point_type": "origin", "points_str": "45.366916, -122.368897" }, "geometry": { "type": "Point", "coordinates": [ -122.368897455659322, 45.36691637183123 ] } },
{ "type": "Feature", "properties": { "point_type": "destination", "points_str": "45.4455, -122.59189" }, "geometry": { "type": "Point", "coordinates": [ -122.591890245016046, 45.445500242452361 ] } }
]
}
