{
"type": "FeatureCollection",
"name": "origin_destination_points",
"crs": { "type": "name", "properties": { "name": "urn:ogc:def:crs:OGC:1.3:CRS84" } },
"features": [
{ "type": "Feature", "properties": { "point_type": "origin", "points_str": "45.460636, -122.61983" }, "geometry": { "type": "Point", "coordinates": [ -122.619830339919076, 45.460635624107447 ] } },
{ "type": "Feature", "properties": { "point_type": "destination", "points_str": "45.549442, -122.618884" }, "geometry": { "type": "Point", "coordinates": [ -122.618884116790809, 45.549442257536398 ] } }
]
}
