{
"type": "FeatureCollection",
"crs": { "type": "name", "properties": { "name": "urn:ogc:def:crs:OGC:1.3:CRS84" } },
"features": [
{ "type": "Feature", "properties": { "point_type": "origin", "points_str": "45.557524, -122.602956" }, "geometry": { "type": "Point", "coordinates": [ -122.602955953122503, 45.557523924915934 ] } },
{ "type": "Feature", "properties": { "point_type": "destination", "points_str": "45.579858, -122.720542" }, "geometry": { "type": "Point", "coordinates": [ -122.720541859059495, 45.57985837482908 ] } }
]
}
