{
"type": "FeatureCollection",
"crs": { "type": "name", "properties": { "name": "urn:ogc:def:crs:OGC:1.3:CRS84" } },
"features": [
{ "type": "Feature", "properties": { "point_type": "origin", "points_str": "45.458707, -122.711129" }, "geometry": { "type": "Point", "coordinates": [ -122.711128991690344, 45.458706578454461 ] } },
{ "type": "Feature", "properties": { "point_type": "destination", "points_str": "45.491769, -122.459604" }, "geometry": { "type": "Point", "coordinates": [ -122.459603606166922, 45.491768799445978 ] } }
]
}
