{
"type": "FeatureCollection",
"name": "origin_destination_points",
"crs": { "type": "name", "properties": { "name": "urn:ogc:def:crs:OGC:1.3:CRS84" } },
"features": [
{ "type": "Feature", "properties": { "point_type": "origin", "points_str": "45.589607, -122.748605" }, "geometry": { "type": "Point", "coordinates": [ -122.748605330487322, 45.589606983570633 ] } },
{ "type": "Feature", "properties": { "point_type": "destination", "points_str": "45.575442, -122.680893" }, "geometry": { "type": "Point", "coordinates": [ -122.680893428373722, 45.575441649504334 ] } }
]
}
