{
"type": "FeatureCollection",
"crs": { "type": "name", "properties": { "name": "urn:ogc:def:crs:OGC:1.3:CRS84" } },
"features": [
{ "type": "Feature", "properties": { "point_type": "origin", "points_str": "45.521333, -122.563214" }, "geometry": { "type": "Point", "coordinates": [ -122.563214118201287, 45.521333073752977 ] } },
{ "type": "Feature", "properties": { "point_type": "destination", "points_str": "45.596363, -122.745917" }, "geometry": { "type": "Point", "coordinates": [ -122.745917286560811, 45.596362784002558 ] } }
]
}
