{
"type": "FeatureCollection",
"name": "origin_destination_points",
"crs": { "type": "name", "properties": { "name": "urn:ogc:def:crs:OGC:1.3:CRS84" } },
"features": [
{ "type": "Feature", "properties": { "point_type": "origin", "points_str": "45.528966, -122.685576" }, "geometry": { "type": "Point", "coordinates": [ -122.685575574751311, 45.528966002791726 ] } },
{ "type": "Feature", "properties": { "point_type": "destination", "points_str": "45.557629, -122.727624" }, "geometry": { "type": "Point", "coordinates": [ -122.727624128259961, 45.557629171196368 ] } }
]
}
