{
"type": "FeatureCollection",
"name": "origin_destination_points",
"crs": { "type": "name", "properties": { "name": "urn:ogc:def:crs:OGC:1.3:CRS84" } },
"features": [
{ "type": "Feature", "properties": { "point_type": "origin", "points_str": "45.449824, -122.59626" }, "geometry": { "type": "Point", "coordinates": [ -122.596260369209674, 45.449824121385333 ] } },
{ "type": "Feature", "properties": { "point_type": "destination", "points_str": "45.330334, -122.349831" }, "geometry": { "type": "Point", "coordinates": [ -122.349831055213713, 45.330334282837711 ] } }
]
}
