{
"type": "FeatureCollection",
"name": "origin_destination_points",
"crs": { "type": "name", "properties": { "name": "urn:ogc:def:crs:OGC:1.3:CRS84" } },
"features": [
{ "type": "Feature", "properties": { "point_type": "origin", "points_str": "45.404817, -122.587235" }, "geometry": { "type": "Point", "coordinates": [ -122.587234719189638, 45.404817148458321 ] } },
{ "type": "Feature", "properties": { "point_type": "destination", "points_str": "45.312315, -122.342947" }, "geometry": { "type": "Point", "coordinates": [ -122.342947318844267, 45.312314517537807 ] } }
]
}
