{
"type": "FeatureCollection",
"name": "origin_destination_points",
"crs": { "type": "name", "properties": { "name": "urn:ogc:def:crs:OGC:1.3:CRS84" } },
"features": [
{ "type": "Feature", "properties": { "point_type": "origin", "points_str": "45.523907, -122.866089" }, "geometry": { "type": "Point", "coordinates": [ -122.866088876239672, 45.52390682401245 ] } },
{ "type": "Feature", "properties": { "point_type": "destination", "points_str": "45.44251, -122.818414" }, "geometry": { "type": "Point", "coordinates": [ -122.818413524943679, 45.442510046302083 ] } }
]
}
