{
"type": "FeatureCollection",
"name": "origin_destination_points",
"crs": { "type": "name", "properties": { "name": "urn:ogc:def:crs:OGC:1.3:CRS84" } },
"features": [
{ "type": "Feature", "properties": { "point_type": "origin", "points_str": "45.522864, -122.890121" }, "geometry": { "type": "Point", "coordinates": [ -122.890120595990282, 45.522863872759679 ] } },
{ "type": "Feature", "properties": { "point_type": "destination", "points_str": "45.497678, -122.520551" }, "geometry": { "type": "Point", "coordinates": [ -122.520551071515456, 45.497677927050404 ] } }
]
}
