{
"type": "FeatureCollection",
"name": "origin_destination_points",
"crs": { "type": "name", "properties": { "name": "urn:ogc:def:crs:OGC:1.3:CRS84" } },
"features": [
{ "type": "Feature", "properties": { "point_type": "origin", "points_str": "45.513956, -122.678558" }, "geometry": { "type": "Point", "coordinates": [ -122.678558268701764, 45.513956419956976 ] } },
{ "type": "Feature", "properties": { "point_type": "destination", "points_str": "45.524367, -122.606988" }, "geometry": { "type": "Point", "coordinates": [ -122.606987890836606, 45.524367339775431 ] } }
]
}
