{
"type": "FeatureCollection",
"crs": { "type": "name", "properties": { "name": "urn:ogc:def:crs:OGC:1.3:CRS84" } },
"features": [
{ "type": "Feature", "properties": { "point_type": "origin", "points_str": "45.385029, -122.46034" }, "geometry": { "type": "Point", "coordinates": [ -122.460340104055518, 45.385029414866544 ] } },
{ "type": "Feature", "properties": { "point_type": "destination", "points_str": "45.563839, -122.718584" }, "geometry": { "type": "Point", "coordinates": [ -122.71858373717491, 45.563839166343762 ] } }
]
}
