{
"type": "FeatureCollection",
"name": "origin_destination_points",
"crs": { "type": "name", "properties": { "name": "urn:ogc:def:crs:OGC:1.3:CRS84" } },
"features": [
{ "type": "Feature", "properties": { "point_type": "origin", "points_str": "45.548982, -122.487537" }, "geometry": { "type": "Point", "coordinates": [ -122.487537478060872, 45.548982089084902 ] } },
{ "type": "Feature", "properties": { "point_type": "destination", "points_str": "45.54942, -122.52147" }, "geometry": { "type": "Point", "coordinates": [ -122.521470244720547, 45.549419886036496 ] } }
]
}
