{
"type": "FeatureCollection",
"crs": { "type": "name", "properties": { "name": "urn:ogc:def:crs:OGC:1.3:CRS84" } },
"features": [
{ "type": "Feature", "properties": { "point_type": "origin", "points_str": "45.534916, -122.48047" }, "geometry": { "type": "Point", "coordinates": [ -122.480470165806651, 45.534916022347588 ] } },
{ "type": "Feature", "properties": { "point_type": "destination", "points_str": "45.473677, -122.690027" }, "geometry": { "type": "Point", "coordinates": [ -122.690027101497762, 45.473677460417861 ] } }
]
}
