{
"type": "FeatureCollection",
"name": "origin_destination_points",
"crs": { "type": "name", "properties": { "name": "urn:ogc:def:crs:OGC:1.3:CRS84" } },
"features": [
{ "type": "Feature", "properties": { "point_type": "origin", "points_str": "45.594399, -122.63422" }, "geometry": { "type": "Point", "coordinates": [ -122.634220036416508, 45.594399274096602 ] } },
{ "type": "Feature", "properties": { "point_type": "destination", "points_str": "45.466846, -122.569226" }, "geometry": { "type": "Point", "coordinates": [ -122.569226035302563, 45.46684578227039 ] } }
]
}
