{
"type": "FeatureCollection",
"name": "origin_destination_points",
"crs": { "type": "name", "properties": { "name": "urn:ogc:def:crs:OGC:1.3:CRS84" } },
"features": [
{ "type": "Feature", "properties": { "point_type": "origin", "points_str": "45.470587, -122.582566" }, "geometry": { "type": "Point", "coordinates": [ -122.582565602761477, 45.470586548882686 ] } },
{ "type": "Feature", "properties": { "point_type": "destination", "points_str": "45.437786, -122.562567" }, "geometry": { "type": "Point", "coordinates": [ -122.562567388912456, 45.437785599695054 ] } }
]
}
