{
"type": "FeatureCollection",
"crs": { "type": "name", "properties": { "name": "urn:ogc:def:crs:OGC:1.3:CRS84" } },
"features": [
{ "type": "Feature", "properties": { "point_type": "origin", "points_str": "45.444812, -122.613122" }, "geometry": { "type": "Point", "coordinates": [ -122.613121932567239, 45.444811622099415 ] } },
{ "type": "Feature", "properties": { "point_type": "destination", "points_str": "45.447688, -122.640104" }, "geometry": { "type": "Point", "coordinates": [ -122.64010417827842, 45.447688013823033 ] } }
]
}
