{
"type": "FeatureCollection",
"name": "origin_destination_points",
"crs": { "type": "name", "properties": { "name": "urn:ogc:def:crs:OGC:1.3:CRS84" } },
"features": [
{ "type": "Feature", "properties": { "point_type": "origin", "points_str": "45.381311, -122.835648" }, "geometry": { "type": "Point", "coordinates": [ -122.835647954422996, 45.381310930206389 ] } },
{ "type": "Feature", "properties": { "point_type": "destination", "points_str": "45.515348, -122.684436" }, "geometry": { "type": "Point", "coordinates": [ -122.684435538960258, 45.51534836135972 ] } }
]
}
