{
"type": "FeatureCollection",
"crs": { "type": "name", "properties": { "name": "urn:ogc:def:crs:OGC:1.3:CRS84" } },
"features": [
{ "type": "Feature", "properties": { "point_type": "origin", "points_str": "45.397777, -122.630031" }, "geometry": { "type": "Point", "coordinates": [ -122.630030507800583, 45.397777498634809 ] } },
{ "type": "Feature", "properties": { "point_type": "destination", "points_str": "45.343989, -122.665329" }, "geometry": { "type": "Point", "coordinates": [ -122.665329127410203, 45.343988937812398 ] } }
]
}
