{
"type": "FeatureCollection",
"name": "origin_destination_points",
"crs": { "type": "name", "properties": { "name": "urn:ogc:def:crs:OGC:1.3:CRS84" } },
"features": [
{ "type": "Feature", "properties": { "point_type": "origin", "points_str": "45.504283, -122.421419" }, "geometry": { "type": "Point", "coordinates": [ -122.421418995469395, 45.504283316511803 ] } },
{ "type": "Feature", "properties": { "point_type": "destination", "points_str": "45.537495, -122.910237" }, "geometry": { "type": "Point", "coordinates": [ -122.910237188282892, 45.537494741818179 ] } }
]
}
