{
"type": "FeatureCollection",
"name": "origin_destination_points",
"crs": { "type": "name", "properties": { "name": "urn:ogc:def:crs:OGC:1.3:CRS84" } },
"features": [
{ "type": "Feature", "properties": { "point_type": "origin", "points_str": "45.436562, -122.671264" }, "geometry": { "type": "Point", "coordinates": [ -122.671264497726028, 45.43656189618936 ] } },
{ "type": "Feature", "properties": { "point_type": "destination", "points_str": "45.420481, -122.668156" }, "geometry": { "type": "Point", "coordinates": [ -122.668156001455458, 45.42048129343388 ] } }
]
}
