{
"type": "FeatureCollection",
"crs": { "type": "name", "properties": { "name": "urn:ogc:def:crs:OGC:1.3:CRS84" } },
"features": [
{ "type": "Feature", "properties": { "point_type": "origin", "points_str": "45.548296, -122.721211" }, "geometry": { "type": "Point", "coordinates": [ -122.721211074576019, 45.548295516684448 ] } },
{ "type": "Feature", "properties": { "point_type": "destination", "points_str": "45.534545, -122.530487" }, "geometry": { "type": "Point", "coordinates": [ -122.530487072911171, 45.534545242995584 ] } }
]
}
