{
"type": "FeatureCollection",
"crs": { "type": "name", "properties": { "name": "urn:ogc:def:crs:OGC:1.3:CRS84" } },
"features": [
{ "type": "Feature", "properties": { "point_type": "origin", "points_str": "45.4304, -122.566433" }, "geometry": { "type": "Point", "coordinates": [ -122.566433211535028, 45.43039997191083 ] } },
{ "type": "Feature", "properties": { "point_type": "destination", "points_str": "45.396681, -122.4924" }, "geometry": { "type": "Point", "coordinates": [ -122.492400200808859, 45.396680951608488 ] } }
]
}
