{
"type": "FeatureCollection",
"crs": { "type": "name", "properties": { "name": "urn:ogc:def:crs:OGC:1.3:CRS84" } },
"features": [
{ "type": "Feature", "properties": { "point_type": "origin", "points_str": "45.522574, -122.674168" }, "geometry": { "type": "Point", "coordinates": [ -122.674167570161103, 45.522574277106166 ] } },
{ "type": "Feature", "properties": { "point_type": "destination", "points_str": "45.549139, -122.631771" }, "geometry": { "type": "Point", "coordinates": [ -122.631771261623769, 45.549138652376371 ] } }
]
}
