{
"type": "FeatureCollection",
"crs": { "type": "name", "properties": { "name": "urn:ogc:def:crs:OGC:1.3:CRS84" } },
"features": [
{ "type": "Feature", "properties": { "point_type": "origin", "points_str": "45.521372, -122.661028" }, "geometry": { "type": "Point", "coordinates": [ -122.66102834770561, 45.521372411024807 ] } },
{ "type": "Feature", "properties": { "point_type": "destination", "points_str": "45.574107, -122.577134" }, "geometry": { "type": "Point", "coordinates": [ -122.577134358369705, 45.574107232247613 ] } }
]
}
