{
"type": "FeatureCollection",
"name": "origin_destination_points",
"crs": { "type": "name", "properties": { "name": "urn:ogc:def:crs:OGC:1.3:CRS84" } },
"features": [
{ "type": "Feature", "properties": { "point_type": "origin", "points_str": "45.510807, -122.666358" }, "geometry": { "type": "Point", "coordinates": [ -122.666358130597501, 45.510807039906283 ] } },
{ "type": "Feature", "properties": { "point_type": "destination", "points_str": "45.463221, -122.579384" }, "geometry": { "type": "Point", "coordinates": [ -122.579383740859441, 45.463220729581614 ] } }
]
}
