{
"type": "FeatureCollection",
"name": "origin_destination_points",
"crs": { "type": "name", "properties": { "name": "urn:ogc:def:crs:OGC:1.3:CRS84" } },
"features": [
{ "type": "Feature", "properties": { "point_type": "origin", "points_str": "45.399334, -122.655851" }, "geometry": { "type": "Point", "coordinates": [ -122.655851064134438, 45.39933409079903 ] } },
{ "type": "Feature", "properties": { "point_type": "destination", "points_str": "45.34867, -122.600916" }, "geometry": { "type": "Point", "coordinates": [ -122.600915982160643, 45.348669968988247 ] } }
]
}
