{
"type": "FeatureCollection",
"name": "origin_destination_points",
"crs": { "type": "name", "properties": { "name": "urn:ogc:def:crs:OGC:1.3:CRS84" } },
"features": [
{ "type": "Feature", "properties": { "point_type": "origin", "points_str": "45.519316, -122.497091" }, "geometry": { "type": "Point", "coordinates": [ -122.497090516226834, 45.519316217839993 ] } },
{ "type": "Feature", "properties": { "point_type": "destination", "points_str": "45.447372, -122.589199" }, "geometry": { "type": "Point", "coordinates": [ -122.589198617546842, 45.44737212536365 ] } }
]
}
