{
"type": "FeatureCollection",
"crs": { "type": "name", "properties": { "name": "urn:ogc:def:crs:OGC:1.3:CRS84" } },
"features": [
{ "type": "Feature", "properties": { "point_type": "origin", "points_str": "45.478622, -122.777707" }, "geometry": { "type": "Point", "coordinates": [ -122.777707308797858, 45.478621855374591 ] } },
{ "type": "Feature", "properties": { "point_type": "destination", "points_str": "45.448806, -122.668802" }, "geometry": { "type": "Point", "coordinates": [ -122.668801893549073, 45.448805531997301 ] } }
]
}
