{
"type": "FeatureCollection",
"name": "origin_destination_points",
"crs": { "type": "name", "properties": { "name": "urn:ogc:def:crs:OGC:1.3:CRS84" } },
"features": [
{ "type": "Feature", "properties": { "point_type": "origin", "points_str": "45.519161, -122.499895" }, "geometry": { "type": "Point", "coordinates": [ -122.499895103938698, 45.519161044177444 ] } },
{ "type": "Feature", "properties": { "point_type": "destination", "points_str": "45.4839, -122.769016" }, "geometry": { "type": "Point", "coordinates": [ -122.769016388197002, 45.48390042031037 ] } }
]
}
