{
"type": "FeatureCollection",
"crs": { "type": "name", "properties": { "name": "urn:ogc:def:crs:OGC:1.3:CRS84" } },
"features": [
{ "type": "Feature", "properties": { "point_type": "origin", "points_str": "45.54966, -122.585978" }, "geometry": { "type": "Point", "coordinates": [ -122.585977830111418, 45.549659798042029 ] } },
{ "type": "Feature", "properties": { "point_type": "destination", "points_str": "45.500018, -122.595332" }, "geometry": { "type": "Point", "coordinates": [ -122.595332070685529, 45.500018256326356 ] } }
]
}
