{
"type": "FeatureCollection",
"name": "origin_destination_points",
"crs": { "type": "name", "properties": { "name": "urn:ogc:def:crs:OGC:1.3:CRS84" } },
"features": [
{ "type": "Feature", "properties": { "point_type": "origin", "points_str": "45.512607, -122.662885" }, "geometry": { "type": "Point", "coordinates": [ -122.66288548037771, 45.512606949922258 ] } },
{ "type": "Feature", "properties": { "point_type": "destination", "points_str": "45.503374, -122.477177" }, "geometry": { "type": "Point", "coordinates": [ -122.477177133016184, 45.503374231815414 ] } }
]
}
