{
"type": "FeatureCollection",
"name": "origin_destination_points",
"crs": { "type": "name", "properties": { "name": "urn:ogc:def:crs:OGC:1.3:CRS84" } },
"features": [
{ "type": "Feature", "properties": { "point_type": "origin", "points_str": "45.540483, -122.690192" }, "geometry": { "type": "Point", "coordinates": [ -122.690191895201792, 45.540482962974053 ] } },
{ "type": "Feature", "properties": { "point_type": "destination", "points_str": "45.491339, -122.679545" }, "geometry": { "type": "Point", "coordinates": [ -122.679544672273181, 45.491338543047036 ] } }
]
}
