{
"type": "FeatureCollection",
"name": "origin_destination_points",
"crs": { "type": "name", "properties": { "name": "urn:ogc:def:crs:OGC:1.3:CRS84" } },
"features": [
{ "type": "Feature", "properties": { "point_type": "origin", "points_str": "45.478725, -122.57744" }, "geometry": { "type": "Point", "coordinates": [ -122.577440069427297, 45.478725028988883 ] } },
{ "type": "Feature", "properties": { "point_type": "destination", "points_str": "45.498479, -122.589413" }, "geometry": { "type": "Point", "coordinates": [ -122.589413049700624, 45.498479065445942 ] } }
]
}
