{
"type": "FeatureCollection",
"name": "origin_destination_points",
"crs": { "type": "name", "properties": { "name": "urn:ogc:def:crs:OGC:1.3:CRS84" } },
"features": [
{ "type": "Feature", "properties": { "point_type": "origin", "points_str": "45.516802, -122.663355" }, "geometry": { "type": "Point", "coordinates": [ -122.663355260912141, 45.516802137172206 ] } },
{ "type": "Feature", "properties": { "point_type": "destination", "points_str": "45.471197, -122.719796" }, "geometry": { "type": "Point", "coordinates": [ -122.719795813439276, 45.471197193224029 ] } }
]
}
