{
"type": "FeatureCollection",
"name": "origin_destination_points",
"crs": { "type": "name", "properties": { "name": "urn:ogc:def:crs:OGC:1.3:CRS84" } },
"features": [
{ "type": "Feature", "properties": { "point_type": "origin", "points_str": "45.552045, -122.404061" }, "geometry": { "type": "Point", "coordinates": [ -122.404060935431659, 45.552045028513483 ] } },
{ "type": "Feature", "properties": { "point_type": "destination", "points_str": "45.495401, -122.459832" }, "geometry": { "type": "Point", "coordinates": [ -122.459831978083173, 45.495401332354092 ] } }
]
}
