{
"type": "FeatureCollection",
"crs": { "type": "name", "properties": { "name": "urn:ogc:def:crs:OGC:1.3:CRS84" } },
"features": [
{ "type": "Feature", "properties": { "point_type": "origin", "points_str": "45.501048, -122.680667" }, "geometry": { "type": "Point", "coordinates": [ -122.680666787668201, 45.501047719987348 ] } },
{ "type": "Feature", "properties": { "point_type": "destination", "points_str": "45.464942, -122.746911" }, "geometry": { "type": "Point", "coordinates": [ -122.746910971771001, 45.464942110651997 ] } }
]
}
