{
"type": "FeatureCollection",
"crs": { "type": "name", "properties": { "name": "urn:ogc:def:crs:OGC:1.3:CRS84" } },
"features": [
{ "type": "Feature", "properties": { "point_type": "origin", "points_str": "45.52403, -122.653161" }, "geometry": { "type": "Point", "coordinates": [ -122.653160573281681, 45.524029683819549 ] } },
{ "type": "Feature", "properties": { "point_type": "destination", "points_str": "45.501661, -122.943096" }, "geometry": { "type": "Point", "coordinates": [ -122.943096182487295, 45.50166095756645 ] } }
]
}
