{
"type": "FeatureCollection",
"name": "origin_destination_points",
"crs": { "type": "name", "properties": { "name": "urn:ogc:def:crs:OGC:1.3:CRS84" } },
"features": [
{ "type": "Feature", "properties": { "point_type": "origin", "points_str": "45.520807, -122.393065" }, "geometry": { "type": "Point", "coordinates": [ -122.393064784552848, 45.520807416300471 ] } },
{ "type": "Feature", "properties": { "point_type": "destination", "points_str": "45.495402, -122.603261" }, "geometry": { "type": "Point", "coordinates": [ -122.603260813126923, 45.495402414851313 ] } }
]
}
