{
"type": "FeatureCollection",
"name": "origin_destination_points",
"crs": { "type": "name", "properties": { "name": "urn:ogc:def:crs:OGC:1.3:CRS84" } },
"features": [
{ "type": "Feature", "properties": { "point_type": "origin", "points_str": "45.512754, -122.588977" }, "geometry": { "type": "Point", "coordinates": [ -122.588977308797723, 45.512754143131723 ] } },
{ "type": "Feature", "properties": { "point_type": "destination", "points_str": "45.384536, -122.641792" }, "geometry": { "type": "Point", "coordinates": [ -122.641791598219754, 45.384535601728054 ] } }
]
}
