{
"type": "FeatureCollection",
"name": "origin_destination_points",
"crs": { "type": "name", "properties": { "name": "urn:ogc:def:crs:OGC:1.3:CRS84" } },
"features": [
{ "type": "Feature", "properties": { "point_type": "origin", "points_str": "45.505414, -122.439537" }, "geometry": { "type": "Point", "coordinates": [ -122.439537187716184, 45.50541423000432 ] } },
{ "type": "Feature", "properties": { "point_type": "destination", "points_str": "45.451708, -122.723638" }, "geometry": { "type": "Point", "coordinates": [ -122.723637536771278, 45.451707963737974 ] } }
]
}
