{
"type": "FeatureCollection",
"name": "origin_destination_points",
"crs": { "type": "name", "properties": { "name": "urn:ogc:def:crs:OGC:1.3:CRS84" } },
"features": [
{ "type": "Feature", "properties": { "point_type": "origin", "points_str": "45.46716, -122.709938" }, "geometry": { "type": "Point", "coordinates": [ -122.709937733631833, 45.467159501986487 ] } },
{ "type": "Feature", "properties": { "point_type": "destination", "points_str": "45.476713, -122.730556" }, "geometry": { "type": "Point", "coordinates": [ -122.730555688492203, 45.4767125501645 ] } }
]
}
