{
"type": "FeatureCollection",
"crs": { "type": "name", "properties": { "name": "urn:ogc:def:crs:OGC:1.3:CRS84" } },
"features": [
{ "type": "Feature", "properties": { "point_type": "origin", "points_str": "45.513519, -122.973846" }, "geometry": { "type": "Point", "coordinates": [ -122.97384638774669, 45.513518593898667 ] } },
{ "type": "Feature", "properties": { "point_type": "destination", "points_str": "45.435184, -122.764753" }, "geometry": { "type": "Point", "coordinates": [ -122.764753135781575, 45.43518418850104 ] } }
]
}
