{
"type": "FeatureCollection",
"name": "origin_destination_points",
"crs": { "type": "name", "properties": { "name": "urn:ogc:def:crs:OGC:1.3:CRS84" } },
"features": [
{ "type": "Feature", "properties": { "point_type": "origin", "points_str": "45.557636, -122.636357" }, "geometry": { "type": "Point", "coordinates": [ -122.636357306877301, 45.557635953159938 ] } },
{ "type": "Feature", "properties": { "point_type": "destination", "points_str": "45.548716, -122.61411" }, "geometry": { "type": "Point", "coordinates": [ -122.614110045365521, 45.548716322130758 ] } }
]
}
