{
"type": "FeatureCollection",
"name": "origin_destination_points",
"crs": { "type": "name", "properties": { "name": "urn:ogc:def:crs:OGC:1.3:CRS84" } },
"features": [
{ "type": "Feature", "properties": { "point_type": "origin", "points_str": "45.43642, -122.640901" }, "geometry": { "type": "Point", "coordinates": [ -122.64090124430848, 45.436419617397881 ] } },
{ "type": "Feature", "properties": { "point_type": "destination", "points_str": "45.56903, -122.604405" }, "geometry": { "type": "Point", "coordinates": [ -122.604404780357129, 45.569029901509928 ] } }
]
}
