{
"type": "FeatureCollection",
"name": "origin_destination_points",
"crs": { "type": "name", "properties": { "name": "urn:ogc:def:crs:OGC:1.3:CRS84" } },
"features": [
{ "type": "Feature", "properties": { "point_type": "origin", "points_str": "45.468794, -122.612103" }, "geometry": { "type": "Point", "coordinates": [ -122.612103233218605, 45.468793641825023 ] } },
{ "type": "Feature", "properties": { "point_type": "destination", "points_str": "45.514433, -122.593977" }, "geometry": { "type": "Point", "coordinates": [ -122.59397734184175, 45.514433255071545 ] } }
]
}
