{
"type": "FeatureCollection",
"crs": { "type": "name", "properties": { "name": "urn:ogc:def:crs:OGC:1.3:CRS84" } },
"features": [
{ "type": "Feature", "properties": { "point_type": "origin", "points_str": "45.494115, -122.790833" }, "geometry": { "type": "Point", "coordinates": [ -122.790832694040873, 45.494115222354317 ] } },
{ "type": "Feature", "properties": { "point_type": "destination", "points_str": "45.476127, -122.869503" }, "geometry": { "type": "Point", "coordinates": [ -122.869503057179841, 45.476127360284835 ] } }
]
}
