{
"type": "FeatureCollection",
"name": "origin_destination_points",
"crs": { "type": "name", "properties": { "name": "urn:ogc:def:crs:OGC:1.3:CRS84" } },
"features": [
{ "type": "Feature", "properties": { "point_type": "origin", "points_str": "45.46084, -122.715015" }, "geometry": { "type": "Point", "coordinates": [ -122.715015436990569, 45.460839909281511 ] } },
{ "type": "Feature", "properties": { "point_type": "destination", "points_str": "45.511372, -122.676205" }, "geometry": { "type": "Point", "coordinates": [ -122.676205424572046, 45.51137151417386 ] } }
]
}
