{
"type": "FeatureCollection",
"name": "origin_destination_points",
"crs": { "type": "name", "properties": { "name": "urn:ogc:def:crs:OGC:1.3:CRS84" } },
"features": [
{ "type": "Feature", "properties": { "point_type": "origin", "points_str": "45.488722, -122.452041" }, "geometry": { "type": "Point", "coordinates": [ -122.452041360079363, 45.48872195278777 ] } },
{ "type": "Feature", "properties": { "point_type": "destination", "points_str": "45.502079, -122.601923" }, "geometry": { "type": "Point", "coordinates": [ -122.601922567509277, 45.502079420846421 ] } }
]
}
