{
"type": "FeatureCollection",
"name": "origin_destination_points",
"crs": { "type": "name", "properties": { "name": "urn:ogc:def:crs:OGC:1.3:CRS84" } },
"features": [
{ "type": "Feature", "properties": { "point_type": "origin", "points_str": "45.487719, -122.557077" }, "geometry": { "type": "Point", "coordinates": [ -122.557077379936402, 45.487719243438384 ] } },
{ "type": "Feature", "properties": { "point_type": "destination", "points_str": "45.53375, -122.536067" }, "geometry": { "type": "Point", "coordinates": [ -122.536066657473242, 45.533749957398982 ] } }
]
}
