{
"type": "FeatureCollection",
"name": "origin_destination_points",
"crs": { "type": "name", "properties": { "name": "urn:ogc:def:crs:OGC:1.3:CRS84" } },
"features": [
{ "type": "Feature", "properties": { "point_type": "origin", "points_str": "45.376948, -122.766192" }, "geometry": { "type": "Point", "coordinates": [ -122.766192432335117, 45.37694763721553 ] } },
{ "type": "Feature", "properties": { "point_type": "destination", "points_str": "45.453961, -122.764272" }, "geometry": { "type": "Point", "coordinates": [ -122.764271655672658, 45.453961066035539 ] } }
]
}
