{
"type": "FeatureCollection",
"name": "origin_destination_points",
"crs": { "type": "name", "properties": { "name": "urn:ogc:def:crs:OGC:1.3:CRS84" } },
"features": [
{ "type": "Feature", "properties": { "point_type": "origin", "points_str": "45.493681, -122.684237" }, "geometry": { "type": "Point", "coordinates": [ -122.684237092762189, 45.493681340392961 ] } },
{ "type": "Feature", "properties": { "point_type": "destination", "points_str": "45.482986, -122.70645" }, "geometry": { "type": "Point", "coordinates": [ -122.706450197590058, 45.482985956391424 ] } }
]
}
