{
"type": "FeatureCollection",
"crs": { "type": "name", "properties": { "name": "urn:ogc:def:crs:OGC:1.3:CRS84" } },
"features": [
{ "type": "Feature", "properties": { "point_type": "origin", "points_str": "45.525832, -122.710403" }, "geometry": { "type": "Point", "coordinates": [ -122.710402662559659, 45.525832160889379 ] } },
{ "type": "Feature", "properties": { "point_type": "destination", "points_str": "45.51042, -122.775113" }, "geometry": { "type": "Point", "coordinates": [ -122.775113102405456, 45.510420242260984 ] } }
]
}
