{
"type": "FeatureCollection",
"name": "origin_destination_points",
"crs": { "type": "name", "properties": { "name": "urn:ogc:def:crs:OGC:1.3:CRS84" } },
"features": [
{ "type": "Feature", "properties": { "point_type": "origin", "points_str": "45.435978, -122.78118" }, "geometry": { "type": "Point", "coordinates": [ -122.781180342291194, 45.435977510674668 ] } },
{ "type": "Feature", "properties": { "point_type": "destination", "points_str": "45.509372, -122.960746" }, "geometry": { "type": "Point", "coordinates": [ -122.96074622630907, 45.509371622204689 ] } }
]
}
