{
"type": "FeatureCollection",
"crs": { "type": "name", "properties": { "name": "urn:ogc:def:crs:OGC:1.3:CRS84" } },
"features": [
{ "type": "Feature", "properties": { "point_type": "origin", "points_str": "45.541147, -122.660732" }, "geometry": { "type": "Point", "coordinates": [ -122.660732041951036, 45.541146862681501 ] } },
{ "type": "Feature", "properties": { "point_type": "destination", "points_str": "45.518546, -122.693701" }, "geometry": { "type": "Point", "coordinates": [ -122.693700756701489, 45.518546299423456 ] } }
]
}
