{
"type": "FeatureCollection",
"name": "origin_destination_points",
"crs": { "type": "name", "properties": { "name": "urn:ogc:def:crs:OGC:1.3:CRS84" } },
"features": [
{ "type": "Feature", "properties": { "point_type": "origin", "points_str": "45.570859, -122.687568" }, "geometry": { "type": "Point", "coordinates": [ -122.687567503308941, 45.570859291341428 ] } },
{ "type": "Feature", "properties": { "point_type": "destination", "points_str": "45.545005, -122.639901" }, "geometry": { "type": "Point", "coordinates": [ -122.639901200519915, 45.545005373246802 ] } }
]
}
