{
"type": "FeatureCollection",
"name": "origin_destination_points",
"crs": { "type": "name", "properties": { "name": "urn:ogc:def:crs:OGC:1.3:CRS84" } },
"features": [
{ "type": "Feature", "properties": { "point_type": "origin", "points_str": "45.521063, -122.605633" }, "geometry": { "type": "Point", "coordinates": [ -122.605632695163081, 45.52106275974576 ] } },
{ "type": "Feature", "properties": { "point_type": "destination", "points_str": "45.561802, -122.61273" }, "geometry": { "type": "Point", "coordinates": [ -122.612730444464873, 45.561801934946004 ] } }
]
}
