{
"type": "FeatureCollection",
"name": "origin_destination_points",
"crs": { "type": "name", "properties": { "name": "urn:ogc:def:crs:OGC:1.3:CRS84" } },
"features": [
{ "type": "Feature", "properties": { "point_type": "origin", "points_str": "45.48989, -122.571793" }, "geometry": { "type": "Point", "coordinates": [ -122.571792688253197, 45.48988970024746 ] } },
{ "type": "Feature", "properties": { "point_type": "destination", "points_str": "45.500346, -122.685249" }, "geometry": { "type": "Point", "coordinates": [ -122.685248743903898, 45.500346256526477 ] } }
]
}
