{
"type": "FeatureCollection",
"name": "origin_destination_points",
"crs": { "type": "name", "properties": { "name": "urn:ogc:def:crs:OGC:1.3:CRS84" } },
"features": [
{ "type": "Feature", "properties": { "point_type": "origin", "points_str": "45.441231, -122.644049" }, "geometry": { "type": "Point", "coordinates": [ -122.644049314317158, 45.441231060090253 ] } },
{ "type": "Feature", "properties": { "point_type": "destination", "points_str": "45.554032, -122.615823" }, "geometry": { "type": "Point", "coordinates": [ -122.615822768179171, 45.554031706140833 ] } }
]
}
