{
"type": "FeatureCollection",
"name": "origin_destination_points",
"crs": { "type": "name", "properties": { "name": "urn:ogc:def:crs:OGC:1.3:CRS84" } },
"features": [
{ "type": "Feature", "properties": { "point_type": "origin", "points_str": "45.522991, -122.49974" }, "geometry": { "type": "Point", "coordinates": [ -122.49974035758855, 45.522990826529508 ] } },
{ "type": "Feature", "properties": { "point_type": "destination", "points_str": "45.541201, -122.653338" }, "geometry": { "type": "Point", "coordinates": [ -122.653337551100179, 45.541200639730043 ] } }
]
}
