{
"type": "FeatureCollection",
"name": "origin_destination_points",
"crs": { "type": "name", "properties": { "name": "urn:ogc:def:crs:OGC:1.3:CRS84" } },
"features": [
{ "type": "Feature", "properties": { "point_type": "origin", "points_str": "45.530233, -122.59821" }, "geometry": { "type": "Point", "coordinates": [ -122.598210080374457, 45.530232624720888 ] } },
{ "type": "Feature", "properties": { "point_type": "destination", "points_str": "45.557371, -122.681827" }, "geometry": { "type": "Point", "coordinates": [ -122.681826950393926, 45.557371254117598 ] } }
]
}
