{
"type": "FeatureCollection",
"crs": { "type": "name", "properties": { "name": "urn:ogc:def:crs:OGC:1.3:CRS84" } },
"features": [
{ "type": "Feature", "properties": { "point_type": "origin", "points_str": "45.557608, -122.682128" }, "geometry": { "type": "Point", "coordinates": [ -122.682127621477548, 45.557607692549958 ] } },
{ "type": "Feature", "properties": { "point_type": "destination", "points_str": "45.507608, -122.665396" }, "geometry": { "type": "Point", "coordinates": [ -122.665396172311148, 45.507607530549173 ] } }
]
}
