{
"type": "FeatureCollection",
"crs": { "type": "name", "properties": { "name": "urn:ogc:def:crs:OGC:1.3:CRS84" } },
"features": [
{ "type": "Feature", "properties": { "point_type": "origin", "points_str": "45.467994, -122.721082" }, "geometry": { "type": "Point", "coordinates": [ -122.721082026254464, 45.467994005323028 ] } },
{ "type": "Feature", "properties": { "point_type": "destination", "points_str": "45.547682, -122.408384" }, "geometry": { "type": "Point", "coordinates": [ -122.408383644535249, 45.547682382702568 ] } }
]
}
