{
"type": "FeatureCollection",
"crs": { "type": "name", "properties": { "name": "urn:ogc:def:crs:OGC:1.3:CRS84" } },
"features": [
{ "type": "Feature", "properties": { "point_type": "origin", "points_str": "45.371213, -122.761465" }, "geometry": { "type": "Point", "coordinates": [ -122.761464573554676, 45.371212837766763 ] } },
{ "type": "Feature", "properties": { "point_type": "destination", "points_str": "45.331623, -122.56859" }, "geometry": { "type": "Point", "coordinates": [ -122.568589803124638, 45.331623115700943 ] } }
]
}
