{
"type": "FeatureCollection",
"crs": { "type": "name", "properties": { "name": "urn:ogc:def:crs:OGC:1.3:CRS84" } },
"features": [
{ "type": "Feature", "properties": { "point_type": "origin", "points_str": "45.378909, -122.738455" }, "geometry": { "type": "Point", "coordinates": [ -122.738455024366118, 45.378908574455117 ] } },
{ "type": "Feature", "properties": { "point_type": "destination", "points_str": "45.547556, -122.581253" }, "geometry": { "type": "Point", "coordinates": [ -122.581253297024602, 45.547556020100494 ] } }
]
}
