{
"type": "FeatureCollection",
"crs": { "type": "name", "properties": { "name": "urn:ogc:def:crs:OGC:1.3:CRS84" } },
"features": [
{ "type": "Feature", "properties": { "point_type": "origin", "points_str": "45.503416, -122.649328" }, "geometry": { "type": "Point", "coordinates": [ -122.649328209106855, 45.503416226550442 ] } },
{ "type": "Feature", "properties": { "point_type": "destination", "points_str": "45.467323, -122.652694" }, "geometry": { "type": "Point", "coordinates": [ -122.652693637721057, 45.467323443158087 ] } }
]
}
