{
"type": "FeatureCollection",
"name": "origin_destination_points",
"crs": { "type": "name", "properties": { "name": "urn:ogc:def:crs:OGC:1.3:CRS84" } },
"features": [
{ "type": "Feature", "properties": { "point_type": "origin", "points_str": "45.550284, -122.656115" }, "geometry": { "type": "Point", "coordinates": [ -122.656115246464623, 45.550283921592751 ] } },
{ "type": "Feature", "properties": { "point_type": "destination", "points_str": "45.52768, -122.698881" }, "geometry": { "type": "Point", "coordinates": [ -122.698880660718729, 45.527680465526167 ] } }
]
}
