{
"type": "FeatureCollection",
"name": "origin_destination_points",
"crs": { "type": "name", "properties": { "name": "urn:ogc:def:crs:OGC:1.3:CRS84" } },
"features": [
{ "type": "Feature", "properties": { "point_type": "origin", "points_str": "45.548467, -122.614002" }, "geometry": { "type": "Point", "coordinates": [ -122.614001740152077, 45.548467434056477 ] } },
{ "type": "Feature", "properties": { "point_type": "destination", "points_str": "45.506892, -122.7512" }, "geometry": { "type": "Point", "coordinates": [ -122.75119994304454, 45.506892058473262 ] } }
]
}
