{
"type": "FeatureCollection",
"name": "origin_destination_points",
"crs": { "type": "name", "properties": { "name": "urn:ogc:def:crs:OGC:1.3:CRS84" } },
"features": [
{ "type": "Feature", "properties": { "point_type": "origin", "points_str": "45.50667, -122.767151" }, "geometry": { "type": "Point", "coordinates": [ -122.767150650130034, 45.506670234874079 ] } },
{ "type": "Feature", "properties": { "point_type": "destination", "points_str": "45.532577, -122.605432" }, "geometry": { "type": "Point", "coordinates": [ -122.605431527918654, 45.532576599449008 ] } }
]
}
