{
"type": "FeatureCollection",
"name": "origin_destination_points",
"crs": { "type": "name", "properties": { "name": "urn:ogc:def:crs:OGC:1.3:CRS84" } },
"features": [
{ "type": "Feature", "properties": { "point_type": "origin", "points_str": "45.410754, -122.536296" }, "geometry": { "type": "Point", "coordinates": [ -122.536296124037918, 45.41075355365345 ] } },
{ "type": "Feature", "properties": { "point_type": "destination", "points_str": "45.384018, -122.393304" }, "geometry": { "type": "Point", "coordinates": [ -122.393303993674948, 45.384018416748518 ] } }
]
}
