{
"type": "FeatureCollection",
"name": "origin_destination_points",
"crs": { "type": "name", "properties": { "name": "urn:ogc:def:crs:OGC:1.3:CRS84" } },
"features": [
{ "type": "Feature", "properties": { "point_type": "origin", "points_str": "45.444822, -122.638228" }, "geometry": { "type": "Point", "coordinates": [ -122.638228100812867, 45.444821915354822 ] } },
{ "type": "Feature", "properties": { "point_type": "destination", "points_str": "45.489753, -122.568541" }, "geometry": { "type": "Point", "coordinates": [ -122.568541411291207, 45.489753101422977 ] } }
]
}
