{
"type": "FeatureCollection",
"name": "origin_destination_points",
"crs": { "type": "name", "properties": { "name": "urn:ogc:def:crs:OGC:1.3:CRS84" } },
"features": [
{ "type": "Feature", "properties": { "point_type": "origin", "points_str": "45.540477, -122.649835" }, "geometry": { "type": "Point", "coordinates": [ -122.649835106028135, 45.54047705428227 ] } },
{ "type": "Feature", "properties": { "point_type": "destination", "points_str": "45.486732, -122.681691" }, "geometry": { "type": "Point", "coordinates": [ -122.681691056543542, 45.486731608577756 ] } }
]
}
