{
"type": "FeatureCollection",
"name": "origin_destination_points",
"crs": { "type": "name", "properties": { "name": "urn:ogc:def:crs:OGC:1.3:CRS84" } },
"features": [
{ "type": "Feature", "properties": { "point_type": "origin", "points_str": "45.553328, -122.584713" }, "geometry": { "type": "Point", "coordinates": [ -122.584712582391205, 45.553328296299327 ] } },
{ "type": "Feature", "properties": { "point_type": "destination", "points_str": "45.413927, -122.592053" }, "geometry": { "type": "Point", "coordinates": [ -122.592052600508424, 45.413926668752516 ] } }
]
}
