{
"type": "FeatureCollection",
"name": "origin_destination_points",
"crs": { "type": "name", "properties": { "name": "urn:ogc:def:crs:OGC:1.3:CRS84" } },
"features": [
{ "type": "Feature", "properties": { "point_type": "origin", "points_str": "45.493157, -122.781904" }, "geometry": { "type": "Point", "coordinates": [ -122.781904473705325, 45.49315697284559 ] } },
{ "type": "Feature", "properties": { "point_type": "destination", "points_str": "45.505122, -122.744805" }, "geometry": { "type": "Point", "coordinates": [ -122.744804745679858, 45.505122271427254 ] } }
]
}
