{
"type": "FeatureCollection",
"name": "origin_destination_points",
"crs": { "type": "name", "properties": { "name": "urn:ogc:def:crs:OGC:1.3:CRS84" } },
"features": [
{ "type": "Feature", "properties": { "point_type": "origin", "points_str": "45.448575, -122.658768" }, "geometry": { "type": "Point", "coordinates": [ -122.658768484334473, 45.448575174664334 ] } },
{ "type": "Feature", "properties": { "point_type": "destination", "points_str": "45.543827, -122.695809" }, "geometry": { "type": "Point", "coordinates": [ -122.695809417996813, 45.54382740232311 ] } }
]
}
