{
"type": "FeatureCollection",
"name": "origin_destination_points",
"crs": { "type": "name", "properties": { "name": "urn:ogc:def:crs:OGC:1.3:CRS84" } },
"features": [
{ "type": "Feature", "properties": { "point_type": "origin", "points_str": "45.49814, -122.907691" }, "geometry": { "type": "Point", "coordinates": [ -122.907690683869021, 45.49814000839249 ] } },
{ "type": "Feature", "properties": { "point_type": "destination", "points_str": "45.521746, -122.617219" }, "geometry": { "type": "Point", "coordinates": [ -122.617219265740871, 45.521746214446431 ] } }
]
}
