{
"type": "FeatureCollection",
"name": "origin_destination_points",
"crs": { "type": "name", "properties": { "name": "urn:ogc:def:crs:OGC:1.3:CRS84" } },
"features": [
{ "type": "Feature", "properties": { "point_type": "origin", "points_str": "45.503974, -122.399284" }, "geometry": { "type": "Point", "coordinates": [ -122.399283749673188, 45.503974461448571 ] } },
{ "type": "Feature", "properties": { "point_type": "destination", "points_str": "45.524849, -122.589387" }, "geometry": { "type": "Point", "coordinates": [ -122.589386893551904, 45.52484930243542 ] } }
]
}
