{
"type": "FeatureCollection",
"crs": { "type": "name", "properties": { "name": "urn:ogc:def:crs:OGC:1.3:CRS84" } },
"features": [
{ "type": "Feature", "properties": { "point_type": "origin", "points_str": "45.528287, -122.649812" }, "geometry": { "type": "Point", "coordinates": [ -122.649811740930005, 45.528287008448601 ] } },
{ "type": "Feature", "properties": { "point_type": "destination", "points_str": "45.491786, -122.619012" }, "geometry": { "type": "Point", "coordinates": [ -122.619011793405988, 45.491786052711568 ] } }
]
}
