{
"type": "FeatureCollection",
"name": "origin_destination_points",
"crs": { "type": "name", "properties": { "name": "urn:ogc:def:crs:OGC:1.3:CRS84" } },
"features": [
{ "type": "Feature", "properties": { "point_type": "origin", "points_str": "45.32484, -122.572136" }, "geometry": { "type": "Point", "coordinates": [ -122.572135732301874, 45.324840229382694 ] } },
{ "type": "Feature", "properties": { "point_type": "destination", "points_str": "45.42693, -122.632087" }, "geometry": { "type": "Point", "coordinates": [ -122.632086579691091, 45.426929851335217 ] } }
]
}
