{
"type": "FeatureCollection",
"crs": { "type": "name", "properties": { "name": "urn:ogc:def:crs:OGC:1.3:CRS84" } },
"features": [
{ "type": "Feature", "properties": { "point_type": "origin", "points_str": "45.476213, -122.612916" }, "geometry": { "type": "Point", "coordinates": [ -122.61291642684877, 45.476213098146715 ] } },
{ "type": "Feature", "properties": { "point_type": "destination", "points_str": "45.483776, -122.575527" }, "geometry": { "type": "Point", "coordinates": [ -122.575526861434184, 45.483776362586859 ] } }
]
}
