{
"type": "FeatureCollection",
"name": "origin_destination_points",
"crs": { "type": "name", "properties": { "name": "urn:ogc:def:crs:OGC:1.3:CRS84" } },
"features": [
{ "type": "Feature", "properties": { "point_type": "origin", "points_str": "45.519998, -122.627391" }, "geometry": { "type": "Point", "coordinates": [ -122.627391489486925, 45.51999789837118 ] } },
{ "type": "Feature", "properties": { "point_type": "destination", "points_str": "45.49084, -122.54403" }, "geometry": { "type": "Point", "coordinates": [ -122.544030050360746, 45.490839698913298 ] } }
]
}
