{
"type": "FeatureCollection",
"crs": { "type": "name", "properties": { "name": "urn:ogc:def:crs:OGC:1.3:CRS84" } },
"features": [
{ "type": "Feature", "properties": { "point_type": "origin", "points_str": "45.501207, -122.823235" }, "geometry": { "type": "Point", "coordinates": [ -122.823234878889707, 45.501207159637488 ] } },
{ "type": "Feature", "properties": { "point_type": "destination", "points_str": "45.483499, -122.85499" }, "geometry": { "type": "Point", "coordinates": [ -122.85498973163007, 45.483498785958503 ] } }
]
}
