{
"type": "FeatureCollection",
"crs": { "type": "name", "properties": { "name": "urn:ogc:def:crs:OGC:1.3:CRS84" } },
"features": [
{ "type": "Feature", "properties": { "point_type": "origin", "points_str": "45.477269, -122.649491" }, "geometry": { "type": "Point", "coordinates": [ -122.64949076745846, 45.477268895361114 ] } },
{ "type": "Feature", "properties": { "point_type": "destination", "points_str": "45.506749, -122.549907" }, "geometry": { "type": "Point", "coordinates": [ -122.549907447720344, 45.506748564242926 ] } }
]
}
