{
"type": "FeatureCollection",
"name": "origin_destination_points",
"crs": { "type": "name", "properties": { "name": "urn:ogc:def:crs:OGC:1.3:CRS84" } },
"features": [
{ "type": "Feature", "properties": { "point_type": "origin", "points_str": "45.596827, -122.754995" }, "geometry": { "type": "Point", "coordinates": [ -122.754994978254345, 45.59682667403122 ] } },
{ "type": "Feature", "properties": { "point_type": "destination", "points_str": "45.549774, -122.617623" }, "geometry": { "type": "Point", "coordinates": [ -122.617622868231422, 45.549774269586919 ] } }
]
}
