{
"type": "FeatureCollection",
"name": "origin_destination_points",
"crs": { "type": "name", "properties": { "name": "urn:ogc:def:crs:OGC:1.3:CRS84" } },
"features": [
{ "type": "Feature", "properties": { "point_type": "origin", "points_str": "45.423586, -122.669045" }, "geometry": { "type": "Point", "coordinates": [ -122.669044957370431, 45.4235860280656 ] } },
{ "type": "Feature", "properties": { "point_type": "destination", "points_str": "45.528565, -122.698234" }, "geometry": { "type": "Point", "coordinates": [ -122.698233579498122, 45.528565343863413 ] } }
]
}
