{
"type": "FeatureCollection",
"name": "origin_destination_points",
"crs": { "type": "name", "properties": { "name": "urn:ogc:def:crs:OGC:1.3:CRS84" } },
"features": [
{ "type": "Feature", "properties": { "point_type": "origin", "points_str": "45.503269, -122.607248" }, "geometry": { "type": "Point", "coordinates": [ -122.607248353991906, 45.503269007639567 ] } },
{ "type": "Feature", "properties": { "point_type": "destination", "points_str": "45.504452, -122.667933" }, "geometry": { "type": "Point", "coordinates": [ -122.667932919557458, 45.504452314582302 ] } }
]
}
