{
"type": "FeatureCollection",
"name": "origin_destination_points",
"crs": { "type": "name", "properties": { "name": "urn:ogc:def:crs:OGC:1.3:CRS84" } },
"features": [
{ "type": "Feature", "properties": { "point_type": "origin", "points_str": "45.487156, -122.72051" }, "geometry": { "type": "Point", "coordinates": [ -122.720509590317462, 45.487156104691984 ] } },
{ "type": "Feature", "properties": { "point_type": "destination", "points_str": "45.497697, -122.60989" }, "geometry": { "type": "Point", "coordinates": [ -122.609890120289037, 45.497697066821551 ] } }
]
}
