{
"type": "FeatureCollection",
"name": "origin_destination_points",
"crs": { "type": "name", "properties": { "name": "urn:ogc:def:crs:OGC:1.3:CRS84" } },
"features": [
{ "type": "Feature", "properties": { "point_type": "origin", "points_str": "45.495207, -122.680894" }, "geometry": { "type": "Point", "coordinates": [ -122.680894351028073, 45.495206623959504 ] } },
{ "type": "Feature", "properties": { "point_type": "destination", "points_str": "45.472202, -122.710394" }, "geometry": { "type": "Point", "coordinates": [ -122.71039372454112, 45.472201761180365 ] } }
]
}
