{
"type": "FeatureCollection",
"name": "origin_destination_points",
"crs": { "type": "name", "properties": { "name": "urn:ogc:def:crs:OGC:1.3:CRS84" } },
"features": [
{ "type": "Feature", "properties": { "point_type": "origin", "points_str": "45.580051, -122.63623" }, "geometry": { "type": "Point", "coordinates": [ -122.636229841458643, 45.58005122056916 ] } },
{ "type": "Feature", "properties": { "point_type": "destination", "points_str": "45.502249, -122.591832" }, "geometry": { "type": "Point", "coordinates": [ -122.591831940855315, 45.502249072859087 ] } }
]
}
