{
"type": "FeatureCollection",
"name": "origin_destination_points",
"crs": { "type": "name", "properties": { "name": "urn:ogc:def:crs:OGC:1.3:CRS84" } },
"features": [
{ "type": "Feature", "properties": { "point_type": "origin", "points_str": "45.536064, -122.701645" }, "geometry": { "type": "Point", "coordinates": [ -122.701644890690716, 45.536064169767002 ] } },
{ "type": "Feature", "properties": { "point_type": "destination", "points_str": "45.51301, -122.699054" }, "geometry": { "type": "Point", "coordinates": [ -122.69905361965769, 45.513010165154114 ] } }
]
}
