{
"type": "FeatureCollection",
"name": "origin_destination_points",
"crs": { "type": "name", "properties": { "name": "urn:ogc:def:crs:OGC:1.3:CRS84" } },
"features": [
{ "type": "Feature", "properties": { "point_type": "origin", "points_str": "45.542459, -122.646738" }, "geometry": { "type": "Point", "coordinates": [ -122.646737639713535, 45.542458648536524 ] } },
{ "type": "Feature", "properties": { "point_type": "destination", "points_str": "45.367865, -122.618027" }, "geometry": { "type": "Point", "coordinates": [ -122.618026811328903, 45.367865181188847 ] } }
]
}
