{
"type": "FeatureCollection",
"crs": { "type": "name", "properties": { "name": "urn:ogc:def:crs:OGC:1.3:CRS84" } },
"features": [
{ "type": "Feature", "properties": { "point_type": "origin", "points_str": "45.5486, -122.606373" }, "geometry": { "type": "Point", "coordinates": [ -122.606372685545551, 45.548599885850031 ] } },
{ "type": "Feature", "properties": { "point_type": "destination", "points_str": "45.514371, -122.463485" }, "geometry": { "type": "Point", "coordinates": [ -122.463485275485155, 45.514371339370115 ] } }
]
}
