{
"type": "FeatureCollection",
"name": "origin_destination_points",
"crs": { "type": "name", "properties": { "name": "urn:ogc:def:crs:OGC:1.3:CRS84" } },
"features": [
{ "type": "Feature", "properties": { "point_type": "origin", "points_str": "45.532085, -122.481143" }, "geometry": { "type": "Point", "coordinates": [ -122.481143294194879, 45.532085031284517 ] } },
{ "type": "Feature", "properties": { "point_type": "destination", "points_str": "45.521024, -122.987204" }, "geometry": { "type": "Point", "coordinates": [ -122.987204396509242, 45.521023678218029 ] } }
]
}
