{
"type": "FeatureCollection",
"name": "origin_destination_points",
"crs": { "type": "name", "properties": { "name": "urn:ogc:def:crs:OGC:1.3:CRS84" } },
"features": [
{ "type": "Feature", "properties": { "point_type": "origin", "points_str": "45.56254, -122.636781" }, "geometry": { "type": "Point", "coordinates": [ -122.636781201627315, 45.562539928320035 ] } },
{ "type": "Feature", "properties": { "point_type": "destination", "points_str": "45.459253, -122.682541" }, "geometry": { "type": "Point", "coordinates": [ -122.682540853342488, 45.459252936967303 ] } }
]
}
