{
"type": "FeatureCollection",
"crs": { "type": "name", "properties": { "name": "urn:ogc:def:crs:OGC:1.3:CRS84" } },
"features": [
{ "type": "Feature", "properties": { "point_type": "origin", "points_str": "45.516156, -122.624036" }, "geometry": { "type": "Point", "coordinates": [ -122.624035892099471, 45.516156049795477 ] } },
{ "type": "Feature", "properties": { "point_type": "destination", "points_str": "45.50479, -122.564354" }, "geometry": { "type": "Point", "coordinates": [ -122.564353722258474, 45.504790426874088 ] } }
]
}
