{
"type": "FeatureCollection",
"name": "origin_destination_points",
"crs": { "type": "name", "properties": { "name": "urn:ogc:def:crs:OGC:1.3:CRS84" } },
"features": [
{ "type": "Feature", "properties": { "point_type": "origin", "points_str": "45.549092, -122.902893" }, "geometry": { "type": "Point", "coordinates": [ -122.902892878152016, 45.549091537406525 ] } },
{ "type": "Feature", "properties": { "point_type": "destination", "points_str": "45.509805, -122.441694" }, "geometry": { "type": "Point", "coordinates": [ -122.441693895277766, 45.509805419963108 ] } }
]
}
