{
"type": "FeatureCollection",
"crs": { "type": "name", "properties": { "name": "urn:ogc:def:crs:OGC:1.3:CRS84" } },
"features": [
{ "type": "Feature", "properties": { "point_type": "origin", "points_str": "45.496133, -122.505073" }, "geometry": { "type": "Point", "coordinates": [ -122.505073057976389, 45.49613311492471 ] } },
{ "type": "Feature", "properties": { "point_type": "destination", "points_str": "45.520069, -122.499765" }, "geometry": { "type": "Point", "coordinates": [ -122.499765187775949, 45.520069247091463 ] } }
]
}
