{
"type": "FeatureCollection",
"crs": { "type": "name", "properties": { "name": "urn:ogc:def:crs:OGC:1.3:CRS84" } },
"features": [
{ "type": "Feature", "properties": { "point_type": "origin", "points_str": "45.503503, -122.428941" }, "geometry": { "type": "Point", "coordinates": [ -122.428940510760157, 45.503503243315031 ] } },
{ "type": "Feature", "properties": { "point_type": "destination", "points_str": "45.527059, -122.944604" }, "geometry": { "type": "Point", "coordinates": [ -122.944604218540519, 45.527058919523988 ] } }
]
}
