{
"type": "FeatureCollection",
"name": "origin_destination_points",
"crs": { "type": "name", "properties": { "name": "urn:ogc:def:crs:OGC:1.3:CRS84" } },
"features": [
{ "type": "Feature", "properties": { "point_type": "origin", "points_str": "45.353532, -122.773922" }, "geometry": { "type": "Point", "coordinates": [ -122.773921867519391, 45.353531999383783 ] } },
{ "type": "Feature", "properties": { "point_type": "destination", "points_str": "45.463501, -122.658567" }, "geometry": { "type": "Point", "coordinates": [ -122.658567348144189, 45.463501190974029 ] } }
]
}
