{
"type": "FeatureCollection",
"crs": { "type": "name", "properties": { "name": "urn:ogc:def:crs:OGC:1.3:CRS84" } },
"features": [
{ "type": "Feature", "properties": { "point_type": "origin", "points_str": "45.486292, -122.728211" }, "geometry": { "type": "Point", "coordinates": [ -122.728211412442192, 45.486291661866694 ] } },
{ "type": "Feature", "properties": { "point_type": "destination", "points_str": "45.478004, -122.530233" }, "geometry": { "type": "Point", "coordinates": [ -122.530233381198173, 45.478003732572226 ] } }
]
}
