{
"type": "FeatureCollection",
"crs": { "type": "name", "properties": { "name": "urn:ogc:def:crs:OGC:1.3:CRS84" } },
"features": [
{ "type": "Feature", "properties": { "point_type": "origin", "points_str": "45.519711, -122.504848" }, "geometry": { "type": "Point", "coordinates": [ -122.50484831444497, 45.519711077898073 ] } },
{ "type": "Feature", "properties": { "point_type": "destination", "points_str": "45.444204, -122.575648" }, "geometry": { "type": "Point", "coordinates": [ -122.575648439484794, 45.444203534951029 ] } }
]
}
