{
"type": "FeatureCollection",
"name": "origin_destination_points",
"crs": { "type": "name", "properties": { "name": "urn:ogc:def:crs:OGC:1.3:CRS84" } },
"features": [
{ "type": "Feature", "properties": { "point_type": "origin", "points_str": "45.316808, -122.568873" }, "geometry": { "type": "Point", "coordinates": [ -122.568873373404301, 45.316808383185723 ] } },
{ "type": "Feature", "properties": { "point_type": "destination", "points_str": "45.410556, -122.584872" }, "geometry": { "type": "Point", "coordinates": [ -122.584871558607901, 45.410555546946298 ] } }
]
}
