{
"type": "FeatureCollection",
"name": "origin_destination_points",
"crs": { "type": "name", "properties": { "name": "urn:ogc:def:crs:OGC:1.3:CRS84" } },
"features": [
{ "type": "Feature", "properties": { "point_type": "origin", "points_str": "45.52366, -122.797641" }, "geometry": { "type": "Point", "coordinates": [ -122.797641419837035, 45.52366011506399 ] } },
{ "type": "Feature", "properties": { "point_type": "destination", "points_str": "45.469908, -122.82181" }, "geometry": { "type": "Point", "coordinates": [ -122.821810338166927, 45.46990757734612 ] } }
]
}
