{
"type": "FeatureCollection",
"name": "origin_destination_points",
"crs": { "type": "name", "properties": { "name": "urn:ogc:def:crs:OGC:1.3:CRS84" } },
"features": [
{ "type": "Feature", "properties": { "point_type": "origin", "points_str": "45.5298, -122.62978" }, "geometry": { "type": "Point", "coordinates": [ -122.629779766982367, 45.529800038769856 ] } },
{ "type": "Feature", "properties": { "point_type": "destination", "points_str": "45.517835, -122.791491" }, "geometry": { "type": "Point", "coordinates": [ -122.791491195962365, 45.517835065384162 ] } }
]
}
