{
"type": "FeatureCollection",
"name": "origin_destination_points",
"crs": { "type": "name", "properties": { "name": "urn:ogc:def:crs:OGC:1.3:CRS84" } },
"features": [
{ "type": "Feature", "properties": { "point_type": "origin", "points_str": "45.564632, -122.556144" }, "geometry": { "type": "Point", "coordinates": [ -122.556144489472914, 45.564632085502417 ] } },
{ "type": "Feature", "properties": { "point_type": "destination", "points_str": "45.496954, -122.451962" }, "geometry": { "type": "Point", "coordinates": [ -122.451962060424194, 45.496953918448199 ] } }
]
}
