{
"type": "FeatureCollection",
"crs": { "type": "name", "properties": { "name": "urn:ogc:def:crs:OGC:1.3:CRS84" } },
"features": [
{ "type": "Feature", "properties": { "point_type": "origin", "points_str": "45.433978, -122.543556" }, "geometry": { "type": "Point", "coordinates": [ -122.543556311301572, 45.433978297437939 ] } },
{ "type": "Feature", "properties": { "point_type": "destination", "points_str": "45.431475, -122.5785" }, "geometry": { "type": "Point", "coordinates": [ -122.57850010005285, 45.431475104783551 ] } }
]
}
