{
"type": "FeatureCollection",
"name": "origin_destination_points",
"crs": { "type": "name", "properties": { "name": "urn:ogc:def:crs:OGC:1.3:CRS84" } },
"features": [
{ "type": "Feature", "properties": { "point_type": "origin", "points_str": "45.572127, -122.679356" }, "geometry": { "type": "Point", "coordinates": [ -122.679355916529957, 45.572127395302509 ] } },
{ "type": "Feature", "properties": { "point_type": "destination", "points_str": "45.560002, -122.61589" }, "geometry": { "type": "Point", "coordinates": [ -122.615889670620774, 45.56000205028694 ] } }
]
}
