{
"type": "FeatureCollection",
"crs": { "type": "name", "properties": { "name": "urn:ogc:def:crs:OGC:1.3:CRS84" } },
"features": [
{ "type": "Feature", "properties": { "point_type": "origin", "points_str": "45.566022, -122.533861" }, "geometry": { "type": "Point", "coordinates": [ -122.533861240876362, 45.566022298042981 ] } },
{ "type": "Feature", "properties": { "point_type": "destination", "points_str": "45.480532, -122.756588" }, "geometry": { "type": "Point", "coordinates": [ -122.756587702928599, 45.480531715545908 ] } }
]
}
