{
"type": "FeatureCollection",
"crs": { "type": "name", "properties": { "name": "urn:ogc:def:crs:OGC:1.3:CRS84" } },
"features": [
{ "type": "Feature", "properties": { "point_type": "origin", "points_str": "45.517206, -122.497353" }, "geometry": { "type": "Point", "coordinates": [ -122.497353441383495, 45.517205661926667 ] } },
{ "type": "Feature", "properties": { "point_type": "destination", "points_str": "45.477085, -122.55888" }, "geometry": { "type": "Point", "coordinates": [ -122.558879544302329, 45.477084837878721 ] } }
]
}
