{
"type": "FeatureCollection",
"name": "origin_destination_points",
"crs": { "type": "name", "properties": { "name": "urn:ogc:def:crs:OGC:1.3:CRS84" } },
"features": [
{ "type": "Feature", "properties": { "point_type": "origin", "points_str": "45.521075, -123.00025" }, "geometry": { "type": "Point", "coordinates": [ -123.000250059236336, 45.521074642439508 ] } },
{ "type": "Feature", "properties": { "point_type": "destination", "points_str": "45.48898, -122.839616" }, "geometry": { "type": "Point", "coordinates": [ -122.839616477876234, 45.488979977142925 ] } }
]
}
