{
"type": "FeatureCollection",
"name": "origin_destination_points",
"crs": { "type": "name", "properties": { "name": "urn:ogc:def:crs:OGC:1.3:CRS84" } },
"features": [
{ "type": "Feature", "properties": { "point_type": "origin", "points_str": "45.486338, -122.686828" }, "geometry": { "type": "Point", "coordinates": [ -122.686827538015223, 45.486338148598144 ] } },
{ "type": "Feature", "properties": { "point_type": "destination", "points_str": "45.611477, -122.685259" }, "geometry": { "type": "Point", "coordinates": [ -122.685259427421016, 45.61147726600737 ] } }
]
}
