{
"type": "FeatureCollection",
"name": "origin_destination_points",
"crs": { "type": "name", "properties": { "name": "urn:ogc:def:crs:OGC:1.3:CRS84" } },
"features": [
{ "type": "Feature", "properties": { "point_type": "origin", "points_str": "45.411373, -122.50495" }, "geometry": { "type": "Point", "coordinates": [ -122.504950327533265, 45.411372782844317 ] } },
{ "type": "Feature", "properties": { "point_type": "destination", "points_str": "45.449016, -122.592002" }, "geometry": { "type": "Point", "coordinates": [ -122.592001628155913, 45.449015794573128 ] } }
]
}
