{
"type": "FeatureCollection",
"name": "origin_destination_points",
"crs": { "type": "name", "properties": { "name": "urn:ogc:def:crs:OGC:1.3:CRS84" } },
"features": [
{ "type": "Feature", "properties": { "point_type": "origin", "points_str": "45.518259, -122.395952" }, "geometry": { "type": "Point", "coordinates": [ -122.39595152303562, 45.518258750818184 ] } },
{ "type": "Feature", "properties": { "point_type": "destination", "points_str": "45.504742, -122.827543" }, "geometry": { "type": "Point", "coordinates": [ -122.827542780120112, 45.504742447371761 ] } }
]
}
