{
"type": "FeatureCollection",
"crs": { "type": "name", "properties": { "name": "urn:ogc:def:crs:OGC:1.3:CRS84" } },
"features": [
{ "type": "Feature", "properties": { "point_type": "origin", "points_str": "45.490819, -122.479292" }, "geometry": { "type": "Point", "coordinates": [ -122.479291558440934, 45.490818833634407 ] } },
{ "type": "Feature", "properties": { "point_type": "destination", "points_str": "45.535209, -122.503075" }, "geometry": { "type": "Point", "coordinates": [ -122.503074663920671, 45.535209473670307 ] } }
]
}
