{
"type": "FeatureCollection",
"crs": { "type": "name", "properties": { "name": "urn:ogc:def:crs:OGC:1.3:CRS84" } },
"features": [
{ "type": "Feature", "properties": { "point_type": "origin", "points_str": "45.497757, -122.402696" }, "geometry": { "type": "Point", "coordinates": [ -122.402696220115544, 45.497756582580479 ] } },
{ "type": "Feature", "properties": { "point_type": "destination", "points_str": "45.522391, -122.553304" }, "geometry": { "type": "Point", "coordinates": [ -122.553304145336028, 45.522390852505794 ] } }
]
}
