{
"type": "FeatureCollection",
"name": "origin_destination_points",
"crs": { "type": "name", "properties": { "name": "urn:ogc:def:crs:OGC:1.3:CRS84" } },
"features": [
{ "type": "Feature", "properties": { "point_type": "origin", "points_str": "45.457654, -122.574026" }, "geometry": { "type": "Point", "coordinates": [ -122.574025670977974, 45.457653757402092 ] } },
{ "type": "Feature", "properties": { "point_type": "destination", "points_str": "45.391824, -122.463342" }, "geometry": { "type": "Point", "coordinates": [ -122.463342393619868, 45.391824415715519 ] } }
]
}
