{
"type": "FeatureCollection",
"crs": { "type": "name", "properties": { "name": "urn:ogc:def:crs:OGC:1.3:CRS84" } },
"features": [
{ "type": "Feature", "properties": { "point_type": "origin", "points_str": "45.408986, -122.562394" }, "geometry": { "type": "Point", "coordinates": [ -122.562394131896141, 45.408985953239558 ] } },
{ "type": "Feature", "properties": { "point_type": "destination", "points_str": "45.564673, -122.686726" }, "geometry": { "type": "Point", "coordinates": [ -122.686725641775894, 45.564673181258421 ] } }
]
}
