{
"type": "FeatureCollection",
"crs": { "type": "name", "properties": { "name": "urn:ogc:def:crs:OGC:1.3:CRS84" } },
"features": [
{ "type": "Feature", "properties": { "point_type": "origin", "points_str": "45.49224, -122.770416" }, "geometry": { "type": "Point", "coordinates": [ -122.770416054531537, 45.492240293218153 ] } },
{ "type": "Feature", "properties": { "point_type": "destination", "points_str": "45.426806, -122.657305" }, "geometry": { "type": "Point", "coordinates": [ -122.657305156602149, 45.426805889747172 ] } }
]
}
