{
"type": "FeatureCollection",
"name": "origin_destination_points",
"crs": { "type": "name", "properties": { "name": "urn:ogc:def:crs:OGC:1.3:CRS84" } },
"features": [
{ "type": "Feature", "properties": { "point_type": "origin", "points_str": "45.52172, -122.536663" }, "geometry": { "type": "Point", "coordinates": [ -122.536662773110194, 45.521720037638651 ] } },
{ "type": "Feature", "properties": { "point_type": "destination", "points_str": "45.597893, -122.743911" }, "geometry": { "type": "Point", "coordinates": [ -122.743911168310262, 45.597892928962544 ] } }
]
}
