{
"type": "FeatureCollection",
"name": "origin_destination_points",
"crs": { "type": "name", "properties": { "name": "urn:ogc:def:crs:OGC:1.3:CRS84" } },
"features": [
{ "type": "Feature", "properties": { "point_type": "origin", "points_str": "45.489193, -122.887216" }, "geometry": { "type": "Point", "coordinates": [ -122.887216257663908, 45.489192948894576 ] } },
{ "type": "Feature", "properties": { "point_type": "destination", "points_str": "45.518291, -123.021886" }, "geometry": { "type": "Point", "coordinates": [ -123.021885714019575, 45.518290718473637 ] } }
]
}
