{
"type": "FeatureCollection",
"name": "origin_destination_points",
"crs": { "type": "name", "properties": { "name": "urn:ogc:def:crs:OGC:1.3:CRS84" } },
"features": [
{ "type": "Feature", "properties": { "point_type": "origin", "points_str": "45.507078, -122.548608" }, "geometry": { "type": "Point", "coordinates": [ -122.548608246498645, 45.507078292845321 ] } },
{ "type": "Feature", "properties": { "point_type": "destination", "points_str": "45.496881, -122.664862" }, "geometry": { "type": "Point", "coordinates": [ -122.664861501832078, 45.496880996194619 ] } }
]
}
