{
"type": "FeatureCollection",
"name": "origin_destination_points",
"crs": { "type": "name", "properties": { "name": "urn:ogc:def:crs:OGC:1.3:CRS84" } },
"features": [
{ "type": "Feature", "properties": { "point_type": "origin", "points_str": "45.597971, -122.662381" }, "geometry": { "type": "Point", "coordinates": [ -122.66238108405993, 45.597971042517955 ] } },
{ "type": "Feature", "properties": { "point_type": "destination", "points_str": "45.620545, -122.727043" }, "geometry": { "type": "Point", "coordinates": [ -122.727042795093865, 45.620545140642378 ] } }
]
}
