{
"type": "FeatureCollection",
"name": "origin_destination_points",
"crs": { "type": "name", "properties": { "name": "urn:ogc:def:crs:OGC:1.3:CRS84" } },
"features": [
{ "type": "Feature", "properties": { "point_type": "origin", "points_str": "45.496522, -122.867205" }, "geometry": { "type": "Point", "coordinates": [ -122.867205349929975, 45.496521740082237 ] } },
{ "type": "Feature", "properties": { "point_type": "destination", "points_str": "45.484044, -122.716172" }, "geometry": { "type": "Point", "coordinates": [ -122.716171655881567, 45.484044316541969 ] } }
]
}
