{
"type": "FeatureCollection",
"name": "origin_destination_points",
"crs": { "type": "name", "properties": { "name": "urn:ogc:def:crs:OGC:1.3:CRS84" } },
"features": [
{ "type": "Feature", "properties": { "point_type": "origin", "points_str": "45.544406, -122.715228" }, "geometry": { "type": "Point", "coordinates": [ -122.715228435209653, 45.544405826779908 ] } },
{ "type": "Feature", "properties": { "point_type": "destination", "points_str": "45.581793, -122.638258" }, "geometry": { "type": "Point", "coordinates": [ -122.638258434555709, 45.581792893486025 ] } }
]
}
