{
"type": "FeatureCollection",
"name": "origin_destination_points",
"crs": { "type": "name", "properties": { "name": "urn:ogc:def:crs:OGC:1.3:CRS84" } },
"features": [
{ "type": "Feature", "properties": { "point_type": "origin", "points_str": "45.505922, -122.796324" }, "geometry": { "type": "Point", "coordinates": [ -122.796323620265781, 45.505922484326284 ] } },
{ "type": "Feature", "properties": { "point_type": "destination", "points_str": "45.472989, -122.805937" }, "geometry": { "type": "Point", "coordinates": [ -122.805937220561603, 45.47298908247452 ] } }
]
}
