{
"type": "FeatureCollection",
"name": "origin_destination_points",
"crs": { "type": "name", "properties": { "name": "urn:ogc:def:crs:OGC:1.3:CRS84" } },
"features": [
{ "type": "Feature", "properties": { "point_type": "origin", "points_str": "45.39175, -122.754001" }, "geometry": { "type": "Point", "coordinates": [ -122.754001349266829, 45.391750405682366 ] } },
{ "type": "Feature", "properties": { "point_type": "destination", "points_str": "45.489301, -122.792237" }, "geometry": { "type": "Point", "coordinates": [ -122.792236825155356, 45.489300843839914 ] } }
]
}
