{
"type": "FeatureCollection",
"crs": { "type": "name", "properties": { "name": "urn:ogc:def:crs:OGC:1.3:CRS84" } },
"features": [
{ "type": "Feature", "properties": { "point_type": "origin", "points_str": "45.519408, -122.475928" }, "geometry": { "type": "Point", "coordinates": [ -122.475927530956568, 45.519407578144133 ] } },
{ "type": "Feature", "properties": { "point_type": "destination", "points_str": "45.522659, -122.737403" }, "geometry": { "type": "Point", "coordinates": [ -122.737403215949882, 45.522659103094114 ] } }
]
}
