{
"type": "FeatureCollection",
"name": "origin_destination_points",
"crs": { "type": "name", "properties": { "name": "urn:ogc:def:crs:OGC:1.3:CRS84" } },
"features": [
{ "type": "Feature", "properties": { "point_type": "origin", "points_str": "45.475067, -122.665805" }, "geometry": { "type": "Point", "coordinates": [ -122.66580504781038, 45.475066628852744 ] } },
{ "type": "Feature", "properties": { "point_type": "destination", "points_str": "45.570838, -122.702263" }, "geometry": { "type": "Point", "coordinates": [ -122.702263143285705, 45.570837617559782 ] } }
]
}
