{
"type": "FeatureCollection",
"name": "origin_destination_points",
"crs": { "type": "name", "properties": { "name": "urn:ogc:def:crs:OGC:1.3:CRS84" } },
"features": [
{ "type": "Feature", "properties": { "point_type": "origin", "points_str": "45.454756, -122.728421" }, "geometry": { "type": "Point", "coordinates": [ -122.72842082830357, 45.45475638566262 ] } },
{ "type": "Feature", "properties": { "point_type": "destination", "points_str": "45.464533, -122.804197" }, "geometry": { "type": "Point", "coordinates": [ -122.804196836689229, 45.464533083535912 ] } }
]
}
