{
"type": "FeatureCollection",
"name": "origin_destination_points",
"crs": { "type": "name", "properties": { "name": "urn:ogc:def:crs:OGC:1.3:CRS84" } },
"features": [
{ "type": "Feature", "properties": { "point_type": "origin", "points_str": "45.427398, -122.48404" }, "geometry": { "type": "Point", "coordinates": [ -122.484040089730968, 45.427398001015973 ] } },
{ "type": "Feature", "properties": { "point_type": "destination", "points_str": "45.45906, -122.582603" }, "geometry": { "type": "Point", "coordinates": [ -122.582603357529081, 45.459059579360414 ] } }
]
}
