{
"type": "FeatureCollection",
"name": "origin_destination_points",
"crs": { "type": "name", "properties": { "name": "urn:ogc:def:crs:OGC:1.3:CRS84" } },
"features": [
{ "type": "Feature", "properties": { "point_type": "origin", "points_str": "45.430026, -122.498503" }, "geometry": { "type": "Point", "coordinates": [ -122.498502984921274, 45.430025505859149 ] } },
{ "type": "Feature", "properties": { "point_type": "destination", "points_str": "45.427859, -122.519739" }, "geometry": { "type": "Point", "coordinates": [ -122.519738761727595, 45.427859365894534 ] } }
]
}
