{
"type": "FeatureCollection",
"name": "origin_destination_points",
"crs": { "type": "name", "properties": { "name": "urn:ogc:def:crs:OGC:1.3:CRS84" } },
"features": [
{ "type": "Feature", "properties": { "point_type": "origin", "points_str": "45.497006, -122.60319" }, "geometry": { "type": "Point", "coordinates": [ -122.603189967230819, 45.497005931070539 ] } },
{ "type": "Feature", "properties": { "point_type": "destination", "points_str": "45.437568, -122.653186" }, "geometry": { "type": "Point", "coordinates": [ -122.653186258034793, 45.43756764330012 ] } }
]
}
