{
"type": "FeatureCollection",
"name": "origin_destination_points",
"crs": { "type": "name", "properties": { "name": "urn:ogc:def:crs:OGC:1.3:CRS84" } },
"features": [
{ "type": "Feature", "properties": { "point_type": "origin", "points_str": "45.590785, -122.737171" }, "geometry": { "type": "Point", "coordinates": [ -122.737170688194453, 45.590785147561121 ] } },
{ "type": "Feature", "properties": { "point_type": "destination", "points_str": "45.584029, -122.709299" }, "geometry": { "type": "Point", "coordinates": [ -122.709298839000041, 45.584029142056103 ] } }
]
}
