{
"type": "FeatureCollection",
"crs": { "type": "name", "properties": { "name": "urn:ogc:def:crs:OGC:1.3:CRS84" } },
"features": [
{ "type": "Feature", "properties": { "point_type": "origin", "points_str": "45.312975, -122.774054" }, "geometry": { "type": "Point", "coordinates": [ -122.774053915094498, 45.312974744818376 ] } },
{ "type": "Feature", "properties": { "point_type": "destination", "points_str": "45.506674, -122.747715" }, "geometry": { "type": "Point", "coordinates": [ -122.747715439539448, 45.506674372612977 ] } }
]
}
