{
"type": "FeatureCollection",
"name": "origin_destination_points",
"crs": { "type": "name", "properties": { "name": "urn:ogc:def:crs:OGC:1.3:CRS84" } },
"features": [
{ "type": "Feature", "properties": { "point_type": "origin", "points_str": "45.514022, -122.603551" }, "geometry": { "type": "Point", "coordinates": [ -122.60355062723518, 45.514021885057964 ] } },
{ "type": "Feature", "properties": { "point_type": "destination", "points_str": "45.523084, -122.978918" }, "geometry": { "type": "Point", "coordinates": [ -122.978917712508874, 45.523083879942 ] } }
]
}
