{
"type": "FeatureCollection",
"name": "origin_destination_points",
"crs": { "type": "name", "properties": { "name": "urn:ogc:def:crs:OGC:1.3:CRS84" } },
"features": [
{ "type": "Feature", "properties": { "point_type": "origin", "points_str": "45.5229, -122.68396" }, "geometry": { "type": "Point", "coordinates": [ -122.683959790223426, 45.522900200380406 ] } },
{ "type": "Feature", "properties": { "point_type": "destination", "points_str": "45.5389, -122.385026" }, "geometry": { "type": "Point", "coordinates": [ -122.385025824480195, 45.53889984074636 ] } }
]
}
