{
"type": "FeatureCollection",
"name": "origin_destination_points",
"crs": { "type": "name", "properties": { "name": "urn:ogc:def:crs:OGC:1.3:CRS84" } },
"features": [
{ "type": "Feature", "properties": { "point_type": "origin", "points_str": "45.49558, -122.676375" }, "geometry": { "type": "Point", "coordinates": [ -122.676375259416091, 45.495580401909535 ] } },
{ "type": "Feature", "properties": { "point_type": "destination", "points_str": "45.550446, -122.618634" }, "geometry": { "type": "Point", "coordinates": [ -122.618633854030634, 45.550446388275589 ] } }
]
}
