{
"type": "FeatureCollection",
"crs": { "type": "name", "properties": { "name": "urn:ogc:def:crs:OGC:1.3:CRS84" } },
"features": [
{ "type": "Feature", "properties": { "point_type": "origin", "points_str": "45.50255, -122.617437" }, "geometry": { "type": "Point", "coordinates": [ -122.617437194733753, 45.502549576093031 ] } },
{ "type": "Feature", "properties": { "point_type": "destination", "points_str": "45.548814, -122.577691" }, "geometry": { "type": "Point", "coordinates": [ -122.577690947492471, 45.548813799906569 ] } }
]
}
