{
"type": "FeatureCollection",
"crs": { "type": "name", "properties": { "name": "urn:ogc:def:crs:OGC:1.3:CRS84" } },
"features": [
{ "type": "Feature", "properties": { "point_type": "origin", "points_str": "45.53404, -122.418563" }, "geometry": { "type": "Point", "coordinates": [ -122.418563135716752, 45.534039839216021 ] } },
{ "type": "Feature", "properties": { "point_type": "destination", "points_str": "45.507576, -122.636263" }, "geometry": { "type": "Point", "coordinates": [ -122.636263204506164, 45.507576358949905 ] } }
]
}
