{
"type": "FeatureCollection",
"name": "origin_destination_points",
"crs": { "type": "name", "properties": { "name": "urn:ogc:def:crs:OGC:1.3:CRS84" } },
"features": [
{ "type": "Feature", "properties": { "point_type": "origin", "points_str": "45.549895, -122.624477" }, "geometry": { "type": "Point", "coordinates": [ -122.62447690150708, 45.549895109508213 ] } },
{ "type": "Feature", "properties": { "point_type": "destination", "points_str": "45.563113, -122.603883" }, "geometry": { "type": "Point", "coordinates": [ -122.603883448353315, 45.563112668601036 ] } }
]
}
