{
"type": "FeatureCollection",
"crs": { "type": "name", "properties": { "name": "urn:ogc:def:crs:OGC:1.3:CRS84" } },
"features": [
{ "type": "Feature", "properties": { "point_type": "origin", "points_str": "45.603558, -122.75831" }, "geometry": { "type": "Point", "coordinates": [ -122.758310486592336, 45.603558179222816 ] } },
{ "type": "Feature", "properties": { "point_type": "destination", "points_str": "45.486724, -122.719161" }, "geometry": { "type": "Point", "coordinates": [ -122.719160804295569, 45.486723794869526 ] } }
]
}
