{
"type": "FeatureCollection",
"name": "origin_destination_points",
"crs": { "type": "name", "properties": { "name": "urn:ogc:def:crs:OGC:1.3:CRS84" } },
"features": [
{ "type": "Feature", "properties": { "point_type": "origin", "points_str": "45.553993, -122.5803" }, "geometry": { "type": "Point", "coordinates": [ -122.580300305052745, 45.553992755821675 ] } },
{ "type": "Feature", "properties": { "point_type": "destination", "points_str": "45.520011, -122.629473" }, "geometry": { "type": "Point", "coordinates": [ -122.62947323947418, 45.520010875037045 ] } }
]
}
