{
"type": "FeatureCollection",
"crs": { "type": "name", "properties": { "name": "urn:ogc:def:crs:OGC:1.3:CRS84" } },
"features": [
{ "type": "Feature", "properties": { "point_type": "origin", "points_str": "45.520282, -122.479524" }, "geometry": { "type": "Point", "coordinates": [ -122.479523626376462, 45.52028227940152 ] } },
{ "type": "Feature", "properties": { "point_type": "destination", "points_str": "45.603714, -122.788652" }, "geometry": { "type": "Point", "coordinates": [ -122.788652369359809, 45.603714016974948 ] } }
]
}
