{
"type": "FeatureCollection",
"name": "origin_destination_points",
"crs": { "type": "name", "properties": { "name": "urn:ogc:def:crs:OGC:1.3:CRS84" } },
"features": [
{ "type": "Feature", "properties": { "point_type": "origin", "points_str": "45.470575, -122.704907" }, "geometry": { "type": "Point", "coordinates": [ -122.704907315002814, 45.470575294453965 ] } },
{ "type": "Feature", "properties": { "point_type": "destination", "points_str": "45.541737, -122.696663" }, "geometry": { "type": "Point", "coordinates": [ -122.696663016911756, 45.541737336262031 ] } }
]
}
