{
"type": "FeatureCollection",
"crs": { "type": "name", "properties": { "name": "urn:ogc:def:crs:OGC:1.3:CRS84" } },
"features": [
{ "type": "Feature", "properties": { "point_type": "origin", "points_str": "45.495218, -122.838273" }, "geometry": { "type": "Point", "coordinates": [ -122.83827259782062, 45.49521783602048 ] } },
{ "type": "Feature", "properties": { "point_type": "destination", "points_str": "45.474436, -122.597508" }, "geometry": { "type": "Point", "coordinates": [ -122.597507911796228, 45.474436305770524 ] } }
]
}
