{
"type": "FeatureCollection",
"name": "origin_destination_points",
"crs": { "type": "name", "properties": { "name": "urn:ogc:def:crs:OGC:1.3:CRS84" } },
"features": [
{ "type": "Feature", "properties": { "point_type": "origin", "points_str": "45.516843, -122.680985" }, "geometry": { "type": "Point", "coordinates": [ -122.680985138191105, 45.516842669838752 ] } },
{ "type": "Feature", "properties": { "point_type": "destination", "points_str": "45.490683, -122.377857" }, "geometry": { "type": "Point", "coordinates": [ -122.377857378303432, 45.490682601492388 ] } }
]
}
