{
"type": "FeatureCollection",
"crs": { "type": "name", "properties": { "name": "urn:ogc:def:crs:OGC:1.3:CRS84" } },
"features": [
{ "type": "Feature", "properties": { "point_type": "origin", "points_str": "45.420111, -122.575292" }, "geometry": { "type": "Point", "coordinates": [ -122.575292492851773, 45.420111243965344 ] } },
{ "type": "Feature", "properties": { "point_type": "destination", "points_str": "45.344305, -122.655316" }, "geometry": { "type": "Point", "coordinates": [ -122.655316391608778, 45.344305455256311 ] } }
]
}
