{
"type": "FeatureCollection",
"name": "origin_destination_points",
"crs": { "type": "name", "properties": { "name": "urn:ogc:def:crs:OGC:1.3:CRS84" } },
"features": [
{ "type": "Feature", "properties": { "point_type": "origin", "points_str": "45.579284, -122.674263" }, "geometry": { "type": "Point", "coordinates": [ -122.6742628468905, 45.579284272425397 ] } },
{ "type": "Feature", "properties": { "point_type": "destination", "points_str": "45.498234, -122.824923" }, "geometry": { "type": "Point", "coordinates": [ -122.824923486775944, 45.498234158602571 ] } }
]
}
