{
"type": "FeatureCollection",
"crs": { "type": "name", "properties": { "name": "urn:ogc:def:crs:OGC:1.3:CRS84" } },
"features": [
{ "type": "Feature", "properties": { "point_type": "origin", "points_str": "45.529245, -122.563967" }, "geometry": { "type": "Point", "coordinates": [ -122.563967254446354, 45.529244652435672 ] } },
{ "type": "Feature", "properties": { "point_type": "destination", "points_str": "45.322098, -122.343308" }, "geometry": { "type": "Point", "coordinates": [ -122.343308059761497, 45.322098485040208 ] } }
]
}
