{
"type": "FeatureCollection",
"name": "origin_destination_points",
"crs": { "type": "name", "properties": { "name": "urn:ogc:def:crs:OGC:1.3:CRS84" } },
"features": [
{ "type": "Feature", "properties": { "point_type": "origin", "points_str": "45.474557, -122.645767" }, "geometry": { "type": "Point", "coordinates": [ -122.645766728527477, 45.47455720282818 ] } },
{ "type": "Feature", "properties": { "point_type": "destination", "points_str": "45.476732, -122.698236" }, "geometry": { "type": "Point", "coordinates": [ -122.698235683420506, 45.476732070404594 ] } }
]
}
