{
"type": "FeatureCollection",
"crs": { "type": "name", "properties": { "name": "urn:ogc:def:crs:OGC:1.3:CRS84" } },
"features": [
{ "type": "Feature", "properties": { "point_type": "origin", "points_str": "45.49315, -122.625573" }, "geometry": { "type": "Point", "coordinates": [ -122.625573250219617, 45.493150482482989 ] } },
{ "type": "Feature", "properties": { "point_type": "destination", "points_str": "45.610694, -122.685824" }, "geometry": { "type": "Point", "coordinates": [ -122.685824478850577, 45.610694129356204 ] } }
]
}
