{
"type": "FeatureCollection",
"name": "origin_destination_points",
"crs": { "type": "name", "properties": { "name": "urn:ogc:def:crs:OGC:1.3:CRS84" } },
"features": [
{ "type": "Feature", "properties": { "point_type": "origin", "points_str": "45.542935, -122.559013" }, "geometry": { "type": "Point", "coordinates": [ -122.559012855692686, 45.542935348289383 ] } },
{ "type": "Feature", "properties": { "point_type": "destination", "points_str": "45.523426, -122.690908" }, "geometry": { "type": "Point", "coordinates": [ -122.690908062767789, 45.52342571624731 ] } }
]
}
