{
"type": "FeatureCollection",
"name": "origin_destination_points",
"crs": { "type": "name", "properties": { "name": "urn:ogc:def:crs:OGC:1.3:CRS84" } },
"features": [
{ "type": "Feature", "properties": { "point_type": "origin", "points_str": "45.471574, -122.807261" }, "geometry": { "type": "Point", "coordinates": [ -122.807260705248282, 45.471573823502183 ] } },
{ "type": "Feature", "properties": { "point_type": "destination", "points_str": "45.501455, -122.805653" }, "geometry": { "type": "Point", "coordinates": [ -122.805652709949825, 45.501455413813026 ] } }
]
}
