{
"type": "FeatureCollection",
"name": "origin_destination_points",
"crs": { "type": "name", "properties": { "name": "urn:ogc:def:crs:OGC:1.3:CRS84" } },
"features": [
{ "type": "Feature", "properties": { "point_type": "origin", "points_str": "45.494009, -122.585891" }, "geometry": { "type": "Point", "coordinates": [ -122.585891290822843, 45.494008753343813 ] } },
{ "type": "Feature", "properties": { "point_type": "destination", "points_str": "45.480325, -122.56171" }, "geometry": { "type": "Point", "coordinates": [ -122.561709515933757, 45.48032549339986 ] } }
]
}
