{
"type": "FeatureCollection",
"name": "origin_destination_points",
"crs": { "type": "name", "properties": { "name": "urn:ogc:def:crs:OGC:1.3:CRS84" } },
"features": [
{ "type": "Feature", "properties": { "point_type": "origin", "points_str": "45.535918, -122.612424" }, "geometry": { "type": "Point", "coordinates": [ -122.612423576937601, 45.53591833357288 ] } },
{ "type": "Feature", "properties": { "point_type": "destination", "points_str": "45.549891, -122.558386" }, "geometry": { "type": "Point", "coordinates": [ -122.558385655090035, 45.549890768191389 ] } }
]
}
