{
"type": "FeatureCollection",
"crs": { "type": "name", "properties": { "name": "urn:ogc:def:crs:OGC:1.3:CRS84" } },
"features": [
{ "type": "Feature", "properties": { "point_type": "origin", "points_str": "45.509599, -122.973495" }, "geometry": { "type": "Point", "coordinates": [ -122.973495152368628, 45.509599450038422 ] } },
{ "type": "Feature", "properties": { "point_type": "destination", "points_str": "45.523812, -122.512955" }, "geometry": { "type": "Point", "coordinates": [ -122.512954584733421, 45.523811804110473 ] } }
]
}
