{
"type": "FeatureCollection",
"crs": { "type": "name", "properties": { "name": "urn:ogc:def:crs:OGC:1.3:CRS84" } },
"features": [
{ "type": "Feature", "properties": { "point_type": "origin", "points_str": "45.453185, -122.63589" }, "geometry": { "type": "Point", "coordinates": [ -122.635889670914224, 45.453185119150753 ] } },
{ "type": "Feature", "properties": { "point_type": "destination", "points_str": "45.488982, -122.80668" }, "geometry": { "type": "Point", "coordinates": [ -122.806680089338514, 45.488981502976948 ] } }
]
}
