{
"type": "FeatureCollection",
"name": "origin_destination_points",
"crs": { "type": "name", "properties": { "name": "urn:ogc:def:crs:OGC:1.3:CRS84" } },
"features": [
{ "type": "Feature", "properties": { "point_type": "origin", "points_str": "45.524672, -122.62981" }, "geometry": { "type": "Point", "coordinates": [ -122.629809894099452, 45.524671946766787 ] } },
{ "type": "Feature", "properties": { "point_type": "destination", "points_str": "45.453985, -122.596956" }, "geometry": { "type": "Point", "coordinates": [ -122.596955721240846, 45.453984952980854 ] } }
]
}
