{
"type": "FeatureCollection",
"name": "origin_destination_points",
"crs": { "type": "name", "properties": { "name": "urn:ogc:def:crs:OGC:1.3:CRS84" } },
"features": [
{ "type": "Feature", "properties": { "point_type": "origin", "points_str": "45.531463, -122.697096" }, "geometry": { "type": "Point", "coordinates": [ -122.697096337421627, 45.531462796236674 ] } },
{ "type": "Feature", "properties": { "point_type": "destination", "points_str": "45.583171, -122.742027" }, "geometry": { "type": "Point", "coordinates": [ -122.7420272571092, 45.58317126750751 ] } }
]
}
