{
"type": "FeatureCollection",
"crs": { "type": "name", "properties": { "name": "urn:ogc:def:crs:OGC:1.3:CRS84" } },
"features": [
{ "type": "Feature", "properties": { "point_type": "origin", "points_str": "45.530969, -122.849454" }, "geometry": { "type": "Point", "coordinates": [ -122.849454087185848, 45.530968898492844 ] } },
{ "type": "Feature", "properties": { "point_type": "destination", "points_str": "45.534537, -122.580918" }, "geometry": { "type": "Point", "coordinates": [ -122.580917573303836, 45.534536708696756 ] } }
]
}
