{
"type": "FeatureCollection",
"name": "origin_destination_points",
"crs": { "type": "name", "properties": { "name": "urn:ogc:def:crs:OGC:1.3:CRS84" } },
"features": [
{ "type": "Feature", "properties": { "point_type": "origin", "points_str": "45.46249, -122.692782" }, "geometry": { "type": "Point", "coordinates": [ -122.692782007656874, 45.462490088920113 ] } },
{ "type": "Feature", "properties": { "point_type": "destination", "points_str": "45.584252, -122.743893" }, "geometry": { "type": "Point", "coordinates": [ -122.743893288917661, 45.584251513100142 ] } }
]
}
