{
"type": "FeatureCollection",
"name": "origin_destination_points",
"crs": { "type": "name", "properties": { "name": "urn:ogc:def:crs:OGC:1.3:CRS84" } },
"features": [
{ "type": "Feature", "properties": { "point_type": "origin", "points_str": "45.51546, -122.736318" }, "geometry": { "type": "Point", "coordinates": [ -122.736318423770413, 45.515460061683783 ] } },
{ "type": "Feature", "properties": { "point_type": "destination", "points_str": "45.545262, -122.662871" }, "geometry": { "type": "Point", "coordinates": [ -122.662870544153037, 45.545262172009195 ] } }
]
}
