{
"type": "FeatureCollection",
"crs": { "type": "name", "properties": { "name": "urn:ogc:def:crs:OGC:1.3:CRS84" } },
"features": [
{ "type": "Feature", "properties": { "point_type": "origin", "points_str": "45.391988, -122.477605" }, "geometry": { "type": "Point", "coordinates": [ -122.477605239877491, 45.39198814778419 ] } },
{ "type": "Feature", "properties": { "point_type": "destination", "points_str": "45.444012, -122.578091" }, "geometry": { "type": "Point", "coordinates": [ -122.578090947716603, 45.444011707407455 ] } }
]
}
