{
"type": "FeatureCollection",
"crs": { "type": "name", "properties": { "name": "urn:ogc:def:crs:OGC:1.3:CRS84" } },
"features": [
{ "type": "Feature", "properties": { "point_type": "origin", "points_str": "45.529841, -122.950285" }, "geometry": { "type": "Point", "coordinates": [ -122.950284600518174, 45.529841044836374 ] } },
{ "type": "Feature", "properties": { "point_type": "destination", "points_str": "45.53258, -122.916432" }, "geometry": { "type": "Point", "coordinates": [ -122.916431989435878, 45.53257996685312 ] } }
]
}
