{
"type": "FeatureCollection",
"name": "origin_destination_points",
"crs": { "type": "name", "properties": { "name": "urn:ogc:def:crs:OGC:1.3:CRS84" } },
"features": [
{ "type": "Feature", "properties": { "point_type": "origin", "points_str": "45.53842, -122.585896" }, "geometry": { "type": "Point", "coordinates": [ -122.585895822815786, 45.538419790399701 ] } },
{ "type": "Feature", "properties": { "point_type": "destination", "points_str": "45.488512, -122.669134" }, "geometry": { "type": "Point", "coordinates": [ -122.669134215127727, 45.488511765751731 ] } }
]
}
