{
"type": "FeatureCollection",
"name": "origin_destination_points",
"crs": { "type": "name", "properties": { "name": "urn:ogc:def:crs:OGC:1.3:CRS84" } },
"features": [
{ "type": "Feature", "properties": { "point_type": "origin", "points_str": "45.500742, -122.54285" }, "geometry": { "type": "Point", "coordinates": [ -122.542849690293906, 45.500741889508362 ] } },
{ "type": "Feature", "properties": { "point_type": "destination", "points_str": "45.523204, -122.676795" }, "geometry": { "type": "Point", "coordinates": [ -122.67679462004142, 45.523204232406542 ] } }
]
}
