{
"type": "FeatureCollection",
"name": "origin_destination_points",
"crs": { "type": "name", "properties": { "name": "urn:ogc:def:crs:OGC:1.3:CRS84" } },
"features": [
{ "type": "Feature", "properties": { "point_type": "origin", "points_str": "45.443226, -122.631836" }, "geometry": { "type": "Point", "coordinates": [ -122.631835836253629, 45.443225832772889 ] } },
{ "type": "Feature", "properties": { "point_type": "destination", "points_str": "45.486282, -122.648386" }, "geometry": { "type": "Point", "coordinates": [ -122.648385682046623, 45.486282365717322 ] } }
]
}
