{
"type": "FeatureCollection",
"crs": { "type": "name", "properties": { "name": "urn:ogc:def:crs:OGC:1.3:CRS84" } },
"features": [
{ "type": "Feature", "properties": { "point_type": "origin", "points_str": "45.580596, -122.557893" }, "geometry": { "type": "Point", "coordinates": [ -122.557892725710389, 45.58059612314883 ] } },
{ "type": "Feature", "properties": { "point_type": "destination", "points_str": "45.534633, -122.499412" }, "geometry": { "type": "Point", "coordinates": [ -122.499412373929516, 45.534633051760494 ] } }
]
}
