{
"type": "FeatureCollection",
"name": "origin_destination_points",
"crs": { "type": "name", "properties": { "name": "urn:ogc:def:crs:OGC:1.3:CRS84" } },
"features": [
{ "type": "Feature", "properties": { "point_type": "origin", "points_str": "45.466044, -122.568211" }, "geometry": { "type": "Point", "coordinates": [ -122.568210820520903, 45.466043700156213 ] } },
{ "type": "Feature", "properties": { "point_type": "destination", "points_str": "45.448826, -122.621873" }, "geometry": { "type": "Point", "coordinates": [ -122.621872724035597, 45.448826055610631 ] } }
]
}
