{
"type": "FeatureCollection",
"crs": { "type": "name", "properties": { "name": "urn:ogc:def:crs:OGC:1.3:CRS84" } },
"features": [
{ "type": "Feature", "properties": { "point_type": "origin", "points_str": "45.559476, -122.562886" }, "geometry": { "type": "Point", "coordinates": [ -122.562885978045671, 45.559476364919831 ] } },
{ "type": "Feature", "properties": { "point_type": "destination", "points_str": "45.529643, -122.536777" }, "geometry": { "type": "Point", "coordinates": [ -122.536776533678875, 45.529643433354281 ] } }
]
}
