{
"type": "FeatureCollection",
"name": "origin_destination_points",
"crs": { "type": "name", "properties": { "name": "urn:ogc:def:crs:OGC:1.3:CRS84" } },
"features": [
{ "type": "Feature", "properties": { "point_type": "origin", "points_str": "45.48885, -122.760456" }, "geometry": { "type": "Point", "coordinates": [ -122.760456195037506, 45.488849515005263 ] } },
{ "type": "Feature", "properties": { "point_type": "destination", "points_str": "45.497136, -122.452234" }, "geometry": { "type": "Point", "coordinates": [ -122.452233524887944, 45.497135722817852 ] } }
]
}
