{
"type": "FeatureCollection",
"name": "origin_destination_points",
"crs": { "type": "name", "properties": { "name": "urn:ogc:def:crs:OGC:1.3:CRS84" } },
"features": [
{ "type": "Feature", "properties": { "point_type": "origin", "points_str": "45.50092, -122.641016" }, "geometry": { "type": "Point", "coordinates": [ -122.641016448270889, 45.500919988683989 ] } },
{ "type": "Feature", "properties": { "point_type": "destination", "points_str": "45.530756, -122.701132" }, "geometry": { "type": "Point", "coordinates": [ -122.701131985721986, 45.530755622827698 ] } }
]
}
