{
"type": "FeatureCollection",
"name": "origin_destination_points",
"crs": { "type": "name", "properties": { "name": "urn:ogc:def:crs:OGC:1.3:CRS84" } },
"features": [
{ "type": "Feature", "properties": { "point_type": "origin", "points_str": "45.533138, -122.663957" }, "geometry": { "type": "Point", "coordinates": [ -122.663957152820814, 45.533138418588898 ] } },
{ "type": "Feature", "properties": { "point_type": "destination", "points_str": "45.491062, -122.713328" }, "geometry": { "type": "Point", "coordinates": [ -122.713327963828249, 45.491062005515644 ] } }
]
}
