{
"type": "FeatureCollection",
"name": "origin_destination_points",
"crs": { "type": "name", "properties": { "name": "urn:ogc:def:crs:OGC:1.3:CRS84" } },
"features": [
{ "type": "Feature", "properties": { "point_type": "origin", "points_str": "45.497342, -122.805007" }, "geometry": { "type": "Point", "coordinates": [ -122.805006536891739, 45.49734213709349 ] } },
{ "type": "Feature", "properties": { "point_type": "destination", "points_str": "45.513161, -122.538414" }, "geometry": { "type": "Point", "coordinates": [ -122.538413740563371, 45.513160539393979 ] } }
]
}
