{
"type": "FeatureCollection",
"crs": { "type": "name", "properties": { "name": "urn:ogc:def:crs:OGC:1.3:CRS84" } },
"features": [
{ "type": "Feature", "properties": { "point_type": "origin", "points_str": "45.536903, -122.621052" }, "geometry": { "type": "Point", "coordinates": [ -122.621051918919022, 45.536903174621358 ] } },
{ "type": "Feature", "properties": { "point_type": "destination", "points_str": "45.605423, -122.789983" }, "geometry": { "type": "Point", "coordinates": [ -122.789983188386472, 45.605423332880818 ] } }
]
}
