{
"type": "FeatureCollection",
"crs": { "type": "name", "properties": { "name": "urn:ogc:def:crs:OGC:1.3:CRS84" } },
"features": [
{ "type": "Feature", "properties": { "point_type": "origin", "points_str": "45.421448, -122.78219" }, "geometry": { "type": "Point", "coordinates": [ -122.782189641693236, 45.421448024306976 ] } },
{ "type": "Feature", "properties": { "point_type": "destination", "points_str": "45.492851, -122.877253" }, "geometry": { "type": "Point", "coordinates": [ -122.877252621485084, 45.492850658995373 ] } }
]
}
