{
"type": "FeatureCollection",
"crs": { "type": "name", "properties": { "name": "urn:ogc:def:crs:OGC:1.3:CRS84" } },
"features": [
{ "type": "Feature", "properties": { "point_type": "origin", "points_str": "45.491911, -122.651517" }, "geometry": { "type": "Point", "coordinates": [ -122.651516954898995, 45.491910566967633 ] } },
{ "type": "Feature", "properties": { "point_type": "destination", "points_str": "45.523653, -122.632084" }, "geometry": { "type": "Point", "coordinates": [ -122.632083604549095, 45.523653118929055 ] } }
]
}
