{
"type": "FeatureCollection",
"name": "origin_destination_points",
"crs": { "type": "name", "properties": { "name": "urn:ogc:def:crs:OGC:1.3:CRS84" } },
"features": [
{ "type": "Feature", "properties": { "point_type": "origin", "points_str": "45.540114, -122.617671" }, "geometry": { "type": "Point", "coordinates": [ -122.617671125609832, 45.540113738849676 ] } },
{ "type": "Feature", "properties": { "point_type": "destination", "points_str": "45.554471, -122.486458" }, "geometry": { "type": "Point", "coordinates": [ -122.486458346372274, 45.554470901394005 ] } }
]
}
