{
"type": "FeatureCollection",
"name": "origin_destination_points",
"crs": { "type": "name", "properties": { "name": "urn:ogc:def:crs:OGC:1.3:CRS84" } },
"features": [
{ "type": "Feature", "properties": { "point_type": "origin", "points_str": "45.510573, -122.478405" }, "geometry": { "type": "Point", "coordinates": [ -122.478405226892718, 45.510573254379175 ] } },
{ "type": "Feature", "properties": { "point_type": "destination", "points_str": "45.510449, -122.848504" }, "geometry": { "type": "Point", "coordinates": [ -122.84850397430435, 45.510448818120921 ] } }
]
}
