{
"type": "FeatureCollection",
"name": "origin_destination_points",
"crs": { "type": "name", "properties": { "name": "urn:ogc:def:crs:OGC:1.3:CRS84" } },
"features": [
{ "type": "Feature", "properties": { "point_type": "origin", "points_str": "45.485037, -122.80671" }, "geometry": { "type": "Point", "coordinates": [ -122.806710070394132, 45.485037322797119 ] } },
{ "type": "Feature", "properties": { "point_type": "destination", "points_str": "45.406708, -122.798682" }, "geometry": { "type": "Point", "coordinates": [ -122.798681822603953, 45.406708253151038 ] } }
]
}
