{
"type": "FeatureCollection",
"name": "origin_destination_points",
"crs": { "type": "name", "properties": { "name": "urn:ogc:def:crs:OGC:1.3:CRS84" } },
"features": [
{ "type": "Feature", "properties": { "point_type": "origin", "points_str": "45.536715, -122.966922" }, "geometry": { "type": "Point", "coordinates": [ -122.966922310352146, 45.536715287650274 ] } },
{ "type": "Feature", "properties": { "point_type": "destination", "points_str": "45.527892, -122.652554" }, "geometry": { "type": "Point", "coordinates": [ -122.65255415243449, 45.527891805408679 ] } }
]
}
