{
"type": "FeatureCollection",
"name": "origin_destination_points",
"crs": { "type": "name", "properties": { "name": "urn:ogc:def:crs:OGC:1.3:CRS84" } },
"features": [
{ "type": "Feature", "properties": { "point_type": "origin", "points_str": "45.495305, -122.490294" }, "geometry": { "type": "Point", "coordinates": [ -122.490294000190403, 45.495304573902622 ] } },
{ "type": "Feature", "properties": { "point_type": "destination", "points_str": "45.499899, -122.451449" }, "geometry": { "type": "Point", "coordinates": [ -122.451449013794488, 45.49989913335029 ] } }
]
}
