{
"type": "FeatureCollection",
"name": "origin_destination_points",
"crs": { "type": "name", "properties": { "name": "urn:ogc:def:crs:OGC:1.3:CRS84" } },
"features": [
{ "type": "Feature", "properties": { "point_type": "origin", "points_str": "45.564599, -122.704982" }, "geometry": { "type": "Point", "coordinates": [ -122.704981999313063, 45.564599133037575 ] } },
{ "type": "Feature", "properties": { "point_type": "destination", "points_str": "45.469275, -122.711718" }, "geometry": { "type": "Point", "coordinates": [ -122.711718354195582, 45.469275303833825 ] } }
]
}
