{
"type": "FeatureCollection",
"name": "origin_destination_points",
"crs": { "type": "name", "properties": { "name": "urn:ogc:def:crs:OGC:1.3:CRS84" } },
"features": [
{ "type": "Feature", "properties": { "point_type": "origin", "points_str": "45.438897, -122.745021" }, "geometry": { "type": "Point", "coordinates": [ -122.745020887918272, 45.438897089914605 ] } },
{ "type": "Feature", "properties": { "point_type": "destination", "points_str": "45.465534, -122.724504" }, "geometry": { "type": "Point", "coordinates": [ -122.724503509709066, 45.465533575112296 ] } }
]
}
