{
"type": "FeatureCollection",
"name": "origin_destination_points",
"crs": { "type": "name", "properties": { "name": "urn:ogc:def:crs:OGC:1.3:CRS84" } },
"features": [
{ "type": "Feature", "properties": { "point_type": "origin", "points_str": "45.530195, -122.519644" }, "geometry": { "type": "Point", "coordinates": [ -122.519644308922551, 45.530195377224892 ] } },
{ "type": "Feature", "properties": { "point_type": "destination", "points_str": "45.55025, -122.406492" }, "geometry": { "type": "Point", "coordinates": [ -122.406492279792388, 45.550249518838399 ] } }
]
}
