{
"type": "FeatureCollection",
"name": "origin_destination_points",
"crs": { "type": "name", "properties": { "name": "urn:ogc:def:crs:OGC:1.3:CRS84" } },
"features": [
{ "type": "Feature", "properties": { "point_type": "origin", "points_str": "45.485203, -122.588274" }, "geometry": { "type": "Point", "coordinates": [ -122.588273609688343, 45.485203301223045 ] } },
{ "type": "Feature", "properties": { "point_type": "destination", "points_str": "45.565061, -122.636903" }, "geometry": { "type": "Point", "coordinates": [ -122.636903488877849, 45.565060772557061 ] } }
]
}
