{
"type": "FeatureCollection",
"crs": { "type": "name", "properties": { "name": "urn:ogc:def:crs:OGC:1.3:CRS84" } },
"features": [
{ "type": "Feature", "properties": { "point_type": "origin", "points_str": "45.455016, -122.624503" }, "geometry": { "type": "Point", "coordinates": [ -122.624503356023254, 45.455016283694263 ] } },
{ "type": "Feature", "properties": { "point_type": "destination", "points_str": "45.552429, -122.600423" }, "geometry": { "type": "Point", "coordinates": [ -122.600423209260853, 45.552429240511259 ] } }
]
}
