{
"type": "FeatureCollection",
"name": "origin_destination_points",
"crs": { "type": "name", "properties": { "name": "urn:ogc:def:crs:OGC:1.3:CRS84" } },
"features": [
{ "type": "Feature", "properties": { "point_type": "origin", "points_str": "45.520766, -122.663605" }, "geometry": { "type": "Point", "coordinates": [ -122.663604547543059, 45.520765554004946 ] } },
{ "type": "Feature", "properties": { "point_type": "destination", "points_str": "45.542377, -122.534778" }, "geometry": { "type": "Point", "coordinates": [ -122.534777873868364, 45.542376594515133 ] } }
]
}
