{
"type": "FeatureCollection",
"crs": { "type": "name", "properties": { "name": "urn:ogc:def:crs:OGC:1.3:CRS84" } },
"features": [
{ "type": "Feature", "properties": { "point_type": "origin", "points_str": "45.48455, -122.544447" }, "geometry": { "type": "Point", "coordinates": [ -122.544446959826303, 45.48455025281276 ] } },
{ "type": "Feature", "properties": { "point_type": "destination", "points_str": "45.520759, -122.890564" }, "geometry": { "type": "Point", "coordinates": [ -122.890563884110335, 45.520758905281056 ] } }
]
}
