{
"type": "FeatureCollection",
"crs": { "type": "name", "properties": { "name": "urn:ogc:def:crs:OGC:1.3:CRS84" } },
"features": [
{ "type": "Feature", "properties": { "point_type": "origin", "points_str": "45.541197, -122.70291" }, "geometry": { "type": "Point", "coordinates": [ -122.702909615684987, 45.541196853250426 ] } },
{ "type": "Feature", "properties": { "point_type": "destination", "points_str": "45.406747, -122.745683" }, "geometry": { "type": "Point", "coordinates": [ -122.745682899233969, 45.406747140432692 ] } }
]
}
