{
"type": "FeatureCollection",
"crs": { "type": "name", "properties": { "name": "urn:ogc:def:crs:OGC:1.3:CRS84" } },
"features": [
{ "type": "Feature", "properties": { "point_type": "origin", "points_str": "45.530163, -122.625766" }, "geometry": { "type": "Point", "coordinates": [ -122.625765943240623, 45.530162878676997 ] } },
{ "type": "Feature", "properties": { "point_type": "destination", "points_str": "45.544869, -122.454763" }, "geometry": { "type": "Point", "coordinates": [ -122.454762871836948, 45.544869030831698 ] } }
]
}
