{
"type": "FeatureCollection",
"name": "origin_destination_points",
"crs": { "type": "name", "properties": { "name": "urn:ogc:def:crs:OGC:1.3:CRS84" } },
"features": [
{ "type": "Feature", "properties": { "point_type": "origin", "points_str": "45.359577, -122.842165" }, "geometry": { "type": "Point", "coordinates": [ -122.842165026027658, 45.359577343680243 ] } },
{ "type": "Feature", "properties": { "point_type": "destination", "points_str": "45.457936, -122.796279" }, "geometry": { "type": "Point", "coordinates": [ -122.796279341882041, 45.457935664498933 ] } }
]
}
