{
"type": "FeatureCollection",
"name": "origin_destination_points",
"crs": { "type": "name", "properties": { "name": "urn:ogc:def:crs:OGC:1.3:CRS84" } },
"features": [
{ "type": "Feature", "properties": { "point_type": "origin", "points_str": "45.553944, -122.483561" }, "geometry": { "type": "Point", "coordinates": [ -122.483561353291122, 45.553944290088893 ] } },
{ "type": "Feature", "properties": { "point_type": "destination", "points_str": "45.534503, -122.593994" }, "geometry": { "type": "Point", "coordinates": [ -122.593994273620069, 45.534502890177102 ] } }
]
}
