{
"type": "FeatureCollection",
"name": "origin_destination_points",
"crs": { "type": "name", "properties": { "name": "urn:ogc:def:crs:OGC:1.3:CRS84" } },
"features": [
{ "type": "Feature", "properties": { "point_type": "origin", "points_str": "45.52528, -122.986802" }, "geometry": { "type": "Point", "coordinates": [ -122.986802286113402, 45.525280315450743 ] } },
{ "type": "Feature", "properties": { "point_type": "destination", "points_str": "45.476696, -122.591961" }, "geometry": { "type": "Point", "coordinates": [ -122.591960584474251, 45.476695517122486 ] } }
]
}
