{
"type": "FeatureCollection",
"crs": { "type": "name", "properties": { "name": "urn:ogc:def:crs:OGC:1.3:CRS84" } },
"features": [
{ "type": "Feature", "properties": { "point_type": "origin", "points_str": "45.569088, -122.72203" }, "geometry": { "type": "Point", "coordinates": [ -122.722029515120838, 45.569087676759814 ] } },
{ "type": "Feature", "properties": { "point_type": "destination", "points_str": "45.609379, -122.676715" }, "geometry": { "type": "Point", "coordinates": [ -122.6767148831469, 45.609378532263243 ] } }
]
}
