{
"type": "FeatureCollection",
"name": "origin_destination_points",
"crs": { "type": "name", "properties": { "name": "urn:ogc:def:crs:OGC:1.3:CRS84" } },
"features": [
{ "type": "Feature", "properties": { "point_type": "origin", "points_str": "45.413189, -122.670703" }, "geometry": { "type": "Point", "coordinates": [ -122.670702614701909, 45.413189393391356 ] } },
{ "type": "Feature", "properties": { "point_type": "destination", "points_str": "45.477846, -122.693333" }, "geometry": { "type": "Point", "coordinates": [ -122.693333419273486, 45.477845633078324 ] } }
]
}
