{
"type": "FeatureCollection",
"name": "origin_destination_points",
"crs": { "type": "name", "properties": { "name": "urn:ogc:def:crs:OGC:1.3:CRS84" } },
"features": [
{ "type": "Feature", "properties": { "point_type": "origin", "points_str": "45.520527, -123.05655" }, "geometry": { "type": "Point", "coordinates": [ -123.056550283258929, 45.520527220151642 ] } },
{ "type": "Feature", "properties": { "point_type": "destination", "points_str": "45.405502, -122.756507" }, "geometry": { "type": "Point", "coordinates": [ -122.756506867506133, 45.405501782618309 ] } }
]
}
