{
"type": "FeatureCollection",
"crs": { "type": "name", "properties": { "name": "urn:ogc:def:crs:OGC:1.3:CRS84" } },
"features": [
{ "type": "Feature", "properties": { "point_type": "origin", "points_str": "45.523938, -123.021949" }, "geometry": { "type": "Point", "coordinates": [ -123.02194884209834, 45.52393826570529 ] } },
{ "type": "Feature", "properties": { "point_type": "destination", "points_str": "45.512127, -122.494345" }, "geometry": { "type": "Point", "coordinates": [ -122.494345182978122, 45.51212727487227 ] } }
]
}
