{
"type": "FeatureCollection",
"name": "origin_destination_points",
"crs": { "type": "name", "properties": { "name": "urn:ogc:def:crs:OGC:1.3:CRS84" } },
"features": [
{ "type": "Feature", "properties": { "point_type": "origin", "points_str": "45.460717, -122.619174" }, "geometry": { "type": "Point", "coordinates": [ -122.619173636946627, 45.460717288252148 ] } },
{ "type": "Feature", "properties": { "point_type": "destination", "points_str": "45.500544, -122.617635" }, "geometry": { "type": "Point", "coordinates": [ -122.617635029633348, 45.500544457567997 ] } }
]
}
