{
"type": "FeatureCollection",
"name": "origin_destination_points",
"crs": { "type": "name", "properties": { "name": "urn:ogc:def:crs:OGC:1.3:CRS84" } },
"features": [
{ "type": "Feature", "properties": { "point_type": "origin", "points_str": "45.414445, -122.760402" }, "geometry": { "type": "Point", "coordinates": [ -122.760401625437609, 45.414445227518819 ] } },
{ "type": "Feature", "properties": { "point_type": "destination", "points_str": "45.520602, -122.691228" }, "geometry": { "type": "Point", "coordinates": [ -122.691227929626734, 45.520602312166375 ] } }
]
}
