{
"type": "FeatureCollection",
"crs": { "type": "name", "properties": { "name": "urn:ogc:def:crs:OGC:1.3:CRS84" } },
"features": [
{ "type": "Feature", "properties": { "point_type": "origin", "points_str": "45.501593, -122.393567" }, "geometry": { "type": "Point", "coordinates": [ -122.393566600311345, 45.50159319870059 ] } },
{ "type": "Feature", "properties": { "point_type": "destination", "points_str": "45.405428, -122.680611" }, "geometry": { "type": "Point", "coordinates": [ -122.680610974297252, 45.405427599979447 ] } }
]
}
