{
"type": "FeatureCollection",
"crs": { "type": "name", "properties": { "name": "urn:ogc:def:crs:OGC:1.3:CRS84" } },
"features": [
{ "type": "Feature", "properties": { "point_type": "origin", "points_str": "45.465222, -122.69848" }, "geometry": { "type": "Point", "coordinates": [ -122.69847965441555, 45.465222087328222 ] } },
{ "type": "Feature", "properties": { "point_type": "destination", "points_str": "45.454562, -122.728372" }, "geometry": { "type": "Point", "coordinates": [ -122.728372123237534, 45.454561570372924 ] } }
]
}
