{
"type": "FeatureCollection",
"name": "origin_destination_points",
"crs": { "type": "name", "properties": { "name": "urn:ogc:def:crs:OGC:1.3:CRS84" } },
"features": [
{ "type": "Feature", "properties": { "point_type": "origin", "points_str": "45.418621, -122.549082" }, "geometry": { "type": "Point", "coordinates": [ -122.549082084078165, 45.418620501039754 ] } },
{ "type": "Feature", "properties": { "point_type": "destination", "points_str": "45.387254, -122.440691" }, "geometry": { "type": "Point", "coordinates": [ -122.440691471538599, 45.387254361262691 ] } }
]
}
