{
"type": "FeatureCollection",
"name": "origin_destination_points",
"crs": { "type": "name", "properties": { "name": "urn:ogc:def:crs:OGC:1.3:CRS84" } },
"features": [
{ "type": "Feature", "properties": { "point_type": "origin", "points_str": "45.519672, -122.410191" }, "geometry": { "type": "Point", "coordinates": [ -122.410191170981008, 45.519672471709804 ] } },
{ "type": "Feature", "properties": { "point_type": "destination", "points_str": "45.520959, -122.523082" }, "geometry": { "type": "Point", "coordinates": [ -122.523082113673894, 45.520958772103505 ] } }
]
}
