{
"type": "FeatureCollection",
"name": "origin_destination_points",
"crs": { "type": "name", "properties": { "name": "urn:ogc:def:crs:OGC:1.3:CRS84" } },
"features": [
{ "type": "Feature", "properties": { "point_type": "origin", "points_str": "45.520765, -122.548419" }, "geometry": { "type": "Point", "coordinates": [ -122.548419008594749, 45.520764937315946 ] } },
{ "type": "Feature", "properties": { "point_type": "destination", "points_str": "45.566043, -122.656265" }, "geometry": { "type": "Point", "coordinates": [ -122.656264690698094, 45.566042674513525 ] } }
]
}
