{
"type": "FeatureCollection",
"name": "origin_destination_points",
"crs": { "type": "name", "properties": { "name": "urn:ogc:def:crs:OGC:1.3:CRS84" } },
"features": [
{ "type": "Feature", "properties": { "point_type": "origin", "points_str": "45.569514, -122.645273" }, "geometry": { "type": "Point", "coordinates": [ -122.645273108660135, 45.569514106602554 ] } },
{ "type": "Feature", "properties": { "point_type": "destination", "points_str": "45.531984, -122.462095" }, "geometry": { "type": "Point", "coordinates": [ -122.462094874028466, 45.531983577237959 ] } }
]
}
