{
"type": "FeatureCollection",
"crs": { "type": "name", "properties": { "name": "urn:ogc:def:crs:OGC:1.3:CRS84" } },
"features": [
{ "type": "Feature", "properties": { "point_type": "origin", "points_str": "45.451573, -122.722982" }, "geometry": { "type": "Point", "coordinates": [ -122.722982207895001, 45.45157263377574 ] } },
{ "type": "Feature", "properties": { "point_type": "destination", "points_str": "45.561863, -122.560224" }, "geometry": { "type": "Point", "coordinates": [ -122.560223642857537, 45.561862598094862 ] } }
]
}
