{
"type": "FeatureCollection",
"crs": { "type": "name", "properties": { "name": "urn:ogc:def:crs:OGC:1.3:CRS84" } },
"features": [
{ "type": "Feature", "properties": { "point_type": "origin", "points_str": "45.443246, -122.622135" }, "geometry": { "type": "Point", "coordinates": [ -122.622134779377035, 45.443245768729938 ] } },
{ "type": "Feature", "properties": { "point_type": "destination", "points_str": "45.459528, -122.592465" }, "geometry": { "type": "Point", "coordinates": [ -122.5924648341433, 45.459527694200645 ] } }
]
}
