{
"type": "FeatureCollection",
"crs": { "type": "name", "properties": { "name": "urn:ogc:def:crs:OGC:1.3:CRS84" } },
"features": [
{ "type": "Feature", "properties": { "point_type": "origin", "points_str": "45.516091, -122.945891" }, "geometry": { "type": "Point", "coordinates": [ -122.94589098359566, 45.51609076800046 ] } },
{ "type": "Feature", "properties": { "point_type": "destination", "points_str": "45.588305, -122.700456" }, "geometry": { "type": "Point", "coordinates": [ -122.700456315138979, 45.588305413401301 ] } }
]
}
