{
"type": "FeatureCollection",
"name": "origin_destination_points",
"crs": { "type": "name", "properties": { "name": "urn:ogc:def:crs:OGC:1.3:CRS84" } },
"features": [
{ "type": "Feature", "properties": { "point_type": "origin", "points_str": "45.456183, -122.741086" }, "geometry": { "type": "Point", "coordinates": [ -122.74108618333554, 45.456183109036552 ] } },
{ "type": "Feature", "properties": { "point_type": "destination", "points_str": "45.446733, -122.758817" }, "geometry": { "type": "Point", "coordinates": [ -122.758816590470758, 45.44673331823239 ] } }
]
}
