{
"type": "FeatureCollection",
"name": "origin_destination_points",
"crs": { "type": "name", "properties": { "name": "urn:ogc:def:crs:OGC:1.3:CRS84" } },
"features": [
{ "type": "Feature", "properties": { "point_type": "origin", "points_str": "45.581712, -122.668592" }, "geometry": { "type": "Point", "coordinates": [ -122.668592244789764, 45.58171212785448 ] } },
{ "type": "Feature", "properties": { "point_type": "destination", "points_str": "45.500052, -122.573804" }, "geometry": { "type": "Point", "coordinates": [ -122.57380417523288, 45.500052283799285 ] } }
]
}
