{
"type": "FeatureCollection",
"name": "origin_destination_points",
"crs": { "type": "name", "properties": { "name": "urn:ogc:def:crs:OGC:1.3:CRS84" } },
"features": [
{ "type": "Feature", "properties": { "point_type": "origin", "points_str": "45.481937, -122.806604" }, "geometry": { "type": "Point", "coordinates": [ -122.806603669807046, 45.481936948517721 ] } },
{ "type": "Feature", "properties": { "point_type": "destination", "points_str": "45.469324, -122.785565" }, "geometry": { "type": "Point", "coordinates": [ -122.785564560674658, 45.46932363321136 ] } }
]
}
