{
"type": "FeatureCollection",
"name": "origin_destination_points",
"crs": { "type": "name", "properties": { "name": "urn:ogc:def:crs:OGC:1.3:CRS84" } },
"features": [
{ "type": "Feature", "properties": { "point_type": "origin", "points_str": "45.527358, -122.653155" }, "geometry": { "type": "Point", "coordinates": [ -122.653155180448479, 45.527358353124612 ] } },
{ "type": "Feature", "properties": { "point_type": "destination", "points_str": "45.589032, -122.631518" }, "geometry": { "type": "Point", "coordinates": [ -122.631517922532169, 45.589032148917518 ] } }
]
}
