{
"type": "FeatureCollection",
"name": "origin_destination_points",
"crs": { "type": "name", "properties": { "name": "urn:ogc:def:crs:OGC:1.3:CRS84" } },
"features": [
{ "type": "Feature", "properties": { "point_type": "origin", "points_str": "45.518018, -123.114758" }, "geometry": { "type": "Point", "coordinates": [ -123.11475774730738, 45.518018001304512 ] } },
{ "type": "Feature", "properties": { "point_type": "destination", "points_str": "45.51096, -122.781214" }, "geometry": { "type": "Point", "coordinates": [ -122.781214459430473, 45.510960411970963 ] } }
]
}
