{
"type": "FeatureCollection",
"crs": { "type": "name", "properties": { "name": "urn:ogc:def:crs:OGC:1.3:CRS84" } },
"features": [
{ "type": "Feature", "properties": { "point_type": "origin", "points_str": "45.600636, -122.653491" }, "geometry": { "type": "Point", "coordinates": [ -122.65349110474169, 45.600635684448029 ] } },
{ "type": "Feature", "properties": { "point_type": "destination", "points_str": "45.487615, -122.722303" }, "geometry": { "type": "Point", "coordinates": [ -122.722302610688018, 45.487614953435056 ] } }
]
}
