{
"type": "FeatureCollection",
"name": "origin_destination_points",
"crs": { "type": "name", "properties": { "name": "urn:ogc:def:crs:OGC:1.3:CRS84" } },
"features": [
{ "type": "Feature", "properties": { "point_type": "origin", "points_str": "45.512062, -122.401587" }, "geometry": { "type": "Point", "coordinates": [ -122.401587252341756, 45.512061840613619 ] } },
{ "type": "Feature", "properties": { "point_type": "destination", "points_str": "45.532501, -122.39436" }, "geometry": { "type": "Point", "coordinates": [ -122.394360035909713, 45.532500852722272 ] } }
]
}
