{
"type": "FeatureCollection",
"crs": { "type": "name", "properties": { "name": "urn:ogc:def:crs:OGC:1.3:CRS84" } },
"features": [
{ "type": "Feature", "properties": { "point_type": "origin", "points_str": "45.537271, -122.607629" }, "geometry": { "type": "Point", "coordinates": [ -122.607629052494389, 45.537271222409018 ] } },
{ "type": "Feature", "properties": { "point_type": "destination", "points_str": "45.390027, -122.40088" }, "geometry": { "type": "Point", "coordinates": [ -122.400879528928826, 45.39002739714536 ] } }
]
}
