{
"type": "FeatureCollection",
"name": "origin_destination_points",
"crs": { "type": "name", "properties": { "name": "urn:ogc:def:crs:OGC:1.3:CRS84" } },
"features": [
{ "type": "Feature", "properties": { "point_type": "origin", "points_str": "45.596386, -122.737483" }, "geometry": { "type": "Point", "coordinates": [ -122.73748273483038, 45.596385925873307 ] } },
{ "type": "Feature", "properties": { "point_type": "destination", "points_str": "45.47586, -122.582131" }, "geometry": { "type": "Point", "coordinates": [ -122.582131266578514, 45.475860299782973 ] } }
]
}
