{
"type": "FeatureCollection",
"name": "origin_destination_points",
"crs": { "type": "name", "properties": { "name": "urn:ogc:def:crs:OGC:1.3:CRS84" } },
"features": [
{ "type": "Feature", "properties": { "point_type": "origin", "points_str": "45.46569, -122.591333" }, "geometry": { "type": "Point", "coordinates": [ -122.591333453050666, 45.465689832670414 ] } },
{ "type": "Feature", "properties": { "point_type": "destination", "points_str": "45.495669, -122.63681" }, "geometry": { "type": "Point", "coordinates": [ -122.636810066266889, 45.495668708511843 ] } }
]
}
