{
"type": "FeatureCollection",
"name": "origin_destination_points",
"crs": { "type": "name", "properties": { "name": "urn:ogc:def:crs:OGC:1.3:CRS84" } },
"features": [
{ "type": "Feature", "properties": { "point_type": "origin", "points_str": "45.492087, -122.470953" }, "geometry": { "type": "Point", "coordinates": [ -122.470952608686474, 45.492087118358747 ] } },
{ "type": "Feature", "properties": { "point_type": "destination", "points_str": "45.463874, -122.645738" }, "geometry": { "type": "Point", "coordinates": [ -122.645737938255763, 45.463873997958757 ] } }
]
}
