{
"type": "FeatureCollection",
"crs": { "type": "name", "properties": { "name": "urn:ogc:def:crs:OGC:1.3:CRS84" } },
"features": [
{ "type": "Feature", "properties": { "point_type": "origin", "points_str": "45.489448, -122.617385" }, "geometry": { "type": "Point", "coordinates": [ -122.617384557896031, 45.489447725676825 ] } },
{ "type": "Feature", "properties": { "point_type": "destination", "points_str": "45.465644, -122.700638" }, "geometry": { "type": "Point", "coordinates": [ -122.700637547900186, 45.465643881700963 ] } }
]
}
