{
"type": "FeatureCollection",
"crs": { "type": "name", "properties": { "name": "urn:ogc:def:crs:OGC:1.3:CRS84" } },
"features": [
{ "type": "Feature", "properties": { "point_type": "origin", "points_str": "45.495953, -122.557314" }, "geometry": { "type": "Point", "coordinates": [ -122.557313582214519, 45.495953273753464 ] } },
{ "type": "Feature", "properties": { "point_type": "destination", "points_str": "45.517341, -122.401294" }, "geometry": { "type": "Point", "coordinates": [ -122.401294068669898, 45.517340575467713 ] } }
]
}
