{
"type": "FeatureCollection",
"name": "origin_destination_points",
"crs": { "type": "name", "properties": { "name": "urn:ogc:def:crs:OGC:1.3:CRS84" } },
"features": [
{ "type": "Feature", "properties": { "point_type": "origin", "points_str": "45.572311, -122.555884" }, "geometry": { "type": "Point", "coordinates": [ -122.555883800504361, 45.572310761983744 ] } },
{ "type": "Feature", "properties": { "point_type": "destination", "points_str": "45.578081, -122.691481" }, "geometry": { "type": "Point", "coordinates": [ -122.691480995250856, 45.578080788941961 ] } }
]
}
