{
"type": "FeatureCollection",
"name": "origin_destination_points",
"crs": { "type": "name", "properties": { "name": "urn:ogc:def:crs:OGC:1.3:CRS84" } },
"features": [
{ "type": "Feature", "properties": { "point_type": "origin", "points_str": "45.438657, -122.570922" }, "geometry": { "type": "Point", "coordinates": [ -122.570922118334636, 45.43865734370349 ] } },
{ "type": "Feature", "properties": { "point_type": "destination", "points_str": "45.448131, -122.641063" }, "geometry": { "type": "Point", "coordinates": [ -122.641063103538087, 45.448131492817879 ] } }
]
}
