{
"type": "FeatureCollection",
"name": "origin_destination_points",
"crs": { "type": "name", "properties": { "name": "urn:ogc:def:crs:OGC:1.3:CRS84" } },
"features": [
{ "type": "Feature", "properties": { "point_type": "origin", "points_str": "45.48989, -122.582644" }, "geometry": { "type": "Point", "coordinates": [ -122.582644163377239, 45.489889615638909 ] } },
{ "type": "Feature", "properties": { "point_type": "destination", "points_str": "45.515747, -122.62377" }, "geometry": { "type": "Point", "coordinates": [ -122.6237698373928, 45.515746582051705 ] } }
]
}
