{
"type": "FeatureCollection",
"name": "origin_destination_points",
"crs": { "type": "name", "properties": { "name": "urn:ogc:def:crs:OGC:1.3:CRS84" } },
"features": [
{ "type": "Feature", "properties": { "point_type": "origin", "points_str": "45.515358, -122.671877" }, "geometry": { "type": "Point", "coordinates": [ -122.671876738891726, 45.515357688965267 ] } },
{ "type": "Feature", "properties": { "point_type": "destination", "points_str": "45.576399, -122.723297" }, "geometry": { "type": "Point", "coordinates": [ -122.723297091364387, 45.576399140222883 ] } }
]
}
