{
"type": "FeatureCollection",
"name": "origin_destination_points",
"crs": { "type": "name", "properties": { "name": "urn:ogc:def:crs:OGC:1.3:CRS84" } },
"features": [
{ "type": "Feature", "properties": { "point_type": "origin", "points_str": "45.45339, -122.674925" }, "geometry": { "type": "Point", "coordinates": [ -122.674925363710685, 45.453390206581801 ] } },
{ "type": "Feature", "properties": { "point_type": "destination", "points_str": "45.397596, -122.575184" }, "geometry": { "type": "Point", "coordinates": [ -122.575184308955727, 45.397596241948463 ] } }
]
}
