{
"type": "FeatureCollection",
"name": "origin_destination_points",
"crs": { "type": "name", "properties": { "name": "urn:ogc:def:crs:OGC:1.3:CRS84" } },
"features": [
{ "type": "Feature", "properties": { "point_type": "origin", "points_str": "45.529607, -122.629252" }, "geometry": { "type": "Point", "coordinates": [ -122.629251782900909, 45.529606922810189 ] } },
{ "type": "Feature", "properties": { "point_type": "destination", "points_str": "45.448236, -122.577169" }, "geometry": { "type": "Point", "coordinates": [ -122.577169219386832, 45.448236254455765 ] } }
]
}
