{
"type": "FeatureCollection",
"name": "origin_destination_points",
"crs": { "type": "name", "properties": { "name": "urn:ogc:def:crs:OGC:1.3:CRS84" } },
"features": [
{ "type": "Feature", "properties": { "point_type": "origin", "points_str": "45.467572, -122.601109" }, "geometry": { "type": "Point", "coordinates": [ -122.60110891023912, 45.46757207420071 ] } },
{ "type": "Feature", "properties": { "point_type": "destination", "points_str": "45.5177, -122.613766" }, "geometry": { "type": "Point", "coordinates": [ -122.613765542918628, 45.517700185156507 ] } }
]
}
