{
"type": "FeatureCollection",
"crs": { "type": "name", "properties": { "name": "urn:ogc:def:crs:OGC:1.3:CRS84" } },
"features": [
{ "type": "Feature", "properties": { "point_type": "origin", "points_str": "45.476316, -122.69252" }, "geometry": { "type": "Point", "coordinates": [ -122.692519916988047, 45.476315834493114 ] } },
{ "type": "Feature", "properties": { "point_type": "destination", "points_str": "45.49581, -122.800736" }, "geometry": { "type": "Point", "coordinates": [ -122.800736488186629, 45.495810464374649 ] } }
]
}
