{
"type": "FeatureCollection",
"name": "origin_destination_points",
"crs": { "type": "name", "properties": { "name": "urn:ogc:def:crs:OGC:1.3:CRS84" } },
"features": [
{ "type": "Feature", "properties": { "point_type": "origin", "points_str": "45.506875, -122.485916" }, "geometry": { "type": "Point", "coordinates": [ -122.485915855850365, 45.506875060374114 ] } },
{ "type": "Feature", "properties": { "point_type": "destination", "points_str": "45.546771, -122.575718" }, "geometry": { "type": "Point", "coordinates": [ -122.575717542522327, 45.546771026452795 ] } }
]
}
