{
"type": "FeatureCollection",
"crs": { "type": "name", "properties": { "name": "urn:ogc:def:crs:OGC:1.3:CRS84" } },
"features": [
{ "type": "Feature", "properties": { "point_type": "origin", "points_str": "45.535031, -122.560736" }, "geometry": { "type": "Point", "coordinates": [ -122.560735747133634, 45.5350308411493 ] } },
{ "type": "Feature", "properties": { "point_type": "destination", "points_str": "45.519559, -122.975681" }, "geometry": { "type": "Point", "coordinates": [ -122.97568080047175, 45.519559379162388 ] } }
]
}
