{
"type": "FeatureCollection",
"name": "origin_destination_points",
"crs": { "type": "name", "properties": { "name": "urn:ogc:def:crs:OGC:1.3:CRS84" } },
"features": [
{ "type": "Feature", "properties": { "point_type": "origin", "points_str": "45.47622, -122.633309" }, "geometry": { "type": "Point", "coordinates": [ -122.633309035330328, 45.476219593348389 ] } },
{ "type": "Feature", "properties": { "point_type": "destination", "points_str": "45.515391, -122.867787" }, "geometry": { "type": "Point", "coordinates": [ -122.867787067822931, 45.515391208251799 ] } }
]
}
