{
"type": "FeatureCollection",
"crs": { "type": "name", "properties": { "name": "urn:ogc:def:crs:OGC:1.3:CRS84" } },
"features": [
{ "type": "Feature", "properties": { "point_type": "origin", "points_str": "45.519408, -122.414722" }, "geometry": { "type": "Point", "coordinates": [ -122.414722272929723, 45.51940754726165 ] } },
{ "type": "Feature", "properties": { "point_type": "destination", "points_str": "45.442087, -122.74852" }, "geometry": { "type": "Point", "coordinates": [ -122.748520458438051, 45.442086681368565 ] } }
]
}
