{
"type": "FeatureCollection",
"name": "origin_destination_points",
"crs": { "type": "name", "properties": { "name": "urn:ogc:def:crs:OGC:1.3:CRS84" } },
"features": [
{ "type": "Feature", "properties": { "point_type": "origin", "points_str": "45.533283, -122.455436" }, "geometry": { "type": "Point", "coordinates": [ -122.455435687117443, 45.533282765376356 ] } },
{ "type": "Feature", "properties": { "point_type": "destination", "points_str": "45.55725, -122.54176" }, "geometry": { "type": "Point", "coordinates": [ -122.541760242893488, 45.557249509165921 ] } }
]
}
