{
"type": "FeatureCollection",
"crs": { "type": "name", "properties": { "name": "urn:ogc:def:crs:OGC:1.3:CRS84" } },
"features": [
{ "type": "Feature", "properties": { "point_type": "origin", "points_str": "45.38585, -122.61834" }, "geometry": { "type": "Point", "coordinates": [ -122.618339939344949, 45.385849668958855 ] } },
{ "type": "Feature", "properties": { "point_type": "destination", "points_str": "45.524829, -122.600992" }, "geometry": { "type": "Point", "coordinates": [ -122.600991574632047, 45.524829107521221 ] } }
]
}
