{
"type": "FeatureCollection",
"crs": { "type": "name", "properties": { "name": "urn:ogc:def:crs:OGC:1.3:CRS84" } },
"features": [
{ "type": "Feature", "properties": { "point_type": "origin", "points_str": "45.494518, -122.850204" }, "geometry": { "type": "Point", "coordinates": [ -122.850204317633484, 45.494518244012845 ] } },
{ "type": "Feature", "properties": { "point_type": "destination", "points_str": "45.520333, -123.010247" }, "geometry": { "type": "Point", "coordinates": [ -123.010246793335412, 45.520333396867265 ] } }
]
}
