{
"type": "FeatureCollection",
"name": "origin_destination_points",
"crs": { "type": "name", "properties": { "name": "urn:ogc:def:crs:OGC:1.3:CRS84" } },
"features": [
{ "type": "Feature", "properties": { "point_type": "origin", "points_str": "45.544276, -122.479306" }, "geometry": { "type": "Point", "coordinates": [ -122.479306338627296, 45.544275899424072 ] } },
{ "type": "Feature", "properties": { "point_type": "destination", "points_str": "45.526252, -122.454901" }, "geometry": { "type": "Point", "coordinates": [ -122.454900889759813, 45.526251665189797 ] } }
]
}
