{
"type": "FeatureCollection",
"crs": { "type": "name", "properties": { "name": "urn:ogc:def:crs:OGC:1.3:CRS84" } },
"features": [
{ "type": "Feature", "properties": { "point_type": "origin", "points_str": "45.615733, -122.804702" }, "geometry": { "type": "Point", "coordinates": [ -122.804701857195212, 45.615733160114864 ] } },
{ "type": "Feature", "properties": { "point_type": "destination", "points_str": "45.484279, -122.670296" }, "geometry": { "type": "Point", "coordinates": [ -122.670296280020636, 45.484278622346622 ] } }
]
}
