{
"type": "FeatureCollection",
"name": "origin_destination_points",
"crs": { "type": "name", "properties": { "name": "urn:ogc:def:crs:OGC:1.3:CRS84" } },
"features": [
{ "type": "Feature", "properties": { "point_type": "origin", "points_str": "45.4526, -122.641281" }, "geometry": { "type": "Point", "coordinates": [ -122.641280802598217, 45.452599625198779 ] } },
{ "type": "Feature", "properties": { "point_type": "destination", "points_str": "45.396452, -122.579385" }, "geometry": { "type": "Point", "coordinates": [ -122.579385153306291, 45.396451587433667 ] } }
]
}
