{
"type": "FeatureCollection",
"crs": { "type": "name", "properties": { "name": "urn:ogc:def:crs:OGC:1.3:CRS84" } },
"features": [
{ "type": "Feature", "properties": { "point_type": "origin", "points_str": "45.519411, -122.55517" }, "geometry": { "type": "Point", "coordinates": [ -122.555169947261163, 45.51941123068363 ] } },
{ "type": "Feature", "properties": { "point_type": "destination", "points_str": "45.508038, -122.653815" }, "geometry": { "type": "Point", "coordinates": [ -122.653815062835193, 45.508037922567944 ] } }
]
}
