{
"type": "FeatureCollection",
"name": "origin_destination_points",
"crs": { "type": "name", "properties": { "name": "urn:ogc:def:crs:OGC:1.3:CRS84" } },
"features": [
{ "type": "Feature", "properties": { "point_type": "origin", "points_str": "45.440931, -122.730581" }, "geometry": { "type": "Point", "coordinates": [ -122.730580639187608, 45.440930563442578 ] } },
{ "type": "Feature", "properties": { "point_type": "destination", "points_str": "45.48017, -122.753414" }, "geometry": { "type": "Point", "coordinates": [ -122.753413861490131, 45.480170385607252 ] } }
]
}
