{
"type": "FeatureCollection",
"crs": { "type": "name", "properties": { "name": "urn:ogc:def:crs:OGC:1.3:CRS84" } },
"features": [
{ "type": "Feature", "properties": { "point_type": "origin", "points_str": "45.49602, -122.688302" }, "geometry": { "type": "Point", "coordinates": [ -122.688301715381328, 45.496019548749125 ] } },
{ "type": "Feature", "properties": { "point_type": "destination", "points_str": "45.514182, -122.454229" }, "geometry": { "type": "Point", "coordinates": [ -122.45422916086082, 45.514182037298291 ] } }
]
}
