{
"type": "FeatureCollection",
"crs": { "type": "name", "properties": { "name": "urn:ogc:def:crs:OGC:1.3:CRS84" } },
"features": [
{ "type": "Feature", "properties": { "point_type": "origin", "points_str": "45.592441, -122.764272" }, "geometry": { "type": "Point", "coordinates": [ -122.764272308219859, 45.592441479934095 ] } },
{ "type": "Feature", "properties": { "point_type": "destination", "points_str": "45.530844, -122.636574" }, "geometry": { "type": "Point", "coordinates": [ -122.63657358685559, 45.530843593661274 ] } }
]
}
