{
"type": "FeatureCollection",
"crs": { "type": "name", "properties": { "name": "urn:ogc:def:crs:OGC:1.3:CRS84" } },
"features": [
{ "type": "Feature", "properties": { "point_type": "origin", "points_str": "45.471252, -122.886327" }, "geometry": { "type": "Point", "coordinates": [ -122.886326945930392, 45.471252302897312 ] } },
{ "type": "Feature", "properties": { "point_type": "destination", "points_str": "45.480578, -122.796471" }, "geometry": { "type": "Point", "coordinates": [ -122.79647091944895, 45.480578123325373 ] } }
]
}
