{
"type": "FeatureCollection",
"name": "origin_destination_points",
"crs": { "type": "name", "properties": { "name": "urn:ogc:def:crs:OGC:1.3:CRS84" } },
"features": [
{ "type": "Feature", "properties": { "point_type": "origin", "points_str": "45.533366, -122.498216" }, "geometry": { "type": "Point", "coordinates": [ -122.498216042662548, 45.53336559993334 ] } },
{ "type": "Feature", "properties": { "point_type": "destination", "points_str": "45.518435, -122.865019" }, "geometry": { "type": "Point", "coordinates": [ -122.865018880697306, 45.518434679191714 ] } }
]
}
