{
"type": "FeatureCollection",
"name": "origin_destination_points",
"crs": { "type": "name", "properties": { "name": "urn:ogc:def:crs:OGC:1.3:CRS84" } },
"features": [
{ "type": "Feature", "properties": { "point_type": "origin", "points_str": "45.516873, -122.817623" }, "geometry": { "type": "Point", "coordinates": [ -122.817622959352875, 45.516873169372516 ] } },
{ "type": "Feature", "properties": { "point_type": "destination", "points_str": "45.499355, -122.894782" }, "geometry": { "type": "Point", "coordinates": [ -122.894781595354402, 45.499355049763047 ] } }
]
}
