{
"type": "FeatureCollection",
"name": "origin_destination_points",
"crs": { "type": "name", "properties": { "name": "urn:ogc:def:crs:OGC:1.3:CRS84" } },
"features": [
{ "type": "Feature", "properties": { "point_type": "origin", "points_str": "45.49592, -122.610704" }, "geometry": { "type": "Point", "coordinates": [ -122.610704057621007, 45.495919542784371 ] } },
{ "type": "Feature", "properties": { "point_type": "destination", "points_str": "45.513066, -122.668523" }, "geometry": { "type": "Point", "coordinates": [ -122.668522939282823, 45.513066364011152 ] } }
]
}
