{
"type": "FeatureCollection",
"name": "origin_destination_points",
"crs": { "type": "name", "properties": { "name": "urn:ogc:def:crs:OGC:1.3:CRS84" } },
"features": [
{ "type": "Feature", "properties": { "point_type": "origin", "points_str": "45.419001, -122.769847" }, "geometry": { "type": "Point", "coordinates": [ -122.769847052957587, 45.419001298125828 ] } },
{ "type": "Feature", "properties": { "point_type": "destination", "points_str": "45.521202, -123.027981" }, "geometry": { "type": "Point", "coordinates": [ -123.027980573900848, 45.521202083145027 ] } }
]
}
