{
"type": "FeatureCollection",
"name": "origin_destination_points",
"crs": { "type": "name", "properties": { "name": "urn:ogc:def:crs:OGC:1.3:CRS84" } },
"features": [
{ "type": "Feature", "properties": { "point_type": "origin", "points_str": "45.510265, -122.785007" }, "geometry": { "type": "Point", "coordinates": [ -122.785006928573694, 45.510265148291801 ] } },
{ "type": "Feature", "properties": { "point_type": "destination", "points_str": "45.559215, -122.666199" }, "geometry": { "type": "Point", "coordinates": [ -122.666198662986659, 45.559215134156695 ] } }
]
}
