{
"type": "FeatureCollection",
"crs": { "type": "name", "properties": { "name": "urn:ogc:def:crs:OGC:1.3:CRS84" } },
"features": [
{ "type": "Feature", "properties": { "point_type": "origin", "points_str": "45.498441, -122.443535" }, "geometry": { "type": "Point", "coordinates": [ -122.443535368624154, 45.498441169207744 ] } },
{ "type": "Feature", "properties": { "point_type": "destination", "points_str": "45.554788, -122.551267" }, "geometry": { "type": "Point", "coordinates": [ -122.551267311457806, 45.554787804948354 ] } }
]
}
