{
"type": "FeatureCollection",
"name": "origin_destination_points",
"crs": { "type": "name", "properties": { "name": "urn:ogc:def:crs:OGC:1.3:CRS84" } },
"features": [
{ "type": "Feature", "properties": { "point_type": "origin", "points_str": "45.516395, -123.020683" }, "geometry": { "type": "Point", "coordinates": [ -123.020682936788262, 45.516394650896835 ] } },
{ "type": "Feature", "properties": { "point_type": "destination", "points_str": "45.310878, -122.777565" }, "geometry": { "type": "Point", "coordinates": [ -122.777565359230337, 45.310878066879312 ] } }
]
}
