{
"type": "FeatureCollection",
"name": "origin_destination_points",
"crs": { "type": "name", "properties": { "name": "urn:ogc:def:crs:OGC:1.3:CRS84" } },
"features": [
{ "type": "Feature", "properties": { "point_type": "origin", "points_str": "45.470009, -122.618335" }, "geometry": { "type": "Point", "coordinates": [ -122.618334842143099, 45.470008883985798 ] } },
{ "type": "Feature", "properties": { "point_type": "destination", "points_str": "45.481813, -122.647163" }, "geometry": { "type": "Point", "coordinates": [ -122.647163219486728, 45.481813047736935 ] } }
]
}
