{
"type": "FeatureCollection",
"name": "origin_destination_points",
"crs": { "type": "name", "properties": { "name": "urn:ogc:def:crs:OGC:1.3:CRS84" } },
"features": [
{ "type": "Feature", "properties": { "point_type": "origin", "points_str": "45.510432, -122.674386" }, "geometry": { "type": "Point", "coordinates": [ -122.674386340158989, 45.510431636831271 ] } },
{ "type": "Feature", "properties": { "point_type": "destination", "points_str": "45.527708, -122.633227" }, "geometry": { "type": "Point", "coordinates": [ -122.633226856920984, 45.527708001135593 ] } }
]
}
