{
"type": "FeatureCollection",
"name": "origin_destination_points",
"crs": { "type": "name", "properties": { "name": "urn:ogc:def:crs:OGC:1.3:CRS84" } },
"features": [
{ "type": "Feature", "properties": { "point_type": "origin", "points_str": "45.503714, -122.578693" }, "geometry": { "type": "Point", "coordinates": [ -122.578692952339267, 45.503714165177051 ] } },
{ "type": "Feature", "properties": { "point_type": "destination", "points_str": "45.567653, -122.712782" }, "geometry": { "type": "Point", "coordinates": [ -122.712782235831142, 45.567652769653392 ] } }
]
}
