{
"type": "FeatureCollection",
"name": "origin_destination_points",
"crs": { "type": "name", "properties": { "name": "urn:ogc:def:crs:OGC:1.3:CRS84" } },
"features": [
{ "type": "Feature", "properties": { "point_type": "origin", "points_str": "45.533415, -122.932285" }, "geometry": { "type": "Point", "coordinates": [ -122.932284910426716, 45.533414611154889 ] } },
{ "type": "Feature", "properties": { "point_type": "destination", "points_str": "45.501344, -122.425982" }, "geometry": { "type": "Point", "coordinates": [ -122.425981825114746, 45.501343595349681 ] } }
]
}
