{
"type": "FeatureCollection",
"name": "origin_destination_points",
"crs": { "type": "name", "properties": { "name": "urn:ogc:def:crs:OGC:1.3:CRS84" } },
"features": [
{ "type": "Feature", "properties": { "point_type": "origin", "points_str": "45.452576, -122.773047" }, "geometry": { "type": "Point", "coordinates": [ -122.773046520472789, 45.452576324056011 ] } },
{ "type": "Feature", "properties": { "point_type": "destination", "points_str": "45.469692, -122.779809" }, "geometry": { "type": "Point", "coordinates": [ -122.779809468144123, 45.46969211382568 ] } }
]
}
