{
"type": "FeatureCollection",
"name": "origin_destination_points",
"crs": { "type": "name", "properties": { "name": "urn:ogc:def:crs:OGC:1.3:CRS84" } },
"features": [
{ "type": "Feature", "properties": { "point_type": "origin", "points_str": "45.559964, -122.588096" }, "geometry": { "type": "Point", "coordinates": [ -122.588095920814553, 45.559964425469303 ] } },
{ "type": "Feature", "properties": { "point_type": "destination", "points_str": "45.532171, -122.504152" }, "geometry": { "type": "Point", "coordinates": [ -122.50415242665764, 45.532170704209456 ] } }
]
}
