{
"type": "FeatureCollection",
"name": "origin_destination_points",
"crs": { "type": "name", "properties": { "name": "urn:ogc:def:crs:OGC:1.3:CRS84" } },
"features": [
{ "type": "Feature", "properties": { "point_type": "origin", "points_str": "45.542185, -122.871162" }, "geometry": { "type": "Point", "coordinates": [ -122.871161924655496, 45.542185063774568 ] } },
{ "type": "Feature", "properties": { "point_type": "destination", "points_str": "45.50071, -122.835529" }, "geometry": { "type": "Point", "coordinates": [ -122.835529024768178, 45.500710168610901 ] } }
]
}
