{
"type": "FeatureCollection",
"crs": { "type": "name", "properties": { "name": "urn:ogc:def:crs:OGC:1.3:CRS84" } },
"features": [
{ "type": "Feature", "properties": { "point_type": "origin", "points_str": "45.445111, -122.761721" }, "geometry": { "type": "Point", "coordinates": [ -122.761721013554748, 45.445111444655687 ] } },
{ "type": "Feature", "properties": { "point_type": "destination", "points_str": "45.544599, -122.623711" }, "geometry": { "type": "Point", "coordinates": [ -122.623711126451525, 45.544598609022827 ] } }
]
}
