{
"type": "FeatureCollection",
"name": "origin_destination_points",
"crs": { "type": "name", "properties": { "name": "urn:ogc:def:crs:OGC:1.3:CRS84" } },
"features": [
{ "type": "Feature", "properties": { "point_type": "origin", "points_str": "45.485963, -122.575369" }, "geometry": { "type": "Point", "coordinates": [ -122.575369316255575, 45.485962858377491 ] } },
{ "type": "Feature", "properties": { "point_type": "destination", "points_str": "45.504436, -122.596339" }, "geometry": { "type": "Point", "coordinates": [ -122.596338724179887, 45.504435772545143 ] } }
]
}
