{
"type": "FeatureCollection",
"name": "origin_destination_points",
"crs": { "type": "name", "properties": { "name": "urn:ogc:def:crs:OGC:1.3:CRS84" } },
"features": [
{ "type": "Feature", "properties": { "point_type": "origin", "points_str": "45.596426, -122.762584" }, "geometry": { "type": "Point", "coordinates": [ -122.762584352435042, 45.596426176691288 ] } },
{ "type": "Feature", "properties": { "point_type": "destination", "points_str": "45.50726, -122.606638" }, "geometry": { "type": "Point", "coordinates": [ -122.606637999029346, 45.507260210608045 ] } }
]
}
