{
"type": "FeatureCollection",
"name": "origin_destination_points",
"crs": { "type": "name", "properties": { "name": "urn:ogc:def:crs:OGC:1.3:CRS84" } },
"features": [
{ "type": "Feature", "properties": { "point_type": "origin", "points_str": "45.526763, -122.582825" }, "geometry": { "type": "Point", "coordinates": [ -122.582825370649559, 45.526762999358013 ] } },
{ "type": "Feature", "properties": { "point_type": "destination", "points_str": "45.557359, -122.618995" }, "geometry": { "type": "Point", "coordinates": [ -122.61899542817001, 45.557358565462273 ] } }
]
}
