{
"type": "FeatureCollection",
"crs": { "type": "name", "properties": { "name": "urn:ogc:def:crs:OGC:1.3:CRS84" } },
"features": [
{ "type": "Feature", "properties": { "point_type": "origin", "points_str": "45.550611, -122.986107" }, "geometry": { "type": "Point", "coordinates": [ -122.986106624008045, 45.550611269573899 ] } },
{ "type": "Feature", "properties": { "point_type": "destination", "points_str": "45.514579, -123.104935" }, "geometry": { "type": "Point", "coordinates": [ -123.104934560335465, 45.514578681708791 ] } }
]
}
