{
"type": "FeatureCollection",
"name": "origin_destination_points",
"crs": { "type": "name", "properties": { "name": "urn:ogc:def:crs:OGC:1.3:CRS84" } },
"features": [
{ "type": "Feature", "properties": { "point_type": "origin", "points_str": "45.610997, -122.674889" }, "geometry": { "type": "Point", "coordinates": [ -122.674889275260981, 45.610997015945131 ] } },
{ "type": "Feature", "properties": { "point_type": "destination", "points_str": "45.519158, -122.510731" }, "geometry": { "type": "Point", "coordinates": [ -122.510730550517906, 45.519158079655384 ] } }
]
}
