{
"type": "FeatureCollection",
"name": "origin_destination_points",
"crs": { "type": "name", "properties": { "name": "urn:ogc:def:crs:OGC:1.3:CRS84" } },
"features": [
{ "type": "Feature", "properties": { "point_type": "origin", "points_str": "45.560249, -122.624413" }, "geometry": { "type": "Point", "coordinates": [ -122.624413393001149, 45.560249461476282 ] } },
{ "type": "Feature", "properties": { "point_type": "destination", "points_str": "45.48491, -122.581483" }, "geometry": { "type": "Point", "coordinates": [ -122.581482512366307, 45.484910413325508 ] } }
]
}
