{
"type": "FeatureCollection",
"name": "origin_destination_points",
"crs": { "type": "name", "properties": { "name": "urn:ogc:def:crs:OGC:1.3:CRS84" } },
"features": [
{ "type": "Feature", "properties": { "point_type": "origin", "points_str": "45.489876, -122.576643" }, "geometry": { "type": "Point", "coordinates": [ -122.576642576210162, 45.489876374556175 ] } },
{ "type": "Feature", "properties": { "point_type": "destination", "points_str": "45.408997, -122.539212" }, "geometry": { "type": "Point", "coordinates": [ -122.539212345547313, 45.408996642584519 ] } }
]
}
