{
"type": "FeatureCollection",
"name": "origin_destination_points",
"crs": { "type": "name", "properties": { "name": "urn:ogc:def:crs:OGC:1.3:CRS84" } },
"features": [
{ "type": "Feature", "properties": { "point_type": "origin", "points_str": "45.524084, -122.889019" }, "geometry": { "type": "Point", "coordinates": [ -122.889018939321588, 45.524083727430785 ] } },
{ "type": "Feature", "properties": { "point_type": "destination", "points_str": "45.374532, -122.630251" }, "geometry": { "type": "Point", "coordinates": [ -122.630250981961808, 45.37453172846088 ] } }
]
}
