{
"type": "FeatureCollection",
"crs": { "type": "name", "properties": { "name": "urn:ogc:def:crs:OGC:1.3:CRS84" } },
"features": [
{ "type": "Feature", "properties": { "point_type": "origin", "points_str": "45.598227, -122.787605" }, "geometry": { "type": "Point", "coordinates": [ -122.787605157020153, 45.598226560685177 ] } },
{ "type": "Feature", "properties": { "point_type": "destination", "points_str": "45.547948, -122.699054" }, "geometry": { "type": "Point", "coordinates": [ -122.699054050808755, 45.54794757879646 ] } }
]
}
