{
"type": "FeatureCollection",
"name": "origin_destination_points",
"crs": { "type": "name", "properties": { "name": "urn:ogc:def:crs:OGC:1.3:CRS84" } },
"features": [
{ "type": "Feature", "properties": { "point_type": "origin", "points_str": "45.524208, -122.614051" }, "geometry": { "type": "Point", "coordinates": [ -122.614050999401741, 45.524208153587843 ] } },
{ "type": "Feature", "properties": { "point_type": "destination", "points_str": "45.554365, -122.678274" }, "geometry": { "type": "Point", "coordinates": [ -122.678273550777917, 45.554365175208204 ] } }
]
}
