{
"type": "FeatureCollection",
"crs": { "type": "name", "properties": { "name": "urn:ogc:def:crs:OGC:1.3:CRS84" } },
"features": [
{ "type": "Feature", "properties": { "point_type": "origin", "points_str": "45.531603, -122.934749" }, "geometry": { "type": "Point", "coordinates": [ -122.934748914728374, 45.531602512753949 ] } },
{ "type": "Feature", "properties": { "point_type": "destination", "points_str": "45.555676, -122.837499" }, "geometry": { "type": "Point", "coordinates": [ -122.837498783720633, 45.555675880239953 ] } }
]
}
