{
"type": "FeatureCollection",
"name": "origin_destination_points",
"crs": { "type": "name", "properties": { "name": "urn:ogc:def:crs:OGC:1.3:CRS84" } },
"features": [
{ "type": "Feature", "properties": { "point_type": "origin", "points_str": "45.508812, -122.606299" }, "geometry": { "type": "Point", "coordinates": [ -122.606298970021982, 45.508812259948677 ] } },
{ "type": "Feature", "properties": { "point_type": "destination", "points_str": "45.49591, -122.462867" }, "geometry": { "type": "Point", "coordinates": [ -122.462867350104986, 45.495910040651523 ] } }
]
}
