{
"type": "FeatureCollection",
"crs": { "type": "name", "properties": { "name": "urn:ogc:def:crs:OGC:1.3:CRS84" } },
"features": [
{ "type": "Feature", "properties": { "point_type": "origin", "points_str": "45.484335, -122.56713" }, "geometry": { "type": "Point", "coordinates": [ -122.567129973616119, 45.484334755985195 ] } },
{ "type": "Feature", "properties": { "point_type": "destination", "points_str": "45.469605, -122.72549" }, "geometry": { "type": "Point", "coordinates": [ -122.725489731904233, 45.469605276334889 ] } }
]
}
