{
"type": "FeatureCollection",
"name": "origin_destination_points",
"crs": { "type": "name", "properties": { "name": "urn:ogc:def:crs:OGC:1.3:CRS84" } },
"features": [
{ "type": "Feature", "properties": { "point_type": "origin", "points_str": "45.511793, -122.573393" }, "geometry": { "type": "Point", "coordinates": [ -122.573393490523685, 45.511793357459823 ] } },
{ "type": "Feature", "properties": { "point_type": "destination", "points_str": "45.574568, -122.559896" }, "geometry": { "type": "Point", "coordinates": [ -122.559895650416848, 45.57456803997308 ] } }
]
}
