{
"type": "FeatureCollection",
"name": "origin_destination_points",
"crs": { "type": "name", "properties": { "name": "urn:ogc:def:crs:OGC:1.3:CRS84" } },
"features": [
{ "type": "Feature", "properties": { "point_type": "origin", "points_str": "45.446478, -122.747812" }, "geometry": { "type": "Point", "coordinates": [ -122.747812215426393, 45.446477922778087 ] } },
{ "type": "Feature", "properties": { "point_type": "destination", "points_str": "45.512406, -122.461767" }, "geometry": { "type": "Point", "coordinates": [ -122.461767438115047, 45.512406158481369 ] } }
]
}
