{
"type": "FeatureCollection",
"crs": { "type": "name", "properties": { "name": "urn:ogc:def:crs:OGC:1.3:CRS84" } },
"features": [
{ "type": "Feature", "properties": { "point_type": "origin", "points_str": "45.456583, -122.739568" }, "geometry": { "type": "Point", "coordinates": [ -122.739568297654216, 45.456582888536197 ] } },
{ "type": "Feature", "properties": { "point_type": "destination", "points_str": "45.528366, -122.787853" }, "geometry": { "type": "Point", "coordinates": [ -122.787852663939546, 45.528365617913174 ] } }
]
}
