{
"type": "FeatureCollection",
"name": "origin_destination_points",
"crs": { "type": "name", "properties": { "name": "urn:ogc:def:crs:OGC:1.3:CRS84" } },
"features": [
{ "type": "Feature", "properties": { "point_type": "origin", "points_str": "45.454287, -122.633313" }, "geometry": { "type": "Point", "coordinates": [ -122.633312627424885, 45.454287387478089 ] } },
{ "type": "Feature", "properties": { "point_type": "destination", "points_str": "45.52994, -122.466959" }, "geometry": { "type": "Point", "coordinates": [ -122.466958913639218, 45.529939690438745 ] } }
]
}
