{
"type": "FeatureCollection",
"name": "origin_destination_points",
"crs": { "type": "name", "properties": { "name": "urn:ogc:def:crs:OGC:1.3:CRS84" } },
"features": [
{ "type": "Feature", "properties": { "point_type": "origin", "points_str": "45.468046, -122.695366" }, "geometry": { "type": "Point", "coordinates": [ -122.695366491057413, 45.468045775260876 ] } },
{ "type": "Feature", "properties": { "point_type": "destination", "points_str": "45.481644, -122.703595" }, "geometry": { "type": "Point", "coordinates": [ -122.703595096933, 45.481644190573924 ] } }
]
}
