{
"type": "FeatureCollection",
"name": "origin_destination_points",
"crs": { "type": "name", "properties": { "name": "urn:ogc:def:crs:OGC:1.3:CRS84" } },
"features": [
{ "type": "Feature", "properties": { "point_type": "origin", "points_str": "45.519972, -122.516104" }, "geometry": { "type": "Point", "coordinates": [ -122.516103613421294, 45.519972472196706 ] } },
{ "type": "Feature", "properties": { "point_type": "destination", "points_str": "45.51684, -122.450956" }, "geometry": { "type": "Point", "coordinates": [ -122.450955559158658, 45.516839947546202 ] } }
]
}
