{
"type": "FeatureCollection",
"name": "origin_destination_points",
"crs": { "type": "name", "properties": { "name": "urn:ogc:def:crs:OGC:1.3:CRS84" } },
"features": [
{ "type": "Feature", "properties": { "point_type": "origin", "points_str": "45.517676, -122.581004" }, "geometry": { "type": "Point", "coordinates": [ -122.581003679935009, 45.517675879335243 ] } },
{ "type": "Feature", "properties": { "point_type": "destination", "points_str": "45.526893, -122.407145" }, "geometry": { "type": "Point", "coordinates": [ -122.407144863536445, 45.526893258081031 ] } }
]
}
