{
"type": "FeatureCollection",
"name": "origin_destination_points",
"crs": { "type": "name", "properties": { "name": "urn:ogc:def:crs:OGC:1.3:CRS84" } },
"features": [
{ "type": "Feature", "properties": { "point_type": "origin", "points_str": "45.498086, -122.57248" }, "geometry": { "type": "Point", "coordinates": [ -122.572480494391087, 45.498085780158512 ] } },
{ "type": "Feature", "properties": { "point_type": "destination", "points_str": "45.48906, -122.741459" }, "geometry": { "type": "Point", "coordinates": [ -122.741459087663713, 45.489059756193051 ] } }
]
}
