{
"type": "FeatureCollection",
"name": "origin_destination_points",
"crs": { "type": "name", "properties": { "name": "urn:ogc:def:crs:OGC:1.3:CRS84" } },
"features": [
{ "type": "Feature", "properties": { "point_type": "origin", "points_str": "45.352843, -122.58811" }, "geometry": { "type": "Point", "coordinates": [ -122.588110211109097, 45.352842534150255 ] } },
{ "type": "Feature", "properties": { "point_type": "destination", "points_str": "45.441602, -122.634131" }, "geometry": { "type": "Point", "coordinates": [ -122.634131166140321, 45.441601807544778 ] } }
]
}
