{
"type": "FeatureCollection",
"crs": { "type": "name", "properties": { "name": "urn:ogc:def:crs:OGC:1.3:CRS84" } },
"features": [
{ "type": "Feature", "properties": { "point_type": "origin", "points_str": "45.522472, -122.680161" }, "geometry": { "type": "Point", "coordinates": [ -122.680160640450609, 45.522472046472295 ] } },
{ "type": "Feature", "properties": { "point_type": "destination", "points_str": "45.472856, -122.827657" }, "geometry": { "type": "Point", "coordinates": [ -122.827656690366908, 45.472855563389942 ] } }
]
}
