{
"type": "FeatureCollection",
"name": "origin_destination_points",
"crs": { "type": "name", "properties": { "name": "urn:ogc:def:crs:OGC:1.3:CRS84" } },
"features": [
{ "type": "Feature", "properties": { "point_type": "origin", "points_str": "45.448605, -122.770597" }, "geometry": { "type": "Point", "coordinates": [ -122.770597456592256, 45.448605085705019 ] } },
{ "type": "Feature", "properties": { "point_type": "destination", "points_str": "45.428996, -122.747436" }, "geometry": { "type": "Point", "coordinates": [ -122.747435861796518, 45.428996239256165 ] } }
]
}
