{
"type": "FeatureCollection",
"name": "origin_destination_points",
"crs": { "type": "name", "properties": { "name": "urn:ogc:def:crs:OGC:1.3:CRS84" } },
"features": [
{ "type": "Feature", "properties": { "point_type": "origin", "points_str": "45.520353, -122.973085" }, "geometry": { "type": "Point", "coordinates": [ -122.973085027047404, 45.520352851661947 ] } },
{ "type": "Feature", "properties": { "point_type": "destination", "points_str": "45.517864, -122.578995" }, "geometry": { "type": "Point", "coordinates": [ -122.578994956844298, 45.517863930677024 ] } }
]
}
