{
"type": "FeatureCollection",
"crs": { "type": "name", "properties": { "name": "urn:ogc:def:crs:OGC:1.3:CRS84" } },
"features": [
{ "type": "Feature", "properties": { "point_type": "origin", "points_str": "45.525464, -122.679554" }, "geometry": { "type": "Point", "coordinates": [ -122.679553962062613, 45.525463748120231 ] } },
{ "type": "Feature", "properties": { "point_type": "destination", "points_str": "45.470368, -122.768337" }, "geometry": { "type": "Point", "coordinates": [ -122.768336555140223, 45.470368280626289 ] } }
]
}
