{
"type": "FeatureCollection",
"name": "origin_destination_points",
"crs": { "type": "name", "properties": { "name": "urn:ogc:def:crs:OGC:1.3:CRS84" } },
"features": [
{ "type": "Feature", "properties": { "point_type": "origin", "points_str": "45.401123, -122.640979" }, "geometry": { "type": "Point", "coordinates": [ -122.6409790960723, 45.401122757979032 ] } },
{ "type": "Feature", "properties": { "point_type": "destination", "points_str": "45.373052, -122.594706" }, "geometry": { "type": "Point", "coordinates": [ -122.594706272389615, 45.373051776692947 ] } }
]
}
