{
"type": "FeatureCollection",
"name": "origin_destination_points",
"crs": { "type": "name", "properties": { "name": "urn:ogc:def:crs:OGC:1.3:CRS84" } },
"features": [
{ "type": "Feature", "properties": { "point_type": "origin", "points_str": "45.451216, -122.77426" }, "geometry": { "type": "Point", "coordinates": [ -122.774259515295569, 45.451216150969721 ] } },
{ "type": "Feature", "properties": { "point_type": "destination", "points_str": "45.471823, -122.802922" }, "geometry": { "type": "Point", "coordinates": [ -122.80292212651608, 45.471822584347045 ] } }
]
}
