{
"type": "FeatureCollection",
"name": "origin_destination_points",
"crs": { "type": "name", "properties": { "name": "urn:ogc:def:crs:OGC:1.3:CRS84" } },
"features": [
{ "type": "Feature", "properties": { "point_type": "origin", "points_str": "45.581682, -122.740145" }, "geometry": { "type": "Point", "coordinates": [ -122.740144746122695, 45.58168216057139 ] } },
{ "type": "Feature", "properties": { "point_type": "destination", "points_str": "45.551566, -122.626426" }, "geometry": { "type": "Point", "coordinates": [ -122.626425545957957, 45.551565659082797 ] } }
]
}
