{
"type": "FeatureCollection",
"name": "origin_destination_points",
"crs": { "type": "name", "properties": { "name": "urn:ogc:def:crs:OGC:1.3:CRS84" } },
"features": [
{ "type": "Feature", "properties": { "point_type": "origin", "points_str": "45.368236, -122.577695" }, "geometry": { "type": "Point", "coordinates": [ -122.577695022774634, 45.368236175200657 ] } },
{ "type": "Feature", "properties": { "point_type": "destination", "points_str": "45.483126, -122.672631" }, "geometry": { "type": "Point", "coordinates": [ -122.672630794146713, 45.483125757809226 ] } }
]
}
