{
"type": "FeatureCollection",
"name": "origin_destination_points",
"crs": { "type": "name", "properties": { "name": "urn:ogc:def:crs:OGC:1.3:CRS84" } },
"features": [
{ "type": "Feature", "properties": { "point_type": "origin", "points_str": "45.532356, -122.92956" }, "geometry": { "type": "Point", "coordinates": [ -122.929560282314256, 45.532355917125948 ] } },
{ "type": "Feature", "properties": { "point_type": "destination", "points_str": "45.518637, -123.066315" }, "geometry": { "type": "Point", "coordinates": [ -123.066314947994385, 45.518637091100729 ] } }
]
}
