{
"type": "FeatureCollection",
"name": "origin_destination_points",
"crs": { "type": "name", "properties": { "name": "urn:ogc:def:crs:OGC:1.3:CRS84" } },
"features": [
{ "type": "Feature", "properties": { "point_type": "origin", "points_str": "45.442814, -122.730641" }, "geometry": { "type": "Point", "coordinates": [ -122.730640889599982, 45.442813862507428 ] } },
{ "type": "Feature", "properties": { "point_type": "destination", "points_str": "45.48794, -122.637982" }, "geometry": { "type": "Point", "coordinates": [ -122.637981973894355, 45.48794039857134 ] } }
]
}
