{
"type": "FeatureCollection",
"name": "origin_destination_points",
"crs": { "type": "name", "properties": { "name": "urn:ogc:def:crs:OGC:1.3:CRS84" } },
"features": [
{ "type": "Feature", "properties": { "point_type": "origin", "points_str": "45.589084, -122.701276" }, "geometry": { "type": "Point", "coordinates": [ -122.70127577090382, 45.589083502160378 ] } },
{ "type": "Feature", "properties": { "point_type": "destination", "points_str": "45.490793, -122.678665" }, "geometry": { "type": "Point", "coordinates": [ -122.678664554898177, 45.490792846102131 ] } }
]
}
