{
"type": "FeatureCollection",
"name": "origin_destination_points",
"crs": { "type": "name", "properties": { "name": "urn:ogc:def:crs:OGC:1.3:CRS84" } },
"features": [
{ "type": "Feature", "properties": { "point_type": "origin", "points_str": "45.445675, -122.612139" }, "geometry": { "type": "Point", "coordinates": [ -122.61213853652572, 45.445675455363194 ] } },
{ "type": "Feature", "properties": { "point_type": "destination", "points_str": "45.397531, -122.621872" }, "geometry": { "type": "Point", "coordinates": [ -122.621872334292377, 45.397530834189716 ] } }
]
}
