{
"type": "FeatureCollection",
"name": "origin_destination_points",
"crs": { "type": "name", "properties": { "name": "urn:ogc:def:crs:OGC:1.3:CRS84" } },
"features": [
{ "type": "Feature", "properties": { "point_type": "origin", "points_str": "45.516448, -122.49807" }, "geometry": { "type": "Point", "coordinates": [ -122.498069689817157, 45.516447657520594 ] } },
{ "type": "Feature", "properties": { "point_type": "destination", "points_str": "45.543533, -122.493503" }, "geometry": { "type": "Point", "coordinates": [ -122.493502711999142, 45.543532673390139 ] } }
]
}
