{
"type": "FeatureCollection",
"name": "origin_destination_points",
"crs": { "type": "name", "properties": { "name": "urn:ogc:def:crs:OGC:1.3:CRS84" } },
"features": [
{ "type": "Feature", "properties": { "point_type": "origin", "points_str": "45.50763, -122.438357" }, "geometry": { "type": "Point", "coordinates": [ -122.438356540904678, 45.507630488825832 ] } },
{ "type": "Feature", "properties": { "point_type": "destination", "points_str": "45.493574, -122.789125" }, "geometry": { "type": "Point", "coordinates": [ -122.789124894909477, 45.493574352287119 ] } }
]
}
