{
"type": "FeatureCollection",
"crs": { "type": "name", "properties": { "name": "urn:ogc:def:crs:OGC:1.3:CRS84" } },
"features": [
{ "type": "Feature", "properties": { "point_type": "origin", "points_str": "45.560934, -122.680032" }, "geometry": { "type": "Point", "coordinates": [ -122.680032383320864, 45.560933825276628 ] } },
{ "type": "Feature", "properties": { "point_type": "destination", "points_str": "45.513636, -122.563274" }, "geometry": { "type": "Point", "coordinates": [ -122.563273758940369, 45.513635537403559 ] } }
]
}
