{
"type": "FeatureCollection",
"crs": { "type": "name", "properties": { "name": "urn:ogc:def:crs:OGC:1.3:CRS84" } },
"features": [
{ "type": "Feature", "properties": { "point_type": "origin", "points_str": "45.472607, -122.687439" }, "geometry": { "type": "Point", "coordinates": [ -122.687439369836255, 45.472606817175127 ] } },
{ "type": "Feature", "properties": { "point_type": "destination", "points_str": "45.330278, -122.577226" }, "geometry": { "type": "Point", "coordinates": [ -122.577225802811796, 45.330277653411088 ] } }
]
}
