{
"type": "FeatureCollection",
"name": "origin_destination_points",
"crs": { "type": "name", "properties": { "name": "urn:ogc:def:crs:OGC:1.3:CRS84" } },
"features": [
{ "type": "Feature", "properties": { "point_type": "origin", "points_str": "45.552509, -122.494839" }, "geometry": { "type": "Point", "coordinates": [ -122.494839025617267, 45.55250921450687 ] } },
{ "type": "Feature", "properties": { "point_type": "destination", "points_str": "45.497695, -122.628647" }, "geometry": { "type": "Point", "coordinates": [ -122.628646963472022, 45.497694625049199 ] } }
]
}
