{
"type": "FeatureCollection",
"crs": { "type": "name", "properties": { "name": "urn:ogc:def:crs:OGC:1.3:CRS84" } },
"features": [
{ "type": "Feature", "properties": { "point_type": "origin", "points_str": "45.560465, -122.721199" }, "geometry": { "type": "Point", "coordinates": [ -122.721199484068293, 45.560465222124691 ] } },
{ "type": "Feature", "properties": { "point_type": "destination", "points_str": "45.564213, -122.548905" }, "geometry": { "type": "Point", "coordinates": [ -122.548905280453766, 45.56421277283291 ] } }
]
}
