{
"type": "FeatureCollection",
"name": "origin_destination_points",
"crs": { "type": "name", "properties": { "name": "urn:ogc:def:crs:OGC:1.3:CRS84" } },
"features": [
{ "type": "Feature", "properties": { "point_type": "origin", "points_str": "45.517441, -122.51667" }, "geometry": { "type": "Point", "coordinates": [ -122.516670223935407, 45.517440604245643 ] } },
{ "type": "Feature", "properties": { "point_type": "destination", "points_str": "45.550075, -122.540758" }, "geometry": { "type": "Point", "coordinates": [ -122.540758375007456, 45.550074653562348 ] } }
]
}
