{
"type": "FeatureCollection",
"name": "origin_destination_points",
"crs": { "type": "name", "properties": { "name": "urn:ogc:def:crs:OGC:1.3:CRS84" } },
"features": [
{ "type": "Feature", "properties": { "point_type": "origin", "points_str": "45.51641, -123.092318" }, "geometry": { "type": "Point", "coordinates": [ -123.092318364717315, 45.516409898198297 ] } },
{ "type": "Feature", "properties": { "point_type": "destination", "points_str": "45.522692, -122.540703" }, "geometry": { "type": "Point", "coordinates": [ -122.540702904879097, 45.522692135377866 ] } }
]
}
