{
"type": "FeatureCollection",
"name": "origin_destination_points",
"crs": { "type": "name", "properties": { "name": "urn:ogc:def:crs:OGC:1.3:CRS84" } },
"features": [
{ "type": "Feature", "properties": { "point_type": "origin", "points_str": "45.576275, -122.566517" }, "geometry": { "type": "Point", "coordinates": [ -122.566516876224242, 45.576275169542185 ] } },
{ "type": "Feature", "properties": { "point_type": "destination", "points_str": "45.534819, -122.700966" }, "geometry": { "type": "Point", "coordinates": [ -122.700965675264555, 45.534818514678832 ] } }
]
}
