{
"type": "FeatureCollection",
"name": "origin_destination_points",
"crs": { "type": "name", "properties": { "name": "urn:ogc:def:crs:OGC:1.3:CRS84" } },
"features": [
{ "type": "Feature", "properties": { "point_type": "origin", "points_str": "45.555473, -122.59235" }, "geometry": { "type": "Point", "coordinates": [ -122.592350173367549, 45.555473127051123 ] } },
{ "type": "Feature", "properties": { "point_type": "destination", "points_str": "45.556289, -122.550919" }, "geometry": { "type": "Point", "coordinates": [ -122.550919370414547, 45.556288732868197 ] } }
]
}
