{
"type": "FeatureCollection",
"name": "origin_destination_points",
"crs": { "type": "name", "properties": { "name": "urn:ogc:def:crs:OGC:1.3:CRS84" } },
"features": [
{ "type": "Feature", "properties": { "point_type": "origin", "points_str": "45.57032, -122.636196" }, "geometry": { "type": "Point", "coordinates": [ -122.636195852691245, 45.570320467396918 ] } },
{ "type": "Feature", "properties": { "point_type": "destination", "points_str": "45.522945, -122.680855" }, "geometry": { "type": "Point", "coordinates": [ -122.680855481148967, 45.522944834712213 ] } }
]
}
