{
"type": "FeatureCollection",
"name": "origin_destination_points",
"crs": { "type": "name", "properties": { "name": "urn:ogc:def:crs:OGC:1.3:CRS84" } },
"features": [
{ "type": "Feature", "properties": { "point_type": "origin", "points_str": "45.582013, -122.708084" }, "geometry": { "type": "Point", "coordinates": [ -122.708083561530998, 45.582013095250424 ] } },
{ "type": "Feature", "properties": { "point_type": "destination", "points_str": "45.538907, -122.680146" }, "geometry": { "type": "Point", "coordinates": [ -122.680146347863214, 45.538907263567715 ] } }
]
}
