{
"type": "FeatureCollection",
"crs": { "type": "name", "properties": { "name": "urn:ogc:def:crs:OGC:1.3:CRS84" } },
"features": [
{ "type": "Feature", "properties": { "point_type": "origin", "points_str": "45.410489, -122.622176" }, "geometry": { "type": "Point", "coordinates": [ -122.622176062500202, 45.41048856331517 ] } },
{ "type": "Feature", "properties": { "point_type": "destination", "points_str": "45.379556, -122.392169" }, "geometry": { "type": "Point", "coordinates": [ -122.392169478534043, 45.379555667000091 ] } }
]
}
