{
"type": "FeatureCollection",
"name": "origin_destination_points",
"crs": { "type": "name", "properties": { "name": "urn:ogc:def:crs:OGC:1.3:CRS84" } },
"features": [
{ "type": "Feature", "properties": { "point_type": "origin", "points_str": "45.5593, -122.562371" }, "geometry": { "type": "Point", "coordinates": [ -122.562370967410075, 45.559300474889739 ] } },
{ "type": "Feature", "properties": { "point_type": "destination", "points_str": "45.449629, -122.575712" }, "geometry": { "type": "Point", "coordinates": [ -122.575711855332472, 45.449629261223087 ] } }
]
}
