{
"type": "FeatureCollection",
"name": "origin_destination_points",
"crs": { "type": "name", "properties": { "name": "urn:ogc:def:crs:OGC:1.3:CRS84" } },
"features": [
{ "type": "Feature", "properties": { "point_type": "origin", "points_str": "45.531265, -122.842809" }, "geometry": { "type": "Point", "coordinates": [ -122.842809193315588, 45.531265281249738 ] } },
{ "type": "Feature", "properties": { "point_type": "destination", "points_str": "45.551039, -122.929255" }, "geometry": { "type": "Point", "coordinates": [ -122.92925457357893, 45.551039209470481 ] } }
]
}
