{
"type": "FeatureCollection",
"crs": { "type": "name", "properties": { "name": "urn:ogc:def:crs:OGC:1.3:CRS84" } },
"features": [
{ "type": "Feature", "properties": { "point_type": "origin", "points_str": "45.500569, -122.874963" }, "geometry": { "type": "Point", "coordinates": [ -122.874962586442848, 45.500569324528293 ] } },
{ "type": "Feature", "properties": { "point_type": "destination", "points_str": "45.63419, -122.774089" }, "geometry": { "type": "Point", "coordinates": [ -122.774088519471761, 45.634189570648665 ] } }
]
}
