{
"type": "FeatureCollection",
"name": "origin_destination_points",
"crs": { "type": "name", "properties": { "name": "urn:ogc:def:crs:OGC:1.3:CRS84" } },
"features": [
{ "type": "Feature", "properties": { "point_type": "origin", "points_str": "45.503545, -122.671638" }, "geometry": { "type": "Point", "coordinates": [ -122.671638485080891, 45.503544633708678 ] } },
{ "type": "Feature", "properties": { "point_type": "destination", "points_str": "45.487861, -122.722816" }, "geometry": { "type": "Point", "coordinates": [ -122.722816171552267, 45.487860502358572 ] } }
]
}
