{
"type": "FeatureCollection",
"crs": { "type": "name", "properties": { "name": "urn:ogc:def:crs:OGC:1.3:CRS84" } },
"features": [
{ "type": "Feature", "properties": { "point_type": "origin", "points_str": "45.518294, -122.976675" }, "geometry": { "type": "Point", "coordinates": [ -122.976674598251208, 45.518294462900869 ] } },
{ "type": "Feature", "properties": { "point_type": "destination", "points_str": "45.501598, -122.635638" }, "geometry": { "type": "Point", "coordinates": [ -122.635637768871135, 45.501597731866184 ] } }
]
}
