{
"type": "FeatureCollection",
"crs": { "type": "name", "properties": { "name": "urn:ogc:def:crs:OGC:1.3:CRS84" } },
"features": [
{ "type": "Feature", "properties": { "point_type": "origin", "points_str": "45.471118, -122.603565" }, "geometry": { "type": "Point", "coordinates": [ -122.603565055385786, 45.471118437639241 ] } },
{ "type": "Feature", "properties": { "point_type": "destination", "points_str": "45.532181, -122.612111" }, "geometry": { "type": "Point", "coordinates": [ -122.61211148809322, 45.532180785540838 ] } }
]
}
