{
"type": "FeatureCollection",
"name": "origin_destination_points",
"crs": { "type": "name", "properties": { "name": "urn:ogc:def:crs:OGC:1.3:CRS84" } },
"features": [
{ "type": "Feature", "properties": { "point_type": "origin", "points_str": "45.518771, -122.988116" }, "geometry": { "type": "Point", "coordinates": [ -122.988116393753018, 45.518771281730068 ] } },
{ "type": "Feature", "properties": { "point_type": "destination", "points_str": "45.487642, -122.728433" }, "geometry": { "type": "Point", "coordinates": [ -122.728433306452615, 45.487642484359007 ] } }
]
}
