{
"type": "FeatureCollection",
"name": "origin_destination_points",
"crs": { "type": "name", "properties": { "name": "urn:ogc:def:crs:OGC:1.3:CRS84" } },
"features": [
{ "type": "Feature", "properties": { "point_type": "origin", "points_str": "45.504519, -122.681767" }, "geometry": { "type": "Point", "coordinates": [ -122.681766734100705, 45.504519318638863 ] } },
{ "type": "Feature", "properties": { "point_type": "destination", "points_str": "45.500266, -122.645832" }, "geometry": { "type": "Point", "coordinates": [ -122.645832114473563, 45.500265742573397 ] } }
]
}
