{
"type": "FeatureCollection",
"name": "origin_destination_points",
"crs": { "type": "name", "properties": { "name": "urn:ogc:def:crs:OGC:1.3:CRS84" } },
"features": [
{ "type": "Feature", "properties": { "point_type": "origin", "points_str": "45.517066, -122.506876" }, "geometry": { "type": "Point", "coordinates": [ -122.506876478793984, 45.517066153978384 ] } },
{ "type": "Feature", "properties": { "point_type": "destination", "points_str": "45.60824, -122.792872" }, "geometry": { "type": "Point", "coordinates": [ -122.792872238810659, 45.608240154537462 ] } }
]
}
