{
"type": "FeatureCollection",
"name": "origin_destination_points",
"crs": { "type": "name", "properties": { "name": "urn:ogc:def:crs:OGC:1.3:CRS84" } },
"features": [
{ "type": "Feature", "properties": { "point_type": "origin", "points_str": "45.522858, -123.06521" }, "geometry": { "type": "Point", "coordinates": [ -123.065210129078508, 45.522857664702791 ] } },
{ "type": "Feature", "properties": { "point_type": "destination", "points_str": "45.49258, -122.863258" }, "geometry": { "type": "Point", "coordinates": [ -122.863258394770781, 45.492580179298862 ] } }
]
}
