{
"type": "FeatureCollection",
"name": "origin_destination_points",
"crs": { "type": "name", "properties": { "name": "urn:ogc:def:crs:OGC:1.3:CRS84" } },
"features": [
{ "type": "Feature", "properties": { "point_type": "origin", "points_str": "45.450255, -122.724008" }, "geometry": { "type": "Point", "coordinates": [ -122.724008109529748, 45.450254932341402 ] } },
{ "type": "Feature", "properties": { "point_type": "destination", "points_str": "45.535041, -122.550602" }, "geometry": { "type": "Point", "coordinates": [ -122.550601978517406, 45.535041164253158 ] } }
]
}
