{
"type": "FeatureCollection",
"crs": { "type": "name", "properties": { "name": "urn:ogc:def:crs:OGC:1.3:CRS84" } },
"features": [
{ "type": "Feature", "properties": { "point_type": "origin", "points_str": "45.495953, -122.711192" }, "geometry": { "type": "Point", "coordinates": [ -122.71119159285746, 45.495953121684046 ] } },
{ "type": "Feature", "properties": { "point_type": "destination", "points_str": "45.550751, -122.726369" }, "geometry": { "type": "Point", "coordinates": [ -122.726368799828123, 45.550751170235039 ] } }
]
}
