{
"type": "FeatureCollection",
"name": "origin_destination_points",
"crs": { "type": "name", "properties": { "name": "urn:ogc:def:crs:OGC:1.3:CRS84" } },
"features": [
{ "type": "Feature", "properties": { "point_type": "origin", "points_str": "45.527321, -122.672354" }, "geometry": { "type": "Point", "coordinates": [ -122.672353905402232, 45.527321335242945 ] } },
{ "type": "Feature", "properties": { "point_type": "destination", "points_str": "45.523812, -122.534887" }, "geometry": { "type": "Point", "coordinates": [ -122.534886643753495, 45.523811838051053 ] } }
]
}
