{
"type": "FeatureCollection",
"name": "origin_destination_points",
"crs": { "type": "name", "properties": { "name": "urn:ogc:def:crs:OGC:1.3:CRS84" } },
"features": [
{ "type": "Feature", "properties": { "point_type": "origin", "points_str": "45.518319, -122.500036" }, "geometry": { "type": "Point", "coordinates": [ -122.500036322688374, 45.518318831560705 ] } },
{ "type": "Feature", "properties": { "point_type": "destination", "points_str": "45.517241, -122.572993" }, "geometry": { "type": "Point", "coordinates": [ -122.572992934383393, 45.517241010397228 ] } }
]
}
