{
"type": "FeatureCollection",
"name": "origin_destination_points",
"crs": { "type": "name", "properties": { "name": "urn:ogc:def:crs:OGC:1.3:CRS84" } },
"features": [
{ "type": "Feature", "properties": { "point_type": "origin", "points_str": "45.480318, -122.669336" }, "geometry": { "type": "Point", "coordinates": [ -122.669336092457272, 45.480317897272919 ] } },
{ "type": "Feature", "properties": { "point_type": "destination", "points_str": "45.558464, -122.640369" }, "geometry": { "type": "Point", "coordinates": [ -122.640368681579645, 45.558464152478805 ] } }
]
}
