{
"type": "FeatureCollection",
"name": "origin_destination_points",
"crs": { "type": "name", "properties": { "name": "urn:ogc:def:crs:OGC:1.3:CRS84" } },
"features": [
{ "type": "Feature", "properties": { "point_type": "origin", "points_str": "45.469698, -122.688441" }, "geometry": { "type": "Point", "coordinates": [ -122.688441336312607, 45.469698258472249 ] } },
{ "type": "Feature", "properties": { "point_type": "destination", "points_str": "45.49096, -122.553294" }, "geometry": { "type": "Point", "coordinates": [ -122.553294008522826, 45.490960096993142 ] } }
]
}
