{
"type": "FeatureCollection",
"name": "origin_destination_points",
"crs": { "type": "name", "properties": { "name": "urn:ogc:def:crs:OGC:1.3:CRS84" } },
"features": [
{ "type": "Feature", "properties": { "point_type": "origin", "points_str": "45.526146, -122.626498" }, "geometry": { "type": "Point", "coordinates": [ -122.626497950159433, 45.526145842117351 ] } },
{ "type": "Feature", "properties": { "point_type": "destination", "points_str": "45.520316, -122.668432" }, "geometry": { "type": "Point", "coordinates": [ -122.668432283868711, 45.520316224768692 ] } }
]
}
