{
"type": "FeatureCollection",
"name": "origin_destination_points",
"crs": { "type": "name", "properties": { "name": "urn:ogc:def:crs:OGC:1.3:CRS84" } },
"features": [
{ "type": "Feature", "properties": { "point_type": "origin", "points_str": "45.501832, -122.833582" }, "geometry": { "type": "Point", "coordinates": [ -122.833581786773891, 45.501831749828519 ] } },
{ "type": "Feature", "properties": { "point_type": "destination", "points_str": "45.45324, -122.687551" }, "geometry": { "type": "Point", "coordinates": [ -122.687550899399398, 45.453239978016242 ] } }
]
}
