{
"type": "FeatureCollection",
"crs": { "type": "name", "properties": { "name": "urn:ogc:def:crs:OGC:1.3:CRS84" } },
"features": [
{ "type": "Feature", "properties": { "point_type": "origin", "points_str": "45.567856, -122.554954" }, "geometry": { "type": "Point", "coordinates": [ -122.554953716849653, 45.5678564742283 ] } },
{ "type": "Feature", "properties": { "point_type": "destination", "points_str": "45.409959, -122.640597" }, "geometry": { "type": "Point", "coordinates": [ -122.640596609651283, 45.409959299339285 ] } }
]
}
