{
"type": "FeatureCollection",
"crs": { "type": "name", "properties": { "name": "urn:ogc:def:crs:OGC:1.3:CRS84" } },
"features": [
{ "type": "Feature", "properties": { "point_type": "origin", "points_str": "45.514238, -122.609914" }, "geometry": { "type": "Point", "coordinates": [ -122.609914361153486, 45.514238132248053 ] } },
{ "type": "Feature", "properties": { "point_type": "destination", "points_str": "45.5257, -122.703394" }, "geometry": { "type": "Point", "coordinates": [ -122.703393508397809, 45.525700171857245 ] } }
]
}
