{
"type": "FeatureCollection",
"name": "origin_destination_points",
"crs": { "type": "name", "properties": { "name": "urn:ogc:def:crs:OGC:1.3:CRS84" } },
"features": [
{ "type": "Feature", "properties": { "point_type": "origin", "points_str": "45.444543, -122.734514" }, "geometry": { "type": "Point", "coordinates": [ -122.734513638889737, 45.444542664026706 ] } },
{ "type": "Feature", "properties": { "point_type": "destination", "points_str": "45.454897, -122.778555" }, "geometry": { "type": "Point", "coordinates": [ -122.778554503866914, 45.454897420299822 ] } }
]
}
