{
"type": "FeatureCollection",
"crs": { "type": "name", "properties": { "name": "urn:ogc:def:crs:OGC:1.3:CRS84" } },
"features": [
{ "type": "Feature", "properties": { "point_type": "origin", "points_str": "45.445384, -122.687471" }, "geometry": { "type": "Point", "coordinates": [ -122.687470937724029, 45.445383983282994 ] } },
{ "type": "Feature", "properties": { "point_type": "destination", "points_str": "45.489429, -122.464981" }, "geometry": { "type": "Point", "coordinates": [ -122.464981147616129, 45.489429411457131 ] } }
]
}
