{
"type": "FeatureCollection",
"name": "origin_destination_points",
"crs": { "type": "name", "properties": { "name": "urn:ogc:def:crs:OGC:1.3:CRS84" } },
"features": [
{ "type": "Feature", "properties": { "point_type": "origin", "points_str": "45.500464, -122.876642" }, "geometry": { "type": "Point", "coordinates": [ -122.876641591379382, 45.500464128533196 ] } },
{ "type": "Feature", "properties": { "point_type": "destination", "points_str": "45.477935, -122.801129" }, "geometry": { "type": "Point", "coordinates": [ -122.801128506749308, 45.477935387956791 ] } }
]
}
