{
"type": "FeatureCollection",
"name": "origin_destination_points",
"crs": { "type": "name", "properties": { "name": "urn:ogc:def:crs:OGC:1.3:CRS84" } },
"features": [
{ "type": "Feature", "properties": { "point_type": "origin", "points_str": "45.471912, -122.682257" }, "geometry": { "type": "Point", "coordinates": [ -122.682257229399838, 45.471912254726568 ] } },
{ "type": "Feature", "properties": { "point_type": "destination", "points_str": "45.532402, -122.685549" }, "geometry": { "type": "Point", "coordinates": [ -122.685549272751246, 45.532401606634849 ] } }
]
}
