{
"type": "FeatureCollection",
"crs": { "type": "name", "properties": { "name": "urn:ogc:def:crs:OGC:1.3:CRS84" } },
"features": [
{ "type": "Feature", "properties": { "point_type": "origin", "points_str": "45.587513, -122.669083" }, "geometry": { "type": "Point", "coordinates": [ -122.669082717172785, 45.587512811990592 ] } },
{ "type": "Feature", "properties": { "point_type": "destination", "points_str": "45.555844, -122.696589" }, "geometry": { "type": "Point", "coordinates": [ -122.696588738570469, 45.555843636440969 ] } }
]
}
