{
"type": "FeatureCollection",
"crs": { "type": "name", "properties": { "name": "urn:ogc:def:crs:OGC:1.3:CRS84" } },
"features": [
{ "type": "Feature", "properties": { "point_type": "origin", "points_str": "45.534819, -122.488005" }, "geometry": { "type": "Point", "coordinates": [ -122.488004795221428, 45.534819302558766 ] } },
{ "type": "Feature", "properties": { "point_type": "destination", "points_str": "45.431673, -122.760671" }, "geometry": { "type": "Point", "coordinates": [ -122.760671427181549, 45.431673302265317 ] } }
]
}
