{
"type": "FeatureCollection",
"crs": { "type": "name", "properties": { "name": "urn:ogc:def:crs:OGC:1.3:CRS84" } },
"features": [
{ "type": "Feature", "properties": { "point_type": "origin", "points_str": "45.5671, -122.698886" }, "geometry": { "type": "Point", "coordinates": [ -122.698885761766277, 45.567100123379369 ] } },
{ "type": "Feature", "properties": { "point_type": "destination", "points_str": "45.45843, -122.708692" }, "geometry": { "type": "Point", "coordinates": [ -122.708692050402831, 45.458430210193903 ] } }
]
}
