{
"type": "FeatureCollection",
"name": "origin_destination_points",
"crs": { "type": "name", "properties": { "name": "urn:ogc:def:crs:OGC:1.3:CRS84" } },
"features": [
{ "type": "Feature", "properties": { "point_type": "origin", "points_str": "45.497935, -122.685801" }, "geometry": { "type": "Point", "coordinates": [ -122.685801017521385, 45.497935130133271 ] } },
{ "type": "Feature", "properties": { "point_type": "destination", "points_str": "45.451988, -122.756977" }, "geometry": { "type": "Point", "coordinates": [ -122.756977144429342, 45.45198806056117 ] } }
]
}
