{
"type": "FeatureCollection",
"crs": { "type": "name", "properties": { "name": "urn:ogc:def:crs:OGC:1.3:CRS84" } },
"features": [
{ "type": "Feature", "properties": { "point_type": "origin", "points_str": "45.527786, -122.564701" }, "geometry": { "type": "Point", "coordinates": [ -122.564701361170677, 45.527786063913091 ] } },
{ "type": "Feature", "properties": { "point_type": "destination", "points_str": "45.55625, -122.481011" }, "geometry": { "type": "Point", "coordinates": [ -122.48101064656241, 45.556249759645304 ] } }
]
}
