{
"type": "FeatureCollection",
"crs": { "type": "name", "properties": { "name": "urn:ogc:def:crs:OGC:1.3:CRS84" } },
"features": [
{ "type": "Feature", "properties": { "point_type": "origin", "points_str": "45.481522, -122.800805" }, "geometry": { "type": "Point", "coordinates": [ -122.800804750580767, 45.481522037627833 ] } },
{ "type": "Feature", "properties": { "point_type": "destination", "points_str": "45.50909, -122.644701" }, "geometry": { "type": "Point", "coordinates": [ -122.64470107373937, 45.509089737996618 ] } }
]
}
