{
"type": "FeatureCollection",
"crs": { "type": "name", "properties": { "name": "urn:ogc:def:crs:OGC:1.3:CRS84" } },
"features": [
{ "type": "Feature", "properties": { "point_type": "origin", "points_str": "45.610964, -122.683505" }, "geometry": { "type": "Point", "coordinates": [ -122.683504691698502, 45.61096395628693 ] } },
{ "type": "Feature", "properties": { "point_type": "destination", "points_str": "45.476456, -122.723561" }, "geometry": { "type": "Point", "coordinates": [ -122.723560688076148, 45.476455643545584 ] } }
]
}
