{
"type": "FeatureCollection",
"name": "origin_destination_points",
"crs": { "type": "name", "properties": { "name": "urn:ogc:def:crs:OGC:1.3:CRS84" } },
"features": [
{ "type": "Feature", "properties": { "point_type": "origin", "points_str": "45.579494, -122.664983" }, "geometry": { "type": "Point", "coordinates": [ -122.664982959676692, 45.579493521526949 ] } },
{ "type": "Feature", "properties": { "point_type": "destination", "points_str": "45.475955, -122.569449" }, "geometry": { "type": "Point", "coordinates": [ -122.569449138716024, 45.475955204764645 ] } }
]
}
