{
"type": "FeatureCollection",
"name": "origin_destination_points",
"crs": { "type": "name", "properties": { "name": "urn:ogc:def:crs:OGC:1.3:CRS84" } },
"features": [
{ "type": "Feature", "properties": { "point_type": "origin", "points_str": "45.52268, -122.536829" }, "geometry": { "type": "Point", "coordinates": [ -122.536828960389926, 45.522680009643061 ] } },
{ "type": "Feature", "properties": { "point_type": "destination", "points_str": "45.519597, -123.013053" }, "geometry": { "type": "Point", "coordinates": [ -123.013053306700243, 45.519597313720453 ] } }
]
}
