{
"type": "FeatureCollection",
"name": "origin_destination_points",
"crs": { "type": "name", "properties": { "name": "urn:ogc:def:crs:OGC:1.3:CRS84" } },
"features": [
{ "type": "Feature", "properties": { "point_type": "origin", "points_str": "45.426813, -122.764354" }, "geometry": { "type": "Point", "coordinates": [ -122.764353816069118, 45.426812556897701 ] } },
{ "type": "Feature", "properties": { "point_type": "destination", "points_str": "45.422876, -122.665127" }, "geometry": { "type": "Point", "coordinates": [ -122.665127313926646, 45.422876446676973 ] } }
]
}
