{
"type": "FeatureCollection",
"crs": { "type": "name", "properties": { "name": "urn:ogc:def:crs:OGC:1.3:CRS84" } },
"features": [
{ "type": "Feature", "properties": { "point_type": "origin", "points_str": "45.523408, -122.542526" }, "geometry": { "type": "Point", "coordinates": [ -122.542525955704235, 45.523407998685435 ] } },
{ "type": "Feature", "properties": { "point_type": "destination", "points_str": "45.467635, -122.581054" }, "geometry": { "type": "Point", "coordinates": [ -122.581054237321169, 45.467634742430086 ] } }
]
}
