{
"type": "FeatureCollection",
"name": "origin_destination_points",
"crs": { "type": "name", "properties": { "name": "urn:ogc:def:crs:OGC:1.3:CRS84" } },
"features": [
{ "type": "Feature", "properties": { "point_type": "origin", "points_str": "45.532749, -122.535947" }, "geometry": { "type": "Point", "coordinates": [ -122.535947125957108, 45.532748691018895 ] } },
{ "type": "Feature", "properties": { "point_type": "destination", "points_str": "45.516724, -122.743434" }, "geometry": { "type": "Point", "coordinates": [ -122.743433935717903, 45.516723814156357 ] } }
]
}
