{
"type": "FeatureCollection",
"crs": { "type": "name", "properties": { "name": "urn:ogc:def:crs:OGC:1.3:CRS84" } },
"features": [
{ "type": "Feature", "properties": { "point_type": "origin", "points_str": "45.504016, -122.552065" }, "geometry": { "type": "Point", "coordinates": [ -122.552064586380226, 45.504016412143613 ] } },
{ "type": "Feature", "properties": { "point_type": "destination", "points_str": "45.576865, -122.769295" }, "geometry": { "type": "Point", "coordinates": [ -122.769294891045732, 45.576864679149836 ] } }
]
}
