{
"type": "FeatureCollection",
"crs": { "type": "name", "properties": { "name": "urn:ogc:def:crs:OGC:1.3:CRS84" } },
"features": [
{ "type": "Feature", "properties": { "point_type": "origin", "points_str": "45.440277, -122.817231" }, "geometry": { "type": "Point", "coordinates": [ -122.817230594905311, 45.440277116650918 ] } },
{ "type": "Feature", "properties": { "point_type": "destination", "points_str": "45.4868, -122.734727" }, "geometry": { "type": "Point", "coordinates": [ -122.734726837496495, 45.486799957030762 ] } }
]
}
