{
"type": "FeatureCollection",
"crs": { "type": "name", "properties": { "name": "urn:ogc:def:crs:OGC:1.3:CRS84" } },
"features": [
{ "type": "Feature", "properties": { "point_type": "origin", "points_str": "45.394492, -122.647846" }, "geometry": { "type": "Point", "coordinates": [ -122.64784636801032, 45.394491656364643 ] } },
{ "type": "Feature", "properties": { "point_type": "destination", "points_str": "45.561567, -122.681454" }, "geometry": { "type": "Point", "coordinates": [ -122.681454106213152, 45.561567185541151 ] } }
]
}
