{
"type": "FeatureCollection",
"crs": { "type": "name", "properties": { "name": "urn:ogc:def:crs:OGC:1.3:CRS84" } },
"features": [
{ "type": "Feature", "properties": { "point_type": "origin", "points_str": "45.446469, -122.722837" }, "geometry": { "type": "Point", "coordinates": [ -122.722837368944241, 45.446468783816385 ] } },
{ "type": "Feature", "properties": { "point_type": "destination", "points_str": "45.501517, -122.705697" }, "geometry": { "type": "Point", "coordinates": [ -122.705696951571838, 45.501516895153301 ] } }
]
}
