{
"type": "FeatureCollection",
"name": "origin_destination_points",
"crs": { "type": "name", "properties": { "name": "urn:ogc:def:crs:OGC:1.3:CRS84" } },
"features": [
{ "type": "Feature", "properties": { "point_type": "origin", "points_str": "45.469512, -122.619579" }, "geometry": { "type": "Point", "coordinates": [ -122.619579428491747, 45.469511677419547 ] } },
{ "type": "Feature", "properties": { "point_type": "destination", "points_str": "45.469985, -122.580884" }, "geometry": { "type": "Point", "coordinates": [ -122.58088378422309, 45.469985014125022 ] } }
]
}
