{
"type": "FeatureCollection",
"name": "origin_destination_points",
"crs": { "type": "name", "properties": { "name": "urn:ogc:def:crs:OGC:1.3:CRS84" } },
"features": [
{ "type": "Feature", "properties": { "point_type": "origin", "points_str": "45.539813, -122.610493" }, "geometry": { "type": "Point", "coordinates": [ -122.610493142719804, 45.539812625096843 ] } },
{ "type": "Feature", "properties": { "point_type": "destination", "points_str": "45.450114, -122.634529" }, "geometry": { "type": "Point", "coordinates": [ -122.634528837930176, 45.450114253931687 ] } }
]
}
