{
"type": "FeatureCollection",
"crs": { "type": "name", "properties": { "name": "urn:ogc:def:crs:OGC:1.3:CRS84" } },
"features": [
{ "type": "Feature", "properties": { "point_type": "origin", "points_str": "45.518357, -123.084495" }, "geometry": { "type": "Point", "coordinates": [ -123.084494874129163, 45.518356679703125 ] } },
{ "type": "Feature", "properties": { "point_type": "destination", "points_str": "45.520081, -123.058356" }, "geometry": { "type": "Point", "coordinates": [ -123.058355904940967, 45.520080676971425 ] } }
]
}
