{
"type": "FeatureCollection",
"name": "origin_destination_points",
"crs": { "type": "name", "properties": { "name": "urn:ogc:def:crs:OGC:1.3:CRS84" } },
"features": [
{ "type": "Feature", "properties": { "point_type": "origin", "points_str": "45.514222, -122.677281" }, "geometry": { "type": "Point", "coordinates": [ -122.677280529611423, 45.514222023167264 ] } },
{ "type": "Feature", "properties": { "point_type": "destination", "points_str": "45.500363, -122.504483" }, "geometry": { "type": "Point", "coordinates": [ -122.504482668453846, 45.500363133991179 ] } }
]
}
