{
"type": "FeatureCollection",
"name": "origin_destination_points",
"crs": { "type": "name", "properties": { "name": "urn:ogc:def:crs:OGC:1.3:CRS84" } },
"features": [
{ "type": "Feature", "properties": { "point_type": "origin", "points_str": "45.518553, -122.445845" }, "geometry": { "type": "Point", "coordinates": [ -122.445845288322516, 45.518552512683151 ] } },
{ "type": "Feature", "properties": { "point_type": "destination", "points_str": "45.510994, -122.662075" }, "geometry": { "type": "Point", "coordinates": [ -122.662074830917376, 45.510994170398519 ] } }
]
}
