{
"type": "FeatureCollection",
"name": "origin_destination_points",
"crs": { "type": "name", "properties": { "name": "urn:ogc:def:crs:OGC:1.3:CRS84" } },
"features": [
{ "type": "Feature", "properties": { "point_type": "origin", "points_str": "45.400403, -122.660289" }, "geometry": { "type": "Point", "coordinates": [ -122.660288627960526, 45.40040262699236 ] } },
{ "type": "Feature", "properties": { "point_type": "destination", "points_str": "45.596149, -122.765566" }, "geometry": { "type": "Point", "coordinates": [ -122.765566262987448, 45.596149188386292 ] } }
]
}
