{
"type": "FeatureCollection",
"crs": { "type": "name", "properties": { "name": "urn:ogc:def:crs:OGC:1.3:CRS84" } },
"features": [
{ "type": "Feature", "properties": { "point_type": "origin", "points_str": "45.53046, -122.546651" }, "geometry": { "type": "Point", "coordinates": [ -122.546651339467289, 45.530460453627313 ] } },
{ "type": "Feature", "properties": { "point_type": "destination", "points_str": "45.587252, -122.740999" }, "geometry": { "type": "Point", "coordinates": [ -122.740999289946444, 45.587251695698285 ] } }
]
}
