{
"type": "FeatureCollection",
"name": "origin_destination_points",
"crs": { "type": "name", "properties": { "name": "urn:ogc:def:crs:OGC:1.3:CRS84" } },
"features": [
{ "type": "Feature", "properties": { "point_type": "origin", "points_str": "45.523668, -122.671243" }, "geometry": { "type": "Point", "coordinates": [ -122.671242837378827, 45.523667879484421 ] } },
{ "type": "Feature", "properties": { "point_type": "destination", "points_str": "45.429668, -122.770893" }, "geometry": { "type": "Point", "coordinates": [ -122.770893082235347, 45.429667769681608 ] } }
]
}
