{
"type": "FeatureCollection",
"name": "origin_destination_points",
"crs": { "type": "name", "properties": { "name": "urn:ogc:def:crs:OGC:1.3:CRS84" } },
"features": [
{ "type": "Feature", "properties": { "point_type": "origin", "points_str": "45.522367, -122.691676" }, "geometry": { "type": "Point", "coordinates": [ -122.691676447870279, 45.522367058316192 ] } },
{ "type": "Feature", "properties": { "point_type": "destination", "points_str": "45.508557, -122.778755" }, "geometry": { "type": "Point", "coordinates": [ -122.778755069004688, 45.508557090993243 ] } }
]
}
