{
"type": "FeatureCollection",
"name": "origin_destination_points",
"crs": { "type": "name", "properties": { "name": "urn:ogc:def:crs:OGC:1.3:CRS84" } },
"features": [
{ "type": "Feature", "properties": { "point_type": "origin", "points_str": "45.517875, -122.536124" }, "geometry": { "type": "Point", "coordinates": [ -122.536123604790845, 45.517875038347327 ] } },
{ "type": "Feature", "properties": { "point_type": "destination", "points_str": "45.500733, -122.448171" }, "geometry": { "type": "Point", "coordinates": [ -122.448171466702192, 45.500732877761806 ] } }
]
}
