{
"type": "FeatureCollection",
"crs": { "type": "name", "properties": { "name": "urn:ogc:def:crs:OGC:1.3:CRS84" } },
"features": [
{ "type": "Feature", "properties": { "point_type": "origin", "points_str": "45.345225, -122.642599" }, "geometry": { "type": "Point", "coordinates": [ -122.642598976103827, 45.345225192630615 ] } },
{ "type": "Feature", "properties": { "point_type": "destination", "points_str": "45.460901, -122.68808" }, "geometry": { "type": "Point", "coordinates": [ -122.688079962866126, 45.460901410447136 ] } }
]
}
