{
"type": "FeatureCollection",
"name": "origin_destination_points",
"crs": { "type": "name", "properties": { "name": "urn:ogc:def:crs:OGC:1.3:CRS84" } },
"features": [
{ "type": "Feature", "properties": { "point_type": "origin", "points_str": "45.530539, -122.594756" }, "geometry": { "type": "Point", "coordinates": [ -122.594755896963875, 45.530539066629075 ] } },
{ "type": "Feature", "properties": { "point_type": "destination", "points_str": "45.511774, -122.735385" }, "geometry": { "type": "Point", "coordinates": [ -122.735385499667856, 45.511774263294349 ] } }
]
}
